Workbook
Name \a: #REF!
Name \a: #REF!
Name \a: #REF!
Name \a: #REF!
Name \a: #REF!
Name \a: #REF!
Name \a: #REF!
Name \a: #REF!
Name \a: #REF!
Name \a: #REF!
Name \a: #REF!
Name \a: #REF!
Name \a: #REF!
Name \a: #REF!
Name \a: #REF!
Name \a: #REF!
Name \a: #REF!
Name \a: #REF!
Name \a: #REF!
Name \a: #REF!
Name \a: #REF!
Name \a: #REF!
Name \a: #REF!
Name \a: #REF!
Name \a: #REF!
Name \a: #REF!
Name \s: #REF!
Name \s: #REF!
Name \s: #REF!
Name \s: #REF!
Name \s: #REF!
Name \s: #REF!
Name \s: #REF!
Name \s: #REF!
Name \s: #REF!
Name \s: #REF!
Name \s: #REF!
Name \s: #REF!
Name \s: #REF!
Name \s: #REF!
Name \s: #REF!
Name \s: #REF!
Name \s: #REF!
Name \s: #REF!
Name \s: #REF!
Name \s: #REF!
Name \s: #REF!
Name a: #REF!
Name a: #REF!
Name a: #REF!
Name a: #REF!
Name a: #REF!
Name a: #REF!
Name a: #REF!
Name a: #REF!
Name a: #REF!
Name a: #REF!
Name a: #REF!
Name a: #REF!
Name a: #REF!

Sheet Portada
C33: ='Pm2'!G6 -> 45870
C34: =PROPER(TEXT(C33,"Mmmm"))& " de " & PROPER(TEXT(C33,"aaa")) -> Agosto de 2025

Sheet Nota
B4: La presente información corresponde a la que, en cumplimiento a las Disposiciones aplicables a cada sector, entregan las entidades supervisadas a la CNBV a través de los reportes regulatorios debiéndose asegurar que la misma sea completa, correcta, precisa, integra, confiable y oportuna. Es importante mencionar, como lo indican las propias Disposiciones, que dicha información debe cumplir con las validaciones establecidas en el Sistema Interinstitucional de Transferencia de Información, así como los estándares de calidad que indique la Comisión a través de dicho sistema, además debe existir consistencia entre la información que las entidades incluyan en uno o más reportes regulatorios, aunque se encuentre con un nivel distinto de integración, por lo que puede ser modificada derivado de las revisiones internas que se hagan a la misma. Por lo anterior se informa que la presente publicación se genera con la información con la que se cuenta al momento de su elaboración, se recomienda su uso tomando en cuenta los aspectos anteriormente descritos.
B6: Consideraciones sobre los criterios para integrar los estados financieros del sector de Banca Múltiple a partir de enero de 2022. El 13 de marzo de 2020 se publicó en el Diario Oficial de la Federación la resolución que modificó las Disposiciones de carácter general aplicables a las instituciones de crédito (Disposiciones), la cual incorporó las nuevas normas de información emitidas por el Consejo Mexicano de Normas de Información Financiera A.C., mismas que serían exigibles a partir del 1 de enero de 2021; sin embargo, su entrada en vigor se aplazó hasta el 1 de enero de 2022, mediante la resolución modificatoria publicada en el Diario Oficial de la Federación el 4 de diciembre de 2020. En la resolución modificatoria del 4 de diciembre, se indica que los estados financieros básicos consolidados trimestrales y anuales requeridos a las instituciones de conformidad con las disposiciones señaladas correspondientes al periodo concluido el 31 de diciembre de 2022, no deberán presentarse comparativos con cada trimestre del ejercicio 2021 y por el periodo terminado el 31 de diciembre de 2021. La información del comunicado de prensa de Banca Múltiple se puede consultar en https://www.cnbv.gob.mx/PRENSA/Paginas/Boletines-de-Prensa.aspx Para la información financiera histórica se recomienda utilizar los reportes publicados en el Portafolio de Información. Para consultar las cifras bajo la norma internacional de información financiera 9 “Instrumentos Financieros” (IFRS 9), dirigirse a la sección de IFRS 9 del Portafolio Consultas.
B11: El presente Boletín Estadístico se elaboró por personal de la Comisión Nacional Bancaria y de Valores (CNBV) con la información correspondiente a agosto de 2025 contenida en los reportes regulatorios que las entidades supervisadas envían a esta Comisión, la cual estuvo disponible a partir del 23 de septiembre de 2025.
B13: Las cifras aquí contenidas no se actualizan en el tiempo, por lo que para consultar series históricas se recomienda utilizar los reportes publicados en el Portafolio de Información.
B15: Al cierre de agosto de 2025, el sector de Banca Múltiple estuvo integrado por 52 instituciones en operación, dos más que el año anterior, considerando el inicio de operaciones de; Openbank México, S.A., Institución de Banca Múltiple, Grupo Financiero Santander México el 19 de noviembre de 2024 y de Hey Banco, S.A. Institución de Banca Múltiple, Banregio Grupo Financiero el 12 de febrero de 2025.
B17: Mediante oficio con fecha del 24 de septiembre de 2024 se aprobó el cambio de denominación de CBM Banco, S.A., Institución de Banca Múltiple, Integrante del Grupo Financiero Citibanamex a Banco Citi México, S.A., Institución de Banca Múltiple, Grupo Financiero Citi México, en el presente Boletin estadístico (Citi México). Mediante oficio con fecha del 24 de septiembre de 2024 se aprobó el cambio de denominación de ABC Capital, S.A., Institución de Banca Múltiple (ABC Capital) a Ualá, S.A., Institución de Banca Múltiple, en el presente Boletín estadístico (Banco Ualá).
B19: El 1 de diciembre de 2024 Citigroup (Citigroup Inc.) concretó la separación del negocio de banca corporativa y privada de los negocios de consumo y banca empresarial. A partir de esa fecha, Citi opera en México a través de dos grupos financieros separados e independientes: Grupo Financiero Banamex y Grupo Financiero Citi México; por lo anterior, Citi gestionará el negocio de banca corporativa y privada (cartera comercial) y Banamex llevará el negocio de consumo y la banca empresarial (cartera comercial, de consumo y a la vivienda).
B21: El 18 de diciembre de 2024 se le notifica a Banco Sabadell, S.A., Institución de Banca Múltiple, que podrá llevar a cabo la fusión con Sabcapital, S.A. de C.V., Sociedad Financiera de Objeto Múltiple, Entidad Regulada, como sociedad fusionada, a partir de enero de 2025.

Sheet Índice
B4: Índice
B5: Presentación
B7: I. Índice de Capitalización y Evaluación de la Calidad de la Información
B8: Artículo 121 Ley de Instituciones de Crédito
B9: Metodología de Evaluación Sistema Financiero
B10: Metodología Evaluación Cartera Comercial
B11: Metodología Evaluación Cartera a la Vivienda
B12: Evaluación de Calidad a la Información
B14: II. Estadísticas de la Banca Múltiple
B15: Principales Rubros del Estado de Situación Financiera y Estado de Resultado Integral
B16: Indicadores Financieros
B17: Cartera de Crédito Total
... B36: III. Estados Financieros

Sheet Presentación
A2: Presentación
A3: La Comisión Nacional Bancaria y de Valores (CNBV) emite el presente documento para cumplir con lo dispuesto por la fracción XXIII del Artículo 4º de la Ley de la Comisión Nacional Bancaria y de Valores. Mediante la difusión de este boletín estadístico se persigue promover la transparencia y autorregulación del sector de Banca Múltiple, así como proveer a los mercados y al público en general información suficiente y confiable, que permita el análisis y seguimiento de estas instituciones.
A4: El boletín estadístico se encuentra dividido en 3 secciones: En primer lugar se informa sobre el nivel del Índice de Capitalización de las instituciones y su correspondiente categoría de Alertas Tempranas. Además, se presenta la tabla de Evaluación de la Calidad y Oportunidad de la Información con el que se califica el envío de los reportes regulatorios que las entidades supervisadas entregan a este organismo.
A5: En segundo lugar se muestra la información estadística relevante y principales indicadores de rentabilidad de cada institución de banca múltiple que proviene o se calcula con sus estados financieros consolidados.
A6: Enseguida se presenta la información reportada por las 52 instituciones de banca múltiple en operación correspondiente a agosto de 2025, consolidada con la de sus SOFOMER (Sociedades Financieras de Objeto Múltiple, Entidades Reguladas) en el caso de los siguientes bancos: Banamex con Tarjetas Banamex; Santander con Santander Inclusión Financiera; CI Banco con Finanmadrid México; Banco del Bajío con Financiera Bajío; Banregio con Start Banregio; Inbursa con STM Financial, SOFOM Inbursa y CETELEM Inbursa; Afirme con Arrendadora Afirme; Banco Base con Arrendadora Base, Invex con Invex Consumo; Bancrea con Arrendadora Bancrea, así como Ve por Más con Arrendadora Ve por Más.
A7: Se incluyen los indicadores financieros destacados, los saldos de cada tipo de crédito y de la captación de recursos.
A8: Por último, se hace un compendio de los estados financieros que las instituciones de banca múltiple reportaron a esta Comisión, al igual que en las secciones anteriores, se incluye información consolidada de las instituciones de banca múltiple con las SOFOMER de cada banco.

Sheet Portadilla I
A7: I. Índice de Capitalización y Evaluación de la Calidad de la Información.
A8: El objetivo de este apartado es proporcionar al público los indicadores de capitalización de los bancos, con las cifras disponibles en la fecha de elaboración del presente boletín, así como la clasificación de las instituciones de banca múltiple en distintas categorías, de acuerdo con las disposiciones de Alertas Tempranas.
A9: Por otra parte, se presenta la evaluación de la calidad y oportunidad de la información que entregan las instituciones a este Organismo, la cual considera la oportunidad con la que reportan y el número de reenvíos.

Sheet Art_121
B4: REGLAS DE CARÁCTER GENERAL A QUE SE REFIERE EL ARTÍCULO 121 DE LA LEY DE INSTITUCIONES DE CRÉDITO.
B5: Con el fin de mantener informado al público sobre el desempeño de las instituciones que conforman al sector de banca múltiple, la CNBV con fundamento en lo dispuesto en el artículo 121 de la Ley de Instituciones de Crédito, en relación con los artículos 220 y 221 de las Disposiciones de carácter general aplicables a las instituciones de crédito (las Disposiciones), da a conocer la clasificación de las instituciones de banca múltiple en categorías, con base en el índice de capitalización requerido conforme a las disposiciones aplicables a los requerimientos de capitalización, emitidas por esta Comisión en términos del artículo 50 de la Ley de Instituciones de Crédito
B6: CLASIFICACIÓN DE LAS INSTITUCIONES DE BANCA MÚLTIPLE DE ACUERDO CON EL ARTÍCULO 220 DE LAS DISPOSICIONES
B7: INDICADORES DE CAPITALIZACIÓN CIFRAS AL 31 DE JULIO DE 20251/
B8: Institución | C8: CCB 2/ % | D8: CCF 3/ % | E8: ICAP 4/ % | F8: Categoría 5/
B9: Actinver | C9: 18.196937 | D9: 18.196937 | E9: 18.196937 | F9: I
B10: Afirme | C10: 11.430329 | D10: 10.403862 | E10: 15.351335 | F10: I
B11: Autofin | C11: 13.20908 | D11: 13.20908 | E11: 13.20908 | F11: I
B12: Banamex | C12: 21.007107 | D12: 17.867328 | E12: 21.007107 | F12: I
B13: Banca Mifel | C13: 16.590164 | D13: 16.590164 | E13: 16.735582 | F13: I
B14: Banco Azteca | C14: 13.889673 | D14: 13.889673 | E14: 14.365216 | F14: I
B15: Banco Base | C15: 23.354958 | D15: 23.354958 | E15: 23.354958 | F15: I
B16: Banco Bineo | C16: 259.1889 | D16: 259.1889 | E16: 259.1889 | F16: I
B17: Banco Covalto | C17: 13.337459 | D17: 13.337459 | E17: 13.337459 | F17: I
B18: Banco del Bajío | C18: 14.466207 | D18: 14.466207 | E18: 14.709493 | F18: I
B19: Banco S3 | C19: 181.66557 | D19: 181.66557 | E19: 181.66557 | F19: I
B20: Banco Ualá | C20: 36.441537 | D20: 36.441537 | E20: 36.441537 | F20: I
... B60: Volkswagen Bank | C60: 27.505769 | D60: 27.505769 | E60: 27.505769 | F60: I
B61: Total Banca Múltiple | C61: 18.1448 | D61: 16.8123 | E61: 20.2415
B62: 1/ Dado a conocer a esta Comisión por el Banco de México el 12 de agosto de 2025, con base en la información entregada por las Instituciones, conforme a lo dispuesto por el artículo 2 Bis y 2 Bis 4 de las Disposiciones.
B63: 2/ CCB (Coeficiente de Capital Básico) = (Capital Fundamental + Capital no Fundamental) / Activos Ponderados Sujetos a Riesgo Total.
B64: 3/ CCF (Coeficiente de Capital Fundamental) = Capital Fundamental / Activos Ponderados Sujetos a Riesgo Total.
B65: 4/ ICAP (Índice de Capitalización) = Capital Neto / Activos Ponderados Sujetos a Riesgo Total.
B66: 5/ Categorías de Alertas Tempranas determinadas con base en el artículo 220 de las Disposiciones.

Sheet Ficha Técnica
B11: Evaluación de la Calidad de la Información
B12: Banca Múltiple
B14: Derivado de la mejora continua en los procesos de verificación de la calidad en la información, esta comisión ha modificado los criterios de evaluación de la calidad y los hábitos de envío de los reportes regulatorios que son transmitidos por las Instituciones de Banca Múltiple, por lo cual, se ha optado por generar un indicador único de calidad que refleje el estado actual obtenido para los reportes regulatorios, clasificados en 5 tipos de información distintos:
B20: Clave | C20: Clasificación | E20: Reportes | F20: Descripción
B21: 1 | C21: Situación financiera | E21: 22 | F21: Reportes de las series R01, R04 A, R06, R07, R08, R10, R12 , R13, R14, R32, R34 y R36.
B22: 2 | C22: Cartera Comercial | E22: 11 | F22: Reportes de la serie R04 C.
B23: 3 | C23: Cartera a la Vivienda | E23: 4 | F23: Reportes de la serie R04 H.
B24: 4 | C24: Captación | E24: 1 | F24: Reporte R24 B-2421.
B25: 5 | C25: Operativos | E25: 23 | F25: Reportes de las series R15, R24 B-2422, R24 B-2423, R24 C, R24 D, R24 E, R26, R27, R28, R29 y R35.
B27: Tomando en consideración la anterior clasificación, se generan 2 métricas para el cálculo del indicador único, como a continuación se muestra:
B30: 1. Calidad
B32: Para la medición del porcentaje de calidad obtenido, se identifican las incidencias presentadas en la ventana de evaluación del periodo, estas incidencias tienen ponderadores específicos para cada IBM, los cuáles se calculan a través de la distribución de sus errores presentados de manera histórica y se omiten aquellos reportes que por la naturaleza de su negocio no le son aplicables a cada IBM.
B37: 2. Oportunidad 1/
B39: Para la evaluación de hábitos de envío se consideran 3 conductas que no son adecuadas, siendo estas, los reenvíos, entregas extemporáneas y reportes omisos a la fecha de corte y que se encuentren en la ventana de evaluación. De igual forma se ponderan en la ventana de evaluación en función del comportamiento histórico y se ponderan de diferente forma en función del porcentaje de calidad obtenido.
B43: 2. Calificación final
B45: Tomando en consideración las 2 calificaciones previas, se determina una calificación final, la cual servirá como indicador general de evaluación para las IBM, el cual se calcula multiplicando el porcentaje de calidad obtenido por el porcentaje de oportunidad.
B50: Determinación de semáforos
B52: La determinación de semáforos se realiza con base en los siguientes criterios:
B54: Rojo | D54: Se asigna para instituciones que tienen una calificación final inferior a 90 puntos.
B56: Amarillo | D56: Se asigna para las instituciones que tienen una calificación de 90 o más y menor de 95 puntos.
B58: Verde | D58: Se asigna para las instituciones con 95 puntos o más.
B60: 1/ Debido a las intermitencias en el aplicativo SITI WEB, que han ocasionado retrasos involuntarios en la recepción de los Reportes Regulatorios transmitidos a la CNBV, la calificación no penaliza los hábitos de envío desde diciembre de 2023 hasta la fecha.

Sheet Evaluación Calidad
B7: Evaluación de la Calidad de la Información
B8: Banca Múltiple
B9: agosto 2025
J10: Fecha de corte: 23 de septiembre de 2025
B11: RANKING | C11: INSTITUCIÓN | G11: CALIFICACIÓN | J11: CALIDAD | K11: OPORTUNIDAD
B12: 1 | C12: 040126 | D12: Credit Suisse | G12: 100 | H12: 100 | J12: 100 | K12: 100
B13: 1 | C13: 040139 | D13: BIAfirme | G13: 100 | H13: 100 | J13: 100 | K13: 100
B14: 1 | C14: 040162 | D14: KEB Hana México | G14: 100 | H14: 100 | J14: 100 | K14: 100
B15: 1 | C15: 040165 | D15: Banco Bineo | G15: 100 | H15: 100 | J15: 100 | K15: 100
B16: 1 | C16: 040167 | D16: Hey Banco | G16: 100 | H16: 100 | J16: 100 | K16: 100
B17: 1 | C17: 040169 | D17: Openbank | G17: 100 | H17: 100 | J17: 100 | K17: 100
B18: 7 | C18: 040002 | D18: Banamex | G18: 99.93 | H18: 99.93 | J18: 99.93 | K18: 100
B19: 8 | C19: 040030 | D19: Banco del Bajío | G19: 99.86 | H19: 99.86 | J19: 99.86 | K19: 100
B20: 9 | C20: 040151 | D20: Dondé Banco | G20: 99.71 | H20: 99.71 | J20: 99.71 | K20: 100
B21: 10 | C21: 040108 | D21: MUFG Bank | G21: 99.61 | H21: 99.61 | J21: 99.61 | K21: 100
B22: 11 | C22: 040129 | D22: Barclays | G22: 99.56 | H22: 99.56 | J22: 99.56 | K22: 100
B23: 12 | C23: 040159 | D23: Bank of China | G23: 99.52 | H23: 99.52 | J23: 99.52 | K23: 100
... B63: 52 | C63: 040136 | D63: Intercam Banco | G63: 76.88 | H63: 76.88 | J63: 76.88 | K63: 100
B101: =_xlfn.XLOOKUP(C101,[1]Calificación!D:D,[1]Calificación!A:A,"",0,1) | C101: =IF([1]Calificación!D88=0,"",[1]Calificación!D88) | D101: =IFERROR(VLOOKUP(C101,[1]Calificación!$D$1:$X$53,2,0),"") | G101: =IFERROR(VLOOKUP(C101,[1]Calificación!$D$1:$X$53,5,0),"") | H101: =IFERROR(VLOOKUP(C101,[1]Calificación!$D$1:$X$53,6,0),"") | J101: =IFERROR(VLOOKUP(C101,[1]Calificación!$D$1:$X$53,3,0),"") | K101: =IFERROR(VLOOKUP(C101,[1]Calificación!$D$1:$X$53,4,0),"")
B102: =_xlfn.XLOOKUP(C102,[1]Calificación!D:D,[1]Calificación!A:A,"",0,1) | C102: =IF([1]Calificación!D89=0,"",[1]Calificación!D89) | D102: =IFERROR(VLOOKUP(C102,[1]Calificación!$D$1:$X$53,2,0),"") | G102: =IFERROR(VLOOKUP(C102,[1]Calificación!$D$1:$X$53,5,0),"") | H102: =IFERROR(VLOOKUP(C102,[1]Calificación!$D$1:$X$53,6,0),"") | J102: =IFERROR(VLOOKUP(C102,[1]Calificación!$D$1:$X$53,3,0),"") | K102: =IFERROR(VLOOKUP(C102,[1]Calificación!$D$1:$X$53,4,0),"")
B103: =_xlfn.XLOOKUP(C103,[1]Calificación!D:D,[1]Calificación!A:A,"",0,1) | C103: =IF([1]Calificación!D90=0,"",[1]Calificación!D90) | D103: =IFERROR(VLOOKUP(C103,[1]Calificación!$D$1:$X$53,2,0),"") | G103: =IFERROR(VLOOKUP(C103,[1]Calificación!$D$1:$X$53,5,0),"") | H103: =IFERROR(VLOOKUP(C103,[1]Calificación!$D$1:$X$53,6,0),"") | J103: =IFERROR(VLOOKUP(C103,[1]Calificación!$D$1:$X$53,3,0),"") | K103: =IFERROR(VLOOKUP(C103,[1]Calificación!$D$1:$X$53,4,0),"")
B104: =_xlfn.XLOOKUP(C104,[1]Calificación!D:D,[1]Calificación!A:A,"",0,1) | C104: =IF([1]Calificación!D91=0,"",[1]Calificación!D91) | D104: =IFERROR(VLOOKUP(C104,[1]Calificación!$D$1:$X$53,2,0),"") | G104: =IFERROR(VLOOKUP(C104,[1]Calificación!$D$1:$X$53,5,0),"") | H104: =IFERROR(VLOOKUP(C104,[1]Calificación!$D$1:$X$53,6,0),"") | J104: =IFERROR(VLOOKUP(C104,[1]Calificación!$D$1:$X$53,3,0),"") | K104: =IFERROR(VLOOKUP(C104,[1]Calificación!$D$1:$X$53,4,0),"")
B105: =_xlfn.XLOOKUP(C105,[1]Calificación!D:D,[1]Calificación!A:A,"",0,1) | C105: =IF([1]Calificación!D92=0,"",[1]Calificación!D92) | D105: =IFERROR(VLOOKUP(C105,[1]Calificación!$D$1:$X$53,2,0),"") | G105: =IFERROR(VLOOKUP(C105,[1]Calificación!$D$1:$X$53,5,0),"") | H105: =IFERROR(VLOOKUP(C105,[1]Calificación!$D$1:$X$53,6,0),"") | J105: =IFERROR(VLOOKUP(C105,[1]Calificación!$D$1:$X$53,3,0),"") | K105: =IFERROR(VLOOKUP(C105,[1]Calificación!$D$1:$X$53,4,0),"")
B106: =_xlfn.XLOOKUP(C106,[1]Calificación!D:D,[1]Calificación!A:A,"",0,1) | C106: =IF([1]Calificación!D93=0,"",[1]Calificación!D93) | D106: =IFERROR(VLOOKUP(C106,[1]Calificación!$D$1:$X$53,2,0),"") | G106: =IFERROR(VLOOKUP(C106,[1]Calificación!$D$1:$X$53,5,0),"") | H106: =IFERROR(VLOOKUP(C106,[1]Calificación!$D$1:$X$53,6,0),"") | J106: =IFERROR(VLOOKUP(C106,[1]Calificación!$D$1:$X$53,3,0),"") | K106: =IFERROR(VLOOKUP(C106,[1]Calificación!$D$1:$X$53,4,0),"")
B107: =_xlfn.XLOOKUP(C107,[1]Calificación!D:D,[1]Calificación!A:A,"",0,1) | C107: =IF([1]Calificación!D94=0,"",[1]Calificación!D94) | D107: =IFERROR(VLOOKUP(C107,[1]Calificación!$D$1:$X$53,2,0),"") | G107: =IFERROR(VLOOKUP(C107,[1]Calificación!$D$1:$X$53,5,0),"") | H107: =IFERROR(VLOOKUP(C107,[1]Calificación!$D$1:$X$53,6,0),"") | J107: =IFERROR(VLOOKUP(C107,[1]Calificación!$D$1:$X$53,3,0),"") | K107: =IFERROR(VLOOKUP(C107,[1]Calificación!$D$1:$X$53,4,0),"")
B108: =_xlfn.XLOOKUP(C108,[1]Calificación!D:D,[1]Calificación!A:A,"",0,1) | C108: =IF([1]Calificación!D95=0,"",[1]Calificación!D95) | D108: =IFERROR(VLOOKUP(C108,[1]Calificación!$D$1:$X$53,2,0),"") | G108: =IFERROR(VLOOKUP(C108,[1]Calificación!$D$1:$X$53,5,0),"") | H108: =IFERROR(VLOOKUP(C108,[1]Calificación!$D$1:$X$53,6,0),"") | J108: =IFERROR(VLOOKUP(C108,[1]Calificación!$D$1:$X$53,3,0),"") | K108: =IFERROR(VLOOKUP(C108,[1]Calificación!$D$1:$X$53,4,0),"")
B109: =_xlfn.XLOOKUP(C109,[1]Calificación!D:D,[1]Calificación!A:A,"",0,1) | C109: =IF([1]Calificación!D96=0,"",[1]Calificación!D96) | D109: =IFERROR(VLOOKUP(C109,[1]Calificación!$D$1:$X$53,2,0),"") | G109: =IFERROR(VLOOKUP(C109,[1]Calificación!$D$1:$X$53,5,0),"") | H109: =IFERROR(VLOOKUP(C109,[1]Calificación!$D$1:$X$53,6,0),"") | J109: =IFERROR(VLOOKUP(C109,[1]Calificación!$D$1:$X$53,3,0),"") | K109: =IFERROR(VLOOKUP(C109,[1]Calificación!$D$1:$X$53,4,0),"")
B110: =_xlfn.XLOOKUP(C110,[1]Calificación!D:D,[1]Calificación!A:A,"",0,1) | C110: =IF([1]Calificación!D97=0,"",[1]Calificación!D97) | D110: =IFERROR(VLOOKUP(C110,[1]Calificación!$D$1:$X$53,2,0),"") | G110: =IFERROR(VLOOKUP(C110,[1]Calificación!$D$1:$X$53,5,0),"") | H110: =IFERROR(VLOOKUP(C110,[1]Calificación!$D$1:$X$53,6,0),"") | J110: =IFERROR(VLOOKUP(C110,[1]Calificación!$D$1:$X$53,3,0),"") | K110: =IFERROR(VLOOKUP(C110,[1]Calificación!$D$1:$X$53,4,0),"")
B111: =_xlfn.XLOOKUP(C111,[1]Calificación!D:D,[1]Calificación!A:A,"",0,1) | C111: =IF([1]Calificación!D98=0,"",[1]Calificación!D98) | D111: =IFERROR(VLOOKUP(C111,[1]Calificación!$D$1:$X$53,2,0),"") | G111: =IFERROR(VLOOKUP(C111,[1]Calificación!$D$1:$X$53,5,0),"") | H111: =IFERROR(VLOOKUP(C111,[1]Calificación!$D$1:$X$53,6,0),"") | J111: =IFERROR(VLOOKUP(C111,[1]Calificación!$D$1:$X$53,3,0),"") | K111: =IFERROR(VLOOKUP(C111,[1]Calificación!$D$1:$X$53,4,0),"")
B112: =_xlfn.XLOOKUP(C112,[1]Calificación!D:D,[1]Calificación!A:A,"",0,1) | C112: =IF([1]Calificación!D99=0,"",[1]Calificación!D99) | D112: =IFERROR(VLOOKUP(C112,[1]Calificación!$D$1:$X$53,2,0),"") | G112: =IFERROR(VLOOKUP(C112,[1]Calificación!$D$1:$X$53,5,0),"") | H112: =IFERROR(VLOOKUP(C112,[1]Calificación!$D$1:$X$53,6,0),"") | J112: =IFERROR(VLOOKUP(C112,[1]Calificación!$D$1:$X$53,3,0),"") | K112: =IFERROR(VLOOKUP(C112,[1]Calificación!$D$1:$X$53,4,0),"")
... B133: =_xlfn.XLOOKUP(C133,[1]Calificación!D:D,[1]Calificación!A:A,"",0,1) | C133: =IF([1]Calificación!D120=0,"",[1]Calificación!D120) | D133: =IFERROR(VLOOKUP(C133,[1]Calificación!$D$1:$X$53,2,0),"") | G133: =IFERROR(VLOOKUP(C133,[1]Calificación!$D$1:$X$53,5,0),"") | H133: =IFERROR(VLOOKUP(C133,[1]Calificación!$D$1:$X$53,6,0),"") | J133: =IFERROR(VLOOKUP(C133,[1]Calificación!$D$1:$X$53,3,0),"") | K133: =IFERROR(VLOOKUP(C133,[1]Calificación!$D$1:$X$53,4,0),"")

Sheet Evaluación Calidad Grupos
B7: Evaluación de la Calidad de la Información
B8: Banca Múltiple
B9: agosto 2025
K10: Fecha de corte: 23 de septiembre de 2025
B11: RANKING | C11: INSTITUCIÓN | G11: CALIFICACIÓN | K11: CALIDAD | L11: OPORTUNIDAD
B12: G7
B13: 1 | C13: 040002 | D13: Banamex | G13: 99.93 | H13: 99.93 | K13: 99.93 | L13: 100 | O13: G-7
B14: 2 | C14: 040072 | D14: Banorte | G14: 97.83 | H14: 97.83 | K14: 97.83 | L14: 100 | O14: G-7
B15: 3 | C15: 040036 | D15: Inbursa | G15: 96.87 | H15: 96.87 | K15: 96.87 | L15: 100 | O15: G-7
B16: 4 | C16: 040044 | D16: Scotiabank | G16: 96.8 | H16: 96.8 | K16: 96.8 | L16: 100 | O16: G-7
B17: 5 | C17: 040021 | D17: HSBC | G17: 95.68 | H17: 95.68 | K17: 95.68 | L17: 100 | O17: G-7
B18: 6 | C18: 040012 | D18: BBVA México | G18: 95.15 | H18: 95.15 | K18: 95.15 | L18: 100 | O18: G-7
B19: 7 | C19: 040014 | D19: Santander | G19: 90.2 | H19: 90.2 | K19: 90.2 | L19: 100 | O19: G-7
B21: BANCOS CAMBIARIOS
B22: 1 | C22: 040112 | D22: Monex | G22: 96.67 | H22: 96.67 | K22: 96.67 | L22: 100 | O22: Bancos Cambiarios
B23: 2 | C23: 040143 | D23: CIBanco | G23: 92.76 | H23: 92.76 | K23: 92.76 | L23: 100 | O23: Bancos Cambiarios
B24: 3 | C24: 040145 | D24: Banco Base | G24: 90.46 | H24: 90.46 | K24: 90.46 | L24: 100 | O24: Bancos Cambiarios
B25: 4 | C25: 040136 | D25: Intercam Banco | G25: 76.88 | H25: 76.88 | K25: 76.88 | L25: 100 | O25: Bancos Cambiarios
B27: BANCA DE INVERSIÓN Y OTROS SERVICIOS
B28: 1 | C28: 040126 | D28: Credit Suisse | G28: 100 | H28: 100 | K28: 100 | L28: 100 | O28: Banca de Inversión y Otros Servicios
B29: 1 | C29: 040139 | D29: BIAfirme | G29: 100 | H29: 100 | K29: 100 | L29: 100 | O29: Banca de Inversión y Otros Servicios
B30: 3 | C30: 040108 | D30: MUFG Bank | G30: 99.61 | H30: 99.61 | K30: 99.61 | L30: 100 | O30: Banca de Inversión y Otros Servicios
B31: 4 | C31: 040129 | D31: Barclays | G31: 99.56 | H31: 99.56 | K31: 99.56 | L31: 100 | O31: Banca de Inversión y Otros Servicios
B32: 5 | C32: 040124 | D32: Citi México (Antes CBM Banco) | G32: 99.01 | H32: 99.01 | K32: 99.01 | L32: 100 | O32: Banca de Inversión y Otros Servicios
B33: 6 | C33: 040148 | D33: Pagatodo | G33: 98.19 | H33: 98.19 | K33: 98.19 | L33: 100 | O33: Banca de Inversión y Otros Servicios
B34: 7 | C34: 040164 | D34: BNP Paribas México | G34: 97.99 | H34: 97.99 | K34: 97.99 | L34: 100 | O34: Banca de Inversión y Otros Servicios
B35: 8 | C35: 040106 | D35: Bank of America | G35: 97.65 | H35: 97.65 | K35: 97.65 | L35: 100 | O35: Banca de Inversión y Otros Servicios
B36: 9 | C36: 040160 | D36: Banco S3 | G36: 96.77 | H36: 96.77 | K36: 96.77 | L36: 100 | O36: Banca de Inversión y Otros Servicios
B37: 10 | C37: 040110 | D37: J.P. Morgan | G37: 94.57 | H37: 94.57 | K37: 94.57 | L37: 100 | O37: Banca de Inversión y Otros Servicios
B38: 11 | C38: 040062 | D38: Afirme | G38: 93.49 | H38: 93.49 | K38: 93.49 | L38: 100 | O38: Banca de Inversión y Otros Servicios
B39: 12 | C39: 040059 | D39: Invex | G39: 87.81 | H39: 87.81 | K39: 87.81 | L39: 100 | O39: Banca de Inversión y Otros Servicios
B41: COMERCIAL MEDIANO
B42: 1 | C42: 040030 | D42: Banco del Bajío | G42: 99.86 | H42: 99.86 | K42: 99.86 | L42: 100 | O42: Comercial Mediano
B43: 2 | C43: 040113 | D43: Ve por Más | G43: 99.43 | H43: 99.43 | K43: 99.43 | L43: 100 | O43: Comercial Mediano
B44: 3 | C44: 040156 | D44: Sabadell | G44: 98.53 | H44: 98.53 | K44: 98.53 | L44: 100 | O44: Comercial Mediano
B45: 4 | C45: 040058 | D45: Banregio | G45: 96.93 | H45: 96.93 | K45: 96.93 | L45: 100 | O45: Comercial Mediano
B46: 5 | C46: 040132 | D46: Multiva | G46: 95.16 | H46: 95.16 | K46: 95.16 | L46: 100 | O46: Comercial Mediano
B47: 6 | C47: 040042 | D47: Banca Mifel | G47: 94.9 | H47: 94.9 | K47: 94.9 | L47: 100 | O47: Comercial Mediano
B49: COMERCIAL PEQUEÑO
B50: 1 | C50: 040162 | D50: KEB Hana México | G50: 100 | H50: 100 | K50: 100 | L50: 100 | O50: Comercial pequeño
B51: 2 | C51: 040151 | D51: Dondé Banco | G51: 99.71 | H51: 99.71 | K51: 99.71 | L51: 100 | O51: Comercial pequeño
B52: 3 | C52: 040159 | D52: Bank of China | G52: 99.52 | H52: 99.52 | K52: 99.52 | L52: 100 | O52: Comercial pequeño
B53: 4 | C53: 040147 | D53: Bankaool | G53: 99.43 | H53: 99.43 | K53: 99.43 | L53: 100 | O53: Comercial pequeño
B54: 5 | C54: 040155 | D54: ICBC | G54: 98.96 | H54: 98.96 | K54: 98.96 | L54: 100 | O54: Comercial pequeño
B55: 6 | C55: 040060 | D55: Bansí | G55: 98.26 | H55: 98.26 | K55: 98.26 | L55: 100 | O55: Comercial pequeño
B56: 7 | C56: 040154 | D56: Covalto | G56: 97.47 | H56: 97.47 | K56: 97.47 | L56: 100 | O56: Comercial pequeño
B57: 8 | C57: 040157 | D57: Shinhan | G57: 97.32 | H57: 97.32 | K57: 97.32 | L57: 100 | O57: Comercial pequeño
B58: 9 | C58: 040158 | D58: Mizuho Bank | G58: 96.62 | H58: 96.62 | K58: 96.62 | L58: 100 | O58: Comercial pequeño
B59: 10 | C59: 040150 | D59: Inmobiliario Mexicano | G59: 96.28 | H59: 96.28 | K59: 96.28 | L59: 100 | O59: Comercial pequeño
B60: 11 | C60: 040133 | D60: Actinver | G60: 95.62 | H60: 95.62 | K60: 95.62 | L60: 100 | O60: Comercial pequeño
B61: 12 | C61: 040138 | D61: Ualá | G61: 95.04 | H61: 95.04 | K61: 95.04 | L61: 100 | O61: Comercial pequeño
... B63: 14 | C63: 040152 | D63: Bancrea | G63: 87.2 | H63: 87.2 | K63: 87.2 | L63: 100 | O63: Comercial pequeño
B65: CRÉDITOS A LOS HOGARES
B66: 1 | C66: 040165 | D66: Banco Bineo | G66: 100 | H66: 100 | K66: 100 | L66: 100 | O66: Créditos a los Hogares
B67: 1 | C67: 040167 | D67: Hey Banco | G67: 100 | H67: 100 | K67: 100 | L67: 100 | O67: Créditos a los Hogares
B68: 1 | C68: 040169 | D68: Openbank | G68: 100 | H68: 100 | K68: 100 | L68: 100 | O68: Créditos a los Hogares
B69: 4 | C69: 040149 | D69: Forjadores | G69: 99.32 | H69: 99.32 | K69: 99.32 | L69: 100 | O69: Créditos a los Hogares
B70: 5 | C70: 040130 | D70: Compartamos | G70: 98.97 | H70: 98.97 | K70: 98.97 | L70: 100 | O70: Créditos a los Hogares
B71: 6 | C71: 040141 | D71: Volkswagen Bank | G71: 98.84 | H71: 98.84 | K71: 98.84 | L71: 100 | O71: Créditos a los Hogares
B72: 7 | C72: 040137 | D72: Bancoppel | G72: 97.3 | H72: 97.3 | K72: 97.3 | L72: 100 | O72: Créditos a los Hogares
B73: 8 | C73: 040127 | D73: Banco Azteca | G73: 96.12 | H73: 96.12 | K73: 96.12 | L73: 100 | O73: Créditos a los Hogares
B74: 9 | C74: 040140 | D74: Consubanco | G74: 91.5 | H74: 91.5 | K74: 91.5 | L74: 100 | O74: Créditos a los Hogares

Sheet Evaluación Calidad Detallada
B3: Evaluación de la Calidad de la Información
B4: Banca Múltiple
B5: agosto 2025
M6: Fecha de corte: 23 de septiembre de 2025
B8: RANKING | C8: INSTITUCIÓN | G8: SITUACIÓN FINANCIERA | J8: CARTERA COMERCIAL | M8: CARTERA A LA VIVIENDA | P8: PRODUCTOS DE CAPTACIÓN | S8: OPERATIVOS
G9: CALIDAD | H9: OPORTUNIDAD | J9: CALIDAD | K9: OPORTUNIDAD | M9: CALIDAD | N9: OPORTUNIDAD | P9: CALIDAD | Q9: OPORTUNIDAD | S9: CALIDAD | T9: OPORTUNIDAD
B10: 1 | C10: 040126 | D10: Credit Suisse | G10: 100 | H10: 100 | J10: n.a | K10: 100 | M10: n.a | N10: 100 | P10: 100 | Q10: 100 | S10: 100 | T10: 100
B11: 1 | C11: 040139 | D11: BIAfirme | G11: 100 | H11: 100 | J11: 100 | K11: 100 | M11: n.a | N11: 100 | P11: 100 | Q11: 100 | S11: 100 | T11: 100
B12: 1 | C12: 040162 | D12: KEB Hana México | G12: 100 | H12: 100 | J12: 100 | K12: 100 | M12: n.a | N12: 100 | P12: 100 | Q12: 100 | S12: 100 | T12: 100
B13: 1 | C13: 040165 | D13: Banco Bineo | G13: 100 | H13: 100 | J13: n.a | K13: 100 | M13: n.a | N13: 100 | P13: 100 | Q13: 100 | S13: 100 | T13: 100
B14: 1 | C14: 040167 | D14: Hey Banco | G14: 100 | H14: 100 | J14: n.a | K14: 100 | M14: n.a | N14: 100 | P14: 100 | Q14: 100 | S14: 100 | T14: 100
B15: 1 | C15: 040169 | D15: Openbank | G15: 100 | H15: 100 | J15: n.a | K15: 100 | M15: n.a | N15: 100 | P15: 100 | Q15: 100 | S15: 100 | T15: 100
B16: 7 | C16: 040002 | D16: Banamex | G16: 100 | H16: 100 | J16: 99.76 | K16: 100 | M16: 100 | N16: 100 | P16: 100 | Q16: 100 | S16: 100 | T16: 100
B17: 8 | C17: 040030 | D17: Banco del Bajío | G17: 100 | H17: 100 | J17: 99.52 | K17: 100 | M17: 100 | N17: 100 | P17: 100 | Q17: 100 | S17: 100 | T17: 100
B18: 9 | C18: 040151 | D18: Dondé Banco | G18: 100 | H18: 100 | J18: 99.54 | K18: 100 | M18: n.a | N18: 100 | P18: 97.44 | Q18: 100 | S18: 100 | T18: 100
B19: 10 | C19: 040108 | D19: MUFG Bank | G19: 99.73 | H19: 100 | J19: 99.31 | K19: 100 | M19: n.a | N19: 100 | P19: 100 | Q19: 100 | S19: 100 | T19: 100
B20: 11 | C20: 040129 | D20: Barclays | G20: 99.1 | H20: 100 | J20: n.a | K20: 100 | M20: n.a | N20: 100 | P20: 100 | Q20: 100 | S20: 100 | T20: 100
B21: 12 | C21: 040159 | D21: Bank of China | G21: 99.43 | H21: 100 | J21: 100 | K21: 100 | M21: n.a | N21: 100 | P21: 92.31 | Q21: 100 | S21: 100 | T21: 100
B22: 13 | C22: 040113 | D22: Ve por Más | G22: 100 | H22: 100 | J22: 98.29 | K22: 100 | M22: 100 | N22: 100 | P22: 100 | Q22: 100 | S22: 99.49 | T22: 100
B23: 14 | C23: 040147 | D23: Bankaool | G23: 99.47 | H23: 100 | J23: 99.31 | K23: 100 | M23: n.a | N23: 100 | P23: 100 | Q23: 100 | S23: 99.49 | T23: 100
B24: 15 | C24: 040149 | D24: Forjadores | G24: 100 | H24: 100 | J24: 98.38 | K24: 100 | M24: n.a | N24: 100 | P24: 100 | Q24: 100 | S24: 100 | T24: 100
B25: 16 | C25: 040124 | D25: Citi México (Antes CBM Banco) | G25: 100 | H25: 100 | J25: 98.33 | K25: 100 | M25: n.a | N25: 100 | P25: n.a | Q25: 100 | S25: 98.46 | T25: 100
B26: 17 | C26: 040130 | D26: Compartamos | G26: 99.01 | H26: 100 | J26: 99.76 | K26: 100 | M26: n.a | N26: 100 | P26: 84.62 | Q26: 100 | S26: 100 | T26: 100
B27: 18 | C27: 040155 | D27: ICBC | G27: 97.53 | H27: 100 | J27: 100 | K27: 100 | M27: n.a | N27: 100 | P27: 94.87 | Q27: 100 | S27: 100 | T27: 100
B28: 19 | C28: 040141 | D28: Volkswagen Bank | G28: 99.49 | H28: 100 | J28: n.a | K28: 100 | M28: n.a | N28: 100 | P28: 100 | Q28: 100 | S28: 100 | T28: 100
B29: 20 | C29: 040156 | D29: Sabadell | G29: 100 | H29: 100 | J29: 95.21 | K29: 100 | M29: 100 | N29: 100 | P29: 100 | Q29: 100 | S29: 100 | T29: 100
B30: 21 | C30: 040060 | D30: Bansí | G30: 100 | H30: 100 | J30: 96.38 | K30: 100 | M30: 100 | N30: 100 | P30: 100 | Q30: 100 | S30: 95.38 | T30: 100
B31: 22 | C31: 040148 | D31: Pagatodo | G31: 100 | H31: 100 | J31: n.a | K31: 100 | M31: n.a | N31: 100 | P31: 79.49 | Q31: 100 | S31: 100 | T31: 100
B32: 23 | C32: 040164 | D32: BNP Paribas México | G32: 96.1 | H32: 100 | J32: n.a | K32: 100 | M32: n.a | N32: 100 | P32: n.a | Q32: 100 | S32: 100 | T32: 100
B33: 24 | C33: 040072 | D33: Banorte | G33: 100 | H33: 100 | J33: 96.64 | K33: 100 | M33: 95.95 | N33: 100 | P33: 100 | Q33: 100 | S33: 100 | T33: 100
B34: 25 | C34: 040106 | D34: Bank of America | G34: 98.87 | H34: 100 | J34: 97.9 | K34: 100 | M34: n.a | N34: 100 | P34: 97.44 | Q34: 100 | S34: 94.87 | T34: 100
B35: 26 | C35: 040154 | D35: Covalto | G35: 98.63 | H35: 100 | J35: 95.2 | K35: 100 | M35: n.a | N35: 100 | P35: 100 | Q35: 100 | S35: 100 | T35: 100
B36: 27 | C36: 040157 | D36: Shinhan | G36: 100 | H36: 100 | J36: 93.74 | K36: 100 | M36: n.a | N36: 100 | P36: 100 | Q36: 100 | S36: 100 | T36: 100
B37: 28 | C37: 040137 | D37: Bancoppel | G37: 96.4 | H37: 100 | J37: 96.94 | K37: 100 | M37: 99.31 | N37: 100 | P37: 100 | Q37: 100 | S37: 94.87 | T37: 100
B38: 29 | C38: 040058 | D38: Banregio | G38: 100 | H38: 100 | J38: 98.04 | K38: 100 | M38: 91.28 | N38: 100 | P38: 100 | Q38: 100 | S38: 100 | T38: 100
B39: 30 | C39: 040036 | D39: Inbursa | G39: 99.47 | H39: 100 | J39: 95.99 | K39: 100 | M39: 98.68 | N39: 100 | P39: 66.67 | Q39: 100 | S39: 95.9 | T39: 100
B40: 31 | C40: 040044 | D40: Scotiabank | G40: 100 | H40: 100 | J40: 98.38 | K40: 100 | M40: 90.81 | N40: 100 | P40: 100 | Q40: 100 | S40: 100 | T40: 100
B41: 32 | C41: 040160 | D41: Banco S3 | G41: 97.55 | H41: 100 | J41: 96.71 | K41: 100 | M41: n.a | N41: 100 | P41: 100 | Q41: 100 | S41: 94.87 | T41: 100
B42: 33 | C42: 040112 | D42: Monex | G42: 100 | H42: 100 | J42: 91.79 | K42: 100 | M42: 100 | N42: 100 | P42: 100 | Q42: 100 | S42: 93.33 | T42: 100
B43: 34 | C43: 040158 | D43: Mizuho Bank | G43: 99.18 | H43: 100 | J43: 92.76 | K43: 100 | M43: n.a | N43: 100 | P43: 100 | Q43: 100 | S43: 100 | T43: 100
B44: 35 | C44: 040150 | D44: Inmobiliario Mexicano | G44: 100 | H44: 100 | J44: 87.73 | K44: 100 | M44: 100 | N44: 100 | P44: 100 | Q44: 100 | S44: 100 | T44: 100
B45: 36 | C45: 040127 | D45: Banco Azteca | G45: 98.94 | H45: 100 | J45: 94.43 | K45: 100 | M45: 93.49 | N45: 100 | P45: 100 | Q45: 100 | S45: 99.49 | T45: 100
B46: 37 | C46: 040021 | D46: HSBC | G46: 100 | H46: 100 | J46: 96.96 | K46: 100 | M46: 88.06 | N46: 100 | P46: 100 | Q46: 100 | S46: 100 | T46: 100
B47: 38 | C47: 040133 | D47: Actinver | G47: 99.73 | H47: 100 | J47: 90.2 | K47: 100 | M47: n.a | N47: 100 | P47: 97.44 | Q47: 100 | S47: 100 | T47: 100
B48: 39 | C48: 040132 | D48: Multiva | G48: 100 | H48: 100 | J48: 86.54 | K48: 100 | M48: 97.16 | N48: 100 | P48: 100 | Q48: 100 | S48: 99.49 | T48: 100
B49: 40 | C49: 040012 | D49: BBVA México | G49: 100 | H49: 100 | J49: 84.09 | K49: 100 | M49: 100 | N49: 100 | P49: 100 | Q49: 100 | S49: 100 | T49: 100
B50: 41 | C50: 040138 | D50: Ualá | G50: 97.08 | H50: 100 | J50: 90.21 | K50: 100 | M50: 99.27 | N50: 100 | P50: 100 | Q50: 100 | S50: 92.82 | T50: 100
B51: 42 | C51: 040042 | D51: Banca Mifel | G51: 100 | H51: 100 | J51: 93.15 | K51: 100 | M51: 91.46 | N51: 100 | P51: 97.44 | Q51: 100 | S51: 96.41 | T51: 100
B52: 43 | C52: 040110 | D52: J.P. Morgan | G52: 100 | H52: 100 | J52: 90.69 | K52: 100 | M52: n.a | N52: 100 | P52: 94.87 | Q52: 100 | S52: 93.33 | T52: 100
B53: 44 | C53: 040062 | D53: Afirme | G53: 100 | H53: 100 | J53: 86.8 | K53: 100 | M53: 93.85 | N53: 100 | P53: 100 | Q53: 100 | S53: 93.85 | T53: 100
B54: 45 | C54: 040143 | D54: CIBanco | G54: 96.05 | H54: 100 | J54: 94.08 | K54: 100 | M54: 89.15 | N54: 100 | P54: 79.49 | Q54: 100 | S54: 94.36 | T54: 100
B55: 46 | C55: 040140 | D55: Consubanco | G55: 92.31 | H55: 100 | J55: 87.25 | K55: 100 | M55: n.a | N55: 100 | P55: 97.44 | Q55: 100 | S55: 98.46 | T55: 100
B56: 47 | C56: 040145 | D56: Banco Base | G56: 98.88 | H56: 100 | J56: 80.78 | K56: 100 | M56: n.a | N56: 100 | P56: 84.62 | Q56: 100 | S56: 97.95 | T56: 100
B57: 48 | C57: 040014 | D57: Santander | G57: 100 | H57: 100 | J57: 82.63 | K57: 100 | M57: 84.46 | N57: 100 | P57: 100 | Q57: 100 | S57: 98.97 | T57: 100
B58: 49 | C58: 040128 | D58: Kapital (Antes Autofin) | G58: 97.59 | H58: 100 | J58: 76.78 | K58: 100 | M58: 92.74 | N58: 100 | P58: 64.1 | Q58: 100 | S58: 95.9 | T58: 100
B59: 50 | C59: 040059 | D59: Invex | G59: 100 | H59: 100 | J59: 71.35 | K59: 100 | M59: 89.23 | N59: 100 | P59: 87.18 | Q59: 100 | S59: 99.49 | T59: 100
B60: 51 | C60: 040152 | D60: Bancrea | G60: 95.61 | H60: 100 | J60: 64.16 | K60: 100 | M60: 100 | N60: 100 | P60: 71.79 | Q60: 100 | S60: 97.95 | T60: 100
B61: 52 | C61: 040136 | D61: Intercam Banco | G61: 94.18 | H61: 100 | J61: 66.43 | K61: 100 | M61: n.a | N61: 100 | P61: 89.74 | Q61: 100 | S61: 92.31 | T61: 100
B101: =_xlfn.XLOOKUP(C101,[1]Calificación!D:D,[1]Calificación!A:A,"",0,1) | C101: =IF([1]Calificación!D90=0,"",[1]Calificación!D90) | D101: =IFERROR(VLOOKUP(C101,[1]Calificación!$D$1:$X$53,2,0),"") | G101: =IFERROR(VLOOKUP(C101,[1]Calificación!$D$1:$X$53,12,0),"") | H101: =IFERROR(IF(VLOOKUP(C101,[1]Calificación!$D$1:$X$53,13,0)=0,"n.a",VLOOKUP(C101,[1]Calificación!$D$1:$X$53,13,0)),"") | J101: =IFERROR(IF(VLOOKUP(C101,[1]Calificación!$D$1:$X$53,14,0)=0,"n.a",VLOOKUP(C101,[1]Calificación!$D$1:$X$53,14,0)),"") | K101: =IFERROR(IF(VLOOKUP(C101,[1]Calificación!$D$1:$X$53,15,0)=0,"n.a",VLOOKUP(C101,[1]Calificación!$D$1:$X$53,15,0)),"") | M101: =IFERROR(IF(VLOOKUP(C101,[1]Calificación!$D$1:$X$53,16,0)=0,"n.a",VLOOKUP(C101,[1]Calificación!$D$1:$X$53,16,0)),"") | N101: =IFERROR(IF(VLOOKUP(C101,[1]Calificación!$D$1:$X$53,17,0)=0,"n.a",VLOOKUP(C101,[1]Calificación!$D$1:$X$53,17,0)),"") | P101: =IFERROR(IF(VLOOKUP(C101,[1]Calificación!$D$1:$X$53,18,0)=0,"n.a",VLOOKUP(C101,[1]Calificación!$D$1:$X$53,18,0)),"") | Q101: =IFERROR(IF(VLOOKUP(C101,[1]Calificación!$D$1:$X$53,19,0)=0,"n.a",VLOOKUP(C101,[1]Calificación!$D$1:$X$53,19,0)),"") | S101: =IFERROR(IF(VLOOKUP(C101,[1]Calificación!$D$1:$X$53,20,0)=0,"n.a",VLOOKUP(C101,[1]Calificación!$D$1:$X$53,20,0)),"") | T101: =IFERROR(IF(VLOOKUP(C101,[1]Calificación!$D$1:$X$53,21,0)=0,"n.a",VLOOKUP(C101,[1]Calificación!$D$1:$X$53,21,0)),"")
B102: =_xlfn.XLOOKUP(C102,[1]Calificación!D:D,[1]Calificación!A:A,"",0,1) | C102: =IF([1]Calificación!D91=0,"",[1]Calificación!D91) | D102: =IFERROR(VLOOKUP(C102,[1]Calificación!$D$1:$X$53,2,0),"") | G102: =IFERROR(VLOOKUP(C102,[1]Calificación!$D$1:$X$53,12,0),"") | H102: =IFERROR(IF(VLOOKUP(C102,[1]Calificación!$D$1:$X$53,13,0)=0,"n.a",VLOOKUP(C102,[1]Calificación!$D$1:$X$53,13,0)),"") | J102: =IFERROR(IF(VLOOKUP(C102,[1]Calificación!$D$1:$X$53,14,0)=0,"n.a",VLOOKUP(C102,[1]Calificación!$D$1:$X$53,14,0)),"") | K102: =IFERROR(IF(VLOOKUP(C102,[1]Calificación!$D$1:$X$53,15,0)=0,"n.a",VLOOKUP(C102,[1]Calificación!$D$1:$X$53,15,0)),"") | M102: =IFERROR(IF(VLOOKUP(C102,[1]Calificación!$D$1:$X$53,16,0)=0,"n.a",VLOOKUP(C102,[1]Calificación!$D$1:$X$53,16,0)),"") | N102: =IFERROR(IF(VLOOKUP(C102,[1]Calificación!$D$1:$X$53,17,0)=0,"n.a",VLOOKUP(C102,[1]Calificación!$D$1:$X$53,17,0)),"") | P102: =IFERROR(IF(VLOOKUP(C102,[1]Calificación!$D$1:$X$53,18,0)=0,"n.a",VLOOKUP(C102,[1]Calificación!$D$1:$X$53,18,0)),"") | Q102: =IFERROR(IF(VLOOKUP(C102,[1]Calificación!$D$1:$X$53,19,0)=0,"n.a",VLOOKUP(C102,[1]Calificación!$D$1:$X$53,19,0)),"") | S102: =IFERROR(IF(VLOOKUP(C102,[1]Calificación!$D$1:$X$53,20,0)=0,"n.a",VLOOKUP(C102,[1]Calificación!$D$1:$X$53,20,0)),"") | T102: =IFERROR(IF(VLOOKUP(C102,[1]Calificación!$D$1:$X$53,21,0)=0,"n.a",VLOOKUP(C102,[1]Calificación!$D$1:$X$53,21,0)),"")
B103: =_xlfn.XLOOKUP(C103,[1]Calificación!D:D,[1]Calificación!A:A,"",0,1) | C103: =IF([1]Calificación!D92=0,"",[1]Calificación!D92) | D103: =IFERROR(VLOOKUP(C103,[1]Calificación!$D$1:$X$53,2,0),"") | G103: =IFERROR(VLOOKUP(C103,[1]Calificación!$D$1:$X$53,12,0),"") | H103: =IFERROR(IF(VLOOKUP(C103,[1]Calificación!$D$1:$X$53,13,0)=0,"n.a",VLOOKUP(C103,[1]Calificación!$D$1:$X$53,13,0)),"") | J103: =IFERROR(IF(VLOOKUP(C103,[1]Calificación!$D$1:$X$53,14,0)=0,"n.a",VLOOKUP(C103,[1]Calificación!$D$1:$X$53,14,0)),"") | K103: =IFERROR(IF(VLOOKUP(C103,[1]Calificación!$D$1:$X$53,15,0)=0,"n.a",VLOOKUP(C103,[1]Calificación!$D$1:$X$53,15,0)),"") | M103: =IFERROR(IF(VLOOKUP(C103,[1]Calificación!$D$1:$X$53,16,0)=0,"n.a",VLOOKUP(C103,[1]Calificación!$D$1:$X$53,16,0)),"") | N103: =IFERROR(IF(VLOOKUP(C103,[1]Calificación!$D$1:$X$53,17,0)=0,"n.a",VLOOKUP(C103,[1]Calificación!$D$1:$X$53,17,0)),"") | P103: =IFERROR(IF(VLOOKUP(C103,[1]Calificación!$D$1:$X$53,18,0)=0,"n.a",VLOOKUP(C103,[1]Calificación!$D$1:$X$53,18,0)),"") | Q103: =IFERROR(IF(VLOOKUP(C103,[1]Calificación!$D$1:$X$53,19,0)=0,"n.a",VLOOKUP(C103,[1]Calificación!$D$1:$X$53,19,0)),"") | S103: =IFERROR(IF(VLOOKUP(C103,[1]Calificación!$D$1:$X$53,20,0)=0,"n.a",VLOOKUP(C103,[1]Calificación!$D$1:$X$53,20,0)),"") | T103: =IFERROR(IF(VLOOKUP(C103,[1]Calificación!$D$1:$X$53,21,0)=0,"n.a",VLOOKUP(C103,[1]Calificación!$D$1:$X$53,21,0)),"")
B104: =_xlfn.XLOOKUP(C104,[1]Calificación!D:D,[1]Calificación!A:A,"",0,1) | C104: =IF([1]Calificación!D93=0,"",[1]Calificación!D93) | D104: =IFERROR(VLOOKUP(C104,[1]Calificación!$D$1:$X$53,2,0),"") | G104: =IFERROR(VLOOKUP(C104,[1]Calificación!$D$1:$X$53,12,0),"") | H104: =IFERROR(IF(VLOOKUP(C104,[1]Calificación!$D$1:$X$53,13,0)=0,"n.a",VLOOKUP(C104,[1]Calificación!$D$1:$X$53,13,0)),"") | J104: =IFERROR(IF(VLOOKUP(C104,[1]Calificación!$D$1:$X$53,14,0)=0,"n.a",VLOOKUP(C104,[1]Calificación!$D$1:$X$53,14,0)),"") | K104: =IFERROR(IF(VLOOKUP(C104,[1]Calificación!$D$1:$X$53,15,0)=0,"n.a",VLOOKUP(C104,[1]Calificación!$D$1:$X$53,15,0)),"") | M104: =IFERROR(IF(VLOOKUP(C104,[1]Calificación!$D$1:$X$53,16,0)=0,"n.a",VLOOKUP(C104,[1]Calificación!$D$1:$X$53,16,0)),"") | N104: =IFERROR(IF(VLOOKUP(C104,[1]Calificación!$D$1:$X$53,17,0)=0,"n.a",VLOOKUP(C104,[1]Calificación!$D$1:$X$53,17,0)),"") | P104: =IFERROR(IF(VLOOKUP(C104,[1]Calificación!$D$1:$X$53,18,0)=0,"n.a",VLOOKUP(C104,[1]Calificación!$D$1:$X$53,18,0)),"") | Q104: =IFERROR(IF(VLOOKUP(C104,[1]Calificación!$D$1:$X$53,19,0)=0,"n.a",VLOOKUP(C104,[1]Calificación!$D$1:$X$53,19,0)),"") | S104: =IFERROR(IF(VLOOKUP(C104,[1]Calificación!$D$1:$X$53,20,0)=0,"n.a",VLOOKUP(C104,[1]Calificación!$D$1:$X$53,20,0)),"") | T104: =IFERROR(IF(VLOOKUP(C104,[1]Calificación!$D$1:$X$53,21,0)=0,"n.a",VLOOKUP(C104,[1]Calificación!$D$1:$X$53,21,0)),"")
B105: =_xlfn.XLOOKUP(C105,[1]Calificación!D:D,[1]Calificación!A:A,"",0,1) | C105: =IF([1]Calificación!D94=0,"",[1]Calificación!D94) | D105: =IFERROR(VLOOKUP(C105,[1]Calificación!$D$1:$X$53,2,0),"") | G105: =IFERROR(VLOOKUP(C105,[1]Calificación!$D$1:$X$53,12,0),"") | H105: =IFERROR(IF(VLOOKUP(C105,[1]Calificación!$D$1:$X$53,13,0)=0,"n.a",VLOOKUP(C105,[1]Calificación!$D$1:$X$53,13,0)),"") | J105: =IFERROR(IF(VLOOKUP(C105,[1]Calificación!$D$1:$X$53,14,0)=0,"n.a",VLOOKUP(C105,[1]Calificación!$D$1:$X$53,14,0)),"") | K105: =IFERROR(IF(VLOOKUP(C105,[1]Calificación!$D$1:$X$53,15,0)=0,"n.a",VLOOKUP(C105,[1]Calificación!$D$1:$X$53,15,0)),"") | M105: =IFERROR(IF(VLOOKUP(C105,[1]Calificación!$D$1:$X$53,16,0)=0,"n.a",VLOOKUP(C105,[1]Calificación!$D$1:$X$53,16,0)),"") | N105: =IFERROR(IF(VLOOKUP(C105,[1]Calificación!$D$1:$X$53,17,0)=0,"n.a",VLOOKUP(C105,[1]Calificación!$D$1:$X$53,17,0)),"") | P105: =IFERROR(IF(VLOOKUP(C105,[1]Calificación!$D$1:$X$53,18,0)=0,"n.a",VLOOKUP(C105,[1]Calificación!$D$1:$X$53,18,0)),"") | Q105: =IFERROR(IF(VLOOKUP(C105,[1]Calificación!$D$1:$X$53,19,0)=0,"n.a",VLOOKUP(C105,[1]Calificación!$D$1:$X$53,19,0)),"") | S105: =IFERROR(IF(VLOOKUP(C105,[1]Calificación!$D$1:$X$53,20,0)=0,"n.a",VLOOKUP(C105,[1]Calificación!$D$1:$X$53,20,0)),"") | T105: =IFERROR(IF(VLOOKUP(C105,[1]Calificación!$D$1:$X$53,21,0)=0,"n.a",VLOOKUP(C105,[1]Calificación!$D$1:$X$53,21,0)),"")
B106: =_xlfn.XLOOKUP(C106,[1]Calificación!D:D,[1]Calificación!A:A,"",0,1) | C106: =IF([1]Calificación!D95=0,"",[1]Calificación!D95) | D106: =IFERROR(VLOOKUP(C106,[1]Calificación!$D$1:$X$53,2,0),"") | G106: =IFERROR(VLOOKUP(C106,[1]Calificación!$D$1:$X$53,12,0),"") | H106: =IFERROR(IF(VLOOKUP(C106,[1]Calificación!$D$1:$X$53,13,0)=0,"n.a",VLOOKUP(C106,[1]Calificación!$D$1:$X$53,13,0)),"") | J106: =IFERROR(IF(VLOOKUP(C106,[1]Calificación!$D$1:$X$53,14,0)=0,"n.a",VLOOKUP(C106,[1]Calificación!$D$1:$X$53,14,0)),"") | K106: =IFERROR(IF(VLOOKUP(C106,[1]Calificación!$D$1:$X$53,15,0)=0,"n.a",VLOOKUP(C106,[1]Calificación!$D$1:$X$53,15,0)),"") | M106: =IFERROR(IF(VLOOKUP(C106,[1]Calificación!$D$1:$X$53,16,0)=0,"n.a",VLOOKUP(C106,[1]Calificación!$D$1:$X$53,16,0)),"") | N106: =IFERROR(IF(VLOOKUP(C106,[1]Calificación!$D$1:$X$53,17,0)=0,"n.a",VLOOKUP(C106,[1]Calificación!$D$1:$X$53,17,0)),"") | P106: =IFERROR(IF(VLOOKUP(C106,[1]Calificación!$D$1:$X$53,18,0)=0,"n.a",VLOOKUP(C106,[1]Calificación!$D$1:$X$53,18,0)),"") | Q106: =IFERROR(IF(VLOOKUP(C106,[1]Calificación!$D$1:$X$53,19,0)=0,"n.a",VLOOKUP(C106,[1]Calificación!$D$1:$X$53,19,0)),"") | S106: =IFERROR(IF(VLOOKUP(C106,[1]Calificación!$D$1:$X$53,20,0)=0,"n.a",VLOOKUP(C106,[1]Calificación!$D$1:$X$53,20,0)),"") | T106: =IFERROR(IF(VLOOKUP(C106,[1]Calificación!$D$1:$X$53,21,0)=0,"n.a",VLOOKUP(C106,[1]Calificación!$D$1:$X$53,21,0)),"")
B107: =_xlfn.XLOOKUP(C107,[1]Calificación!D:D,[1]Calificación!A:A,"",0,1) | C107: =IF([1]Calificación!D96=0,"",[1]Calificación!D96) | D107: =IFERROR(VLOOKUP(C107,[1]Calificación!$D$1:$X$53,2,0),"") | G107: =IFERROR(VLOOKUP(C107,[1]Calificación!$D$1:$X$53,12,0),"") | H107: =IFERROR(IF(VLOOKUP(C107,[1]Calificación!$D$1:$X$53,13,0)=0,"n.a",VLOOKUP(C107,[1]Calificación!$D$1:$X$53,13,0)),"") | J107: =IFERROR(IF(VLOOKUP(C107,[1]Calificación!$D$1:$X$53,14,0)=0,"n.a",VLOOKUP(C107,[1]Calificación!$D$1:$X$53,14,0)),"") | K107: =IFERROR(IF(VLOOKUP(C107,[1]Calificación!$D$1:$X$53,15,0)=0,"n.a",VLOOKUP(C107,[1]Calificación!$D$1:$X$53,15,0)),"") | M107: =IFERROR(IF(VLOOKUP(C107,[1]Calificación!$D$1:$X$53,16,0)=0,"n.a",VLOOKUP(C107,[1]Calificación!$D$1:$X$53,16,0)),"") | N107: =IFERROR(IF(VLOOKUP(C107,[1]Calificación!$D$1:$X$53,17,0)=0,"n.a",VLOOKUP(C107,[1]Calificación!$D$1:$X$53,17,0)),"") | P107: =IFERROR(IF(VLOOKUP(C107,[1]Calificación!$D$1:$X$53,18,0)=0,"n.a",VLOOKUP(C107,[1]Calificación!$D$1:$X$53,18,0)),"") | Q107: =IFERROR(IF(VLOOKUP(C107,[1]Calificación!$D$1:$X$53,19,0)=0,"n.a",VLOOKUP(C107,[1]Calificación!$D$1:$X$53,19,0)),"") | S107: =IFERROR(IF(VLOOKUP(C107,[1]Calificación!$D$1:$X$53,20,0)=0,"n.a",VLOOKUP(C107,[1]Calificación!$D$1:$X$53,20,0)),"") | T107: =IFERROR(IF(VLOOKUP(C107,[1]Calificación!$D$1:$X$53,21,0)=0,"n.a",VLOOKUP(C107,[1]Calificación!$D$1:$X$53,21,0)),"")
B108: =_xlfn.XLOOKUP(C108,[1]Calificación!D:D,[1]Calificación!A:A,"",0,1) | C108: =IF([1]Calificación!D97=0,"",[1]Calificación!D97) | D108: =IFERROR(VLOOKUP(C108,[1]Calificación!$D$1:$X$53,2,0),"") | G108: =IFERROR(VLOOKUP(C108,[1]Calificación!$D$1:$X$53,12,0),"") | H108: =IFERROR(IF(VLOOKUP(C108,[1]Calificación!$D$1:$X$53,13,0)=0,"n.a",VLOOKUP(C108,[1]Calificación!$D$1:$X$53,13,0)),"") | J108: =IFERROR(IF(VLOOKUP(C108,[1]Calificación!$D$1:$X$53,14,0)=0,"n.a",VLOOKUP(C108,[1]Calificación!$D$1:$X$53,14,0)),"") | K108: =IFERROR(IF(VLOOKUP(C108,[1]Calificación!$D$1:$X$53,15,0)=0,"n.a",VLOOKUP(C108,[1]Calificación!$D$1:$X$53,15,0)),"") | M108: =IFERROR(IF(VLOOKUP(C108,[1]Calificación!$D$1:$X$53,16,0)=0,"n.a",VLOOKUP(C108,[1]Calificación!$D$1:$X$53,16,0)),"") | N108: =IFERROR(IF(VLOOKUP(C108,[1]Calificación!$D$1:$X$53,17,0)=0,"n.a",VLOOKUP(C108,[1]Calificación!$D$1:$X$53,17,0)),"") | P108: =IFERROR(IF(VLOOKUP(C108,[1]Calificación!$D$1:$X$53,18,0)=0,"n.a",VLOOKUP(C108,[1]Calificación!$D$1:$X$53,18,0)),"") | Q108: =IFERROR(IF(VLOOKUP(C108,[1]Calificación!$D$1:$X$53,19,0)=0,"n.a",VLOOKUP(C108,[1]Calificación!$D$1:$X$53,19,0)),"") | S108: =IFERROR(IF(VLOOKUP(C108,[1]Calificación!$D$1:$X$53,20,0)=0,"n.a",VLOOKUP(C108,[1]Calificación!$D$1:$X$53,20,0)),"") | T108: =IFERROR(IF(VLOOKUP(C108,[1]Calificación!$D$1:$X$53,21,0)=0,"n.a",VLOOKUP(C108,[1]Calificación!$D$1:$X$53,21,0)),"")
B109: =_xlfn.XLOOKUP(C109,[1]Calificación!D:D,[1]Calificación!A:A,"",0,1) | C109: =IF([1]Calificación!D98=0,"",[1]Calificación!D98) | D109: =IFERROR(VLOOKUP(C109,[1]Calificación!$D$1:$X$53,2,0),"") | G109: =IFERROR(VLOOKUP(C109,[1]Calificación!$D$1:$X$53,12,0),"") | H109: =IFERROR(IF(VLOOKUP(C109,[1]Calificación!$D$1:$X$53,13,0)=0,"n.a",VLOOKUP(C109,[1]Calificación!$D$1:$X$53,13,0)),"") | J109: =IFERROR(IF(VLOOKUP(C109,[1]Calificación!$D$1:$X$53,14,0)=0,"n.a",VLOOKUP(C109,[1]Calificación!$D$1:$X$53,14,0)),"") | K109: =IFERROR(IF(VLOOKUP(C109,[1]Calificación!$D$1:$X$53,15,0)=0,"n.a",VLOOKUP(C109,[1]Calificación!$D$1:$X$53,15,0)),"") | M109: =IFERROR(IF(VLOOKUP(C109,[1]Calificación!$D$1:$X$53,16,0)=0,"n.a",VLOOKUP(C109,[1]Calificación!$D$1:$X$53,16,0)),"") | N109: =IFERROR(IF(VLOOKUP(C109,[1]Calificación!$D$1:$X$53,17,0)=0,"n.a",VLOOKUP(C109,[1]Calificación!$D$1:$X$53,17,0)),"") | P109: =IFERROR(IF(VLOOKUP(C109,[1]Calificación!$D$1:$X$53,18,0)=0,"n.a",VLOOKUP(C109,[1]Calificación!$D$1:$X$53,18,0)),"") | Q109: =IFERROR(IF(VLOOKUP(C109,[1]Calificación!$D$1:$X$53,19,0)=0,"n.a",VLOOKUP(C109,[1]Calificación!$D$1:$X$53,19,0)),"") | S109: =IFERROR(IF(VLOOKUP(C109,[1]Calificación!$D$1:$X$53,20,0)=0,"n.a",VLOOKUP(C109,[1]Calificación!$D$1:$X$53,20,0)),"") | T109: =IFERROR(IF(VLOOKUP(C109,[1]Calificación!$D$1:$X$53,21,0)=0,"n.a",VLOOKUP(C109,[1]Calificación!$D$1:$X$53,21,0)),"")
B110: =_xlfn.XLOOKUP(C110,[1]Calificación!D:D,[1]Calificación!A:A,"",0,1) | C110: =IF([1]Calificación!D99=0,"",[1]Calificación!D99) | D110: =IFERROR(VLOOKUP(C110,[1]Calificación!$D$1:$X$53,2,0),"") | G110: =IFERROR(VLOOKUP(C110,[1]Calificación!$D$1:$X$53,12,0),"") | H110: =IFERROR(IF(VLOOKUP(C110,[1]Calificación!$D$1:$X$53,13,0)=0,"n.a",VLOOKUP(C110,[1]Calificación!$D$1:$X$53,13,0)),"") | J110: =IFERROR(IF(VLOOKUP(C110,[1]Calificación!$D$1:$X$53,14,0)=0,"n.a",VLOOKUP(C110,[1]Calificación!$D$1:$X$53,14,0)),"") | K110: =IFERROR(IF(VLOOKUP(C110,[1]Calificación!$D$1:$X$53,15,0)=0,"n.a",VLOOKUP(C110,[1]Calificación!$D$1:$X$53,15,0)),"") | M110: =IFERROR(IF(VLOOKUP(C110,[1]Calificación!$D$1:$X$53,16,0)=0,"n.a",VLOOKUP(C110,[1]Calificación!$D$1:$X$53,16,0)),"") | N110: =IFERROR(IF(VLOOKUP(C110,[1]Calificación!$D$1:$X$53,17,0)=0,"n.a",VLOOKUP(C110,[1]Calificación!$D$1:$X$53,17,0)),"") | P110: =IFERROR(IF(VLOOKUP(C110,[1]Calificación!$D$1:$X$53,18,0)=0,"n.a",VLOOKUP(C110,[1]Calificación!$D$1:$X$53,18,0)),"") | Q110: =IFERROR(IF(VLOOKUP(C110,[1]Calificación!$D$1:$X$53,19,0)=0,"n.a",VLOOKUP(C110,[1]Calificación!$D$1:$X$53,19,0)),"") | S110: =IFERROR(IF(VLOOKUP(C110,[1]Calificación!$D$1:$X$53,20,0)=0,"n.a",VLOOKUP(C110,[1]Calificación!$D$1:$X$53,20,0)),"") | T110: =IFERROR(IF(VLOOKUP(C110,[1]Calificación!$D$1:$X$53,21,0)=0,"n.a",VLOOKUP(C110,[1]Calificación!$D$1:$X$53,21,0)),"")
B111: =_xlfn.XLOOKUP(C111,[1]Calificación!D:D,[1]Calificación!A:A,"",0,1) | C111: =IF([1]Calificación!D100=0,"",[1]Calificación!D100) | D111: =IFERROR(VLOOKUP(C111,[1]Calificación!$D$1:$X$53,2,0),"") | G111: =IFERROR(VLOOKUP(C111,[1]Calificación!$D$1:$X$53,12,0),"") | H111: =IFERROR(IF(VLOOKUP(C111,[1]Calificación!$D$1:$X$53,13,0)=0,"n.a",VLOOKUP(C111,[1]Calificación!$D$1:$X$53,13,0)),"") | J111: =IFERROR(IF(VLOOKUP(C111,[1]Calificación!$D$1:$X$53,14,0)=0,"n.a",VLOOKUP(C111,[1]Calificación!$D$1:$X$53,14,0)),"") | K111: =IFERROR(IF(VLOOKUP(C111,[1]Calificación!$D$1:$X$53,15,0)=0,"n.a",VLOOKUP(C111,[1]Calificación!$D$1:$X$53,15,0)),"") | M111: =IFERROR(IF(VLOOKUP(C111,[1]Calificación!$D$1:$X$53,16,0)=0,"n.a",VLOOKUP(C111,[1]Calificación!$D$1:$X$53,16,0)),"") | N111: =IFERROR(IF(VLOOKUP(C111,[1]Calificación!$D$1:$X$53,17,0)=0,"n.a",VLOOKUP(C111,[1]Calificación!$D$1:$X$53,17,0)),"") | P111: =IFERROR(IF(VLOOKUP(C111,[1]Calificación!$D$1:$X$53,18,0)=0,"n.a",VLOOKUP(C111,[1]Calificación!$D$1:$X$53,18,0)),"") | Q111: =IFERROR(IF(VLOOKUP(C111,[1]Calificación!$D$1:$X$53,19,0)=0,"n.a",VLOOKUP(C111,[1]Calificación!$D$1:$X$53,19,0)),"") | S111: =IFERROR(IF(VLOOKUP(C111,[1]Calificación!$D$1:$X$53,20,0)=0,"n.a",VLOOKUP(C111,[1]Calificación!$D$1:$X$53,20,0)),"") | T111: =IFERROR(IF(VLOOKUP(C111,[1]Calificación!$D$1:$X$53,21,0)=0,"n.a",VLOOKUP(C111,[1]Calificación!$D$1:$X$53,21,0)),"")
B112: =_xlfn.XLOOKUP(C112,[1]Calificación!D:D,[1]Calificación!A:A,"",0,1) | C112: =IF([1]Calificación!D101=0,"",[1]Calificación!D101) | D112: =IFERROR(VLOOKUP(C112,[1]Calificación!$D$1:$X$53,2,0),"") | G112: =IFERROR(VLOOKUP(C112,[1]Calificación!$D$1:$X$53,12,0),"") | H112: =IFERROR(IF(VLOOKUP(C112,[1]Calificación!$D$1:$X$53,13,0)=0,"n.a",VLOOKUP(C112,[1]Calificación!$D$1:$X$53,13,0)),"") | J112: =IFERROR(IF(VLOOKUP(C112,[1]Calificación!$D$1:$X$53,14,0)=0,"n.a",VLOOKUP(C112,[1]Calificación!$D$1:$X$53,14,0)),"") | K112: =IFERROR(IF(VLOOKUP(C112,[1]Calificación!$D$1:$X$53,15,0)=0,"n.a",VLOOKUP(C112,[1]Calificación!$D$1:$X$53,15,0)),"") | M112: =IFERROR(IF(VLOOKUP(C112,[1]Calificación!$D$1:$X$53,16,0)=0,"n.a",VLOOKUP(C112,[1]Calificación!$D$1:$X$53,16,0)),"") | N112: =IFERROR(IF(VLOOKUP(C112,[1]Calificación!$D$1:$X$53,17,0)=0,"n.a",VLOOKUP(C112,[1]Calificación!$D$1:$X$53,17,0)),"") | P112: =IFERROR(IF(VLOOKUP(C112,[1]Calificación!$D$1:$X$53,18,0)=0,"n.a",VLOOKUP(C112,[1]Calificación!$D$1:$X$53,18,0)),"") | Q112: =IFERROR(IF(VLOOKUP(C112,[1]Calificación!$D$1:$X$53,19,0)=0,"n.a",VLOOKUP(C112,[1]Calificación!$D$1:$X$53,19,0)),"") | S112: =IFERROR(IF(VLOOKUP(C112,[1]Calificación!$D$1:$X$53,20,0)=0,"n.a",VLOOKUP(C112,[1]Calificación!$D$1:$X$53,20,0)),"") | T112: =IFERROR(IF(VLOOKUP(C112,[1]Calificación!$D$1:$X$53,21,0)=0,"n.a",VLOOKUP(C112,[1]Calificación!$D$1:$X$53,21,0)),"")
B113: =_xlfn.XLOOKUP(C113,[1]Calificación!D:D,[1]Calificación!A:A,"",0,1) | C113: =IF([1]Calificación!D102=0,"",[1]Calificación!D102) | D113: =IFERROR(VLOOKUP(C113,[1]Calificación!$D$1:$X$53,2,0),"") | G113: =IFERROR(VLOOKUP(C113,[1]Calificación!$D$1:$X$53,12,0),"") | H113: =IFERROR(IF(VLOOKUP(C113,[1]Calificación!$D$1:$X$53,13,0)=0,"n.a",VLOOKUP(C113,[1]Calificación!$D$1:$X$53,13,0)),"") | J113: =IFERROR(IF(VLOOKUP(C113,[1]Calificación!$D$1:$X$53,14,0)=0,"n.a",VLOOKUP(C113,[1]Calificación!$D$1:$X$53,14,0)),"") | K113: =IFERROR(IF(VLOOKUP(C113,[1]Calificación!$D$1:$X$53,15,0)=0,"n.a",VLOOKUP(C113,[1]Calificación!$D$1:$X$53,15,0)),"") | M113: =IFERROR(IF(VLOOKUP(C113,[1]Calificación!$D$1:$X$53,16,0)=0,"n.a",VLOOKUP(C113,[1]Calificación!$D$1:$X$53,16,0)),"") | N113: =IFERROR(IF(VLOOKUP(C113,[1]Calificación!$D$1:$X$53,17,0)=0,"n.a",VLOOKUP(C113,[1]Calificación!$D$1:$X$53,17,0)),"") | P113: =IFERROR(IF(VLOOKUP(C113,[1]Calificación!$D$1:$X$53,18,0)=0,"n.a",VLOOKUP(C113,[1]Calificación!$D$1:$X$53,18,0)),"") | Q113: =IFERROR(IF(VLOOKUP(C113,[1]Calificación!$D$1:$X$53,19,0)=0,"n.a",VLOOKUP(C113,[1]Calificación!$D$1:$X$53,19,0)),"") | S113: =IFERROR(IF(VLOOKUP(C113,[1]Calificación!$D$1:$X$53,20,0)=0,"n.a",VLOOKUP(C113,[1]Calificación!$D$1:$X$53,20,0)),"") | T113: =IFERROR(IF(VLOOKUP(C113,[1]Calificación!$D$1:$X$53,21,0)=0,"n.a",VLOOKUP(C113,[1]Calificación!$D$1:$X$53,21,0)),"")

Sheet Portadilla II
B2: II. Estadísticas de la Banca Múltiple
B3: El objetivo de este apartado es proporcionar al público indicadores estadísticos que reflejen adecuadamente la evolución de la condición financiera de la Banca Múltiple, por lo que en esta sección, se presenta la información reportada por las 52 instituciones de banca múltiple en operación correspondiente a agosto de 2025, consolidada con la de sus SOFOMER en el caso de las siguientes instituciones: Banamex con Tarjetas Banamex; Santander con Santander Inclusión Financiera; CI Banco con Finanmadrid México; Banco del Bajío con Financiera Bajío; Banregio con Start Banregio; Inbursa con STM Financial, SOFOM Inbursa y CETELEM Inbursa; Afirme con Arrendadora Afirme; Banco Base con Arrendadora Base, Invex con Invex Consumo; Bancrea con Arrendadora Bancrea, así como Ve por Más con Arrendadora Ve por Más.
B5: Notas:
B7: 1/ Para la cartera total se considera la información de cartera de los bancos junto con la cartera de sus respectivas Sociedades Financieras de Objeto Múltiple Reguladas a las que consolidan. Hasta diciembre 2021: Cartera total = Cartera vigente + cartera vencida. A partir de enero 2022: Cartera total = Cartera de crédito con riesgo de crédito en etapa 1 + 2 + 3 + cartera de crédito valuada a valor razonable.
B9: 2/ Respecto al resultado neto se muestran saldos acumulados al cierre de mes.
B10: 3/ ROA = Resultado neto (flujo 12 meses) / Activos totales, promedio 12 meses.
B11: 4/ ROE = Resultado neto (flujo 12 meses) / Capital contable, promedio 12 meses.
B12: 5/ Hasta diciembre 2021: IMOR = Índice de Morosidad = cartera vencida / (Cartera vigente + cartera vencida). A partir de enero 2022: IMOR = Índice de Morosidad = cartera de crédito con riesgo de crédito en etapa 3 / (Cartera de crédito con riesgo de crédito en etapa 1 + 2 + 3).
B13: 6/ Hasta diciembre 2021: ICOR = Índice de cobertura= Estimaciones preventivas para riesgos crediticios del balance general / cartera de crédito vencida. A partir de enero 2022: ICOR = Índice de cobertura= Estimaciones preventivas para riesgos crediticios del estado de situación financiera / cartera de crédito con riesgo de crédito en etapa 3.
B14: 7/ Hasta diciembre 2021: Estimaciones preventivas para riesgo crediticio del balance general / (Cartera vigente + cartera vencida). A partir de enero 2022: Estimaciones preventivas para riesgo crediticio del estado de situación financiera / (Cartera de crédito con riesgo de crédito en etapa 1 + 2 + 3).
B16: */ En todos los casos se presentan las instituciones en orden descendente por tamaño de activo total en el mes de análisis más reciente.
B18: El símbolo ( - ) indica que la cifra es cero. Las cifras en cero indican una cantidad cercana a cero.
... B21: n.d.: No disponible

Sheet Pm2
B3: Principales rubros del estado de situación financiera y estado de resultado integral
B4: Millones de pesos y porcentajes
C5: Activo total | I5: Inversiones en instrumentos financieros | O5: Cartera total1/ | U5: Captación total | AA5: Capital contable | AG5: Resultado neto 2/
C6: 45505 | E6: 45839 | G6: 45870 | I6: =+$C$6 -> 45505 | K6: =+$E$6 -> 45839 | M6: =+$G$6 -> 45870 | O6: =+$C$6 -> 45505 | Q6: =+$E$6 -> 45839 | S6: =+$G$6 -> 45870 | U6: =+$C$6 -> 45505 | W6: =+$E$6 -> 45839 | Y6: =+$G$6 -> 45870 | AA6: =+$C$6 -> 45505 | AC6: =+$E$6 -> 45839 | AE6: =+$G$6 -> 45870 | AG6: =+$C$6 -> 45505 | AI6: =+$E$6 -> 45839 | AK6: =+$G$6 -> 45870
B7: Sistema */ | C7: 14453699 | D7: 100 | E7: 15389124 | F7: 100 | G7: 15431060 | H7: 100 | I7: 3799962.4 | J7: 100 | K7: 4053496.7 | L7: 100 | M7: 4023367.5 | N7: 100 | O7: 7351193.1 | P7: 100 | Q7: 7839661.6 | R7: 100 | S7: 7858406 | T7: 100 | U7: 8556208 | V7: 100 | W7: 9174885.7 | X7: 100 | Y7: 9233014.2 | Z7: 100 | AA7: 1620356.6 | AB7: 100 | AC7: 1775851.1 | AD7: 100 | AE7: 1804585.8 | AF7: 100 | AG7: 195972.35 | AH7: 100 | AI7: 178430.47 | AJ7: 100 | AK7: 203173.6 | AL7: 100
B8: BBVA México | C8: 3197252.1 | D8: 22.120649 | E8: 3340530.4 | F8: 21.707086 | G8: 3334146.9 | H8: 21.606726 | I8: 669721.11 | J8: 17.624414 | K8: 598949.41 | L8: 14.776117 | M8: 563805.88 | N8: 14.013283 | O8: 1848363 | P8: 25.143714 | Q8: 2015513.2 | R8: 25.709186 | S8: 2012068.9 | T8: 25.604033 | U8: 1854174.8 | V8: 21.67052 | W8: 2036733.9 | X8: 22.199012 | Y8: 2053500.3 | Z8: 22.240844 | AA8: 359852.84 | AB8: 22.208249 | AC8: 390680.59 | AD8: 21.999625 | AE8: 401144.42 | AF8: 22.229169 | AG8: 61691.6 | AH8: 31.479747 | AI8: 57711.877 | AJ8: 32.344182 | AK8: 66280.766 | AL8: 32.622726
B9: Santander | C9: 1910817.7 | D9: 13.220267 | E9: 1974060 | F9: 12.827631 | G9: 1991916.7 | H9: 12.908489 | I9: 593748.53 | J9: 15.625116 | K9: 593626.65 | L9: 14.644804 | M9: 599303.74 | N9: 14.895575 | O9: 897751.35 | P9: 12.212322 | Q9: 934236.43 | R9: 11.916795 | S9: 929316.63 | T9: 11.825765 | U9: 1042644.3 | V9: 12.185822 | W9: 1098918.5 | X9: 11.977463 | Y9: 1104934 | Z9: 11.967208 | AA9: 165286.29 | AB9: 10.200611 | AC9: 161669.97 | AD9: 9.103802 | AE9: 164899.95 | AF9: 9.1378281 | AG9: 19919.508 | AH9: 10.164448 | AI9: 18535.116 | AJ9: 10.387865 | AK9: 21432.466 | AL9: 10.548844
B10: Banorte | C10: 1779664.9 | D10: 12.312868 | E10: 1887469.4 | F10: 12.264957 | G10: 1862912 | H10: 12.072482 | I10: 406145.19 | J10: 10.688137 | K10: 451283.27 | L10: 11.133184 | M10: 443714.17 | N10: 11.028428 | O10: 1077778.1 | P10: 14.661268 | Q10: 1148959.6 | R10: 14.655729 | S10: 1158655.5 | T10: 14.744154 | U10: 1142322.8 | V10: 13.350807 | W10: 1186183.1 | X10: 12.928587 | Y10: 1193359.6 | Z10: 12.924919 | AA10: 152101.55 | AB10: 9.386918 | AC10: 166405.23 | AD10: 9.3704493 | AE10: 170852.09 | AF10: 9.4676621 | AG10: 30488.225 | AH10: 15.557412 | AI10: 27354.42 | AJ10: 15.330577 | AK10: 31389.194 | AL10: 15.449445
B11: Banamex | C11: 1557957.8 | D11: 10.778955 | E11: 1106121.1 | F11: 7.1876805 | G11: 1110881.5 | H11: 7.1989971 | I11: 579217.32 | J11: 15.242712 | K11: 416428.74 | L11: 10.273321 | M11: 402823.79 | N11: 10.012105 | O11: 615260.37 | P11: 8.3695307 | Q11: 486300.07 | R11: 6.2030748 | S11: 492087.34 | T11: 6.2619231 | U11: 975268.79 | V11: 11.398376 | W11: 763127.06 | X11: 8.3175647 | Y11: 773161.3 | Z11: 8.3738775 | AA11: 229099.8 | AB11: 14.13885 | AC11: 177913.35 | AD11: 10.018483 | AE11: 179568.57 | AF11: 9.9506808 | AG11: 16168.762 | AH11: 8.2505325 | AI11: 8553.0559 | AJ11: 4.7934951 | AK11: 9664.7347 | AL11: 4.7568852
B12: HSBC | C12: 892827.59 | D12: 6.1771563 | E12: 907745.99 | F12: 5.8986202 | G12: 890120.35 | H12: 5.7683682 | I12: 177627.01 | J12: 4.6744413 | K12: 210476.27 | L12: 5.1924617 | M12: 218382.91 | N12: 5.427864 | O12: 497798.4 | P12: 6.7716681 | Q12: 493741.75 | R12: 6.2979982 | S12: 490989.81 | T12: 6.2479568 | U12: 607280.22 | V12: 7.0975392 | W12: 574253.19 | X12: 6.2589683 | Y12: 560878.44 | Z12: 6.0747057 | AA12: 82274.003 | AB12: 5.0775243 | AC12: 86701.786 | AD12: 4.8822665 | AE12: 87796.547 | AF12: 4.865191 | AG12: 5963.8352 | AH12: 3.0432024 | AI12: 5108.3384 | AJ12: 2.8629294 | AK12: 5896.0556 | AL12: 2.9019792
B13: Scotiabank | C13: 844413.08 | D13: 5.8421935 | E13: 861735.43 | F13: 5.5996392 | G13: 871850.28 | H13: 5.6499702 | I13: 176691.74 | J13: 4.6498287 | K13: 166595.17 | L13: 4.1099125 | M13: 171111.93 | N13: 4.2529531 | O13: 526787.83 | P13: 7.1660181 | Q13: 527986.99 | R13: 6.7348186 | S13: 532170.63 | T13: 6.771992 | U13: 573306.69 | V13: 6.7004763 | W13: 589058.65 | X13: 6.4203378 | Y13: 591248.14 | Z13: 6.4036307 | AA13: 85858.881 | AB13: 5.2987644 | AC13: 91615.061 | AD13: 5.1589381 | AE13: 92317.678 | AF13: 5.1157267 | AG13: 7175.9957 | AH13: 3.6617389 | AI13: 5781.6631 | AJ13: 3.2402891 | AK13: 6651.1116 | AL13: 3.2736102
B14: Inbursa | C14: 633983.01 | D14: 4.3863028 | E14: 698989.33 | F14: 4.5420995 | G14: 704687.72 | H14: 4.5666839 | I14: 67406.516 | J14: 1.7738733 | K14: 70030.352 | L14: 1.7276529 | M14: 73588.344 | N14: 1.8290237 | O14: 444836.88 | P14: 6.0512202 | Q14: 461921.58 | R14: 5.8921112 | S14: 466601.03 | T14: 5.937604 | U14: 418068.73 | V14: 4.886145 | W14: 465217.13 | X14: 5.0705496 | Y14: 466616.41 | Z14: 5.053782 | AA14: 173603.2 | AB14: 10.713888 | AC14: 200527.29 | AD14: 11.291897 | AE14: 201509.51 | AF14: 11.166524 | AG14: 15998.562 | AH14: 8.1636832 | AI14: 13661.102 | AJ14: 7.6562607 | AK14: 15208.85 | AL14: 7.4856431
B15: Citi México | C15: 2041.4179 | D15: 0.014123843 | E15: 577231.71 | F15: 3.7509068 | G15: 583611.65 | H15: 3.7820581 | I15: 0.00101047 | J15: 2.6591579e-08 | K15: 235392.56 | L15: 5.8071482 | M15: 251623.63 | N15: 6.2540553 | O15: 0 | P15: 0 | Q15: 167718.59 | R15: 2.1393601 | S15: 162838.46 | T15: 2.0721564 | U15: 0.0010006 | V15: 1.1694433e-08 | W15: 339318.51 | X15: 3.6983405 | Y15: 334183.09 | Z15: 3.6194365 | AA15: 1483.9522 | AB15: 0.091581826 | AC15: 75077.878 | AD15: 4.2277123 | AE15: 76590.889 | AF15: 4.2442365 | AG15: 9.0233955 | AH15: 0.0046044228 | AI15: 6447.7772 | AJ15: 3.6136077 | AK15: 7578.955 | AL15: 3.7302854
B16: Banco del Bajío | C16: 345011.85 | D16: 2.3870142 | E16: 374884.01 | F16: 2.4360321 | G16: 382977.7 | H16: 2.4818626 | I16: 23829.615 | J16: 0.62710133 | K16: 28262.579 | L16: 0.69723947 | M16: 29641.297 | N16: 0.73672855 | O16: 250049.72 | P16: 3.4014848 | Q16: 264080.65 | R16: 3.368521 | S16: 266968.83 | T16: 3.397239 | U16: 283896.7 | V16: 3.31802 | W16: 310533.69 | X16: 3.3846056 | Y16: 316482.61 | Z16: 3.427728 | AA16: 42258.375 | AB16: 2.6079675 | AC16: 45523.253 | AD16: 2.5634611 | AE16: 46337.389 | AF16: 2.5677576 | AG16: 7348.528 | AH16: 3.749778 | AI16: 5367.0088 | AJ16: 3.0078992 | AK16: 6181.8116 | AL16: 3.0426255
B17: Banco Azteca | C17: 315426.51 | D17: 2.1823237 | E17: 358130.15 | F17: 2.3271639 | G17: 360844.95 | H17: 2.3384327 | I17: 80618.311 | J17: 2.1215555 | K17: 107881.59 | L17: 2.661445 | M17: 106765.34 | N17: 2.6536313 | O17: 182604.06 | P17: 2.4840057 | Q17: 201079.6 | R17: 2.5649015 | S17: 204657.34 | T17: 2.6043111 | U17: 223119.72 | V17: 2.607694 | W17: 242117.71 | X17: 2.638918 | Y17: 247637.47 | Z17: 2.682087 | AA17: 36912.903 | AB17: 2.2780728 | AC17: 44506.63 | AD17: 2.506214 | AE17: 44985.17 | AF17: 2.4928252 | AG17: 3439.6783 | AH17: 1.7551855 | AI17: 3379.8051 | AJ17: 1.8941861 | AK17: 3858.3457 | AL17: 1.8990389
B18: Afirme | C18: 306533.08 | D18: 2.1207933 | E18: 311426.66 | F18: 2.0236802 | G18: 314172.38 | H18: 2.0359741 | I18: 177564.6 | J18: 4.6727989 | K18: 177438.47 | L18: 4.3774172 | M18: 179170.06 | N18: 4.4532362 | O18: 64514.881 | P18: 0.87761102 | Q18: 68150.646 | R18: 0.86930597 | S18: 68901.897 | T18: 0.87679228 | U18: 92792.455 | V18: 1.0845044 | W18: 84558.258 | X18: 0.92162738 | Y18: 87043.479 | Z18: 0.94274175 | AA18: 8493.1311 | AB18: 0.52415196 | AC18: 9157.2074 | AD18: 0.51565174 | AE18: 9236.0385 | AF18: 0.51180933 | AG18: 358.79395 | AH18: 0.18308397 | AI18: 540.2653 | AJ18: 0.30278758 | AK18: 650.37462 | AL18: 0.32010785
... B59: Forjadores | C59: 843.66971 | D59: 0.0058370504 | E59: 913.07317 | F59: 0.0059332368 | G59: 928.82824 | H59: 0.0060192122 | I59: 0 | J59: 0 | K59: 0 | L59: 0 | M59: 0 | N59: 0 | O59: 500.24758 | P59: 0.0068049849 | Q59: 381.86235 | R59: 0.0048709034 | S59: 404.2503 | T59: 0.0051441769 | U59: 190.86092 | V59: 0.0022306718 | W59: 247.02857 | X59: 0.002692443 | Y59: 251.81786 | Z59: 0.0027273635 | AA59: 592.32135 | AB59: 0.036554999 | AC59: 618.63044 | AD59: 0.034835715 | AE59: 629.25154 | AF59: 0.034869583 | AG59: 2.386828 | AH59: 0.0012179412 | AI59: -22.003246 | AJ59: -0.012331552 | AK59: -28.382147 | AL59: -0.013969407

Sheet Indicadores
B2: Indicadores financieros
B3: Porcentajes | O3: 1.5853443
C5: ROA (Flujo 12 meses) 3/ | F5: ROE (Flujo 12 meses) 4/
C6: 45505 | D6: 45839 | E6: 45870 | F6: =+C6 -> 45505 | G6: =+D6 -> 45839 | H6: =+E6 -> 45870
B7: Sistema */ | C7: 2.0842601 | D7: 1.9686615 | E7: 1.9621093 | F7: 18.567215 | G7: 17.511634 | H7: 17.390149
B8: BBVA México | C8: 2.9999937 | D8: 2.9236001 | E8: 2.9566591 | F8: 26.412335 | G8: 25.7504 | H8: 25.893534
B9: Santander | C9: 1.5439158 | D9: 1.5078758 | E9: 1.5219715 | F9: 17.579834 | G9: 18.619496 | H9: 18.861805
B10: Banorte | C10: 2.5467199 | D10: 2.4773689 | E10: 2.4700136 | F10: 29.381563 | G10: 29.008945 | H10: 28.748222
B11: Banamex | C11: 1.5914304 | D11: 1.3808035 | E11: 1.3444569 | F11: 11.021205 | G11: 8.8335011 | H11: 8.5236798
B12: HSBC | C12: 1.057819 | D12: 0.70730798 | E12: 0.74108866 | F12: 11.116019 | G12: 7.7701024 | H12: 8.0945442
B13: Scotiabank | C13: 1.3050293 | D13: 1.1895722 | E13: 1.1707526 | F13: 13.5182 | G13: 11.752307 | H13: 11.527083
B14: Inbursa | C14: 4.1412355 | D14: 3.6215481 | E14: 3.5410859 | F14: 15.412832 | G14: 12.961588 | H14: 12.628435
B15: Citi México | C15: 3.3111676 | D15: 1.2665408 | E15: 1.3806368 | F15: 3.7313789 | G15: 10.327018 | H15: 11.192472
B16: Banco del Bajío | C16: 3.2649173 | D16: 2.6363784 | E16: 2.604197 | F16: 26.905679 | G16: 21.281448 | H16: 21.045841
B17: Banco Azteca | C17: 1.3773551 | D17: 1.7763661 | E17: 1.7760803 | F17: 11.520614 | G17: 14.45623 | H17: 14.381277
B18: Afirme | C18: 0.14805289 | D18: 0.24656215 | E18: 0.26444664 | F18: 5.0737462 | G18: 8.4441541 | H18: 9.012611
... B46: Banco Covalto | C46: 0.089192074 | D46: 1.518938 | E46: 1.5704968 | F46: 0.65705523 | G46: 12.329478 | H46: 12.76194
B47: Openbank | C47: n.a. | D47: -26.245312 | E47: -24.527727 | F47: n.a. | G47: -35.059007 | H47: -35.666321
B48: Volkswagen Bank | C48: 6.229125 | D48: 5.9361469 | E48: 6.0615049 | F48: 8.950684 | G48: 12.266385 | H48: 12.705889
B49: Bank of China | C49: 2.210429 | D49: 1.7082272 | E49: 1.9968873 | F49: 11.575147 | G49: 7.884571 | H49: 8.741238
B50: Shinhan | C50: 2.4433133 | D50: 1.7688039 | E50: 1.817915 | F50: 7.4935447 | G50: 6.1589319 | H50: 6.4123743
B51: Banco Ualá | C51: -25.945126 | D51: -18.776095 | E51: -18.580999 | F51: -140.85025 | G51: -154.2955 | H51: -149.41837
B52: Banco S3 | C52: 5.8032152 | D52: 5.5992688 | E52: 5.4365239 | F52: 13.433112 | G52: 13.23618 | H52: 13.00302
B53: KEB Hana México | C53: 0.95587014 | D53: 0.80838528 | E53: 0.76336247 | F53: 2.7798711 | G53: 2.6714134 | H53: 2.5198903
B54: Banco Bineo | C54: -28.123312 | D54: -30.346281 | E54: -30.148729 | F54: -30.750235 | G54: -32.608705 | H54: -32.213142
B55: Dondé Banco | C55: -10.778621 | D55: -5.0866478 | E55: -4.64868 | F55: -20.404659 | G55: -22.529182 | H55: -21.648423
B56: Credit Suisse | C56: -10.012602 | D56: -4.8495628 | E56: -5.3130418 | F56: -15.269295 | G56: -5.2370058 | H56: -5.6906418
B57: Hey Banco | C57: n.a. | D57: 5.6622236 | E57: 5.2069735 | F57: n.a. | G57: 5.6890569 | H57: 5.2308925
B58: Pagatodo | C58: -12.618275 | D58: -21.537666 | E58: -19.390734 | F58: -17.28854 | G58: -24.703061 | H58: -26.405367
B59: Forjadores | C59: 0.94138292 | D59: -1.8791918 | E59: -2.8065719 | F59: 1.346443 | G59: -2.7057418 | H59: -4.0533763

Sheet CCT
B2: Cartera de crédito total
B3: Millones de pesos y porcentajes
C5: Cartera total (MDP) 1/ | F5: IMOR (%) 5/ | I5: ICOR (%) 6/ | L5: Pérdida esperada (%) 7/
C6: 45505 | D6: 45839 | E6: 45870 | F6: =C6 -> 45505 | G6: =D6 -> 45839 | H6: =E6 -> 45870 | I6: =C6 -> 45505 | J6: =D6 -> 45839 | K6: =E6 -> 45870 | L6: =C6 -> 45505 | M6: =D6 -> 45839 | N6: =E6 -> 45870
B7: Sistema */ | C7: 7351193.1 | D7: 7839661.6 | E7: 7858406 | F7: 2.0339519 | G7: 2.1254588 | H7: 2.1597894 | I7: 156.07681 | J7: 151.25758 | K7: 150.15523 | L7: 3.1745273 | M7: 3.2149175 | N7: 3.2430367
B8: BBVA México | C8: 1848363 | D8: 2015513.2 | E8: 2012068.9 | F8: 1.677326 | G8: 1.6346425 | H8: 1.6507735 | I8: 192.18911 | J8: 189.1028 | K8: 189.94649 | L8: 3.223638 | M8: 3.0911547 | N8: 3.1355863
B9: Santander | C9: 897751.35 | D9: 934236.43 | E9: 929316.63 | F9: 2.230355 | G9: 2.3224121 | H9: 2.2979288 | I9: 136.39113 | J9: 134.65926 | K9: 135.87507 | L9: 3.0420065 | M9: 3.1273428 | N9: 3.1223123
B10: Banorte | C10: 1077778.1 | D10: 1148959.6 | E10: 1158655.5 | F10: 0.95385101 | G10: 1.1035814 | H10: 1.0782108 | I10: 171.96559 | J10: 152.29449 | K10: 156.92802 | L10: 1.6402955 | M10: 1.6806937 | N10: 1.6920148
B11: Banamex | C11: 615260.37 | D11: 486300.07 | E11: 492087.34 | F11: 2.1266056 | G11: 2.8293089 | H11: 2.8062853 | I11: 202.67029 | J11: 189.17816 | K11: 190.14216 | L11: 4.3099978 | M11: 5.3524345 | N11: 5.3359315
B12: HSBC | C12: 497798.4 | D12: 493741.75 | E12: 490989.81 | F12: 2.2185892 | G12: 2.7387882 | H12: 2.9594283 | I12: 152.51038 | J12: 139.95075 | K12: 129.70583 | L12: 3.3835789 | M12: 3.8329547 | N12: 3.8385512
B13: Scotiabank | C13: 526787.83 | D13: 527986.99 | E13: 532170.63 | F13: 3.7765415 | G13: 4.0517553 | H13: 4.042423 | I13: 73.903024 | J13: 68.652291 | K13: 69.024933 | L13: 2.7909784 | M13: 2.7816228 | N13: 2.7902798
B14: Inbursa | C14: 444836.88 | D14: 461921.58 | E14: 466601.03 | F14: 1.614095 | G14: 1.4786003 | H14: 1.5063476 | I14: 136.03706 | J14: 149.75024 | K14: 149.20137 | L14: 2.1957673 | M14: 2.2142075 | N14: 2.2474914
B15: Citi México | C15: 0 | D15: 167718.59 | E15: 162838.46 | F15: - | G15: 1.350366 | H15: 1.3908188 | I15: - | J15: 189.67717 | K15: 188.59079 | L15: - | M15: 2.561336 | N15: 2.6229561
B16: Banco del Bajío | C16: 250049.72 | D16: 264080.65 | E16: 266968.83 | F16: 1.499852 | G16: 1.8704086 | H16: 1.845093 | I16: 147.73168 | J16: 121.57592 | K16: 119.95995 | L16: 2.2157566 | M16: 2.2739665 | N16: 2.2133728
B17: Banco Azteca | C17: 182604.06 | D17: 201079.6 | E17: 204657.34 | F17: 3.2642665 | G17: 4.2294726 | H17: 4.6627621 | I17: 353.7681 | J17: 274.04411 | K17: 255.08493 | L17: 11.547933 | M17: 11.590621 | N17: 11.894004
B18: Afirme | C18: 64514.881 | D18: 68150.646 | E18: 68901.897 | F18: 5.5169331 | G18: 3.9543661 | H18: 3.9420726 | I18: 67.950399 | J18: 86.624197 | K18: 84.882725 | L18: 3.7487781 | M18: 3.4254379 | N18: 3.3461386
B19: Monex | C19: 45180.419 | D19: 55679.67 | E19: 55196.869 | F19: 1.3916776 | G19: 1.4838624 | H19: 1.4745026 | I19: 128.60088 | J19: 128.40821 | K19: 128.6824 | L19: 1.7897097 | M19: 1.9054012 | N19: 1.8974253
B20: Banregio | C20: 169812.35 | D20: 184818.19 | E20: 186462.78 | F20: 1.3026005 | G20: 1.4945681 | H20: 1.5762546 | I20: 162.54127 | J20: 143.5183 | K20: 134.43745 | L20: 2.1172634 | M20: 2.1449786 | N20: 2.1190765
B21: J.P. Morgan | C21: 19577.149 | D21: 25545.122 | E21: 24842.326 | F21: 0 | G21: 0 | H21: 0 | I21: - | J21: - | K21: - | L21: 0.728024 | M21: 0.61994842 | N21: 0.64205721
B22: Bank of America | C22: 35275.451 | D22: 41861.69 | E22: 43913.817 | F22: 0 | G22: 0 | H22: 0 | I22: - | J22: - | K22: - | L22: 0.82833874 | M22: 1.0426333 | N22: 0.98873116
B23: Invex | C23: 41051.764 | D23: 49386.651 | E23: 49339.463 | F23: 2.1943845 | G23: 2.1702776 | H23: 2.35529 | I23: 232.16863 | J23: 257.61508 | K23: 241.82046 | L23: 5.0946724 | M23: 5.5909625 | N23: 5.6955732
B24: BanCoppel | C24: 62557.798 | D24: 69846.329 | E24: 79132.111 | F24: 8.1417468 | G24: 5.881127 | H24: 5.4084956 | I24: 134.68384 | J24: 149.55988 | K24: 150.1693 | L24: 10.965618 | M24: 8.7958066 | N24: 8.1218998
B25: Multiva | C25: 70432.555 | D25: 80241.469 | E25: 81408.031 | F25: 3.3603167 | G25: 2.6201476 | H25: 2.568871 | I25: 96.547063 | J25: 112.41907 | K25: 114.35006 | L25: 3.244287 | M25: 2.9455456 | N25: 2.9375055
B26: Banca Mifel | C26: 77476.547 | D26: 83334.566 | E26: 84449.258 | F26: 2.4114249 | G26: 2.6526099 | H26: 2.8478877 | I26: 89.129097 | J26: 86.550689 | K26: 79.624047 | L26: 2.1492813 | M26: 2.2958521 | N26: 2.2676034
B27: Barclays | C27: 0 | D27: 0 | E27: 0 | F27: - | G27: - | H27: - | I27: - | J27: - | K27: - | L27: - | M27: - | N27: -
B28: Banco Base | C28: 11447.083 | D28: 10522.093 | E28: 10437.397 | F28: 2.259522 | G28: 3.1417019 | H28: 3.3503311 | I28: 134.46992 | J28: 104.19206 | K28: 101.09046 | L28: 3.0383774 | M28: 3.2734038 | N28: 3.386865
B29: Sabadell | C29: 95773.992 | D29: 100065.78 | E29: 100285.57 | F29: 1.8440014 | G29: 2.2519243 | H29: 2.0369979 | I29: 76.087214 | J29: 66.052912 | K29: 68.998084 | L29: 1.4030493 | M29: 1.4874616 | N29: 1.4054895
B30: Ve por Más | C30: 57537.13 | D30: 60019.8 | E30: 59826.379 | F30: 3.2737893 | G30: 2.8738416 | H30: 2.8954991 | I30: 92.663317 | J30: 107.71404 | K30: 111.15768 | L30: 3.0336018 | M30: 3.095531 | N30: 3.2185697
B31: Actinver | C31: 26881.578 | D31: 28375.644 | E31: 29803.299 | F31: 3.390111 | G31: 3.3318947 | H31: 3.1306968 | I31: 113.89842 | J31: 107.55651 | K31: 111.1205 | L31: 3.8612828 | M31: 3.5836697 | N31: 3.4788458
B32: Bansí | C32: 22066.521 | D32: 29730.699 | E32: 30139.47 | F32: 4.7666328 | G32: 3.6975682 | H32: 3.5418365 | I32: 148.19033 | J32: 166.68465 | K32: 173.29319 | L32: 7.0636888 | M32: 6.1632786 | N32: 6.1377615
B33: CIBanco | C33: 13393.746 | D33: 16743.919 | E33: 6940.8554 | F33: 3.4924121 | G33: 3.3272579 | H33: 8.1069954 | I33: 104.45486 | J33: 102.02887 | K33: 64.710529 | L33: 3.6479943 | M33: 3.3947636 | N33: 5.2460796
B34: Compartamos | C34: 48082.232 | D34: 58883.972 | E34: 59110.491 | F34: 3.0169088 | G34: 3.1850154 | H34: 3.2626805 | I34: 245.44252 | J34: 234.46744 | K34: 236.87828 | L34: 7.404777 | M34: 7.467824 | N34: 7.7285813
B35: BIAfirme | C35: 273.0448 | D35: 244.16608 | E35: 244.07477 | F35: 0 | G35: 0 | H35: 0 | I35: - | J35: - | K35: - | L35: 0.52293068 | M35: 0.44172885 | N35: 0.56619249
B36: Bancrea | C36: 35826.643 | D36: 43235.349 | E36: 43738.995 | F36: 0.86946747 | G36: 1.035172 | H36: 2.1351984 | I36: 118.58853 | J36: 149.35787 | K36: 72.374258 | L36: 1.0310887 | M36: 1.5461108 | N36: 1.545334
B37: MUFG Bank | C37: 14809.127 | D37: 6866.0949 | E37: 7477.1335 | F37: 0 | G37: 0 | H37: 0 | I37: - | J37: - | K37: - | L37: 0.52512656 | M37: 0.78265206 | N37: 0.77410859
B38: Consubanco | C38: 23248.393 | D38: 30750.111 | E38: 31460.825 | F38: 1.763396 | G38: 1.6180695 | H38: 1.5104281 | I38: 210.14353 | J38: 224.02722 | K38: 232.96449 | L38: 3.7056624 | M38: 3.6249161 | N38: 3.5187612
B39: Intercam Banco | C39: 20818.492 | D39: 18997.184 | E39: 13701.469 | F39: 3.0342007 | G39: 4.8650035 | H39: 7.0765523 | I39: 186.64977 | J39: 144.79065 | K39: 143.23318 | L39: 5.6633286 | M39: 7.0440702 | N39: 10.135971
B40: Autofin | C40: 4417.2963 | D40: 9513.4427 | E40: 10101.269 | F40: 3.1345408 | G40: 3.2162558 | H40: 2.7156992 | I40: 151.64069 | J40: 131.88122 | K40: 153.72453 | L40: 4.7532394 | M40: 4.2416374 | N40: 4.1746959
B41: Bankaool | C41: 7487.3347 | D41: 12586.946 | E41: 12973.417 | F41: 1.6258189 | G41: 0.88075599 | H41: 0.84564655 | I41: 187.93417 | J41: 209.12365 | K41: 216.91464 | L41: 3.0554693 | M41: 1.8418691 | N41: 1.8343311
B42: BNP Paribas México | C42: 0 | D42: 0 | E42: 0 | F42: - | G42: - | H42: - | I42: - | J42: - | K42: - | L42: - | M42: - | N42: -
B43: Inmobiliario Mexicano | C43: 11248.642 | D43: 12477.747 | E43: 12581.466 | F43: 3.793325 | G43: 2.8705839 | H43: 2.825377 | I43: 61.132263 | J43: 65.885064 | K43: 64.458994 | L43: 2.3189454 | M43: 1.891286 | N43: 1.8212096
B44: Mizuho Bank | C44: 4701.6547 | D44: 6063.7803 | E44: 6064.05 | F44: 0 | G44: 0 | H44: 0 | I44: - | J44: - | K44: - | L44: 0.46697452 | M44: 0.46593333 | N44: 0.46360062
B45: ICBC | C45: 3175.4614 | D45: 4847.7865 | E45: 4986.133 | F45: 0 | G45: 0 | H45: 0 | I45: - | J45: - | K45: - | L45: 3.4090649 | M45: 1.9621832 | N45: 1.9400029
B46: Banco Covalto | C46: 4609.1614 | D46: 6995.6593 | E46: 7229.0721 | F46: 6.5580086 | G46: 5.1230232 | H46: 5.11827 | I46: 62.332868 | J46: 69.276736 | K46: 69.831469 | L46: 4.0877949 | M46: 3.5490632 | N46: 3.5741631
B47: Openbank | C47: 0 | D47: 137.80434 | E47: 181.24835 | F47: - | G47: 0.90948808 | H47: 2.3362166 | I47: - | J47: 2173.6899 | K47: 1034.7188 | L47: - | M47: 19.769451 | N47: 24.173272
B48: Volkswagen Bank | C48: 5018.8679 | D48: 7276.972 | E48: 7404.2091 | F48: 1.0018261 | G48: 1.0732016 | H48: 1.1170978 | I48: 278.02668 | J48: 210.49931 | K48: 249.91953 | L48: 2.7853438 | M48: 2.2590819 | N48: 2.7918457
B49: Bank of China | C49: 4465.3113 | D49: 3537.1302 | E49: 2680.1986 | F49: 3.9666434 | G49: 3.3687604 | H49: 4.2112451 | I49: 99.556397 | J49: 111.31278 | K49: 109.58848 | L49: 3.9490473 | M49: 3.7498608 | N49: 4.6150395
B50: Shinhan | C50: 3429.752 | D50: 4552.7844 | E50: 4488.8661 | F50: 1.623545 | G50: 1.2230662 | H50: 1.2404818 | I50: 60.244361 | J50: 82.618728 | K50: 74.343511 | L50: 0.97809431 | M50: 1.0104817 | N50: 0.92221773
B51: Banco Ualá | C51: 519.75743 | D51: 753.47903 | E51: 807.73272 | F51: 27.15028 | G51: 16.617521 | H51: 16.512534 | I51: 82.576664 | J51: 119.81877 | K51: 122.12105 | L51: 22.419795 | M51: 19.910909 | N51: 20.16528
B52: Banco S3 | C52: 11.498022 | D52: 159.36079 | E52: 149.06457 | F52: 0 | G52: 0 | H52: 0 | I52: - | J52: - | K52: - | L52: 0.71170502 | M52: 1.0595655 | N52: 0.85647579
B53: KEB Hana México | C53: 3511.5556 | D53: 3885.1295 | E53: 3613.1037 | F53: 1.5908355 | G53: 1.485582 | H53: 1.5999749 | I53: 109.90399 | J53: 128.45375 | K53: 127.47702 | L53: 1.7483918 | M53: 1.9082858 | N53: 2.0396004
B54: Banco Bineo | C54: 43.474256 | D54: 13.728232 | E54: 9.8025796 | F54: 1.7710431 | G54: 41.156656 | H54: 42.710186 | I54: 634.09941 | J54: 98.108709 | K54: 94.337196 | L54: 11.230174 | M54: 40.378264 | N54: 40.291592
B55: Dondé Banco | C55: 786.52665 | D55: 1640.4681 | E55: 1565.196 | F55: 0.41253211 | G55: 0.19778958 | H55: 0.20730151 | I55: 247.91919 | J55: 388.35683 | K55: 369.28688 | L55: 1.0227463 | M55: 0.76812936 | N55: 0.76553728
B56: Credit Suisse | C56: 0 | D56: 0 | E56: 0 | F56: - | G56: - | H56: - | I56: - | J56: - | K56: - | L56: - | M56: - | N56: -
B57: Hey Banco | C57: 0 | D57: 0 | E57: 0 | F57: - | G57: - | H57: - | I57: - | J57: - | K57: - | L57: - | M57: - | N57: -
B58: Pagatodo | C58: 0 | D58: 0 | E58: 0 | F58: - | G58: - | H58: - | I58: - | J58: - | K58: - | L58: - | M58: - | N58: -
B59: Forjadores | C59: 500.24758 | D59: 381.86234 | E59: 404.2503 | F59: 6.3548429 | G59: 9.7035952 | H59: 8.4306326 | I59: 149.99968 | J59: 125.55923 | K59: 135.05629 | L59: 9.5322438 | M59: 12.18376 | N59: 11.3861

Sheet CCE
B2: Cartera de crédito a empresas
B3: Millones de pesos y porcentajes
C5: Cartera total (MDP) 1/ | F5: IMOR (%) 5/ | I5: ICOR (%) 6/ | L5: Pérdida esperada (%) 7/
C6: 45505 | D6: 45839 | E6: 45870 | F6: =C6 -> 45505 | G6: =D6 -> 45839 | H6: =E6 -> 45870 | I6: =C6 -> 45505 | J6: =D6 -> 45839 | K6: =E6 -> 45870 | L6: =C6 -> 45505 | M6: =D6 -> 45839 | N6: =E6 -> 45870
B7: Sistema */ | C7: 3488266 | D7: 3727749.3 | E7: 3737376.9 | F7: 1.7436158 | G7: 1.7291745 | H7: 1.758917 | I7: 95.141328 | J7: 97.092335 | K7: 96.012094 | L7: 1.6588992 | M7: 1.6788959 | N7: 1.688773
B8: BBVA México | C8: 779484.92 | D8: 845064.71 | E8: 842552.82 | F8: 1.3250227 | G8: 1.0930512 | H8: 1.0776563 | I8: 93.870375 | J8: 107.45246 | K8: 108.17431 | L8: 1.2438038 | M8: 1.1745104 | N8: 1.1657472
B9: Santander | C9: 380240.3 | D9: 387976.99 | E9: 380939.14 | F9: 1.5380285 | G9: 1.5405653 | H9: 1.6108388 | I9: 91.163006 | J9: 97.156531 | K9: 97.016733 | L9: 1.402113 | M9: 1.4967598 | N9: 1.5627832
B10: Banorte | C10: 425261.94 | D10: 454619.9 | E10: 460160.81 | F10: 0.96568098 | G10: 1.1437797 | H10: 1.1429573 | I10: 85.204664 | J10: 68.126721 | K10: 70.824159 | L10: 0.82280523 | M10: 0.77921957 | N10: 0.8094899
B11: Banamex | C11: 248834.16 | D11: 130847.47 | E11: 132285.57 | F11: 1.1254841 | G11: 2.9437062 | H11: 2.754815 | I11: 160.23722 | J11: 96.591479 | K11: 98.840577 | L11: 1.8034445 | M11: 2.8433693 | N11: 2.722875
B12: HSBC | C12: 209691.57 | D12: 222562.97 | E12: 220723.03 | F12: 2.1024589 | G12: 2.8024905 | H12: 2.8889034 | I12: 89.779297 | J12: 86.598885 | K12: 85.842568 | L12: 1.8875729 | M12: 2.4269255 | N12: 2.4799089
B13: Scotiabank | C13: 199231.79 | D13: 192263.08 | E13: 194943.21 | F13: 3.8056645 | G13: 2.8542654 | H13: 2.7577768 | I13: 82.356963 | J13: 78.308601 | K13: 80.099535 | L13: 3.1342297 | M13: 2.2351353 | N13: 2.2089664
B14: Inbursa | C14: 310768.57 | D14: 321335.89 | E14: 326660.46 | F14: 1.7020299 | G14: 1.494835 | H14: 1.5115313 | I14: 108.95063 | J14: 120.13973 | K14: 119.96108 | L14: 1.8543723 | M14: 1.7958907 | N14: 1.8132494
B15: Citi México | C15: 0 | D15: 137893.37 | E15: 133585.88 | F15: - | G15: 0.0065067991 | H15: 0.0067496803 | I15: - | J15: 17977.824 | K15: 17006.207 | L15: - | M15: 1.1697809 | N15: 1.1478646
B16: Banco del Bajío | C16: 210343.7 | D16: 228199.91 | E16: 231432.33 | F16: 1.6023045 | G16: 1.969894 | H16: 1.9486717 | I16: 103.60407 | J16: 95.214421 | K16: 94.534993 | L16: 1.6600527 | M16: 1.8756232 | N16: 1.8421767
B17: Banco Azteca | C17: 42775.047 | D17: 44433.97 | E17: 45638.894 | F17: 0.99164085 | G17: 2.7649932 | H17: 4.1774129 | I17: 80.503202 | J17: 56.704017 | K17: 49.173183 | L17: 0.79830264 | M17: 1.5678622 | N17: 2.0541669
B18: Afirme | C18: 36895.075 | D18: 39323.978 | E18: 39898.806 | F18: 6.6393133 | G18: 4.5647443 | H18: 4.4209898 | I18: 45.016951 | J18: 54.302093 | K18: 51.792746 | L18: 2.9888164 | M18: 2.4787517 | N18: 2.289752
B19: Monex | C19: 34008.243 | D19: 41614.196 | E19: 41955.725 | F19: 1.6993332 | G19: 1.8939995 | H19: 1.8500347 | I19: 107.32172 | J19: 110.35244 | K19: 114.38409 | L19: 1.8237537 | M19: 2.0900747 | N19: 2.1161453
B20: Banregio | C20: 136816.5 | D20: 148361.92 | E20: 149692.77 | F20: 1.2174093 | G20: 1.5097903 | H20: 1.6140326 | I20: 131.71533 | J20: 114.66077 | K20: 105.58514 | L20: 1.6035147 | M20: 1.7311372 | N20: 1.7041785
B21: J.P. Morgan | C21: 19577.149 | D21: 24248.486 | E21: 23991.417 | F21: 0 | G21: 0 | H21: 0 | I21: - | J21: - | K21: - | L21: 0.71147067 | M21: 0.60987204 | N21: 0.62284812
B22: Bank of America | C22: 28708.577 | D22: 28411.346 | E22: 30806.887 | F22: 0 | G22: 0 | H22: 0 | I22: - | J22: - | K22: - | L22: 0.88412104 | M22: 1.1874196 | N22: 1.0791899
B23: Invex | C23: 14156.4 | D23: 14881.706 | E23: 14454.032 | F23: 2.5428001 | G23: 1.8285654 | H23: 1.8825516 | I23: 78.799881 | J23: 119.84949 | K23: 119.8119 | L23: 2.0037234 | M23: 2.1915263 | N23: 2.2555209
B24: BanCoppel | C24: 33232.416 | D24: 41303.117 | E24: 42102.249 | F24: 4.1793086 | G24: 3.7822899 | H24: 3.8361586 | I24: 78.553056 | J24: 86.626422 | K24: 85.584636 | L24: 3.2829746 | M24: 3.2764624 | N24: 3.2831624
B25: Multiva | C25: 34769.146 | D25: 42771.104 | E25: 44501.538 | F25: 5.3923204 | G25: 3.8824297 | H25: 3.666852 | I25: 82.944187 | J25: 97.585618 | K25: 101.04747 | L25: 4.4726163 | M25: 3.788693 | N25: 3.7052613
B26: Banca Mifel | C26: 52809.359 | D26: 59764.998 | E26: 61096.464 | F26: 1.3508007 | G26: 1.1732697 | H26: 1.3121854 | I26: 131.17396 | J26: 146.55307 | K26: 129.89843 | L26: 1.7718987 | M26: 1.7194627 | N26: 1.7045083
B27: Barclays | C27: 0 | D27: 0 | E27: 0 | F27: - | G27: - | H27: - | I27: - | J27: - | K27: - | L27: - | M27: - | N27: -
B28: Banco Base | C28: 11049.292 | D28: 10225.457 | E28: 10138.432 | F28: 2.3408681 | G28: 3.2328412 | H28: 3.4491267 | I28: 105.65935 | J28: 85.596186 | K28: 82.087936 | L28: 2.4733461 | M28: 2.7671888 | N28: 2.8313169
B29: Sabadell | C29: 93252.803 | D29: 97372.271 | E29: 97700.862 | F29: 1.7827664 | G29: 2.312779 | H29: 2.0907283 | I29: 75.041327 | J29: 65.431454 | K29: 68.298771 | L29: 1.3378115 | M29: 1.5132849 | N29: 1.4279417
B30: Ve por Más | C30: 40629.88 | D30: 43982.27 | E30: 44053.567 | F30: 4.1998776 | G30: 3.670094 | H30: 3.6631818 | I30: 71.990302 | J30: 83.36192 | K30: 87.041864 | L30: 3.0235046 | M30: 3.0594608 | N30: 3.1885017
B31: Actinver | C31: 22220.383 | D31: 22346.736 | E31: 23748.61 | F31: 3.0601161 | G31: 3.2085731 | H31: 2.9992543 | I31: 100.17331 | J31: 85.317737 | K31: 88.38311 | L31: 3.0654197 | M31: 2.737482 | N31: 2.6508342
B32: Bansí | C32: 17132.629 | D32: 19102.034 | E32: 19368.466 | F32: 5.8389909 | G32: 5.3504309 | H32: 5.112532 | I32: 120.42579 | J32: 151.00092 | K32: 155.61775 | L32: 7.0316507 | M32: 8.0791998 | N32: 7.9560071
B33: CIBanco | C33: 4613.0434 | D33: 6578.9624 | E33: 5125.1878 | F33: 4.451945 | G33: 5.0529099 | H33: 7.0233442 | I33: 75.565972 | J33: 71.063815 | K33: 66.929101 | L33: 3.3641555 | M33: 3.5907905 | N33: 4.7006612
B34: Compartamos | C34: 0 | D34: 0 | E34: 0 | F34: - | G34: - | H34: - | I34: - | J34: - | K34: - | L34: - | M34: - | N34: -
B35: BIAfirme | C35: 273.0448 | D35: 244.16608 | E35: 244.07477 | F35: 0 | G35: 0 | H35: 0 | I35: - | J35: - | K35: - | L35: 0.52293068 | M35: 0.44172885 | N35: 0.56619249
B36: Bancrea | C36: 30730.523 | D36: 36516.345 | E36: 36922.142 | F36: 0.92234964 | G36: 1.1203138 | H36: 2.424181 | I36: 111.64801 | J36: 142.8028 | K36: 63.38558 | L36: 1.029785 | M36: 1.5998394 | N36: 1.5365812
B37: MUFG Bank | C37: 11435.112 | D37: 6866.0949 | E37: 7456.553 | F37: 0 | G37: 0 | H37: 0 | I37: - | J37: - | K37: - | L37: 0.50519678 | M37: 0.77800167 | N37: 0.76217465
B38: Consubanco | C38: 3344.4169 | D38: 7043.5293 | E38: 7258.8692 | F38: 0 | G38: 0 | H38: 0 | I38: - | J38: - | K38: - | L38: 1.0311816 | M38: 1.5676168 | N38: 1.4481195
B39: Intercam Banco | C39: 17435.372 | D39: 17071.35 | E39: 12548.744 | F39: 3.6169378 | G39: 5.4001408 | H39: 7.6773351 | I39: 95.551785 | J39: 84.497253 | K39: 83.860293 | L39: 3.4560487 | M39: 4.5629706 | N39: 6.4382357
B40: Autofin | C40: 2879.5909 | D40: 7390.6898 | E40: 7785.3669 | F40: 2.4415831 | G40: 3.5535934 | H40: 2.9590422 | I40: 195.22791 | J40: 126.70123 | K40: 150.99112 | L40: 4.7666516 | M40: 4.5024467 | N40: 4.467891
B41: Bankaool | C41: 7406.0315 | D41: 12001.764 | E41: 12389.731 | F41: 1.6229657 | G41: 0.91539267 | H41: 0.87660468 | I41: 185.25087 | J41: 185.93478 | K41: 193.62594 | L41: 3.0065582 | M41: 1.7020334 | N41: 1.6973341
B42: BNP Paribas México | C42: 0 | D42: 0 | E42: 0 | F42: - | G42: - | H42: - | I42: - | J42: - | K42: - | L42: - | M42: - | N42: -
B43: Inmobiliario Mexicano | C43: 10945.449 | D43: 12233.377 | E43: 12359.499 | F43: 3.7899246 | G43: 2.8732986 | H43: 2.8512192 | I43: 61.546589 | J43: 66.385032 | K43: 64.575388 | L43: 2.3325693 | M43: 1.9074402 | N43: 1.8411859
B44: Mizuho Bank | C44: 384.05071 | D44: 1416.4615 | E44: 1437.1177 | F44: 0 | G44: 0 | H44: 0 | I44: - | J44: - | K44: - | L44: 0.46214952 | M44: 0.56292149 | N44: 0.54729914
B45: ICBC | C45: 2184.7576 | D45: 3429.4465 | E45: 3584.0265 | F45: 0 | G45: 0 | H45: 0 | I45: - | J45: - | K45: - | L45: 2.2979069 | M45: 1.7337215 | N45: 1.7061966
B46: Banco Covalto | C46: 4517.6582 | D46: 6339.671 | E46: 6593.3137 | F46: 6.6908382 | G46: 5.6531206 | H46: 5.6117977 | I46: 61.666776 | J46: 68.7847 | K46: 68.975172 | L46: 4.1260242 | M46: 3.8884821 | N46: 3.8707471
B47: Openbank | C47: 0 | D47: 0 | E47: 0 | F47: - | G47: - | H47: - | I47: - | J47: - | K47: - | L47: - | M47: - | N47: -
B48: Volkswagen Bank | C48: 0 | D48: 0 | E48: 0 | F48: - | G48: - | H48: - | I48: - | J48: - | K48: - | L48: - | M48: - | N48: -
B49: Bank of China | C49: 2541.3243 | D49: 2097.0594 | E49: 2045.3193 | F49: 4.7617072 | G49: 3.1197058 | H49: 3.1986244 | I49: 91.131697 | J49: 110.05393 | K49: 111.618 | L49: 4.3394246 | M49: 3.4333587 | N49: 3.5702404
B50: Shinhan | C50: 3429.752 | D50: 4552.7844 | E50: 4488.8661 | F50: 1.623545 | G50: 1.2230662 | H50: 1.2404818 | I50: 60.244361 | J50: 82.618728 | K50: 74.343511 | L50: 0.97809431 | M50: 1.0104817 | N50: 0.92221773
B51: Banco Ualá | C51: 260.56222 | D51: 196.85592 | E51: 185.75579 | F51: 38.178883 | G51: 36.809819 | H51: 40.429958 | I51: 39.567403 | J51: 36.441596 | K51: 38.299392 | L51: 15.106392 | M51: 13.414086 | N51: 15.484428
B52: Banco S3 | C52: 0 | D52: 0 | E52: 0 | F52: - | G52: - | H52: - | I52: - | J52: - | K52: - | L52: - | M52: - | N52: -
B53: KEB Hana México | C53: 3455.6925 | D53: 3827.4127 | E53: 3555.295 | F53: 0 | G53: 0 | H53: 0 | I53: - | J53: - | K53: - | L53: 0.46724814 | M53: 0.51955719 | N53: 0.51181334
B54: Banco Bineo | C54: 0 | D54: 0 | E54: 0 | F54: - | G54: - | H54: - | I54: - | J54: - | K54: - | L54: - | M54: - | N54: -
B55: Dondé Banco | C55: 539.62447 | D55: 1035.4823 | E55: 965.0296 | F55: 0.60128389 | G55: 0.31334914 | H55: 0.33622544 | I55: 145.14246 | J55: 213.79889 | K55: 202.33139 | L55: 0.8727182 | M55: 0.66993696 | N55: 0.6802896
B56: Credit Suisse | C56: 0 | D56: 0 | E56: 0 | F56: - | G56: - | H56: - | I56: - | J56: - | K56: - | L56: - | M56: - | N56: -
B57: Hey Banco | C57: 0 | D57: 0 | E57: 0 | F57: - | G57: - | H57: - | I57: - | J57: - | K57: - | L57: - | M57: - | N57: -
B58: Pagatodo | C58: 0 | D58: 0 | E58: 0 | F58: - | G58: - | H58: - | I58: - | J58: - | K58: - | L58: - | M58: - | N58: -
B59: Forjadores | C59: 0.137155 | D59: 0 | E59: 0 | F59: 0 | G59: - | H59: - | I59: - | J59: - | K59: - | L59: 10.717801 | M59: - | N59: -

Sheet CCEF
B2: Cartera de crédito a entidades financieras
B3: Millones de pesos y porcentajes
C5: Cartera total (MDP) 1/ | F5: IMOR (%) 5/ | I5: ICOR (%) 6/ | L5: Pérdida esperada (%) 7/
C6: 45505 | D6: 45839 | E6: 45870 | F6: =C6 -> 45505 | G6: =D6 -> 45839 | H6: =E6 -> 45870 | I6: =C6 -> 45505 | J6: =D6 -> 45839 | K6: =E6 -> 45870 | L6: =C6 -> 45505 | M6: =D6 -> 45839 | N6: =E6 -> 45870
B7: Sistema */ | C7: 251412.64 | D7: 293277.47 | E7: 302250.41 | F7: 1.2073572 | G7: 1.038416 | H7: 1.2362234 | I7: 164.66845 | J7: 174.3029 | K7: 142.76072 | L7: 1.9881364 | M7: 1.8099893 | N7: 1.7648414
B8: BBVA México | C8: 37861.471 | D8: 54562.6 | E8: 53327.992 | F8: 0.042926418 | G8: 0.039576953 | H8: 0.031183903 | I8: 991.61306 | J8: 1745.4577 | K8: 2248.4813 | L8: 0.42566397 | M8: 0.69079899 | N8: 0.70116423
B9: Santander | C9: 9664.1562 | D9: 14410.398 | E9: 18111.078 | F9: 0 | G9: 0.069556246 | H9: 0.055796232 | I9: - | J9: 3305.1547 | K9: 3523.3188 | L9: 3.5768904 | M9: 2.2989416 | N9: 1.9658791
B10: Banorte | C10: 51800.181 | D10: 60102.622 | E10: 63593.813 | F10: 0.25036268 | G10: 0.3856237 | H10: 0.20694638 | I10: 121.01248 | J10: 87.970249 | K10: 139.92219 | L10: 0.30297009 | M10: 0.33923413 | N10: 0.2895639
B11: Banamex | C11: 38717.422 | D11: 2433.1488 | E11: 2507.7808 | F11: 5.8226983 | G11: 0 | H11: 0 | I11: 119.95883 | J11: - | K11: - | L11: 6.9848409 | M11: 1.159257 | N11: 1.1378862
B12: HSBC | C12: 12081.418 | D12: 8973.9394 | E12: 9151.5685 | F12: 0.00036083512 | G12: 2.3144796e-05 | H12: 8.5467985 | I12: 726310.83 | J12: 21711718 | K12: 55.933213 | L12: 2.6207846 | M12: 5.0251329 | N12: 4.780499
B13: Scotiabank | C13: 19534.942 | D13: 24925.328 | E13: 26476.244 | F13: 0.28854173 | G13: 0.38297017 | H13: 0.36053668 | I13: 333.78002 | J13: 204.50157 | K13: 223.06812 | L13: 0.96309465 | M13: 0.78318001 | N13: 0.8042424
B14: Inbursa | C14: 14762.575 | D14: 17041.669 | E14: 17753.317 | F14: 0 | G14: 0 | H14: 0 | I14: - | J14: - | K14: - | L14: 0.70721201 | M14: 0.81219593 | N14: 0.78556408
B15: Citi México | C15: 0 | D15: 24860.938 | E15: 26127.85 | F15: n.a. | G15: 9.0738427 | H15: 8.6335897 | I15: - | J15: 105.99102 | K15: 107.26264 | L15: - | M15: 9.6174582 | N15: 9.2606166
B16: Banco del Bajío | C16: 12620.879 | D16: 11742.266 | E16: 11341.702 | F16: 0.52558372 | G16: 0.96219996 | H16: 0.99618279 | I16: 145.00358 | J16: 222.1715 | K16: 204.32764 | L16: 0.76211522 | M16: 2.1377341 | N16: 2.0354768
B17: Banco Azteca | C17: 14294.608 | D17: 13613.495 | E17: 13627.822 | F17: 0 | G17: 0 | H17: 0 | I17: - | J17: - | K17: - | L17: 1.0052584 | M17: 0.95390729 | N17: 0.94359385
B18: Afirme | C18: 56.410575 | D18: 110.98007 | E18: 110.63634 | F18: 0 | G18: 0 | H18: 0 | I18: - | J18: - | K18: - | L18: 6.2464387 | M18: 3.9378728 | N18: 3.4875467
B19: Monex | C19: 5966.1782 | D19: 9032.9909 | E19: 8963.9835 | F19: 0.77357378 | G19: 0.42109034 | H19: 0.42039109 | I19: 125.2597 | J19: 173.30627 | K19: 152.91457 | L19: 0.96897619 | M19: 0.72977595 | N19: 0.64283923
B20: Banregio | C20: 4595.9211 | D20: 5858.8205 | E20: 5918.6715 | F20: 0 | G20: 0 | H20: 0 | I20: - | J20: - | K20: - | L20: 2.9592156 | M20: 2.2388704 | N20: 2.2043771
B21: J.P. Morgan | C21: 0 | D21: 1296.6367 | E21: 850.90924 | F21: n.a. | G21: 0 | H21: 0 | I21: - | J21: - | K21: - | L21: - | M21: 0.62797475 | N21: 0.87478495
B22: Bank of America | C22: 6566.8744 | D22: 13450.343 | E22: 13106.93 | F22: 0 | G22: 0 | H22: 0 | I22: - | J22: - | K22: - | L22: 0.58447381 | M22: 0.73679928 | N22: 0.77611453
B23: Invex | C23: 1347.7749 | D23: 1798.9664 | E23: 1750.1621 | F23: 0 | G23: 0 | H23: 0 | I23: - | J23: - | K23: - | L23: 0.50803794 | M23: 0.56445328 | N23: 1.0923315
B24: BanCoppel | C24: 2103.8104 | D24: 1504.7594 | E24: 1506.5101 | F24: 1.775816 | G24: 2.4827758 | H24: 2.4798907 | I24: 95.213451 | J24: 110.09841 | K24: 109.98457 | L24: 1.6908157 | M24: 2.7334967 | N24: 2.7274972
B25: Multiva | C25: 1876.1377 | D25: 6304.3348 | E25: 6464.1901 | F25: 3.5185472 | G25: 1.2675965 | H25: 1.4490178 | I25: 70.54359 | J25: 129.10088 | K25: 120.14173 | L25: 2.4821095 | M25: 1.6364783 | N25: 1.7408751
B26: Banca Mifel | C26: 2285.525 | D26: 2405.2553 | E26: 2435.5247 | F26: 0 | G26: 0 | H26: 0.18221983 | I26: - | J26: - | K26: 728.53786 | L26: 0.51832161 | M26: 0.9646494 | N26: 1.3275405
B27: Barclays | C27: 0 | D27: 0 | E27: 0 | F27: n.a. | G27: n.a. | H27: n.a. | I27: - | J27: - | K27: - | L27: - | M27: - | N27: -
B28: Banco Base | C28: 397.79083 | D28: 296.63581 | E28: 298.96526 | F28: 0 | G28: 0 | H28: 0 | I28: - | J28: - | K28: - | L28: 0.56044931 | M28: 0.61810946 | N28: 0.60440167
B29: Sabadell | C29: 1156.6899 | D29: 2091.7696 | E29: 1995.0113 | F29: 8.7333374 | G29: 0 | H29: 0 | I29: 83.686531 | J29: - | K29: - | L29: 7.3086271 | M29: 0.43583333 | N29: 0.43685507
B30: Ve por Más | C30: 3171.7546 | D30: 3098.6526 | E30: 3495.7048 | F30: 1.2236557 | G30: 1.0220829 | H30: 0.90599177 | I30: 120.68877 | J30: 65.590005 | K30: 72.805939 | L30: 1.4768151 | M30: 0.67038422 | N30: 0.65961582
B31: Actinver | C31: 1431.9477 | D31: 2412.1418 | E31: 2408.0401 | F31: 0 | G31: 0 | H31: 0 | I31: - | J31: - | K31: - | L31: 0.86614517 | M31: 1.1394403 | N31: 1.1906884
B32: Bansí | C32: 736.77652 | D32: 823.32027 | E32: 790.5194 | F32: 0.9664643 | G32: 0.86487389 | H32: 0.90075993 | I32: 547.40509 | J32: 321.5449 | K32: 321.96886 | L32: 5.2904748 | M32: 2.7809579 | N32: 2.9001665
B33: CIBanco | C33: 460.74823 | D33: 492.1 | E33: 376.93734 | F33: 16.8549 | G33: 0 | H33: 0 | I33: 88.850846 | J33: - | K33: - | L33: 14.975721 | M33: 1.4994597 | N33: 0.92960198
B34: Compartamos | C34: 0 | D34: 0 | E34: 0 | F34: n.a. | G34: n.a. | H34: n.a. | I34: - | J34: - | K34: - | L34: - | M34: - | N34: -
B35: BIAfirme | C35: 0 | D35: 0 | E35: 0 | F35: n.a. | G35: n.a. | H35: n.a. | I35: - | J35: - | K35: - | L35: - | M35: - | N35: -
B36: Bancrea | C36: 1927.4802 | D36: 2054.5098 | E36: 2355.1212 | F36: 0 | G36: 0 | H36: 0 | I36: - | J36: - | K36: - | L36: 0.24559286 | M36: 0.75526158 | N36: 0.69013521
B37: MUFG Bank | C37: 0 | D37: 0 | E37: 20.580509 | F37: n.a. | G37: n.a. | H37: 0 | I37: - | J37: - | K37: - | L37: - | M37: - | N37: 3.4836699
B38: Consubanco | C38: 2406.0135 | D38: 2086.2108 | E38: 2119.9027 | F38: 0 | G38: 0 | H38: 0 | I38: - | J38: - | K38: - | L38: 2.051184 | M38: 1.6850506 | N38: 1.6655405
B39: Intercam Banco | C39: 1105.3773 | D39: 567.4266 | E39: 206.76203 | F39: 0 | G39: 0 | H39: 0 | I39: - | J39: - | K39: - | L39: 0.67939264 | M39: 1.595421 | N39: 0.16320211
B40: Autofin | C40: 749.47684 | D40: 1436.5551 | E40: 1629.8663 | F40: 3.5032957 | G40: 0 | H40: 0 | I40: 97.641622 | J40: - | K40: - | L40: 3.4206748 | M40: 1.5681268 | N40: 1.5160427
B41: Bankaool | C41: 69.294059 | D41: 558.4779 | E41: 558.84676 | F41: 0 | G41: 0 | H41: 0 | I41: - | J41: - | K41: - | L41: 2.8943304 | M41: 3.9345073 | N41: 3.9327382
B42: BNP Paribas México | C42: 0 | D42: 0 | E42: 0 | F42: n.a. | G42: n.a. | H42: n.a. | I42: - | J42: - | K42: - | L42: - | M42: - | N42: -
B43: Inmobiliario Mexicano | C43: 33.425578 | D43: 22.964855 | E43: 8.5341719 | F43: 0 | G43: 0 | H43: 0 | I43: - | J43: - | K43: - | L43: 0.47517733 | M43: 0.3672996 | N43: 0.36729961
B44: Mizuho Bank | C44: 1167.697 | D44: 1083.8879 | E44: 1076.6711 | F44: 0 | G44: 0 | H44: 0 | I44: - | J44: - | K44: - | L44: 0.19826295 | M44: 0.18807348 | N44: 0.19194961
B45: ICBC | C45: 0 | D45: 0 | E45: 0 | F45: n.a. | G45: n.a. | H45: n.a. | I45: - | J45: - | K45: - | L45: - | M45: - | N45: -
B46: Banco Covalto | C46: 91.503195 | D46: 655.98836 | E46: 635.75836 | F46: 0 | G46: 0 | H46: 0 | I46: - | J46: - | K46: - | L46: 1.1074923 | M46: 0.26881653 | N46: 0.49835433
B47: Openbank | C47: 0 | D47: 0 | E47: 0 | F47: n.a. | G47: n.a. | H47: n.a. | I47: - | J47: - | K47: - | L47: - | M47: - | N47: -
B48: Volkswagen Bank | C48: 0 | D48: 0 | E48: 0 | F48: n.a. | G48: n.a. | H48: n.a. | I48: - | J48: - | K48: - | L48: - | M48: - | N48: -
B49: Bank of China | C49: 56.112554 | D49: 305.38733 | E49: 298.97601 | F49: 100 | G49: 17.595805 | H49: 15.870053 | I49: 88 | J49: 97.177929 | K49: 101.33337 | L49: 88 | M49: 17.099239 | N49: 16.08166
B50: Shinhan | C50: 0 | D50: 0 | E50: 0 | F50: n.a. | G50: n.a. | H50: n.a. | I50: - | J50: - | K50: - | L50: - | M50: - | N50: -
B51: Banco Ualá | C51: 0 | D51: 39.889862 | E51: 40.48821 | F51: n.a. | G51: 0 | H51: 0 | I51: - | J51: - | K51: - | L51: - | M51: 0.29991079 | N51: 0.30054675
B52: Banco S3 | C52: 11.498022 | D52: 159.36079 | E52: 149.06457 | F52: 0 | G52: 0 | H52: 0 | I52: - | J52: - | K52: - | L52: 0.71170502 | M52: 1.0595655 | N52: 0.85647579
B53: KEB Hana México | C53: 55.863074 | D53: 57.716784 | E53: 57.808754 | F53: 100 | G53: 100 | H53: 100 | I53: 81 | J53: 93.999998 | K53: 96 | L53: 81 | M53: 93.999998 | N53: 96
B54: Banco Bineo | C54: 0 | D54: 0 | E54: 0 | F54: n.a. | G54: n.a. | H54: n.a. | I54: - | J54: - | K54: - | L54: - | M54: - | N54: -
B55: Dondé Banco | C55: 246.90217 | D55: 604.98574 | E55: 600.16641 | F55: 0 | G55: 0 | H55: 0 | I55: - | J55: - | K55: - | L55: 1.3226064 | M55: 0.92956885 | N55: 0.89593218
B56: Credit Suisse | C56: 0 | D56: 0 | E56: 0 | F56: n.a. | G56: n.a. | H56: n.a. | I56: - | J56: - | K56: - | L56: - | M56: - | N56: -
B57: Hey Banco | C57: 0 | D57: 0 | E57: 0 | F57: n.a. | G57: n.a. | H57: n.a. | I57: - | J57: - | K57: - | L57: - | M57: - | N57: -
B58: Pagatodo | C58: 0 | D58: 0 | E58: 0 | F58: n.a. | G58: n.a. | H58: n.a. | I58: - | J58: - | K58: - | L58: - | M58: - | N58: -
B59: Forjadores | C59: 0 | D59: 0 | E59: 0 | F59: n.a. | G59: n.a. | H59: n.a. | I59: - | J59: - | K59: - | L59: - | M59: - | N59: -

Sheet CCGT
B2: Cartera de crédito a entidades gubernamentales
B3: Millones de pesos y porcentajes
C5: Cartera total (MDP) 1/ | F5: IMOR (%) 5/ | I5: ICOR (%) 6/ | L5: Pérdida esperada (%) 7/
C6: 45505 | D6: 45839 | E6: 45870 | F6: =C6 -> 45505 | G6: =D6 -> 45839 | H6: =E6 -> 45870 | I6: =C6 -> 45505 | J6: =D6 -> 45839 | K6: =E6 -> 45870 | L6: =C6 -> 45505 | M6: =D6 -> 45839 | N6: =E6 -> 45870
B7: Sistema */ | C7: 613106.45 | D7: 542948.96 | E7: 514660.76 | F7: 0.007124764 | G7: 0.0045685877 | H7: 0.0048196989 | I7: 6446.9582 | J7: 11378.872 | K7: 12897.503 | L7: 0.45933056 | M7: 0.51985374 | N7: 0.62162083
B8: BBVA México | C8: 192716.9 | D8: 196749.62 | E8: 186548.24 | F8: 4.487184e-05 | G8: 0 | H8: 0 | I8: 764713.91 | J8: - | K8: - | L8: 0.3431412 | M8: 0.48551861 | N8: 0.77148882
B9: Santander | C9: 84619.548 | D9: 71061.77 | E9: 66714.625 | F9: 0 | G9: 0 | H9: 0 | I9: - | J9: - | K9: - | L9: 0.28804466 | M9: 0.38905853 | N9: 0.39531695
B10: Banorte | C10: 140556.1 | D10: 124724.95 | E10: 120199.23 | F10: 0.0019742072 | G10: 0 | H10: 0 | I10: 26385.043 | J10: - | K10: - | L10: 0.52089543 | M10: 0.50527903 | N10: 0.51691559
B11: Banamex | C11: 41755.48 | D11: 30030.26 | E11: 29908.503 | F11: 0 | G11: 0 | H11: 0 | I11: - | J11: - | K11: - | L11: 0.49450122 | M11: 0.52146905 | N11: 0.43059558
B12: HSBC | C12: 18550.463 | D12: 11140.016 | E12: 11374.742 | F12: 5.4769521e-06 | G12: 9.120274e-06 | H12: 8.932071e-06 | I12: 12030880 | J12: 6571802.7 | K12: 7007004.8 | L12: 0.65892555 | M12: 0.59936641 | N12: 0.62587064
B13: Scotiabank | C13: 23666.687 | D13: 7225.8747 | E13: 5395.741 | F13: 0 | G13: 0 | H13: 0 | I13: - | J13: - | K13: - | L13: 0.53195214 | M13: 0.59551915 | N13: 0.56499681
B14: Inbursa | C14: 31309.635 | D14: 24548.263 | E14: 21994.368 | F14: 0 | G14: 0 | H14: 0 | I14: - | J14: - | K14: - | L14: 0.5 | M14: 0.5 | N14: 0.5
B15: Citi México | C15: 0 | D15: 4964.2834 | E15: 3124.7296 | F15: n.a. | G15: 0 | H15: 0 | I15: - | J15: - | K15: - | L15: - | M15: 0.54644286 | N15: 0.50413614
B16: Banco del Bajío | C16: 16186.914 | D16: 13008.697 | E16: 12982.565 | F16: 0 | G16: 0 | H16: 0 | I16: - | J16: - | K16: - | L16: 0.51130567 | M16: 0.46929883 | N16: 0.47011783
B17: Banco Azteca | C17: 4777.3642 | D17: 4320.6831 | E17: 4756.7319 | F17: 0 | G17: 0 | H17: 0 | I17: - | J17: - | K17: - | L17: 0.73459403 | M17: 0.52253581 | N17: 0.53186023
B18: Afirme | C18: 1934.0724 | D18: 1274.0176 | E18: 1258.4097 | F18: 0 | G18: 0 | H18: 0 | I18: - | J18: - | K18: - | L18: 0.2935795 | M18: 0.56171397 | N18: 0.55688762
B19: Monex | C19: 5198.9279 | D19: 5032.4839 | E19: 4277.1611 | F19: 0 | G19: 0 | H19: 0 | I19: - | J19: - | K19: - | L19: 0.50018992 | M19: 0.50139744 | N19: 0.50153006
B20: Banregio | C20: 207.0423 | D20: 147.68195 | E20: 140.3283 | F20: 0 | G20: 0 | H20: 0 | I20: - | J20: - | K20: - | L20: 6.2065511 | M20: 4.2475147 | N20: 4.2295172
B21: J.P. Morgan | C21: 0 | D21: 0 | E21: 0 | F21: n.a. | G21: n.a. | H21: n.a. | I21: - | J21: - | K21: - | L21: - | M21: - | N21: -
B22: Bank of America | C22: 0 | D22: 0 | E22: 0 | F22: n.a. | G22: n.a. | H22: n.a. | I22: - | J22: - | K22: - | L22: - | M22: - | N22: -
B23: Invex | C23: 0 | D23: 0 | E23: 0 | F23: n.a. | G23: n.a. | H23: n.a. | I23: - | J23: - | K23: - | L23: - | M23: - | N23: -
B24: BanCoppel | C24: 0 | D24: 0 | E24: 0 | F24: n.a. | G24: n.a. | H24: n.a. | I24: - | J24: - | K24: - | L24: - | M24: - | N24: -
B25: Multiva | C25: 28210.918 | D25: 24486.46 | E25: 23593.013 | F25: 0 | G25: 0 | H25: 0 | I25: - | J25: - | K25: - | L25: 0.52120958 | M25: 0.58349758 | N25: 0.57280274
B26: Banca Mifel | C26: 3477.7774 | D26: 3314.6056 | E26: 3345.1092 | F26: 0 | G26: 0 | H26: 0 | I26: - | J26: - | K26: - | L26: 0.61112873 | M26: 0.61111105 | N26: 0.61111106
B27: Barclays | C27: 0 | D27: 0 | E27: 0 | F27: n.a. | G27: n.a. | H27: n.a. | I27: - | J27: - | K27: - | L27: - | M27: - | N27: -
B28: Banco Base | C28: 0 | D28: 0 | E28: 0 | F28: n.a. | G28: n.a. | H28: n.a. | I28: - | J28: - | K28: - | L28: - | M28: - | N28: -
B29: Sabadell | C29: 1294.691 | D29: 544.19448 | E29: 540.49321 | F29: 0 | G29: 0 | H29: 0 | I29: - | J29: - | K29: - | L29: 0.50000007 | M29: 0.50000011 | N29: 0.49999999
B30: Ve por Más | C30: 2542.3245 | D30: 2130.3047 | E30: 1565.2936 | F30: 0 | G30: 0 | H30: 0 | I30: - | J30: - | K30: - | L30: 0.49999999 | M30: 0.49260887 | N30: 0.48669133
B31: Actinver | C31: 0 | D31: 0 | E31: 0 | F31: n.a. | G31: n.a. | H31: n.a. | I31: - | J31: - | K31: - | L31: - | M31: - | N31: -
B32: Bansí | C32: 3548.5995 | D32: 8934.1054 | E32: 9098.8192 | F32: 1.1503137 | G32: 0.27763365 | H32: 0.27260771 | I32: 373.90489 | J32: 803.55321 | K32: 780.45989 | L32: 4.3010793 | M32: 2.2309341 | N32: 2.1275939
B33: CIBanco | C33: 0 | D33: 0 | E33: 0 | F33: n.a. | G33: n.a. | H33: n.a. | I33: - | J33: - | K33: - | L33: - | M33: - | N33: -
B34: Compartamos | C34: 0 | D34: 0 | E34: 0 | F34: n.a. | G34: n.a. | H34: n.a. | I34: - | J34: - | K34: - | L34: - | M34: - | N34: -
B35: BIAfirme | C35: 0 | D35: 0 | E35: 0 | F35: n.a. | G35: n.a. | H35: n.a. | I35: - | J35: - | K35: - | L35: - | M35: - | N35: -
B36: Bancrea | C36: 1288.2029 | D36: 2310.7763 | E36: 2077.0415 | F36: 0 | G36: 0 | H36: 0 | I36: - | J36: - | K36: - | L36: 0.43550695 | M36: 0.49267855 | N36: 0.46919114
B37: MUFG Bank | C37: 3374.0158 | D37: 0 | E37: 0 | F37: 0 | G37: n.a. | H37: n.a. | I37: - | J37: - | K37: - | L37: 0.58583457 | M37: - | N37: -
B38: Consubanco | C38: 0 | D38: 0 | E38: 0 | F38: n.a. | G38: n.a. | H38: n.a. | I38: - | J38: - | K38: - | L38: - | M38: - | N38: -
B39: Intercam Banco | C39: 1882.294 | D39: 883.45699 | E39: 477.34243 | F39: 0 | G39: 0 | H39: 0 | I39: - | J39: - | K39: - | L39: 0.49999501 | M39: 0.49999503 | N39: 0.49999494
B40: Autofin | C40: 0 | D40: 0 | E40: 0 | F40: n.a. | G40: n.a. | H40: n.a. | I40: - | J40: - | K40: - | L40: - | M40: - | N40: -
B41: Bankaool | C41: 0 | D41: 0 | E41: 0 | F41: n.a. | G41: n.a. | H41: n.a. | I41: - | J41: - | K41: - | L41: - | M41: - | N41: -
B42: BNP Paribas México | C42: 0 | D42: 0 | E42: 0 | F42: n.a. | G42: n.a. | H42: n.a. | I42: - | J42: - | K42: - | L42: - | M42: - | N42: -
B43: Inmobiliario Mexicano | C43: 0 | D43: 0 | E43: 0 | F43: n.a. | G43: n.a. | H43: n.a. | I43: - | J43: - | K43: - | L43: - | M43: - | N43: -
B44: Mizuho Bank | C44: 3149.9069 | D44: 3563.4308 | E44: 3550.2612 | F44: 0 | G44: 0 | H44: 0 | I44: - | J44: - | K44: - | L44: 0.5 | M44: 0.5 | N44: 0.5
B45: ICBC | C45: 990.70376 | D45: 1418.34 | E45: 1402.1065 | F45: 0 | G45: 0 | H45: 0 | I45: - | J45: - | K45: - | L45: 0.50000002 | M45: 0.5 | N45: 0.49999997
B46: Banco Covalto | C46: 0 | D46: 0 | E46: 0 | F46: n.a. | G46: n.a. | H46: n.a. | I46: - | J46: - | K46: - | L46: - | M46: - | N46: -
B47: Openbank | C47: 0 | D47: 0 | E47: 0 | F47: n.a. | G47: n.a. | H47: n.a. | I47: - | J47: - | K47: - | L47: - | M47: - | N47: -
B48: Volkswagen Bank | C48: 0 | D48: 0 | E48: 0 | F48: n.a. | G48: n.a. | H48: n.a. | I48: - | J48: - | K48: - | L48: - | M48: - | N48: -
B49: Bank of China | C49: 1867.8744 | D49: 1134.6835 | E49: 335.90335 | F49: 0 | G49: 0 | H49: 0 | I49: - | J49: - | K49: - | L49: 0.52764903 | M49: 0.5 | N49: 0.5
B50: Shinhan | C50: 0 | D50: 0 | E50: 0 | F50: n.a. | G50: n.a. | H50: n.a. | I50: - | J50: - | K50: - | L50: - | M50: - | N50: -
B51: Banco Ualá | C51: 0 | D51: 0 | E51: 0 | F51: n.a. | G51: n.a. | H51: n.a. | I51: - | J51: - | K51: - | L51: - | M51: - | N51: -
B52: Banco S3 | C52: 0 | D52: 0 | E52: 0 | F52: n.a. | G52: n.a. | H52: n.a. | I52: - | J52: - | K52: - | L52: - | M52: - | N52: -
B53: KEB Hana México | C53: 0 | D53: 0 | E53: 0 | F53: n.a. | G53: n.a. | H53: n.a. | I53: - | J53: - | K53: - | L53: - | M53: - | N53: -
B54: Banco Bineo | C54: 0 | D54: 0 | E54: 0 | F54: n.a. | G54: n.a. | H54: n.a. | I54: - | J54: - | K54: - | L54: - | M54: - | N54: -
B55: Dondé Banco | C55: 0 | D55: 0 | E55: 0 | F55: n.a. | G55: n.a. | H55: n.a. | I55: - | J55: - | K55: - | L55: - | M55: - | N55: -
B56: Credit Suisse | C56: 0 | D56: 0 | E56: 0 | F56: n.a. | G56: n.a. | H56: n.a. | I56: - | J56: - | K56: - | L56: - | M56: - | N56: -
B57: Hey Banco | C57: 0 | D57: 0 | E57: 0 | F57: n.a. | G57: n.a. | H57: n.a. | I57: - | J57: - | K57: - | L57: - | M57: - | N57: -
B58: Pagatodo | C58: 0 | D58: 0 | E58: 0 | F58: n.a. | G58: n.a. | H58: n.a. | I58: - | J58: - | K58: - | L58: - | M58: - | N58: -
B59: Forjadores | C59: 0 | D59: 0 | E59: 0 | F59: n.a. | G59: n.a. | H59: n.a. | I59: - | J59: - | K59: - | L59: - | M59: - | N59: -

Sheet CCG EyM
B2: Cartera de crédito a estados y municipios
B3: Millones de pesos y porcentajes
C5: Cartera total (MDP) 1/ | G5: IMOR (%) 5/
C6: 45505 | D6: 45839 | E6: 45870 | F6: =C6 -> 45505 | G6: =D6 -> 45839 | H6: =E6 -> 45870
B7: Sistema */ | C7: 277157.45 | D7: 279285.02 | E7: 282324.61 | F7: 0.015729289 | G7: 0.0088812796 | H7: 0.0087856609
B8: BBVA México | C8: 87791.258 | D8: 96306.544 | E8: 95922.575 | F8: 0 | G8: 0 | H8: 0
B9: Santander | C9: 48114.341 | D9: 47964.883 | E9: 47054.334 | F9: 0 | G9: 0 | H9: 0
B10: Banorte | C10: 81503.713 | D10: 75962.761 | E10: 76729.893 | F10: 0.0034045917 | G10: 0 | H10: 0
B11: Banamex | C11: 27401.196 | D11: 26189.195 | E11: 29540.339 | F11: 0 | G11: 0 | H11: 0
B12: HSBC | C12: 6224.2873 | D12: 4769.719 | E12: 4948.0634 | F12: 0 | G12: 0 | H12: 0
B13: Scotiabank | C13: 1835.0936 | D13: 451.8688 | E13: 501.161 | F13: 0 | G13: 0 | H13: 0
B14: Inbursa | C14: 0 | D14: 0 | E14: 0 | F14: n.a. | G14: n.a. | H14: n.a.
B15: Citi México | C15: 0 | D15: 0 | E15: 0 | F15: n.a. | G15: n.a. | H15: n.a.
B16: Banco del Bajío | C16: 7655.6535 | D16: 6543.1968 | E16: 6497.3103 | F16: 0 | G16: 0 | H16: 0
B17: Banco Azteca | C17: 3389.9468 | D17: 2997.1543 | E17: 3422.1123 | F17: 0 | G17: 0 | H17: 0
B18: Afirme | C18: 686.15594 | D18: 898.93462 | E18: 888.85103 | F18: 0 | G18: 0 | H18: 0
B19: Monex | C19: 0 | D19: 0 | E19: 0 | F19: n.a. | G19: n.a. | H19: n.a.
B20: Banregio | C20: 207.0423 | D20: 147.68195 | E20: 140.3283 | F20: 0 | G20: 0 | H20: 0
B21: J.P. Morgan | C21: 0 | D21: 0 | E21: 0 | F21: n.a. | G21: n.a. | H21: n.a.
B22: Bank of America | C22: 0 | D22: 0 | E22: 0 | F22: n.a. | G22: n.a. | H22: n.a.
B23: Invex | C23: 0 | D23: 0 | E23: 0 | F23: n.a. | G23: n.a. | H23: n.a.
B24: BanCoppel | C24: 0 | D24: 0 | E24: 0 | F24: n.a. | G24: n.a. | H24: n.a.
B25: Multiva | C25: 8281.0382 | D25: 10210.792 | E25: 10094.209 | F25: 0 | G25: 0 | H25: 0
B26: Banca Mifel | C26: 2.127804 | D26: 0 | E26: 0 | F26: 0 | G26: n.a. | H26: n.a.
B27: Barclays | C27: 0 | D27: 0 | E27: 0 | F27: n.a. | G27: n.a. | H27: n.a.
B28: Banco Base | C28: 0 | D28: 0 | E28: 0 | F28: n.a. | G28: n.a. | H28: n.a.
B29: Sabadell | C29: 0 | D29: 0 | E29: 0 | F29: n.a. | G29: n.a. | H29: n.a.
B30: Ve por Más | C30: 0 | D30: 0 | E30: 0 | F30: n.a. | G30: n.a. | H30: n.a.
B31: Actinver | C31: 0 | D31: 0 | E31: 0 | F31: n.a. | G31: n.a. | H31: n.a.
B32: Bansí | C32: 3369.107 | D32: 5430.5719 | E32: 5260.0618 | F32: 1.2115978 | G32: 0.456749 | H32: 0.47155498
B33: CIBanco | C33: 0 | D33: 0 | E33: 0 | F33: n.a. | G33: n.a. | H33: n.a.
B34: Compartamos | C34: 0 | D34: 0 | E34: 0 | F34: n.a. | G34: n.a. | H34: n.a.
B35: BIAfirme | C35: 0 | D35: 0 | E35: 0 | F35: n.a. | G35: n.a. | H35: n.a.
B36: Bancrea | C36: 696.4932 | D36: 1411.7116 | E36: 1325.3736 | F36: 0 | G36: 0 | H36: 0
B37: MUFG Bank | C37: 0 | D37: 0 | E37: 0 | F37: n.a. | G37: n.a. | H37: n.a.
B38: Consubanco | C38: 0 | D38: 0 | E38: 0 | F38: n.a. | G38: n.a. | H38: n.a.
B39: Intercam Banco | C39: 0 | D39: 0 | E39: 0 | F39: n.a. | G39: n.a. | H39: n.a.
B40: Autofin | C40: 0 | D40: 0 | E40: 0 | F40: n.a. | G40: n.a. | H40: n.a.
B41: Bankaool | C41: 0 | D41: 0 | E41: 0 | F41: n.a. | G41: n.a. | H41: n.a.
B42: BNP Paribas México | C42: 0 | D42: 0 | E42: 0 | F42: n.a. | G42: n.a. | H42: n.a.
B43: Inmobiliario Mexicano | C43: 0 | D43: 0 | E43: 0 | F43: n.a. | G43: n.a. | H43: n.a.
B44: Mizuho Bank | C44: 0 | D44: 0 | E44: 0 | F44: n.a. | G44: n.a. | H44: n.a.
B45: ICBC | C45: 0 | D45: 0 | E45: 0 | F45: n.a. | G45: n.a. | H45: n.a.
B46: Banco Covalto | C46: 0 | D46: 0 | E46: 0 | F46: n.a. | G46: n.a. | H46: n.a.
B47: Openbank | C47: 0 | D47: 0 | E47: 0 | F47: n.a. | G47: n.a. | H47: n.a.
B48: Volkswagen Bank | C48: 0 | D48: 0 | E48: 0 | F48: n.a. | G48: n.a. | H48: n.a.
... B59: Forjadores | C59: 0 | D59: 0 | E59: 0 | F59: n.a. | G59: n.a. | H59: n.a.

Sheet CCG OG
B2: Cartera de crédito a otras entidades gubernamentales
B3: Millones de pesos y porcentajes
C5: Cartera total (MDP) 1/ | G5: IMOR (%) 5/
C6: 45505 | D6: 45839 | E6: 45870 | F6: =C6 -> 45505 | G6: =D6 -> 45839 | H6: =E6 -> 45870
B7: Sistema */ | C7: 335948.99 | D7: 263663.94 | E7: 232336.15 | F7: 2.6043126e-07 | G7: 3.85339e-09 | H7: 4.3729743e-09
B8: BBVA México | C8: 104925.65 | D8: 100443.07 | E8: 90625.664 | F8: 8.2416096e-07 | G8: 0 | H8: 0
B9: Santander | C9: 36505.207 | D9: 23096.887 | E9: 19660.291 | F9: 0 | G9: 0 | H9: 0
B10: Banorte | C10: 59052.388 | D10: 48762.189 | E10: 43469.338 | F10: 0 | G10: 0 | H10: 0
B11: Banamex | C11: 14354.284 | D11: 3841.065 | E11: 368.16427 | F11: 0 | G11: 0 | H11: 0
B12: HSBC | C12: 12326.176 | D12: 6370.2972 | E12: 6426.6783 | F12: 8.2426212e-08 | G12: 1.594902e-07 | H12: 1.58091e-07
B13: Scotiabank | C13: 21831.594 | D13: 6774.0059 | E13: 4894.5801 | F13: 0 | G13: 0 | H13: 0
B14: Inbursa | C14: 31309.635 | D14: 24548.263 | E14: 21994.368 | F14: 0 | G14: 0 | H14: 0
B15: Citi México | C15: 0 | D15: 4964.2834 | E15: 3124.7296 | F15: n. a. | G15: 0 | H15: 0
B16: Banco del Bajío | C16: 8531.2607 | D16: 6465.5004 | E16: 6485.2551 | F16: 0 | G16: 0 | H16: 0
B17: Banco Azteca | C17: 1387.4174 | D17: 1323.5288 | E17: 1334.6195 | F17: 0 | G17: 0 | H17: 0
B18: Afirme | C18: 1247.9164 | D18: 375.083 | E18: 369.5587 | F18: 0 | G18: 0 | H18: 0
B19: Monex | C19: 5198.9279 | D19: 5032.4839 | E19: 4277.1611 | F19: 0 | G19: 0 | H19: 0
B20: Banregio | C20: 0 | D20: 0 | E20: 0 | F20: n. a. | G20: n. a. | H20: n. a.
B21: J.P. Morgan | C21: 0 | D21: 0 | E21: 0 | F21: n. a. | G21: n. a. | H21: n. a.
B22: Bank of America | C22: 0 | D22: 0 | E22: 0 | F22: n. a. | G22: n. a. | H22: n. a.
B23: Invex | C23: 0 | D23: 0 | E23: 0 | F23: n. a. | G23: n. a. | H23: n. a.
B24: BanCoppel | C24: 0 | D24: 0 | E24: 0 | F24: n. a. | G24: n. a. | H24: n. a.
B25: Multiva | C25: 19929.879 | D25: 14275.668 | E25: 13498.804 | F25: 0 | G25: 0 | H25: 0
B26: Banca Mifel | C26: 3475.6496 | D26: 3314.6056 | E26: 3345.1092 | F26: 0 | G26: 0 | H26: 0
B27: Barclays | C27: 0 | D27: 0 | E27: 0 | F27: n. a. | G27: n. a. | H27: n. a.
B28: Banco Base | C28: 0 | D28: 0 | E28: 0 | F28: n. a. | G28: n. a. | H28: n. a.
B29: Sabadell | C29: 1294.691 | D29: 544.19448 | E29: 540.49321 | F29: 0 | G29: 0 | H29: 0
B30: Ve por Más | C30: 2542.3245 | D30: 2130.3047 | E30: 1565.2936 | F30: 0 | G30: 0 | H30: 0
B31: Actinver | C31: 0 | D31: 0 | E31: 0 | F31: n. a. | G31: n. a. | H31: n. a.
B32: Bansí | C32: 179.49244 | D32: 3503.5335 | E32: 3838.7575 | F32: 0 | G32: 0 | H32: 0
B33: CIBanco | C33: 0 | D33: 0 | E33: 0 | F33: n. a. | G33: n. a. | H33: n. a.
B34: Compartamos | C34: 0 | D34: 0 | E34: 0 | F34: n. a. | G34: n. a. | H34: n. a.
B35: BIAfirme | C35: 0 | D35: 0 | E35: 0 | F35: n. a. | G35: n. a. | H35: n. a.
B36: Bancrea | C36: 591.70966 | D36: 899.06466 | E36: 751.66799 | F36: 0 | G36: 0 | H36: 0
B37: MUFG Bank | C37: 3374.0158 | D37: 0 | E37: 0 | F37: 0 | G37: n. a. | H37: n. a.
B38: Consubanco | C38: 0 | D38: 0 | E38: 0 | F38: n. a. | G38: n. a. | H38: n. a.
B39: Intercam Banco | C39: 1882.294 | D39: 883.45699 | E39: 477.34243 | F39: 0 | G39: 0 | H39: 0
B40: Autofin | C40: 0 | D40: 0 | E40: 0 | F40: n. a. | G40: n. a. | H40: n. a.
B41: Bankaool | C41: 0 | D41: 0 | E41: 0 | F41: n. a. | G41: n. a. | H41: n. a.
B42: BNP Paribas México | C42: 0 | D42: 0 | E42: 0 | F42: n. a. | G42: n. a. | H42: n. a.
B43: Inmobiliario Mexicano | C43: 0 | D43: 0 | E43: 0 | F43: n. a. | G43: n. a. | H43: n. a.
B44: Mizuho Bank | C44: 3149.9069 | D44: 3563.4308 | E44: 3550.2612 | F44: 0 | G44: 0 | H44: 0
B45: ICBC | C45: 990.70376 | D45: 1418.34 | E45: 1402.1065 | F45: 0 | G45: 0 | H45: 0
B46: Banco Covalto | C46: 0 | D46: 0 | E46: 0 | F46: n. a. | G46: n. a. | H46: n. a.
B47: Openbank | C47: 0 | D47: 0 | E47: 0 | F47: n. a. | G47: n. a. | H47: n. a.
B48: Volkswagen Bank | C48: 0 | D48: 0 | E48: 0 | F48: n. a. | G48: n. a. | H48: n. a.
B49: Bank of China | C49: 1867.8744 | D49: 1134.6835 | E49: 335.90335 | F49: 0 | G49: 0 | H49: 0
B50: Shinhan | C50: 0 | D50: 0 | E50: 0 | F50: n. a. | G50: n. a. | H50: n. a.
B51: Banco Ualá | C51: 0 | D51: 0 | E51: 0 | F51: n. a. | G51: n. a. | H51: n. a.
B52: Banco S3 | C52: 0 | D52: 0 | E52: 0 | F52: n. a. | G52: n. a. | H52: n. a.
B53: KEB Hana México | C53: 0 | D53: 0 | E53: 0 | F53: n. a. | G53: n. a. | H53: n. a.
B54: Banco Bineo | C54: 0 | D54: 0 | E54: 0 | F54: n. a. | G54: n. a. | H54: n. a.
B55: Dondé Banco | C55: 0 | D55: 0 | E55: 0 | F55: n. a. | G55: n. a. | H55: n. a.
B56: Credit Suisse | C56: 0 | D56: 0 | E56: 0 | F56: n. a. | G56: n. a. | H56: n. a.
B57: Hey Banco | C57: 0 | D57: 0 | E57: 0 | F57: n. a. | G57: n. a. | H57: n. a.
B58: Pagatodo | C58: 0 | D58: 0 | E58: 0 | F58: n. a. | G58: n. a. | H58: n. a.
B59: Forjadores | C59: 0 | D59: 0 | E59: 0 | F59: n. a. | G59: n. a. | H59: n. a.

Sheet CCCT
B2: Cartera de crédito al consumo
B3: Millones de pesos y porcentajes
C5: Cartera total (MDP) 1/ | F5: IMOR (%) 5/ | I5: ICOR (%) 6/ | L5: Pérdida esperada (%) 7/
C6: 45505 | D6: 45839 | E6: 45870 | F6: =C6 -> 45505 | G6: =D6 -> 45839 | H6: =E6 -> 45870 | I6: =C6 -> 45505 | J6: =D6 -> 45839 | K6: =E6 -> 45870 | L6: =C6 -> 45505 | M6: =D6 -> 45839 | N6: =E6 -> 45870
B7: Sistema */ | C7: 1601868.5 | D7: 1800615.7 | E7: 1822653.3 | F7: 2.9724891 | G7: 3.0176025 | H7: 2.9869845 | I7: 268.40312 | J7: 264.39788 | K7: 267.6479 | L7: 7.9782537 | M7: 7.9784769 | N7: 7.9946014
B8: BBVA México | C8: 475451.04 | D8: 533772.29 | E8: 541506.77 | F8: 2.7003564 | G8: 2.7038895 | H8: 2.6941315 | I8: 292.66566 | J8: 297.53794 | K8: 298.18759 | L8: 7.903016 | M8: 8.0450972 | N8: 8.0335659
B9: Santander | C9: 194633.3 | D9: 211070.48 | E9: 212286.11 | F9: 3.1624001 | G9: 3.1676704 | H9: 2.8271694 | I9: 260.62166 | J9: 253.27721 | K9: 274.81993 | L9: 8.2418996 | M9: 8.0229871 | N9: 7.769625
B10: Banorte | C10: 193055.75 | D10: 222368.01 | E10: 225836.76 | F10: 2.1086355 | G10: 2.157128 | H10: 2.0258503 | I10: 296.11689 | J10: 283.65547 | K10: 300.47461 | L10: 6.2440259 | M10: 6.1188116 | N10: 6.087166
B11: Banamex | C11: 214314.5 | D11: 244484.25 | E11: 248744.95 | F11: 2.9763079 | G11: 3.2765524 | H11: 3.3091709 | I11: 268.61534 | J11: 253.23448 | K11: 250.76127 | L11: 7.9948196 | M11: 8.2973602 | N11: 8.2981191
B12: HSBC | C12: 105928.32 | D12: 99988.103 | E12: 99132.472 | F12: 2.7408141 | G12: 3.0434319 | H12: 3.1700013 | I12: 359.57332 | J12: 350.22197 | K12: 333.48215 | L12: 9.8552363 | M12: 10.658767 | N12: 10.571389
B13: Scotiabank | C13: 44907.28 | D13: 54528.826 | E13: 55377.447 | F13: 2.4059743 | G13: 2.6813656 | H13: 2.7042194 | I13: 277.32741 | J13: 259.4155 | K13: 257.66245 | L13: 6.6724263 | M13: 6.955878 | N13: 6.9677579
B14: Inbursa | C14: 82918.247 | D14: 94558.224 | E14: 95775.572 | F14: 1.4066431 | G14: 1.5888618 | H14: 1.6220663 | I14: 297.56662 | J14: 268.14343 | K14: 266.81961 | L14: 4.1857003 | M14: 4.2604285 | N14: 4.3279909
B15: Citi México | C15: 0 | D15: 0 | E15: 0 | F15: n.a. | G15: n.a. | H15: n.a. | I15: - | J15: - | K15: - | L15: - | M15: - | N15: -
B16: Banco del Bajío | C16: 6619.7597 | D16: 7462.3593 | E16: 7559.2715 | F16: 2.347435 | G16: 2.5645603 | H16: 2.3746221 | I16: 381.30041 | J16: 349.53921 | K16: 367.48919 | L16: 8.9507795 | M16: 8.9641438 | N16: 8.7264795
B17: Banco Azteca | C17: 120172.92 | D17: 138102.77 | E17: 140020.54 | F17: 4.578076 | G17: 5.2547384 | H17: 5.4400519 | I17: 231.31795 | J17: 204.32913 | K17: 209.15742 | L17: 10.589912 | M17: 10.736961 | N17: 11.378272
B18: Afirme | C18: 12091.667 | D18: 13234.525 | E18: 13324.26 | F18: 2.7806922 | G18: 2.3201301 | H18: 2.6214628 | I18: 271.80302 | J18: 330.63617 | K18: 296.60493 | L18: 7.5580053 | M18: 7.6711893 | N18: 7.7753878
B19: Monex | C19: 0 | D19: 0 | E19: 0 | F19: n.a. | G19: n.a. | H19: n.a. | I19: - | J19: - | K19: - | L19: - | M19: - | N19: -
B20: Banregio | C20: 12288.701 | D20: 13346.974 | E20: 13480.463 | F20: 2.6109284 | G20: 2.2179998 | H20: 2.2083474 | I20: 324.11674 | J20: 363.28692 | K20: 362.81425 | L20: 8.462456 | M20: 8.0577031 | N20: 8.0121992
B21: J.P. Morgan | C21: 0 | D21: 0 | E21: 0 | F21: n.a. | G21: n.a. | H21: n.a. | I21: - | J21: - | K21: - | L21: - | M21: - | N21: -
B22: Bank of America | C22: 0 | D22: 0 | E22: 0 | F22: n.a. | G22: n.a. | H22: n.a. | I22: - | J22: - | K22: - | L22: - | M22: - | N22: -
B23: Invex | C23: 25484.391 | D23: 32652.582 | E23: 33080.122 | F23: 2.1223368 | G23: 2.4491346 | H23: 2.6903856 | I23: 331.64253 | J23: 301.96074 | K23: 275.80715 | L23: 7.0385714 | M23: 7.3954251 | N23: 7.4202757
B24: BanCoppel | C24: 22815.998 | D24: 22527.043 | E24: 31042.911 | F24: 15.7937 | G24: 10.43607 | H24: 7.8862728 | I24: 151.17992 | J24: 192.21657 | K24: 194.79657 | L24: 23.876904 | M24: 20.059856 | N24: 15.362189
B25: Multiva | C25: 5136.1533 | D25: 6243.7788 | E25: 6416.8215 | F25: 1.8194923 | G25: 1.1835833 | H25: 1.2338864 | I25: 206.41345 | J25: 276.64369 | K25: 255.464 | L25: 3.7556768 | M25: 3.2743086 | N25: 3.1521356
B26: Banca Mifel | C26: 285.37244 | D26: 433.82471 | E26: 432.43564 | F26: 8.1000875 | G26: 5.2994499 | H26: 5.8188749 | I26: 243.41114 | J26: 324.20116 | K26: 329.44362 | L26: 19.716515 | M26: 17.180878 | N26: 19.169912
B27: Barclays | C27: 0 | D27: 0 | E27: 0 | F27: n.a. | G27: n.a. | H27: n.a. | I27: - | J27: - | K27: - | L27: - | M27: - | N27: -
B28: Banco Base | C28: 0 | D28: 0 | E28: 0 | F28: n.a. | G28: n.a. | H28: n.a. | I28: - | J28: - | K28: - | L28: - | M28: - | N28: -
B29: Sabadell | C29: 13.121385 | D29: 11.580522 | E29: 10.144499 | F29: 9.8176755 | G29: 1.3422538 | H29: 1.532259 | I29: 178.15062 | J29: 735.94184 | K29: 691.1001 | L29: 17.49025 | M29: 9.8782076 | N29: 10.589444
B30: Ve por Más | C30: 147.70817 | D30: 153.45537 | E30: 157.21551 | F30: 0.16174867 | G30: 1.0322559 | H30: 1.2495002 | I30: 1599.4257 | J30: 333.59947 | K30: 345.45471 | L30: 2.5870499 | M30: 3.4436 | N30: 4.3164572
B31: Actinver | C31: 3229.2467 | D31: 3616.766 | E31: 3646.6493 | F31: 7.16408 | G31: 6.3160071 | H31: 6.0540435 | I31: 145.6042 | J31: 161.29538 | K31: 167.33983 | L31: 10.431201 | M31: 10.187428 | N31: 10.130826
B32: Bansí | C32: 630.82185 | D32: 855.70546 | E32: 866.55585 | F32: 0.007742598 | G32: 4.896132 | H32: 4.8348262 | I32: 65882.859 | J32: 157.06003 | K32: 160.29972 | L32: 5.1010449 | M32: 7.6898663 | N32: 7.7502128
B33: CIBanco | C33: 7351.5885 | D33: 8962.1391 | E33: 762.24429 | F33: 2.4806869 | G33: 2.4724452 | H33: 5.9730368 | I33: 134.95543 | J33: 138.06547 | K33: 173.2126 | L33: 3.3478216 | M33: 3.4135931 | N33: 10.346052
B34: Compartamos | C34: 48082.232 | D34: 58883.972 | E34: 59110.491 | F34: 3.0169088 | G34: 3.1850154 | H34: 3.2626805 | I34: 245.33827 | J34: 234.3868 | K34: 236.79986 | L34: 7.4016318 | M34: 7.4652557 | N34: 7.7260229
B35: BIAfirme | C35: 0 | D35: 0 | E35: 0 | F35: n.a. | G35: n.a. | H35: n.a. | I35: - | J35: - | K35: - | L35: - | M35: - | N35: -
B36: Bancrea | C36: 1880.4375 | D36: 2353.7182 | E36: 2384.69 | F36: 1.4921072 | G36: 1.6341196 | H36: 1.6293416 | I36: 151.83533 | J36: 149.13689 | K36: 150.54595 | L36: 2.265546 | M36: 2.437075 | N36: 2.4529077
B37: MUFG Bank | C37: 0 | D37: 0 | E37: 0 | F37: n.a. | G37: n.a. | H37: n.a. | I37: - | J37: - | K37: - | L37: - | M37: - | N37: -
B38: Consubanco | C38: 17497.963 | D38: 21620.371 | E38: 22082.053 | F38: 2.3429083 | G38: 2.3013396 | H38: 2.1519428 | I38: 189.69311 | J38: 194.77049 | K38: 203.41336 | L38: 4.4443356 | M38: 4.4823304 | N38: 4.3773391
B39: Intercam Banco | C39: 395.44953 | D39: 474.9505 | E39: 468.62083 | F39: 0.26509097 | G39: 0.49199548 | H39: 1.3193005 | I39: 1653.6623 | J39: 2566.5374 | K39: 1000.5674 | L39: 4.3837094 | M39: 12.627248 | N39: 13.20049
B40: Autofin | C40: 721.48133 | D40: 573.04424 | E40: 559.64683 | F40: 1.5484001 | G40: 2.2954838 | H40: 2.7261695 | I40: 351.01256 | J40: 242.47833 | K40: 224.31894 | L40: 5.4350789 | M40: 5.5660508 | N40: 6.1153147
B41: Bankaool | C41: 12.009076 | D41: 26.703181 | E41: 24.838977 | F41: 12.766611 | G41: 3.7336563 | H41: 4.4296873 | I41: 95.908038 | J41: 158.47754 | K41: 153.86894 | L41: 12.244206 | M41: 5.9170067 | N41: 6.8159127
B42: BNP Paribas México | C42: 0 | D42: 0 | E42: 0 | F42: n.a. | G42: n.a. | H42: n.a. | I42: - | J42: - | K42: - | L42: - | M42: - | N42: -
B43: Inmobiliario Mexicano | C43: 0 | D43: 0 | E43: 0 | F43: n.a. | G43: n.a. | H43: n.a. | I43: - | J43: - | K43: - | L43: - | M43: - | N43: -
B44: Mizuho Bank | C44: 0 | D44: 0 | E44: 0 | F44: n.a. | G44: n.a. | H44: n.a. | I44: - | J44: - | K44: - | L44: - | M44: - | N44: -
B45: ICBC | C45: 0 | D45: 0 | E45: 0 | F45: n.a. | G45: n.a. | H45: n.a. | I45: - | J45: - | K45: - | L45: - | M45: - | N45: -
B46: Banco Covalto | C46: 0 | D46: 0 | E46: 0 | F46: n.a. | G46: n.a. | H46: n.a. | I46: - | J46: - | K46: - | L46: - | M46: - | N46: -
B47: Openbank | C47: 0 | D47: 137.80434 | E47: 181.24835 | F47: n.a. | G47: 0.90948808 | H47: 2.3362166 | I47: - | J47: 1416.6733 | K47: 749.53558 | L47: - | M47: 12.884475 | N47: 17.510775
B48: Volkswagen Bank | C48: 5018.8679 | D48: 7276.972 | E48: 7404.2091 | F48: 1.0018261 | G48: 1.0732016 | H48: 1.1170978 | I48: 278.02668 | J48: 210.49931 | K48: 249.91953 | L48: 2.7853438 | M48: 2.2590819 | N48: 2.7918457
B49: Bank of China | C49: 0 | D49: 0 | E49: 0 | F49: n.a. | G49: n.a. | H49: n.a. | I49: - | J49: - | K49: - | L49: - | M49: - | N49: -
B50: Shinhan | C50: 0 | D50: 0 | E50: 0 | F50: n.a. | G50: n.a. | H50: n.a. | I50: - | J50: - | K50: - | L50: - | M50: - | N50: -
B51: Banco Ualá | C51: 240.61451 | D51: 498.93344 | E51: 563.71402 | F51: 17.303965 | G51: 10.301717 | H51: 10.098672 | I51: 185.23632 | J51: 237.09834 | K51: 232.49745 | L51: 32.053228 | M51: 24.425198 | N51: 23.479155
B52: Banco S3 | C52: 0 | D52: 0 | E52: 0 | F52: n.a. | G52: n.a. | H52: n.a. | I52: - | J52: - | K52: - | L52: - | M52: - | N52: -
B53: KEB Hana México | C53: 0 | D53: 0 | E53: 0 | F53: n.a. | G53: n.a. | H53: n.a. | I53: - | J53: - | K53: - | L53: - | M53: - | N53: -
B54: Banco Bineo | C54: 43.474256 | D54: 13.728232 | E54: 9.8025796 | F54: 1.7710431 | G54: 41.156656 | H54: 42.710186 | I54: 634.09941 | J54: 98.108709 | K54: 94.337196 | L54: 11.230174 | M54: 40.378264 | N54: 40.291592
B55: Dondé Banco | C55: 0 | D55: 0 | E55: 0 | F55: n.a. | G55: n.a. | H55: n.a. | I55: - | J55: - | K55: - | L55: - | M55: - | N55: -
B56: Credit Suisse | C56: 0 | D56: 0 | E56: 0 | F56: n.a. | G56: n.a. | H56: n.a. | I56: - | J56: - | K56: - | L56: - | M56: - | N56: -
B57: Hey Banco | C57: 0 | D57: 0 | E57: 0 | F57: n.a. | G57: n.a. | H57: n.a. | I57: - | J57: - | K57: - | L57: - | M57: - | N57: -
B58: Pagatodo | C58: 0 | D58: 0 | E58: 0 | F58: n.a. | G58: n.a. | H58: n.a. | I58: - | J58: - | K58: - | L58: - | M58: - | N58: -
B59: Forjadores | C59: 500.11043 | D59: 381.86234 | E59: 404.2503 | F59: 6.3565857 | G59: 9.7035952 | H59: 8.4306326 | I59: 141.15239 | J59: 117.05369 | K59: 126.12129 | L59: 8.9724728 | M59: 11.358417 | N59: 10.632823

Sheet CCCTC
B2: Cartera de crédito al consumo
B3: Millones de pesos y porcentajes
C5: Tarjeta de crédito (MDP) 1/ | F5: IMOR (%) 5/ | I5: ICOR (%) 6/ | L5: Pérdida esperada (%) 7/
C6: 45505 | D6: 45839 | E6: 45870 | F6: =C6 -> 45505 | G6: =D6 -> 45839 | H6: =E6 -> 45870 | I6: =C6 -> 45505 | J6: =D6 -> 45839 | K6: =E6 -> 45870 | L6: =C6 -> 45505 | M6: =D6 -> 45839 | N6: =E6 -> 45870
B7: Sistema */ | C7: 595588.51 | D7: 658350.58 | E7: 666604.23 | F7: 3.3972098 | G7: 3.2697198 | H7: 3.2312751 | I7: 310.11277 | J7: 325.30862 | K7: 326.84425 | L7: 10.535181 | M7: 10.63668 | N7: 10.561237
B8: BBVA México | C8: 191035.05 | D8: 214347.95 | E8: 217244.66 | F8: 2.8856788 | G8: 2.6645707 | H8: 2.6449774 | I8: 327.67322 | J8: 371.59516 | K8: 376.43989 | L8: 9.4555966 | M8: 9.9014156 | N8: 9.9567499
B9: Santander | C9: 82132.383 | D9: 82579.934 | E9: 82812.449 | F9: 4.0547684 | G9: 4.0030479 | H9: 3.7593093 | I9: 294.87304 | J9: 294.81869 | K9: 306.96554 | L9: 11.956419 | M9: 11.801734 | N9: 11.539784
B10: Banorte | C10: 59978.822 | D10: 68957.995 | E10: 70458.26 | F10: 2.7336096 | G10: 3.0251406 | H10: 2.8072347 | I10: 338.81125 | J10: 319.77149 | K10: 341.57205 | L10: 9.2617769 | M10: 9.6735369 | N10: 9.5887292
B11: Banamex | C11: 134210.3 | D11: 153359.24 | E11: 156264.06 | F11: 3.0374231 | G11: 3.2139626 | H11: 3.2361493 | I11: 295.95425 | J11: 285.37423 | K11: 280.48968 | L11: 8.9893827 | M11: 9.171821 | N11: 9.0770649
B12: HSBC | C12: 43042.346 | D12: 42937.521 | E12: 42449.457 | F12: 3.2296492 | G12: 3.9009822 | H12: 4.1714877 | I12: 409.13967 | J12: 368.07781 | K12: 343.04595 | L12: 13.213776 | M12: 14.35865 | N12: 14.31012
B13: Scotiabank | C13: 11578.879 | D13: 13421.879 | E13: 13630.179 | F13: 2.7495386 | G13: 2.6308271 | H13: 2.6924766 | I13: 438.10881 | J13: 481.9732 | K13: 467.10596 | L13: 12.045971 | M13: 12.679882 | N13: 12.576719
B14: Inbursa | C14: 14990.243 | D14: 16529.981 | E14: 16697.374 | F14: 1.236643 | G14: 1.4187997 | H14: 1.4417579 | I14: 844.13834 | J14: 746.67908 | K14: 729.06756 | L14: 10.438978 | M14: 10.59388 | N14: 10.511389
B15: Citi México | C15: 0 | D15: 0 | E15: 0 | F15: n.a. | G15: n.a. | H15: n.a. | I15: - | J15: - | K15: - | L15: - | M15: - | N15: -
B16: Banco del Bajío | C16: 2676.529 | D16: 3029.7871 | E16: 3050.0896 | F16: 2.9738109 | G16: 2.9798901 | H16: 3.1106177 | I16: 398.26053 | J16: 390.5011 | K16: 363.86373 | L16: 11.843515 | M16: 11.636503 | N16: 11.31841
B17: Banco Azteca | C17: 7999.3383 | D17: 6666.9365 | E17: 6580.2363 | F17: 7.8810509 | G17: 7.3743289 | H17: 7.3829853 | I17: 268.47954 | J17: 288.7011 | K17: 285.34312 | L17: 21.159009 | M17: 21.289769 | N17: 21.06684
B18: Afirme | C18: 1535.0874 | D18: 1737.4808 | E18: 1769.0786 | F18: 3.2461874 | G18: 3.0269642 | H18: 3.5003377 | I18: 475.18258 | J18: 512.6568 | K18: 444.18598 | L18: 15.425317 | M18: 15.517938 | N18: 15.548009
B19: Monex | C19: 0 | D19: 0 | E19: 0 | F19: n.a. | G19: n.a. | H19: n.a. | I19: - | J19: - | K19: - | L19: - | M19: - | N19: -
B20: Banregio | C20: 5969.0448 | D20: 6332.5415 | E20: 6366.2649 | F20: 4.1185566 | G20: 3.4681109 | H20: 3.4412151 | I20: 327.96 | J20: 384.03489 | K20: 383.53928 | L20: 13.507218 | M20: 13.318756 | N20: 13.198411
B21: J.P. Morgan | C21: 0 | D21: 0 | E21: 0 | F21: n.a. | G21: n.a. | H21: n.a. | I21: - | J21: - | K21: - | L21: - | M21: - | N21: -
B22: Bank of America | C22: 0 | D22: 0 | E22: 0 | F22: n.a. | G22: n.a. | H22: n.a. | I22: - | J22: - | K22: - | L22: - | M22: - | N22: -
B23: Invex | C23: 25286.534 | D23: 32471.908 | E23: 32900.523 | F23: 2.1036739 | G23: 2.4627617 | H23: 2.705072 | I23: 334.14863 | J23: 301.17773 | K23: 274.89462 | L23: 7.0293976 | M23: 7.4172897 | N23: 7.4360972
B24: BanCoppel | C24: 14660.265 | D24: 14945.64 | E24: 15244.317 | F24: 14.873429 | G24: 10.08453 | H24: 9.4060602 | I24: 166.83966 | J24: 212.47552 | K24: 223.00318 | L24: 24.814779 | M24: 21.427158 | N24: 20.975813
B25: Multiva | C25: 0 | D25: 0 | E25: 0 | F25: n.a. | G25: n.a. | H25: n.a. | I25: - | J25: - | K25: - | L25: - | M25: - | N25: -
B26: Banca Mifel | C26: 283.0522 | D26: 431.77166 | E26: 430.31971 | F26: 8.1664855 | G26: 5.3051704 | H26: 5.8291142 | I26: 242.77087 | J26: 324.49837 | K26: 329.71596 | L26: 19.825847 | M26: 17.215191 | N26: 19.21952
B27: Barclays | C27: 0 | D27: 0 | E27: 0 | F27: n.a. | G27: n.a. | H27: n.a. | I27: - | J27: - | K27: - | L27: - | M27: - | N27: -
B28: Banco Base | C28: 0 | D28: 0 | E28: 0 | F28: n.a. | G28: n.a. | H28: n.a. | I28: - | J28: - | K28: - | L28: - | M28: - | N28: -
B29: Sabadell | C29: 0 | D29: 0 | E29: 0 | F29: n.a. | G29: n.a. | H29: n.a. | I29: - | J29: - | K29: - | L29: - | M29: - | N29: -
B30: Ve por Más | C30: 0 | D30: 0 | E30: 0 | F30: n.a. | G30: n.a. | H30: n.a. | I30: - | J30: - | K30: - | L30: - | M30: - | N30: -
B31: Actinver | C31: 0 | D31: 0 | E31: 0 | F31: n.a. | G31: n.a. | H31: n.a. | I31: - | J31: - | K31: - | L31: - | M31: - | N31: -
B32: Bansí | C32: 0 | D32: 0 | E32: 0 | F32: n.a. | G32: n.a. | H32: n.a. | I32: - | J32: - | K32: - | L32: - | M32: - | N32: -
B33: CIBanco | C33: 0 | D33: 0 | E33: 0 | F33: n.a. | G33: n.a. | H33: n.a. | I33: - | J33: - | K33: - | L33: - | M33: - | N33: -
B34: Compartamos | C34: 0 | D34: 0 | E34: 0 | F34: n.a. | G34: n.a. | H34: n.a. | I34: - | J34: - | K34: - | L34: - | M34: - | N34: -
B35: BIAfirme | C35: 0 | D35: 0 | E35: 0 | F35: n.a. | G35: n.a. | H35: n.a. | I35: - | J35: - | K35: - | L35: - | M35: - | N35: -
B36: Bancrea | C36: 0 | D36: 0 | E36: 0 | F36: n.a. | G36: n.a. | H36: n.a. | I36: - | J36: - | K36: - | L36: - | M36: - | N36: -
B37: MUFG Bank | C37: 0 | D37: 0 | E37: 0 | F37: n.a. | G37: n.a. | H37: n.a. | I37: - | J37: - | K37: - | L37: - | M37: - | N37: -
B38: Consubanco | C38: 0 | D38: 0 | E38: 0 | F38: n.a. | G38: n.a. | H38: n.a. | I38: - | J38: - | K38: - | L38: - | M38: - | N38: -
... B46: Banco Covalto | C46: 0 | D46: 0 | E46: 0 | F46: n.a. | G46: n.a. | H46: n.a. | I46: - | J46: - | K46: - | L46: - | M46: - | N46: -
B47: Openbank | C47: 0 | D47: 137.80434 | E47: 181.24835 | F47: n.a. | G47: 0.90948808 | H47: 2.3362166 | I47: - | J47: 1416.6733 | K47: 749.53558 | L47: - | M47: 12.884475 | N47: 17.510775
B48: Volkswagen Bank | C48: 0 | D48: 0 | E48: 0 | F48: n.a. | G48: n.a. | H48: n.a. | I48: - | J48: - | K48: - | L48: - | M48: - | N48: -
B49: Bank of China | C49: 0 | D49: 0 | E49: 0 | F49: n.a. | G49: n.a. | H49: n.a. | I49: - | J49: - | K49: - | L49: - | M49: - | N49: -
B50: Shinhan | C50: 0 | D50: 0 | E50: 0 | F50: n.a. | G50: n.a. | H50: n.a. | I50: - | J50: - | K50: - | L50: - | M50: - | N50: -
B51: Banco Ualá | C51: 210.64223 | D51: 462.21036 | E51: 525.71164 | F51: 18.625489 | G51: 10.005616 | H51: 9.9515985 | I51: 182.69287 | J51: 247.53224 | K51: 239.40984 | L51: 34.02744 | M51: 24.767125 | N51: 23.825106
B52: Banco S3 | C52: 0 | D52: 0 | E52: 0 | F52: n.a. | G52: n.a. | H52: n.a. | I52: - | J52: - | K52: - | L52: - | M52: - | N52: -
B53: KEB Hana México | C53: 0 | D53: 0 | E53: 0 | F53: n.a. | G53: n.a. | H53: n.a. | I53: - | J53: - | K53: - | L53: - | M53: - | N53: -
B54: Banco Bineo | C54: 0 | D54: 0 | E54: 0 | F54: n.a. | G54: n.a. | H54: n.a. | I54: - | J54: - | K54: - | L54: - | M54: - | N54: -
B55: Dondé Banco | C55: 0 | D55: 0 | E55: 0 | F55: n.a. | G55: n.a. | H55: n.a. | I55: - | J55: - | K55: - | L55: - | M55: - | N55: -
B56: Credit Suisse | C56: 0 | D56: 0 | E56: 0 | F56: n.a. | G56: n.a. | H56: n.a. | I56: - | J56: - | K56: - | L56: - | M56: - | N56: -
B57: Hey Banco | C57: 0 | D57: 0 | E57: 0 | F57: n.a. | G57: n.a. | H57: n.a. | I57: - | J57: - | K57: - | L57: - | M57: - | N57: -
B58: Pagatodo | C58: 0 | D58: 0 | E58: 0 | F58: n.a. | G58: n.a. | H58: n.a. | I58: - | J58: - | K58: - | L58: - | M58: - | N58: -
B59: Forjadores | C59: 0 | D59: 0 | E59: 0 | F59: n.a. | G59: n.a. | H59: n.a. | I59: - | J59: - | K59: - | L59: - | M59: - | N59: -

Sheet CCCN
B2: Cartera de crédito al consumo
B3: Millones de pesos y porcentajes
C5: Cartera de nómina (MDP) 1/ | F5: IMOR (%) 5/ | I5: ICOR (%) 6/ | L5: Pérdida esperada (%) 7/
C6: 45505 | D6: 45839 | E6: 45870 | F6: =C6 -> 45505 | G6: =D6 -> 45839 | H6: =E6 -> 45870 | I6: =C6 -> 45505 | J6: =D6 -> 45839 | K6: =E6 -> 45870 | L6: =C6 -> 45505 | M6: =D6 -> 45839 | N6: =E6 -> 45870
B7: Sistema */ | C7: 395817.13 | D7: 422658.79 | E7: 428009.69 | F7: 2.6317871 | G7: 2.7954448 | H7: 2.6887651 | I7: 271.00977 | J7: 253.78037 | K7: 262.84806 | L7: 7.1324001 | M7: 7.09429 | N7: 7.0673669
B8: BBVA México | C8: 154723.06 | D8: 168966.31 | E8: 171956.42 | F8: 2.3968523 | G8: 2.6142045 | H8: 2.540234 | I8: 301.48098 | J8: 260.55378 | K8: 267.85976 | L8: 7.2260537 | M8: 6.8114087 | N8: 6.8042646
B9: Santander | C9: 54249.736 | D9: 55425.954 | E9: 55919.909 | F9: 3.291739 | G9: 3.5071355 | H9: 3.0760877 | I9: 221.2627 | J9: 200.21912 | K9: 227.80564 | L9: 7.2833906 | M9: 7.021956 | N9: 7.0075012
B10: Banorte | C10: 82770.17 | D10: 89295.962 | E10: 89913.965 | F10: 2.5590556 | G10: 2.5852445 | H10: 2.4766463 | I10: 270.26509 | J10: 256.39646 | K10: 271.87374 | L10: 6.916234 | M10: 6.6284754 | N10: 6.7333509
B11: Banamex | C11: 60221.687 | D11: 66865.377 | E11: 67890.425 | F11: 2.7374157 | G11: 3.1530465 | H11: 3.1992817 | I11: 226.65812 | J11: 193.71842 | K11: 194.03448 | L11: 6.2045748 | M11: 6.1080318 | N11: 6.2077096
B12: HSBC | C12: 33246.195 | D12: 30570.598 | E12: 30601.229 | F12: 2.7070982 | G12: 2.3533093 | H12: 2.3170599 | I12: 321.71601 | J12: 375.07078 | K12: 379.01524 | L12: 8.7091684 | M12: 8.8265757 | N12: 8.7820102
B13: Scotiabank | C13: 1958.5995 | D13: 1633.7834 | E13: 1610.0103 | F13: 2.4557355 | G13: 3.9720694 | H13: 3.0702257 | I13: 253.16777 | J13: 155.97108 | K13: 210.22195 | L13: 6.2171309 | M13: 6.1952797 | N13: 6.4542884
B14: Inbursa | C14: 1764.8226 | D14: 2434.2377 | E14: 2532.7329 | F14: 1.8167333 | G14: 3.0363816 | H14: 2.9888912 | I14: 386.91403 | J14: 275.91123 | K14: 287.78523 | L14: 7.029196 | M14: 8.3777179 | N14: 8.6015873
B15: Citi México | C15: 0 | D15: 0 | E15: 0 | F15: n.a. | G15: n.a. | H15: n.a. | I15: - | J15: - | K15: - | L15: - | M15: - | N15: -
B16: Banco del Bajío | C16: 2405.3184 | D16: 2660.5293 | E16: 2719.8843 | F16: 2.1424865 | G16: 2.3782292 | H16: 2.0608559 | I16: 333.94405 | J16: 290.84805 | K16: 333.47784 | L16: 7.1547061 | M16: 6.9170331 | N16: 6.8724978
B17: Banco Azteca | C17: 2039.5721 | D17: 1991.5408 | E17: 1987.9961 | F17: 3.2403003 | G17: 2.6782164 | H17: 2.6138524 | I17: 231.35114 | J17: 271.41062 | K17: 283.27652 | L17: 7.4964719 | M17: 7.2689638 | N17: 7.4044301
B18: Afirme | C18: 2325.2416 | D18: 2281.2487 | E18: 2281.3974 | F18: 2.3335846 | G18: 1.9089713 | H18: 2.2978697 | I18: 300.18061 | J18: 402.18176 | K18: 314.58736 | L18: 7.0049686 | M18: 7.6775343 | N18: 7.2288078
B19: Monex | C19: 0 | D19: 0 | E19: 0 | F19: n.a. | G19: n.a. | H19: n.a. | I19: - | J19: - | K19: - | L19: - | M19: - | N19: -
B20: Banregio | C20: 15.024821 | D20: 36.121764 | E20: 39.12632 | F20: 3.950559 | G20: 0.77776982 | H20: 0.72701098 | I20: 228.97033 | J20: 828.78911 | K20: 904.3259 | L20: 9.0456081 | M20: 6.4460716 | N20: 6.5745486
B21: J.P. Morgan | C21: 0 | D21: 0 | E21: 0 | F21: n.a. | G21: n.a. | H21: n.a. | I21: - | J21: - | K21: - | L21: - | M21: - | N21: -
B22: Bank of America | C22: 0 | D22: 0 | E22: 0 | F22: n.a. | G22: n.a. | H22: n.a. | I22: - | J22: - | K22: - | L22: - | M22: - | N22: -
B23: Invex | C23: 0 | D23: 0 | E23: 0 | F23: n.a. | G23: n.a. | H23: n.a. | I23: - | J23: - | K23: - | L23: - | M23: - | N23: -
B24: BanCoppel | C24: 54.6224 | D24: 443.63179 | E24: 501.79691 | F24: 6.3228602 | G24: 4.0409498 | H24: 5.0126781 | I24: 166.39167 | J24: 165.94737 | K24: 133.24261 | L24: 10.520712 | M24: 6.7058501 | N24: 6.6790229
B25: Multiva | C25: 40.400307 | D25: 51.129241 | E25: 52.59656 | F25: 0.095170069 | G25: 0.99077356 | H25: 1.4484559 | I25: 5567.0108 | J25: 653.42467 | K25: 454.80772 | L25: 5.2981281 | M25: 6.4739588 | N25: 6.5876894
B26: Banca Mifel | C26: 0.156805 | D26: 0.082928 | E26: 0.080288 | F26: 0 | G26: 0 | H26: 0 | I26: - | J26: - | K26: - | L26: 9.4812028 | M26: 11.765628 | N26: 15.957553
B27: Barclays | C27: 0 | D27: 0 | E27: 0 | F27: n.a. | G27: n.a. | H27: n.a. | I27: - | J27: - | K27: - | L27: - | M27: - | N27: -
B28: Banco Base | C28: 0 | D28: 0 | E28: 0 | F28: n.a. | G28: n.a. | H28: n.a. | I28: - | J28: - | K28: - | L28: - | M28: - | N28: -
B29: Sabadell | C29: 0 | D29: 0 | E29: 0 | F29: n.a. | G29: n.a. | H29: n.a. | I29: - | J29: - | K29: - | L29: - | M29: - | N29: -
B30: Ve por Más | C30: 0 | D30: 0 | E30: 0 | F30: n.a. | G30: n.a. | H30: n.a. | I30: - | J30: - | K30: - | L30: - | M30: - | N30: -
B31: Actinver | C31: 0 | D31: 0 | E31: 0 | F31: n.a. | G31: n.a. | H31: n.a. | I31: - | J31: - | K31: - | L31: - | M31: - | N31: -
B32: Bansí | C32: 0 | D32: 0 | E32: 0 | F32: n.a. | G32: n.a. | H32: n.a. | I32: - | J32: - | K32: - | L32: - | M32: - | N32: -
B33: CIBanco | C33: 0 | D33: 0 | E33: 0 | F33: n.a. | G33: n.a. | H33: n.a. | I33: - | J33: - | K33: - | L33: - | M33: - | N33: -
B34: Compartamos | C34: 0 | D34: 0 | E34: 0 | F34: n.a. | G34: n.a. | H34: n.a. | I34: - | J34: - | K34: - | L34: - | M34: - | N34: -
B35: BIAfirme | C35: 0 | D35: 0 | E35: 0 | F35: n.a. | G35: n.a. | H35: n.a. | I35: - | J35: - | K35: - | L35: - | M35: - | N35: -
B36: Bancrea | C36: 0 | D36: 0 | E36: 0 | F36: n.a. | G36: n.a. | H36: n.a. | I36: - | J36: - | K36: - | L36: - | M36: - | N36: -
B37: MUFG Bank | C37: 0 | D37: 0 | E37: 0 | F37: n.a. | G37: n.a. | H37: n.a. | I37: - | J37: - | K37: - | L37: - | M37: - | N37: -
B38: Consubanco | C38: 0 | D38: 0 | E38: 0 | F38: n.a. | G38: n.a. | H38: n.a. | I38: - | J38: - | K38: - | L38: - | M38: - | N38: -
B39: Intercam Banco | C39: 0 | D39: 0 | E39: 0 | F39: n.a. | G39: n.a. | H39: n.a. | I39: - | J39: - | K39: - | L39: - | M39: - | N39: -
B40: Autofin | C40: 2.0031087 | D40: 1.4574089 | E40: 1.3777755 | F40: 0.3530737 | G40: 11.126392 | H40: 12.761438 | I40: 1904.613 | J40: 78.352494 | K40: 76.383584 | L40: 6.7246874 | M40: 8.7178053 | N40: 9.7476436
B41: Bankaool | C41: 0.522874 | D41: 0.82494 | E41: 0.745488 | F41: 4.8021129 | G41: 15.106432 | H41: 10.985556 | I41: 141.1008 | J41: 74.307289 | K41: 92.795741 | L41: 6.7758198 | M41: 11.22518 | N41: 10.194128
B42: BNP Paribas México | C42: 0 | D42: 0 | E42: 0 | F42: n.a. | G42: n.a. | H42: n.a. | I42: - | J42: - | K42: - | L42: - | M42: - | N42: -
B43: Inmobiliario Mexicano | C43: 0 | D43: 0 | E43: 0 | F43: n.a. | G43: n.a. | H43: n.a. | I43: - | J43: - | K43: - | L43: - | M43: - | N43: -
B44: Mizuho Bank | C44: 0 | D44: 0 | E44: 0 | F44: n.a. | G44: n.a. | H44: n.a. | I44: - | J44: - | K44: - | L44: - | M44: - | N44: -
B45: ICBC | C45: 0 | D45: 0 | E45: 0 | F45: n.a. | G45: n.a. | H45: n.a. | I45: - | J45: - | K45: - | L45: - | M45: - | N45: -
B46: Banco Covalto | C46: 0 | D46: 0 | E46: 0 | F46: n.a. | G46: n.a. | H46: n.a. | I46: - | J46: - | K46: - | L46: - | M46: - | N46: -
B47: Openbank | C47: 0 | D47: 0 | E47: 0 | F47: n.a. | G47: n.a. | H47: n.a. | I47: - | J47: - | K47: - | L47: - | M47: - | N47: -
B48: Volkswagen Bank | C48: 0 | D48: 0 | E48: 0 | F48: n.a. | G48: n.a. | H48: n.a. | I48: - | J48: - | K48: - | L48: - | M48: - | N48: -
B49: Bank of China | C49: 0 | D49: 0 | E49: 0 | F49: n.a. | G49: n.a. | H49: n.a. | I49: - | J49: - | K49: - | L49: - | M49: - | N49: -
B50: Shinhan | C50: 0 | D50: 0 | E50: 0 | F50: n.a. | G50: n.a. | H50: n.a. | I50: - | J50: - | K50: - | L50: - | M50: - | N50: -
B51: Banco Ualá | C51: 0 | D51: 0 | E51: 0 | F51: n.a. | G51: n.a. | H51: n.a. | I51: - | J51: - | K51: - | L51: - | M51: - | N51: -
B52: Banco S3 | C52: 0 | D52: 0 | E52: 0 | F52: n.a. | G52: n.a. | H52: n.a. | I52: - | J52: - | K52: - | L52: - | M52: - | N52: -
B53: KEB Hana México | C53: 0 | D53: 0 | E53: 0 | F53: n.a. | G53: n.a. | H53: n.a. | I53: - | J53: - | K53: - | L53: - | M53: - | N53: -
... B59: Forjadores | C59: 0 | D59: 0 | E59: 0 | F59: n.a. | G59: n.a. | H59: n.a. | I59: - | J59: - | K59: - | L59: - | M59: - | N59: -

Sheet CCCnrP
B2: Cartera de crédito al consumo
B3: Millones de pesos y porcentajes
C5: Créditos personales (MDP) 1/ | F5: IMOR (%) 5/ | I5: ICOR (%) 6/ | L5: Pérdida esperada (%) 7/
C6: 45505 | D6: 45839 | E6: 45870 | F6: =C6 -> 45505 | G6: =D6 -> 45839 | H6: =E6 -> 45870 | I6: =C6 -> 45505 | J6: =D6 -> 45839 | K6: =E6 -> 45870 | L6: =C6 -> 45505 | M6: =D6 -> 45839 | N6: =E6 -> 45870
B7: Sistema */ | C7: 249085.44 | D7: 286390.18 | E7: 290850.97 | F7: 4.4382958 | G7: 4.6233246 | H7: 4.6711707 | I7: 207.17755 | J7: 208.17168 | K7: 210.62007 | L7: 9.1951528 | M7: 9.6244523 | N7: 9.8384231
B8: BBVA México | C8: 67195.446 | D8: 76095.132 | E8: 77276.726 | F8: 4.5945892 | G8: 4.7398545 | H8: 4.8869911 | I8: 221.73933 | J8: 217.7479 | K8: 208.50246 | L8: 10.188011 | M8: 10.320934 | N8: 10.189497
B9: Santander | C9: 14764.013 | D9: 13823.56 | E9: 13733.391 | F9: 4.8127836 | G9: 5.2679381 | H9: 4.6933102 | I9: 187.97051 | J9: 241.22897 | K9: 261.69705 | L9: 9.0466138 | M9: 12.707793 | N9: 12.282254
B10: Banorte | C10: 1099.5086 | D10: 1109.9151 | E10: 1123.9648 | F10: 5.8531007 | G10: 4.6160801 | H10: 3.4041126 | I10: 198.92726 | J10: 221.90666 | K10: 263.37458 | L10: 11.643413 | M10: 10.243389 | N10: 8.9655674
B11: Banamex | C11: 19878.802 | D11: 24259.242 | E11: 24590.137 | F11: 3.2821579 | G11: 4.011446 | H11: 4.0755411 | I11: 204.09552 | J11: 185.78824 | K11: 184.44795 | L11: 6.6987371 | M11: 7.452795 | N11: 7.5172522
B12: HSBC | C12: 12719.526 | D12: 12202.198 | E12: 12057.385 | F12: 2.4347592 | G12: 3.1953135 | H12: 3.2101963 | I12: 389.98346 | J12: 334.09163 | K12: 329.60555 | L12: 9.4951582 | M12: 10.675275 | N12: 10.580985
B13: Scotiabank | C13: 7731.2057 | D13: 9396.2079 | E13: 9567.4264 | F13: 3.0722917 | G13: 3.4919317 | H13: 3.7252629 | I13: 323.23086 | J13: 278.98091 | K13: 261.10658 | L13: 9.930595 | M13: 9.741823 | N13: 9.7269067
B14: Inbursa | C14: 7164.8581 | D14: 8794.4087 | E14: 8848.2235 | F14: 3.8526571 | G14: 3.5211182 | H14: 3.5337637 | I14: 207.07012 | J14: 198.98134 | K14: 200.17069 | L14: 7.9777017 | M14: 7.0063681 | N14: 7.0735591
B15: Citi México | C15: 0 | D15: 0 | E15: 0 | F15: n.a. | G15: n.a. | H15: n.a. | I15: - | J15: - | K15: - | L15: - | M15: - | N15: -
B16: Banco del Bajío | C16: 1186.9983 | D16: 1413.4348 | E16: 1425.6904 | F16: 1.7396714 | G16: 2.2971461 | H16: 1.6419859 | I16: 454.14025 | J16: 354.74577 | K16: 489.893 | L16: 7.9005479 | M16: 8.1490288 | N16: 8.0439738
B17: Banco Azteca | C17: 70203.942 | D17: 83852.352 | E17: 85664.188 | F17: 4.5166501 | G17: 5.5903025 | H17: 5.7707198 | I17: 203.11988 | J17: 188.01614 | K17: 198.66792 | L17: 9.1742143 | M17: 10.510671 | N17: 11.464569
B18: Afirme | C18: 2571.4769 | D18: 2461.0094 | E18: 2469.6497 | F18: 3.6732326 | G18: 3.0164433 | H18: 3.3756415 | I18: 274.40968 | J18: 320.70824 | K18: 299.034 | L18: 10.079706 | M18: 9.673982 | N18: 10.094316
B19: Monex | C19: 0 | D19: 0 | E19: 0 | F19: n.a. | G19: n.a. | H19: n.a. | I19: - | J19: - | K19: - | L19: - | M19: - | N19: -
B20: Banregio | C20: 955.83241 | D20: 1060.5314 | E20: 1079.7272 | F20: 4.1307715 | G20: 3.0110695 | H20: 2.9671136 | I20: 271.85158 | J20: 337.31942 | K20: 344.67925 | L20: 11.229568 | M20: 10.156922 | N20: 10.227025
B21: J.P. Morgan | C21: 0 | D21: 0 | E21: 0 | F21: n.a. | G21: n.a. | H21: n.a. | I21: - | J21: - | K21: - | L21: - | M21: - | N21: -
B22: Bank of America | C22: 0 | D22: 0 | E22: 0 | F22: n.a. | G22: n.a. | H22: n.a. | I22: - | J22: - | K22: - | L22: - | M22: - | N22: -
B23: Invex | C23: 194.24051 | D23: 180.67476 | E23: 179.59878 | F23: 4.591416 | G23: 0 | H23: 0 | I23: 182.16326 | J23: - | K23: - | L23: 8.3638731 | M23: 3.4657841 | N23: 4.521959
B24: BanCoppel | C24: 8101.111 | D24: 7137.7711 | E24: 7174.7753 | F24: 17.522937 | G24: 11.569627 | H24: 11.134483 | I24: 127.08899 | J24: 154.52612 | K24: 159.44861 | L24: 22.269724 | M24: 17.878095 | N24: 17.753779
B25: Multiva | C25: 5086.6651 | D25: 6186.1077 | E25: 6357.9887 | F25: 1.8364383 | G25: 1.1864286 | H25: 1.2333216 | I25: 204.07266 | J25: 273.27455 | K25: 252.56001 | L25: 3.7476685 | M25: 3.2422074 | N25: 3.1148772
B26: Banca Mifel | C26: 2.163429 | D26: 1.970123 | E26: 2.035643 | F26: 0 | G26: 4.2688198 | H26: 3.8838834 | I26: - | J26: 231.65242 | K26: 226.83337 | L26: 6.1538419 | M26: 9.8888242 | N26: 8.8099436
B27: Barclays | C27: 0 | D27: 0 | E27: 0 | F27: n.a. | G27: n.a. | H27: n.a. | I27: - | J27: - | K27: - | L27: - | M27: - | N27: -
B28: Banco Base | C28: 0 | D28: 0 | E28: 0 | F28: n.a. | G28: n.a. | H28: n.a. | I28: - | J28: - | K28: - | L28: - | M28: - | N28: -
B29: Sabadell | C29: 13.121385 | D29: 11.580522 | E29: 10.144499 | F29: 9.8176755 | G29: 1.3422538 | H29: 1.532259 | I29: 178.15062 | J29: 735.94184 | K29: 691.1001 | L29: 17.49025 | M29: 9.8782076 | N29: 10.589444
B30: Ve por Más | C30: 9.266753 | D30: 7.417216 | E30: 7.304874 | F30: 2.5782062 | G30: 21.191644 | H30: 24.977734 | I30: 333.19577 | J30: 126.8363 | K30: 102.52281 | L30: 8.5904739 | M30: 26.878697 | N30: 25.607875
B31: Actinver | C31: 2884.3844 | D31: 3199.7647 | E31: 3235.2035 | F31: 7.7394192 | G31: 6.8902744 | H31: 6.5943588 | I31: 135.92439 | J31: 155.43903 | K31: 160.77367 | L31: 10.519759 | M31: 10.710175 | N31: 10.601992
B32: Bansí | C32: 629.11332 | D32: 854.44588 | E32: 865.35275 | F32: 0.006709761 | G32: 4.9025737 | H32: 4.8407819 | I32: 76185.812 | J32: 157.06016 | K32: 160.30077 | L32: 5.1118859 | M32: 7.69999 | N32: 7.7598104
B33: CIBanco | C33: 618.10258 | D33: 523.3974 | E33: 510.7304 | F33: 7.365132 | G33: 8.1356795 | H33: 8.3383606 | I33: 128.75434 | J33: 150.30078 | K33: 167.26727 | L33: 9.4829267 | M33: 12.22799 | N33: 13.947348
B34: Compartamos | C34: 6205.3447 | D34: 9228.5462 | E34: 9571.6831 | F34: 2.5413831 | G34: 2.9597687 | H34: 2.9572692 | I34: 362.96243 | J34: 319.82091 | K34: 322.2992 | L34: 9.2242661 | M34: 9.4659594 | N34: 9.531255
B35: BIAfirme | C35: 0 | D35: 0 | E35: 0 | F35: n.a. | G35: n.a. | H35: n.a. | I35: - | J35: - | K35: - | L35: - | M35: - | N35: -
B36: Bancrea | C36: 1880.4375 | D36: 2353.7182 | E36: 2384.69 | F36: 1.4921072 | G36: 1.6341196 | H36: 1.6293416 | I36: 151.83533 | J36: 149.13689 | K36: 150.54595 | L36: 2.265546 | M36: 2.437075 | N36: 2.4529077
B37: MUFG Bank | C37: 0 | D37: 0 | E37: 0 | F37: n.a. | G37: n.a. | H37: n.a. | I37: - | J37: - | K37: - | L37: - | M37: - | N37: -
B38: Consubanco | C38: 17497.963 | D38: 21620.371 | E38: 22082.053 | F38: 2.3429083 | G38: 2.3013396 | H38: 2.1519428 | I38: 189.69311 | J38: 194.77049 | K38: 203.41336 | L38: 4.4443356 | M38: 4.4823304 | N38: 4.3773391
B39: Intercam Banco | C39: 395.44953 | D39: 474.9505 | E39: 468.62083 | F39: 0.26509097 | G39: 0.49199548 | H39: 1.3193005 | I39: 1653.6623 | J39: 2566.5374 | K39: 1000.5674 | L39: 4.3837094 | M39: 12.627248 | N39: 13.20049
B40: Autofin | C40: 10.456832 | D40: 28.958102 | E40: 29.818047 | F40: 0.1086659 | G40: 0 | H40: 0 | I40: 7098.2252 | J40: - | K40: - | L40: 7.7133501 | M40: 7.8850478 | N40: 7.9548422
B41: Bankaool | C41: 10.517775 | D41: 22.551151 | E41: 20.844746 | F41: 9.3139946 | G41: 3.8684766 | H41: 4.88561 | I41: 92.382085 | J41: 147.08099 | K41: 142.21396 | L41: 8.6044624 | M41: 5.6897938 | N41: 6.9480194
B42: BNP Paribas México | C42: 0 | D42: 0 | E42: 0 | F42: n.a. | G42: n.a. | H42: n.a. | I42: - | J42: - | K42: - | L42: - | M42: - | N42: -
B43: Inmobiliario Mexicano | C43: 0 | D43: 0 | E43: 0 | F43: n.a. | G43: n.a. | H43: n.a. | I43: - | J43: - | K43: - | L43: - | M43: - | N43: -
B44: Mizuho Bank | C44: 0 | D44: 0 | E44: 0 | F44: n.a. | G44: n.a. | H44: n.a. | I44: - | J44: - | K44: - | L44: - | M44: - | N44: -
B45: ICBC | C45: 0 | D45: 0 | E45: 0 | F45: n.a. | G45: n.a. | H45: n.a. | I45: - | J45: - | K45: - | L45: - | M45: - | N45: -
B46: Banco Covalto | C46: 0 | D46: 0 | E46: 0 | F46: n.a. | G46: n.a. | H46: n.a. | I46: - | J46: - | K46: - | L46: - | M46: - | N46: -
B47: Openbank | C47: 0 | D47: 0 | E47: 0 | F47: n.a. | G47: n.a. | H47: n.a. | I47: - | J47: - | K47: - | L47: - | M47: - | N47: -
B48: Volkswagen Bank | C48: 0 | D48: 0 | E48: 0 | F48: n.a. | G48: n.a. | H48: n.a. | I48: - | J48: - | K48: - | L48: - | M48: - | N48: -
B49: Bank of China | C49: 0 | D49: 0 | E49: 0 | F49: n.a. | G49: n.a. | H49: n.a. | I49: - | J49: - | K49: - | L49: - | M49: - | N49: -
B50: Shinhan | C50: 0 | D50: 0 | E50: 0 | F50: n.a. | G50: n.a. | H50: n.a. | I50: - | J50: - | K50: - | L50: - | M50: - | N50: -
B51: Banco Ualá | C51: 29.972282 | D51: 36.723086 | E51: 38.002379 | F51: 8.0164266 | G51: 14.028551 | H51: 12.133238 | I51: 226.76761 | J51: 143.43313 | K51: 154.06757 | L51: 18.178659 | M51: 20.121591 | N51: 18.693385
B52: Banco S3 | C52: 0 | D52: 0 | E52: 0 | F52: n.a. | G52: n.a. | H52: n.a. | I52: - | J52: - | K52: - | L52: - | M52: - | N52: -
B53: KEB Hana México | C53: 0 | D53: 0 | E53: 0 | F53: n.a. | G53: n.a. | H53: n.a. | I53: - | J53: - | K53: - | L53: - | M53: - | N53: -
B54: Banco Bineo | C54: 43.474256 | D54: 13.728232 | E54: 9.8025796 | F54: 1.7710431 | G54: 41.156656 | H54: 42.710186 | I54: 634.09941 | J54: 98.108709 | K54: 94.337196 | L54: 11.230174 | M54: 40.378264 | N54: 40.291592
B55: Dondé Banco | C55: 0 | D55: 0 | E55: 0 | F55: n.a. | G55: n.a. | H55: n.a. | I55: - | J55: - | K55: - | L55: - | M55: - | N55: -
B56: Credit Suisse | C56: 0 | D56: 0 | E56: 0 | F56: n.a. | G56: n.a. | H56: n.a. | I56: - | J56: - | K56: - | L56: - | M56: - | N56: -
B57: Hey Banco | C57: 0 | D57: 0 | E57: 0 | F57: n.a. | G57: n.a. | H57: n.a. | I57: - | J57: - | K57: - | L57: - | M57: - | N57: -
B58: Pagatodo | C58: 0 | D58: 0 | E58: 0 | F58: n.a. | G58: n.a. | H58: n.a. | I58: - | J58: - | K58: - | L58: - | M58: - | N58: -
B59: Forjadores | C59: 2.051463 | D59: 39.516348 | E59: 65.809828 | F59: 60.478644 | G59: 3.0170146 | H59: 2.7588873 | I59: 86.002626 | J59: 404.81239 | K59: 451.19367 | L59: 52.013222 | M59: 12.213249 | N59: 12.447925

Sheet CCCAut
B2: Cartera de crédito al consumo
B3: Millones de pesos y porcentajes
C5: Automotriz (MDP) 1/ | F5: IMOR (%) 5/ | I5: ICOR (%) 6/ | L5: Pérdida esperada (%) 7/
C6: 45505 | D6: 45839 | E6: 45870 | F6: =C6 -> 45505 | G6: =D6 -> 45839 | H6: =E6 -> 45870 | I6: =C6 -> 45505 | J6: =D6 -> 45839 | K6: =E6 -> 45870 | L6: =C6 -> 45505 | M6: =D6 -> 45839 | N6: =E6 -> 45870
B7: Sistema */ | C7: 273296.36 | D7: 333131.89 | E7: 337003.7 | F7: 1.0043126 | G7: 1.1919643 | H7: 1.1480705 | I7: 215.39467 | J7: 192.26597 | K7: 200.36594 | L7: 2.1632359 | M7: 2.2917417 | N7: 2.3003422
B8: BBVA México | C8: 62485.993 | D8: 74340.891 | E8: 74996.912 | F8: 0.88224483 | G8: 1.0054726 | H8: 1.0099755 | I8: 274.4149 | J8: 249.63264 | K8: 243.77265 | L8: 2.4210113 | M8: 2.5099878 | N8: 2.4620439
B9: Santander | C9: 41581.819 | D9: 57000.872 | E9: 57555.23 | F9: 0.68157328 | G9: 1.1150568 | H9: 0.78202254 | I9: 274.66335 | J9: 190.89386 | K9: 258.35936 | L9: 1.872032 | M9: 2.128575 | N9: 2.0204284
B10: Banorte | C10: 49150.048 | D10: 62949.063 | E10: 64288.668 | F10: 0.49720602 | G10: 0.55035941 | H10: 0.50962628 | I10: 259.34804 | J10: 217.35448 | K10: 230.9296 | L10: 1.2894941 | M10: 1.1962308 | N10: 1.1768779
B11: Banamex | C11: 3.5286211 | D11: 0.19818957 | E11: 0.13802915 | F11: 27.391528 | G11: 57.287662 | H11: 58.596434 | I11: 110.21869 | J11: 83.062806 | K11: 81.29383 | L11: 30.190583 | M11: 47.584739 | N11: 47.635286
B12: HSBC | C12: 15764.892 | D12: 13107.893 | E12: 12864.132 | F12: 1.2296426 | G12: 1.5320433 | H12: 1.6064907 | I12: 232.66095 | J12: 228.71155 | K12: 211.08428 | L12: 2.8608983 | M12: 3.5039599 | N12: 3.3910492
B13: Scotiabank | C13: 23630.246 | D13: 30069.257 | E13: 30562.815 | F13: 1.9985016 | G13: 2.3671141 | H13: 2.3573151 | I13: 149.86595 | J13: 148.61844 | K13: 153.36975 | L13: 2.9950734 | M13: 3.517968 | N13: 3.6154083
B14: Inbursa | C14: 57009.678 | D14: 66786.042 | E14: 67684.978 | F14: 1.0961168 | G14: 1.3223194 | H14: 1.3652786 | I14: 173.10085 | J14: 161.13043 | K14: 163.47648 | L14: 1.8973874 | M14: 2.1306589 | N14: 2.2319094
B15: Citi México | C15: 0 | D15: 0 | E15: 0 | F15: n.a. | G15: n.a. | H15: n.a. | I15: - | J15: - | K15: - | L15: - | M15: - | N15: -
B16: Banco del Bajío | C16: 350.91405 | D16: 358.60809 | E16: 363.60715 | F16: 1.030497 | G16: 1.4919443 | H16: 1.4204812 | I16: 266.91726 | J16: 173.91628 | K16: 195.01847 | L16: 2.7505743 | M16: 2.594734 | N16: 2.7702007
B17: Banco Azteca | C17: 8.2437013 | D17: 20.693281 | E17: 20.877941 | F17: 0 | G17: 0 | H17: 0 | I17: - | J17: - | K17: - | L17: 1.4485357 | M17: 1.4909364 | N17: 1.4992234
B18: Afirme | C18: 5615.0433 | D18: 6449.5198 | E18: 6487.4279 | F18: 2.4279151 | G18: 1.988746 | H18: 2.1961288 | I18: 182.17594 | J18: 233.7552 | K18: 216.2111 | L18: 4.423077 | M18: 4.6487972 | N18: 4.7482742
B19: Monex | C19: 0 | D19: 0 | E19: 0 | F19: n.a. | G19: n.a. | H19: n.a. | I19: - | J19: - | K19: - | L19: - | M19: - | N19: -
B20: Banregio | C20: 5266.8073 | D20: 5817.7304 | E20: 5896.0837 | F20: 0.64812157 | G20: 0.74570086 | H20: 0.7738868 | I20: 360.615 | J20: 276.77918 | K20: 274.04384 | L20: 2.3372236 | M20: 2.0639448 | N20: 2.1207892
B21: J.P. Morgan | C21: 0 | D21: 0 | E21: 0 | F21: n.a. | G21: n.a. | H21: n.a. | I21: - | J21: - | K21: - | L21: - | M21: - | N21: -
B22: Bank of America | C22: 0 | D22: 0 | E22: 0 | F22: n.a. | G22: n.a. | H22: n.a. | I22: - | J22: - | K22: - | L22: - | M22: - | N22: -
B23: Invex | C23: 0 | D23: 0 | E23: 0 | F23: n.a. | G23: n.a. | H23: n.a. | I23: - | J23: - | K23: - | L23: - | M23: - | N23: -
B24: BanCoppel | C24: 0 | D24: 0 | E24: 8122.0221 | F24: n.a. | G24: n.a. | H24: 2.3419223 | I24: - | J24: - | K24: 130.49908 | L24: - | M24: - | N24: 3.056187
B25: Multiva | C25: 9.087883 | D25: 6.541886 | E25: 6.236233 | F25: 0 | G25: 0 | H25: 0 | I25: - | J25: - | K25: - | L25: 1.3811137 | M25: 1.8345933 | N25: 2.1524853
B26: Banca Mifel | C26: 0 | D26: 0 | E26: 0 | F26: n.a. | G26: n.a. | H26: n.a. | I26: - | J26: - | K26: - | L26: - | M26: - | N26: -
B27: Barclays | C27: 0 | D27: 0 | E27: 0 | F27: n.a. | G27: n.a. | H27: n.a. | I27: - | J27: - | K27: - | L27: - | M27: - | N27: -
B28: Banco Base | C28: 0 | D28: 0 | E28: 0 | F28: n.a. | G28: n.a. | H28: n.a. | I28: - | J28: - | K28: - | L28: - | M28: - | N28: -
B29: Sabadell | C29: 0 | D29: 0 | E29: 0 | F29: n.a. | G29: n.a. | H29: n.a. | I29: - | J29: - | K29: - | L29: - | M29: - | N29: -
B30: Ve por Más | C30: 0 | D30: 0 | E30: 0 | F30: n.a. | G30: n.a. | H30: n.a. | I30: - | J30: - | K30: - | L30: - | M30: - | N30: -
B31: Actinver | C31: 21.805449 | D31: 8.878185 | E31: 8.431314 | F31: 12.758077 | G31: 3.6020087 | H31: 3.5290466 | I31: 106.69515 | J31: 111.77574 | K31: 136.54607 | L31: 13.612249 | M31: 4.026172 | N31: 4.8187744
B32: Bansí | C32: 1.708533 | D32: 1.25958 | E32: 1.203098 | F32: 0.38805221 | G32: 0.52636593 | H32: 0.5510773 | I32: 285.8371 | J32: 156.24434 | K32: 153.68024 | L32: 1.1091972 | M32: 0.822417 | N32: 0.84689693
B33: CIBanco | C33: 6667.6867 | D33: 8391.5169 | E33: 209.02757 | F33: 2.0230515 | G33: 2.1099234 | H33: 0.47610323 | I33: 135.35853 | J33: 134.46955 | K33: 375.1924 | L33: 2.7383728 | M33: 2.8372046 | N33: 1.7863031
B34: Compartamos | C34: 0 | D34: 0 | E34: 0 | F34: n.a. | G34: n.a. | H34: n.a. | I34: - | J34: - | K34: - | L34: - | M34: - | N34: -
B35: BIAfirme | C35: 0 | D35: 0 | E35: 0 | F35: n.a. | G35: n.a. | H35: n.a. | I35: - | J35: - | K35: - | L35: - | M35: - | N35: -
B36: Bancrea | C36: 0 | D36: 0 | E36: 0 | F36: n.a. | G36: n.a. | H36: n.a. | I36: - | J36: - | K36: - | L36: - | M36: - | N36: -
B37: MUFG Bank | C37: 0 | D37: 0 | E37: 0 | F37: n.a. | G37: n.a. | H37: n.a. | I37: - | J37: - | K37: - | L37: - | M37: - | N37: -
B38: Consubanco | C38: 0 | D38: 0 | E38: 0 | F38: n.a. | G38: n.a. | H38: n.a. | I38: - | J38: - | K38: - | L38: - | M38: - | N38: -
B39: Intercam Banco | C39: 0 | D39: 0 | E39: 0 | F39: n.a. | G39: n.a. | H39: n.a. | I39: - | J39: - | K39: - | L39: - | M39: - | N39: -
B40: Autofin | C40: 709.02139 | D40: 542.62873 | E40: 528.451 | F40: 1.5730107 | G40: 2.3942671 | H40: 2.8538307 | I40: 343.1531 | J40: 226.59531 | K40: 209.2976 | L40: 5.397835 | M40: 5.4252968 | N40: 5.9729992
B41: Bankaool | C41: 0.968427 | D41: 3.32709 | E41: 3.248743 | F41: 54.564567 | G41: 0 | H41: 0 | I41: 100.2973 | J41: - | K41: - | L41: 54.726789 | M41: 4.0902711 | N41: 4.0044411
B42: BNP Paribas México | C42: 0 | D42: 0 | E42: 0 | F42: n.a. | G42: n.a. | H42: n.a. | I42: - | J42: - | K42: - | L42: - | M42: - | N42: -
B43: Inmobiliario Mexicano | C43: 0 | D43: 0 | E43: 0 | F43: n.a. | G43: n.a. | H43: n.a. | I43: - | J43: - | K43: - | L43: - | M43: - | N43: -
B44: Mizuho Bank | C44: 0 | D44: 0 | E44: 0 | F44: n.a. | G44: n.a. | H44: n.a. | I44: - | J44: - | K44: - | L44: - | M44: - | N44: -
B45: ICBC | C45: 0 | D45: 0 | E45: 0 | F45: n.a. | G45: n.a. | H45: n.a. | I45: - | J45: - | K45: - | L45: - | M45: - | N45: -
B46: Banco Covalto | C46: 0 | D46: 0 | E46: 0 | F46: n.a. | G46: n.a. | H46: n.a. | I46: - | J46: - | K46: - | L46: - | M46: - | N46: -
B47: Openbank | C47: 0 | D47: 0 | E47: 0 | F47: n.a. | G47: n.a. | H47: n.a. | I47: - | J47: - | K47: - | L47: - | M47: - | N47: -
B48: Volkswagen Bank | C48: 5018.8679 | D48: 7276.972 | E48: 7404.2091 | F48: 1.0018261 | G48: 1.0732016 | H48: 1.1170978 | I48: 278.02668 | J48: 210.49931 | K48: 249.91953 | L48: 2.7853438 | M48: 2.2590819 | N48: 2.7918457
B49: Bank of China | C49: 0 | D49: 0 | E49: 0 | F49: n.a. | G49: n.a. | H49: n.a. | I49: - | J49: - | K49: - | L49: - | M49: - | N49: -
B50: Shinhan | C50: 0 | D50: 0 | E50: 0 | F50: n.a. | G50: n.a. | H50: n.a. | I50: - | J50: - | K50: - | L50: - | M50: - | N50: -
B51: Banco Ualá | C51: 0 | D51: 0 | E51: 0 | F51: n.a. | G51: n.a. | H51: n.a. | I51: - | J51: - | K51: - | L51: - | M51: - | N51: -
B52: Banco S3 | C52: 0 | D52: 0 | E52: 0 | F52: n.a. | G52: n.a. | H52: n.a. | I52: - | J52: - | K52: - | L52: - | M52: - | N52: -
B53: KEB Hana México | C53: 0 | D53: 0 | E53: 0 | F53: n.a. | G53: n.a. | H53: n.a. | I53: - | J53: - | K53: - | L53: - | M53: - | N53: -
B54: Banco Bineo | C54: 0 | D54: 0 | E54: 0 | F54: n.a. | G54: n.a. | H54: n.a. | I54: - | J54: - | K54: - | L54: - | M54: - | N54: -
B55: Dondé Banco | C55: 0 | D55: 0 | E55: 0 | F55: n.a. | G55: n.a. | H55: n.a. | I55: - | J55: - | K55: - | L55: - | M55: - | N55: -
B56: Credit Suisse | C56: 0 | D56: 0 | E56: 0 | F56: n.a. | G56: n.a. | H56: n.a. | I56: - | J56: - | K56: - | L56: - | M56: - | N56: -
B57: Hey Banco | C57: 0 | D57: 0 | E57: 0 | F57: n.a. | G57: n.a. | H57: n.a. | I57: - | J57: - | K57: - | L57: - | M57: - | N57: -
B58: Pagatodo | C58: 0 | D58: 0 | E58: 0 | F58: n.a. | G58: n.a. | H58: n.a. | I58: - | J58: - | K58: - | L58: - | M58: - | N58: -
B59: Forjadores | C59: 0 | D59: 0 | E59: 0 | F59: n.a. | G59: n.a. | H59: n.a. | I59: - | J59: - | K59: - | L59: - | M59: - | N59: -

Sheet CCCAdq BiMu
B2: Cartera de crédito al consumo
B3: Millones de pesos y porcentajes
C5: Adquisición de bienes muebles (MDP) 1/ | F5: IMOR (%) 5/ | I5: ICOR (%) 6/ | L5: Pérdida esperada (%) 7/
C6: 45505 | D6: 45839 | E6: 45870 | F6: =C6 -> 45505 | G6: =D6 -> 45839 | H6: =E6 -> 45870 | I6: =C6 -> 45505 | J6: =D6 -> 45839 | K6: =E6 -> 45870 | L6: =C6 -> 45505 | M6: =D6 -> 45839 | N6: =E6 -> 45870
B7: Sistema */ | C7: 39395.001 | D7: 44445.115 | E7: 44620.598 | F7: 4.061739 | G7: 4.3777003 | H7: 4.5785877 | I7: 276.24893 | J7: 224.27364 | K7: 219.35412 | L7: 11.220511 | M7: 9.8180278 | N7: 10.043321
B8: BBVA México | C8: 0 | D8: 0 | E8: 0 | F8: n.a. | G8: n.a. | H8: n.a. | I8: - | J8: - | K8: - | L8: - | M8: - | N8: -
B9: Santander | C9: 939.41839 | D9: 1134.883 | E9: 1151.9416 | F9: 1.0723386 | G9: 1.3101137 | H9: 0.91706777 | I9: 741.06275 | J9: 642.26574 | K9: 903.48314 | L9: 7.9467019 | M9: 8.4144116 | N9: 8.2855527
B10: Banorte | C10: 0 | D10: 0 | E10: 0 | F10: n.a. | G10: n.a. | H10: n.a. | I10: - | J10: - | K10: - | L10: - | M10: - | N10: -
B11: Banamex | C11: 0 | D11: 0 | E11: 0 | F11: n.a. | G11: n.a. | H11: n.a. | I11: - | J11: - | K11: - | L11: - | M11: - | N11: -
B12: HSBC | C12: 0 | D12: 0 | E12: 0 | F12: n.a. | G12: n.a. | H12: n.a. | I12: - | J12: - | K12: - | L12: - | M12: - | N12: -
B13: Scotiabank | C13: 0 | D13: 0 | E13: 0 | F13: n.a. | G13: n.a. | H13: n.a. | I13: - | J13: - | K13: - | L13: - | M13: - | N13: -
B14: Inbursa | C14: 9.474807 | D14: 2.90531 | E14: 2.623219 | F14: 8.8231243 | G14: 6.0769763 | H14: 6.8028251 | I14: 154.49512 | J14: 146.63136 | K14: 127.37079 | L14: 13.631296 | M14: 8.9107531 | N14: 8.6648122
B15: Citi México | C15: 0 | D15: 0 | E15: 0 | F15: n.a. | G15: n.a. | H15: n.a. | I15: - | J15: - | K15: - | L15: - | M15: - | N15: -
B16: Banco del Bajío | C16: 0 | D16: 0 | E16: 0 | F16: n.a. | G16: n.a. | H16: n.a. | I16: - | J16: - | K16: - | L16: - | M16: - | N16: -
B17: Banco Azteca | C17: 38335.49 | D17: 43223.439 | E17: 43384.351 | F17: 4.1369064 | G17: 4.4616539 | H17: 4.6798056 | I17: 273.20699 | J17: 220.86144 | K17: 215.578 | L17: 11.302318 | M17: 9.8540728 | N17: 10.088631
B18: Afirme | C18: 44.818285 | D18: 36.662047 | E18: 39.195924 | F18: 3.020979 | G18: 0.54936376 | H18: 0 | I18: 491.84402 | J18: 2366.552 | K18: - | L18: 14.858505 | M18: 13.000979 | N18: 12.591819
B19: Monex | C19: 0 | D19: 0 | E19: 0 | F19: n.a. | G19: n.a. | H19: n.a. | I19: - | J19: - | K19: - | L19: - | M19: - | N19: -
B20: Banregio | C20: 0 | D20: 0 | E20: 0 | F20: n.a. | G20: n.a. | H20: n.a. | I20: - | J20: - | K20: - | L20: - | M20: - | N20: -
B21: J.P. Morgan | C21: 0 | D21: 0 | E21: 0 | F21: n.a. | G21: n.a. | H21: n.a. | I21: - | J21: - | K21: - | L21: - | M21: - | N21: -
B22: Bank of America | C22: 0 | D22: 0 | E22: 0 | F22: n.a. | G22: n.a. | H22: n.a. | I22: - | J22: - | K22: - | L22: - | M22: - | N22: -
B23: Invex | C23: 0 | D23: 0 | E23: 0 | F23: n.a. | G23: n.a. | H23: n.a. | I23: - | J23: - | K23: - | L23: - | M23: - | N23: -
B24: BanCoppel | C24: 0 | D24: 0 | E24: 0 | F24: n.a. | G24: n.a. | H24: n.a. | I24: - | J24: - | K24: - | L24: - | M24: - | N24: -
B25: Multiva | C25: 0 | D25: 0 | E25: 0 | F25: n.a. | G25: n.a. | H25: n.a. | I25: - | J25: - | K25: - | L25: - | M25: - | N25: -
B26: Banca Mifel | C26: 0 | D26: 0 | E26: 0 | F26: n.a. | G26: n.a. | H26: n.a. | I26: - | J26: - | K26: - | L26: - | M26: - | N26: -
B27: Barclays | C27: 0 | D27: 0 | E27: 0 | F27: n.a. | G27: n.a. | H27: n.a. | I27: - | J27: - | K27: - | L27: - | M27: - | N27: -
B28: Banco Base | C28: 0 | D28: 0 | E28: 0 | F28: n.a. | G28: n.a. | H28: n.a. | I28: - | J28: - | K28: - | L28: - | M28: - | N28: -
B29: Sabadell | C29: 0 | D29: 0 | E29: 0 | F29: n.a. | G29: n.a. | H29: n.a. | I29: - | J29: - | K29: - | L29: - | M29: - | N29: -
B30: Ve por Más | C30: 0 | D30: 0 | E30: 0 | F30: n.a. | G30: n.a. | H30: n.a. | I30: - | J30: - | K30: - | L30: - | M30: - | N30: -
... B32: Bansí | C32: 0 | D32: 0 | E32: 0 | F32: n.a. | G32: n.a. | H32: n.a. | I32: - | J32: - | K32: - | L32: - | M32: - | N32: -
B33: CIBanco | C33: 65.799277 | D33: 47.224782 | E33: 42.486321 | F33: 2.971291 | G33: 4.1238009 | H33: 4.5835976 | I33: 251.53528 | J33: 197.46192 | K33: 200.00893 | L33: 7.473845 | M33: 8.1429365 | N33: 9.1676048
B34: Compartamos | C34: 0 | D34: 0 | E34: 0 | F34: n.a. | G34: n.a. | H34: n.a. | I34: - | J34: - | K34: - | L34: - | M34: - | N34: -
B35: BIAfirme | C35: 0 | D35: 0 | E35: 0 | F35: n.a. | G35: n.a. | H35: n.a. | I35: - | J35: - | K35: - | L35: - | M35: - | N35: -
B36: Bancrea | C36: 0 | D36: 0 | E36: 0 | F36: n.a. | G36: n.a. | H36: n.a. | I36: - | J36: - | K36: - | L36: - | M36: - | N36: -
B37: MUFG Bank | C37: 0 | D37: 0 | E37: 0 | F37: n.a. | G37: n.a. | H37: n.a. | I37: - | J37: - | K37: - | L37: - | M37: - | N37: -
B38: Consubanco | C38: 0 | D38: 0 | E38: 0 | F38: n.a. | G38: n.a. | H38: n.a. | I38: - | J38: - | K38: - | L38: - | M38: - | N38: -
B39: Intercam Banco | C39: 0 | D39: 0 | E39: 0 | F39: n.a. | G39: n.a. | H39: n.a. | I39: - | J39: - | K39: - | L39: - | M39: - | N39: -
B40: Autofin | C40: 0 | D40: 0 | E40: 0 | F40: n.a. | G40: n.a. | H40: n.a. | I40: - | J40: - | K40: - | L40: - | M40: - | N40: -
B41: Bankaool | C41: 0 | D41: 0 | E41: 0 | F41: n.a. | G41: n.a. | H41: n.a. | I41: - | J41: - | K41: - | L41: - | M41: - | N41: -
B42: BNP Paribas México | C42: 0 | D42: 0 | E42: 0 | F42: n.a. | G42: n.a. | H42: n.a. | I42: - | J42: - | K42: - | L42: - | M42: - | N42: -
B43: Inmobiliario Mexicano | C43: 0 | D43: 0 | E43: 0 | F43: n.a. | G43: n.a. | H43: n.a. | I43: - | J43: - | K43: - | L43: - | M43: - | N43: -
B44: Mizuho Bank | C44: 0 | D44: 0 | E44: 0 | F44: n.a. | G44: n.a. | H44: n.a. | I44: - | J44: - | K44: - | L44: - | M44: - | N44: -
B45: ICBC | C45: 0 | D45: 0 | E45: 0 | F45: n.a. | G45: n.a. | H45: n.a. | I45: - | J45: - | K45: - | L45: - | M45: - | N45: -
... B59: Forjadores | C59: 0 | D59: 0 | E59: 0 | F59: n.a. | G59: n.a. | H59: n.a. | I59: - | J59: - | K59: - | L59: - | M59: - | N59: -

Sheet CCOAC
B2: Cartera de crédito al consumo
B3: Millones de pesos y porcentajes
C5: Op. de arrendamiento financiero (MDP) 1/ | F5: IMOR (%) 5/ | I5: ICOR (%) 6/ | L5: Pérdida esperada (%) 7/
C6: 45505 | D6: 45839 | E6: 45870 | F6: =C6 -> 45505 | G6: =D6 -> 45839 | H6: =E6 -> 45870 | I6: =C6 -> 45505 | J6: =D6 -> 45839 | K6: =E6 -> 45870 | L6: =C6 -> 45505 | M6: =D6 -> 45839 | N6: =E6 -> 45870
B7: Sistema */ | C7: 93.218357 | D7: 111.27518 | E7: 110.12227 | F7: 0.85666512 | G7: 0.73613374 | H7: 0.60695661 | I7: 256.12939 | J7: 274.63985 | K7: 316.31686 | L7: 2.1941711 | M7: 2.0217166 | N7: 1.9199061
B8: BBVA México | C8: 0 | D8: 0 | E8: 0 | F8: n.a. | G8: n.a. | H8: n.a. | I8: - | J8: - | K8: - | L8: - | M8: - | N8: -
B9: Santander | C9: 0 | D9: 0 | E9: 0 | F9: n.a. | G9: n.a. | H9: n.a. | I9: - | J9: - | K9: - | L9: - | M9: - | N9: -
B10: Banorte | C10: 0 | D10: 0 | E10: 0 | F10: n.a. | G10: n.a. | H10: n.a. | I10: - | J10: - | K10: - | L10: - | M10: - | N10: -
B11: Banamex | C11: 0 | D11: 0 | E11: 0 | F11: n.a. | G11: n.a. | H11: n.a. | I11: - | J11: - | K11: - | L11: - | M11: - | N11: -
B12: HSBC | C12: 0 | D12: 0 | E12: 0 | F12: n.a. | G12: n.a. | H12: n.a. | I12: - | J12: - | K12: - | L12: - | M12: - | N12: -
B13: Scotiabank | C13: 0 | D13: 0 | E13: 0 | F13: n.a. | G13: n.a. | H13: n.a. | I13: - | J13: - | K13: - | L13: - | M13: - | N13: -
B14: Inbursa | C14: 0 | D14: 0 | E14: 0 | F14: n.a. | G14: n.a. | H14: n.a. | I14: - | J14: - | K14: - | L14: - | M14: - | N14: -
B15: Citi México | C15: 0 | D15: 0 | E15: 0 | F15: n.a. | G15: n.a. | H15: n.a. | I15: - | J15: - | K15: - | L15: - | M15: - | N15: -
B16: Banco del Bajío | C16: 0 | D16: 0 | E16: 0 | F16: n.a. | G16: n.a. | H16: n.a. | I16: - | J16: - | K16: - | L16: - | M16: - | N16: -
B17: Banco Azteca | C17: 0 | D17: 0 | E17: 0 | F17: n.a. | G17: n.a. | H17: n.a. | I17: - | J17: - | K17: - | L17: - | M17: - | N17: -
B18: Afirme | C18: 0 | D18: 0 | E18: 0 | F18: n.a. | G18: n.a. | H18: n.a. | I18: - | J18: - | K18: - | L18: - | M18: - | N18: -
B19: Monex | C19: 0 | D19: 0 | E19: 0 | F19: n.a. | G19: n.a. | H19: n.a. | I19: - | J19: - | K19: - | L19: - | M19: - | N19: -
B20: Banregio | C20: 81.961744 | D20: 100.04839 | E20: 99.261166 | F20: 0.97431937 | G20: 0.81873796 | H20: 0.67336948 | I20: 235.57212 | J20: 262.89672 | K20: 303.8799 | L20: 2.2952248 | M20: 2.1524353 | N20: 2.0462345
B21: J.P. Morgan | C21: 0 | D21: 0 | E21: 0 | F21: n.a. | G21: n.a. | H21: n.a. | I21: - | J21: - | K21: - | L21: - | M21: - | N21: -
B22: Bank of America | C22: 0 | D22: 0 | E22: 0 | F22: n.a. | G22: n.a. | H22: n.a. | I22: - | J22: - | K22: - | L22: - | M22: - | N22: -
B23: Invex | C23: 0 | D23: 0 | E23: 0 | F23: n.a. | G23: n.a. | H23: n.a. | I23: - | J23: - | K23: - | L23: - | M23: - | N23: -
B24: BanCoppel | C24: 0 | D24: 0 | E24: 0 | F24: n.a. | G24: n.a. | H24: n.a. | I24: - | J24: - | K24: - | L24: - | M24: - | N24: -
B25: Multiva | C25: 0 | D25: 0 | E25: 0 | F25: n.a. | G25: n.a. | H25: n.a. | I25: - | J25: - | K25: - | L25: - | M25: - | N25: -
B26: Banca Mifel | C26: 0 | D26: 0 | E26: 0 | F26: n.a. | G26: n.a. | H26: n.a. | I26: - | J26: - | K26: - | L26: - | M26: - | N26: -
B27: Barclays | C27: 0 | D27: 0 | E27: 0 | F27: n.a. | G27: n.a. | H27: n.a. | I27: - | J27: - | K27: - | L27: - | M27: - | N27: -
B28: Banco Base | C28: 0 | D28: 0 | E28: 0 | F28: n.a. | G28: n.a. | H28: n.a. | I28: - | J28: - | K28: - | L28: - | M28: - | N28: -
B29: Sabadell | C29: 0 | D29: 0 | E29: 0 | F29: n.a. | G29: n.a. | H29: n.a. | I29: - | J29: - | K29: - | L29: - | M29: - | N29: -
B30: Ve por Más | C30: 11.256613 | D30: 11.226791 | E30: 10.861104 | F30: 0 | G30: 0 | H30: 0 | I30: - | J30: - | K30: - | L30: 1.4583783 | M30: 0.85680761 | N30: 0.76537339
B31: Actinver | C31: 0 | D31: 0 | E31: 0 | F31: n.a. | G31: n.a. | H31: n.a. | I31: - | J31: - | K31: - | L31: - | M31: - | N31: -
B32: Bansí | C32: 0 | D32: 0 | E32: 0 | F32: n.a. | G32: n.a. | H32: n.a. | I32: - | J32: - | K32: - | L32: - | M32: - | N32: -
B33: CIBanco | C33: 0 | D33: 0 | E33: 0 | F33: n.a. | G33: n.a. | H33: n.a. | I33: - | J33: - | K33: - | L33: - | M33: - | N33: -
B34: Compartamos | C34: 0 | D34: 0 | E34: 0 | F34: n.a. | G34: n.a. | H34: n.a. | I34: - | J34: - | K34: - | L34: - | M34: - | N34: -
B35: BIAfirme | C35: 0 | D35: 0 | E35: 0 | F35: n.a. | G35: n.a. | H35: n.a. | I35: - | J35: - | K35: - | L35: - | M35: - | N35: -
B36: Bancrea | C36: 0 | D36: 0 | E36: 0 | F36: n.a. | G36: n.a. | H36: n.a. | I36: - | J36: - | K36: - | L36: - | M36: - | N36: -
B37: MUFG Bank | C37: 0 | D37: 0 | E37: 0 | F37: n.a. | G37: n.a. | H37: n.a. | I37: - | J37: - | K37: - | L37: - | M37: - | N37: -
B38: Consubanco | C38: 0 | D38: 0 | E38: 0 | F38: n.a. | G38: n.a. | H38: n.a. | I38: - | J38: - | K38: - | L38: - | M38: - | N38: -
B39: Intercam Banco | C39: 0 | D39: 0 | E39: 0 | F39: n.a. | G39: n.a. | H39: n.a. | I39: - | J39: - | K39: - | L39: - | M39: - | N39: -
B40: Autofin | C40: 0 | D40: 0 | E40: 0 | F40: n.a. | G40: n.a. | H40: n.a. | I40: - | J40: - | K40: - | L40: - | M40: - | N40: -
B41: Bankaool | C41: 0 | D41: 0 | E41: 0 | F41: n.a. | G41: n.a. | H41: n.a. | I41: - | J41: - | K41: - | L41: - | M41: - | N41: -
B42: BNP Paribas México | C42: 0 | D42: 0 | E42: 0 | F42: n.a. | G42: n.a. | H42: n.a. | I42: - | J42: - | K42: - | L42: - | M42: - | N42: -
... B59: Forjadores | C59: 0 | D59: 0 | E59: 0 | F59: n.a. | G59: n.a. | H59: n.a. | I59: - | J59: - | K59: - | L59: - | M59: - | N59: -

Sheet CCCMicro
B2: Cartera de crédito al consumo
B3: Millones de pesos y porcentajes
C5: Microcréditos (MDP) 1/ | F5: IMOR (%) 5/ | I5: ICOR (%) 6/ | L5: Pérdida esperada (%) 7/
C6: 45505 | D6: 45839 | E6: 45870 | F6: =C6 -> 45505 | G6: =D6 -> 45839 | H6: =E6 -> 45870 | I6: =C6 -> 45505 | J6: =D6 -> 45839 | K6: =E6 -> 45870 | L6: =C6 -> 45505 | M6: =D6 -> 45839 | N6: =E6 -> 45870
B7: Sistema */ | C7: 43340.88 | D7: 51371.162 | E7: 51267.454 | F7: 3.1343309 | G7: 3.3163959 | H7: 3.4126195 | I7: 229.065 | J7: 217.46984 | K7: 219.56947 | L7: 7.1796551 | M7: 7.2121609 | N7: 7.4930707
B8: BBVA México | C8: 0 | D8: 0 | E8: 0 | F8: n.a. | G8: n.a. | H8: n.a. | I8: - | J8: - | K8: - | L8: - | M8: - | N8: -
B9: Santander | C9: 965.93338 | D9: 1105.2752 | E9: 1113.185 | F9: 3.6236294 | G9: 5.2260675 | H9: 5.6735218 | I9: 232.69784 | J9: 189.18431 | K9: 186.45517 | L9: 8.4321074 | M9: 9.8868996 | N9: 10.578575
B10: Banorte | C10: 0 | D10: 0 | E10: 0 | F10: n.a. | G10: n.a. | H10: n.a. | I10: - | J10: - | K10: - | L10: - | M10: - | N10: -
B11: Banamex | C11: 0 | D11: 0 | E11: 0 | F11: n.a. | G11: n.a. | H11: n.a. | I11: - | J11: - | K11: - | L11: - | M11: - | N11: -
B12: HSBC | C12: 0 | D12: 0 | E12: 0 | F12: n.a. | G12: n.a. | H12: n.a. | I12: - | J12: - | K12: - | L12: - | M12: - | N12: -
B13: Scotiabank | C13: 0 | D13: 0 | E13: 0 | F13: n.a. | G13: n.a. | H13: n.a. | I13: - | J13: - | K13: - | L13: - | M13: - | N13: -
B14: Inbursa | C14: 0 | D14: 0 | E14: 0 | F14: n.a. | G14: n.a. | H14: n.a. | I14: - | J14: - | K14: - | L14: - | M14: - | N14: -
B15: Citi México | C15: 0 | D15: 0 | E15: 0 | F15: n.a. | G15: n.a. | H15: n.a. | I15: - | J15: - | K15: - | L15: - | M15: - | N15: -
B16: Banco del Bajío | C16: 0 | D16: 0 | E16: 0 | F16: n.a. | G16: n.a. | H16: n.a. | I16: - | J16: - | K16: - | L16: - | M16: - | N16: -
B17: Banco Azteca | C17: 0 | D17: 0 | E17: 0 | F17: n.a. | G17: n.a. | H17: n.a. | I17: - | J17: - | K17: - | L17: - | M17: - | N17: -
B18: Afirme | C18: 0 | D18: 268.60438 | E18: 277.51004 | F18: n.a. | G18: 3.0587621 | H18: 3.2807631 | I18: - | J18: 429.45186 | K18: 382.21231 | L18: - | M18: 13.135911 | N18: 12.53948
B19: Monex | C19: 0 | D19: 0 | E19: 0 | F19: n.a. | G19: n.a. | H19: n.a. | I19: - | J19: - | K19: - | L19: - | M19: - | N19: -
B20: Banregio | C20: 0 | D20: 0 | E20: 0 | F20: n.a. | G20: n.a. | H20: n.a. | I20: - | J20: - | K20: - | L20: - | M20: - | N20: -
B21: J.P. Morgan | C21: 0 | D21: 0 | E21: 0 | F21: n.a. | G21: n.a. | H21: n.a. | I21: - | J21: - | K21: - | L21: - | M21: - | N21: -
B22: Bank of America | C22: 0 | D22: 0 | E22: 0 | F22: n.a. | G22: n.a. | H22: n.a. | I22: - | J22: - | K22: - | L22: - | M22: - | N22: -
B23: Invex | C23: 0 | D23: 0 | E23: 0 | F23: n.a. | G23: n.a. | H23: n.a. | I23: - | J23: - | K23: - | L23: - | M23: - | N23: -
B24: BanCoppel | C24: 0 | D24: 0 | E24: 0 | F24: n.a. | G24: n.a. | H24: n.a. | I24: - | J24: - | K24: - | L24: - | M24: - | N24: -
B25: Multiva | C25: 0 | D25: 0 | E25: 0 | F25: n.a. | G25: n.a. | H25: n.a. | I25: - | J25: - | K25: - | L25: - | M25: - | N25: -
B26: Banca Mifel | C26: 0 | D26: 0 | E26: 0 | F26: n.a. | G26: n.a. | H26: n.a. | I26: - | J26: - | K26: - | L26: - | M26: - | N26: -
B27: Barclays | C27: 0 | D27: 0 | E27: 0 | F27: n.a. | G27: n.a. | H27: n.a. | I27: - | J27: - | K27: - | L27: - | M27: - | N27: -
B28: Banco Base | C28: 0 | D28: 0 | E28: 0 | F28: n.a. | G28: n.a. | H28: n.a. | I28: - | J28: - | K28: - | L28: - | M28: - | N28: -
B29: Sabadell | C29: 0 | D29: 0 | E29: 0 | F29: n.a. | G29: n.a. | H29: n.a. | I29: - | J29: - | K29: - | L29: - | M29: - | N29: -
B30: Ve por Más | C30: 0 | D30: 0 | E30: 0 | F30: n.a. | G30: n.a. | H30: n.a. | I30: - | J30: - | K30: - | L30: - | M30: - | N30: -
... B33: CIBanco | C33: 0 | D33: 0 | E33: 0 | F33: n.a. | G33: n.a. | H33: n.a. | I33: - | J33: - | K33: - | L33: - | M33: - | N33: -
B34: Compartamos | C34: 41876.888 | D34: 49654.937 | E34: 49538.319 | F34: 3.0873725 | G34: 3.2259241 | H34: 3.3207358 | I34: 230.99098 | J34: 219.86486 | K34: 222.13231 | L34: 7.1315518 | M34: 7.0926734 | N34: 7.376427
B35: BIAfirme | C35: 0 | D35: 0 | E35: 0 | F35: n.a. | G35: n.a. | H35: n.a. | I35: - | J35: - | K35: - | L35: - | M35: - | N35: -
B36: Bancrea | C36: 0 | D36: 0 | E36: 0 | F36: n.a. | G36: n.a. | H36: n.a. | I36: - | J36: - | K36: - | L36: - | M36: - | N36: -
B37: MUFG Bank | C37: 0 | D37: 0 | E37: 0 | F37: n.a. | G37: n.a. | H37: n.a. | I37: - | J37: - | K37: - | L37: - | M37: - | N37: -
B38: Consubanco | C38: 0 | D38: 0 | E38: 0 | F38: n.a. | G38: n.a. | H38: n.a. | I38: - | J38: - | K38: - | L38: - | M38: - | N38: -
B39: Intercam Banco | C39: 0 | D39: 0 | E39: 0 | F39: n.a. | G39: n.a. | H39: n.a. | I39: - | J39: - | K39: - | L39: - | M39: - | N39: -
B40: Autofin | C40: 0 | D40: 0 | E40: 0 | F40: n.a. | G40: n.a. | H40: n.a. | I40: - | J40: - | K40: - | L40: - | M40: - | N40: -
B41: Bankaool | C41: 0 | D41: 0 | E41: 0 | F41: n.a. | G41: n.a. | H41: n.a. | I41: - | J41: - | K41: - | L41: - | M41: - | N41: -
B42: BNP Paribas México | C42: 0 | D42: 0 | E42: 0 | F42: n.a. | G42: n.a. | H42: n.a. | I42: - | J42: - | K42: - | L42: - | M42: - | N42: -
B43: Inmobiliario Mexicano | C43: 0 | D43: 0 | E43: 0 | F43: n.a. | G43: n.a. | H43: n.a. | I43: - | J43: - | K43: - | L43: - | M43: - | N43: -
B44: Mizuho Bank | C44: 0 | D44: 0 | E44: 0 | F44: n.a. | G44: n.a. | H44: n.a. | I44: - | J44: - | K44: - | L44: - | M44: - | N44: -
B45: ICBC | C45: 0 | D45: 0 | E45: 0 | F45: n.a. | G45: n.a. | H45: n.a. | I45: - | J45: - | K45: - | L45: - | M45: - | N45: -
B46: Banco Covalto | C46: 0 | D46: 0 | E46: 0 | F46: n.a. | G46: n.a. | H46: n.a. | I46: - | J46: - | K46: - | L46: - | M46: - | N46: -
... B58: Pagatodo | C58: 0 | D58: 0 | E58: 0 | F58: n.a. | G58: n.a. | H58: n.a. | I58: - | J58: - | K58: - | L58: - | M58: - | N58: -
B59: Forjadores | C59: 498.05896 | D59: 342.346 | E59: 338.44048 | F59: 6.1336615 | G59: 10.475414 | H59: 9.5335048 | I59: 143.39219 | J59: 107.48735 | K59: 107.82893 | L59: 8.7951916 | M59: 11.259745 | N59: 10.279876

Sheet CCCnrO
B2: Cartera de crédito al consumo
B3: Millones de pesos y porcentajes
C5: Otros créditos al consumo (MDP) 1/ | F5: IMOR (%) 5/ | I5: ICOR (%) 6/ | L5: Pérdida esperada (%) 7/
C6: 45505 | D6: 45839 | E6: 45870 | F6: =C6 -> 45505 | G6: =D6 -> 45839 | H6: =E6 -> 45870 | I6: =C6 -> 45505 | J6: =D6 -> 45839 | K6: =E6 -> 45870 | L6: =C6 -> 45505 | M6: =D6 -> 45839 | N6: =E6 -> 45870
B7: Sistema */ | C7: 5251.9802 | D7: 4156.7498 | E7: 4186.5204 | F7: 4.3922175 | G7: 4.1388928 | H7: 4.576684 | I7: 214.32496 | J7: 245.46817 | K7: 219.59908 | L7: 9.4136184 | M7: 10.159664 | N7: 10.050356
B8: BBVA México | C8: 11.497158 | D8: 22.006469 | E8: 32.055433 | F8: 99.557531 | G8: 0.75818447 | H8: 0.61414641 | I8: 100.00002 | J8: 1792.5832 | K8: 2108.5746 | L8: 99.557547 | M8: 13.591088 | N8: 12.949735
B9: Santander | C9: 0 | D9: 0 | E9: 0 | F9: n.a. | G9: n.a. | H9: n.a. | I9: - | J9: - | K9: - | L9: - | M9: - | N9: -
B10: Banorte | C10: 57.200011 | D10: 55.075033 | E10: 51.902923 | F10: 7.6716066 | G10: 8.1466807 | H10: 8.5586308 | I10: 295.34662 | J10: 241.33972 | K10: 233.83396 | L10: 22.657831 | M10: 19.661177 | N10: 20.012985
B11: Banamex | C11: 0.18682194 | D11: 0.18931033 | E11: 0.18931153 | F11: 100 | G11: 100 | H11: 100 | I11: 100 | J11: 100 | K11: 99.999366 | L11: 100 | M11: 100 | N11: 99.999366
B12: HSBC | C12: 1155.3578 | D12: 1169.8935 | E12: 1160.2701 | F12: 9.4890684 | G12: 4.9531789 | H12: 5.9426883 | I12: 180.36859 | J12: 302.40975 | K12: 233.50662 | L12: 17.115299 | M12: 14.978896 | N12: 13.876571
B13: Scotiabank | C13: 8.349388 | D13: 7.698748 | E13: 7.016527 | F13: 50.516577 | G13: 54.982122 | H13: 60.339296 | I13: 103.13647 | J13: 101.17148 | K13: 101.21867 | L13: 52.101016 | M13: 55.626226 | N13: 61.074631
B14: Inbursa | C14: 1979.1708 | D14: 10.649414 | E14: 9.639678 | F14: 2.3828088 | G14: 9.3578388 | H14: 1.707474 | I14: 269.82985 | J14: 81.112533 | K14: 125.16176 | L14: 6.4295292 | M14: 7.5903801 | N14: 2.1371046
B15: Citi México | C15: 0 | D15: 0 | E15: 0 | F15: n.a. | G15: n.a. | H15: n.a. | I15: - | J15: - | K15: - | L15: - | M15: - | N15: -
B16: Banco del Bajío | C16: 0 | D16: 0 | E16: 0 | F16: n.a. | G16: n.a. | H16: n.a. | I16: - | J16: - | K16: - | L16: - | M16: - | N16: -
B17: Banco Azteca | C17: 1586.3301 | D17: 2347.8135 | E17: 2382.8931 | F17: 3.0458668 | G17: 4.0837844 | H17: 4.4343347 | I17: 221.76355 | J17: 207.52783 | K17: 198.02027 | L17: 6.7546224 | M17: 8.4749891 | N17: 8.7808817
B18: Afirme | C18: 0 | D18: 0 | E18: 0 | F18: n.a. | G18: n.a. | H18: n.a. | I18: - | J18: - | K18: - | L18: - | M18: - | N18: -
B19: Monex | C19: 0 | D19: 0 | E19: 0 | F19: n.a. | G19: n.a. | H19: n.a. | I19: - | J19: - | K19: - | L19: - | M19: - | N19: -
B20: Banregio | C20: 0.03001231 | D20: 0 | E20: 0 | F20: 0 | G20: n.a. | H20: n.a. | I20: - | J20: - | K20: - | L20: 2.7519375 | M20: - | N20: -
B21: J.P. Morgan | C21: 0 | D21: 0 | E21: 0 | F21: n.a. | G21: n.a. | H21: n.a. | I21: - | J21: - | K21: - | L21: - | M21: - | N21: -
B22: Bank of America | C22: 0 | D22: 0 | E22: 0 | F22: n.a. | G22: n.a. | H22: n.a. | I22: - | J22: - | K22: - | L22: - | M22: - | N22: -
B23: Invex | C23: 3.61653 | D23: 0 | E23: 0 | F23: 0 | G23: n.a. | H23: n.a. | I23: - | J23: - | K23: - | L23: 0 | M23: - | N23: -
B24: BanCoppel | C24: 0 | D24: 0 | E24: 0 | F24: n.a. | G24: n.a. | H24: n.a. | I24: - | J24: - | K24: - | L24: - | M24: - | N24: -
B25: Multiva | C25: 0 | D25: 0 | E25: 0 | F25: n.a. | G25: n.a. | H25: n.a. | I25: - | J25: - | K25: - | L25: - | M25: - | N25: -
B26: Banca Mifel | C26: 0 | D26: 0 | E26: 0 | F26: n.a. | G26: n.a. | H26: n.a. | I26: - | J26: - | K26: - | L26: - | M26: - | N26: -
B27: Barclays | C27: 0 | D27: 0 | E27: 0 | F27: n.a. | G27: n.a. | H27: n.a. | I27: - | J27: - | K27: - | L27: - | M27: - | N27: -
B28: Banco Base | C28: 0 | D28: 0 | E28: 0 | F28: n.a. | G28: n.a. | H28: n.a. | I28: - | J28: - | K28: - | L28: - | M28: - | N28: -
B29: Sabadell | C29: 0 | D29: 0 | E29: 0 | F29: n.a. | G29: n.a. | H29: n.a. | I29: - | J29: - | K29: - | L29: - | M29: - | N29: -
B30: Ve por Más | C30: 127.1848 | D30: 134.81136 | E30: 139.04953 | F30: 0 | G30: 0.0090660016 | H30: 0.10055122 | I30: - | J30: 26137.67 | K30: 3456.2489 | L30: 2.2495313 | M30: 2.3696416 | N30: 3.4753006
B31: Actinver | C31: 323.05678 | D31: 408.12308 | E31: 403.01445 | F31: 1.6496342 | G31: 1.8726785 | H31: 1.7694805 | I31: 571.38793 | J31: 332.30547 | K31: 365.06008 | L31: 9.4258106 | M31: 6.223013 | N31: 6.4596668
B32: Bansí | C32: 0 | D32: 0 | E32: 0 | F32: n.a. | G32: n.a. | H32: n.a. | I32: - | J32: - | K32: - | L32: - | M32: - | N32: -
B33: CIBanco | C33: 0 | D33: 0 | E33: 0 | F33: n.a. | G33: n.a. | H33: n.a. | I33: - | J33: - | K33: - | L33: - | M33: - | N33: -
B34: Compartamos | C34: 0 | D34: 0.489365 | E34: 0.489365 | F34: n.a. | G34: 100 | H34: 100 | I34: - | J34: 83.00001 | K34: 87.999959 | L34: - | M34: 83.00001 | N34: 87.999959
B35: BIAfirme | C35: 0 | D35: 0 | E35: 0 | F35: n.a. | G35: n.a. | H35: n.a. | I35: - | J35: - | K35: - | L35: - | M35: - | N35: -
B36: Bancrea | C36: 0 | D36: 0 | E36: 0 | F36: n.a. | G36: n.a. | H36: n.a. | I36: - | J36: - | K36: - | L36: - | M36: - | N36: -
B37: MUFG Bank | C37: 0 | D37: 0 | E37: 0 | F37: n.a. | G37: n.a. | H37: n.a. | I37: - | J37: - | K37: - | L37: - | M37: - | N37: -
B38: Consubanco | C38: 0 | D38: 0 | E38: 0 | F38: n.a. | G38: n.a. | H38: n.a. | I38: - | J38: - | K38: - | L38: - | M38: - | N38: -
B39: Intercam Banco | C39: 0 | D39: 0 | E39: 0 | F39: n.a. | G39: n.a. | H39: n.a. | I39: - | J39: - | K39: - | L39: - | M39: - | N39: -
B40: Autofin | C40: 0 | D40: 0 | E40: 0 | F40: n.a. | G40: n.a. | H40: n.a. | I40: - | J40: - | K40: - | L40: - | M40: - | N40: -
B41: Bankaool | C41: 0 | D41: 0 | E41: 0 | F41: n.a. | G41: n.a. | H41: n.a. | I41: - | J41: - | K41: - | L41: - | M41: - | N41: -
B42: BNP Paribas México | C42: 0 | D42: 0 | E42: 0 | F42: n.a. | G42: n.a. | H42: n.a. | I42: - | J42: - | K42: - | L42: - | M42: - | N42: -
B43: Inmobiliario Mexicano | C43: 0 | D43: 0 | E43: 0 | F43: n.a. | G43: n.a. | H43: n.a. | I43: - | J43: - | K43: - | L43: - | M43: - | N43: -
B44: Mizuho Bank | C44: 0 | D44: 0 | E44: 0 | F44: n.a. | G44: n.a. | H44: n.a. | I44: - | J44: - | K44: - | L44: - | M44: - | N44: -
B45: ICBC | C45: 0 | D45: 0 | E45: 0 | F45: n.a. | G45: n.a. | H45: n.a. | I45: - | J45: - | K45: - | L45: - | M45: - | N45: -
B46: Banco Covalto | C46: 0 | D46: 0 | E46: 0 | F46: n.a. | G46: n.a. | H46: n.a. | I46: - | J46: - | K46: - | L46: - | M46: - | N46: -
... B59: Forjadores | C59: 0 | D59: 0 | E59: 0 | F59: n.a. | G59: n.a. | H59: n.a. | I59: - | J59: - | K59: - | L59: - | M59: - | N59: -

Sheet CCV
B2: Cartera de crédito a la vivienda
B3: Millones de pesos y porcentajes
C5: Cartera total (MDP) 1/ | F5: IMOR (%) 5/ | I5: ICOR (%) 6/ | L5: Pérdida esperada (%) 7/
C6: 45505 | D6: 45839 | E6: 45870 | F6: =C6 -> 45505 | G6: =D6 -> 45839 | H6: =E6 -> 45870 | I6: =C6 -> 45505 | J6: =D6 -> 45839 | K6: =E6 -> 45870 | L6: =C6 -> 45505 | M6: =D6 -> 45839 | N6: =E6 -> 45870
B7: Sistema */ | C7: 1396539.5 | D7: 1475070.1 | E7: 1481464.7 | F7: 2.721452 | G7: 3.0338235 | H7: 3.0897356 | I7: 56.113392 | J7: 54.528415 | K7: 54.254003 | L7: 1.5270991 | M7: 1.6542958 | N7: 1.6763052
B8: BBVA México | C8: 357795.44 | D8: 385363.94 | E8: 388133.06 | F8: 2.1858921 | G8: 2.3958391 | H8: 2.4493451 | I8: 66.990082 | J8: 65.972488 | K8: 66.395884 | L8: 1.4643309 | M8: 1.5805947 | N8: 1.6262643
B9: Santander | C9: 233647.23 | D9: 249716.79 | E9: 251265.68 | F9: 3.4324201 | G9: 3.6135898 | H9: 3.6642195 | I9: 64.339545 | J9: 63.199723 | K9: 62.885852 | L9: 2.2084034 | M9: 2.2837787 | N9: 2.3042756
B10: Banorte | C10: 267104.15 | D10: 287144.1 | E10: 288864.83 | F10: 0.73769675 | G10: 0.85369057 | H10: 0.87466044 | I10: 62.477838 | J10: 53.920689 | K10: 52.217974 | L10: 0.46089698 | M10: 0.46031583 | N10: 0.45672996
B11: Banamex | C11: 71638.799 | D11: 78504.947 | E11: 78640.535 | F11: 2.3039388 | G11: 2.4157862 | H11: 2.4589813 | I11: 50.542677 | J11: 44.298045 | K11: 43.369641 | L11: 1.1644724 | M11: 1.0701461 | N11: 1.0664514
B12: HSBC | C12: 151546.63 | D12: 151076.72 | E12: 150608 | F12: 2.462661 | G12: 2.807952 | H12: 2.8081832 | I12: 52.564632 | J12: 51.667314 | K12: 52.64709 | L12: 1.2944887 | M12: 1.4507934 | N12: 1.4784267
B13: Scotiabank | C13: 239447.13 | D13: 249043.88 | E13: 249977.99 | F13: 4.6671861 | G13: 5.7610203 | H13: 5.8179143 | I13: 42.106403 | J13: 42.269868 | K13: 42.190067 | L13: 1.9651842 | M13: 2.4351757 | N13: 2.4545819
B14: Inbursa | C14: 5077.8575 | D14: 4437.5326 | E14: 4417.3115 | F14: 14.264915 | G14: 11.81137 | H14: 12.168373 | I14: 34.262127 | J14: 27.536164 | K14: 27.065349 | L14: 4.8874634 | M14: 3.2523982 | N14: 3.2934128
B15: Citi México | C15: 0 | D15: 0 | E15: 0 | F15: n.a. | G15: n.a. | H15: n.a. | I15: - | J15: - | K15: - | L15: - | M15: - | N15: -
B16: Banco del Bajío | C16: 4278.4667 | D16: 3667.4166 | E16: 3652.963 | F16: 3.6999503 | G16: 3.8100395 | H16: 3.380233 | I16: 41.559265 | J16: 45.097257 | K16: 42.812096 | L16: 1.5376721 | M16: 1.7182233 | N16: 1.4471486
B17: Banco Azteca | C17: 584.12004 | D17: 608.67915 | E17: 613.34604 | F17: 5.9749151 | G17: 3.1331622 | H17: 3.0927989 | I17: 24.582758 | J17: 40.917008 | K17: 49.394295 | L17: 1.4687989 | M17: 1.2819963 | N17: 1.5276662
B18: Afirme | C18: 13537.655 | D18: 14207.146 | E18: 14309.786 | F18: 5.7131841 | G18: 4.1727509 | H18: 4.2135515 | I18: 39.08422 | J18: 45.927971 | K18: 46.960063 | L18: 2.2329534 | M18: 1.9164598 | N18: 1.9786864
B19: Monex | C19: 7.0704059 | D19: 0 | E19: 0 | F19: 66.469137 | G19: n.a. | H19: n.a. | I19: 96.952241 | J19: - | K19: - | L19: 64.443318 | M19: - | N19: -
B20: Banregio | C20: 15904.187 | D20: 17102.787 | E20: 17230.552 | F20: 1.4179315 | G20: 1.3228479 | H20: 1.3078085 | I20: 72.353899 | J20: 77.959231 | K20: 78.607662 | L20: 1.0259287 | M20: 1.031282 | N20: 1.0280377
B21: J.P. Morgan | C21: 0 | D21: 0 | E21: 0 | F21: n.a. | G21: n.a. | H21: n.a. | I21: - | J21: - | K21: - | L21: - | M21: - | N21: -
B22: Bank of America | C22: 0 | D22: 0 | E22: 0 | F22: n.a. | G22: n.a. | H22: n.a. | I22: - | J22: - | K22: - | L22: - | M22: - | N22: -
B23: Invex | C23: 63.198491 | D23: 53.39593 | E23: 55.146837 | F23: 0 | G23: 0 | H23: 0 | I23: - | J23: - | K23: - | L23: 0.13377218 | M23: 0.11869631 | N23: 0.13192234
B24: BanCoppel | C24: 4405.5731 | D24: 4511.4099 | E24: 4480.441 | F24: 1.4427659 | G24: 3.4856055 | H24: 4.0009283 | I24: 167.55026 | J24: 103.21644 | K24: 94.151523 | L24: 2.4173581 | M24: 3.5977181 | N24: 3.766935
B25: Multiva | C25: 440.1999 | D25: 435.7915 | E25: 432.46833 | F25: 75.517604 | G25: 66.103404 | H25: 66.274956 | I25: 97.178712 | J25: 98.844699 | K25: 98.781703 | L25: 73.387035 | M25: 65.339711 | N25: 65.46753
B26: Banca Mifel | C26: 18618.514 | D26: 17415.882 | E26: 17139.724 | F26: 6.0790253 | G26: 8.5344284 | H26: 9.1817126 | I26: 49.64481 | J26: 42.724203 | K26: 39.989067 | L26: 3.0179206 | M26: 3.6462665 | N26: 3.6716812
B27: Barclays | C27: 0 | D27: 0 | E27: 0 | F27: n.a. | G27: n.a. | H27: n.a. | I27: - | J27: - | K27: - | L27: - | M27: - | N27: -
B28: Banco Base | C28: 0 | D28: 0 | E28: 0 | F28: n.a. | G28: n.a. | H28: n.a. | I28: - | J28: - | K28: - | L28: - | M28: - | N28: -
B29: Sabadell | C29: 56.686927 | D29: 45.960187 | E29: 39.062637 | F29: 2.2726069 | G29: 2.7081004 | H29: 0 | I29: 38.71468 | J29: 31.10751 | K29: - | L29: 0.87983249 | M29: 0.8424226 | N29: 0.41588078
B30: Ve por Más | C30: 11045.463 | D30: 10655.117 | E30: 10554.598 | F30: 1.2510919 | G30: 0.72667893 | H30: 0.80415018 | I30: 273.58301 | J30: 522.78728 | K30: 475.67016 | L30: 3.422775 | M30: 3.798985 | N30: 3.8251024
B31: Actinver | C31: 0 | D31: 0 | E31: 0 | F31: n.a. | G31: n.a. | H31: n.a. | I31: - | J31: - | K31: - | L31: - | M31: - | N31: -
B32: Bansí | C32: 17.693927 | D32: 15.533492 | E32: 15.109478 | F32: 19.598837 | G32: 22.213234 | H32: 22.8366 | I32: 30.068568 | J32: 31.343423 | K32: 35.770358 | L32: 5.8930898 | M32: 6.9623881 | N32: 8.1687336
B33: CIBanco | C33: 968.36604 | D33: 710.71782 | E33: 676.486 | F33: 0.24434066 | G33: 0.43622953 | H33: 23.238636 | I33: 751.26824 | J33: 593.42428 | K33: 25.689413 | L33: 1.8356538 | M33: 2.588692 | N33: 5.9698691
B34: Compartamos | C34: 0 | D34: 0 | E34: 0 | F34: n.a. | G34: n.a. | H34: n.a. | I34: - | J34: - | K34: - | L34: - | M34: - | N34: -
B35: BIAfirme | C35: 0 | D35: 0 | E35: 0 | F35: n.a. | G35: n.a. | H35: n.a. | I35: - | J35: - | K35: - | L35: - | M35: - | N35: -
B36: Bancrea | C36: 0 | D36: 0 | E36: 0 | F36: n.a. | G36: n.a. | H36: n.a. | I36: - | J36: - | K36: - | L36: - | M36: - | N36: -
B37: MUFG Bank | C37: 0 | D37: 0 | E37: 0 | F37: n.a. | G37: n.a. | H37: n.a. | I37: - | J37: - | K37: - | L37: - | M37: - | N37: -
B38: Consubanco | C38: 0 | D38: 0 | E38: 0 | F38: n.a. | G38: n.a. | H38: n.a. | I38: - | J38: - | K38: - | L38: - | M38: - | N38: -
B39: Intercam Banco | C39: 0 | D39: 0 | E39: 0 | F39: n.a. | G39: n.a. | H39: n.a. | I39: - | J39: - | K39: - | L39: - | M39: - | N39: -
B40: Autofin | C40: 66.74721 | D40: 113.15354 | E40: 126.3893 | F40: 46.034199 | G40: 26.678305 | H40: 22.700401 | I40: 25.562126 | J40: 54.131559 | K40: 52.009351 | L40: 11.76732 | M40: 14.441382 | N40: 11.806331
B41: Bankaool | C41: 0 | D41: 0 | E41: 0 | F41: n.a. | G41: n.a. | H41: n.a. | I41: - | J41: - | K41: - | L41: - | M41: - | N41: -
B42: BNP Paribas México | C42: 0 | D42: 0 | E42: 0 | F42: n.a. | G42: n.a. | H42: n.a. | I42: - | J42: - | K42: - | L42: - | M42: - | N42: -
B43: Inmobiliario Mexicano | C43: 269.76739 | D43: 221.40536 | E43: 213.43295 | F43: 4.4013042 | G43: 3.0183324 | H43: 1.4418774 | I43: 45.318972 | J43: 38.325375 | K43: 50.112148 | L43: 1.9946258 | M43: 1.1567872 | N43: 0.72255572
B44: Mizuho Bank | C44: 0 | D44: 0 | E44: 0 | F44: n.a. | G44: n.a. | H44: n.a. | I44: - | J44: - | K44: - | L44: - | M44: - | N44: -
B45: ICBC | C45: 0 | D45: 0 | E45: 0 | F45: n.a. | G45: n.a. | H45: n.a. | I45: - | J45: - | K45: - | L45: - | M45: - | N45: -
B46: Banco Covalto | C46: 0 | D46: 0 | E46: 0 | F46: n.a. | G46: n.a. | H46: n.a. | I46: - | J46: - | K46: - | L46: - | M46: - | N46: -
B47: Openbank | C47: 0 | D47: 0 | E47: 0 | F47: n.a. | G47: n.a. | H47: n.a. | I47: - | J47: - | K47: - | L47: - | M47: - | N47: -
B48: Volkswagen Bank | C48: 0 | D48: 0 | E48: 0 | F48: n.a. | G48: n.a. | H48: n.a. | I48: - | J48: - | K48: - | L48: - | M48: - | N48: -
B49: Bank of China | C49: 0 | D49: 0 | E49: 0 | F49: n.a. | G49: n.a. | H49: n.a. | I49: - | J49: - | K49: - | L49: - | M49: - | N49: -
B50: Shinhan | C50: 0 | D50: 0 | E50: 0 | F50: n.a. | G50: n.a. | H50: n.a. | I50: - | J50: - | K50: - | L50: - | M50: - | N50: -
B51: Banco Ualá | C51: 18.580702 | D51: 17.799801 | E51: 17.774698 | F51: 0 | G51: 7.5760341 | H51: 7.5867337 | I51: - | J51: 11.205626 | K51: 11.203253 | L51: 0.22756406 | M51: 0.84894208 | N51: 0.849961
B52: Banco S3 | C52: 0 | D52: 0 | E52: 0 | F52: n.a. | G52: n.a. | H52: n.a. | I52: - | J52: - | K52: - | L52: - | M52: - | N52: -
B53: KEB Hana México | C53: 0 | D53: 0 | E53: 0 | F53: n.a. | G53: n.a. | H53: n.a. | I53: - | J53: - | K53: - | L53: - | M53: - | N53: -
B54: Banco Bineo | C54: 0 | D54: 0 | E54: 0 | F54: n.a. | G54: n.a. | H54: n.a. | I54: - | J54: - | K54: - | L54: - | M54: - | N54: -
B55: Dondé Banco | C55: 0 | D55: 0 | E55: 0 | F55: n.a. | G55: n.a. | H55: n.a. | I55: - | J55: - | K55: - | L55: - | M55: - | N55: -
B56: Credit Suisse | C56: 0 | D56: 0 | E56: 0 | F56: n.a. | G56: n.a. | H56: n.a. | I56: - | J56: - | K56: - | L56: - | M56: - | N56: -
B57: Hey Banco | C57: 0 | D57: 0 | E57: 0 | F57: n.a. | G57: n.a. | H57: n.a. | I57: - | J57: - | K57: - | L57: - | M57: - | N57: -
B58: Pagatodo | C58: 0 | D58: 0 | E58: 0 | F58: n.a. | G58: n.a. | H58: n.a. | I58: - | J58: - | K58: - | L58: - | M58: - | N58: -
B59: Forjadores | C59: 0 | D59: 0 | E59: 0 | F59: n.a. | G59: n.a. | H59: n.a. | I59: - | J59: - | K59: - | L59: - | M59: - | N59: -

Sheet CaptRec
B2: Saldos de la captación bancaria
B3: Millones de pesos
C5: Captación total | F5: Depósitos exigibilidad inmediata | I5: Depósitos a plazo público en general | L5: Depósitos a plazo mercado de dinero | O5: Títulos de crédito | R5: Préstamos interbancarios y otros | U5: Cuenta global de captación sin movimientos
C6: 45505 | D6: 45839 | E6: 45870 | F6: =C6 -> 45505 | G6: =D6 -> 45839 | H6: =E6 -> 45870 | I6: =C6 -> 45505 | J6: =D6 -> 45839 | K6: =E6 -> 45870 | L6: =C6 -> 45505 | M6: =D6 -> 45839 | N6: =E6 -> 45870 | O6: =C6 -> 45505 | P6: =D6 -> 45839 | Q6: =E6 -> 45870 | R6: =C6 -> 45505 | S6: =D6 -> 45839 | T6: =E6 -> 45870 | U6: =C6 -> 45505 | V6: =D6 -> 45839 | W6: =E6 -> 45870
B7: Sistema */ | C7: 8556208 | D7: 9174885.7 | E7: 9233014.2 | F7: 5388772.7 | G7: 5769964.9 | H7: 5794950.2 | I7: 2018226.5 | J7: 2091608.5 | K7: 2103129.1 | L7: 395053.46 | M7: 484377.6 | N7: 505936.77 | O7: 353645.45 | P7: 366274.29 | Q7: 362862.96 | R7: 371551.17 | S7: 433158.66 | T7: 436091.77 | U7: 28958.733 | V7: 29501.709 | W7: 30043.39
B8: BBVA México | C8: 1854174.8 | D8: 2036733.9 | E8: 2053500.3 | F8: 1446694 | G8: 1543480.4 | H8: 1550178.2 | I8: 248875.36 | J8: 293383.71 | K8: 299998.05 | L8: 20435.362 | M8: 26947.908 | N8: 28969.2 | O8: 107419.37 | P8: 149157.34 | Q8: 150219.39 | R8: 23924.601 | S8: 16414.325 | T8: 16549.136 | U8: 6826.1203 | V8: 7350.2648 | W8: 7586.2688
B9: Santander | C9: 1042644.3 | D9: 1098918.5 | E9: 1104934 | F9: 624325.83 | G9: 663304.68 | H9: 663239.63 | I9: 253310.01 | J9: 268209.36 | K9: 272648.67 | L9: 47178.062 | M9: 62030.315 | N9: 62050.963 | O9: 83464.358 | P9: 64462.076 | Q9: 65677.243 | R9: 31886.012 | S9: 38195.625 | T9: 38606.444 | U9: 2480.006 | V9: 2716.4515 | W9: 2711.07
B10: Banorte | C10: 1142322.8 | D10: 1186183.1 | E10: 1193359.6 | F10: 707999.17 | G10: 772141.42 | H10: 774270.17 | I10: 362550.88 | J10: 363755.19 | K10: 373200.56 | L10: 4013.6935 | M10: 5177.8475 | N10: 1999.6983 | O10: 48688.107 | P10: 32108.67 | Q10: 31898.653 | R10: 13092.135 | S10: 8717.6055 | T10: 7530.1051 | U10: 5978.807 | V10: 4282.3733 | W10: 4460.4155
B11: Banamex | C11: 975268.79 | D11: 763127.06 | E11: 773161.3 | F11: 727389.16 | G11: 537405.93 | H11: 535793.15 | I11: 119113.35 | J11: 121299.03 | K11: 118824.2 | L11: 109747.69 | M11: 71137.909 | N11: 90941.379 | O11: 4149.7362 | P11: 0 | Q11: 0 | R11: 6678.5181 | S11: 24560.443 | T11: 18817.975 | U11: 8190.3388 | V11: 8723.7519 | W11: 8784.5899
