Workbook
Name \a: #REF!
Name \a: #REF!
Name \a: #REF!
Name \a: #REF!
Name \a: #REF!
Name \a: #REF!
Name \a: #REF!
Name \a: #REF!
Name \a: #REF!
Name \a: #REF!
Name \a: #REF!
Name \a: #REF!
Name \a: #REF!
Name \a: #REF!
Name \a: #REF!
Name \a: #REF!
Name \a: #REF!
Name \a: #REF!
Name \a: #REF!
Name \a: #REF!
Name \a: #REF!
Name \a: #REF!
Name \a: #REF!
Name \a: #REF!
Name \a: #REF!
Name \a: #REF!
Name \s: #REF!
Name \s: #REF!
Name \s: #REF!
Name \s: #REF!
Name \s: #REF!
Name \s: #REF!
Name \s: #REF!
Name \s: #REF!
Name \s: #REF!
Name \s: #REF!
Name \s: #REF!
Name \s: #REF!
Name \s: #REF!
Name \s: #REF!
Name \s: #REF!
Name \s: #REF!
Name \s: #REF!
Name \s: #REF!
Name \s: #REF!
Name \s: #REF!
Name \s: #REF!
Name a: #REF!
Name a: #REF!
Name a: #REF!
Name a: #REF!
Name a: #REF!
Name a: #REF!
Name a: #REF!
Name a: #REF!
Name a: #REF!
Name a: #REF!
Name a: #REF!
Name a: #REF!
Name a: #REF!

Sheet Portada
C33: ='Pm2'!G6 -> 45901
C34: =PROPER(TEXT(C33,"Mmmm"))& " de " & PROPER(TEXT(C33,"aaa")) -> Septiembre de 2025

Sheet Nota
B4: La presente información corresponde a la que, en cumplimiento a las Disposiciones aplicables a cada sector, entregan las entidades supervisadas a la CNBV a través de los reportes regulatorios debiéndose asegurar que la misma sea completa, correcta, precisa, integra, confiable y oportuna. Es importante mencionar, como lo indican las propias Disposiciones, que dicha información debe cumplir con las validaciones establecidas en el Sistema Interinstitucional de Transferencia de Información, así como los estándares de calidad que indique la Comisión a través de dicho sistema, además debe existir consistencia entre la información que las entidades incluyan en uno o más reportes regulatorios, aunque se encuentre con un nivel distinto de integración, por lo que puede ser modificada derivado de las revisiones internas que se hagan a la misma. Por lo anterior se informa que la presente publicación se genera con la información con la que se cuenta al momento de su elaboración, se recomienda su uso tomando en cuenta los aspectos anteriormente descritos.
B6: Consideraciones sobre los criterios para integrar los estados financieros del sector de Banca Múltiple a partir de enero de 2022. El 13 de marzo de 2020 se publicó en el Diario Oficial de la Federación la resolución que modificó las Disposiciones de carácter general aplicables a las instituciones de crédito (Disposiciones), la cual incorporó las nuevas normas de información emitidas por el Consejo Mexicano de Normas de Información Financiera A.C., mismas que serían exigibles a partir del 1 de enero de 2021; sin embargo, su entrada en vigor se aplazó hasta el 1 de enero de 2022, mediante la resolución modificatoria publicada en el Diario Oficial de la Federación el 4 de diciembre de 2020. En la resolución modificatoria del 4 de diciembre, se indica que los estados financieros básicos consolidados trimestrales y anuales requeridos a las instituciones de conformidad con las disposiciones señaladas correspondientes al periodo concluido el 31 de diciembre de 2022, no deberán presentarse comparativos con cada trimestre del ejercicio 2021 y por el periodo terminado el 31 de diciembre de 2021. La información del comunicado de prensa de Banca Múltiple se puede consultar en https://www.cnbv.gob.mx/PRENSA/Paginas/Boletines-de-Prensa.aspx Para la información financiera histórica se recomienda utilizar los reportes publicados en el Portafolio de Información. Para consultar las cifras bajo la norma internacional de información financiera 9 “Instrumentos Financieros” (IFRS 9), dirigirse a la sección de IFRS 9 del Portafolio Consultas.
B11: El presente Boletín Estadístico se elaboró por personal de la Comisión Nacional Bancaria y de Valores (CNBV) con la información correspondiente a septiembre de 2025 contenida en los reportes regulatorios que las entidades supervisadas envían a esta Comisión, la cual estuvo disponible a partir del 21 de octubre de 2025.
B13: Las cifras aquí contenidas no se actualizan en el tiempo, por lo que para consultar series históricas se recomienda utilizar los reportes publicados en el Portafolio de Información.
B15: Al cierre de septiembre de 2025, el sector de Banca Múltiple estuvo integrado por 52 instituciones en operación, dos más que el año anterior, considerando el inicio de operaciones de; Openbank México, S.A., Institución de Banca Múltiple, Grupo Financiero Santander México el 19 de noviembre de 2024 y de Hey Banco, S.A. Institución de Banca Múltiple, Banregio Grupo Financiero el 12 de febrero de 2025.
B17: Mediante oficio con fecha del 24 de septiembre de 2024 se aprobó el cambio de denominación de CBM Banco, S.A., Institución de Banca Múltiple, Integrante del Grupo Financiero Citibanamex a Banco Citi México, S.A., Institución de Banca Múltiple, Grupo Financiero Citi México, en el presente Boletin estadístico (Citi México). Mediante oficio con fecha del 24 de septiembre de 2024 se aprobó el cambio de denominación de ABC Capital, S.A., Institución de Banca Múltiple (ABC Capital) a Ualá, S.A., Institución de Banca Múltiple, en el presente Boletín estadístico (Banco Ualá).
B19: El 1 de diciembre de 2024 Citigroup (Citigroup Inc.) concretó la separación del negocio de banca corporativa y privada de los negocios de consumo y banca empresarial. A partir de esa fecha, Citi opera en México a través de dos grupos financieros separados e independientes: Grupo Financiero Banamex y Grupo Financiero Citi México; por lo anterior, Citi gestionará el negocio de banca corporativa y privada (cartera comercial) y Banamex llevará el negocio de consumo y la banca empresarial (cartera comercial, de consumo y a la vivienda).
B21: El 18 de diciembre de 2024 se le notifica a Banco Sabadell, S.A., Institución de Banca Múltiple, que podrá llevar a cabo la fusión con Sabcapital, S.A. de C.V., Sociedad Financiera de Objeto Múltiple, Entidad Regulada, como sociedad fusionada, a partir de enero de 2025.

Sheet Índice
B4: Índice
B5: Presentación
B7: I. Índice de Capitalización y Evaluación de la Calidad de la Información
B8: Artículo 121 Ley de Instituciones de Crédito
B9: Metodología de Evaluación Sistema Financiero
B10: Metodología Evaluación Cartera Comercial
B11: Metodología Evaluación Cartera a la Vivienda
B12: Evaluación de Calidad a la Información
B14: II. Estadísticas de la Banca Múltiple
B15: Principales Rubros del Estado de Situación Financiera y Estado de Resultado Integral
B16: Indicadores Financieros
B17: Cartera de Crédito Total
... B36: III. Estados Financieros

Sheet Presentación
A2: Presentación
A3: La Comisión Nacional Bancaria y de Valores (CNBV) emite el presente documento para cumplir con lo dispuesto por la fracción XXIII del Artículo 4º de la Ley de la Comisión Nacional Bancaria y de Valores. Mediante la difusión de este boletín estadístico se persigue promover la transparencia y autorregulación del sector de Banca Múltiple, así como proveer a los mercados y al público en general información suficiente y confiable, que permita el análisis y seguimiento de estas instituciones.
A4: El boletín estadístico se encuentra dividido en 3 secciones: En primer lugar se informa sobre el nivel del Índice de Capitalización de las instituciones y su correspondiente categoría de Alertas Tempranas. Además, se presenta la tabla de Evaluación de la Calidad y Oportunidad de la Información con el que se califica el envío de los reportes regulatorios que las entidades supervisadas entregan a este organismo.
A5: En segundo lugar se muestra la información estadística relevante y principales indicadores de rentabilidad de cada institución de banca múltiple que proviene o se calcula con sus estados financieros consolidados.
A6: Enseguida se presenta la información reportada por las 52 instituciones de banca múltiple en operación correspondiente a septiembre de 2025, consolidada con la de sus SOFOMER (Sociedades Financieras de Objeto Múltiple, Entidades Reguladas) en el caso de los siguientes bancos: Banamex con Tarjetas Banamex; Santander con Santander Inclusión Financiera; CI Banco con Finanmadrid México; Banco del Bajío con Financiera Bajío; Banregio con Start Banregio; Inbursa con STM Financial, SOFOM Inbursa y CETELEM Inbursa; Afirme con Arrendadora Afirme; Banco Base con Arrendadora Base, Invex con Invex Consumo; Bancrea con Arrendadora Bancrea, así como Ve por Más con Arrendadora Ve por Más.
A7: Se incluyen los indicadores financieros destacados, los saldos de cada tipo de crédito y de la captación de recursos.
A8: Por último, se hace un compendio de los estados financieros que las instituciones de banca múltiple reportaron a esta Comisión, al igual que en las secciones anteriores, se incluye información consolidada de las instituciones de banca múltiple con las SOFOMER de cada banco.

Sheet Portadilla I
A7: I. Índice de Capitalización y Evaluación de la Calidad de la Información.
A8: El objetivo de este apartado es proporcionar al público los indicadores de capitalización de los bancos, con las cifras disponibles en la fecha de elaboración del presente boletín, así como la clasificación de las instituciones de banca múltiple en distintas categorías, de acuerdo con las disposiciones de Alertas Tempranas.
A9: Por otra parte, se presenta la evaluación de la calidad y oportunidad de la información que entregan las instituciones a este Organismo, la cual considera la oportunidad con la que reportan y el número de reenvíos.

Sheet Art_121
B4: REGLAS DE CARÁCTER GENERAL A QUE SE REFIERE EL ARTÍCULO 121 DE LA LEY DE INSTITUCIONES DE CRÉDITO.
B5: Con el fin de mantener informado al público sobre el desempeño de las instituciones que conforman al sector de banca múltiple, la CNBV con fundamento en lo dispuesto en el artículo 121 de la Ley de Instituciones de Crédito, en relación con los artículos 220 y 221 de las Disposiciones de carácter general aplicables a las instituciones de crédito (las Disposiciones), da a conocer la clasificación de las instituciones de banca múltiple en categorías, con base en el índice de capitalización requerido conforme a las disposiciones aplicables a los requerimientos de capitalización, emitidas por esta Comisión en términos del artículo 50 de la Ley de Instituciones de Crédito
B6: CLASIFICACIÓN DE LAS INSTITUCIONES DE BANCA MÚLTIPLE DE ACUERDO CON EL ARTÍCULO 220 DE LAS DISPOSICIONES
B7: INDICADORES DE CAPITALIZACIÓN CIFRAS AL 31 DE AGOSTO DE 20251/
B8: Institución | C8: CCB 2/ % | D8: CCF 3/ % | E8: ICAP 4/ % | F8: Categoría 5/
B9: Actinver | C9: 17.464176 | D9: 17.464176 | E9: 17.464176 | F9: I
B10: Afirme | C10: 11.433743 | D10: 10.412407 | E10: 15.314787 | F10: I
B11: Banamex | C11: 21.082687 | D11: 17.958478 | E11: 21.082687 | F11: I
B12: Banca Mifel | C12: 16.077282 | D12: 16.077282 | E12: 16.190525 | F12: I
B13: Banco Azteca | C13: 13.550355 | D13: 13.550355 | E13: 14.011343 | F13: I
B14: Banco Base | C14: 22.5006 | D14: 22.5006 | E14: 22.5006 | F14: I
B15: Banco Bineo | C15: 235.95282 | D15: 235.95282 | E15: 235.95282 | F15: I
B16: Banco Covalto | C16: 13.189118 | D16: 13.189118 | E16: 13.189118 | F16: I
B17: Banco del Bajío | C17: 15.532215 | D17: 15.532215 | E17: 15.532215 | F17: I
B18: Banco S3 | C18: 175.3321 | D18: 175.3321 | E18: 175.3321 | F18: I
B19: Banco Ualá | C19: 46.199143 | D19: 46.199143 | E19: 46.199143 | F19: I
B20: BanCoppel | C20: 15.806196 | D20: 15.806196 | E20: 15.806196 | F20: I
... B60: Volkswagen Bank | C60: 27.35858 | D60: 27.35858 | E60: 27.35858 | F60: I
B61: Total Banca Múltiple | C61: 18.2732 | D61: 16.9631 | E61: 20.3149
B62: 1/ Dado a conocer a esta Comisión por el Banco de México el 10 de octubre de 2025, con base en la información entregada por las Instituciones, conforme a lo dispuesto por el artículo 2 Bis y 2 Bis 4 de las Disposiciones.
B63: 2/ CCB (Coeficiente de Capital Básico) = (Capital Fundamental + Capital no Fundamental) / Activos Ponderados Sujetos a Riesgo Total.
B64: 3/ CCF (Coeficiente de Capital Fundamental) = Capital Fundamental / Activos Ponderados Sujetos a Riesgo Total.
B65: 4/ ICAP (Índice de Capitalización) = Capital Neto / Activos Ponderados Sujetos a Riesgo Total.
B66: 5/ Categorías de Alertas Tempranas determinadas con base en el artículo 220 de las Disposiciones.

Sheet Ficha Técnica
B11: Evaluación de la Calidad de la Información
B12: Banca Múltiple
B14: Derivado de la mejora continua en los procesos de verificación de la calidad en la información, esta comisión ha modificado los criterios de evaluación de la calidad y los hábitos de envío de los reportes regulatorios que son transmitidos por las Instituciones de Banca Múltiple, por lo cual, se ha optado por generar un indicador único de calidad que refleje el estado actual obtenido para los reportes regulatorios, clasificados en 5 tipos de información distintos:
B20: Clave | C20: Clasificación | E20: Reportes | F20: Descripción
B21: 1 | C21: Situación financiera | E21: 22 | F21: Reportes de las series R01, R04 A, R06, R07, R08, R10, R12 , R13, R14, R32, R34 y R36.
B22: 2 | C22: Cartera Comercial | E22: 11 | F22: Reportes de la serie R04 C.
B23: 3 | C23: Cartera a la Vivienda | E23: 4 | F23: Reportes de la serie R04 H.
B24: 4 | C24: Captación | E24: 1 | F24: Reporte R24 B-2421.
B25: 5 | C25: Operativos | E25: 23 | F25: Reportes de las series R15, R24 B-2422, R24 B-2423, R24 C, R24 D, R24 E, R26, R27, R28, R29 y R35.
B27: Tomando en consideración la anterior clasificación, se generan 2 métricas para el cálculo del indicador único, como a continuación se muestra:
B30: 1. Calidad
B32: Para la medición del porcentaje de calidad obtenido, se identifican las incidencias presentadas en la ventana de evaluación del periodo, estas incidencias tienen ponderadores específicos para cada IBM, los cuáles se calculan a través de la distribución de sus errores presentados de manera histórica y se omiten aquellos reportes que por la naturaleza de su negocio no le son aplicables a cada IBM.
B37: 2. Oportunidad 1/
B39: Para la evaluación de hábitos de envío se consideran 3 conductas que no son adecuadas, siendo estas, los reenvíos, entregas extemporáneas y reportes omisos a la fecha de corte y que se encuentren en la ventana de evaluación. De igual forma se ponderan en la ventana de evaluación en función del comportamiento histórico y se ponderan de diferente forma en función del porcentaje de calidad obtenido.
B43: 2. Calificación final
B45: Tomando en consideración las 2 calificaciones previas, se determina una calificación final, la cual servirá como indicador general de evaluación para las IBM, el cual se calcula multiplicando el porcentaje de calidad obtenido por el porcentaje de oportunidad.
B50: Determinación de semáforos
B52: La determinación de semáforos se realiza con base en los siguientes criterios:
B54: Rojo | D54: Se asigna para instituciones que tienen una calificación final inferior a 90 puntos.
B56: Amarillo | D56: Se asigna para las instituciones que tienen una calificación de 90 o más y menor de 95 puntos.
B58: Verde | D58: Se asigna para las instituciones con 95 puntos o más.
B60: 1/ Debido a las intermitencias en el aplicativo SITI WEB, que han ocasionado retrasos involuntarios en la recepción de los Reportes Regulatorios transmitidos a la CNBV, la calificación no penaliza los hábitos de envío desde diciembre de 2023 hasta la fecha.

Sheet Evaluación Calidad
B6: Evaluación de la Calidad de la Información
B7: Banca Múltiple
B8: septiembre 2025
J9: Fecha de corte: 21 de octubre de 2025
B10: RANKING | C10: INSTITUCIÓN | G10: CALIFICACIÓN | J10: CALIDAD | K10: OPORTUNIDAD
B11: 1 | C11: 040126 | D11: Credit Suisse | G11: 100 | H11: 100 | J11: 100 | K11: 100
B12: 1 | C12: 040139 | D12: BIAfirme | G12: 100 | H12: 100 | J12: 100 | K12: 100
B13: 1 | C13: 040162 | D13: KEB Hana México | G13: 100 | H13: 100 | J13: 100 | K13: 100
B14: 1 | C14: 040165 | D14: Banco Bineo | G14: 100 | H14: 100 | J14: 100 | K14: 100
B15: 1 | C15: 040167 | D15: Hey Banco | G15: 100 | H15: 100 | J15: 100 | K15: 100
B16: 1 | C16: 040169 | D16: Openbank | G16: 100 | H16: 100 | J16: 100 | K16: 100
B17: 7 | C17: 040002 | D17: Banamex | G17: 99.93 | H17: 99.93 | J17: 99.93 | K17: 100
B18: 8 | C18: 040151 | D18: Dondé Banco | G18: 99.62 | H18: 99.62 | J18: 99.62 | K18: 100
B19: 9 | C19: 040129 | D19: Barclays | G19: 99.56 | H19: 99.56 | J19: 99.56 | K19: 100
B20: 10 | C20: 040149 | D20: Forjadores | G20: 99.32 | H20: 99.32 | J20: 99.32 | K20: 100
B21: 11 | C21: 040147 | D21: Bankaool | G21: 99.23 | H21: 99.23 | J21: 99.23 | K21: 100
B22: 12 | C22: 040130 | D22: Compartamos | G22: 98.97 | H22: 98.97 | J22: 98.97 | K22: 100
... B61: 51 | C61: 040136 | D61: Intercam Banco | G61: 76.38 | H61: 76.38 | J61: 76.38 | K61: 100
B101: =_xlfn.XLOOKUP(C101,[1]Calificación!D:D,[1]Calificación!A:A,"",0,1) | C101: =IF([1]Calificación!D89=0,"",[1]Calificación!D89) | D101: =IFERROR(VLOOKUP(C101,[1]Calificación!$D$1:$X$52,2,0),"") | G101: =IFERROR(VLOOKUP(C101,[1]Calificación!$D$1:$X$52,5,0),"") | H101: =IFERROR(VLOOKUP(C101,[1]Calificación!$D$1:$X$52,6,0),"") | J101: =IFERROR(VLOOKUP(C101,[1]Calificación!$D$1:$X$52,3,0),"") | K101: =IFERROR(VLOOKUP(C101,[1]Calificación!$D$1:$X$52,4,0),"")
B102: =_xlfn.XLOOKUP(C102,[1]Calificación!D:D,[1]Calificación!A:A,"",0,1) | C102: =IF([1]Calificación!D90=0,"",[1]Calificación!D90) | D102: =IFERROR(VLOOKUP(C102,[1]Calificación!$D$1:$X$52,2,0),"") | G102: =IFERROR(VLOOKUP(C102,[1]Calificación!$D$1:$X$52,5,0),"") | H102: =IFERROR(VLOOKUP(C102,[1]Calificación!$D$1:$X$52,6,0),"") | J102: =IFERROR(VLOOKUP(C102,[1]Calificación!$D$1:$X$52,3,0),"") | K102: =IFERROR(VLOOKUP(C102,[1]Calificación!$D$1:$X$52,4,0),"")
B103: =_xlfn.XLOOKUP(C103,[1]Calificación!D:D,[1]Calificación!A:A,"",0,1) | C103: =IF([1]Calificación!D91=0,"",[1]Calificación!D91) | D103: =IFERROR(VLOOKUP(C103,[1]Calificación!$D$1:$X$52,2,0),"") | G103: =IFERROR(VLOOKUP(C103,[1]Calificación!$D$1:$X$52,5,0),"") | H103: =IFERROR(VLOOKUP(C103,[1]Calificación!$D$1:$X$52,6,0),"") | J103: =IFERROR(VLOOKUP(C103,[1]Calificación!$D$1:$X$52,3,0),"") | K103: =IFERROR(VLOOKUP(C103,[1]Calificación!$D$1:$X$52,4,0),"")
B104: =_xlfn.XLOOKUP(C104,[1]Calificación!D:D,[1]Calificación!A:A,"",0,1) | C104: =IF([1]Calificación!D92=0,"",[1]Calificación!D92) | D104: =IFERROR(VLOOKUP(C104,[1]Calificación!$D$1:$X$52,2,0),"") | G104: =IFERROR(VLOOKUP(C104,[1]Calificación!$D$1:$X$52,5,0),"") | H104: =IFERROR(VLOOKUP(C104,[1]Calificación!$D$1:$X$52,6,0),"") | J104: =IFERROR(VLOOKUP(C104,[1]Calificación!$D$1:$X$52,3,0),"") | K104: =IFERROR(VLOOKUP(C104,[1]Calificación!$D$1:$X$52,4,0),"")
B105: =_xlfn.XLOOKUP(C105,[1]Calificación!D:D,[1]Calificación!A:A,"",0,1) | C105: =IF([1]Calificación!D93=0,"",[1]Calificación!D93) | D105: =IFERROR(VLOOKUP(C105,[1]Calificación!$D$1:$X$52,2,0),"") | G105: =IFERROR(VLOOKUP(C105,[1]Calificación!$D$1:$X$52,5,0),"") | H105: =IFERROR(VLOOKUP(C105,[1]Calificación!$D$1:$X$52,6,0),"") | J105: =IFERROR(VLOOKUP(C105,[1]Calificación!$D$1:$X$52,3,0),"") | K105: =IFERROR(VLOOKUP(C105,[1]Calificación!$D$1:$X$52,4,0),"")
B106: =_xlfn.XLOOKUP(C106,[1]Calificación!D:D,[1]Calificación!A:A,"",0,1) | C106: =IF([1]Calificación!D94=0,"",[1]Calificación!D94) | D106: =IFERROR(VLOOKUP(C106,[1]Calificación!$D$1:$X$52,2,0),"") | G106: =IFERROR(VLOOKUP(C106,[1]Calificación!$D$1:$X$52,5,0),"") | H106: =IFERROR(VLOOKUP(C106,[1]Calificación!$D$1:$X$52,6,0),"") | J106: =IFERROR(VLOOKUP(C106,[1]Calificación!$D$1:$X$52,3,0),"") | K106: =IFERROR(VLOOKUP(C106,[1]Calificación!$D$1:$X$52,4,0),"")
B107: =_xlfn.XLOOKUP(C107,[1]Calificación!D:D,[1]Calificación!A:A,"",0,1) | C107: =IF([1]Calificación!D95=0,"",[1]Calificación!D95) | D107: =IFERROR(VLOOKUP(C107,[1]Calificación!$D$1:$X$52,2,0),"") | G107: =IFERROR(VLOOKUP(C107,[1]Calificación!$D$1:$X$52,5,0),"") | H107: =IFERROR(VLOOKUP(C107,[1]Calificación!$D$1:$X$52,6,0),"") | J107: =IFERROR(VLOOKUP(C107,[1]Calificación!$D$1:$X$52,3,0),"") | K107: =IFERROR(VLOOKUP(C107,[1]Calificación!$D$1:$X$52,4,0),"")
B108: =_xlfn.XLOOKUP(C108,[1]Calificación!D:D,[1]Calificación!A:A,"",0,1) | C108: =IF([1]Calificación!D96=0,"",[1]Calificación!D96) | D108: =IFERROR(VLOOKUP(C108,[1]Calificación!$D$1:$X$52,2,0),"") | G108: =IFERROR(VLOOKUP(C108,[1]Calificación!$D$1:$X$52,5,0),"") | H108: =IFERROR(VLOOKUP(C108,[1]Calificación!$D$1:$X$52,6,0),"") | J108: =IFERROR(VLOOKUP(C108,[1]Calificación!$D$1:$X$52,3,0),"") | K108: =IFERROR(VLOOKUP(C108,[1]Calificación!$D$1:$X$52,4,0),"")
B109: =_xlfn.XLOOKUP(C109,[1]Calificación!D:D,[1]Calificación!A:A,"",0,1) | C109: =IF([1]Calificación!D97=0,"",[1]Calificación!D97) | D109: =IFERROR(VLOOKUP(C109,[1]Calificación!$D$1:$X$52,2,0),"") | G109: =IFERROR(VLOOKUP(C109,[1]Calificación!$D$1:$X$52,5,0),"") | H109: =IFERROR(VLOOKUP(C109,[1]Calificación!$D$1:$X$52,6,0),"") | J109: =IFERROR(VLOOKUP(C109,[1]Calificación!$D$1:$X$52,3,0),"") | K109: =IFERROR(VLOOKUP(C109,[1]Calificación!$D$1:$X$52,4,0),"")
B110: =_xlfn.XLOOKUP(C110,[1]Calificación!D:D,[1]Calificación!A:A,"",0,1) | C110: =IF([1]Calificación!D98=0,"",[1]Calificación!D98) | D110: =IFERROR(VLOOKUP(C110,[1]Calificación!$D$1:$X$52,2,0),"") | G110: =IFERROR(VLOOKUP(C110,[1]Calificación!$D$1:$X$52,5,0),"") | H110: =IFERROR(VLOOKUP(C110,[1]Calificación!$D$1:$X$52,6,0),"") | J110: =IFERROR(VLOOKUP(C110,[1]Calificación!$D$1:$X$52,3,0),"") | K110: =IFERROR(VLOOKUP(C110,[1]Calificación!$D$1:$X$52,4,0),"")
B111: =_xlfn.XLOOKUP(C111,[1]Calificación!D:D,[1]Calificación!A:A,"",0,1) | C111: =IF([1]Calificación!D99=0,"",[1]Calificación!D99) | D111: =IFERROR(VLOOKUP(C111,[1]Calificación!$D$1:$X$52,2,0),"") | G111: =IFERROR(VLOOKUP(C111,[1]Calificación!$D$1:$X$52,5,0),"") | H111: =IFERROR(VLOOKUP(C111,[1]Calificación!$D$1:$X$52,6,0),"") | J111: =IFERROR(VLOOKUP(C111,[1]Calificación!$D$1:$X$52,3,0),"") | K111: =IFERROR(VLOOKUP(C111,[1]Calificación!$D$1:$X$52,4,0),"")
B112: =_xlfn.XLOOKUP(C112,[1]Calificación!D:D,[1]Calificación!A:A,"",0,1) | C112: =IF([1]Calificación!D100=0,"",[1]Calificación!D100) | D112: =IFERROR(VLOOKUP(C112,[1]Calificación!$D$1:$X$52,2,0),"") | G112: =IFERROR(VLOOKUP(C112,[1]Calificación!$D$1:$X$52,5,0),"") | H112: =IFERROR(VLOOKUP(C112,[1]Calificación!$D$1:$X$52,6,0),"") | J112: =IFERROR(VLOOKUP(C112,[1]Calificación!$D$1:$X$52,3,0),"") | K112: =IFERROR(VLOOKUP(C112,[1]Calificación!$D$1:$X$52,4,0),"")
... B131: =_xlfn.XLOOKUP(C131,[1]Calificación!D:D,[1]Calificación!A:A,"",0,1) | C131: =IF([1]Calificación!D119=0,"",[1]Calificación!D119) | D131: =IFERROR(VLOOKUP(C131,[1]Calificación!$D$1:$X$52,2,0),"") | G131: =IFERROR(VLOOKUP(C131,[1]Calificación!$D$1:$X$52,5,0),"") | H131: =IFERROR(VLOOKUP(C131,[1]Calificación!$D$1:$X$52,6,0),"") | J131: =IFERROR(VLOOKUP(C131,[1]Calificación!$D$1:$X$52,3,0),"") | K131: =IFERROR(VLOOKUP(C131,[1]Calificación!$D$1:$X$52,4,0),"")

Sheet Evaluación Calidad Grupos 
B7: Evaluación de la Calidad de la Información
B8: Banca Múltiple
B9: septiembre 2025
K10: Fecha de corte: 21 de octubre de 2025
B11: RANKING | C11: INSTITUCIÓN | G11: CALIFICACIÓN | K11: CALIDAD | L11: OPORTUNIDAD
B12: G7
B13: 1 | C13: 040002 | D13: Banamex | G13: 99.93 | H13: 99.93 | K13: 99.93 | L13: 100 | O13: G-7
B14: 2 | C14: 040072 | D14: Banorte | G14: 97.93 | H14: 97.93 | K14: 97.93 | L14: 100 | O14: G-7
B15: 3 | C15: 040044 | D15: Scotiabank | G15: 96.67 | H15: 96.67 | K15: 96.67 | L15: 100 | O15: G-7
B16: 4 | C16: 040021 | D16: HSBC | G16: 94.42 | H16: 94.42 | K16: 94.42 | L16: 100 | O16: G-7
B17: 5 | C17: 040012 | D17: BBVA México | G17: 91.84 | H17: 91.84 | K17: 91.84 | L17: 100 | O17: G-7
B18: 6 | C18: 040036 | D18: Inbursa | G18: 90.76 | H18: 90.76 | K18: 90.76 | L18: 100 | O18: G-7
B19: 7 | C19: 040014 | D19: Santander | G19: 85.83 | H19: 85.83 | K19: 85.83 | L19: 100 | O19: G-7
B21: BANCOS CAMBIARIOS
B22: 1 | C22: 040112 | D22: Monex | G22: 97.42 | H22: 97.42 | K22: 97.42 | L22: 100 | O22: Bancos Cambiarios
B23: 2 | C23: 040145 | D23: Banco Base | G23: 90.56 | H23: 90.56 | K23: 90.56 | L23: 100 | O23: Bancos Cambiarios
B24: 3 | C24: 040136 | D24: Intercam Banco | G24: 76.38 | H24: 76.38 | K24: 76.38 | L24: 100 | O24: Bancos Cambiarios
B26: BANCA DE INVERSIÓN Y OTROS SERVICIOS
B27: 1 | C27: 040126 | D27: Credit Suisse | G27: 100 | H27: 100 | K27: 100 | L27: 100 | O27: Banca de Inversión y Otros Servicios
B28: 1 | C28: 040139 | D28: BIAfirme | G28: 100 | H28: 100 | K28: 100 | L28: 100 | O28: Banca de Inversión y Otros Servicios
B29: 3 | C29: 040129 | D29: Barclays | G29: 99.56 | H29: 99.56 | K29: 99.56 | L29: 100 | O29: Banca de Inversión y Otros Servicios
B30: 4 | C30: 040106 | D30: Bank of America | G30: 98.04 | H30: 98.04 | K30: 98.04 | L30: 100 | O30: Banca de Inversión y Otros Servicios
B31: 5 | C31: 040164 | D31: BNP Paribas México | G31: 97.99 | H31: 97.99 | K31: 97.99 | L31: 100 | O31: Banca de Inversión y Otros Servicios
B32: 6 | C32: 040148 | D32: Pagatodo | G32: 97.96 | H32: 97.96 | K32: 97.96 | L32: 100 | O32: Banca de Inversión y Otros Servicios
B33: 7 | C33: 040160 | D33: Banco S3 | G33: 97.07 | H33: 97.07 | K33: 97.07 | L33: 100 | O33: Banca de Inversión y Otros Servicios
B34: 8 | C34: 040124 | D34: Citi México (Antes CBM Banco) | G34: 95.72 | H34: 95.72 | K34: 95.72 | L34: 100 | O34: Banca de Inversión y Otros Servicios
B35: 9 | C35: 040110 | D35: J.P. Morgan | G35: 95.45 | H35: 95.45 | K35: 95.45 | L35: 100 | O35: Banca de Inversión y Otros Servicios
B36: 10 | C36: 040108 | D36: MUFG Bank | G36: 94.42 | H36: 94.42 | K36: 94.42 | L36: 100 | O36: Banca de Inversión y Otros Servicios
B37: 11 | C37: 040062 | D37: Afirme | G37: 93.36 | H37: 93.36 | K37: 93.36 | L37: 100 | O37: Banca de Inversión y Otros Servicios
B38: 12 | C38: 040059 | D38: Invex | G38: 87.47 | H38: 87.47 | K38: 87.47 | L38: 100 | O38: Banca de Inversión y Otros Servicios
B40: COMERCIAL MEDIANO
B41: 1 | C41: 040030 | D41: Banco del Bajío | G41: 98.87 | H41: 98.87 | K41: 98.87 | L41: 100 | O41: Comercial Mediano
B42: 2 | C42: 040113 | D42: Ve por Más | G42: 98.7 | H42: 98.7 | K42: 98.7 | L42: 100 | O42: Comercial Mediano
B43: 3 | C43: 040156 | D43: Sabadell | G43: 97.89 | H43: 97.89 | K43: 97.89 | L43: 100 | O43: Comercial Mediano
B44: 4 | C44: 040058 | D44: Banregio | G44: 97.87 | H44: 97.87 | K44: 97.87 | L44: 100 | O44: Comercial Mediano
B45: 5 | C45: 040042 | D45: Banca Mifel | G45: 95.12 | H45: 95.12 | K45: 95.12 | L45: 100 | O45: Comercial Mediano
B46: 6 | C46: 040132 | D46: Multiva | G46: 94.12 | H46: 94.12 | K46: 94.12 | L46: 100 | O46: Comercial Mediano
B48: COMERCIAL PEQUEÑO
B49: 1 | C49: 040162 | D49: KEB Hana México | G49: 100 | H49: 100 | K49: 100 | L49: 100 | O49: Comercial pequeño
B50: 2 | C50: 040151 | D50: Dondé Banco | G50: 99.62 | H50: 99.62 | K50: 99.62 | L50: 100 | O50: Comercial pequeño
B51: 3 | C51: 040147 | D51: Bankaool | G51: 99.23 | H51: 99.23 | K51: 99.23 | L51: 100 | O51: Comercial pequeño
B52: 4 | C52: 040159 | D52: Bank of China | G52: 98.38 | H52: 98.38 | K52: 98.38 | L52: 100 | O52: Comercial pequeño
B53: 5 | C53: 040060 | D53: Bansí | G53: 98.12 | H53: 98.12 | K53: 98.12 | L53: 100 | O53: Comercial pequeño
B54: 6 | C54: 040155 | D54: ICBC | G54: 97.72 | H54: 97.72 | K54: 97.72 | L54: 100 | O54: Comercial pequeño
B55: 7 | C55: 040157 | D55: Shinhan | G55: 97.69 | H55: 97.69 | K55: 97.69 | L55: 100 | O55: Comercial pequeño
B56: 8 | C56: 040133 | D56: Actinver | G56: 97.19 | H56: 97.19 | K56: 97.19 | L56: 100 | O56: Comercial pequeño
B57: 9 | C57: 040154 | D57: Covalto | G57: 97 | H57: 97 | K57: 97 | L57: 100 | O57: Comercial pequeño
B58: 10 | C58: 040158 | D58: Mizuho Bank | G58: 96.24 | H58: 96.24 | K58: 96.24 | L58: 100 | O58: Comercial pequeño
B59: 11 | C59: 040138 | D59: Ualá | G59: 95.6 | H59: 95.6 | K59: 95.6 | L59: 100 | O59: Comercial pequeño
B60: 12 | C60: 040150 | D60: Inmobiliario Mexicano | G60: 95.44 | H60: 95.44 | K60: 95.44 | L60: 100 | O60: Comercial pequeño
... B62: 14 | C62: 040152 | D62: Bancrea | G62: 86.69 | H62: 86.69 | K62: 86.69 | L62: 100 | O62: Comercial pequeño
B64: CRÉDITOS A LOS HOGARES
B65: 1 | C65: 040165 | D65: Banco Bineo | G65: 100 | H65: 100 | K65: 100 | L65: 100 | O65: Créditos a los Hogares
B66: 1 | C66: 040167 | D66: Hey Banco | G66: 100 | H66: 100 | K66: 100 | L66: 100 | O66: Créditos a los Hogares
B67: 1 | C67: 040169 | D67: Openbank | G67: 100 | H67: 100 | K67: 100 | L67: 100 | O67: Créditos a los Hogares
B68: 4 | C68: 040149 | D68: Forjadores | G68: 99.32 | H68: 99.32 | K68: 99.32 | L68: 100 | O68: Créditos a los Hogares
B69: 5 | C69: 040130 | D69: Compartamos | G69: 98.97 | H69: 98.97 | K69: 98.97 | L69: 100 | O69: Créditos a los Hogares
B70: 6 | C70: 040141 | D70: Volkswagen Bank | G70: 98.84 | H70: 98.84 | K70: 98.84 | L70: 100 | O70: Créditos a los Hogares
B71: 7 | C71: 040137 | D71: Bancoppel | G71: 96.46 | H71: 96.46 | K71: 96.46 | L71: 100 | O71: Créditos a los Hogares
B72: 8 | C72: 040127 | D72: Banco Azteca | G72: 95.96 | H72: 95.96 | K72: 95.96 | L72: 100 | O72: Créditos a los Hogares
B73: 9 | C73: 040140 | D73: Consubanco | G73: 89.92 | H73: 89.92 | K73: 89.92 | L73: 100 | O73: Créditos a los Hogares

Sheet Evaluación Calidad Detallada
B3: Evaluación de la Calidad de la Información
B4: Banca Múltiple
B5: septiembre 2025
M6: Fecha de corte: 21 de octubre de 2025
B8: RANKING | C8: INSTITUCIÓN | G8: SITUACIÓN FINANCIERA | J8: CARTERA COMERCIAL | M8: CARTERA A LA VIVIENDA | P8: PRODUCTOS DE CAPTACIÓN | S8: OPERATIVOS
G9: CALIDAD | H9: OPORTUNIDAD | J9: CALIDAD | K9: OPORTUNIDAD | M9: CALIDAD | N9: OPORTUNIDAD | P9: CALIDAD | Q9: OPORTUNIDAD | S9: CALIDAD | T9: OPORTUNIDAD
B10: 1 | C10: 040126 | D10: Credit Suisse | G10: 100 | H10: 100 | J10: n.a | K10: 100 | M10: n.a | N10: 100 | P10: 100 | Q10: 100 | S10: 100 | T10: 100
B11: 1 | C11: 040139 | D11: BIAfirme | G11: 100 | H11: 100 | J11: 100 | K11: 100 | M11: n.a | N11: 100 | P11: 100 | Q11: 100 | S11: 100 | T11: 100
B12: 1 | C12: 040162 | D12: KEB Hana México | G12: 100 | H12: 100 | J12: 100 | K12: 100 | M12: n.a | N12: 100 | P12: 100 | Q12: 100 | S12: 100 | T12: 100
B13: 1 | C13: 040165 | D13: Banco Bineo | G13: 100 | H13: 100 | J13: n.a | K13: 100 | M13: n.a | N13: 100 | P13: 100 | Q13: 100 | S13: 100 | T13: 100
B14: 1 | C14: 040167 | D14: Hey Banco | G14: 100 | H14: 100 | J14: n.a | K14: 100 | M14: n.a | N14: 100 | P14: 100 | Q14: 100 | S14: 100 | T14: 100
B15: 1 | C15: 040169 | D15: Openbank | G15: 100 | H15: 100 | J15: n.a | K15: 100 | M15: n.a | N15: 100 | P15: 100 | Q15: 100 | S15: 100 | T15: 100
B16: 7 | C16: 040002 | D16: Banamex | G16: 100 | H16: 100 | J16: 99.77 | K16: 100 | M16: 100 | N16: 100 | P16: 100 | Q16: 100 | S16: 100 | T16: 100
B17: 8 | C17: 040151 | D17: Dondé Banco | G17: 100 | H17: 100 | J17: 99.54 | K17: 100 | M17: n.a | N17: 100 | P17: 94.87 | Q17: 100 | S17: 100 | T17: 100
B18: 9 | C18: 040129 | D18: Barclays | G18: 99.1 | H18: 100 | J18: n.a | K18: 100 | M18: n.a | N18: 100 | P18: 100 | Q18: 100 | S18: 100 | T18: 100
B19: 10 | C19: 040149 | D19: Forjadores | G19: 100 | H19: 100 | J19: 98.38 | K19: 100 | M19: n.a | N19: 100 | P19: 100 | Q19: 100 | S19: 100 | T19: 100
B20: 11 | C20: 040147 | D20: Bankaool | G20: 99.47 | H20: 100 | J20: 98.85 | K20: 100 | M20: n.a | N20: 100 | P20: 100 | Q20: 100 | S20: 99.49 | T20: 100
B21: 12 | C21: 040130 | D21: Compartamos | G21: 99.01 | H21: 100 | J21: 99.76 | K21: 100 | M21: n.a | N21: 100 | P21: 84.62 | Q21: 100 | S21: 100 | T21: 100
B22: 13 | C22: 040030 | D22: Banco del Bajío | G22: 100 | H22: 100 | J22: 96.39 | K22: 100 | M22: 99.76 | N22: 100 | P22: 100 | Q22: 100 | S22: 100 | T22: 100
B23: 14 | C23: 040141 | D23: Volkswagen Bank | G23: 99.49 | H23: 100 | J23: n.a | K23: 100 | M23: n.a | N23: 100 | P23: 100 | Q23: 100 | S23: 100 | T23: 100
B24: 15 | C24: 040113 | D24: Ve por Más | G24: 100 | H24: 100 | J24: 95.74 | K24: 100 | M24: 100 | N24: 100 | P24: 100 | Q24: 100 | S24: 99.49 | T24: 100
B25: 16 | C25: 040159 | D25: Bank of China | G25: 99.72 | H25: 100 | J25: 97.1 | K25: 100 | M25: n.a | N25: 100 | P25: 92.31 | Q25: 100 | S25: 100 | T25: 100
B26: 17 | C26: 040060 | D26: Bansí | G26: 100 | H26: 100 | J26: 95.93 | K26: 100 | M26: 100 | N26: 100 | P26: 100 | Q26: 100 | S26: 95.38 | T26: 100
B27: 18 | C27: 040106 | D27: Bank of America | G27: 98.87 | H27: 100 | J27: 98.6 | K27: 100 | M27: n.a | N27: 100 | P27: 97.44 | Q27: 100 | S27: 95.38 | T27: 100
B28: 19 | C28: 040164 | D28: BNP Paribas México | G28: 96.1 | H28: 100 | J28: n.a | K28: 100 | M28: n.a | N28: 100 | P28: n.a | Q28: 100 | S28: 100 | T28: 100
B29: 20 | C29: 040148 | D29: Pagatodo | G29: 100 | H29: 100 | J29: n.a | K29: 100 | M29: n.a | N29: 100 | P29: 76.92 | Q29: 100 | S29: 100 | T29: 100
B30: 21 | C30: 040072 | D30: Banorte | G30: 100 | H30: 100 | J30: 96.48 | K30: 100 | M30: 96.42 | N30: 100 | P30: 100 | Q30: 100 | S30: 100 | T30: 100
B31: 22 | C31: 040156 | D31: Sabadell | G31: 100 | H31: 100 | J31: 93.13 | K31: 100 | M31: 100 | N31: 100 | P31: 100 | Q31: 100 | S31: 100 | T31: 100
B32: 23 | C32: 040058 | D32: Banregio | G32: 100 | H32: 100 | J32: 98.49 | K32: 100 | M32: 94.11 | N32: 100 | P32: 100 | Q32: 100 | S32: 100 | T32: 100
B33: 24 | C33: 040155 | D33: ICBC | G33: 97.8 | H33: 100 | J33: 96.89 | K33: 100 | M33: n.a | N33: 100 | P33: 94.87 | Q33: 100 | S33: 100 | T33: 100
B34: 25 | C34: 040157 | D34: Shinhan | G34: 100 | H34: 100 | J34: 94.59 | K34: 100 | M34: n.a | N34: 100 | P34: 100 | Q34: 100 | S34: 100 | T34: 100
B35: 26 | C35: 040112 | D35: Monex | G35: 100 | H35: 100 | J35: 91.25 | K35: 100 | M35: 100 | N35: 100 | P35: 100 | Q35: 100 | S35: 100 | T35: 100
B36: 27 | C36: 040133 | D36: Actinver | G36: 100 | H36: 100 | J36: 93.44 | K36: 100 | M36: n.a | N36: 100 | P36: 100 | Q36: 100 | S36: 100 | T36: 100
B37: 28 | C37: 040160 | D37: Banco S3 | G37: 97.28 | H37: 100 | J37: 97.85 | K37: 100 | M37: n.a | N37: 100 | P37: 100 | Q37: 100 | S37: 94.36 | T37: 100
B38: 29 | C38: 040154 | D38: Covalto | G38: 98.9 | H38: 100 | J38: 93.87 | K38: 100 | M38: n.a | N38: 100 | P38: 100 | Q38: 100 | S38: 100 | T38: 100
B39: 30 | C39: 040044 | D39: Scotiabank | G39: 100 | H39: 100 | J39: 97.93 | K39: 100 | M39: 90.81 | N39: 100 | P39: 100 | Q39: 100 | S39: 100 | T39: 100
B40: 31 | C40: 040137 | D40: Bancoppel | G40: 96.4 | H40: 100 | J40: 94.39 | K40: 100 | M40: 99.05 | N40: 100 | P40: 100 | Q40: 100 | S40: 94.87 | T40: 100
B41: 32 | C41: 040158 | D41: Mizuho Bank | G41: 98.9 | H41: 100 | J41: 92.09 | K41: 100 | M41: n.a | N41: 100 | P41: 100 | Q41: 100 | S41: 100 | T41: 100
B42: 33 | C42: 040127 | D42: Banco Azteca | G42: 98.94 | H42: 100 | J42: 94.67 | K42: 100 | M42: 92.71 | N42: 100 | P42: 100 | Q42: 100 | S42: 99.49 | T42: 100
B43: 34 | C43: 040124 | D43: Citi México (Antes CBM Banco) | G43: 100 | H43: 100 | J43: 96.15 | K43: 100 | M43: n.a | N43: 100 | P43: 38.46 | Q43: 100 | S43: 97.95 | T43: 100
B44: 35 | C44: 040138 | D44: Ualá | G44: 98.16 | H44: 100 | J44: 90.7 | K44: 100 | M44: 99.52 | N44: 100 | P44: 100 | Q44: 100 | S44: 93.33 | T44: 100
B45: 36 | C45: 040110 | D45: J.P. Morgan | G45: 100 | H45: 100 | J45: 92.3 | K45: 100 | M45: n.a | N45: 100 | P45: 100 | Q45: 100 | S45: 93.33 | T45: 100
B46: 37 | C46: 040150 | D46: Inmobiliario Mexicano | G46: 100 | H46: 100 | J46: 84.94 | K46: 100 | M46: 100 | N46: 100 | P46: 100 | Q46: 100 | S46: 100 | T46: 100
B47: 38 | C47: 040042 | D47: Banca Mifel | G47: 100 | H47: 100 | J47: 90.64 | K47: 100 | M47: 94.73 | N47: 100 | P47: 97.44 | Q47: 100 | S47: 96.41 | T47: 100
B48: 39 | C48: 040021 | D48: HSBC | G48: 100 | H48: 100 | J48: 93.23 | K48: 100 | M48: 87.57 | N48: 100 | P48: 100 | Q48: 100 | S48: 100 | T48: 100
B49: 40 | C49: 040108 | D49: MUFG Bank | G49: 99.18 | H49: 100 | J49: 99.31 | K49: 100 | M49: n.a | N49: 100 | P49: 100 | Q49: 100 | S49: 100 | T49: 100
B50: 41 | C50: 040132 | D50: Multiva | G50: 99.2 | H50: 100 | J50: 83.9 | K50: 100 | M50: 96.92 | N50: 100 | P50: 100 | Q50: 100 | S50: 99.49 | T50: 100
B51: 42 | C51: 040062 | D51: Afirme | G51: 100 | H51: 100 | J51: 85.63 | K51: 100 | M51: 94.56 | N51: 100 | P51: 100 | Q51: 100 | S51: 93.85 | T51: 100
B52: 43 | C52: 040012 | D52: BBVA México | G52: 100 | H52: 100 | J52: 91.04 | K52: 100 | M52: 98.41 | N52: 100 | P52: 100 | Q52: 100 | S52: 100 | T52: 100
B53: 44 | C53: 040036 | D53: Inbursa | G53: 99.47 | H53: 100 | J53: 92.49 | K53: 100 | M53: 98.45 | N53: 100 | P53: 66.67 | Q53: 100 | S53: 95.9 | T53: 100
B54: 45 | C54: 040145 | D54: Banco Base | G54: 99.15 | H54: 100 | J54: 80.78 | K54: 100 | M54: n.a | N54: 100 | P54: 84.62 | Q54: 100 | S54: 97.95 | T54: 100
B55: 46 | C55: 040140 | D55: Consubanco | G55: 90.39 | H55: 100 | J55: 85.09 | K55: 100 | M55: n.a | N55: 100 | P55: 97.44 | Q55: 100 | S55: 98.46 | T55: 100
B56: 47 | C56: 040128 | D56: Kapital (Antes Autofin) | G56: 96.55 | H56: 100 | J56: 75.3 | K56: 100 | M56: 92.74 | N56: 100 | P56: 64.1 | Q56: 100 | S56: 95.9 | T56: 100
B57: 48 | C57: 040059 | D57: Invex | G57: 100 | H57: 100 | J57: 70.47 | K57: 100 | M57: 89.23 | N57: 100 | P57: 84.62 | Q57: 100 | S57: 99.49 | T57: 100
B58: 49 | C58: 040152 | D58: Bancrea | G58: 94.51 | H58: 100 | J58: 63.82 | K58: 100 | M58: 100 | N58: 100 | P58: 69.23 | Q58: 100 | S58: 97.44 | T58: 100
B59: 50 | C59: 040014 | D59: Santander | G59: 100 | H59: 100 | J59: 84.54 | K59: 100 | M59: 84.46 | N59: 100 | P59: 100 | Q59: 100 | S59: 99.49 | T59: 100
B60: 51 | C60: 040136 | D60: Intercam Banco | G60: 90.73 | H60: 100 | J60: 68.31 | K60: 100 | M60: n.a | N60: 100 | P60: 89.74 | Q60: 100 | S60: 91.79 | T60: 100
B101: =_xlfn.XLOOKUP(C101,[1]Calificación!D:D,[1]Calificación!A:A,"",0,1) | C101: =IF([1]Calificación!D90=0,"",[1]Calificación!D90) | D101: =IFERROR(VLOOKUP(C101,[1]Calificación!$D$1:$X$52,2,0),"") | G101: =IFERROR(VLOOKUP(C101,[1]Calificación!$D$1:$X$52,12,0),"") | H101: =IFERROR(IF(VLOOKUP(C101,[1]Calificación!$D$1:$X$52,13,0)=0,"n.a",VLOOKUP(C101,[1]Calificación!$D$1:$X$52,13,0)),"") | J101: =IFERROR(IF(VLOOKUP(C101,[1]Calificación!$D$1:$X$52,14,0)=0,"n.a",VLOOKUP(C101,[1]Calificación!$D$1:$X$52,14,0)),"") | K101: =IFERROR(IF(VLOOKUP(C101,[1]Calificación!$D$1:$X$52,15,0)=0,"n.a",VLOOKUP(C101,[1]Calificación!$D$1:$X$52,15,0)),"") | M101: =IFERROR(IF(VLOOKUP(C101,[1]Calificación!$D$1:$X$52,16,0)=0,"n.a",VLOOKUP(C101,[1]Calificación!$D$1:$X$52,16,0)),"") | N101: =IFERROR(IF(VLOOKUP(C101,[1]Calificación!$D$1:$X$52,17,0)=0,"n.a",VLOOKUP(C101,[1]Calificación!$D$1:$X$52,17,0)),"") | P101: =IFERROR(IF(VLOOKUP(C101,[1]Calificación!$D$1:$X$52,18,0)=0,"n.a",VLOOKUP(C101,[1]Calificación!$D$1:$X$52,18,0)),"") | Q101: =IFERROR(IF(VLOOKUP(C101,[1]Calificación!$D$1:$X$52,19,0)=0,"n.a",VLOOKUP(C101,[1]Calificación!$D$1:$X$52,19,0)),"") | S101: =IFERROR(IF(VLOOKUP(C101,[1]Calificación!$D$1:$X$52,20,0)=0,"n.a",VLOOKUP(C101,[1]Calificación!$D$1:$X$52,20,0)),"") | T101: =IFERROR(IF(VLOOKUP(C101,[1]Calificación!$D$1:$X$52,21,0)=0,"n.a",VLOOKUP(C101,[1]Calificación!$D$1:$X$52,21,0)),"")
B102: =_xlfn.XLOOKUP(C102,[1]Calificación!D:D,[1]Calificación!A:A,"",0,1) | C102: =IF([1]Calificación!D91=0,"",[1]Calificación!D91) | D102: =IFERROR(VLOOKUP(C102,[1]Calificación!$D$1:$X$52,2,0),"") | G102: =IFERROR(VLOOKUP(C102,[1]Calificación!$D$1:$X$52,12,0),"") | H102: =IFERROR(IF(VLOOKUP(C102,[1]Calificación!$D$1:$X$52,13,0)=0,"n.a",VLOOKUP(C102,[1]Calificación!$D$1:$X$52,13,0)),"") | J102: =IFERROR(IF(VLOOKUP(C102,[1]Calificación!$D$1:$X$52,14,0)=0,"n.a",VLOOKUP(C102,[1]Calificación!$D$1:$X$52,14,0)),"") | K102: =IFERROR(IF(VLOOKUP(C102,[1]Calificación!$D$1:$X$52,15,0)=0,"n.a",VLOOKUP(C102,[1]Calificación!$D$1:$X$52,15,0)),"") | M102: =IFERROR(IF(VLOOKUP(C102,[1]Calificación!$D$1:$X$52,16,0)=0,"n.a",VLOOKUP(C102,[1]Calificación!$D$1:$X$52,16,0)),"") | N102: =IFERROR(IF(VLOOKUP(C102,[1]Calificación!$D$1:$X$52,17,0)=0,"n.a",VLOOKUP(C102,[1]Calificación!$D$1:$X$52,17,0)),"") | P102: =IFERROR(IF(VLOOKUP(C102,[1]Calificación!$D$1:$X$52,18,0)=0,"n.a",VLOOKUP(C102,[1]Calificación!$D$1:$X$52,18,0)),"") | Q102: =IFERROR(IF(VLOOKUP(C102,[1]Calificación!$D$1:$X$52,19,0)=0,"n.a",VLOOKUP(C102,[1]Calificación!$D$1:$X$52,19,0)),"") | S102: =IFERROR(IF(VLOOKUP(C102,[1]Calificación!$D$1:$X$52,20,0)=0,"n.a",VLOOKUP(C102,[1]Calificación!$D$1:$X$52,20,0)),"") | T102: =IFERROR(IF(VLOOKUP(C102,[1]Calificación!$D$1:$X$52,21,0)=0,"n.a",VLOOKUP(C102,[1]Calificación!$D$1:$X$52,21,0)),"")
B103: =_xlfn.XLOOKUP(C103,[1]Calificación!D:D,[1]Calificación!A:A,"",0,1) | C103: =IF([1]Calificación!D92=0,"",[1]Calificación!D92) | D103: =IFERROR(VLOOKUP(C103,[1]Calificación!$D$1:$X$52,2,0),"") | G103: =IFERROR(VLOOKUP(C103,[1]Calificación!$D$1:$X$52,12,0),"") | H103: =IFERROR(IF(VLOOKUP(C103,[1]Calificación!$D$1:$X$52,13,0)=0,"n.a",VLOOKUP(C103,[1]Calificación!$D$1:$X$52,13,0)),"") | J103: =IFERROR(IF(VLOOKUP(C103,[1]Calificación!$D$1:$X$52,14,0)=0,"n.a",VLOOKUP(C103,[1]Calificación!$D$1:$X$52,14,0)),"") | K103: =IFERROR(IF(VLOOKUP(C103,[1]Calificación!$D$1:$X$52,15,0)=0,"n.a",VLOOKUP(C103,[1]Calificación!$D$1:$X$52,15,0)),"") | M103: =IFERROR(IF(VLOOKUP(C103,[1]Calificación!$D$1:$X$52,16,0)=0,"n.a",VLOOKUP(C103,[1]Calificación!$D$1:$X$52,16,0)),"") | N103: =IFERROR(IF(VLOOKUP(C103,[1]Calificación!$D$1:$X$52,17,0)=0,"n.a",VLOOKUP(C103,[1]Calificación!$D$1:$X$52,17,0)),"") | P103: =IFERROR(IF(VLOOKUP(C103,[1]Calificación!$D$1:$X$52,18,0)=0,"n.a",VLOOKUP(C103,[1]Calificación!$D$1:$X$52,18,0)),"") | Q103: =IFERROR(IF(VLOOKUP(C103,[1]Calificación!$D$1:$X$52,19,0)=0,"n.a",VLOOKUP(C103,[1]Calificación!$D$1:$X$52,19,0)),"") | S103: =IFERROR(IF(VLOOKUP(C103,[1]Calificación!$D$1:$X$52,20,0)=0,"n.a",VLOOKUP(C103,[1]Calificación!$D$1:$X$52,20,0)),"") | T103: =IFERROR(IF(VLOOKUP(C103,[1]Calificación!$D$1:$X$52,21,0)=0,"n.a",VLOOKUP(C103,[1]Calificación!$D$1:$X$52,21,0)),"")
B104: =_xlfn.XLOOKUP(C104,[1]Calificación!D:D,[1]Calificación!A:A,"",0,1) | C104: =IF([1]Calificación!D93=0,"",[1]Calificación!D93) | D104: =IFERROR(VLOOKUP(C104,[1]Calificación!$D$1:$X$52,2,0),"") | G104: =IFERROR(VLOOKUP(C104,[1]Calificación!$D$1:$X$52,12,0),"") | H104: =IFERROR(IF(VLOOKUP(C104,[1]Calificación!$D$1:$X$52,13,0)=0,"n.a",VLOOKUP(C104,[1]Calificación!$D$1:$X$52,13,0)),"") | J104: =IFERROR(IF(VLOOKUP(C104,[1]Calificación!$D$1:$X$52,14,0)=0,"n.a",VLOOKUP(C104,[1]Calificación!$D$1:$X$52,14,0)),"") | K104: =IFERROR(IF(VLOOKUP(C104,[1]Calificación!$D$1:$X$52,15,0)=0,"n.a",VLOOKUP(C104,[1]Calificación!$D$1:$X$52,15,0)),"") | M104: =IFERROR(IF(VLOOKUP(C104,[1]Calificación!$D$1:$X$52,16,0)=0,"n.a",VLOOKUP(C104,[1]Calificación!$D$1:$X$52,16,0)),"") | N104: =IFERROR(IF(VLOOKUP(C104,[1]Calificación!$D$1:$X$52,17,0)=0,"n.a",VLOOKUP(C104,[1]Calificación!$D$1:$X$52,17,0)),"") | P104: =IFERROR(IF(VLOOKUP(C104,[1]Calificación!$D$1:$X$52,18,0)=0,"n.a",VLOOKUP(C104,[1]Calificación!$D$1:$X$52,18,0)),"") | Q104: =IFERROR(IF(VLOOKUP(C104,[1]Calificación!$D$1:$X$52,19,0)=0,"n.a",VLOOKUP(C104,[1]Calificación!$D$1:$X$52,19,0)),"") | S104: =IFERROR(IF(VLOOKUP(C104,[1]Calificación!$D$1:$X$52,20,0)=0,"n.a",VLOOKUP(C104,[1]Calificación!$D$1:$X$52,20,0)),"") | T104: =IFERROR(IF(VLOOKUP(C104,[1]Calificación!$D$1:$X$52,21,0)=0,"n.a",VLOOKUP(C104,[1]Calificación!$D$1:$X$52,21,0)),"")
B105: =_xlfn.XLOOKUP(C105,[1]Calificación!D:D,[1]Calificación!A:A,"",0,1) | C105: =IF([1]Calificación!D94=0,"",[1]Calificación!D94) | D105: =IFERROR(VLOOKUP(C105,[1]Calificación!$D$1:$X$52,2,0),"") | G105: =IFERROR(VLOOKUP(C105,[1]Calificación!$D$1:$X$52,12,0),"") | H105: =IFERROR(IF(VLOOKUP(C105,[1]Calificación!$D$1:$X$52,13,0)=0,"n.a",VLOOKUP(C105,[1]Calificación!$D$1:$X$52,13,0)),"") | J105: =IFERROR(IF(VLOOKUP(C105,[1]Calificación!$D$1:$X$52,14,0)=0,"n.a",VLOOKUP(C105,[1]Calificación!$D$1:$X$52,14,0)),"") | K105: =IFERROR(IF(VLOOKUP(C105,[1]Calificación!$D$1:$X$52,15,0)=0,"n.a",VLOOKUP(C105,[1]Calificación!$D$1:$X$52,15,0)),"") | M105: =IFERROR(IF(VLOOKUP(C105,[1]Calificación!$D$1:$X$52,16,0)=0,"n.a",VLOOKUP(C105,[1]Calificación!$D$1:$X$52,16,0)),"") | N105: =IFERROR(IF(VLOOKUP(C105,[1]Calificación!$D$1:$X$52,17,0)=0,"n.a",VLOOKUP(C105,[1]Calificación!$D$1:$X$52,17,0)),"") | P105: =IFERROR(IF(VLOOKUP(C105,[1]Calificación!$D$1:$X$52,18,0)=0,"n.a",VLOOKUP(C105,[1]Calificación!$D$1:$X$52,18,0)),"") | Q105: =IFERROR(IF(VLOOKUP(C105,[1]Calificación!$D$1:$X$52,19,0)=0,"n.a",VLOOKUP(C105,[1]Calificación!$D$1:$X$52,19,0)),"") | S105: =IFERROR(IF(VLOOKUP(C105,[1]Calificación!$D$1:$X$52,20,0)=0,"n.a",VLOOKUP(C105,[1]Calificación!$D$1:$X$52,20,0)),"") | T105: =IFERROR(IF(VLOOKUP(C105,[1]Calificación!$D$1:$X$52,21,0)=0,"n.a",VLOOKUP(C105,[1]Calificación!$D$1:$X$52,21,0)),"")
B106: =_xlfn.XLOOKUP(C106,[1]Calificación!D:D,[1]Calificación!A:A,"",0,1) | C106: =IF([1]Calificación!D95=0,"",[1]Calificación!D95) | D106: =IFERROR(VLOOKUP(C106,[1]Calificación!$D$1:$X$52,2,0),"") | G106: =IFERROR(VLOOKUP(C106,[1]Calificación!$D$1:$X$52,12,0),"") | H106: =IFERROR(IF(VLOOKUP(C106,[1]Calificación!$D$1:$X$52,13,0)=0,"n.a",VLOOKUP(C106,[1]Calificación!$D$1:$X$52,13,0)),"") | J106: =IFERROR(IF(VLOOKUP(C106,[1]Calificación!$D$1:$X$52,14,0)=0,"n.a",VLOOKUP(C106,[1]Calificación!$D$1:$X$52,14,0)),"") | K106: =IFERROR(IF(VLOOKUP(C106,[1]Calificación!$D$1:$X$52,15,0)=0,"n.a",VLOOKUP(C106,[1]Calificación!$D$1:$X$52,15,0)),"") | M106: =IFERROR(IF(VLOOKUP(C106,[1]Calificación!$D$1:$X$52,16,0)=0,"n.a",VLOOKUP(C106,[1]Calificación!$D$1:$X$52,16,0)),"") | N106: =IFERROR(IF(VLOOKUP(C106,[1]Calificación!$D$1:$X$52,17,0)=0,"n.a",VLOOKUP(C106,[1]Calificación!$D$1:$X$52,17,0)),"") | P106: =IFERROR(IF(VLOOKUP(C106,[1]Calificación!$D$1:$X$52,18,0)=0,"n.a",VLOOKUP(C106,[1]Calificación!$D$1:$X$52,18,0)),"") | Q106: =IFERROR(IF(VLOOKUP(C106,[1]Calificación!$D$1:$X$52,19,0)=0,"n.a",VLOOKUP(C106,[1]Calificación!$D$1:$X$52,19,0)),"") | S106: =IFERROR(IF(VLOOKUP(C106,[1]Calificación!$D$1:$X$52,20,0)=0,"n.a",VLOOKUP(C106,[1]Calificación!$D$1:$X$52,20,0)),"") | T106: =IFERROR(IF(VLOOKUP(C106,[1]Calificación!$D$1:$X$52,21,0)=0,"n.a",VLOOKUP(C106,[1]Calificación!$D$1:$X$52,21,0)),"")
B107: =_xlfn.XLOOKUP(C107,[1]Calificación!D:D,[1]Calificación!A:A,"",0,1) | C107: =IF([1]Calificación!D96=0,"",[1]Calificación!D96) | D107: =IFERROR(VLOOKUP(C107,[1]Calificación!$D$1:$X$52,2,0),"") | G107: =IFERROR(VLOOKUP(C107,[1]Calificación!$D$1:$X$52,12,0),"") | H107: =IFERROR(IF(VLOOKUP(C107,[1]Calificación!$D$1:$X$52,13,0)=0,"n.a",VLOOKUP(C107,[1]Calificación!$D$1:$X$52,13,0)),"") | J107: =IFERROR(IF(VLOOKUP(C107,[1]Calificación!$D$1:$X$52,14,0)=0,"n.a",VLOOKUP(C107,[1]Calificación!$D$1:$X$52,14,0)),"") | K107: =IFERROR(IF(VLOOKUP(C107,[1]Calificación!$D$1:$X$52,15,0)=0,"n.a",VLOOKUP(C107,[1]Calificación!$D$1:$X$52,15,0)),"") | M107: =IFERROR(IF(VLOOKUP(C107,[1]Calificación!$D$1:$X$52,16,0)=0,"n.a",VLOOKUP(C107,[1]Calificación!$D$1:$X$52,16,0)),"") | N107: =IFERROR(IF(VLOOKUP(C107,[1]Calificación!$D$1:$X$52,17,0)=0,"n.a",VLOOKUP(C107,[1]Calificación!$D$1:$X$52,17,0)),"") | P107: =IFERROR(IF(VLOOKUP(C107,[1]Calificación!$D$1:$X$52,18,0)=0,"n.a",VLOOKUP(C107,[1]Calificación!$D$1:$X$52,18,0)),"") | Q107: =IFERROR(IF(VLOOKUP(C107,[1]Calificación!$D$1:$X$52,19,0)=0,"n.a",VLOOKUP(C107,[1]Calificación!$D$1:$X$52,19,0)),"") | S107: =IFERROR(IF(VLOOKUP(C107,[1]Calificación!$D$1:$X$52,20,0)=0,"n.a",VLOOKUP(C107,[1]Calificación!$D$1:$X$52,20,0)),"") | T107: =IFERROR(IF(VLOOKUP(C107,[1]Calificación!$D$1:$X$52,21,0)=0,"n.a",VLOOKUP(C107,[1]Calificación!$D$1:$X$52,21,0)),"")
B108: =_xlfn.XLOOKUP(C108,[1]Calificación!D:D,[1]Calificación!A:A,"",0,1) | C108: =IF([1]Calificación!D97=0,"",[1]Calificación!D97) | D108: =IFERROR(VLOOKUP(C108,[1]Calificación!$D$1:$X$52,2,0),"") | G108: =IFERROR(VLOOKUP(C108,[1]Calificación!$D$1:$X$52,12,0),"") | H108: =IFERROR(IF(VLOOKUP(C108,[1]Calificación!$D$1:$X$52,13,0)=0,"n.a",VLOOKUP(C108,[1]Calificación!$D$1:$X$52,13,0)),"") | J108: =IFERROR(IF(VLOOKUP(C108,[1]Calificación!$D$1:$X$52,14,0)=0,"n.a",VLOOKUP(C108,[1]Calificación!$D$1:$X$52,14,0)),"") | K108: =IFERROR(IF(VLOOKUP(C108,[1]Calificación!$D$1:$X$52,15,0)=0,"n.a",VLOOKUP(C108,[1]Calificación!$D$1:$X$52,15,0)),"") | M108: =IFERROR(IF(VLOOKUP(C108,[1]Calificación!$D$1:$X$52,16,0)=0,"n.a",VLOOKUP(C108,[1]Calificación!$D$1:$X$52,16,0)),"") | N108: =IFERROR(IF(VLOOKUP(C108,[1]Calificación!$D$1:$X$52,17,0)=0,"n.a",VLOOKUP(C108,[1]Calificación!$D$1:$X$52,17,0)),"") | P108: =IFERROR(IF(VLOOKUP(C108,[1]Calificación!$D$1:$X$52,18,0)=0,"n.a",VLOOKUP(C108,[1]Calificación!$D$1:$X$52,18,0)),"") | Q108: =IFERROR(IF(VLOOKUP(C108,[1]Calificación!$D$1:$X$52,19,0)=0,"n.a",VLOOKUP(C108,[1]Calificación!$D$1:$X$52,19,0)),"") | S108: =IFERROR(IF(VLOOKUP(C108,[1]Calificación!$D$1:$X$52,20,0)=0,"n.a",VLOOKUP(C108,[1]Calificación!$D$1:$X$52,20,0)),"") | T108: =IFERROR(IF(VLOOKUP(C108,[1]Calificación!$D$1:$X$52,21,0)=0,"n.a",VLOOKUP(C108,[1]Calificación!$D$1:$X$52,21,0)),"")
B109: =_xlfn.XLOOKUP(C109,[1]Calificación!D:D,[1]Calificación!A:A,"",0,1) | C109: =IF([1]Calificación!D98=0,"",[1]Calificación!D98) | D109: =IFERROR(VLOOKUP(C109,[1]Calificación!$D$1:$X$52,2,0),"") | G109: =IFERROR(VLOOKUP(C109,[1]Calificación!$D$1:$X$52,12,0),"") | H109: =IFERROR(IF(VLOOKUP(C109,[1]Calificación!$D$1:$X$52,13,0)=0,"n.a",VLOOKUP(C109,[1]Calificación!$D$1:$X$52,13,0)),"") | J109: =IFERROR(IF(VLOOKUP(C109,[1]Calificación!$D$1:$X$52,14,0)=0,"n.a",VLOOKUP(C109,[1]Calificación!$D$1:$X$52,14,0)),"") | K109: =IFERROR(IF(VLOOKUP(C109,[1]Calificación!$D$1:$X$52,15,0)=0,"n.a",VLOOKUP(C109,[1]Calificación!$D$1:$X$52,15,0)),"") | M109: =IFERROR(IF(VLOOKUP(C109,[1]Calificación!$D$1:$X$52,16,0)=0,"n.a",VLOOKUP(C109,[1]Calificación!$D$1:$X$52,16,0)),"") | N109: =IFERROR(IF(VLOOKUP(C109,[1]Calificación!$D$1:$X$52,17,0)=0,"n.a",VLOOKUP(C109,[1]Calificación!$D$1:$X$52,17,0)),"") | P109: =IFERROR(IF(VLOOKUP(C109,[1]Calificación!$D$1:$X$52,18,0)=0,"n.a",VLOOKUP(C109,[1]Calificación!$D$1:$X$52,18,0)),"") | Q109: =IFERROR(IF(VLOOKUP(C109,[1]Calificación!$D$1:$X$52,19,0)=0,"n.a",VLOOKUP(C109,[1]Calificación!$D$1:$X$52,19,0)),"") | S109: =IFERROR(IF(VLOOKUP(C109,[1]Calificación!$D$1:$X$52,20,0)=0,"n.a",VLOOKUP(C109,[1]Calificación!$D$1:$X$52,20,0)),"") | T109: =IFERROR(IF(VLOOKUP(C109,[1]Calificación!$D$1:$X$52,21,0)=0,"n.a",VLOOKUP(C109,[1]Calificación!$D$1:$X$52,21,0)),"")
B110: =_xlfn.XLOOKUP(C110,[1]Calificación!D:D,[1]Calificación!A:A,"",0,1) | C110: =IF([1]Calificación!D99=0,"",[1]Calificación!D99) | D110: =IFERROR(VLOOKUP(C110,[1]Calificación!$D$1:$X$52,2,0),"") | G110: =IFERROR(VLOOKUP(C110,[1]Calificación!$D$1:$X$52,12,0),"") | H110: =IFERROR(IF(VLOOKUP(C110,[1]Calificación!$D$1:$X$52,13,0)=0,"n.a",VLOOKUP(C110,[1]Calificación!$D$1:$X$52,13,0)),"") | J110: =IFERROR(IF(VLOOKUP(C110,[1]Calificación!$D$1:$X$52,14,0)=0,"n.a",VLOOKUP(C110,[1]Calificación!$D$1:$X$52,14,0)),"") | K110: =IFERROR(IF(VLOOKUP(C110,[1]Calificación!$D$1:$X$52,15,0)=0,"n.a",VLOOKUP(C110,[1]Calificación!$D$1:$X$52,15,0)),"") | M110: =IFERROR(IF(VLOOKUP(C110,[1]Calificación!$D$1:$X$52,16,0)=0,"n.a",VLOOKUP(C110,[1]Calificación!$D$1:$X$52,16,0)),"") | N110: =IFERROR(IF(VLOOKUP(C110,[1]Calificación!$D$1:$X$52,17,0)=0,"n.a",VLOOKUP(C110,[1]Calificación!$D$1:$X$52,17,0)),"") | P110: =IFERROR(IF(VLOOKUP(C110,[1]Calificación!$D$1:$X$52,18,0)=0,"n.a",VLOOKUP(C110,[1]Calificación!$D$1:$X$52,18,0)),"") | Q110: =IFERROR(IF(VLOOKUP(C110,[1]Calificación!$D$1:$X$52,19,0)=0,"n.a",VLOOKUP(C110,[1]Calificación!$D$1:$X$52,19,0)),"") | S110: =IFERROR(IF(VLOOKUP(C110,[1]Calificación!$D$1:$X$52,20,0)=0,"n.a",VLOOKUP(C110,[1]Calificación!$D$1:$X$52,20,0)),"") | T110: =IFERROR(IF(VLOOKUP(C110,[1]Calificación!$D$1:$X$52,21,0)=0,"n.a",VLOOKUP(C110,[1]Calificación!$D$1:$X$52,21,0)),"")
B111: =_xlfn.XLOOKUP(C111,[1]Calificación!D:D,[1]Calificación!A:A,"",0,1) | C111: =IF([1]Calificación!D100=0,"",[1]Calificación!D100) | D111: =IFERROR(VLOOKUP(C111,[1]Calificación!$D$1:$X$52,2,0),"") | G111: =IFERROR(VLOOKUP(C111,[1]Calificación!$D$1:$X$52,12,0),"") | H111: =IFERROR(IF(VLOOKUP(C111,[1]Calificación!$D$1:$X$52,13,0)=0,"n.a",VLOOKUP(C111,[1]Calificación!$D$1:$X$52,13,0)),"") | J111: =IFERROR(IF(VLOOKUP(C111,[1]Calificación!$D$1:$X$52,14,0)=0,"n.a",VLOOKUP(C111,[1]Calificación!$D$1:$X$52,14,0)),"") | K111: =IFERROR(IF(VLOOKUP(C111,[1]Calificación!$D$1:$X$52,15,0)=0,"n.a",VLOOKUP(C111,[1]Calificación!$D$1:$X$52,15,0)),"") | M111: =IFERROR(IF(VLOOKUP(C111,[1]Calificación!$D$1:$X$52,16,0)=0,"n.a",VLOOKUP(C111,[1]Calificación!$D$1:$X$52,16,0)),"") | N111: =IFERROR(IF(VLOOKUP(C111,[1]Calificación!$D$1:$X$52,17,0)=0,"n.a",VLOOKUP(C111,[1]Calificación!$D$1:$X$52,17,0)),"") | P111: =IFERROR(IF(VLOOKUP(C111,[1]Calificación!$D$1:$X$52,18,0)=0,"n.a",VLOOKUP(C111,[1]Calificación!$D$1:$X$52,18,0)),"") | Q111: =IFERROR(IF(VLOOKUP(C111,[1]Calificación!$D$1:$X$52,19,0)=0,"n.a",VLOOKUP(C111,[1]Calificación!$D$1:$X$52,19,0)),"") | S111: =IFERROR(IF(VLOOKUP(C111,[1]Calificación!$D$1:$X$52,20,0)=0,"n.a",VLOOKUP(C111,[1]Calificación!$D$1:$X$52,20,0)),"") | T111: =IFERROR(IF(VLOOKUP(C111,[1]Calificación!$D$1:$X$52,21,0)=0,"n.a",VLOOKUP(C111,[1]Calificación!$D$1:$X$52,21,0)),"")
B112: =_xlfn.XLOOKUP(C112,[1]Calificación!D:D,[1]Calificación!A:A,"",0,1) | C112: =IF([1]Calificación!D101=0,"",[1]Calificación!D101) | D112: =IFERROR(VLOOKUP(C112,[1]Calificación!$D$1:$X$52,2,0),"") | G112: =IFERROR(VLOOKUP(C112,[1]Calificación!$D$1:$X$52,12,0),"") | H112: =IFERROR(IF(VLOOKUP(C112,[1]Calificación!$D$1:$X$52,13,0)=0,"n.a",VLOOKUP(C112,[1]Calificación!$D$1:$X$52,13,0)),"") | J112: =IFERROR(IF(VLOOKUP(C112,[1]Calificación!$D$1:$X$52,14,0)=0,"n.a",VLOOKUP(C112,[1]Calificación!$D$1:$X$52,14,0)),"") | K112: =IFERROR(IF(VLOOKUP(C112,[1]Calificación!$D$1:$X$52,15,0)=0,"n.a",VLOOKUP(C112,[1]Calificación!$D$1:$X$52,15,0)),"") | M112: =IFERROR(IF(VLOOKUP(C112,[1]Calificación!$D$1:$X$52,16,0)=0,"n.a",VLOOKUP(C112,[1]Calificación!$D$1:$X$52,16,0)),"") | N112: =IFERROR(IF(VLOOKUP(C112,[1]Calificación!$D$1:$X$52,17,0)=0,"n.a",VLOOKUP(C112,[1]Calificación!$D$1:$X$52,17,0)),"") | P112: =IFERROR(IF(VLOOKUP(C112,[1]Calificación!$D$1:$X$52,18,0)=0,"n.a",VLOOKUP(C112,[1]Calificación!$D$1:$X$52,18,0)),"") | Q112: =IFERROR(IF(VLOOKUP(C112,[1]Calificación!$D$1:$X$52,19,0)=0,"n.a",VLOOKUP(C112,[1]Calificación!$D$1:$X$52,19,0)),"") | S112: =IFERROR(IF(VLOOKUP(C112,[1]Calificación!$D$1:$X$52,20,0)=0,"n.a",VLOOKUP(C112,[1]Calificación!$D$1:$X$52,20,0)),"") | T112: =IFERROR(IF(VLOOKUP(C112,[1]Calificación!$D$1:$X$52,21,0)=0,"n.a",VLOOKUP(C112,[1]Calificación!$D$1:$X$52,21,0)),"")

Sheet Portadilla II
B2: II. Estadísticas de la Banca Múltiple
B3: El objetivo de este apartado es proporcionar al público indicadores estadísticos que reflejen adecuadamente la evolución de la condición financiera de la Banca Múltiple, por lo que en esta sección, se presenta la información reportada por las 52 instituciones de banca múltiple en operación correspondiente a septiembre de 2025, consolidada con la de sus SOFOMER en el caso de las siguientes instituciones: Banamex con Tarjetas Banamex; Santander con Santander Inclusión Financiera; CI Banco con Finanmadrid México; Banco del Bajío con Financiera Bajío; Banregio con Start Banregio; Inbursa con STM Financial, SOFOM Inbursa y CETELEM Inbursa; Afirme con Arrendadora Afirme; Banco Base con Arrendadora Base, Invex con Invex Consumo; Bancrea con Arrendadora Bancrea, así como Ve por Más con Arrendadora Ve por Más.
B5: Notas:
B7: 1/ Para la cartera total se considera la información de cartera de los bancos junto con la cartera de sus respectivas Sociedades Financieras de Objeto Múltiple Reguladas a las que consolidan. Hasta diciembre 2021: Cartera total = Cartera vigente + cartera vencida. A partir de enero 2022: Cartera total = Cartera de crédito con riesgo de crédito en etapa 1 + 2 + 3 + cartera de crédito valuada a valor razonable.
B9: 2/ Respecto al resultado neto se muestran saldos acumulados al cierre de mes.
B10: 3/ ROA = Resultado neto (flujo 12 meses) / Activos totales, promedio 12 meses.
B11: 4/ ROE = Resultado neto (flujo 12 meses) / Capital contable, promedio 12 meses.
B12: 5/ Hasta diciembre 2021: IMOR = Índice de Morosidad = cartera vencida / (Cartera vigente + cartera vencida). A partir de enero 2022: IMOR = Índice de Morosidad = cartera de crédito con riesgo de crédito en etapa 3 / (Cartera de crédito con riesgo de crédito en etapa 1 + 2 + 3).
B13: 6/ Hasta diciembre 2021: ICOR = Índice de cobertura = Estimaciones preventivas para riesgos crediticios del balance general / cartera de crédito vencida. A partir de enero 2022: ICOR = Índice de cobertura = Estimaciones preventivas para riesgos crediticios del estado de situación financiera / cartera de crédito con riesgo de crédito en etapa 3.
B14: 7/ Hasta diciembre 2021: Estimaciones preventivas para riesgo crediticio del balance general / (Cartera vigente + cartera vencida). A partir de enero 2022: Estimaciones preventivas para riesgo crediticio del estado de situación financiera / (Cartera de crédito con riesgo de crédito en etapa 1 + 2 + 3).
B16: */ En todos los casos se presentan las instituciones en orden descendente por tamaño de activo total en el mes de análisis más reciente.
B18: El símbolo ( - ) indica que la cifra es cero. Las cifras en cero indican una cantidad cercana a cero.
... B21: n.d.: No disponible

Sheet Pm2
B3: Principales rubros del estado de situación financiera y estado de resultado integral
B4: Millones de pesos y porcentajes
C5: Activo total | I5: Inversiones en instrumentos financieros | O5: Cartera total1/ | U5: Captación total | AA5: Capital contable | AG5: Resultado neto 2/
C6: 45536 | E6: 45870 | G6: 45901 | I6: =+$C$6 -> 45536 | K6: =+$E$6 -> 45870 | M6: =+$G$6 -> 45901 | O6: =+$C$6 -> 45536 | Q6: =+$E$6 -> 45870 | S6: =+$G$6 -> 45901 | U6: =+$C$6 -> 45536 | W6: =+$E$6 -> 45870 | Y6: =+$G$6 -> 45901 | AA6: =+$C$6 -> 45536 | AC6: =+$E$6 -> 45870 | AE6: =+$G$6 -> 45901 | AG6: =+$C$6 -> 45536 | AI6: =+$E$6 -> 45870 | AK6: =+$G$6 -> 45901
B7: Sistema */ | C7: 14248896 | D7: 100 | E7: 15431060 | F7: 100 | G7: 15362544 | H7: 100 | I7: 3679985.9 | J7: 100 | K7: 4023367.5 | L7: 100 | M7: 3991475.6 | N7: 100 | O7: 7341346.6 | P7: 100 | Q7: 7858406 | R7: 100 | S7: 7863444.3 | T7: 100 | U7: 8520586.9 | V7: 100 | W7: 9233014.2 | X7: 100 | Y7: 9133939.5 | Z7: 100 | AA7: 1637105 | AB7: 100 | AC7: 1804585.8 | AD7: 100 | AE7: 1799422.5 | AF7: 100 | AG7: 222612.65 | AH7: 100 | AI7: 203173.6 | AJ7: 100 | AK7: 226075.46 | AL7: 100
B8: BBVA México | C8: 3112767.3 | D8: 21.845674 | E8: 3334146.9 | F8: 21.606726 | G8: 3371171.8 | H8: 21.944099 | I8: 659425.83 | J8: 17.919249 | K8: 563805.88 | L8: 14.013283 | M8: 578436.15 | N8: 14.491787 | O8: 1839030.8 | P8: 25.05032 | Q8: 2012068.9 | R8: 25.604033 | S8: 2016789.4 | T8: 25.647659 | U8: 1887722.9 | V8: 22.154846 | W8: 2053500.3 | X8: 22.240844 | Y8: 2096776.8 | Z8: 22.955887 | AA8: 355829.94 | AB8: 21.735316 | AC8: 401144.42 | AD8: 22.229169 | AE8: 394994.22 | AF8: 21.951166 | AG8: 70519.174 | AH8: 31.677973 | AI8: 66280.766 | AJ8: 32.622726 | AK8: 74212.541 | AL8: 32.826447
B9: Santander | C9: 1886565.6 | D9: 13.240083 | E9: 1991916.7 | F9: 12.908489 | G9: 2019417.3 | H9: 13.145071 | I9: 551674.18 | J9: 14.991204 | K9: 599303.74 | L9: 14.895575 | M9: 618043.38 | N9: 15.484083 | O9: 874142.25 | P9: 11.90711 | Q9: 929316.63 | R9: 11.825765 | S9: 926658.93 | T9: 11.78439 | U9: 1033043.4 | V9: 12.124088 | W9: 1104934 | X9: 11.967208 | Y9: 1066511.5 | Z9: 11.676358 | AA9: 168566.7 | AB9: 10.296634 | AC9: 164899.95 | AD9: 9.1378281 | AE9: 167381.66 | AF9: 9.3019657 | AG9: 22275.616 | AH9: 10.006447 | AI9: 21432.466 | AJ9: 10.548844 | AK9: 23805.167 | AL9: 10.529744
B10: Banorte | C10: 1779459.6 | D10: 12.488404 | E10: 1862912 | F10: 12.072482 | G10: 1868293.1 | H10: 12.161353 | I10: 419573.34 | J10: 11.401493 | K10: 443714.17 | L10: 11.028428 | M10: 442150.64 | N10: 11.077373 | O10: 1079814.2 | P10: 14.708666 | Q10: 1158655.5 | R10: 14.744154 | S10: 1164148.4 | T10: 14.80456 | U10: 1154816.9 | V10: 13.553256 | W10: 1193359.6 | X10: 12.924919 | Y10: 1180061.8 | Z10: 12.919528 | AA10: 156968.88 | AB10: 9.588199 | AC10: 170852.09 | AD10: 9.4676621 | AE10: 174062.43 | AF10: 9.6732385 | AG10: 34253.852 | AH10: 15.3872 | AI10: 31389.194 | AJ10: 15.449445 | AK10: 34506.709 | AL10: 15.263359
B11: Banamex | C11: 1520032.6 | D11: 10.667722 | E11: 1110881.5 | F11: 7.1989971 | G11: 1117474.4 | H11: 7.2740194 | I11: 526442.09 | J11: 14.305546 | K11: 402823.79 | L11: 10.012105 | M11: 406459.66 | N11: 10.183193 | O11: 620251.84 | P11: 8.4487475 | Q11: 492087.34 | R11: 6.2619231 | S11: 503424.35 | T11: 6.4020845 | U11: 965592.75 | V11: 11.332468 | W11: 773161.3 | X11: 8.3738775 | Y11: 764231.24 | Z11: 8.36694 | AA11: 232322.09 | AB11: 14.191032 | AC11: 179568.57 | AD11: 9.9506808 | AE11: 180328.72 | AF11: 10.021478 | AG11: 18107.129 | AH11: 8.1339175 | AI11: 9664.7347 | AJ11: 4.7568852 | AK11: 10157.826 | AL11: 4.493113
B12: HSBC | C12: 883735.82 | D12: 6.2021356 | E12: 890120.35 | F12: 5.7683682 | G12: 897782.35 | H12: 5.8439695 | I12: 174294.64 | J12: 4.7362857 | K12: 218382.91 | L12: 5.427864 | M12: 224058.65 | N12: 5.6134291 | O12: 503555.8 | P12: 6.8591748 | Q12: 490989.81 | R12: 6.2479568 | S12: 483659.84 | T12: 6.1507378 | U12: 579365.66 | V12: 6.799598 | W12: 560878.44 | X12: 6.0747057 | Y12: 541428.01 | Z12: 5.9276505 | AA12: 83399.378 | AB12: 5.0943207 | AC12: 87796.547 | AD12: 4.865191 | AE12: 88567.923 | AF12: 4.9220194 | AG12: 6806.6679 | AH12: 3.0576286 | AI12: 5896.0556 | AJ12: 2.9019792 | AK12: 6730.1865 | AL12: 2.9769646
B13: Scotiabank | C13: 877814.05 | D13: 6.160576 | E13: 871850.28 | F13: 5.6499702 | G13: 893048.68 | H13: 5.8131564 | I13: 180770.89 | J13: 4.9122712 | K13: 171111.93 | L13: 4.2529531 | M13: 177633.86 | N13: 4.4503306 | O13: 527608.54 | P13: 7.1868087 | Q13: 532170.63 | R13: 6.771992 | S13: 529339.29 | T13: 6.7316468 | U13: 594724.43 | V13: 6.9798529 | W13: 591248.14 | X13: 6.4036307 | Y13: 589538.92 | Z13: 6.4543774 | AA13: 86404.183 | AB13: 5.2778646 | AC13: 92317.678 | AD13: 5.1157267 | AE13: 93061.955 | AF13: 5.171768 | AG13: 7917.2742 | AH13: 3.5565249 | AI13: 6651.1116 | AJ13: 3.2736102 | AK13: 7479.6545 | AL13: 3.308477
B14: Inbursa | C14: 638270.81 | D14: 4.4794406 | E14: 704687.72 | F14: 4.5666839 | G14: 706596.95 | H14: 4.5994789 | I14: 61005.344 | J14: 1.6577603 | K14: 73588.344 | L14: 1.8290237 | M14: 72118.81 | N14: 1.8068208 | O14: 444506.49 | P14: 6.0548359 | Q14: 466601.03 | R14: 5.937604 | S14: 467303.13 | T14: 5.9427283 | U14: 421058.22 | V14: 4.9416575 | W14: 466616.41 | X14: 5.053782 | Y14: 466402.17 | Z14: 5.1062542 | AA14: 175402.39 | AB14: 10.714181 | AC14: 201509.51 | AD14: 11.166524 | AE14: 202541.75 | AF14: 11.255931 | AG14: 18698.47 | AH14: 8.3995541 | AI14: 15208.85 | AJ14: 7.4856431 | AK14: 16938.198 | AL14: 7.4922762
B15: Citi México | C15: 2219.0303 | D15: 0.015573349 | E15: 583611.65 | F15: 3.7820581 | G15: 556350.64 | H15: 3.6214748 | I15: 206.25123 | J15: 0.0056046745 | K15: 251623.63 | L15: 6.2540553 | M15: 223945.36 | N15: 5.6105908 | O15: 0 | P15: 0 | Q15: 162838.46 | R15: 2.0721564 | S15: 157921.08 | T15: 2.008294 | U15: 109.53043 | V15: 0.0012854799 | W15: 334183.09 | X15: 3.6194365 | Y15: 338381.49 | Z15: 3.7046609 | AA15: 1459.1467 | AB15: 0.089129696 | AC15: 76590.889 | AD15: 4.2442365 | AE15: 77440.191 | AF15: 4.3036137 | AG15: -15.961482 | AH15: -0.00717007 | AI15: 7578.955 | AJ15: 3.7302854 | AK15: 8270.3131 | AL15: 3.6582091
B16: Banco del Bajío | C16: 347044.17 | D16: 2.4355864 | E16: 382977.7 | F16: 2.4818626 | G16: 383294.55 | H16: 2.494994 | I16: 23912.925 | J16: 0.64981024 | K16: 29641.297 | L16: 0.73672855 | M16: 31836.004 | N16: 0.79759987 | O16: 254571.14 | P16: 3.4676355 | Q16: 266968.83 | R16: 3.397239 | S16: 268199.21 | T16: 3.4107091 | U16: 287440.56 | V16: 3.3734832 | W16: 316482.61 | X16: 3.427728 | Y16: 318804.45 | Z16: 3.490328 | AA16: 43057.343 | AB16: 2.6300905 | AC16: 46337.389 | AD16: 2.5677576 | AE16: 47108.401 | AF16: 2.6179734 | AG16: 8150.551 | AH16: 3.6613154 | AI16: 6181.8116 | AJ16: 3.0426255 | AK16: 6924.0481 | AL16: 3.0627155
B17: Banco Azteca | C17: 311661.36 | D17: 2.1872667 | E17: 360844.95 | F17: 2.3384327 | G17: 353123.75 | H17: 2.2986021 | I17: 75412.965 | J17: 2.0492732 | K17: 106765.34 | L17: 2.6536313 | M17: 104454.19 | N17: 2.6169317 | O17: 183525.6 | P17: 2.4998902 | Q17: 204657.34 | R17: 2.6043111 | S17: 203994.87 | T17: 2.5942178 | U17: 222874.58 | V17: 2.6157187 | W17: 247637.47 | X17: 2.682087 | Y17: 240763.79 | Z17: 2.6359249 | AA17: 37306.978 | AB17: 2.2788385 | AC17: 44985.17 | AD17: 2.4928252 | AE17: 47426.02 | AF17: 2.6356245 | AG17: 3833.7532 | AH17: 1.7221633 | AI17: 3858.3457 | AJ17: 1.8990389 | AK17: 4259.1952 | AL17: 1.8839706
B18: Afirme | C18: 295135.44 | D18: 2.0712864 | E18: 314172.38 | F18: 2.0359741 | G18: 317026.41 | H18: 2.0636323 | I18: 162775.96 | J18: 4.4232767 | K18: 179170.06 | L18: 4.4532362 | M18: 178452.96 | N18: 4.4708518 | O18: 64414.765 | P18: 0.87742438 | Q18: 68901.897 | R18: 0.87679228 | S18: 69893.806 | T18: 0.88884468 | U18: 91651.153 | V18: 1.0756437 | W18: 87043.479 | X18: 0.94274175 | Y18: 89448.351 | Z18: 0.97929651 | AA18: 8720.0585 | AB18: 0.53265115 | AC18: 9236.0385 | AD18: 0.51180933 | AE18: 9276.1041 | AF18: 0.51550452 | AG18: 403.28073 | AH18: 0.18115805 | AI18: 650.37462 | AJ18: 0.32010785 | AK18: 743.91518 | AL18: 0.32905614
... B58: CIBanco | C58: 148514.04 | D58: 1.0422846 | E58: 68658.224 | F58: 0.44493525 | G58: 0 | H58: 0 | I58: 60853.073 | J58: 1.6536224 | K58: 46196.814 | L58: 1.1482126 | M58: 0 | N58: 0 | O58: 13484.912 | P58: 0.18368445 | Q58: 6940.8554 | R58: 0.08832396 | S58: 0 | T58: 0 | U58: 55509.599 | V58: 0.65147624 | W58: 11931.171 | X58: 0.12922293 | Y58: 0 | Z58: 0 | AA58: 5319.636 | AB58: 0.32494166 | AC58: 5176.285 | AD58: 0.28684061 | AE58: 0 | AF58: 0 | AG58: 270.63046 | AH58: 0.12157012 | AI58: -533.02978 | AJ58: -0.2623519 | AK58: 0 | AL58: 0
B59: Intercam Banco | C59: 80292.703 | D59: 0.56350124 | E59: 32202.599 | F59: 0.20868689 | G59: n.d. | H59: 0 | I59: 33834.627 | J59: 0.91942275 | K59: 10838.548 | L59: 0.26938996 | M59: n.d. | N59: 0 | O59: 21764.329 | P59: 0.29646235 | Q59: 13701.469 | R59: 0.1743543 | S59: n.d. | T59: 0 | U59: 38295.385 | V59: 0.44944539 | W59: 18720.004 | X59: 0.20275073 | Y59: n.d. | Z59: 0 | AA59: 10091.506 | AB59: 0.61642388 | AC59: 11335.532 | AD59: 0.62815143 | AE59: n.d. | AF59: 0 | AG59: 1966.4093 | AH59: 0.88333227 | AI59: 952.45441 | AJ59: 0.46878848 | AK59: n.d. | AL59: 0
B61: n.d. No disponible

Sheet Indicadores
B2: Indicadores financieros
B3: Porcentajes | O3: 1.5853443
C5: ROA (Flujo 12 meses) 3/ | F5: ROE (Flujo 12 meses) 4/
C6: 45536 | D6: 45870 | E6: 45901 | F6: =+C6 -> 45536 | G6: =+D6 -> 45870 | H6: =+E6 -> 45901
B7: Sistema */ | C7: 2.0903083 | D7: 1.9621093 | E7: 1.9256743 | F7: 18.589893 | G7: 17.390141 | H7: 17.036981
B8: BBVA México | C8: 3.0018527 | D8: 2.9566591 | E8: 2.9105992 | F8: 26.386441 | G8: 25.893534 | H8: 25.436267
B9: Santander | C9: 1.5453166 | D9: 1.5219715 | E9: 1.5143325 | F9: 17.608706 | G9: 18.861805 | H9: 18.88389
B10: Banorte | C10: 2.5373499 | D10: 2.4700136 | E10: 2.425762 | F10: 29.33587 | G10: 28.748222 | H10: 28.095885
B11: Banamex | C11: 1.6243797 | D11: 1.3444569 | E11: 1.2589613 | F11: 11.173534 | G11: 8.5236798 | H11: 7.9401549
B12: HSBC | C12: 0.98113871 | D12: 0.74108866 | E12: 0.7391947 | F12: 10.33091 | G12: 8.0945442 | H12: 8.0428776
B13: Scotiabank | C13: 1.2673771 | D13: 1.1707526 | E13: 1.1788842 | F13: 13.148883 | G13: 11.527083 | H13: 11.55274
B14: Inbursa | C14: 4.2169987 | D14: 3.5410859 | E14: 3.370025 | F14: 15.661865 | G14: 12.628435 | H14: 11.976934
B15: Citi México | C15: 2.0102569 | D15: 1.3806368 | E15: 1.3967315 | F15: 2.3397587 | G15: 11.192472 | H15: 11.205029
B16: Banco del Bajío | C16: 3.2030177 | D16: 2.604197 | E16: 2.566643 | F16: 26.3858 | G16: 21.045841 | H16: 20.758826
B17: Banco Azteca | C17: 1.4243603 | D17: 1.7760803 | E17: 1.7599291 | F17: 11.914921 | G17: 14.381277 | H17: 14.109705
B18: Afirme | C18: 0.15944578 | D18: 0.26444664 | E18: 0.27892826 | F18: 5.4810049 | G18: 9.012611 | H18: 9.5137922
... B43: ICBC | C43: 3.3525343 | D43: 2.2783634 | E43: 2.3146084 | F43: 27.067063 | G43: 20.428629 | H43: 20.938262
B44: Openbank | C44: n.a. | D44: -24.527727 | E44: -22.851442 | F44: n.a. | G44: -35.666321 | H44: -36.766528
B45: Banco Covalto | C45: 0.046420338 | D45: 1.5704968 | E45: 1.5036116 | F45: 0.34590188 | G45: 12.76194 | H45: 12.143935
B46: Volkswagen Bank | C46: 6.08663 | D46: 6.0615049 | E46: 6.2143517 | F46: 9.0370614 | G46: 12.705889 | H46: 13.379389
B47: Banco S3 | C47: 5.6160398 | D47: 5.4365239 | E47: 5.331649 | F47: 12.9828 | G47: 13.00302 | H47: 13.038216
B48: Bank of China | C48: 1.9859903 | D48: 1.9968873 | E48: 1.995916 | F48: 10.4272 | G48: 8.741238 | H48: 8.2352083
B49: Shinhan | C49: 2.3819426 | D49: 1.817915 | E49: 1.7668573 | F49: 7.3517564 | G49: 6.4123743 | H49: 6.2762287
B50: Banco Ualá | C50: -26.207697 | D50: -18.580999 | E50: -18.169057 | F50: -154.13849 | G50: -149.41837 | H50: -142.56008
B51: KEB Hana México | C51: 0.92507228 | D51: 0.76336247 | E51: 0.76038282 | F51: 2.6902856 | G51: 2.5198903 | H51: 2.5057716
B52: Banco Bineo | C52: -27.077141 | D52: -30.148729 | E52: -30.456123 | F52: -29.565611 | G52: -32.213142 | H52: -32.401331
B53: Dondé Banco | C53: -11.140061 | D53: -4.64868 | E53: -4.3926222 | F53: -22.828445 | G53: -21.648423 | H53: -21.362706
B54: Credit Suisse | C54: -10.696884 | D54: -5.3130418 | E54: -4.9125421 | F54: -15.447928 | G54: -5.6906418 | H54: -5.2132177
B55: Hey Banco | C55: n.a. | D55: 5.2069735 | E55: 4.852482 | F55: n.a. | G55: 5.2308925 | H55: 4.874223
B56: Forjadores | C56: 1.4067658 | D56: -2.8065719 | E56: -2.9400751 | F56: 2.0096612 | G56: -4.0533763 | H56: -4.263933
B57: Pagatodo | C57: -13.028624 | D57: -19.390734 | E57: -18.020991 | F57: -17.500247 | G57: -26.405367 | H57: -26.893868
B58: CIBanco | C58: 0.44782896 | D58: -0.11224776 | E58: 0.28000228 | F58: 10.050151 | G58: -2.7877843 | H58: 6.8809651
B59: Intercam Banco | C59: 3.9026326 | D59: 2.6412978 | E59: n.d. | F59: 28.497161 | G59: 18.488138 | H59: n.d.
B62: n.d. No disponible

Sheet CCT
B2: Cartera de crédito total
B3: Millones de pesos y porcentajes
C5: Cartera total (MDP) 1/ | F5: IMOR (%) 5/ | I5: ICOR (%) 6/ | L5: Pérdida esperada (%) 7/
C6: 45536 | D6: 45870 | E6: 45901 | F6: =C6 -> 45536 | G6: =D6 -> 45870 | H6: =E6 -> 45901 | I6: =C6 -> 45536 | J6: =D6 -> 45870 | K6: =E6 -> 45901 | L6: =C6 -> 45536 | M6: =D6 -> 45870 | N6: =E6 -> 45901
B7: Sistema */ | C7: 7341346.6 | D7: 7858406 | E7: 7863444.3 | F7: 2.0590376 | G7: 2.1597894 | H7: 2.235963 | I7: 155.97289 | J7: 150.15523 | K7: 147.33948 | L7: 3.2115406 | M7: 3.2430367 | N7: 3.2944562
B8: BBVA México | C8: 1839030.8 | D8: 2012068.9 | E8: 2016789.4 | F8: 1.6785616 | G8: 1.6507735 | H8: 1.7240306 | I8: 191.71125 | J8: 189.94649 | K8: 182.54423 | L8: 3.2179913 | M8: 3.1355863 | N8: 3.1471184
B9: Santander | C9: 874142.25 | D9: 929316.63 | E9: 926658.93 | F9: 2.3390753 | G9: 2.2979288 | H9: 2.406478 | I9: 135.64018 | J9: 135.87507 | K9: 134.08072 | L9: 3.1727261 | M9: 3.1223123 | N9: 3.226623
B10: Banorte | C10: 1079814.2 | D10: 1158655.5 | E10: 1164148.4 | F10: 0.93695034 | G10: 1.0782108 | H10: 1.3713432 | I10: 173.73259 | J10: 156.92802 | K10: 134.94421 | L10: 1.6277881 | M10: 1.6920148 | N10: 1.8505484
B11: Banamex | C11: 620251.84 | D11: 492087.34 | E11: 503424.35 | F11: 2.1226197 | G11: 2.8062853 | H11: 2.7992908 | I11: 205.79469 | J11: 190.14216 | K11: 190.55203 | L11: 4.3682386 | M11: 5.3359315 | N11: 5.3341055
B12: HSBC | C12: 503555.8 | D12: 490989.81 | E12: 483659.84 | F12: 2.2124578 | G12: 2.9594283 | H12: 2.9904825 | I12: 154.26755 | J12: 129.70583 | K12: 129.23467 | L12: 3.4131044 | M12: 3.8385512 | N12: 3.8647402
B13: Scotiabank | C13: 527608.54 | D13: 532170.63 | E13: 529339.29 | F13: 3.8660942 | G13: 4.042423 | H13: 4.1159353 | I13: 72.368682 | J13: 69.024933 | K13: 69.459426 | L13: 2.7978414 | M13: 2.7902798 | N13: 2.858905
B14: Inbursa | C14: 444506.49 | D14: 466601.03 | E14: 467303.13 | F14: 1.5876496 | G14: 1.5063476 | H14: 1.4700399 | I14: 140.31655 | J14: 149.20137 | K14: 154.16425 | L14: 2.2277352 | M14: 2.2474914 | N14: 2.266276
B15: Citi México | C15: 0 | D15: 162838.46 | E15: 157921.08 | F15: - | G15: 1.3908188 | H15: 1.4345793 | I15: - | J15: 188.59079 | K15: 184.3 | L15: - | M15: 2.6229561 | N15: 2.6439296
B16: Banco del Bajío | C16: 254571.14 | D16: 266968.83 | E16: 268199.21 | F16: 1.4891518 | G16: 1.845093 | H16: 1.9736294 | I16: 141.09045 | J16: 119.95995 | K16: 115.74629 | L16: 2.101051 | M16: 2.2133728 | N16: 2.2844029
B17: Banco Azteca | C17: 183525.6 | D17: 204657.34 | E17: 203994.87 | F17: 3.4627228 | G17: 4.6627621 | H17: 4.8727849 | I17: 344.94667 | J17: 255.08493 | K17: 254.11316 | L17: 11.944547 | M17: 11.894004 | N17: 12.382388
B18: Afirme | C18: 64414.765 | D18: 68901.897 | E18: 69893.806 | F18: 5.5170309 | G18: 3.9420726 | H18: 3.9085741 | I18: 69.017311 | J18: 84.882725 | K18: 86.241004 | L18: 3.8077063 | M18: 3.3461386 | N18: 3.3707935
B19: Monex | C19: 45979.93 | D19: 55196.869 | E19: 54595.986 | F19: 1.4262459 | G19: 1.4745026 | H19: 1.4693963 | I19: 129.42789 | J19: 128.6824 | K19: 129.99268 | L19: 1.8459599 | M19: 1.8974253 | N19: 1.9101075
B20: Banregio | C20: 171638.25 | D20: 186462.78 | E20: 188494.8 | F20: 1.2336374 | G20: 1.5762546 | H20: 1.6140056 | I20: 168.53411 | J20: 134.43745 | K20: 130.42363 | L20: 2.0790998 | M20: 2.1190765 | N20: 2.1050447
B21: J.P. Morgan | C21: 23030.498 | D21: 24842.326 | E21: 23631.979 | F21: 0 | G21: 0 | H21: 0 | I21: - | J21: - | K21: - | L21: 0.72483536 | M21: 0.64205721 | N21: 0.61792183
B22: Invex | C22: 41546.324 | D22: 49339.463 | E22: 49754.432 | F22: 2.186528 | G22: 2.35529 | H22: 2.2510827 | I22: 238.43119 | J22: 241.82046 | K22: 255.65101 | L22: 5.2133648 | M22: 5.6955732 | N22: 5.7549158
B23: Multiva | C23: 70690.182 | D23: 81408.031 | E23: 86876.488 | F23: 3.4114477 | G23: 2.568871 | H23: 2.6903645 | I23: 94.875868 | J23: 114.35006 | K23: 109.92655 | L23: 3.2366406 | M23: 2.9375055 | N23: 2.957425
B24: BanCoppel | C24: 61055.263 | D24: 79132.111 | E24: 78285.569 | F24: 8.4392693 | G24: 5.4084956 | H24: 5.4978305 | I24: 134.19706 | J24: 150.1693 | K24: 150.34336 | L24: 11.325251 | M24: 8.1218998 | N24: 8.2656231
B25: Banca Mifel | C25: 77836.741 | D25: 84449.258 | E25: 83911.035 | F25: 2.4529447 | G25: 2.8478877 | H25: 3.1923916 | I25: 88.655054 | J25: 79.624047 | K25: 71.33299 | L25: 2.1746594 | M25: 2.2676034 | N25: 2.2772283
B26: Barclays | C26: 0 | D26: 0 | E26: 0 | F26: - | G26: - | H26: - | I26: - | J26: - | K26: - | L26: - | M26: - | N26: -
B27: Banco Base | C27: 11442.382 | D27: 10437.397 | E27: 10461.586 | F27: 2.4630544 | G27: 3.3503311 | H27: 3.2162987 | I27: 119.02222 | J27: 101.09046 | K27: 103.56998 | L27: 2.9315821 | M27: 3.386865 | N27: 3.33112
B28: Sabadell | C28: 94054.735 | D28: 100285.57 | E28: 101304.32 | F28: 2.1751498 | G28: 2.0369979 | H28: 1.8835613 | I28: 71.725947 | J28: 68.998084 | K28: 69.585855 | L28: 1.5601468 | M28: 1.4054895 | N28: 1.3106922
B29: Bank of America | C29: 33087.576 | D29: 43913.817 | E29: 45436.847 | F29: 0 | G29: 0 | H29: 0 | I29: - | J29: - | K29: - | L29: 0.8713084 | M29: 0.98873116 | N29: 1.1721605
B30: Ve por Más | C30: 56671.8 | D30: 59826.379 | E30: 62000.729 | F30: 3.0933377 | G30: 2.8954991 | H30: 2.7592538 | I30: 96.811116 | J30: 111.15768 | K30: 115.20369 | L30: 2.9946947 | M30: 3.2185697 | N30: 3.1787623
B31: Actinver | C31: 27303.77 | D31: 29803.299 | E31: 29502.671 | F31: 3.3415707 | G31: 3.1306968 | H31: 2.9741051 | I31: 115.99847 | J31: 111.1205 | K31: 113.46367 | L31: 3.8761707 | M31: 3.4788458 | N31: 3.374529
B32: Bansí | C32: 22101.042 | D32: 30139.47 | E32: 29578.353 | F32: 4.4923449 | G32: 3.5418365 | H32: 3.6772336 | I32: 158.18191 | J32: 173.29319 | K32: 171.68334 | L32: 7.1060768 | M32: 6.1377615 | N32: 6.3131976
B33: Compartamos | C33: 48565.199 | D33: 59110.491 | E33: 58108.319 | F33: 3.3606933 | G33: 3.2626805 | H33: 3.5065949 | I33: 234.72744 | J33: 236.87828 | K33: 236.61154 | L33: 7.8884695 | M33: 7.7285813 | N33: 8.2970081
B34: BIAfirme | C34: 272.76063 | D34: 244.07477 | E34: 241.49468 | F34: 0 | G34: 0 | H34: 0 | I34: - | J34: - | K34: - | L34: 0.44300675 | M34: 0.56619249 | N34: 0.58409361
B35: Bancrea | C35: 36194.128 | D35: 43738.995 | E35: 44154.664 | F35: 0.92127341 | G35: 2.1351984 | H35: 2.1386388 | I35: 139.17427 | J35: 72.374258 | K35: 87.411205 | L35: 1.2821756 | M35: 1.545334 | N35: 1.86941
B36: Kapital Bank | C36: 4640.7704 | D36: 10101.269 | E36: 22058.982 | F36: 3.3784599 | G36: 2.7156992 | H36: 1.4502096 | I36: 130.17619 | J36: 153.72453 | K36: 178.95398 | L36: 4.3979504 | M36: 4.1746959 | N36: 2.5952079
B37: MUFG Bank | C37: 13684.455 | D37: 7477.1335 | E37: 5841.3814 | F37: 0 | G37: 0 | H37: 0 | I37: - | J37: - | K37: - | L37: 0.53910977 | M37: 0.77410859 | N37: 0.85501766
B38: Consubanco | C38: 23743.328 | D38: 31460.825 | E38: 31736.663 | F38: 1.6870264 | G38: 1.5104281 | H38: 1.4718667 | I38: 215.28379 | J38: 232.96449 | K38: 237.15309 | L38: 3.6318944 | M38: 3.5187612 | N38: 3.4905772
B39: Bankaool | C39: 7855.3757 | D39: 12973.417 | E39: 13865.611 | F39: 1.8752992 | G39: 0.84564655 | H39: 0.78218156 | I39: 156.38954 | J39: 216.91464 | K39: 202.21036 | L39: 2.9327718 | M39: 1.8343311 | N39: 1.5816521
B40: BNP Paribas México | C40: 0 | D40: 0 | E40: 0 | F40: - | G40: - | H40: - | I40: - | J40: - | K40: - | L40: - | M40: - | N40: -
B41: Inmobiliario Mexicano | C41: 11686.081 | D41: 12581.466 | E41: 12639.05 | F41: 3.5654478 | G41: 2.825377 | H41: 2.7589361 | I41: 61.604084 | J41: 64.458994 | K41: 64.1077 | L41: 2.1964614 | M41: 1.8212096 | N41: 1.7686905
B42: Mizuho Bank | C42: 4730.6043 | D42: 6064.05 | E42: 6089.6534 | F42: 0 | G42: 0 | H42: 0 | I42: - | J42: - | K42: - | L42: 0.46249331 | M42: 0.46360062 | N42: 0.46501875
B43: ICBC | C43: 3084.2767 | D43: 4986.133 | E43: 5056.2963 | F43: 0 | G43: 0 | H43: 0 | I43: - | J43: - | K43: - | L43: 3.3526654 | M43: 1.9400029 | N43: 1.7640153
B44: Openbank | C44: 0 | D44: 181.24835 | E44: 227.56701 | F44: - | G44: 2.3362166 | H44: 4.4823286 | I44: - | J44: 1034.7188 | K44: 592.77418 | L44: - | M44: 24.173272 | N44: 26.570087
B45: Banco Covalto | C45: 4935.1843 | D45: 7229.0721 | E45: 7422.879 | F45: 5.757832 | G45: 5.11827 | H45: 5.2333331 | I45: 64.448425 | J45: 69.831469 | K45: 70.908165 | L45: 3.7108321 | M45: 3.5741631 | N45: 3.7108605
B46: Volkswagen Bank | C46: 5196.7482 | D46: 7404.2091 | E46: 7533.6041 | F46: 1.0802438 | G46: 1.1170978 | H46: 1.1617912 | I46: 251.20797 | J46: 249.91953 | K46: 197.17179 | L46: 2.7136586 | M46: 2.7918457 | N46: 2.2907245
B47: Banco S3 | C47: 105.10623 | D47: 149.06457 | E47: 48.470706 | F47: 0 | G47: 0 | H47: 0 | I47: - | J47: - | K47: - | L47: 0.41915878 | M47: 0.85647579 | N47: 0.46029451
B48: Bank of China | C48: 4341.4309 | D48: 2680.1986 | E48: 2572.1067 | F48: 4.0791341 | G48: 4.2112451 | H48: 4.2181826 | I48: 99.237901 | J48: 109.58848 | K48: 109.81915 | L48: 4.0480471 | M48: 4.6150395 | N48: 4.6323724
B49: Shinhan | C49: 3656.2998 | D49: 4488.8661 | E49: 4352.6555 | F49: 1.5229486 | G49: 1.2404818 | H49: 1.279301 | I49: 63.474201 | J49: 74.343511 | K49: 72.727293 | L49: 0.96667945 | M49: 0.92221773 | N49: 0.93040102
B50: Banco Ualá | C50: 523.6402 | D50: 807.73272 | E50: 845.31995 | F50: 27.727179 | G50: 16.512534 | H50: 16.268617 | I50: 82.032611 | J50: 122.12105 | K50: 130.39372 | L50: 22.745329 | M50: 20.16528 | N50: 21.213255
B51: KEB Hana México | C51: 3455.5057 | D51: 3613.1037 | E51: 3523.9819 | F51: 1.6157864 | G51: 1.5999749 | H51: 1.6426958 | I51: 109.76151 | J51: 127.47702 | K51: 127.13588 | L51: 1.7735116 | M51: 2.0396004 | N51: 2.0884558
B52: Banco Bineo | C52: 45.981923 | D52: 9.8025796 | E52: 6.5318605 | F52: 5.521153 | G52: 42.710186 | H52: 37.733611 | I52: 293.77194 | J52: 94.337196 | K52: 95.978757 | L52: 16.219598 | M52: 40.291592 | N52: 36.21625
B53: Dondé Banco | C53: 1030.002 | D53: 1565.196 | E53: 1512.996 | F53: 0.31501639 | G53: 0.20730151 | H53: 0.21445364 | I53: 291.95442 | J53: 369.28688 | K53: 352.55784 | L53: 0.91970427 | M53: 0.76553728 | N53: 0.75607312
B54: Credit Suisse | C54: 0 | D54: 0 | E54: 0 | F54: - | G54: - | H54: - | I54: - | J54: - | K54: - | L54: - | M54: - | N54: -
B55: Hey Banco | C55: 0 | D55: 0 | E55: 0 | F55: - | G55: - | H55: - | I55: - | J55: - | K55: - | L55: - | M55: - | N55: -
B56: Forjadores | C56: 490.57564 | D56: 404.2503 | E56: 438.99178 | F56: 7.0301149 | G56: 8.4306326 | H56: 7.2775887 | I56: 144.96996 | J56: 135.05629 | K56: 155.73784 | L56: 10.191555 | M56: 11.3861 | N56: 11.333959
B57: Pagatodo | C57: 0 | D57: 0 | E57: 0 | F57: - | G57: - | H57: - | I57: - | J57: - | K57: - | L57: - | M57: - | N57: -
B58: CIBanco | C58: 13484.912 | D58: 6940.8554 | E58: 0 | F58: 3.5240426 | G58: 8.1069954 | H58: - | I58: 104.42867 | J58: 64.710529 | K58: - | L58: 3.6801109 | M58: 5.2460796 | N58: -
B59: Intercam Banco | C59: 21764.329 | D59: 13701.469 | E59: n.d. | F59: 3.3298833 | G59: 7.0765523 | H59: n.d. | I59: 168.49231 | J59: 143.23318 | K59: n.d. | L59: 5.6105971 | M59: 10.135971 | N59: n.d.
B61: n.d. No disponible

Sheet CCE
B2: Cartera de crédito a empresas
B3: Millones de pesos y porcentajes
C5: Cartera total (MDP) 1/ | F5: IMOR (%) 5/ | I5: ICOR (%) 6/ | L5: Pérdida esperada (%) 7/
C6: 45536 | D6: 45870 | E6: 45901 | F6: =C6 -> 45536 | G6: =D6 -> 45870 | H6: =E6 -> 45901 | I6: =C6 -> 45536 | J6: =D6 -> 45870 | K6: =E6 -> 45901 | L6: =C6 -> 45536 | M6: =D6 -> 45870 | N6: =E6 -> 45901
B7: Sistema */ | C7: 3469495.1 | D7: 3737376.9 | E7: 3724672.5 | F7: 1.7257781 | G7: 1.758917 | H7: 1.8690689 | I7: 95.843779 | J7: 96.012094 | K7: 93.681861 | L7: 1.6540509 | M7: 1.688773 | N7: 1.7509785
B8: BBVA México | C8: 766552.02 | D8: 842552.82 | E8: 839268.06 | F8: 1.234799 | G8: 1.0776563 | H8: 1.1965507 | I8: 96.330757 | J8: 108.17431 | K8: 102.15988 | L8: 1.1894912 | M8: 1.1657472 | N8: 1.2223948
B9: Santander | C9: 372849.84 | D9: 380939.14 | E9: 377258.9 | F9: 1.5604648 | G9: 1.6108388 | H9: 1.7976544 | I9: 91.885848 | J9: 97.016733 | K9: 90.423326 | L9: 1.4338463 | M9: 1.5627832 | N9: 1.6254989
B10: Banorte | C10: 422335.38 | D10: 460160.81 | E10: 457808.28 | F10: 0.87344447 | G10: 1.1429573 | H10: 1.8753544 | I10: 84.177485 | J10: 70.824159 | K10: 62.924932 | L10: 0.73524359 | M10: 0.8094899 | N10: 1.1800655
B11: Banamex | C11: 252774.75 | D11: 132285.57 | E11: 138105.89 | F11: 1.0932264 | G11: 2.754815 | H11: 2.7103877 | I11: 164.1774 | J11: 98.840577 | K11: 98.461742 | L11: 1.7948307 | M11: 2.722875 | N11: 2.668695
B12: HSBC | C12: 212841.1 | D12: 220723.03 | E12: 219529.06 | F12: 2.0628019 | G12: 2.8889034 | H12: 2.8732029 | I12: 91.65809 | J12: 85.842568 | K12: 86.907278 | L12: 1.8907248 | M12: 2.4799089 | N12: 2.4970224
B13: Scotiabank | C13: 192926.81 | D13: 194943.21 | E13: 190991.52 | F13: 4.0624433 | G13: 2.7577768 | H13: 2.8979997 | I13: 78.975587 | J13: 80.099535 | K13: 80.945595 | L13: 3.2083384 | M13: 2.2089664 | N13: 2.3458031
B14: Inbursa | C14: 310558.81 | D14: 326660.46 | E14: 329200.03 | F14: 1.6517417 | G14: 1.5115313 | H14: 1.4172109 | I14: 113.49098 | J14: 119.96108 | K14: 127.35284 | L14: 1.8745779 | M14: 1.8132494 | N14: 1.8048582
B15: Citi México | C15: 0 | D15: 133585.88 | E15: 130764.29 | F15: - | G15: 0.0067496803 | H15: 0.0073875108 | I15: - | J15: 17006.207 | K15: 15957.841 | L15: - | M15: 1.1478646 | N15: 1.1788872
B16: Banco del Bajío | C16: 215258.26 | D16: 231432.33 | E16: 231747.9 | F16: 1.5820078 | G16: 1.9486717 | H16: 2.0765553 | I16: 104.1926 | J16: 94.534993 | K16: 91.532564 | L16: 1.648335 | M16: 1.8421767 | N16: 1.9007243
B17: Banco Azteca | C17: 42600.465 | D17: 45638.894 | E17: 43479.286 | F17: 0.99514157 | G17: 4.1774129 | H17: 3.7861506 | I17: 81.847243 | J17: 49.173183 | K17: 46.450138 | L17: 0.81449594 | M17: 2.0541669 | N17: 1.7586722
B18: Afirme | C18: 36944.826 | D18: 39898.806 | E18: 40246.774 | F18: 6.6808087 | G18: 4.4209898 | H18: 4.2830678 | I18: 45.103807 | J18: 51.792746 | K18: 54.94461 | L18: 3.0132991 | M18: 2.289752 | N18: 2.3533149
B19: Monex | C19: 34072.287 | D19: 41955.725 | E19: 42329.099 | F19: 1.7755753 | G19: 1.8500347 | H19: 1.8076002 | I19: 108.91589 | J19: 114.38409 | K19: 118.58764 | L19: 1.9338837 | M19: 2.1161453 | N19: 2.1435903
B20: Banregio | C20: 138704.14 | D20: 149692.77 | E20: 151663.63 | F20: 1.2018854 | G20: 1.6140326 | H20: 1.6581853 | I20: 134.99208 | J20: 105.58514 | K20: 103.18945 | L20: 1.6224501 | M20: 1.7041785 | N20: 1.7110723
B21: J.P. Morgan | C21: 22505.88 | D21: 23991.417 | E21: 22689.95 | F21: 0 | G21: 0 | H21: 0 | I21: - | J21: - | K21: - | L21: 0.55979871 | M21: 0.62284812 | N21: 0.59459943
B22: Invex | C22: 14082.513 | D22: 14454.032 | E22: 14284.716 | F22: 2.4419374 | G22: 1.8825516 | H22: 1.8799254 | I22: 83.954736 | J22: 119.8119 | K22: 113.3549 | L22: 2.0501221 | M22: 2.2555209 | N22: 2.1309876
B23: Multiva | C23: 32814.668 | D23: 44501.538 | E23: 46069.086 | F23: 5.7618841 | G23: 3.666852 | H23: 4.065764 | I23: 81.606787 | J23: 101.04747 | K23: 96.061725 | L23: 4.7020884 | M23: 3.7052613 | N23: 3.905643
B24: BanCoppel | C24: 31669.944 | D24: 42102.249 | E24: 41391.458 | F24: 4.2233946 | G24: 3.8361586 | H24: 3.7796711 | I24: 80.152697 | J24: 85.584636 | K24: 88.453299 | L24: 3.3851647 | M24: 3.2831624 | N24: 3.3432438
B25: Banca Mifel | C25: 53246.048 | D25: 61096.464 | E25: 60628.149 | F25: 1.3431125 | G25: 1.3121854 | H25: 1.672291 | I25: 130.41486 | J25: 129.89843 | K25: 107.76295 | L25: 1.7516183 | M25: 1.7045083 | N25: 1.80211
B26: Barclays | C26: 0 | D26: 0 | E26: 0 | F26: - | G26: - | H26: - | I26: - | J26: - | K26: - | L26: - | M26: - | N26: -
B27: Banco Base | C27: 11053.735 | D27: 10138.432 | E27: 10175.639 | F27: 2.5496547 | G27: 3.4491267 | H27: 3.3066803 | I27: 91.727322 | J27: 82.087936 | K27: 86.778494 | L27: 2.33873 | M27: 2.8313169 | N27: 2.8694874
B28: Sabadell | C28: 91728.949 | D28: 97700.862 | E28: 98623.466 | F28: 2.1175356 | G28: 2.0907283 | H28: 1.934604 | I28: 70.241925 | J28: 68.298771 | K28: 68.87021 | L28: 1.4873978 | M28: 1.4279417 | N28: 1.3323658
B29: Bank of America | C29: 26737.96 | D29: 30806.887 | E29: 32391.552 | F29: 0 | G29: 0 | H29: 0 | I29: - | J29: - | K29: - | L29: 0.94245674 | M29: 1.0791899 | N29: 1.3234831
B30: Ve por Más | C30: 40004.25 | D30: 44053.567 | E30: 45376.403 | F30: 4.0456977 | G30: 3.6631818 | H30: 3.5109 | I30: 73.570684 | J30: 87.041864 | K30: 90.063462 | L30: 2.9764475 | M30: 3.1885017 | N30: 3.1620381
B31: Actinver | C31: 22222.499 | D31: 23748.61 | E31: 23804.938 | F31: 3.0587309 | G31: 2.9992543 | H31: 2.7863803 | I31: 101.16513 | J31: 88.38311 | K31: 91.305382 | L31: 3.0943692 | M31: 2.6508342 | N31: 2.5441152
B32: Bansí | C32: 17402.968 | D32: 19368.466 | E32: 19171.31 | F32: 5.4094088 | G32: 5.112532 | H32: 5.2891427 | I32: 139.54551 | J32: 155.61775 | K32: 155.64513 | L32: 7.5485872 | M32: 7.9560071 | N32: 8.2322929
B33: Compartamos | C33: 0 | D33: 0 | E33: 0 | F33: - | G33: - | H33: - | I33: - | J33: - | K33: - | L33: - | M33: - | N33: -
B34: BIAfirme | C34: 272.76063 | D34: 244.07477 | E34: 241.49468 | F34: 0 | G34: 0 | H34: 0 | I34: - | J34: - | K34: - | L34: 0.44300675 | M34: 0.56619249 | N34: 0.58409361
B35: Bancrea | C35: 30879.593 | D35: 36922.142 | E35: 37373.714 | F35: 0.98920291 | G35: 2.424181 | H35: 2.423842 | I35: 132.90102 | J35: 63.38558 | K35: 81.631483 | L35: 1.3146608 | M35: 1.5365812 | N35: 1.9786182
B36: Kapital Bank | C36: 2854.4377 | D36: 7785.3669 | E36: 18677.844 | F36: 3.1707125 | G36: 2.9590422 | H36: 1.4305855 | I36: 146.83189 | J36: 150.99112 | K36: 176.91841 | L36: 4.6556171 | M36: 4.467891 | N36: 2.530969
B37: MUFG Bank | C37: 10310.405 | D37: 7456.553 | E37: 5819.8301 | F37: 0 | G37: 0 | H37: 0 | I37: - | J37: - | K37: - | L37: 0.52159276 | M37: 0.76217465 | N37: 0.84194202
B38: Consubanco | C38: 3594.4762 | D38: 7258.8692 | E38: 6996.5595 | F38: 0 | G38: 0 | H38: 0 | I38: - | J38: - | K38: - | L38: 0.93560205 | M38: 1.4481195 | N38: 1.4120513
B39: Bankaool | C39: 7577.3127 | D39: 12389.731 | E39: 13267.93 | F39: 1.9242305 | G39: 0.87660468 | H39: 0.80922021 | I39: 148.25151 | J39: 193.62594 | K39: 181.24229 | L39: 2.8527008 | M39: 1.6973341 | N39: 1.4666492
B40: BNP Paribas México | C40: 0 | D40: 0 | E40: 0 | F40: - | G40: - | H40: - | I40: - | J40: - | K40: - | L40: - | M40: - | N40: -
B41: Inmobiliario Mexicano | C41: 11380.431 | D41: 12359.499 | E41: 12415.985 | F41: 3.5600057 | G41: 2.8512192 | H41: 2.7810724 | I41: 61.95715 | J41: 64.575388 | K41: 64.272479 | L41: 2.2056781 | M41: 1.8411859 | N41: 1.7874642
B42: Mizuho Bank | C42: 432.02711 | D42: 1437.1177 | E42: 1487.7995 | F42: 0 | G42: 0 | H42: 0 | I42: - | J42: - | K42: - | L42: 0.46064659 | M42: 0.54729914 | N42: 0.54581876
B43: ICBC | C43: 2094.4961 | D43: 3584.0265 | E43: 3680.6343 | F43: 0 | G43: 0 | H43: 0 | I43: - | J43: - | K43: - | L43: 2.3250685 | M43: 1.7061966 | N43: 1.4592564
B44: Openbank | C44: 0 | D44: 0 | E44: 0 | F44: - | G44: - | H44: - | I44: - | J44: - | K44: - | L44: - | M44: - | N44: -
B45: Banco Covalto | C45: 4754.516 | D45: 6593.3137 | E45: 6733.642 | F45: 5.9766256 | G45: 5.6117977 | H45: 5.7690026 | I45: 64.035368 | J45: 68.975172 | K45: 70.012528 | L45: 3.8271542 | M45: 3.8707471 | N45: 4.0390246
B46: Volkswagen Bank | C46: 0 | D46: 0 | E46: 0 | F46: - | G46: - | H46: - | I46: - | J46: - | K46: - | L46: - | M46: - | N46: -
B47: Banco S3 | C47: 0 | D47: 0 | E47: 0 | F47: - | G47: - | H47: - | I47: - | J47: - | K47: - | L47: - | M47: - | N47: -
B48: Bank of China | C48: 2484.8594 | D48: 2045.3193 | E48: 1947.9547 | F48: 4.8699102 | G48: 3.1986244 | H48: 3.3585012 | I48: 90.870011 | J48: 111.618 | K48: 111.30584 | L48: 4.4252879 | M48: 3.5702404 | N48: 3.7382079
B49: Shinhan | C49: 3656.2998 | D49: 4488.8661 | E49: 4352.6555 | F49: 1.5229486 | G49: 1.2404818 | H49: 1.279301 | I49: 63.474201 | J49: 74.343511 | K49: 72.727293 | L49: 0.96667945 | M49: 0.92221773 | N49: 0.93040102
B50: Banco Ualá | C50: 250.45699 | D50: 185.75579 | E50: 175.62178 | F50: 39.604835 | G50: 40.429958 | H50: 42.404472 | I50: 38.500332 | J50: 38.299392 | K50: 37.249389 | L50: 15.247993 | M50: 15.484428 | N50: 15.795407
B51: KEB Hana México | C51: 3399.6721 | D51: 3555.295 | E51: 3466.0936 | F51: 0 | G51: 0 | H51: 0 | I51: - | J51: - | K51: - | L51: 0.47235688 | M51: 0.51181334 | N51: 0.52001003
B52: Banco Bineo | C52: 0 | D52: 0 | E52: 0 | F52: - | G52: - | H52: - | I52: - | J52: - | K52: - | L52: - | M52: - | N52: -
B53: Dondé Banco | C53: 729.84391 | D53: 965.0296 | E53: 1035.3302 | F53: 0.44457109 | G53: 0.33622544 | H53: 0.31339517 | I53: 163.64483 | J53: 202.33139 | K53: 208.78017 | L53: 0.72751761 | M53: 0.6802896 | N53: 0.65430697
B54: Credit Suisse | C54: 0 | D54: 0 | E54: 0 | F54: - | G54: - | H54: - | I54: - | J54: - | K54: - | L54: - | M54: - | N54: -
B55: Hey Banco | C55: 0 | D55: 0 | E55: 0 | F55: - | G55: - | H55: - | I55: - | J55: - | K55: - | L55: - | M55: - | N55: -
B56: Forjadores | C56: 0.10496 | D56: 0 | E56: 0 | F56: 0 | G56: - | H56: - | I56: - | J56: - | K56: - | L56: 10.718369 | M56: - | N56: -
B57: Pagatodo | C57: 0 | D57: 0 | E57: 0 | F57: - | G57: - | H57: - | I57: - | J57: - | K57: - | L57: - | M57: - | N57: -
B58: CIBanco | C58: 4535.385 | D58: 5125.1878 | E58: 0 | F58: 4.5315165 | G58: 7.0233442 | H58: - | I58: 75.591486 | J58: 66.929101 | K58: - | L58: 3.4254406 | M58: 4.7006612 | N58: -
B59: Intercam Banco | C59: 18399.895 | D59: 12548.744 | E59: n.d. | F59: 3.932887 | G59: 7.6773351 | H59: n.d. | I59: 81.494715 | J59: 83.860293 | K59: n.d. | L59: 3.205095 | M59: 6.4382357 | N59: n.d.
B61: n.d. No disponible

Sheet CCEF
B2: Cartera de crédito a entidades financieras
B3: Millones de pesos y porcentajes
C5: Cartera total (MDP) 1/ | F5: IMOR (%) 5/ | I5: ICOR (%) 6/ | L5: Pérdida esperada (%) 7/
C6: 45536 | D6: 45870 | E6: 45901 | F6: =C6 -> 45536 | G6: =D6 -> 45870 | H6: =E6 -> 45901 | I6: =C6 -> 45536 | J6: =D6 -> 45870 | K6: =E6 -> 45901 | L6: =C6 -> 45536 | M6: =D6 -> 45870 | N6: =E6 -> 45901
B7: Sistema */ | C7: 264885.14 | D7: 302250.41 | E7: 294664.58 | F7: 1.1755878 | G7: 1.2362234 | H7: 1.2137869 | I7: 172.68823 | J7: 142.76072 | K7: 140.92128 | L7: 2.0301018 | M7: 1.7648414 | N7: 1.710484
B8: BBVA México | C8: 39302.352 | D8: 53327.992 | E8: 53679.004 | F8: 0.041442969 | G8: 0.031183903 | H8: 0.03098436 | I8: 2042.4501 | J8: 2248.4813 | K8: 2429.2658 | L8: 0.84645198 | M8: 0.70116423 | N8: 0.75269247
B9: Santander | C9: 10419.906 | D9: 18111.078 | E9: 16925.773 | F9: 0.54494578 | G9: 0.055796232 | H9: 0.060110489 | I9: 638.73019 | J9: 3523.3188 | K9: 2094.121 | L9: 3.4807332 | M9: 1.9658791 | N9: 1.2587864
B10: Banorte | C10: 55874.237 | D10: 63593.813 | E10: 62514.614 | F10: 0.23210755 | G10: 0.20694638 | H10: 0.11864202 | I10: 125.78679 | J10: 139.92219 | K10: 224.3094 | L10: 0.29196065 | M10: 0.2895639 | N10: 0.26612521
B11: Banamex | C11: 37507.74 | D11: 2507.7808 | E11: 2555.4739 | F11: 6.0105706 | G11: 0 | H11: 0 | I11: 117.85528 | J11: - | K11: - | L11: 7.0837749 | M11: 1.1378862 | N11: 1.123693
B12: HSBC | C12: 14169.039 | D12: 9151.5685 | E12: 6497.4279 | F12: 0.00020635133 | G12: 8.5467985 | H12: 10.50534 | I12: 1367122.4 | J12: 55.933213 | K12: 61.403937 | L12: 2.8210752 | M12: 4.780499 | N12: 6.4506923
B13: Scotiabank | C13: 24213.81 | D13: 26476.244 | E13: 25563.355 | F13: 0.23278641 | G13: 0.36053668 | H13: 0.37341174 | I13: 412.06876 | J13: 223.06812 | K13: 220.37183 | L13: 0.95924007 | M13: 0.8042424 | N13: 0.82289429
B14: Inbursa | C14: 14771.051 | D14: 17753.317 | E14: 18689.09 | F14: 0 | G14: 0 | H14: 0 | I14: - | J14: - | K14: - | L14: 0.81113609 | M14: 0.78556408 | N14: 0.63371569
B15: Citi México | C15: 0 | D15: 26127.85 | E15: 24094.194 | F15: n.a. | G15: 8.6335897 | H15: 9.3625996 | I15: - | J15: 107.26264 | K15: 103.58031 | L15: - | M15: 9.2606166 | N15: 9.6978099
B16: Banco del Bajío | C16: 12408.229 | D16: 11341.702 | E16: 11631.826 | F16: 0.55910742 | G16: 0.99618279 | H16: 0.98003842 | I16: 140.82064 | J16: 204.32764 | K16: 203.05844 | L16: 0.78733864 | M16: 2.0354768 | N16: 1.9900507
B17: Banco Azteca | C17: 14168.858 | D17: 13627.822 | E17: 13430.809 | F17: 0 | G17: 0 | H17: 0 | I17: - | J17: - | K17: - | L17: 1.2557108 | M17: 0.94359385 | N17: 0.67671727
B18: Afirme | C18: 53.04723 | D18: 110.63634 | E18: 118.24382 | F18: 0 | G18: 0 | H18: 0 | I18: - | J18: - | K18: - | L18: 6.6575804 | M18: 3.4875467 | N18: 2.3444034
B19: Monex | C19: 6583.2334 | D19: 8963.9835 | E19: 8035.2776 | F19: 0.70073557 | G19: 0.42039109 | H19: 0.46159588 | I19: 127.10846 | J19: 152.91457 | K19: 149.56224 | L19: 0.89069419 | M19: 0.64283923 | N19: 0.69037315
B20: Banregio | C20: 4554.2497 | D20: 5918.6715 | E20: 5810.9621 | F20: 0 | G20: 0 | H20: 0 | I20: - | J20: - | K20: - | L20: 2.9652711 | M20: 2.2043771 | N20: 2.2255583
B21: J.P. Morgan | C21: 524.61789 | D21: 850.90924 | E21: 942.02904 | F21: 0 | G21: 0 | H21: 0 | I21: - | J21: - | K21: - | L21: 7.1548829 | M21: 0.87478495 | N21: 0.81162031
B22: Invex | C22: 1183.0214 | D22: 1750.1621 | E22: 1671.9727 | F22: 0 | G22: 0 | H22: 0 | I22: - | J22: - | K22: - | L22: 0.43953405 | M22: 1.0923315 | N22: 1.8685307
B23: Multiva | C23: 2285.6743 | D23: 6464.1901 | E23: 7086.2009 | F23: 3.7092244 | G23: 1.4490178 | H23: 1.3979327 | I23: 60.325189 | J23: 120.14173 | K23: 126.16474 | L23: 2.2375966 | M23: 1.7408751 | N23: 1.7636981
B24: BanCoppel | C24: 2116.946 | D24: 1506.5101 | E24: 1462.0747 | F24: 1.7647971 | G24: 2.4798907 | H24: 2.5552595 | I24: 96.944641 | J24: 109.98457 | K24: 112.53093 | L24: 1.7108762 | M24: 2.7274972 | N24: 2.8754572
B25: Banca Mifel | C25: 2176.8314 | D25: 2435.5247 | E25: 2447.705 | F25: 0 | G25: 0.18221983 | H25: 0 | I25: - | J25: 728.53786 | K25: - | L25: 0.54745727 | M25: 1.3275405 | N25: 0.72476202
B26: Barclays | C26: 0 | D26: 0 | E26: 0 | F26: n.a. | G26: n.a. | H26: n.a. | I26: - | J26: - | K26: - | L26: - | M26: - | N26: -
B27: Banco Base | C27: 388.64613 | D27: 298.96526 | E27: 285.9468 | F27: 0 | G27: 0 | H27: 0 | I27: - | J27: - | K27: - | L27: 0.55613779 | M27: 0.60440167 | N27: 0.60682721
B28: Sabadell | C28: 1184.3659 | D28: 1995.0113 | E28: 2095.3839 | F28: 8.5246699 | G28: 0 | H28: 0 | I28: 91.331662 | J28: - | K28: - | L28: 7.7857227 | M28: 0.43685507 | N28: 0.25356127
B29: Bank of America | C29: 6349.6163 | D29: 13106.93 | E29: 13045.295 | F29: 0 | G29: 0 | H29: 0 | I29: - | J29: - | K29: - | L29: 0.57170582 | M29: 0.77611453 | N29: 0.79642541
B30: Ve por Más | C30: 3193.2977 | D30: 3495.7048 | E30: 3675.0075 | F30: 1.2154005 | G30: 0.90599177 | H30: 0.86178867 | I30: 101.3315 | J30: 72.805939 | K30: 70.799899 | L30: 1.2315836 | M30: 0.65961582 | N30: 0.61014551
B31: Actinver | C31: 1685.7583 | D31: 2408.0401 | E31: 2121.0775 | F31: 0 | G31: 0 | H31: 0 | I31: - | J31: - | K31: - | L31: 0.80822323 | M31: 1.1906884 | N31: 0.80121621
B32: Bansí | C32: 712.38533 | D32: 790.5194 | E32: 761.92178 | F32: 0.99955483 | G32: 0.90075993 | H32: 0.93456864 | I32: 585.51076 | J32: 321.96886 | K32: 488.70876 | L32: 5.8525011 | M32: 2.9001665 | N32: 4.5673189
B33: Compartamos | C33: 0 | D33: 0 | E33: 0 | F33: n.a. | G33: n.a. | H33: n.a. | I33: - | J33: - | K33: - | L33: - | M33: - | N33: -
B34: BIAfirme | C34: 0 | D34: 0 | E34: 0 | F34: n.a. | G34: n.a. | H34: n.a. | I34: - | J34: - | K34: - | L34: - | M34: - | N34: -
B35: Bancrea | C35: 1961.2855 | D35: 2355.1212 | E35: 2218.7786 | F35: 0 | G35: 0 | H35: 0 | I35: - | J35: - | K35: - | L35: 0.39165217 | M35: 0.69013521 | N35: 0.76296001
B36: Kapital Bank | C36: 1016.6009 | D36: 1629.8663 | E36: 1811.9722 | F36: 2.5827628 | G36: 0 | H36: 0 | I36: 107.4094 | J36: - | K36: - | L36: 2.7741301 | M36: 1.5160427 | N36: 1.382301
B37: MUFG Bank | C37: 0 | D37: 20.580509 | E37: 21.551339 | F37: n.a. | G37: 0 | H37: 0 | I37: - | J37: - | K37: - | L37: - | M37: 3.4836699 | N37: 3.0634106
B38: Consubanco | C38: 2374.0505 | D38: 2119.9027 | E38: 2222.3415 | F38: 0 | G38: 0 | H38: 0 | I38: - | J38: - | K38: - | L38: 1.9504283 | M38: 1.6655405 | N38: 1.8563126
B39: Bankaool | C39: 264.20827 | D39: 558.84676 | E39: 562.1138 | F39: 0 | G39: 0 | H39: 0 | I39: - | J39: - | K39: - | L39: 3.061353 | M39: 3.9327382 | N39: 3.4288635
B40: BNP Paribas México | C40: 0 | D40: 0 | E40: 0 | F40: n.a. | G40: n.a. | H40: n.a. | I40: - | J40: - | K40: - | L40: - | M40: - | N40: -
B41: Inmobiliario Mexicano | C41: 40.270567 | D41: 8.5341719 | E41: 13.023158 | F41: 0 | G41: 0 | H41: 0 | I41: - | J41: - | K41: - | L41: 0.47517734 | M41: 0.36729961 | N41: 0.36729956
B42: Mizuho Bank | C42: 1160.1324 | D42: 1076.6711 | E42: 1068.8448 | F42: 0 | G42: 0 | H42: 0 | I42: - | J42: - | K42: - | L42: 0.19708757 | M42: 0.19194961 | N42: 0.19802199
B43: ICBC | C43: 0 | D43: 0 | E43: 0 | F43: n.a. | G43: n.a. | H43: n.a. | I43: - | J43: - | K43: - | L43: - | M43: - | N43: -
B44: Openbank | C44: 0 | D44: 0 | E44: 0 | F44: n.a. | G44: n.a. | H44: n.a. | I44: - | J44: - | K44: - | L44: - | M44: - | N44: -
B45: Banco Covalto | C45: 180.66828 | D45: 635.75836 | E45: 689.23694 | F45: 0 | G45: 0 | H45: 0 | I45: - | J45: - | K45: - | L45: 0.64966711 | M45: 0.49835433 | N45: 0.50479399
B46: Volkswagen Bank | C46: 0 | D46: 0 | E46: 0 | F46: n.a. | G46: n.a. | H46: n.a. | I46: - | J46: - | K46: - | L46: - | M46: - | N46: -
B47: Banco S3 | C47: 105.10623 | D47: 149.06457 | E47: 48.470706 | F47: 0 | G47: 0 | H47: 0 | I47: - | J47: - | K47: - | L47: 0.41915878 | M47: 0.85647579 | N47: 0.46029451
B48: Bank of China | C48: 56.082366 | D48: 298.97601 | E48: 294.57477 | F48: 100 | G48: 15.870053 | H48: 14.622459 | I48: 88 | J48: 101.33337 | K48: 101.4686 | L48: 88 | M48: 16.08166 | N48: 14.837204
B49: Shinhan | C49: 0 | D49: 0 | E49: 0 | F49: n.a. | G49: n.a. | H49: n.a. | I49: - | J49: - | K49: - | L49: - | M49: - | N49: -
B50: Banco Ualá | C50: 0 | D50: 40.48821 | E50: 37.449915 | F50: n.a. | G50: 0 | H50: 0 | I50: - | J50: - | K50: - | L50: - | M50: 0.30054675 | N50: 0.16724738
B51: KEB Hana México | C51: 55.83359 | D51: 57.808754 | E51: 57.888302 | F51: 100 | G51: 100 | H51: 100 | I51: 81 | J51: 96 | K51: 96 | L51: 81 | M51: 96 | N51: 96
B52: Banco Bineo | C52: 0 | D52: 0 | E52: 0 | F52: n.a. | G52: n.a. | H52: n.a. | I52: - | J52: - | K52: - | L52: - | M52: - | N52: -
B53: Dondé Banco | C53: 300.15805 | D53: 600.16641 | E53: 477.66574 | F53: 0 | G53: 0 | H53: 0 | I53: - | J53: - | K53: - | L53: 1.3639488 | M53: 0.89593218 | N53: 0.96825846
B54: Credit Suisse | C54: 0 | D54: 0 | E54: 0 | F54: n.a. | G54: n.a. | H54: n.a. | I54: - | J54: - | K54: - | L54: - | M54: - | N54: -
B55: Hey Banco | C55: 0 | D55: 0 | E55: 0 | F55: n.a. | G55: n.a. | H55: n.a. | I55: - | J55: - | K55: - | L55: - | M55: - | N55: -
B56: Forjadores | C56: 0 | D56: 0 | E56: 0 | F56: n.a. | G56: n.a. | H56: n.a. | I56: - | J56: - | K56: - | L56: - | M56: - | N56: -
B57: Pagatodo | C57: 0 | D57: 0 | E57: 0 | F57: n.a. | G57: n.a. | H57: n.a. | I57: - | J57: - | K57: - | L57: - | M57: - | N57: -
B58: CIBanco | C58: 444.81682 | D58: 376.93734 | E58: 0 | F58: 17.458569 | G58: 0 | H58: n.a. | I58: 89.371419 | J58: - | K58: - | L58: 15.602971 | M58: 0.92960198 | N58: -
B59: Intercam Banco | C59: 1099.0177 | D59: 206.76203 | E59: n.d. | F59: 0 | G59: 0 | H59: n.d. | I59: - | J59: - | K59: - | L59: 0.68881584 | M59: 0.16320211 | N59: n.d.
B61: n.d. No disponible
B62: n.a. No aplica

Sheet CCGT
B2: Cartera de crédito a entidades gubernamentales
B3: Millones de pesos y porcentajes
C5: Cartera total (MDP) 1/ | F5: IMOR (%) 5/ | I5: ICOR (%) 6/ | L5: Pérdida esperada (%) 7/
C6: 45536 | D6: 45870 | E6: 45901 | F6: =C6 -> 45536 | G6: =D6 -> 45870 | H6: =E6 -> 45901 | I6: =C6 -> 45536 | J6: =D6 -> 45870 | K6: =E6 -> 45901 | L6: =C6 -> 45536 | M6: =D6 -> 45870 | N6: =E6 -> 45901
B7: Sistema */ | C7: 582401.91 | D7: 514660.76 | E7: 518181.15 | F7: 0.0074249892 | G7: 0.0048196989 | H7: 0.0041975279 | I7: 6492.529 | J7: 12897.503 | K7: 12496.46 | L7: 0.48206958 | M7: 0.62162083 | N7: 0.5245424
B8: BBVA México | C8: 187636.43 | D8: 186548.24 | E8: 184340.95 | F8: 4.6086798e-05 | G8: 0 | H8: 0 | I8: 782652.69 | J8: - | K8: - | L8: 0.36069956 | M8: 0.77148882 | N8: 0.48529337
B9: Santander | C9: 64073.238 | D9: 66714.625 | E9: 67261.967 | F9: 0 | G9: 0 | H9: 0 | I9: - | J9: - | K9: - | L9: 0.35991879 | M9: 0.39531695 | N9: 0.44675904
B10: Banorte | C10: 136825.11 | D10: 120199.23 | E10: 123464.6 | F10: 0.0017071137 | G10: 0 | H10: 0 | I10: 30449.758 | J10: - | K10: - | L10: 0.519812 | M10: 0.51691559 | N10: 0.51875786
B11: Banamex | C11: 41354.771 | D11: 29908.503 | E11: 32145.642 | F11: 0 | G11: 0 | H11: 0 | I11: - | J11: - | K11: - | L11: 0.50175 | M11: 0.43059558 | N11: 0.40747339
B12: HSBC | C12: 18207.278 | D12: 11374.742 | E12: 10381.631 | F12: 5.5801861e-06 | G12: 8.932071e-06 | H12: 9.7865159e-06 | I12: 10913590 | J12: 7007004.8 | K12: 6250087.7 | L12: 0.60899861 | M12: 0.62587064 | N12: 0.61166582
B13: Scotiabank | C13: 23385.542 | D13: 5395.741 | E13: 5429.3928 | F13: 0 | G13: 0 | H13: 0 | I13: - | J13: - | K13: - | L13: 0.52529964 | M13: 0.56499681 | N13: 0.61464654
B14: Inbursa | C14: 30649.737 | D14: 21994.368 | E14: 18601.646 | F14: 0 | G14: 0 | H14: 0 | I14: - | J14: - | K14: - | L14: 0.5 | M14: 0.5 | N14: 0.5
B15: Citi México | C15: 0 | D15: 3124.7296 | E15: 3062.5898 | F15: n.a. | G15: 0 | H15: 0 | I15: - | J15: - | K15: - | L15: - | M15: 0.50413614 | N15: 0.50448867
B16: Banco del Bajío | C16: 15970.781 | D16: 12982.565 | E16: 13662.163 | F16: 0 | G16: 0 | H16: 0 | I16: - | J16: - | K16: - | L16: 0.51306786 | M16: 0.47011783 | N16: 0.46651033
B17: Banco Azteca | C17: 4525.4245 | D17: 4756.7319 | E17: 4489.2684 | F17: 0 | G17: 0 | H17: 0 | I17: - | J17: - | K17: - | L17: 0.59507609 | M17: 0.53186023 | N17: 0.80863706
B18: Afirme | C18: 1666.5551 | D18: 1258.4097 | E18: 1686.6584 | F18: 0 | G18: 0 | H18: 0 | I18: - | J18: - | K18: - | L18: 0.24135925 | M18: 0.55688762 | N18: 0.70998872
B19: Monex | C19: 5317.3888 | D19: 4277.1611 | E19: 4231.6095 | F19: 0 | G19: 0 | H19: 0 | I19: - | J19: - | K19: - | L19: 0.50145086 | M19: 0.50153006 | N19: 0.50113689
B20: Banregio | C20: 195.76535 | D20: 140.3283 | E20: 137.75585 | F20: 0 | G20: 0 | H20: 0 | I20: - | J20: - | K20: - | L20: 6.683723 | M20: 4.2295172 | N20: 1.7760263
B21: J.P. Morgan | C21: 0 | D21: 0 | E21: 0 | F21: n.a. | G21: n.a. | H21: n.a. | I21: - | J21: - | K21: - | L21: - | M21: - | N21: -
B22: Invex | C22: 0 | D22: 0 | E22: 0 | F22: n.a. | G22: n.a. | H22: n.a. | I22: - | J22: - | K22: - | L22: - | M22: - | N22: -
B23: Multiva | C23: 29896.624 | D23: 23593.013 | E23: 26647.804 | F23: 0 | G23: 0 | H23: 0 | I23: - | J23: - | K23: - | L23: 0.51278094 | M23: 0.57280274 | N23: 0.55532781
B24: BanCoppel | C24: 0 | D24: 0 | E24: 0 | F24: n.a. | G24: n.a. | H24: n.a. | I24: - | J24: - | K24: - | L24: - | M24: - | N24: -
B25: Banca Mifel | C25: 3420.6885 | D25: 3345.1092 | E25: 3292.0729 | F25: 0 | G25: 0 | H25: 0 | I25: - | J25: - | K25: - | L25: 0.61112682 | M25: 0.61111106 | N25: 0.61111104
B26: Barclays | C26: 0 | D26: 0 | E26: 0 | F26: n.a. | G26: n.a. | H26: n.a. | I26: - | J26: - | K26: - | L26: - | M26: - | N26: -
B27: Banco Base | C27: 0 | D27: 0 | E27: 0 | F27: n.a. | G27: n.a. | H27: n.a. | I27: - | J27: - | K27: - | L27: - | M27: - | N27: -
B28: Sabadell | C28: 1068.9982 | D28: 540.49321 | E28: 534.27721 | F28: 0 | G28: 0 | H28: 0 | I28: - | J28: - | K28: - | L28: 0.50000002 | M28: 0.49999999 | N28: 0.49999999
B29: Bank of America | C29: 0 | D29: 0 | E29: 0 | F29: n.a. | G29: n.a. | H29: n.a. | I29: - | J29: - | K29: - | L29: - | M29: - | N29: -
B30: Ve por Más | C30: 2275.2666 | D30: 1565.2936 | E30: 2205.563 | F30: 0 | G30: 0 | H30: 0 | I30: - | J30: - | K30: - | L30: 0.5 | M30: 0.48669133 | N30: 0.4913195
B31: Actinver | C31: 0 | D31: 0 | E31: 0 | F31: n.a. | G31: n.a. | H31: n.a. | I31: - | J31: - | K31: - | L31: - | M31: - | N31: -
B32: Bansí | C32: 3354.4822 | D32: 9098.8192 | E32: 8761.9815 | F32: 1.2168801 | G32: 0.27260771 | H32: 0.2435542 | I32: 453.32623 | J32: 780.45989 | K32: 856.88788 | L32: 5.5164369 | M32: 2.1275939 | N32: 2.0869864
B33: Compartamos | C33: 0 | D33: 0 | E33: 0 | F33: n.a. | G33: n.a. | H33: n.a. | I33: - | J33: - | K33: - | L33: - | M33: - | N33: -
B34: BIAfirme | C34: 0 | D34: 0 | E34: 0 | F34: n.a. | G34: n.a. | H34: n.a. | I34: - | J34: - | K34: - | L34: - | M34: - | N34: -
B35: Bancrea | C35: 1417.182 | D35: 2077.0415 | E35: 2129.898 | F35: 0 | G35: 0 | H35: 0 | I35: - | J35: - | K35: - | L35: 0.46127145 | M35: 0.46919114 | N35: 0.46409426
B36: Kapital Bank | C36: 0 | D36: 0 | E36: 475.42949 | F36: n.a. | G36: n.a. | H36: 0 | I36: - | J36: - | K36: - | L36: - | M36: - | N36: 0.50200672
B37: MUFG Bank | C37: 3374.0494 | D37: 0 | E37: 0 | F37: 0 | G37: n.a. | H37: n.a. | I37: - | J37: - | K37: - | L37: 0.58580452 | M37: - | N37: -
B38: Consubanco | C38: 0 | D38: 0 | E38: 0 | F38: n.a. | G38: n.a. | H38: n.a. | I38: - | J38: - | K38: - | L38: - | M38: - | N38: -
B39: Bankaool | C39: 0 | D39: 0 | E39: 0 | F39: n.a. | G39: n.a. | H39: n.a. | I39: - | J39: - | K39: - | L39: - | M39: - | N39: -
B40: BNP Paribas México | C40: 0 | D40: 0 | E40: 0 | F40: n.a. | G40: n.a. | H40: n.a. | I40: - | J40: - | K40: - | L40: - | M40: - | N40: -
B41: Inmobiliario Mexicano | C41: 0 | D41: 0 | E41: 0 | F41: n.a. | G41: n.a. | H41: n.a. | I41: - | J41: - | K41: - | L41: - | M41: - | N41: -
B42: Mizuho Bank | C42: 3138.4448 | D42: 3550.2612 | E42: 3533.0092 | F42: 0 | G42: 0 | H42: 0 | I42: - | J42: - | K42: - | L42: 0.5 | M42: 0.5 | N42: 0.5
B43: ICBC | C43: 989.78066 | D43: 1402.1065 | E43: 1375.6621 | F43: 0 | G43: 0 | H43: 0 | I43: - | J43: - | K43: - | L43: 0.49999997 | M43: 0.49999997 | N43: 0.49999998
B44: Openbank | C44: 0 | D44: 0 | E44: 0 | F44: n.a. | G44: n.a. | H44: n.a. | I44: - | J44: - | K44: - | L44: - | M44: - | N44: -
B45: Banco Covalto | C45: 0 | D45: 0 | E45: 0 | F45: n.a. | G45: n.a. | H45: n.a. | I45: - | J45: - | K45: - | L45: - | M45: - | N45: -
B46: Volkswagen Bank | C46: 0 | D46: 0 | E46: 0 | F46: n.a. | G46: n.a. | H46: n.a. | I46: - | J46: - | K46: - | L46: - | M46: - | N46: -
B47: Banco S3 | C47: 0 | D47: 0 | E47: 0 | F47: n.a. | G47: n.a. | H47: n.a. | I47: - | J47: - | K47: - | L47: - | M47: - | N47: -
B48: Bank of China | C48: 1800.4891 | D48: 335.90335 | E48: 329.57726 | F48: 0 | G48: 0 | H48: 0 | I48: - | J48: - | K48: - | L48: 0.53366816 | M48: 0.5 | N48: 0.5
B49: Shinhan | C49: 0 | D49: 0 | E49: 0 | F49: n.a. | G49: n.a. | H49: n.a. | I49: - | J49: - | K49: - | L49: - | M49: - | N49: -
B50: Banco Ualá | C50: 0 | D50: 0 | E50: 0 | F50: n.a. | G50: n.a. | H50: n.a. | I50: - | J50: - | K50: - | L50: - | M50: - | N50: -
B51: KEB Hana México | C51: 0 | D51: 0 | E51: 0 | F51: n.a. | G51: n.a. | H51: n.a. | I51: - | J51: - | K51: - | L51: - | M51: - | N51: -
B52: Banco Bineo | C52: 0 | D52: 0 | E52: 0 | F52: n.a. | G52: n.a. | H52: n.a. | I52: - | J52: - | K52: - | L52: - | M52: - | N52: -
B53: Dondé Banco | C53: 0 | D53: 0 | E53: 0 | F53: n.a. | G53: n.a. | H53: n.a. | I53: - | J53: - | K53: - | L53: - | M53: - | N53: -
B54: Credit Suisse | C54: 0 | D54: 0 | E54: 0 | F54: n.a. | G54: n.a. | H54: n.a. | I54: - | J54: - | K54: - | L54: - | M54: - | N54: -
B55: Hey Banco | C55: 0 | D55: 0 | E55: 0 | F55: n.a. | G55: n.a. | H55: n.a. | I55: - | J55: - | K55: - | L55: - | M55: - | N55: -
B56: Forjadores | C56: 0 | D56: 0 | E56: 0 | F56: n.a. | G56: n.a. | H56: n.a. | I56: - | J56: - | K56: - | L56: - | M56: - | N56: -
B57: Pagatodo | C57: 0 | D57: 0 | E57: 0 | F57: n.a. | G57: n.a. | H57: n.a. | I57: - | J57: - | K57: - | L57: - | M57: - | N57: -
B58: CIBanco | C58: 0 | D58: 0 | E58: 0 | F58: n.a. | G58: n.a. | H58: n.a. | I58: - | J58: - | K58: - | L58: - | M58: - | N58: -
B59: Intercam Banco | C59: 1857.8861 | D59: 477.34243 | E59: n.d. | F59: 0 | G59: 0 | H59: n.d. | I59: - | J59: - | K59: - | L59: 0.49999496 | M59: 0.49999494 | N59: n.d.
B61: n.d. No disponible
B62: n.a. No aplica

Sheet CCG EyM
B2: Cartera de crédito a estados y municipios
B3: Millones de pesos y porcentajes
C5: Cartera total (MDP) 1/ | G5: IMOR (%) 5/
C6: 45536 | D6: 45870 | E6: 45901 | F6: =C6 -> 45536 | G6: =D6 -> 45870 | H6: =E6 -> 45901
B7: Sistema */ | C7: 274332.24 | D7: 282324.61 | E7: 287268.04 | F7: 0.015731212 | G7: 0.0087856609 | H7: 0.0074286627
B8: BBVA México | C8: 88457.675 | D8: 95922.575 | E8: 95580.43 | F8: 0 | G8: 0 | H8: 0
B9: Santander | C9: 47796.036 | D9: 47054.334 | E9: 46848.84 | F9: 0 | G9: 0 | H9: 0
B10: Banorte | C10: 80013.262 | D10: 76729.893 | E10: 80927.903 | F10: 0.0029192164 | G10: 0 | H10: 0
B11: Banamex | C11: 27148.365 | D11: 29540.339 | E11: 31782.734 | F11: 0 | G11: 0 | H11: 0
B12: HSBC | C12: 5945.0964 | D12: 4948.0634 | E12: 4106.4003 | F12: 0 | G12: 0 | H12: 0
B13: Scotiabank | C13: 1563.4496 | D13: 501.161 | E13: 648.59704 | F13: 0 | G13: 0 | H13: 0
B14: Inbursa | C14: 0 | D14: 0 | E14: 0 | F14: n.a. | G14: n.a. | H14: n.a.
B15: Citi México | C15: 0 | D15: 0 | E15: 0 | F15: n.a. | G15: n.a. | H15: n.a.
B16: Banco del Bajío | C16: 7401.2082 | D16: 6497.3103 | E16: 6447.4347 | F16: 0 | G16: 0 | H16: 0
B17: Banco Azteca | C17: 3160.7275 | D17: 3422.1123 | E17: 3174.749 | F17: 0 | G17: 0 | H17: 0
B18: Afirme | C18: 520.85116 | D18: 888.85103 | E18: 1316.2502 | F18: 0 | G18: 0 | H18: 0
B19: Monex | C19: 0 | D19: 0 | E19: 0 | F19: n.a. | G19: n.a. | H19: n.a.
B20: Banregio | C20: 195.76535 | D20: 140.3283 | E20: 137.75585 | F20: 0 | G20: 0 | H20: 0
B21: J.P. Morgan | C21: 0 | D21: 0 | E21: 0 | F21: n.a. | G21: n.a. | H21: n.a.
B22: Invex | C22: 0 | D22: 0 | E22: 0 | F22: n.a. | G22: n.a. | H22: n.a.
B23: Multiva | C23: 8071.8557 | D23: 10094.209 | E23: 9649.1 | F23: 0 | G23: 0 | H23: 0
B24: BanCoppel | C24: 0 | D24: 0 | E24: 0 | F24: n.a. | G24: n.a. | H24: n.a.
B25: Banca Mifel | C25: 1.867321 | D25: 0 | E25: 0 | F25: 0 | G25: n.a. | H25: n.a.
B26: Barclays | C26: 0 | D26: 0 | E26: 0 | F26: n.a. | G26: n.a. | H26: n.a.
B27: Banco Base | C27: 0 | D27: 0 | E27: 0 | F27: n.a. | G27: n.a. | H27: n.a.
B28: Sabadell | C28: 0 | D28: 0 | E28: 0 | F28: n.a. | G28: n.a. | H28: n.a.
B29: Bank of America | C29: 0 | D29: 0 | E29: 0 | F29: n.a. | G29: n.a. | H29: n.a.
B30: Ve por Más | C30: 0 | D30: 0 | E30: 0 | F30: n.a. | G30: n.a. | H30: n.a.
B31: Actinver | C31: 0 | D31: 0 | E31: 0 | F31: n.a. | G31: n.a. | H31: n.a.
B32: Bansí | C32: 3220.0168 | D32: 5260.0618 | E32: 5147.7687 | F32: 1.2676961 | G32: 0.47155498 | H32: 0.41455192
B33: Compartamos | C33: 0 | D33: 0 | E33: 0 | F33: n.a. | G33: n.a. | H33: n.a.
B34: BIAfirme | C34: 0 | D34: 0 | E34: 0 | F34: n.a. | G34: n.a. | H34: n.a.
B35: Bancrea | C35: 836.0632 | D35: 1325.3736 | E35: 1500.0792 | F35: 0 | G35: 0 | H35: 0
B36: Kapital Bank | C36: 0 | D36: 0 | E36: 0 | F36: n.a. | G36: n.a. | H36: n.a.
B37: MUFG Bank | C37: 0 | D37: 0 | E37: 0 | F37: n.a. | G37: n.a. | H37: n.a.
B38: Consubanco | C38: 0 | D38: 0 | E38: 0 | F38: n.a. | G38: n.a. | H38: n.a.
B39: Bankaool | C39: 0 | D39: 0 | E39: 0 | F39: n.a. | G39: n.a. | H39: n.a.
B40: BNP Paribas México | C40: 0 | D40: 0 | E40: 0 | F40: n.a. | G40: n.a. | H40: n.a.
B41: Inmobiliario Mexicano | C41: 0 | D41: 0 | E41: 0 | F41: n.a. | G41: n.a. | H41: n.a.
B42: Mizuho Bank | C42: 0 | D42: 0 | E42: 0 | F42: n.a. | G42: n.a. | H42: n.a.
B43: ICBC | C43: 0 | D43: 0 | E43: 0 | F43: n.a. | G43: n.a. | H43: n.a.
B44: Openbank | C44: 0 | D44: 0 | E44: 0 | F44: n.a. | G44: n.a. | H44: n.a.
B45: Banco Covalto | C45: 0 | D45: 0 | E45: 0 | F45: n.a. | G45: n.a. | H45: n.a.
B46: Volkswagen Bank | C46: 0 | D46: 0 | E46: 0 | F46: n.a. | G46: n.a. | H46: n.a.
B47: Banco S3 | C47: 0 | D47: 0 | E47: 0 | F47: n.a. | G47: n.a. | H47: n.a.
... B59: Intercam Banco | C59: 0 | D59: 0 | E59: 0 | F59: n.a. | G59: n.a. | H59: n.a.
B61: n.a. No aplica

Sheet CCG OG
B2: Cartera de crédito a otras entidades gubernamentales
B3: Millones de pesos y porcentajes
C5: Cartera total (MDP) 1/ | G5: IMOR (%) 5/
C6: 45536 | D6: 45870 | E6: 45901 | F6: =C6 -> 45536 | G6: =D6 -> 45870 | H6: =E6 -> 45901
B7: Sistema */ | C7: 308069.67 | D7: 232336.15 | E7: 230913.1 | F7: 2.8399946e-07 | G7: 4.3729743e-09 | H7: 4.3999236e-09
B8: BBVA México | C8: 99178.752 | D8: 90625.664 | E8: 88760.519 | F8: 8.719168e-07 | G8: 0 | H8: 0
B9: Santander | C9: 16277.202 | D9: 19660.291 | E9: 20413.127 | F9: 0 | G9: 0 | H9: 0
B10: Banorte | C10: 56811.85 | D10: 43469.338 | E10: 42536.695 | F10: 0 | G10: 0 | H10: 0
B11: Banamex | C11: 14206.405 | D11: 368.16427 | E11: 362.90759 | F11: 0 | G11: 0 | H11: 0
B12: HSBC | C12: 12262.182 | D12: 6426.6783 | E12: 6275.231 | F12: 8.2856382e-08 | G12: 1.58091e-07 | H12: 1.6190639e-07
B13: Scotiabank | C13: 21822.092 | D13: 4894.5801 | E13: 4780.7957 | F13: 0 | G13: 0 | H13: 0
B14: Inbursa | C14: 30649.737 | D14: 21994.368 | E14: 18601.646 | F14: 0 | G14: 0 | H14: 0
B15: Citi México | C15: 0 | D15: 3124.7296 | E15: 3062.5898 | F15: n. a. | G15: 0 | H15: 0
B16: Banco del Bajío | C16: 8569.5732 | D16: 6485.2551 | E16: 7214.7281 | F16: 0 | G16: 0 | H16: 0
B17: Banco Azteca | C17: 1364.697 | D17: 1334.6195 | E17: 1314.5195 | F17: 0 | G17: 0 | H17: 0
B18: Afirme | C18: 1145.704 | D18: 369.5587 | E18: 370.40811 | F18: 0 | G18: 0 | H18: 0
B19: Monex | C19: 5317.3888 | D19: 4277.1611 | E19: 4231.6095 | F19: 0 | G19: 0 | H19: 0
B20: Banregio | C20: 0 | D20: 0 | E20: 0 | F20: n. a. | G20: n. a. | H20: n. a.
B21: J.P. Morgan | C21: 0 | D21: 0 | E21: 0 | F21: n. a. | G21: n. a. | H21: n. a.
B22: Invex | C22: 0 | D22: 0 | E22: 0 | F22: n. a. | G22: n. a. | H22: n. a.
B23: Multiva | C23: 21824.768 | D23: 13498.804 | E23: 16998.704 | F23: 0 | G23: 0 | H23: 0
B24: BanCoppel | C24: 0 | D24: 0 | E24: 0 | F24: n. a. | G24: n. a. | H24: n. a.
B25: Banca Mifel | C25: 3418.8212 | D25: 3345.1092 | E25: 3292.0729 | F25: 0 | G25: 0 | H25: 0
B26: Barclays | C26: 0 | D26: 0 | E26: 0 | F26: n. a. | G26: n. a. | H26: n. a.
B27: Banco Base | C27: 0 | D27: 0 | E27: 0 | F27: n. a. | G27: n. a. | H27: n. a.
B28: Sabadell | C28: 1068.9982 | D28: 540.49321 | E28: 534.27721 | F28: 0 | G28: 0 | H28: 0
B29: Bank of America | C29: 0 | D29: 0 | E29: 0 | F29: n. a. | G29: n. a. | H29: n. a.
B30: Ve por Más | C30: 2275.2666 | D30: 1565.2936 | E30: 2205.563 | F30: 0 | G30: 0 | H30: 0
B31: Actinver | C31: 0 | D31: 0 | E31: 0 | F31: n. a. | G31: n. a. | H31: n. a.
B32: Bansí | C32: 134.46537 | D32: 3838.7575 | E32: 3614.2129 | F32: 0 | G32: 0 | H32: 0
B33: Compartamos | C33: 0 | D33: 0 | E33: 0 | F33: n. a. | G33: n. a. | H33: n. a.
B34: BIAfirme | C34: 0 | D34: 0 | E34: 0 | F34: n. a. | G34: n. a. | H34: n. a.
B35: Bancrea | C35: 581.1188 | D35: 751.66799 | E35: 629.81883 | F35: 0 | G35: 0 | H35: 0
B36: Kapital Bank | C36: 0 | D36: 0 | E36: 475.42949 | F36: n. a. | G36: n. a. | H36: 0
B37: MUFG Bank | C37: 3374.0494 | D37: 0 | E37: 0 | F37: 0 | G37: n. a. | H37: n. a.
B38: Consubanco | C38: 0 | D38: 0 | E38: 0 | F38: n. a. | G38: n. a. | H38: n. a.
B39: Bankaool | C39: 0 | D39: 0 | E39: 0 | F39: n. a. | G39: n. a. | H39: n. a.
B40: BNP Paribas México | C40: 0 | D40: 0 | E40: 0 | F40: n. a. | G40: n. a. | H40: n. a.
B41: Inmobiliario Mexicano | C41: 0 | D41: 0 | E41: 0 | F41: n. a. | G41: n. a. | H41: n. a.
B42: Mizuho Bank | C42: 3138.4448 | D42: 3550.2612 | E42: 3533.0092 | F42: 0 | G42: 0 | H42: 0
B43: ICBC | C43: 989.78066 | D43: 1402.1065 | E43: 1375.6621 | F43: 0 | G43: 0 | H43: 0
B44: Openbank | C44: 0 | D44: 0 | E44: 0 | F44: n. a. | G44: n. a. | H44: n. a.
B45: Banco Covalto | C45: 0 | D45: 0 | E45: 0 | F45: n. a. | G45: n. a. | H45: n. a.
B46: Volkswagen Bank | C46: 0 | D46: 0 | E46: 0 | F46: n. a. | G46: n. a. | H46: n. a.
B47: Banco S3 | C47: 0 | D47: 0 | E47: 0 | F47: n. a. | G47: n. a. | H47: n. a.
B48: Bank of China | C48: 1800.4891 | D48: 335.90335 | E48: 329.57726 | F48: 0 | G48: 0 | H48: 0
B49: Shinhan | C49: 0 | D49: 0 | E49: 0 | F49: n. a. | G49: n. a. | H49: n. a.
B50: Banco Ualá | C50: 0 | D50: 0 | E50: 0 | F50: n. a. | G50: n. a. | H50: n. a.
B51: KEB Hana México | C51: 0 | D51: 0 | E51: 0 | F51: n. a. | G51: n. a. | H51: n. a.
B52: Banco Bineo | C52: 0 | D52: 0 | E52: 0 | F52: n. a. | G52: n. a. | H52: n. a.
B53: Dondé Banco | C53: 0 | D53: 0 | E53: 0 | F53: n. a. | G53: n. a. | H53: n. a.
B54: Credit Suisse | C54: 0 | D54: 0 | E54: 0 | F54: n. a. | G54: n. a. | H54: n. a.
B55: Hey Banco | C55: 0 | D55: 0 | E55: 0 | F55: n. a. | G55: n. a. | H55: n. a.
B56: Forjadores | C56: 0 | D56: 0 | E56: 0 | F56: n. a. | G56: n. a. | H56: n. a.
B57: Pagatodo | C57: 0 | D57: 0 | E57: 0 | F57: n. a. | G57: n. a. | H57: n. a.
B58: CIBanco | C58: 0 | D58: 0 | E58: 0 | F58: n. a. | G58: n. a. | H58: n. a.
B59: Intercam Banco | C59: 1857.8861 | D59: 477.34243 | E59: n.d. | F59: 0 | G59: 0 | H59: n.d.
B61: n.d. No disponible
B62: n.a. No aplica

Sheet CCCT
B2: Cartera de crédito al consumo
B3: Millones de pesos y porcentajes
C5: Cartera total (MDP) 1/ | F5: IMOR (%) 5/ | I5: ICOR (%) 6/ | L5: Pérdida esperada (%) 7/
C6: 45536 | D6: 45870 | E6: 45901 | F6: =C6 -> 45536 | G6: =D6 -> 45870 | H6: =E6 -> 45901 | I6: =C6 -> 45536 | J6: =D6 -> 45870 | K6: =E6 -> 45901 | L6: =C6 -> 45536 | M6: =D6 -> 45870 | N6: =E6 -> 45901
B7: Sistema */ | C7: 1618451.5 | D7: 1822653.3 | E7: 1838223.2 | F7: 3.0716375 | G7: 2.9869845 | H7: 3.0556078 | I7: 261.68177 | J7: 267.6479 | K7: 264.27357 | L7: 8.0379155 | M7: 7.9946014 | N7: 8.0751639
B8: BBVA México | C8: 480561.98 | D8: 541506.77 | E8: 549421.99 | F8: 2.819947 | G8: 2.6941315 | H8: 2.7839411 | I8: 280.65808 | J8: 298.18759 | K8: 291.6419 | L8: 7.9144091 | M8: 8.0335659 | N8: 8.1191387
B9: Santander | C9: 196208.82 | D9: 212286.11 | E9: 212045.47 | F9: 3.2973421 | G9: 2.8271694 | H9: 2.8015974 | I9: 252.96531 | J9: 274.81993 | K9: 280.28732 | L9: 8.3411317 | M9: 7.769625 | N9: 7.8525223
B10: Banorte | C10: 195971.38 | D10: 225836.76 | E10: 229954.73 | F10: 2.1729411 | G10: 2.0258503 | H10: 2.0443138 | I10: 288.76534 | J10: 300.47461 | K10: 297.22285 | L10: 6.2747008 | M10: 6.087166 | N10: 6.0761676
B11: Banamex | C11: 215811.25 | D11: 248744.95 | E11: 251357.64 | F11: 3.013685 | G11: 3.3091709 | H11: 3.3150238 | I11: 272.26703 | J11: 250.76127 | K11: 253.78648 | L11: 8.2052708 | M11: 8.2981191 | N11: 8.4130822
B12: HSBC | C12: 106311.82 | D12: 99132.472 | E12: 97179.158 | F12: 2.832504 | G12: 3.1700013 | H12: 3.2815309 | I12: 351.13083 | J12: 333.48215 | K12: 324.89496 | L12: 9.9457947 | M12: 10.571389 | N12: 10.661529
B13: Scotiabank | C13: 45657.785 | D13: 55377.447 | E13: 56073.571 | F13: 2.3710868 | G13: 2.7042194 | H13: 2.653414 | I13: 280.33544 | J13: 257.66245 | K13: 262.94513 | L13: 6.6469965 | M13: 6.9677579 | N13: 6.9770229
B14: Inbursa | C14: 83469.047 | D14: 95775.572 | E14: 96438.414 | F14: 1.4178059 | G14: 1.6220663 | H14: 1.7231696 | I14: 297.95983 | J14: 266.81961 | K14: 256.37618 | L14: 4.2244921 | M14: 4.3279909 | N14: 4.4177962
B15: Citi México | C15: 0 | D15: 0 | E15: 0 | F15: n.a. | G15: n.a. | H15: n.a. | I15: - | J15: - | K15: - | L15: - | M15: - | N15: -
B16: Banco del Bajío | C16: 6725.1464 | D16: 7559.2715 | E16: 7603.6581 | F16: 2.382058 | G16: 2.3746221 | H16: 2.5428242 | I16: 382.67097 | J16: 367.48919 | K16: 347.78569 | L16: 9.1154444 | M16: 8.7264795 | N16: 8.8435786
B17: Banco Azteca | C17: 121655.7 | D17: 140020.54 | E17: 141990.02 | F17: 4.8464433 | G17: 5.4400519 | H17: 5.8272077 | I17: 216.71846 | J17: 209.15742 | K17: 198.11109 | L17: 10.503137 | M17: 11.378272 | N17: 11.544345
B18: Afirme | C18: 12150.6 | D18: 13324.26 | E18: 13422.302 | F18: 2.7220897 | G18: 2.6214628 | H18: 2.6970969 | I18: 280.34474 | J18: 296.60493 | K18: 287.63599 | L18: 7.6312353 | M18: 7.7753878 | N18: 7.7578215
B19: Monex | C19: 0 | D19: 0 | E19: 0 | F19: n.a. | G19: n.a. | H19: n.a. | I19: - | J19: - | K19: - | L19: - | M19: - | N19: -
B20: Banregio | C20: 12237.093 | D20: 13480.463 | E20: 13571.788 | F20: 1.8570435 | G20: 2.2083474 | H20: 2.1882618 | I20: 421.47239 | J20: 362.81425 | K20: 355.30352 | L20: 7.8269255 | M20: 8.0121992 | N20: 7.7749711
B21: J.P. Morgan | C21: 0 | D21: 0 | E21: 0 | F21: n.a. | G21: n.a. | H21: n.a. | I21: - | J21: - | K21: - | L21: - | M21: - | N21: -
B22: Invex | C22: 26219.76 | D22: 33080.122 | E22: 33743.568 | F22: 2.1530933 | G22: 2.6903856 | H22: 2.5233592 | I22: 330.21964 | J22: 275.80715 | K22: 295.15974 | L22: 7.1099369 | M22: 7.4202757 | N22: 7.4479403
B23: Multiva | C23: 5254.4659 | D23: 6416.8215 | E23: 6641.4572 | F23: 1.9781498 | G23: 1.2338864 | H23: 1.1864147 | I23: 187.48471 | J23: 255.464 | K23: 258.27876 | L23: 3.7087286 | M23: 3.1521356 | N23: 3.0642572
B24: BanCoppel | C24: 22827.775 | D24: 31042.911 | E24: 30870.397 | F24: 16.248142 | G24: 7.8862728 | H24: 7.9357135 | I24: 148.85982 | J24: 194.79657 | K24: 195.89663 | L24: 24.186955 | M24: 15.362189 | N24: 15.545796
B25: Banca Mifel | C25: 301.55909 | D25: 432.43564 | E25: 440.51065 | F25: 6.7130396 | G25: 5.8188749 | H25: 5.9547829 | I25: 287.73799 | J25: 329.44362 | K25: 327.73088 | L25: 19.315965 | M25: 19.169912 | N25: 19.515663
B26: Barclays | C26: 0 | D26: 0 | E26: 0 | F26: n.a. | G26: n.a. | H26: n.a. | I26: - | J26: - | K26: - | L26: - | M26: - | N26: -
B27: Banco Base | C27: 0 | D27: 0 | E27: 0 | F27: n.a. | G27: n.a. | H27: n.a. | I27: - | J27: - | K27: - | L27: - | M27: - | N27: -
B28: Sabadell | C28: 14.055723 | D28: 10.144499 | E28: 10.757736 | F28: 8.442867 | G28: 1.532259 | H28: 1.4449137 | I28: 187.15099 | J28: 691.1001 | K28: 699.96011 | L28: 15.800909 | M28: 10.589444 | N28: 10.113819
B29: Bank of America | C29: 0 | D29: 0 | E29: 0 | F29: n.a. | G29: n.a. | H29: n.a. | I29: - | J29: - | K29: - | L29: - | M29: - | N29: -
B30: Ve por Más | C30: 146.6739 | D30: 157.21551 | E30: 157.83827 | F30: 0.19197349 | G30: 1.2495002 | H30: 1.2175342 | I30: 2003.2595 | J30: 345.45471 | K30: 302.39638 | L30: 3.8457273 | M30: 4.3164572 | N30: 3.6817794
B31: Actinver | C31: 3395.5129 | D31: 3646.6493 | E31: 3576.6554 | F31: 6.8516401 | G31: 6.0540435 | H31: 5.9872792 | I31: 150.42638 | J31: 167.33983 | K31: 170.16077 | L31: 10.306674 | M31: 10.130826 | N31: 10.188001
B32: Bansí | C32: 613.67998 | D32: 866.55585 | E32: 870.31213 | F32: 0.0079588714 | G32: 4.8348262 | H32: 4.797801 | I32: 59468.91 | J32: 160.29972 | K32: 167.92883 | L32: 4.7330541 | M32: 7.7502128 | N32: 8.0568912
B33: Compartamos | C33: 48565.199 | D33: 59110.491 | E33: 58108.319 | F33: 3.3606933 | G33: 3.2626805 | H33: 3.5065949 | I33: 234.63479 | J33: 236.79986 | K33: 236.53732 | L33: 7.8853555 | M33: 7.7260229 | N33: 8.2944055
B34: BIAfirme | C34: 0 | D34: 0 | E34: 0 | F34: n.a. | G34: n.a. | H34: n.a. | I34: - | J34: - | K34: - | L34: - | M34: - | N34: -
B35: Bancrea | C35: 1936.0677 | D35: 2384.69 | E35: 2432.2741 | F35: 1.4454581 | G35: 1.6293416 | H35: 1.5799636 | I35: 156.84055 | J35: 150.54595 | K35: 153.88228 | L35: 2.2670643 | M35: 2.4529077 | N35: 2.431284
B36: Kapital Bank | C36: 703.30292 | D36: 559.64683 | E36: 937.71897 | F36: 1.3207428 | G36: 2.7261695 | H36: 2.5992861 | I36: 378.87447 | J36: 224.31894 | K36: 235.45772 | L36: 5.0039573 | M36: 6.1153147 | N36: 6.1202199
B37: MUFG Bank | C37: 0 | D37: 0 | E37: 0 | F37: n.a. | G37: n.a. | H37: n.a. | I37: - | J37: - | K37: - | L37: - | M37: - | N37: -
B38: Consubanco | C38: 17774.801 | D38: 22082.053 | E38: 22517.763 | F38: 2.253506 | G38: 2.1519428 | H38: 2.0744573 | I38: 195.32801 | J38: 203.41336 | K38: 207.17188 | L38: 4.4017283 | M38: 4.3773391 | N38: 4.2976922
B39: Bankaool | C39: 13.854782 | D39: 24.838977 | E39: 35.567714 | F39: 10.875934 | G39: 4.4296873 | H39: 3.057506 | I39: 99.491385 | J39: 153.86894 | K39: 140.8721 | L39: 10.820618 | M39: 6.8159127 | N39: 4.3071731
B40: BNP Paribas México | C40: 0 | D40: 0 | E40: 0 | F40: n.a. | G40: n.a. | H40: n.a. | I40: - | J40: - | K40: - | L40: - | M40: - | N40: -
B41: Inmobiliario Mexicano | C41: 0 | D41: 0 | E41: 0 | F41: n.a. | G41: n.a. | H41: n.a. | I41: - | J41: - | K41: - | L41: - | M41: - | N41: -
B42: Mizuho Bank | C42: 0 | D42: 0 | E42: 0 | F42: n.a. | G42: n.a. | H42: n.a. | I42: - | J42: - | K42: - | L42: - | M42: - | N42: -
B43: ICBC | C43: 0 | D43: 0 | E43: 0 | F43: n.a. | G43: n.a. | H43: n.a. | I43: - | J43: - | K43: - | L43: - | M43: - | N43: -
B44: Openbank | C44: 0 | D44: 181.24835 | E44: 227.56701 | F44: n.a. | G44: 2.3362166 | H44: 4.4823286 | I44: - | J44: 749.53558 | K44: 465.47878 | L44: - | M44: 17.510775 | N44: 20.864288
B45: Banco Covalto | C45: 0 | D45: 0 | E45: 0 | F45: n.a. | G45: n.a. | H45: n.a. | I45: - | J45: - | K45: - | L45: - | M45: - | N45: -
B46: Volkswagen Bank | C46: 5196.7482 | D46: 7404.2091 | E46: 7533.6041 | F46: 1.0802438 | G46: 1.1170978 | H46: 1.1617912 | I46: 251.20797 | J46: 249.91953 | K46: 197.17179 | L46: 2.7136586 | M46: 2.7918457 | N46: 2.2907245
B47: Banco S3 | C47: 0 | D47: 0 | E47: 0 | F47: n.a. | G47: n.a. | H47: n.a. | I47: - | J47: - | K47: - | L47: - | M47: - | N47: -
B48: Bank of China | C48: 0 | D48: 0 | E48: 0 | F48: n.a. | G48: n.a. | H48: n.a. | I48: - | J48: - | K48: - | L48: - | M48: - | N48: -
B49: Shinhan | C49: 0 | D49: 0 | E49: 0 | F49: n.a. | G49: n.a. | H49: n.a. | I49: - | J49: - | K49: - | L49: - | M49: - | N49: -
B50: Banco Ualá | C50: 254.7166 | D50: 563.71402 | E50: 614.56735 | F50: 18.058336 | G50: 10.098672 | H50: 10.036517 | I50: 175.81905 | J50: 232.49745 | K50: 242.94781 | L50: 31.749994 | M50: 23.479155 | N50: 24.383497
B51: KEB Hana México | C51: 0 | D51: 0 | E51: 0 | F51: n.a. | G51: n.a. | H51: n.a. | I51: - | J51: - | K51: - | L51: - | M51: - | N51: -
B52: Banco Bineo | C52: 45.981923 | D52: 9.8025796 | E52: 6.5318605 | F52: 5.521153 | G52: 42.710186 | H52: 37.733611 | I52: 293.77194 | J52: 94.337196 | K52: 95.978757 | L52: 16.219598 | M52: 40.291592 | N52: 36.21625
B53: Dondé Banco | C53: 0 | D53: 0 | E53: 0 | F53: n.a. | G53: n.a. | H53: n.a. | I53: - | J53: - | K53: - | L53: - | M53: - | N53: -
B54: Credit Suisse | C54: 0 | D54: 0 | E54: 0 | F54: n.a. | G54: n.a. | H54: n.a. | I54: - | J54: - | K54: - | L54: - | M54: - | N54: -
B55: Hey Banco | C55: 0 | D55: 0 | E55: 0 | F55: n.a. | G55: n.a. | H55: n.a. | I55: - | J55: - | K55: - | L55: - | M55: - | N55: -
B56: Forjadores | C56: 490.47068 | D56: 404.2503 | E56: 438.99178 | F56: 7.0316193 | G56: 8.4306326 | H56: 7.2775887 | I56: 136.06036 | J56: 126.12129 | K56: 146.86279 | L56: 9.5672467 | M56: 10.632823 | N56: 10.68807
B57: Pagatodo | C57: 0 | D57: 0 | E57: 0 | F57: n.a. | G57: n.a. | H57: n.a. | I57: - | J57: - | K57: - | L57: - | M57: - | N57: -
B58: CIBanco | C58: 7528.6969 | D58: 762.24429 | E58: 0 | F58: 2.5202025 | G58: 5.9730368 | H58: n.a. | I58: 137.42046 | J58: 173.2126 | K58: - | L58: 3.4632739 | M58: 10.346052 | N58: -
B59: Intercam Banco | C59: 407.5295 | D59: 468.62083 | E59: n.d. | F59: 0.26492585 | G59: 1.3193005 | H59: n.d. | I59: 1661.9138 | J59: 1000.5674 | K59: n.d. | L59: 4.4028393 | M59: 13.20049 | N59: n.d.
B61: n.d. No disponible
B62: n.a. No aplica

Sheet CCCTC
B2: Cartera de crédito al consumo
B3: Millones de pesos y porcentajes
C5: Tarjeta de crédito (MDP) 1/ | F5: IMOR (%) 5/ | I5: ICOR (%) 6/ | L5: Pérdida esperada (%) 7/
C6: 45536 | D6: 45870 | E6: 45901 | F6: =C6 -> 45536 | G6: =D6 -> 45870 | H6: =E6 -> 45901 | I6: =C6 -> 45536 | J6: =D6 -> 45870 | K6: =E6 -> 45901 | L6: =C6 -> 45536 | M6: =D6 -> 45870 | N6: =E6 -> 45901
B7: Sistema */ | C7: 600391.98 | D7: 666604.23 | E7: 669663.99 | F7: 3.4715588 | G7: 3.2312751 | H7: 3.2488569 | I7: 304.13338 | J7: 326.84425 | K7: 328.10893 | L7: 10.558169 | M7: 10.561237 | N7: 10.65979
B8: BBVA México | C8: 192508.05 | D8: 217244.66 | E8: 219009.03 | F8: 3.0933255 | G8: 2.6449774 | H8: 2.8446461 | I8: 306.87601 | J8: 376.43989 | K8: 354.61077 | L8: 9.4926739 | M8: 9.9567499 | N8: 10.087422
B9: Santander | C9: 82480.715 | D9: 82812.449 | E9: 81423.004 | F9: 4.0559331 | G9: 3.7593093 | H9: 3.4887348 | I9: 297.61299 | J9: 306.96554 | K9: 332.52339 | L9: 12.070984 | M9: 11.539784 | N9: 11.600859
B10: Banorte | C10: 61539.629 | D10: 70458.26 | E10: 71993.822 | F10: 2.810228 | G10: 2.8072347 | H10: 2.8796403 | I10: 335.14912 | J10: 341.57205 | K10: 336.33856 | L10: 9.4184546 | M10: 9.5887292 | N10: 9.6853408
B11: Banamex | C11: 134726.24 | D11: 156264.06 | E11: 157573.81 | F11: 3.0476446 | G11: 3.2361493 | H11: 3.2073743 | I11: 300.35615 | J11: 280.48968 | K11: 288.23954 | L11: 9.1537881 | M11: 9.0770649 | N11: 9.2449207
B12: HSBC | C12: 43386.728 | D12: 42449.457 | E12: 41580.603 | F12: 3.2456969 | G12: 4.1714877 | H12: 4.1710149 | I12: 407.24128 | J12: 343.04595 | K12: 342.91004 | L12: 13.217818 | M12: 14.31012 | N12: 14.302829
B13: Scotiabank | C13: 11722.951 | D13: 13630.179 | E13: 13755.072 | F13: 2.8501015 | G13: 2.6924766 | H13: 2.7327891 | I13: 430.10316 | J13: 467.10596 | K13: 470.64796 | L13: 12.258377 | M13: 12.576719 | N13: 12.861816
B14: Inbursa | C14: 14873.58 | D14: 16697.374 | E14: 16570.872 | F14: 1.2254286 | G14: 1.4417579 | H14: 1.5695842 | I14: 856.65723 | J14: 729.06756 | K14: 685.5022 | L14: 10.497723 | M14: 10.511389 | N14: 10.759534
B15: Citi México | C15: 0 | D15: 0 | E15: 0 | F15: n.a. | G15: n.a. | H15: n.a. | I15: - | J15: - | K15: - | L15: - | M15: - | N15: -
B16: Banco del Bajío | C16: 2712.2737 | D16: 3050.0896 | E16: 3082.0096 | F16: 2.8739863 | G16: 3.1106177 | H16: 2.9772425 | I16: 421.2489 | J16: 363.86373 | K16: 382.40165 | L16: 12.106636 | M16: 11.31841 | N16: 11.385024
B17: Banco Azteca | C17: 7804.9783 | D17: 6580.2363 | E17: 6415.5986 | F17: 8.034132 | G17: 7.3829853 | H17: 7.3805954 | I17: 213.87265 | J17: 285.34312 | K17: 291.18862 | L17: 17.182811 | M17: 21.06684 | N17: 21.491454
B18: Afirme | C18: 1555.3526 | D18: 1769.0786 | E18: 1810.7094 | F18: 3.1255341 | G18: 3.5003377 | H18: 3.2187292 | I18: 497.48577 | J18: 444.18598 | K18: 471.4778 | L18: 15.549088 | M18: 15.548009 | N18: 15.175594
B19: Monex | C19: 0 | D19: 0 | E19: 0 | F19: n.a. | G19: n.a. | H19: n.a. | I19: - | J19: - | K19: - | L19: - | M19: - | N19: -
B20: Banregio | C20: 5906.0298 | D20: 6366.2649 | E20: 6368.2979 | F20: 2.8843688 | G20: 3.4412151 | H20: 3.3685223 | I20: 432.23739 | J20: 383.53928 | K20: 378.02235 | L20: 12.46732 | M20: 13.198411 | N20: 12.733767
B21: J.P. Morgan | C21: 0 | D21: 0 | E21: 0 | F21: n.a. | G21: n.a. | H21: n.a. | I21: - | J21: - | K21: - | L21: - | M21: - | N21: -
B22: Invex | C22: 26028.855 | D22: 32900.523 | E22: 33563.737 | F22: 2.1346398 | G22: 2.705072 | H22: 2.5368791 | I22: 332.65088 | J22: 274.89462 | K22: 294.30965 | L22: 7.1008981 | M22: 7.4360972 | N22: 7.46628
B23: Multiva | C23: 0 | D23: 0 | E23: 0 | F23: n.a. | G23: n.a. | H23: n.a. | I23: - | J23: - | K23: - | L23: - | M23: - | N23: -
B24: BanCoppel | C24: 14623.881 | D24: 15244.317 | E24: 15280.744 | F24: 15.312619 | G24: 9.4060602 | H24: 9.1952679 | I24: 163.83804 | J24: 223.00318 | K24: 228.4269 | L24: 25.087895 | M24: 20.975813 | N24: 21.004465
B25: Banca Mifel | C25: 299.16092 | D25: 430.31971 | E25: 438.25721 | F25: 6.7668535 | G25: 5.8291142 | H25: 5.9673613 | I25: 286.41635 | J25: 329.71596 | K25: 327.96679 | L25: 19.381375 | M25: 19.21952 | N25: 19.570963
B26: Barclays | C26: 0 | D26: 0 | E26: 0 | F26: n.a. | G26: n.a. | H26: n.a. | I26: - | J26: - | K26: - | L26: - | M26: - | N26: -
B27: Banco Base | C27: 0 | D27: 0 | E27: 0 | F27: n.a. | G27: n.a. | H27: n.a. | I27: - | J27: - | K27: - | L27: - | M27: - | N27: -
B28: Sabadell | C28: 0 | D28: 0 | E28: 0 | F28: n.a. | G28: n.a. | H28: n.a. | I28: - | J28: - | K28: - | L28: - | M28: - | N28: -
B29: Bank of America | C29: 0 | D29: 0 | E29: 0 | F29: n.a. | G29: n.a. | H29: n.a. | I29: - | J29: - | K29: - | L29: - | M29: - | N29: -
B30: Ve por Más | C30: 0 | D30: 0 | E30: 0 | F30: n.a. | G30: n.a. | H30: n.a. | I30: - | J30: - | K30: - | L30: - | M30: - | N30: -
B31: Actinver | C31: 0 | D31: 0 | E31: 0 | F31: n.a. | G31: n.a. | H31: n.a. | I31: - | J31: - | K31: - | L31: - | M31: - | N31: -
B32: Bansí | C32: 0 | D32: 0 | E32: 0 | F32: n.a. | G32: n.a. | H32: n.a. | I32: - | J32: - | K32: - | L32: - | M32: - | N32: -
B33: Compartamos | C33: 0 | D33: 0 | E33: 0 | F33: n.a. | G33: n.a. | H33: n.a. | I33: - | J33: - | K33: - | L33: - | M33: - | N33: -
B34: BIAfirme | C34: 0 | D34: 0 | E34: 0 | F34: n.a. | G34: n.a. | H34: n.a. | I34: - | J34: - | K34: - | L34: - | M34: - | N34: -
B35: Bancrea | C35: 0 | D35: 0 | E35: 0 | F35: n.a. | G35: n.a. | H35: n.a. | I35: - | J35: - | K35: - | L35: - | M35: - | N35: -
B36: Kapital Bank | C36: 0 | D36: 0 | E36: 0 | F36: n.a. | G36: n.a. | H36: n.a. | I36: - | J36: - | K36: - | L36: - | M36: - | N36: -
B37: MUFG Bank | C37: 0 | D37: 0 | E37: 0 | F37: n.a. | G37: n.a. | H37: n.a. | I37: - | J37: - | K37: - | L37: - | M37: - | N37: -
... B43: ICBC | C43: 0 | D43: 0 | E43: 0 | F43: n.a. | G43: n.a. | H43: n.a. | I43: - | J43: - | K43: - | L43: - | M43: - | N43: -
B44: Openbank | C44: 0 | D44: 181.24835 | E44: 227.56701 | F44: n.a. | G44: 2.3362166 | H44: 4.4823286 | I44: - | J44: 749.53558 | K44: 465.47878 | L44: - | M44: 17.510775 | N44: 20.864288
B45: Banco Covalto | C45: 0 | D45: 0 | E45: 0 | F45: n.a. | G45: n.a. | H45: n.a. | I45: - | J45: - | K45: - | L45: - | M45: - | N45: -
B46: Volkswagen Bank | C46: 0 | D46: 0 | E46: 0 | F46: n.a. | G46: n.a. | H46: n.a. | I46: - | J46: - | K46: - | L46: - | M46: - | N46: -
B47: Banco S3 | C47: 0 | D47: 0 | E47: 0 | F47: n.a. | G47: n.a. | H47: n.a. | I47: - | J47: - | K47: - | L47: - | M47: - | N47: -
B48: Bank of China | C48: 0 | D48: 0 | E48: 0 | F48: n.a. | G48: n.a. | H48: n.a. | I48: - | J48: - | K48: - | L48: - | M48: - | N48: -
B49: Shinhan | C49: 0 | D49: 0 | E49: 0 | F49: n.a. | G49: n.a. | H49: n.a. | I49: - | J49: - | K49: - | L49: - | M49: - | N49: -
B50: Banco Ualá | C50: 223.4247 | D50: 525.71164 | E50: 570.86217 | F50: 19.510472 | G50: 9.9515985 | H50: 10.036461 | I50: 172.89633 | J50: 239.40984 | K50: 248.99711 | L50: 33.73289 | M50: 23.825106 | N50: 24.990499
B51: KEB Hana México | C51: 0 | D51: 0 | E51: 0 | F51: n.a. | G51: n.a. | H51: n.a. | I51: - | J51: - | K51: - | L51: - | M51: - | N51: -
B52: Banco Bineo | C52: 0.13731874 | D52: 0 | E52: 0 | F52: 0 | G52: n.a. | H52: n.a. | I52: - | J52: - | K52: - | L52: 42.678341 | M52: - | N52: -
B53: Dondé Banco | C53: 0 | D53: 0 | E53: 0 | F53: n.a. | G53: n.a. | H53: n.a. | I53: - | J53: - | K53: - | L53: - | M53: - | N53: -
B54: Credit Suisse | C54: 0 | D54: 0 | E54: 0 | F54: n.a. | G54: n.a. | H54: n.a. | I54: - | J54: - | K54: - | L54: - | M54: - | N54: -
B55: Hey Banco | C55: 0 | D55: 0 | E55: 0 | F55: n.a. | G55: n.a. | H55: n.a. | I55: - | J55: - | K55: - | L55: - | M55: - | N55: -
B56: Forjadores | C56: 0 | D56: 0 | E56: 0 | F56: n.a. | G56: n.a. | H56: n.a. | I56: - | J56: - | K56: - | L56: - | M56: - | N56: -
B57: Pagatodo | C57: 0 | D57: 0 | E57: 0 | F57: n.a. | G57: n.a. | H57: n.a. | I57: - | J57: - | K57: - | L57: - | M57: - | N57: -
B58: CIBanco | C58: 0 | D58: 0 | E58: 0 | F58: n.a. | G58: n.a. | H58: n.a. | I58: - | J58: - | K58: - | L58: - | M58: - | N58: -
B59: Intercam Banco | C59: 0 | D59: 0 | E59: 0 | F59: n.a. | G59: n.a. | H59: n.a. | I59: - | J59: - | K59: - | L59: - | M59: - | N59: -
B61: n.a. No aplica

Sheet CCCN
B2: Cartera de crédito al consumo
B3: Millones de pesos y porcentajes
C5: Cartera de nómina (MDP) 1/ | F5: IMOR (%) 5/ | I5: ICOR (%) 6/ | L5: Pérdida esperada (%) 7/
C6: 45536 | D6: 45870 | E6: 45901 | F6: =C6 -> 45536 | G6: =D6 -> 45870 | H6: =E6 -> 45901 | I6: =C6 -> 45536 | J6: =D6 -> 45870 | K6: =E6 -> 45901 | L6: =C6 -> 45536 | M6: =D6 -> 45870 | N6: =E6 -> 45901
B7: Sistema */ | C7: 398295.59 | D7: 428009.69 | E7: 432566.22 | F7: 2.7437106 | G7: 2.6887651 | H7: 2.7314582 | I7: 262.78311 | J7: 262.84806 | K7: 259.21732 | L7: 7.2100081 | M7: 7.0673669 | N7: 7.0804126
B8: BBVA México | C8: 156191.81 | D8: 171956.42 | E8: 174689.83 | F8: 2.4768547 | G8: 2.540234 | H8: 2.5492915 | I8: 292.8121 | J8: 270.51333 | K8: 269.68273 | L8: 7.2525302 | M8: 6.8716714 | N8: 6.874999
B9: Santander | C9: 54355.657 | D9: 55919.909 | E9: 56190.954 | F9: 3.5235665 | G9: 3.0760877 | H9: 3.1393884 | I9: 209.40999 | J9: 233.13438 | K9: 228.94435 | L9: 7.3787002 | M9: 7.1714178 | N9: 7.1874524
B10: Banorte | C10: 83249.895 | D10: 89913.965 | E10: 91268.7 | F10: 2.6204228 | G10: 2.4766463 | H10: 2.4597217 | I10: 261.55288 | J10: 273.51985 | K10: 268.33087 | L10: 6.8537914 | M10: 6.7741193 | N10: 6.6001927
B11: Banamex | C11: 60794.003 | D11: 67890.425 | E11: 68722.003 | F11: 2.8128685 | G11: 3.1992817 | H11: 3.2089725 | I11: 233.75394 | J11: 196.09917 | K11: 195.81755 | L11: 6.575191 | M11: 6.2737647 | N11: 6.2837313
B12: HSBC | C12: 32923.573 | D12: 30601.229 | E12: 29941.892 | F12: 2.940413 | G12: 2.3170599 | H12: 2.650748 | I12: 299.07587 | J12: 389.28748 | K12: 340.26782 | L12: 8.7940659 | M12: 9.0200241 | N12: 9.0196424
B13: Scotiabank | C13: 1910.492 | D13: 1610.0103 | E13: 1581.2978 | F13: 3.1217409 | G13: 3.0702257 | H13: 3.8059722 | I13: 204.70892 | J13: 227.03451 | K13: 166.46118 | L13: 6.3904821 | M13: 6.9704719 | N13: 6.3354663
B14: Inbursa | C14: 1889.5524 | D14: 2532.7329 | E14: 2568.1052 | F14: 1.875809 | G14: 2.9888912 | H14: 3.6133186 | I14: 379.49824 | J14: 291.42301 | K14: 241.40307 | L14: 7.1186621 | M14: 8.7103165 | N14: 8.7226621
B15: Citi México | C15: 0 | D15: 0 | E15: 0 | F15: n.a. | G15: n.a. | H15: n.a. | I15: - | J15: - | K15: - | L15: - | M15: - | N15: -
B16: Banco del Bajío | C16: 2432.5805 | D16: 2719.8843 | E16: 2718.8061 | F16: 2.3264549 | G16: 2.0608559 | H16: 2.2639976 | I16: 317.89918 | J16: 339.25712 | K16: 313.48269 | L16: 7.3957811 | M16: 6.9916003 | N16: 7.0972405
B17: Banco Azteca | C17: 2058.4563 | D17: 1987.9961 | E17: 1981.3245 | F17: 3.750577 | G17: 2.6138524 | H17: 2.5692787 | I17: 215.56728 | J17: 299.23783 | K17: 306.80292 | L17: 8.085017 | M17: 7.8216352 | N17: 7.8826222
B18: Afirme | C18: 2314.7921 | D18: 2281.3974 | E18: 2263.7604 | F18: 2.2202473 | G18: 2.2978697 | H18: 2.4171445 | I18: 318.66198 | J18: 308.85132 | K18: 296.23142 | L18: 7.0750838 | M18: 7.097001 | N18: 7.1603414
B19: Monex | C19: 0 | D19: 0 | E19: 0 | F19: n.a. | G19: n.a. | H19: n.a. | I19: - | J19: - | K19: - | L19: - | M19: - | N19: -
B20: Banregio | C20: 14.792794 | D20: 39.12632 | E20: 42.577086 | F20: 2.7942356 | G20: 0.72701098 | H20: 0.79728039 | I20: 303.78539 | J20: 857.76677 | K20: 763.77836 | L20: 8.4884796 | M20: 6.2360585 | N20: 6.0894551
B21: J.P. Morgan | C21: 0 | D21: 0 | E21: 0 | F21: n.a. | G21: n.a. | H21: n.a. | I21: - | J21: - | K21: - | L21: - | M21: - | N21: -
B22: Invex | C22: 0 | D22: 0 | E22: 0 | F22: n.a. | G22: n.a. | H22: n.a. | I22: - | J22: - | K22: - | L22: - | M22: - | N22: -
B23: Multiva | C23: 43.430503 | D23: 52.59656 | E23: 56.452725 | F23: 0.31102564 | G23: 1.4484559 | H23: 2.4137063 | I23: 1719.6328 | J23: 463.7356 | K23: 266.21393 | L23: 5.348499 | M23: 6.7170058 | N23: 6.4256225
B24: BanCoppel | C24: 113.97988 | D24: 501.79691 | E24: 538.45569 | F24: 3.2222119 | G24: 5.0126781 | H24: 5.9409289 | I24: 262.47962 | J24: 134.53768 | K24: 104.74168 | L24: 8.4576495 | M24: 6.7439406 | N24: 6.2226289
B25: Banca Mifel | C25: 0.146096 | D25: 0.080288 | E25: 0.102097 | F25: 0 | G25: 0 | H25: 0 | I25: - | J25: - | K25: - | L25: 11.870962 | M25: 15.957553 | N25: 12.970019
B26: Barclays | C26: 0 | D26: 0 | E26: 0 | F26: n.a. | G26: n.a. | H26: n.a. | I26: - | J26: - | K26: - | L26: - | M26: - | N26: -
B27: Banco Base | C27: 0 | D27: 0 | E27: 0 | F27: n.a. | G27: n.a. | H27: n.a. | I27: - | J27: - | K27: - | L27: - | M27: - | N27: -
B28: Sabadell | C28: 0 | D28: 0 | E28: 0 | F28: n.a. | G28: n.a. | H28: n.a. | I28: - | J28: - | K28: - | L28: - | M28: - | N28: -
B29: Bank of America | C29: 0 | D29: 0 | E29: 0 | F29: n.a. | G29: n.a. | H29: n.a. | I29: - | J29: - | K29: - | L29: - | M29: - | N29: -
B30: Ve por Más | C30: 0 | D30: 0 | E30: 0 | F30: n.a. | G30: n.a. | H30: n.a. | I30: - | J30: - | K30: - | L30: - | M30: - | N30: -
B31: Actinver | C31: 0 | D31: 0 | E31: 0 | F31: n.a. | G31: n.a. | H31: n.a. | I31: - | J31: - | K31: - | L31: - | M31: - | N31: -
B32: Bansí | C32: 0 | D32: 0 | E32: 0 | F32: n.a. | G32: n.a. | H32: n.a. | I32: - | J32: - | K32: - | L32: - | M32: - | N32: -
B33: Compartamos | C33: 0 | D33: 0 | E33: 0 | F33: n.a. | G33: n.a. | H33: n.a. | I33: - | J33: - | K33: - | L33: - | M33: - | N33: -
B34: BIAfirme | C34: 0 | D34: 0 | E34: 0 | F34: n.a. | G34: n.a. | H34: n.a. | I34: - | J34: - | K34: - | L34: - | M34: - | N34: -
B35: Bancrea | C35: 0 | D35: 0 | E35: 0 | F35: n.a. | G35: n.a. | H35: n.a. | I35: - | J35: - | K35: - | L35: - | M35: - | N35: -
B36: Kapital Bank | C36: 1.9106607 | D36: 1.3777755 | E36: 1.30274 | F36: 1.7403048 | G36: 12.761438 | H36: 13.723076 | I36: 483.65196 | J36: 86.709395 | K36: 85.277397 | L36: 8.4170181 | M36: 11.065365 | N36: 11.702682
B37: MUFG Bank | C37: 0 | D37: 0 | E37: 0 | F37: n.a. | G37: n.a. | H37: n.a. | I37: - | J37: - | K37: - | L37: - | M37: - | N37: -
B38: Consubanco | C38: 0 | D38: 0 | E38: 0 | F38: n.a. | G38: n.a. | H38: n.a. | I38: - | J38: - | K38: - | L38: - | M38: - | N38: -
B39: Bankaool | C39: 0.515852 | D39: 0.745488 | E39: 0.657486 | F39: 0.48870606 | G39: 10.985556 | H39: 3.6855538 | I39: 892.50298 | J39: 74.041467 | K39: 223.40294 | L39: 4.3617162 | M39: 8.1338667 | N39: 8.2336354
B40: BNP Paribas México | C40: 0 | D40: 0 | E40: 0 | F40: n.a. | G40: n.a. | H40: n.a. | I40: - | J40: - | K40: - | L40: - | M40: - | N40: -
B41: Inmobiliario Mexicano | C41: 0 | D41: 0 | E41: 0 | F41: n.a. | G41: n.a. | H41: n.a. | I41: - | J41: - | K41: - | L41: - | M41: - | N41: -
B42: Mizuho Bank | C42: 0 | D42: 0 | E42: 0 | F42: n.a. | G42: n.a. | H42: n.a. | I42: - | J42: - | K42: - | L42: - | M42: - | N42: -
B43: ICBC | C43: 0 | D43: 0 | E43: 0 | F43: n.a. | G43: n.a. | H43: n.a. | I43: - | J43: - | K43: - | L43: - | M43: - | N43: -
B44: Openbank | C44: 0 | D44: 0 | E44: 0 | F44: n.a. | G44: n.a. | H44: n.a. | I44: - | J44: - | K44: - | L44: - | M44: - | N44: -
B45: Banco Covalto | C45: 0 | D45: 0 | E45: 0 | F45: n.a. | G45: n.a. | H45: n.a. | I45: - | J45: - | K45: - | L45: - | M45: - | N45: -
B46: Volkswagen Bank | C46: 0 | D46: 0 | E46: 0 | F46: n.a. | G46: n.a. | H46: n.a. | I46: - | J46: - | K46: - | L46: - | M46: - | N46: -
B47: Banco S3 | C47: 0 | D47: 0 | E47: 0 | F47: n.a. | G47: n.a. | H47: n.a. | I47: - | J47: - | K47: - | L47: - | M47: - | N47: -
B48: Bank of China | C48: 0 | D48: 0 | E48: 0 | F48: n.a. | G48: n.a. | H48: n.a. | I48: - | J48: - | K48: - | L48: - | M48: - | N48: -
B49: Shinhan | C49: 0 | D49: 0 | E49: 0 | F49: n.a. | G49: n.a. | H49: n.a. | I49: - | J49: - | K49: - | L49: - | M49: - | N49: -
B50: Banco Ualá | C50: 0 | D50: 0 | E50: 0 | F50: n.a. | G50: n.a. | H50: n.a. | I50: - | J50: - | K50: - | L50: - | M50: - | N50: -
B51: KEB Hana México | C51: 0 | D51: 0 | E51: 0 | F51: n.a. | G51: n.a. | H51: n.a. | I51: - | J51: - | K51: - | L51: - | M51: - | N51: -
... B59: Intercam Banco | C59: 0 | D59: 0 | E59: 0 | F59: n.a. | G59: n.a. | H59: n.a. | I59: - | J59: - | K59: - | L59: - | M59: - | N59: -
B61: n.a. No aplica

Sheet CCCnrP
B2: Cartera de crédito al consumo
B3: Millones de pesos y porcentajes
C5: Créditos personales (MDP) 1/ | F5: IMOR (%) 5/ | I5: ICOR (%) 6/ | L5: Pérdida esperada (%) 7/
C6: 45536 | D6: 45870 | E6: 45901 | F6: =C6 -> 45536 | G6: =D6 -> 45870 | H6: =E6 -> 45901 | I6: =C6 -> 45536 | J6: =D6 -> 45870 | K6: =E6 -> 45901 | L6: =C6 -> 45536 | M6: =D6 -> 45870 | N6: =E6 -> 45901
B7: Sistema */ | C7: 252633.86 | D7: 290850.97 | E7: 295652.43 | F7: 4.5801246 | G7: 4.6711707 | H7: 4.8724351 | I7: 205.01814 | J7: 210.62007 | K7: 204.58949 | L7: 9.3900861 | M7: 9.8384231 | N7: 9.96849
B8: BBVA México | C8: 67817.397 | D8: 77276.726 | E8: 79643.656 | F8: 4.6791715 | G8: 4.8869911 | H8: 4.8647952 | I8: 218.42317 | J8: 208.50246 | K8: 210.90237 | L8: 10.220395 | M8: 10.189497 | N8: 10.259968
B9: Santander | C9: 14785.54 | D9: 13733.391 | E9: 13739.206 | F9: 5.122893 | G9: 4.6933102 | H9: 5.0246587 | I9: 182.42185 | J9: 261.69705 | K9: 262.18644 | L9: 9.3452763 | M9: 12.282254 | N9: 13.173974
B10: Banorte | C10: 1095.7006 | D10: 1123.9648 | E10: 1108.7068 | F10: 6.3248784 | G10: 3.4041126 | H10: 3.9075014 | I10: 186.68157 | J10: 263.37458 | K10: 257.71963 | L10: 11.807382 | M10: 8.9655674 | N10: 10.070398
B11: Banamex | C11: 20287.803 | D11: 24590.137 | E11: 25061.543 | F11: 3.3849612 | G11: 4.0755411 | H11: 4.2815868 | I11: 200.5004 | J11: 184.44795 | K11: 176.86967 | L11: 6.7868606 | M11: 7.5172522 | N11: 7.5728286
B12: HSBC | C12: 13037.116 | D12: 12057.385 | E12: 11891.106 | F12: 2.4957075 | G12: 3.2101963 | H12: 3.3414518 | I12: 376.66749 | J12: 329.60555 | K12: 315.83313 | L12: 9.4005186 | M12: 10.580985 | N12: 10.553412
B13: Scotiabank | C13: 7782.3294 | D13: 9567.4264 | E13: 9630.0326 | F13: 3.0731379 | G13: 3.7252629 | H13: 3.4902032 | I13: 320.38758 | J13: 261.10658 | K13: 275.12663 | L13: 9.8459521 | M13: 9.7269067 | N13: 9.6024783
B14: Inbursa | C14: 7248.5442 | D14: 8848.2235 | E14: 8904.5322 | F14: 3.865534 | G14: 3.5337637 | H14: 3.4760219 | I14: 204.23208 | J14: 200.17069 | K14: 199.10021 | L14: 7.8946606 | M14: 7.0735591 | N14: 6.9207671
B15: Citi México | C15: 0 | D15: 0 | E15: 0 | F15: n.a. | G15: n.a. | H15: n.a. | I15: - | J15: - | K15: - | L15: - | M15: - | N15: -
B16: Banco del Bajío | C16: 1220.8236 | D16: 1425.6904 | E16: 1427.7825 | F16: 1.6142439 | G16: 1.6419859 | H16: 2.3138319 | I16: 475.86472 | J16: 489.893 | K16: 347.00571 | L16: 7.6816172 | M16: 8.0439738 | N16: 8.029129
B17: Banco Azteca | C17: 71410.554 | D17: 85664.188 | E17: 87488.61 | F17: 4.7982337 | G17: 5.7707198 | H17: 6.3653676 | I17: 202.47408 | J17: 198.66792 | K17: 184.70201 | L17: 9.7151796 | M17: 11.464569 | N17: 11.756962
B18: Afirme | C18: 2596.5778 | D18: 2469.6497 | E18: 2484.8604 | F18: 3.5179421 | G18: 3.3756415 | H18: 3.5444267 | I18: 287.36573 | J18: 299.034 | K18: 290.82061 | L18: 10.10936 | M18: 10.094316 | N18: 10.307923
B19: Monex | C19: 0 | D19: 0 | E19: 0 | F19: n.a. | G19: n.a. | H19: n.a. | I19: - | J19: - | K19: - | L19: - | M19: - | N19: -
B20: Banregio | C20: 969.16633 | D20: 1079.7272 | E20: 1089.6424 | F20: 3.4871771 | G20: 2.9671136 | H20: 3.1239076 | I20: 305.51554 | J20: 344.67925 | K20: 338.15 | L20: 10.653868 | M20: 10.227025 | N20: 10.563494
B21: J.P. Morgan | C21: 0 | D21: 0 | E21: 0 | F21: n.a. | G21: n.a. | H21: n.a. | I21: - | J21: - | K21: - | L21: - | M21: - | N21: -
B22: Invex | C22: 190.90506 | D22: 179.59878 | E22: 179.83148 | F22: 4.669123 | G22: 0 | H22: 0 | I22: 178.67007 | J22: - | K22: - | L22: 8.3423253 | M22: 4.521959 | N22: 4.0250266
B23: Multiva | C23: 5201.4796 | D23: 6357.9887 | E23: 6579.4099 | F23: 1.9957039 | G23: 1.2333216 | H23: 1.1768931 | I23: 185.35193 | J23: 252.56001 | K23: 256.7249 | L23: 3.6990756 | M23: 3.1148772 | N23: 3.0213776
B24: BanCoppel | C24: 8089.9138 | D24: 7174.7753 | E24: 7180.0739 | F24: 18.122782 | G24: 11.134483 | H24: 11.083995 | I24: 125.69796 | J24: 159.44861 | K24: 159.14581 | L24: 22.779967 | M24: 17.753779 | N24: 17.639713
B25: Banca Mifel | C25: 2.252075 | D25: 2.035643 | E25: 2.151342 | F25: 0 | G25: 3.8838834 | H25: 3.6750084 | I25: - | J25: 226.83337 | K25: 232.95009 | L25: 11.110065 | M25: 8.8099436 | N25: 8.5609355
B26: Barclays | C26: 0 | D26: 0 | E26: 0 | F26: n.a. | G26: n.a. | H26: n.a. | I26: - | J26: - | K26: - | L26: - | M26: - | N26: -
B27: Banco Base | C27: 0 | D27: 0 | E27: 0 | F27: n.a. | G27: n.a. | H27: n.a. | I27: - | J27: - | K27: - | L27: - | M27: - | N27: -
B28: Sabadell | C28: 14.055723 | D28: 10.144499 | E28: 10.757736 | F28: 8.442867 | G28: 1.532259 | H28: 1.4449137 | I28: 187.15099 | J28: 691.1001 | K28: 699.96011 | L28: 15.800909 | M28: 10.589444 | N28: 10.113819
B29: Bank of America | C29: 0 | D29: 0 | E29: 0 | F29: n.a. | G29: n.a. | H29: n.a. | I29: - | J29: - | K29: - | L29: - | M29: - | N29: -
B30: Ve por Más | C30: 9.213438 | D30: 7.304874 | E30: 7.59715 | F30: 3.0561339 | G30: 24.977734 | H30: 22.057364 | I30: 433.3389 | J30: 102.52281 | K30: 112.19074 | L30: 13.243417 | M30: 25.607875 | N30: 24.746319
B31: Actinver | C31: 2936.1252 | D31: 3235.2035 | E31: 3222.5812 | F31: 7.680681 | G31: 6.5943588 | H31: 6.4538064 | I31: 141.41478 | J31: 160.77367 | K31: 164.47452 | L31: 10.861618 | M31: 10.601992 | N31: 10.614867
B32: Bansí | C32: 612.02222 | D32: 865.35275 | E32: 869.16751 | F32: 0.0068971351 | G32: 4.8407819 | H32: 4.8033565 | I32: 68779.025 | J32: 160.30077 | K32: 167.9316 | L32: 4.7437823 | M32: 7.7598104 | N32: 8.0663532
B33: Compartamos | C33: 6414.0975 | D33: 9571.6831 | E33: 9574.509 | F33: 2.8199374 | G33: 2.9572692 | H33: 3.203667 | I33: 345.74292 | J33: 322.2992 | K33: 311.68445 | L33: 9.7497341 | M33: 9.531255 | N33: 9.9853317
B34: BIAfirme | C34: 0 | D34: 0 | E34: 0 | F34: n.a. | G34: n.a. | H34: n.a. | I34: - | J34: - | K34: - | L34: - | M34: - | N34: -
B35: Bancrea | C35: 1936.0677 | D35: 2384.69 | E35: 2432.2741 | F35: 1.4454581 | G35: 1.6293416 | H35: 1.5799636 | I35: 156.84055 | J35: 150.54595 | K35: 153.88228 | L35: 2.2670643 | M35: 2.4529077 | N35: 2.431284
B36: Kapital Bank | C36: 5.8783774 | D36: 29.818047 | E36: 431.41215 | F36: 0.19330181 | G36: 0 | H36: 2.2010477 | I36: 3067.1327 | J36: - | K36: 268.94891 | L36: 5.9288232 | M36: 7.9548422 | N36: 5.9196938
B37: MUFG Bank | C37: 0 | D37: 0 | E37: 0 | F37: n.a. | G37: n.a. | H37: n.a. | I37: - | J37: - | K37: - | L37: - | M37: - | N37: -
B38: Consubanco | C38: 17774.801 | D38: 22082.053 | E38: 22517.763 | F38: 2.253506 | G38: 2.1519428 | H38: 2.0744573 | I38: 195.32801 | J38: 203.41336 | K38: 207.17188 | L38: 4.4017283 | M38: 4.3773391 | N38: 4.2976922
B39: Bankaool | C39: 9.891867 | D39: 20.844746 | E39: 31.757369 | F39: 9.8656603 | G39: 4.88561 | H39: 3.3480513 | I39: 95.389272 | J39: 142.21396 | K39: 129.47417 | L39: 9.4107816 | M39: 6.9480194 | N39: 4.3348616
B40: BNP Paribas México | C40: 0 | D40: 0 | E40: 0 | F40: n.a. | G40: n.a. | H40: n.a. | I40: - | J40: - | K40: - | L40: - | M40: - | N40: -
B41: Inmobiliario Mexicano | C41: 0 | D41: 0 | E41: 0 | F41: n.a. | G41: n.a. | H41: n.a. | I41: - | J41: - | K41: - | L41: - | M41: - | N41: -
B42: Mizuho Bank | C42: 0 | D42: 0 | E42: 0 | F42: n.a. | G42: n.a. | H42: n.a. | I42: - | J42: - | K42: - | L42: - | M42: - | N42: -
B43: ICBC | C43: 0 | D43: 0 | E43: 0 | F43: n.a. | G43: n.a. | H43: n.a. | I43: - | J43: - | K43: - | L43: - | M43: - | N43: -
B44: Openbank | C44: 0 | D44: 0 | E44: 0 | F44: n.a. | G44: n.a. | H44: n.a. | I44: - | J44: - | K44: - | L44: - | M44: - | N44: -
B45: Banco Covalto | C45: 0 | D45: 0 | E45: 0 | F45: n.a. | G45: n.a. | H45: n.a. | I45: - | J45: - | K45: - | L45: - | M45: - | N45: -
B46: Volkswagen Bank | C46: 0 | D46: 0 | E46: 0 | F46: n.a. | G46: n.a. | H46: n.a. | I46: - | J46: - | K46: - | L46: - | M46: - | N46: -
B47: Banco S3 | C47: 0 | D47: 0 | E47: 0 | F47: n.a. | G47: n.a. | H47: n.a. | I47: - | J47: - | K47: - | L47: - | M47: - | N47: -
B48: Bank of China | C48: 0 | D48: 0 | E48: 0 | F48: n.a. | G48: n.a. | H48: n.a. | I48: - | J48: - | K48: - | L48: - | M48: - | N48: -
B49: Shinhan | C49: 0 | D49: 0 | E49: 0 | F49: n.a. | G49: n.a. | H49: n.a. | I49: - | J49: - | K49: - | L49: - | M49: - | N49: -
B50: Banco Ualá | C50: 31.291896 | D50: 38.002379 | E50: 43.705178 | F50: 7.690055 | G50: 12.133238 | H50: 10.037236 | I50: 228.7641 | J50: 154.06757 | K50: 163.94007 | L50: 17.592085 | M50: 18.693385 | N50: 16.455053
B51: KEB Hana México | C51: 0 | D51: 0 | E51: 0 | F51: n.a. | G51: n.a. | H51: n.a. | I51: - | J51: - | K51: - | L51: - | M51: - | N51: -
B52: Banco Bineo | C52: 45.844604 | D52: 9.8025796 | E52: 6.5318605 | F52: 5.5376905 | G52: 42.710186 | H52: 37.733611 | I52: 291.46349 | J52: 94.337196 | K52: 95.978757 | L52: 16.140346 | M52: 40.291592 | N52: 36.21625
B53: Dondé Banco | C53: 0 | D53: 0 | E53: 0 | F53: n.a. | G53: n.a. | H53: n.a. | I53: - | J53: - | K53: - | L53: - | M53: - | N53: -
B54: Credit Suisse | C54: 0 | D54: 0 | E54: 0 | F54: n.a. | G54: n.a. | H54: n.a. | I54: - | J54: - | K54: - | L54: - | M54: - | N54: -
B55: Hey Banco | C55: 0 | D55: 0 | E55: 0 | F55: n.a. | G55: n.a. | H55: n.a. | I55: - | J55: - | K55: - | L55: - | M55: - | N55: -
B56: Forjadores | C56: 1.86492 | D56: 65.809828 | E56: 93.225078 | F56: 63.799305 | G56: 2.7588873 | H56: 2.5398338 | I56: 80.047504 | J56: 451.19367 | K56: 588.65933 | L56: 51.069751 | M56: 12.447925 | N56: 14.950968
B57: Pagatodo | C57: 0 | D57: 0 | E57: 0 | F57: n.a. | G57: n.a. | H57: n.a. | I57: - | J57: - | K57: - | L57: - | M57: - | N57: -
B58: CIBanco | C58: 699.07765 | D58: 510.7304 | E58: 0 | F58: 6.6483375 | G58: 8.3383606 | H58: n.a. | I58: 149.8013 | J58: 167.26727 | K58: - | L58: 9.9592962 | M58: 13.947348 | N58: -
B59: Intercam Banco | C59: 407.5295 | D59: 468.62083 | E59: n.d. | F59: 0.26492585 | G59: 1.3193005 | H59: n.d. | I59: 1661.9138 | J59: 1000.5674 | K59: n.d. | L59: 4.4028393 | M59: 13.20049 | N59: n.d.
B61: n.d. No disponible
B62: n.a. No aplica

Sheet CCCAut
B2: Cartera de crédito al consumo
B3: Millones de pesos y porcentajes
C5: Automotriz (MDP) 1/ | F5: IMOR (%) 5/ | I5: ICOR (%) 6/ | L5: Pérdida esperada (%) 7/
C6: 45536 | D6: 45870 | E6: 45901 | F6: =C6 -> 45536 | G6: =D6 -> 45870 | H6: =E6 -> 45901 | I6: =C6 -> 45536 | J6: =D6 -> 45870 | K6: =E6 -> 45901 | L6: =C6 -> 45536 | M6: =D6 -> 45870 | N6: =E6 -> 45901
B7: Sistema */ | C7: 278142.95 | D7: 337003.7 | E7: 341010.09 | F7: 1.045609 | G7: 1.1480705 | H7: 1.211023 | I7: 209.48486 | J7: 200.36594 | K7: 194.62029 | L7: 2.1903926 | M7: 2.3003422 | N7: 2.3568964
B8: BBVA México | C8: 64025.896 | D8: 74996.912 | E8: 76042.488 | F8: 0.90199773 | G8: 1.0099755 | H8: 1.0437766 | I8: 265.07433 | J8: 243.77265 | K8: 243.98103 | L8: 2.3909644 | M8: 2.4620439 | N8: 2.5466168
B9: Santander | C9: 42651.54 | D9: 57555.23 | E9: 58499.123 | F9: 0.94031956 | G9: 0.78202254 | H9: 0.96479908 | I9: 210.88112 | J9: 258.35936 | K9: 220.06353 | L9: 1.9829564 | M9: 2.0204284 | N9: 2.1231709
B10: Banorte | C10: 50027.967 | D10: 64288.668 | E10: 65531.971 | F10: 0.54720652 | G10: 0.50962628 | H10: 0.51104828 | I10: 238.32885 | J10: 230.9296 | K10: 239.96195 | L10: 1.304151 | M10: 1.1768779 | N10: 1.2263214
B11: Banamex | C11: 3.0169612 | D11: 0.13802915 | E11: 0.09735771 | F11: 30.417584 | G11: 58.596434 | H11: 92.53755 | I11: 101.24825 | J11: 81.29383 | K11: 73.442344 | L11: 30.797271 | M11: 47.635286 | N11: 67.961746
B12: HSBC | C12: 15788.295 | D12: 12864.132 | E12: 12615.899 | F12: 1.24443 | G12: 1.6064907 | H12: 1.5872867 | I12: 247.92736 | J12: 211.08428 | K12: 217.27244 | L12: 3.0852824 | M12: 3.3910492 | N12: 3.4487366
B13: Scotiabank | C13: 24232.72 | D13: 30562.815 | E13: 31099.448 | F13: 1.8376732 | G13: 2.3573151 | H13: 2.2873174 | I13: 158.32778 | J13: 153.36975 | K13: 156.57205 | L13: 2.9095472 | M13: 3.6154083 | N13: 3.5812996
B14: Inbursa | C14: 57450.552 | D14: 67684.978 | E14: 68383.931 | F14: 1.1084051 | G14: 1.3652786 | H14: 1.4613373 | I14: 176.82022 | J14: 163.47648 | K14: 159.17135 | L14: 1.9598843 | M14: 2.2319094 | N14: 2.3260303
B15: Citi México | C15: 0 | D15: 0 | E15: 0 | F15: n.a. | G15: n.a. | H15: n.a. | I15: - | J15: - | K15: - | L15: - | M15: - | N15: -
B16: Banco del Bajío | C16: 359.46858 | D16: 363.60715 | E16: 375.05996 | F16: 1.6542624 | G16: 1.4204812 | H16: 1.865987 | I16: 184.55332 | J16: 195.01847 | K16: 152.05847 | L16: 3.0529961 | M16: 2.7702007 | N16: 2.8373913
B17: Banco Azteca | C17: 8.2719746 | D17: 20.877941 | E17: 22.818191 | F17: 0 | G17: 0 | H17: 0 | I17: - | J17: - | K17: - | L17: 1.441847 | M17: 1.4992234 | N17: 1.4608213
B18: Afirme | C18: 5640.5229 | D18: 6487.4279 | E18: 6538.5834 | F18: 2.4584086 | G18: 2.1961288 | H18: 2.3227436 | I18: 182.3897 | J18: 216.2111 | K18: 201.07173 | L18: 4.4838841 | M18: 4.7482742 | N18: 4.6703808
B19: Monex | C19: 0 | D19: 0 | E19: 0 | F19: n.a. | G19: n.a. | H19: n.a. | I19: - | J19: - | K19: - | L19: - | M19: - | N19: -
B20: Banregio | C20: 5263.9167 | D20: 5896.0837 | E20: 5973.1608 | F20: 0.41617918 | G20: 0.7738868 | H20: 0.79422036 | I20: 524.90525 | J20: 274.04384 | K20: 263.69334 | L20: 2.1845463 | M20: 2.1207892 | N20: 2.0943062
B21: J.P. Morgan | C21: 0 | D21: 0 | E21: 0 | F21: n.a. | G21: n.a. | H21: n.a. | I21: - | J21: - | K21: - | L21: - | M21: - | N21: -
B22: Invex | C22: 0 | D22: 0 | E22: 0 | F22: n.a. | G22: n.a. | H22: n.a. | I22: - | J22: - | K22: - | L22: - | M22: - | N22: -
B23: Multiva | C23: 9.555809 | D23: 6.236233 | E23: 5.594563 | F23: 0 | G23: 0 | H23: 0 | I23: - | J23: - | K23: - | L23: 1.5104634 | M23: 2.1524853 | N23: 1.9783136
B24: BanCoppel | C24: 0 | D24: 8122.0221 | E24: 7871.1231 | F24: n.a. | G24: 2.3419223 | H24: 2.75504 | I24: - | J24: 130.49908 | K24: 124.18441 | L24: - | M24: 3.056187 | N24: 3.4213301
B25: Banca Mifel | C25: 0 | D25: 0 | E25: 0 | F25: n.a. | G25: n.a. | H25: n.a. | I25: - | J25: - | K25: - | L25: - | M25: - | N25: -
B26: Barclays | C26: 0 | D26: 0 | E26: 0 | F26: n.a. | G26: n.a. | H26: n.a. | I26: - | J26: - | K26: - | L26: - | M26: - | N26: -
B27: Banco Base | C27: 0 | D27: 0 | E27: 0 | F27: n.a. | G27: n.a. | H27: n.a. | I27: - | J27: - | K27: - | L27: - | M27: - | N27: -
B28: Sabadell | C28: 0 | D28: 0 | E28: 0 | F28: n.a. | G28: n.a. | H28: n.a. | I28: - | J28: - | K28: - | L28: - | M28: - | N28: -
B29: Bank of America | C29: 0 | D29: 0 | E29: 0 | F29: n.a. | G29: n.a. | H29: n.a. | I29: - | J29: - | K29: - | L29: - | M29: - | N29: -
B30: Ve por Más | C30: 0 | D30: 0 | E30: 0 | F30: n.a. | G30: n.a. | H30: n.a. | I30: - | J30: - | K30: - | L30: - | M30: - | N30: -
B31: Actinver | C31: 20.210619 | D31: 8.431314 | E31: 7.884518 | F31: 13.688408 | G31: 3.5290466 | H31: 3.7737881 | I31: 103.78552 | J31: 136.54607 | K31: 145.58168 | L31: 14.206586 | M31: 4.8187744 | N31: 5.493944
B32: Bansí | C32: 1.65775 | D32: 1.203098 | E32: 1.144625 | F32: 0.39993968 | G32: 0.5510773 | H32: 0.57922901 | I32: 193.10709 | J32: 153.68024 | K32: 150.54299 | L32: 0.77231187 | M32: 0.84689693 | N32: 0.87198864
B33: Compartamos | C33: 0 | D33: 0 | E33: 0 | F33: n.a. | G33: n.a. | H33: n.a. | I33: - | J33: - | K33: - | L33: - | M33: - | N33: -
B34: BIAfirme | C34: 0 | D34: 0 | E34: 0 | F34: n.a. | G34: n.a. | H34: n.a. | I34: - | J34: - | K34: - | L34: - | M34: - | N34: -
B35: Bancrea | C35: 0 | D35: 0 | E35: 0 | F35: n.a. | G35: n.a. | H35: n.a. | I35: - | J35: - | K35: - | L35: - | M35: - | N35: -
B36: Kapital Bank | C36: 695.51388 | D36: 528.451 | E36: 505.00408 | F36: 1.3291192 | G36: 2.8538307 | H36: 2.9107955 | I36: 375.19317 | J36: 209.2976 | K36: 214.72895 | L36: 4.9867643 | M36: 5.9729992 | N36: 6.2503206
B37: MUFG Bank | C37: 0 | D37: 0 | E37: 0 | F37: n.a. | G37: n.a. | H37: n.a. | I37: - | J37: - | K37: - | L37: - | M37: - | N37: -
B38: Consubanco | C38: 0 | D38: 0 | E38: 0 | F38: n.a. | G38: n.a. | H38: n.a. | I38: - | J38: - | K38: - | L38: - | M38: - | N38: -
B39: Bankaool | C39: 3.447063 | D39: 3.248743 | E39: 3.152859 | F39: 15.329514 | G39: 0 | H39: 0 | I39: 103.28395 | J39: - | K39: - | L39: 15.832928 | M39: 4.0044411 | N39: 2.7412263
B40: BNP Paribas México | C40: 0 | D40: 0 | E40: 0 | F40: n.a. | G40: n.a. | H40: n.a. | I40: - | J40: - | K40: - | L40: - | M40: - | N40: -
B41: Inmobiliario Mexicano | C41: 0 | D41: 0 | E41: 0 | F41: n.a. | G41: n.a. | H41: n.a. | I41: - | J41: - | K41: - | L41: - | M41: - | N41: -
B42: Mizuho Bank | C42: 0 | D42: 0 | E42: 0 | F42: n.a. | G42: n.a. | H42: n.a. | I42: - | J42: - | K42: - | L42: - | M42: - | N42: -
B43: ICBC | C43: 0 | D43: 0 | E43: 0 | F43: n.a. | G43: n.a. | H43: n.a. | I43: - | J43: - | K43: - | L43: - | M43: - | N43: -
B44: Openbank | C44: 0 | D44: 0 | E44: 0 | F44: n.a. | G44: n.a. | H44: n.a. | I44: - | J44: - | K44: - | L44: - | M44: - | N44: -
B45: Banco Covalto | C45: 0 | D45: 0 | E45: 0 | F45: n.a. | G45: n.a. | H45: n.a. | I45: - | J45: - | K45: - | L45: - | M45: - | N45: -
B46: Volkswagen Bank | C46: 5196.7482 | D46: 7404.2091 | E46: 7533.6041 | F46: 1.0802438 | G46: 1.1170978 | H46: 1.1617912 | I46: 251.20797 | J46: 249.91953 | K46: 197.17179 | L46: 2.7136586 | M46: 2.7918457 | N46: 2.2907245
B47: Banco S3 | C47: 0 | D47: 0 | E47: 0 | F47: n.a. | G47: n.a. | H47: n.a. | I47: - | J47: - | K47: - | L47: - | M47: - | N47: -
B48: Bank of China | C48: 0 | D48: 0 | E48: 0 | F48: n.a. | G48: n.a. | H48: n.a. | I48: - | J48: - | K48: - | L48: - | M48: - | N48: -
B49: Shinhan | C49: 0 | D49: 0 | E49: 0 | F49: n.a. | G49: n.a. | H49: n.a. | I49: - | J49: - | K49: - | L49: - | M49: - | N49: -
B50: Banco Ualá | C50: 0 | D50: 0 | E50: 0 | F50: n.a. | G50: n.a. | H50: n.a. | I50: - | J50: - | K50: - | L50: - | M50: - | N50: -
B51: KEB Hana México | C51: 0 | D51: 0 | E51: 0 | F51: n.a. | G51: n.a. | H51: n.a. | I51: - | J51: - | K51: - | L51: - | M51: - | N51: -
B52: Banco Bineo | C52: 0 | D52: 0 | E52: 0 | F52: n.a. | G52: n.a. | H52: n.a. | I52: - | J52: - | K52: - | L52: - | M52: - | N52: -
B53: Dondé Banco | C53: 0 | D53: 0 | E53: 0 | F53: n.a. | G53: n.a. | H53: n.a. | I53: - | J53: - | K53: - | L53: - | M53: - | N53: -
B54: Credit Suisse | C54: 0 | D54: 0 | E54: 0 | F54: n.a. | G54: n.a. | H54: n.a. | I54: - | J54: - | K54: - | L54: - | M54: - | N54: -
B55: Hey Banco | C55: 0 | D55: 0 | E55: 0 | F55: n.a. | G55: n.a. | H55: n.a. | I55: - | J55: - | K55: - | L55: - | M55: - | N55: -
B56: Forjadores | C56: 0 | D56: 0 | E56: 0 | F56: n.a. | G56: n.a. | H56: n.a. | I56: - | J56: - | K56: - | L56: - | M56: - | N56: -
B57: Pagatodo | C57: 0 | D57: 0 | E57: 0 | F57: n.a. | G57: n.a. | H57: n.a. | I57: - | J57: - | K57: - | L57: - | M57: - | N57: -
B58: CIBanco | C58: 6763.6517 | D58: 209.02757 | E58: 0 | F58: 2.0885055 | G58: 0.47610323 | H58: n.a. | I58: 131.69701 | J58: 375.1924 | K58: - | L58: 2.7504992 | M58: 1.7863031 | N58: -
B59: Intercam Banco | C59: 0 | D59: 0 | E59: 0 | F59: n.a. | G59: n.a. | H59: n.a. | I59: - | J59: - | K59: - | L59: - | M59: - | N59: -
B61: n.a. No aplica

Sheet CCCAdq BiMu
B2: Cartera de crédito al consumo
B3: Millones de pesos y porcentajes
C5: Adquisición de bienes muebles (MDP) 1/ | F5: IMOR (%) 5/ | I5: ICOR (%) 6/ | L5: Pérdida esperada (%) 7/
C6: 45536 | D6: 45870 | E6: 45901 | F6: =C6 -> 45536 | G6: =D6 -> 45870 | H6: =E6 -> 45901 | I6: =C6 -> 45536 | J6: =D6 -> 45870 | K6: =E6 -> 45901 | L6: =C6 -> 45536 | M6: =D6 -> 45870 | N6: =E6 -> 45901
B7: Sistema */ | C7: 39788.593 | D7: 44620.598 | E7: 44799.134 | F7: 4.3377649 | G7: 4.5785877 | H7: 4.648895 | I7: 249.23662 | J7: 219.35412 | K7: 214.994 | L7: 10.811299 | M7: 10.043321 | N7: 9.9948452
B8: BBVA México | C8: 0 | D8: 0 | E8: 0 | F8: n.a. | G8: n.a. | H8: n.a. | I8: - | J8: - | K8: - | L8: - | M8: - | N8: -
B9: Santander | C9: 947.13905 | D9: 1151.9416 | E9: 1098.6965 | F9: 1.0744552 | G9: 0.91706777 | H9: 1.2244639 | I9: 751.991 | J9: 903.48314 | K9: 734.9375 | L9: 8.0798065 | M9: 8.2855527 | N9: 8.9990444
B10: Banorte | C10: 0 | D10: 0 | E10: 0 | F10: n.a. | G10: n.a. | H10: n.a. | I10: - | J10: - | K10: - | L10: - | M10: - | N10: -
B11: Banamex | C11: 0 | D11: 0 | E11: 0 | F11: n.a. | G11: n.a. | H11: n.a. | I11: - | J11: - | K11: - | L11: - | M11: - | N11: -
B12: HSBC | C12: 0 | D12: 0 | E12: 0 | F12: n.a. | G12: n.a. | H12: n.a. | I12: - | J12: - | K12: - | L12: - | M12: - | N12: -
B13: Scotiabank | C13: 0 | D13: 0 | E13: 0 | F13: n.a. | G13: n.a. | H13: n.a. | I13: - | J13: - | K13: - | L13: - | M13: - | N13: -
B14: Inbursa | C14: 8.036328 | D14: 2.623219 | E14: 2.057265 | F14: 5.4184946 | G14: 6.8028251 | H14: 0 | I14: 200.07372 | J14: 127.37079 | K14: - | L14: 10.840984 | M14: 8.6648122 | N14: 2.986538
B15: Citi México | C15: 0 | D15: 0 | E15: 0 | F15: n.a. | G15: n.a. | H15: n.a. | I15: - | J15: - | K15: - | L15: - | M15: - | N15: -
B16: Banco del Bajío | C16: 0 | D16: 0 | E16: 0 | F16: n.a. | G16: n.a. | H16: n.a. | I16: - | J16: - | K16: - | L16: - | M16: - | N16: -
B17: Banco Azteca | C17: 38724.096 | D17: 43384.351 | E17: 43656.398 | F17: 4.4225478 | G17: 4.6798056 | H17: 4.7389352 | I17: 245.99974 | J17: 215.578 | K17: 211.38306 | L17: 10.879456 | M17: 10.088631 | N17: 10.017306
B18: Afirme | C18: 43.354765 | D18: 39.195924 | E18: 41.982523 | F18: 1.6834182 | G18: 0 | H18: 0.86500995 | I18: 851.19272 | J18: - | K18: 1507.7334 | L18: 14.329133 | M18: 12.591819 | N18: 13.042044
B19: Monex | C19: 0 | D19: 0 | E19: 0 | F19: n.a. | G19: n.a. | H19: n.a. | I19: - | J19: - | K19: - | L19: - | M19: - | N19: -
B20: Banregio | C20: 0 | D20: 0 | E20: 0 | F20: n.a. | G20: n.a. | H20: n.a. | I20: - | J20: - | K20: - | L20: - | M20: - | N20: -
B21: J.P. Morgan | C21: 0 | D21: 0 | E21: 0 | F21: n.a. | G21: n.a. | H21: n.a. | I21: - | J21: - | K21: - | L21: - | M21: - | N21: -
B22: Invex | C22: 0 | D22: 0 | E22: 0 | F22: n.a. | G22: n.a. | H22: n.a. | I22: - | J22: - | K22: - | L22: - | M22: - | N22: -
B23: Multiva | C23: 0 | D23: 0 | E23: 0 | F23: n.a. | G23: n.a. | H23: n.a. | I23: - | J23: - | K23: - | L23: - | M23: - | N23: -
B24: BanCoppel | C24: 0 | D24: 0 | E24: 0 | F24: n.a. | G24: n.a. | H24: n.a. | I24: - | J24: - | K24: - | L24: - | M24: - | N24: -
B25: Banca Mifel | C25: 0 | D25: 0 | E25: 0 | F25: n.a. | G25: n.a. | H25: n.a. | I25: - | J25: - | K25: - | L25: - | M25: - | N25: -
B26: Barclays | C26: 0 | D26: 0 | E26: 0 | F26: n.a. | G26: n.a. | H26: n.a. | I26: - | J26: - | K26: - | L26: - | M26: - | N26: -
B27: Banco Base | C27: 0 | D27: 0 | E27: 0 | F27: n.a. | G27: n.a. | H27: n.a. | I27: - | J27: - | K27: - | L27: - | M27: - | N27: -
B28: Sabadell | C28: 0 | D28: 0 | E28: 0 | F28: n.a. | G28: n.a. | H28: n.a. | I28: - | J28: - | K28: - | L28: - | M28: - | N28: -
B29: Bank of America | C29: 0 | D29: 0 | E29: 0 | F29: n.a. | G29: n.a. | H29: n.a. | I29: - | J29: - | K29: - | L29: - | M29: - | N29: -
B30: Ve por Más | C30: 0 | D30: 0 | E30: 0 | F30: n.a. | G30: n.a. | H30: n.a. | I30: - | J30: - | K30: - | L30: - | M30: - | N30: -
... B57: Pagatodo | C57: 0 | D57: 0 | E57: 0 | F57: n.a. | G57: n.a. | H57: n.a. | I57: - | J57: - | K57: - | L57: - | M57: - | N57: -
B58: CIBanco | C58: 65.967549 | D58: 42.486321 | E58: 0 | F58: 3.0350211 | G58: 4.5835976 | H58: n.a. | I58: 253.8296 | J58: 200.00893 | K58: - | L58: 7.7037817 | M58: 9.1676048 | N58: -
B59: Intercam Banco | C59: 0 | D59: 0 | E59: 0 | F59: n.a. | G59: n.a. | H59: n.a. | I59: - | J59: - | K59: - | L59: - | M59: - | N59: -
B61: n.d. No aplica

Sheet CCOAC
B2: Cartera de crédito al consumo
B3: Millones de pesos y porcentajes
C5: Op. de arrendamiento financiero (MDP) 1/ | F5: IMOR (%) 5/ | I5: ICOR (%) 6/ | L5: Pérdida esperada (%) 7/
C6: 45536 | D6: 45870 | E6: 45901 | F6: =C6 -> 45536 | G6: =D6 -> 45870 | H6: =E6 -> 45901 | I6: =C6 -> 45536 | J6: =D6 -> 45870 | K6: =E6 -> 45901 | L6: =C6 -> 45536 | M6: =D6 -> 45870 | N6: =E6 -> 45901
B7: Sistema */ | C7: 95.537299 | D7: 110.12227 | E7: 108.82851 | F7: 0.81563755 | G7: 0.60695661 | H7: 0.59705899 | I7: 283.33508 | J7: 316.31686 | K7: 255.01164 | L7: 2.3109873 | M7: 1.9199061 | N7: 1.5225699
B8: BBVA México | C8: 0 | D8: 0 | E8: 0 | F8: n.a. | G8: n.a. | H8: n.a. | I8: - | J8: - | K8: - | L8: - | M8: - | N8: -
B9: Santander | C9: 0 | D9: 0 | E9: 0 | F9: n.a. | G9: n.a. | H9: n.a. | I9: - | J9: - | K9: - | L9: - | M9: - | N9: -
B10: Banorte | C10: 0 | D10: 0 | E10: 0 | F10: n.a. | G10: n.a. | H10: n.a. | I10: - | J10: - | K10: - | L10: - | M10: - | N10: -
B11: Banamex | C11: 0 | D11: 0 | E11: 0 | F11: n.a. | G11: n.a. | H11: n.a. | I11: - | J11: - | K11: - | L11: - | M11: - | N11: -
B12: HSBC | C12: 0 | D12: 0 | E12: 0 | F12: n.a. | G12: n.a. | H12: n.a. | I12: - | J12: - | K12: - | L12: - | M12: - | N12: -
B13: Scotiabank | C13: 0 | D13: 0 | E13: 0 | F13: n.a. | G13: n.a. | H13: n.a. | I13: - | J13: - | K13: - | L13: - | M13: - | N13: -
B14: Inbursa | C14: 0 | D14: 0 | E14: 0 | F14: n.a. | G14: n.a. | H14: n.a. | I14: - | J14: - | K14: - | L14: - | M14: - | N14: -
B15: Citi México | C15: 0 | D15: 0 | E15: 0 | F15: n.a. | G15: n.a. | H15: n.a. | I15: - | J15: - | K15: - | L15: - | M15: - | N15: -
B16: Banco del Bajío | C16: 0 | D16: 0 | E16: 0 | F16: n.a. | G16: n.a. | H16: n.a. | I16: - | J16: - | K16: - | L16: - | M16: - | N16: -
B17: Banco Azteca | C17: 0 | D17: 0 | E17: 0 | F17: n.a. | G17: n.a. | H17: n.a. | I17: - | J17: - | K17: - | L17: - | M17: - | N17: -
B18: Afirme | C18: 0 | D18: 0 | E18: 0 | F18: n.a. | G18: n.a. | H18: n.a. | I18: - | J18: - | K18: - | L18: - | M18: - | N18: -
B19: Monex | C19: 0 | D19: 0 | E19: 0 | F19: n.a. | G19: n.a. | H19: n.a. | I19: - | J19: - | K19: - | L19: - | M19: - | N19: -
B20: Banregio | C20: 83.177035 | D20: 99.261166 | E20: 98.109639 | F20: 0.93684282 | G20: 0.67336948 | H20: 0.66229005 | I20: 251.79286 | J20: 303.8799 | K20: 241.51887 | L20: 2.3589033 | M20: 2.0462345 | N20: 1.5995555
B21: J.P. Morgan | C21: 0 | D21: 0 | E21: 0 | F21: n.a. | G21: n.a. | H21: n.a. | I21: - | J21: - | K21: - | L21: - | M21: - | N21: -
B22: Invex | C22: 0 | D22: 0 | E22: 0 | F22: n.a. | G22: n.a. | H22: n.a. | I22: - | J22: - | K22: - | L22: - | M22: - | N22: -
B23: Multiva | C23: 0 | D23: 0 | E23: 0 | F23: n.a. | G23: n.a. | H23: n.a. | I23: - | J23: - | K23: - | L23: - | M23: - | N23: -
B24: BanCoppel | C24: 0 | D24: 0 | E24: 0 | F24: n.a. | G24: n.a. | H24: n.a. | I24: - | J24: - | K24: - | L24: - | M24: - | N24: -
B25: Banca Mifel | C25: 0 | D25: 0 | E25: 0 | F25: n.a. | G25: n.a. | H25: n.a. | I25: - | J25: - | K25: - | L25: - | M25: - | N25: -
B26: Barclays | C26: 0 | D26: 0 | E26: 0 | F26: n.a. | G26: n.a. | H26: n.a. | I26: - | J26: - | K26: - | L26: - | M26: - | N26: -
B27: Banco Base | C27: 0 | D27: 0 | E27: 0 | F27: n.a. | G27: n.a. | H27: n.a. | I27: - | J27: - | K27: - | L27: - | M27: - | N27: -
B28: Sabadell | C28: 0 | D28: 0 | E28: 0 | F28: n.a. | G28: n.a. | H28: n.a. | I28: - | J28: - | K28: - | L28: - | M28: - | N28: -
B29: Bank of America | C29: 0 | D29: 0 | E29: 0 | F29: n.a. | G29: n.a. | H29: n.a. | I29: - | J29: - | K29: - | L29: - | M29: - | N29: -
B30: Ve por Más | C30: 12.360264 | D30: 10.861104 | E30: 10.718866 | F30: 0 | G30: 0 | H30: 0 | I30: - | J30: - | K30: - | L30: 1.9885417 | M30: 0.76537339 | N30: 0.81792234
B31: Actinver | C31: 0 | D31: 0 | E31: 0 | F31: n.a. | G31: n.a. | H31: n.a. | I31: - | J31: - | K31: - | L31: - | M31: - | N31: -
B32: Bansí | C32: 0 | D32: 0 | E32: 0 | F32: n.a. | G32: n.a. | H32: n.a. | I32: - | J32: - | K32: - | L32: - | M32: - | N32: -
B33: Compartamos | C33: 0 | D33: 0 | E33: 0 | F33: n.a. | G33: n.a. | H33: n.a. | I33: - | J33: - | K33: - | L33: - | M33: - | N33: -
B34: BIAfirme | C34: 0 | D34: 0 | E34: 0 | F34: n.a. | G34: n.a. | H34: n.a. | I34: - | J34: - | K34: - | L34: - | M34: - | N34: -
B35: Bancrea | C35: 0 | D35: 0 | E35: 0 | F35: n.a. | G35: n.a. | H35: n.a. | I35: - | J35: - | K35: - | L35: - | M35: - | N35: -
B36: Kapital Bank | C36: 0 | D36: 0 | E36: 0 | F36: n.a. | G36: n.a. | H36: n.a. | I36: - | J36: - | K36: - | L36: - | M36: - | N36: -
B37: MUFG Bank | C37: 0 | D37: 0 | E37: 0 | F37: n.a. | G37: n.a. | H37: n.a. | I37: - | J37: - | K37: - | L37: - | M37: - | N37: -
B38: Consubanco | C38: 0 | D38: 0 | E38: 0 | F38: n.a. | G38: n.a. | H38: n.a. | I38: - | J38: - | K38: - | L38: - | M38: - | N38: -
B39: Bankaool | C39: 0 | D39: 0 | E39: 0 | F39: n.a. | G39: n.a. | H39: n.a. | I39: - | J39: - | K39: - | L39: - | M39: - | N39: -
B40: BNP Paribas México | C40: 0 | D40: 0 | E40: 0 | F40: n.a. | G40: n.a. | H40: n.a. | I40: - | J40: - | K40: - | L40: - | M40: - | N40: -
B41: Inmobiliario Mexicano | C41: 0 | D41: 0 | E41: 0 | F41: n.a. | G41: n.a. | H41: n.a. | I41: - | J41: - | K41: - | L41: - | M41: - | N41: -
B42: Mizuho Bank | C42: 0 | D42: 0 | E42: 0 | F42: n.a. | G42: n.a. | H42: n.a. | I42: - | J42: - | K42: - | L42: - | M42: - | N42: -
... B59: Intercam Banco | C59: 0 | D59: 0 | E59: 0 | F59: n.a. | G59: n.a. | H59: n.a. | I59: - | J59: - | K59: - | L59: - | M59: - | N59: -
B61: n.a. No aplica

Sheet CCCMicro
B2: Cartera de crédito al consumo
B3: Millones de pesos y porcentajes
C5: Microcréditos (MDP) 1/ | F5: IMOR (%) 5/ | I5: ICOR (%) 6/ | L5: Pérdida esperada (%) 7/
C6: 45536 | D6: 45870 | E6: 45901 | F6: =C6 -> 45536 | G6: =D6 -> 45870 | H6: =E6 -> 45901 | I6: =C6 -> 45536 | J6: =D6 -> 45870 | K6: =E6 -> 45901 | L6: =C6 -> 45536 | M6: =D6 -> 45870 | N6: =E6 -> 45901
B7: Sistema */ | C7: 43627.933 | D7: 51267.454 | E7: 50255.98 | F7: 3.4952902 | G7: 3.4126195 | H7: 3.6542009 | I7: 219.36689 | J7: 219.56947 | K7: 220.76184 | L7: 7.6675096 | M7: 7.4930707 | N7: 8.0670811
B8: BBVA México | C8: 0 | D8: 0 | E8: 0 | F8: n.a. | G8: n.a. | H8: n.a. | I8: - | J8: - | K8: - | L8: - | M8: - | N8: -
B9: Santander | C9: 988.22548 | D9: 1113.185 | E9: 1094.4876 | F9: 4.0851785 | G9: 5.6735218 | H9: 6.1924029 | I9: 235.37564 | J9: 186.45517 | K9: 183.11768 | L9: 9.6155151 | M9: 10.578575 | N9: 11.339385
B10: Banorte | C10: 0 | D10: 0 | E10: 0 | F10: n.a. | G10: n.a. | H10: n.a. | I10: - | J10: - | K10: - | L10: - | M10: - | N10: -
B11: Banamex | C11: 0 | D11: 0 | E11: 0 | F11: n.a. | G11: n.a. | H11: n.a. | I11: - | J11: - | K11: - | L11: - | M11: - | N11: -
B12: HSBC | C12: 0 | D12: 0 | E12: 0 | F12: n.a. | G12: n.a. | H12: n.a. | I12: - | J12: - | K12: - | L12: - | M12: - | N12: -
B13: Scotiabank | C13: 0 | D13: 0 | E13: 0 | F13: n.a. | G13: n.a. | H13: n.a. | I13: - | J13: - | K13: - | L13: - | M13: - | N13: -
B14: Inbursa | C14: 0 | D14: 0 | E14: 0 | F14: n.a. | G14: n.a. | H14: n.a. | I14: - | J14: - | K14: - | L14: - | M14: - | N14: -
B15: Citi México | C15: 0 | D15: 0 | E15: 0 | F15: n.a. | G15: n.a. | H15: n.a. | I15: - | J15: - | K15: - | L15: - | M15: - | N15: -
B16: Banco del Bajío | C16: 0 | D16: 0 | E16: 0 | F16: n.a. | G16: n.a. | H16: n.a. | I16: - | J16: - | K16: - | L16: - | M16: - | N16: -
B17: Banco Azteca | C17: 0 | D17: 0 | E17: 0 | F17: n.a. | G17: n.a. | H17: n.a. | I17: - | J17: - | K17: - | L17: - | M17: - | N17: -
B18: Afirme | C18: 0 | D18: 277.51004 | E18: 282.4055 | F18: n.a. | G18: 3.2807631 | H18: 3.080873 | I18: - | J18: 382.21231 | K18: 389.09044 | L18: - | M18: 12.53948 | N18: 11.987383
B19: Monex | C19: 0 | D19: 0 | E19: 0 | F19: n.a. | G19: n.a. | H19: n.a. | I19: - | J19: - | K19: - | L19: - | M19: - | N19: -
B20: Banregio | C20: 0 | D20: 0 | E20: 0 | F20: n.a. | G20: n.a. | H20: n.a. | I20: - | J20: - | K20: - | L20: - | M20: - | N20: -
B21: J.P. Morgan | C21: 0 | D21: 0 | E21: 0 | F21: n.a. | G21: n.a. | H21: n.a. | I21: - | J21: - | K21: - | L21: - | M21: - | N21: -
B22: Invex | C22: 0 | D22: 0 | E22: 0 | F22: n.a. | G22: n.a. | H22: n.a. | I22: - | J22: - | K22: - | L22: - | M22: - | N22: -
B23: Multiva | C23: 0 | D23: 0 | E23: 0 | F23: n.a. | G23: n.a. | H23: n.a. | I23: - | J23: - | K23: - | L23: - | M23: - | N23: -
B24: BanCoppel | C24: 0 | D24: 0 | E24: 0 | F24: n.a. | G24: n.a. | H24: n.a. | I24: - | J24: - | K24: - | L24: - | M24: - | N24: -
B25: Banca Mifel | C25: 0 | D25: 0 | E25: 0 | F25: n.a. | G25: n.a. | H25: n.a. | I25: - | J25: - | K25: - | L25: - | M25: - | N25: -
B26: Barclays | C26: 0 | D26: 0 | E26: 0 | F26: n.a. | G26: n.a. | H26: n.a. | I26: - | J26: - | K26: - | L26: - | M26: - | N26: -
B27: Banco Base | C27: 0 | D27: 0 | E27: 0 | F27: n.a. | G27: n.a. | H27: n.a. | I27: - | J27: - | K27: - | L27: - | M27: - | N27: -
B28: Sabadell | C28: 0 | D28: 0 | E28: 0 | F28: n.a. | G28: n.a. | H28: n.a. | I28: - | J28: - | K28: - | L28: - | M28: - | N28: -
B29: Bank of America | C29: 0 | D29: 0 | E29: 0 | F29: n.a. | G29: n.a. | H29: n.a. | I29: - | J29: - | K29: - | L29: - | M29: - | N29: -
B30: Ve por Más | C30: 0 | D30: 0 | E30: 0 | F30: n.a. | G30: n.a. | H30: n.a. | I30: - | J30: - | K30: - | L30: - | M30: - | N30: -
... B32: Bansí | C32: 0 | D32: 0 | E32: 0 | F32: n.a. | G32: n.a. | H32: n.a. | I32: - | J32: - | K32: - | L32: - | M32: - | N32: -
B33: Compartamos | C33: 42151.101 | D33: 49538.319 | E33: 48533.321 | F33: 3.4429797 | G33: 3.3207358 | H33: 3.5653826 | I33: 220.78707 | J33: 222.13231 | K33: 223.25768 | L33: 7.6016538 | M33: 7.376427 | N33: 7.9599907
B34: BIAfirme | C34: 0 | D34: 0 | E34: 0 | F34: n.a. | G34: n.a. | H34: n.a. | I34: - | J34: - | K34: - | L34: - | M34: - | N34: -
B35: Bancrea | C35: 0 | D35: 0 | E35: 0 | F35: n.a. | G35: n.a. | H35: n.a. | I35: - | J35: - | K35: - | L35: - | M35: - | N35: -
B36: Kapital Bank | C36: 0 | D36: 0 | E36: 0 | F36: n.a. | G36: n.a. | H36: n.a. | I36: - | J36: - | K36: - | L36: - | M36: - | N36: -
B37: MUFG Bank | C37: 0 | D37: 0 | E37: 0 | F37: n.a. | G37: n.a. | H37: n.a. | I37: - | J37: - | K37: - | L37: - | M37: - | N37: -
B38: Consubanco | C38: 0 | D38: 0 | E38: 0 | F38: n.a. | G38: n.a. | H38: n.a. | I38: - | J38: - | K38: - | L38: - | M38: - | N38: -
B39: Bankaool | C39: 0 | D39: 0 | E39: 0 | F39: n.a. | G39: n.a. | H39: n.a. | I39: - | J39: - | K39: - | L39: - | M39: - | N39: -
B40: BNP Paribas México | C40: 0 | D40: 0 | E40: 0 | F40: n.a. | G40: n.a. | H40: n.a. | I40: - | J40: - | K40: - | L40: - | M40: - | N40: -
B41: Inmobiliario Mexicano | C41: 0 | D41: 0 | E41: 0 | F41: n.a. | G41: n.a. | H41: n.a. | I41: - | J41: - | K41: - | L41: - | M41: - | N41: -
B42: Mizuho Bank | C42: 0 | D42: 0 | E42: 0 | F42: n.a. | G42: n.a. | H42: n.a. | I42: - | J42: - | K42: - | L42: - | M42: - | N42: -
B43: ICBC | C43: 0 | D43: 0 | E43: 0 | F43: n.a. | G43: n.a. | H43: n.a. | I43: - | J43: - | K43: - | L43: - | M43: - | N43: -
B44: Openbank | C44: 0 | D44: 0 | E44: 0 | F44: n.a. | G44: n.a. | H44: n.a. | I44: - | J44: - | K44: - | L44: - | M44: - | N44: -
B45: Banco Covalto | C45: 0 | D45: 0 | E45: 0 | F45: n.a. | G45: n.a. | H45: n.a. | I45: - | J45: - | K45: - | L45: - | M45: - | N45: -
... B55: Hey Banco | C55: 0 | D55: 0 | E55: 0 | F55: n.a. | G55: n.a. | H55: n.a. | I55: - | J55: - | K55: - | L55: - | M55: - | N55: -
B56: Forjadores | C56: 488.60576 | D56: 338.44048 | E56: 345.7667 | F56: 6.8149473 | G56: 9.5335048 | H56: 8.5549748 | I56: 138.0618 | J56: 107.82893 | K56: 111.49903 | L56: 9.4088392 | M56: 10.279876 | N56: 9.5387142
B57: Pagatodo | C57: 0 | D57: 0 | E57: 0 | F57: n.a. | G57: n.a. | H57: n.a. | I57: - | J57: - | K57: - | L57: - | M57: - | N57: -
B58: CIBanco | C58: 0 | D58: 0 | E58: 0 | F58: n.a. | G58: n.a. | H58: n.a. | I58: - | J58: - | K58: - | L58: - | M58: - | N58: -
B59: Intercam Banco | C59: 0 | D59: 0 | E59: 0 | F59: n.a. | G59: n.a. | H59: n.a. | I59: - | J59: - | K59: - | L59: - | M59: - | N59: -
B61: n.a. No aplica

Sheet CCCnrO
B2: Cartera de crédito al consumo
B3: Millones de pesos y porcentajes
C5: Otros créditos al consumo (MDP) 1/ | F5: IMOR (%) 5/ | I5: ICOR (%) 6/ | L5: Pérdida esperada (%) 7/
C6: 45536 | D6: 45870 | E6: 45901 | F6: =C6 -> 45536 | G6: =D6 -> 45870 | H6: =E6 -> 45901 | I6: =C6 -> 45536 | J6: =D6 -> 45870 | K6: =E6 -> 45901 | L6: =C6 -> 45536 | M6: =D6 -> 45870 | N6: =E6 -> 45901
B7: Sistema */ | C7: 5475.0223 | D7: 4186.5204 | E7: 4166.488 | F7: 4.3570924 | G7: 4.576684 | H7: 4.59007 | I7: 227.56451 | J7: 219.59908 | K7: 227.80376 | L7: 9.9151958 | M7: 10.050356 | N7: 10.456352
B8: BBVA México | C8: 18.837138 | D8: 32.055433 | E8: 36.992186 | F8: 59.125375 | G8: 0.61414641 | H8: 0.58791409 | I8: 104.31116 | J8: 2108.5746 | K8: 2466.8355 | L8: 61.674365 | M8: 12.949735 | N8: 14.502873
B9: Santander | C9: 0 | D9: 0 | E9: 0 | F9: n.a. | G9: n.a. | H9: n.a. | I9: - | J9: - | K9: - | L9: - | M9: - | N9: -
B10: Banorte | C10: 58.184456 | D10: 51.902923 | E10: 51.534993 | F10: 7.5303233 | G10: 8.5586308 | H10: 9.0316201 | I10: 295.50637 | J10: 233.83396 | K10: 220.18606 | L10: 22.252585 | M10: 20.012985 | N10: 19.886368
B11: Banamex | C11: 0.18710899 | D11: 0.18931153 | E11: 0.19204911 | F11: 100 | G11: 100 | H11: 100 | I11: 100 | J11: 99.999366 | K11: 100 | L11: 100 | M11: 99.999366 | N11: 100
B12: HSBC | C12: 1176.1041 | D12: 1160.2701 | E12: 1149.6569 | F12: 9.6210144 | G12: 5.9426883 | H12: 5.5112731 | I12: 203.95869 | J12: 233.50662 | K12: 274.69273 | L12: 19.622895 | M12: 13.876571 | N12: 15.139067
B13: Scotiabank | C13: 9.292171 | D13: 7.016527 | E13: 7.721494 | F13: 46.804767 | G13: 60.339296 | H13: 56.108002 | I13: 101.89043 | J13: 101.21867 | K13: 100.4308 | L13: 47.689577 | M13: 61.074631 | N13: 56.349717
B14: Inbursa | C14: 1998.7815 | D14: 9.639678 | E14: 8.916676 | F14: 2.4166906 | G14: 1.707474 | H14: 0.74464969 | I14: 271.53175 | J14: 125.16176 | K14: 173.01575 | L14: 6.5620825 | M14: 2.1371046 | N14: 1.2883613
B15: Citi México | C15: 0 | D15: 0 | E15: 0 | F15: n.a. | G15: n.a. | H15: n.a. | I15: - | J15: - | K15: - | L15: - | M15: - | N15: -
B16: Banco del Bajío | C16: 0 | D16: 0 | E16: 0 | F16: n.a. | G16: n.a. | H16: n.a. | I16: - | J16: - | K16: - | L16: - | M16: - | N16: -
B17: Banco Azteca | C17: 1649.3483 | D17: 2382.8931 | E17: 2425.2724 | F17: 3.1934779 | G17: 4.4343347 | H17: 4.6105426 | I17: 226.63114 | J17: 198.02027 | K17: 192.42957 | L17: 7.2374154 | M17: 8.7808817 | N17: 8.8720474
B18: Afirme | C18: 0 | D18: 0 | E18: 0 | F18: n.a. | G18: n.a. | H18: n.a. | I18: - | J18: - | K18: - | L18: - | M18: - | N18: -
B19: Monex | C19: 0 | D19: 0 | E19: 0 | F19: n.a. | G19: n.a. | H19: n.a. | I19: - | J19: - | K19: - | L19: - | M19: - | N19: -
B20: Banregio | C20: 0.01014899 | D20: 0 | E20: 0 | F20: 0 | G20: n.a. | H20: n.a. | I20: - | J20: - | K20: - | L20: 3.2390415 | M20: - | N20: -
B21: J.P. Morgan | C21: 0 | D21: 0 | E21: 0 | F21: n.a. | G21: n.a. | H21: n.a. | I21: - | J21: - | K21: - | L21: - | M21: - | N21: -
B22: Invex | C22: 0 | D22: 0 | E22: 0 | F22: n.a. | G22: n.a. | H22: n.a. | I22: - | J22: - | K22: - | L22: - | M22: - | N22: -
B23: Multiva | C23: 0 | D23: 0 | E23: 0 | F23: n.a. | G23: n.a. | H23: n.a. | I23: - | J23: - | K23: - | L23: - | M23: - | N23: -
B24: BanCoppel | C24: 0 | D24: 0 | E24: 0 | F24: n.a. | G24: n.a. | H24: n.a. | I24: - | J24: - | K24: - | L24: - | M24: - | N24: -
B25: Banca Mifel | C25: 0 | D25: 0 | E25: 0 | F25: n.a. | G25: n.a. | H25: n.a. | I25: - | J25: - | K25: - | L25: - | M25: - | N25: -
B26: Barclays | C26: 0 | D26: 0 | E26: 0 | F26: n.a. | G26: n.a. | H26: n.a. | I26: - | J26: - | K26: - | L26: - | M26: - | N26: -
B27: Banco Base | C27: 0 | D27: 0 | E27: 0 | F27: n.a. | G27: n.a. | H27: n.a. | I27: - | J27: - | K27: - | L27: - | M27: - | N27: -
B28: Sabadell | C28: 0 | D28: 0 | E28: 0 | F28: n.a. | G28: n.a. | H28: n.a. | I28: - | J28: - | K28: - | L28: - | M28: - | N28: -
B29: Bank of America | C29: 0 | D29: 0 | E29: 0 | F29: n.a. | G29: n.a. | H29: n.a. | I29: - | J29: - | K29: - | L29: - | M29: - | N29: -
B30: Ve por Más | C30: 125.10019 | D30: 139.04953 | E30: 139.52226 | F30: 0 | G30: 0.10055122 | H30: 0.17631882 | I30: - | J30: 3456.2489 | K30: 1562.4014 | L30: 3.3370972 | M30: 3.4753006 | N30: 2.7548078
B31: Actinver | C31: 439.17708 | D31: 403.01445 | E31: 346.18968 | F31: 0.9944508 | G31: 1.7694805 | H31: 1.6949228 | I31: 645.29221 | J31: 365.06008 | K31: 372.9568 | L31: 6.4171136 | M31: 6.4596668 | N31: 6.3213299
B32: Bansí | C32: 0 | D32: 0 | E32: 0 | F32: n.a. | G32: n.a. | H32: n.a. | I32: - | J32: - | K32: - | L32: - | M32: - | N32: -
B33: Compartamos | C33: 0 | D33: 0.489365 | E33: 0.489365 | F33: n.a. | G33: 100 | H33: 100 | I33: - | J33: 87.999959 | K33: 90.999969 | L33: - | M33: 87.999959 | N33: 90.999969
B34: BIAfirme | C34: 0 | D34: 0 | E34: 0 | F34: n.a. | G34: n.a. | H34: n.a. | I34: - | J34: - | K34: - | L34: - | M34: - | N34: -
B35: Bancrea | C35: 0 | D35: 0 | E35: 0 | F35: n.a. | G35: n.a. | H35: n.a. | I35: - | J35: - | K35: - | L35: - | M35: - | N35: -
B36: Kapital Bank | C36: 0 | D36: 0 | E36: 0 | F36: n.a. | G36: n.a. | H36: n.a. | I36: - | J36: - | K36: - | L36: - | M36: - | N36: -
B37: MUFG Bank | C37: 0 | D37: 0 | E37: 0 | F37: n.a. | G37: n.a. | H37: n.a. | I37: - | J37: - | K37: - | L37: - | M37: - | N37: -
B38: Consubanco | C38: 0 | D38: 0 | E38: 0 | F38: n.a. | G38: n.a. | H38: n.a. | I38: - | J38: - | K38: - | L38: - | M38: - | N38: -
B39: Bankaool | C39: 0 | D39: 0 | E39: 0 | F39: n.a. | G39: n.a. | H39: n.a. | I39: - | J39: - | K39: - | L39: - | M39: - | N39: -
B40: BNP Paribas México | C40: 0 | D40: 0 | E40: 0 | F40: n.a. | G40: n.a. | H40: n.a. | I40: - | J40: - | K40: - | L40: - | M40: - | N40: -
B41: Inmobiliario Mexicano | C41: 0 | D41: 0 | E41: 0 | F41: n.a. | G41: n.a. | H41: n.a. | I41: - | J41: - | K41: - | L41: - | M41: - | N41: -
B42: Mizuho Bank | C42: 0 | D42: 0 | E42: 0 | F42: n.a. | G42: n.a. | H42: n.a. | I42: - | J42: - | K42: - | L42: - | M42: - | N42: -
B43: ICBC | C43: 0 | D43: 0 | E43: 0 | F43: n.a. | G43: n.a. | H43: n.a. | I43: - | J43: - | K43: - | L43: - | M43: - | N43: -
B44: Openbank | C44: 0 | D44: 0 | E44: 0 | F44: n.a. | G44: n.a. | H44: n.a. | I44: - | J44: - | K44: - | L44: - | M44: - | N44: -
B45: Banco Covalto | C45: 0 | D45: 0 | E45: 0 | F45: n.a. | G45: n.a. | H45: n.a. | I45: - | J45: - | K45: - | L45: - | M45: - | N45: -
... B59: Intercam Banco | C59: 0 | D59: 0 | E59: 0 | F59: n.a. | G59: n.a. | H59: n.a. | I59: - | J59: - | K59: - | L59: - | M59: - | N59: -
B61: n.a. No aplica

Sheet CCV
B2: Cartera de crédito a la vivienda
B3: Millones de pesos y porcentajes
C5: Cartera total (MDP) 1/ | F5: IMOR (%) 5/ | I5: ICOR (%) 6/ | L5: Pérdida esperada (%) 7/
C6: 45536 | D6: 45870 | E6: 45901 | F6: =C6 -> 45536 | G6: =D6 -> 45870 | H6: =E6 -> 45901 | I6: =C6 -> 45536 | J6: =D6 -> 45870 | K6: =E6 -> 45901 | L6: =C6 -> 45536 | M6: =D6 -> 45870 | N6: =E6 -> 45901
B7: Sistema */ | C7: 1406113 | D7: 1481464.7 | E7: 1487702.9 | F7: 2.7322513 | G7: 3.0897356 | H7: 3.1062598 | I7: 56.329957 | J7: 54.254003 | K7: 54.116555 | L7: 1.539076 | M7: 1.6763052 | N7: 1.6810008
B8: BBVA México | C8: 359991.25 | D8: 388133.06 | E8: 390079.39 | F8: 2.1769065 | G8: 2.4493451 | H8: 2.4085263 | I8: 65.783087 | J8: 66.395884 | K8: 64.47401 | L8: 1.4320363 | M8: 1.6262643 | N8: 1.5528735
B9: Santander | C9: 235577.25 | D9: 251265.68 | E9: 253166.81 | F9: 3.439295 | G9: 3.6642195 | H9: 3.6862515 | I9: 64.927325 | J9: 62.885852 | K9: 65.602108 | L9: 2.2330423 | M9: 2.3042756 | N9: 2.4182587
B10: Banorte | C10: 268808.06 | D10: 288864.83 | E10: 290406.13 | F10: 0.75819555 | G10: 0.87466044 | H10: 0.89659848 | I10: 61.853933 | J10: 52.217974 | K10: 52.008663 | L10: 0.46897376 | M10: 0.45672996 | N10: 0.46630888
B11: Banamex | C11: 72803.325 | D11: 78640.535 | E11: 79259.696 | F11: 2.2579833 | G11: 2.4589813 | H11: 2.5442197 | I11: 50.337451 | J11: 43.369641 | K11: 41.641412 | L11: 1.1366112 | M11: 1.0664514 | N11: 1.059449
B12: HSBC | C12: 152026.56 | D12: 150608 | E12: 150072.56 | F12: 2.4595388 | G12: 2.8081832 | H12: 2.8550892 | I12: 54.417684 | J12: 52.64709 | K12: 51.686897 | L12: 1.3384241 | M12: 1.4784267 | N12: 1.475707
B13: Scotiabank | C13: 241424.59 | D13: 249977.99 | E13: 251281.46 | F13: 4.7308142 | G13: 5.8179143 | H13: 5.8376805 | I13: 42.688497 | J13: 42.190067 | K13: 42.29852 | L13: 2.0195134 | M13: 2.4545819 | N13: 2.4692525
B14: Inbursa | C14: 5057.8482 | D14: 4417.3115 | E14: 4373.9503 | F14: 14.712719 | G14: 12.168373 | H14: 12.398094 | I14: 34.448514 | J14: 27.065349 | K14: 28.289558 | L14: 5.0683132 | M14: 3.2934128 | N14: 3.5073659
B15: Citi México | C15: 0 | D15: 0 | E15: 0 | F15: n.a. | G15: n.a. | H15: n.a. | I15: - | J15: - | K15: - | L15: - | M15: - | N15: -
B16: Banco del Bajío | C16: 4208.731 | D16: 3652.963 | E16: 3553.6574 | F16: 3.706016 | G16: 3.380233 | H16: 4.8834505 | I16: 47.261278 | J16: 42.812096 | K16: 37.565016 | L16: 1.7515105 | M16: 1.4471486 | N16: 1.834469
B17: Banco Azteca | C17: 575.14954 | D17: 613.34604 | E17: 605.485 | F17: 6.0981066 | G17: 3.0927989 | H17: 3.3009281 | I17: 24.229914 | J17: 49.394295 | K17: 35.454729 | L17: 1.477566 | M17: 1.5276662 | N17: 1.1703351
B18: Afirme | C18: 13599.736 | D18: 14309.786 | E18: 14419.828 | F18: 5.5502478 | G18: 4.2135515 | H18: 4.4802342 | I18: 41.638688 | J18: 46.960063 | K18: 44.965142 | L18: 2.3110503 | M18: 1.9786864 | N18: 2.0145437
B19: Monex | C19: 7.0207377 | D19: 0 | E19: 0 | F19: 66.612686 | G19: n.a. | H19: n.a. | I19: 97.335765 | J19: - | K19: - | L19: 64.837967 | M19: - | N19: -
B20: Banregio | C20: 15946.995 | D20: 17230.552 | E20: 17310.664 | F20: 1.3988878 | G20: 1.3078085 | H20: 1.3313555 | I20: 74.42838 | J20: 78.607662 | K20: 77.791167 | L20: 1.0411696 | M20: 1.0280377 | N20: 1.035677
B21: J.P. Morgan | C21: 0 | D21: 0 | E21: 0 | F21: n.a. | G21: n.a. | H21: n.a. | I21: - | J21: - | K21: - | L21: - | M21: - | N21: -
B22: Invex | C22: 61.029828 | D22: 55.146837 | E22: 54.175026 | F22: 0 | G22: 0 | H22: 0 | I22: - | J22: - | K22: - | L22: 0.13149799 | M22: 0.13192234 | N22: 0.13946463
B23: Multiva | C23: 438.74964 | D23: 432.46833 | E23: 431.94002 | F23: 75.690876 | G23: 66.274956 | H23: 66.300501 | I23: 97.101558 | J23: 98.781703 | K23: 98.770013 | L23: 73.49702 | M23: 65.46753 | N23: 65.485013
B24: BanCoppel | C24: 4440.5984 | D24: 4480.441 | E24: 4561.6395 | F24: 1.5453378 | G24: 4.0009283 | H24: 5.5331164 | I24: 163.15128 | J24: 94.151523 | K24: 71.843826 | L24: 2.5212383 | M24: 3.766935 | N24: 3.9752025
B25: Banca Mifel | C25: 18691.614 | D25: 17139.724 | E25: 17102.597 | F25: 6.2803247 | G25: 9.1817126 | H25: 9.5813417 | I25: 48.611955 | J25: 39.989067 | K25: 37.820146 | L25: 3.0529886 | M25: 3.6716812 | N25: 3.6236774
B26: Barclays | C26: 0 | D26: 0 | E26: 0 | F26: n.a. | G26: n.a. | H26: n.a. | I26: - | J26: - | K26: - | L26: - | M26: - | N26: -
B27: Banco Base | C27: 0 | D27: 0 | E27: 0 | F27: n.a. | G27: n.a. | H27: n.a. | I27: - | J27: - | K27: - | L27: - | M27: - | N27: -
B28: Sabadell | C28: 58.366391 | D28: 39.062637 | E28: 40.432741 | F28: 2.2072137 | G28: 0 | H28: 0 | I28: 38.293185 | J28: - | K28: - | L28: 0.84521244 | M28: 0.41588078 | N28: 0.55799086
B29: Bank of America | C29: 0 | D29: 0 | E29: 0 | F29: n.a. | G29: n.a. | H29: n.a. | I29: - | J29: - | K29: - | L29: - | M29: - | N29: -
B30: Ve por Más | C30: 11052.312 | D30: 10554.598 | E30: 10585.917 | F30: 0.86412856 | G30: 0.80415018 | H30: 0.79393052 | I30: 390.7543 | J30: 475.67016 | K30: 496.94809 | L30: 3.3766195 | M30: 3.8251024 | N30: 3.9454225
B31: Actinver | C31: 0 | D31: 0 | E31: 0 | F31: n.a. | G31: n.a. | H31: n.a. | I31: - | J31: - | K31: - | L31: - | M31: - | N31: -
B32: Bansí | C32: 17.526602 | D32: 15.109478 | E32: 12.82785 | F32: 19.785946 | G32: 22.8366 | H32: 26.898436 | I32: 30.358117 | J32: 35.770358 | K32: 38.27348 | L32: 6.0066406 | M32: 8.1687336 | N32: 10.294968
B33: Compartamos | C33: 0 | D33: 0 | E33: 0 | F33: n.a. | G33: n.a. | H33: n.a. | I33: - | J33: - | K33: - | L33: - | M33: - | N33: -
B34: BIAfirme | C34: 0 | D34: 0 | E34: 0 | F34: n.a. | G34: n.a. | H34: n.a. | I34: - | J34: - | K34: - | L34: - | M34: - | N34: -
B35: Bancrea | C35: 0 | D35: 0 | E35: 0 | F35: n.a. | G35: n.a. | H35: n.a. | I35: - | J35: - | K35: - | L35: - | M35: - | N35: -
B36: Kapital Bank | C36: 66.428864 | D36: 126.3893 | E36: 156.01743 | F36: 46.268052 | G36: 22.700401 | H36: 18.155 | I36: 25.417903 | J36: 52.009351 | K36: 52.681227 | L36: 11.760368 | M36: 11.806331 | N36: 9.5642766
B37: MUFG Bank | C37: 0 | D37: 0 | E37: 0 | F37: n.a. | G37: n.a. | H37: n.a. | I37: - | J37: - | K37: - | L37: - | M37: - | N37: -
B38: Consubanco | C38: 0 | D38: 0 | E38: 0 | F38: n.a. | G38: n.a. | H38: n.a. | I38: - | J38: - | K38: - | L38: - | M38: - | N38: -
B39: Bankaool | C39: 0 | D39: 0 | E39: 0 | F39: n.a. | G39: n.a. | H39: n.a. | I39: - | J39: - | K39: - | L39: - | M39: - | N39: -
B40: BNP Paribas México | C40: 0 | D40: 0 | E40: 0 | F40: n.a. | G40: n.a. | H40: n.a. | I40: - | J40: - | K40: - | L40: - | M40: - | N40: -
B41: Inmobiliario Mexicano | C41: 265.37974 | D41: 213.43295 | E41: 210.04215 | F41: 4.3398667 | G41: 1.4418774 | H41: 1.6214798 | I41: 47.522603 | J41: 50.112148 | K41: 45.996976 | L41: 2.0624176 | M41: 0.72255572 | N41: 0.74583166
B42: Mizuho Bank | C42: 0 | D42: 0 | E42: 0 | F42: n.a. | G42: n.a. | H42: n.a. | I42: - | J42: - | K42: - | L42: - | M42: - | N42: -
B43: ICBC | C43: 0 | D43: 0 | E43: 0 | F43: n.a. | G43: n.a. | H43: n.a. | I43: - | J43: - | K43: - | L43: - | M43: - | N43: -
B44: Openbank | C44: 0 | D44: 0 | E44: 0 | F44: n.a. | G44: n.a. | H44: n.a. | I44: - | J44: - | K44: - | L44: - | M44: - | N44: -
B45: Banco Covalto | C45: 0 | D45: 0 | E45: 0 | F45: n.a. | G45: n.a. | H45: n.a. | I45: - | J45: - | K45: - | L45: - | M45: - | N45: -
B46: Volkswagen Bank | C46: 0 | D46: 0 | E46: 0 | F46: n.a. | G46: n.a. | H46: n.a. | I46: - | J46: - | K46: - | L46: - | M46: - | N46: -
B47: Banco S3 | C47: 0 | D47: 0 | E47: 0 | F47: n.a. | G47: n.a. | H47: n.a. | I47: - | J47: - | K47: - | L47: - | M47: - | N47: -
B48: Bank of China | C48: 0 | D48: 0 | E48: 0 | F48: n.a. | G48: n.a. | H48: n.a. | I48: - | J48: - | K48: - | L48: - | M48: - | N48: -
B49: Shinhan | C49: 0 | D49: 0 | E49: 0 | F49: n.a. | G49: n.a. | H49: n.a. | I49: - | J49: - | K49: - | L49: - | M49: - | N49: -
B50: Banco Ualá | C50: 18.466613 | D50: 17.774698 | E50: 17.680898 | F50: 0 | G50: 7.5867337 | H50: 7.7440976 | I50: - | J50: 11.203253 | K50: 11.158348 | L50: 0.22481654 | M50: 0.849961 | N50: 0.86411335
B51: KEB Hana México | C51: 0 | D51: 0 | E51: 0 | F51: n.a. | G51: n.a. | H51: n.a. | I51: - | J51: - | K51: - | L51: - | M51: - | N51: -
B52: Banco Bineo | C52: 0 | D52: 0 | E52: 0 | F52: n.a. | G52: n.a. | H52: n.a. | I52: - | J52: - | K52: - | L52: - | M52: - | N52: -
B53: Dondé Banco | C53: 0 | D53: 0 | E53: 0 | F53: n.a. | G53: n.a. | H53: n.a. | I53: - | J53: - | K53: - | L53: - | M53: - | N53: -
B54: Credit Suisse | C54: 0 | D54: 0 | E54: 0 | F54: n.a. | G54: n.a. | H54: n.a. | I54: - | J54: - | K54: - | L54: - | M54: - | N54: -
B55: Hey Banco | C55: 0 | D55: 0 | E55: 0 | F55: n.a. | G55: n.a. | H55: n.a. | I55: - | J55: - | K55: - | L55: - | M55: - | N55: -
B56: Forjadores | C56: 0 | D56: 0 | E56: 0 | F56: n.a. | G56: n.a. | H56: n.a. | I56: - | J56: - | K56: - | L56: - | M56: - | N56: -
B57: Pagatodo | C57: 0 | D57: 0 | E57: 0 | F57: n.a. | G57: n.a. | H57: n.a. | I57: - | J57: - | K57: - | L57: - | M57: - | N57: -
B58: CIBanco | C58: 976.01339 | D58: 676.486 | E58: 0 | F58: 0.23516757 | G58: 23.238636 | H58: n.a. | I58: 446.02227 | J58: 25.689413 | K58: - | L58: 1.0488997 | M58: 5.9698691 | N58: -
B59: Intercam Banco | C59: 0 | D59: 0 | E59: 0 | F59: n.a. | G59: n.a. | H59: n.a. | I59: - | J59: - | K59: - | L59: - | M59: - | N59: -
B61: n.a. No aplica

Sheet CaptRec
B2: Saldos de la captación bancaria
B3: Millones de pesos
C5: Captación total | F5: Depósitos exigibilidad inmediata | I5: Depósitos a plazo público en general | L5: Depósitos a plazo mercado de dinero | O5: Títulos de crédito | R5: Préstamos interbancarios y otros | U5: Cuenta global de captación sin movimientos
C6: 45536 | D6: 45870 | E6: 45901 | F6: =C6 -> 45536 | G6: =D6 -> 45870 | H6: =E6 -> 45901 | I6: =C6 -> 45536 | J6: =D6 -> 45870 | K6: =E6 -> 45901 | L6: =C6 -> 45536 | M6: =D6 -> 45870 | N6: =E6 -> 45901 | O6: =C6 -> 45536 | P6: =D6 -> 45870 | Q6: =E6 -> 45901 | R6: =C6 -> 45536 | S6: =D6 -> 45870 | T6: =E6 -> 45901 | U6: =C6 -> 45536 | V6: =D6 -> 45870 | W6: =E6 -> 45901
B7: Sistema */ | C7: 8520586.9 | D7: 9233014.2 | E7: 9133939.5 | F7: 5364467.3 | G7: 5794950.2 | H7: 5748599 | I7: 2034454 | J7: 2103129.1 | K7: 2106292.5 | L7: 343373.17 | M7: 505936.77 | N7: 448271.83 | O7: 372417.51 | P7: 362862.96 | Q7: 377657.77 | R7: 378597.35 | S7: 436091.77 | T7: 422870.34 | U7: 27277.547 | V7: 30043.39 | W7: 30248.118
B8: BBVA México | C8: 1887722.9 | D8: 2053500.3 | E8: 2096776.8 | F8: 1457335.6 | G8: 1550178.2 | H8: 1584471.8 | I8: 260082.65 | J8: 299998.05 | K8: 302628.81 | L8: 21393.459 | M8: 28969.2 | N8: 26659.434 | O8: 118811.91 | P8: 150219.39 | Q8: 158002.9 | R8: 23222.921 | S8: 16549.136 | T8: 17412.577 | U8: 6876.334 | V8: 7586.2688 | W8: 7601.3089
B9: Santander | C9: 1033043.4 | D9: 1104934 | E9: 1066511.5 | F9: 584870.75 | G9: 663239.63 | H9: 625735.69 | I9: 259069.92 | J9: 272648.67 | K9: 270206.33 | L9: 53251.707 | M9: 62050.963 | N9: 63039.227 | O9: 84297.305 | P9: 65677.243 | Q9: 65523.392 | R9: 48875.78 | S9: 38606.444 | T9: 39128.414 | U9: 2677.9832 | V9: 2711.07 | W9: 2878.432
B10: Banorte | C10: 1154816.9 | D10: 1193359.6 | E10: 1180061.8 | F10: 713036.8 | G10: 774270.17 | H10: 755897.16 | I10: 372290.72 | J10: 373200.56 | K10: 378528.31 | L10: 3905.2332 | M10: 1999.6983 | N10: 1841.0087 | O10: 48769.469 | P10: 31898.653 | Q10: 32010.613 | R10: 12891.688 | S10: 7530.1051 | T10: 7344.8886 | U10: 3923.0397 | V10: 4460.4155 | W10: 4439.8782
B11: Banamex | C11: 965592.75 | D11: 773161.3 | E11: 764231.24 | F11: 724510.64 | G11: 535793.15 | H11: 525622.68 | I11: 116345.09 | J11: 118824.2 | K11: 118892.43 | L11: 105527.99 | M11: 90941.379 | N11: 92136.432 | O11: 4345.1708 | P11: 0 | Q11: 0 | R11: 6608.1145 | S11: 18817.975 | T11: 18725.344 | U11: 8255.75 | V11: 8784.5899 | W11: 8854.3519
B12: HSBC | C12: 579365.66 | D12: 560878.44 | E12: 541428.01 | F12: 366432.45 | G12: 365953.1 | H12: 347764.89 | I12: 161535.72 | J12: 154290.98 | K12: 153123.04 | L12: 16288.367 | M12: 9343.5931 | N12: 9347.7264 | O12: 19279.785 | P12: 19128.51 | Q12: 19030.877 | R12: 13677.027 | S12: 9486.277 | T12: 9457.7021 | U12: 2152.3125 | V12: 2675.9838 | W12: 2703.7652
B13: Scotiabank | C13: 594724.43 | D13: 591248.14 | E13: 589538.92 | F13: 290789.92 | G13: 293570.23 | H13: 289209.91 | I13: 207582.9 | J13: 189826.92 | K13: 184860.22 | L13: 25263.235 | M13: 31315.978 | N13: 32432.924 | O13: 29349.904 | P13: 30682.468 | Q13: 36501.405 | R13: 40269.152 | S13: 44201.874 | T13: 44865.149 | U13: 1469.3252 | V13: 1650.6622 | W13: 1669.3185
B14: Inbursa | C14: 421058.22 | D14: 466616.41 | E14: 466402.17 | F14: 305691.67 | G14: 352020.94 | H14: 353137.35 | I14: 51188.578 | J14: 55323.381 | K14: 56432.27 | L14: 1802.6 | M14: 1890.6035 | N14: 6.755532 | O14: 32033.331 | P14: 24740.727 | Q14: 24576.416 | R14: 29875.607 | S14: 32157.864 | T14: 31757.704 | U14: 466.44058 | V14: 482.89053 | W14: 491.6777
B15: Citi México | C15: 109.53043 | D15: 334183.09 | E15: 338381.49 | F15: 109.53043 | G15: 209529.04 | H15: 211538.63 | I15: 0 | J15: 0 | K15: 0 | L15: 0 | M15: 65566.043 | N15: 78009.127 | O15: 0 | P15: 2784.0329 | Q15: 2779.6078 | R15: 0 | S15: 56263.023 | T15: 46012.732 | U15: 0 | V15: 40.951594 | W15: 41.384224
B16: Banco del Bajío | C16: 287440.56 | D16: 316482.61 | E16: 318804.45 | F16: 116638.24 | G16: 138995.68 | H16: 140601.15 | I16: 70830.535 | J16: 81038.97 | K16: 80470.669 | L16: 53714.225 | M16: 51956.829 | N16: 53084.423 | O16: 0 | P16: 0 | Q16: 0 | R16: 46040.231 | S16: 44288.78 | T16: 44447.251 | U16: 217.32714 | V16: 202.35661 | W16: 200.95044
B17: Banco Azteca | C17: 222874.58 | D17: 247637.47 | E17: 240763.79 | F17: 170374.81 | G17: 192292.94 | H17: 185862.64 | I17: 52199.69 | J17: 55344.53 | K17: 54901.149 | L17: 0 | M17: 0 | N17: 0 | O17: 0 | P17: 0 | Q17: 0 | R17: 300.08708 | S17: 0 | T17: 0 | U17: 0 | V17: 0 | W17: 0
