Workbook
Name \a: #REF!
Name \a: #REF!
Name \a: #REF!
Name \a: #REF!
Name \a: #REF!
Name \a: #REF!
Name \a: #REF!
Name \a: #REF!
Name \a: #REF!
Name \a: #REF!
Name \a: #REF!
Name \a: #REF!
Name \a: #REF!
Name \a: #REF!
Name \a: #REF!
Name \a: #REF!
Name \a: #REF!
Name \a: #REF!
Name \a: #REF!
Name \a: #REF!
Name \a: #REF!
Name \a: #REF!
Name \a: #REF!
Name \a: #REF!
Name \a: #REF!
Name \a: #REF!
Name \s: #REF!
Name \s: #REF!
Name \s: #REF!
Name \s: #REF!
Name \s: #REF!
Name \s: #REF!
Name \s: #REF!
Name \s: #REF!
Name \s: #REF!
Name \s: #REF!
Name \s: #REF!
Name \s: #REF!
Name \s: #REF!
Name \s: #REF!
Name \s: #REF!
Name \s: #REF!
Name \s: #REF!
Name \s: #REF!
Name \s: #REF!
Name \s: #REF!
Name \s: #REF!
Name a: #REF!
Name a: #REF!
Name a: #REF!
Name a: #REF!
Name a: #REF!
Name a: #REF!
Name a: #REF!
Name a: #REF!
Name a: #REF!
Name a: #REF!
Name a: #REF!
Name a: #REF!
Name a: #REF!

Sheet Portada
C33: ='Pm2'!G6 -> 45839
C34: =PROPER(TEXT(C33,"Mmmm"))& " de " & PROPER(TEXT(C33,"aaa")) -> Julio de 2025

Sheet Nota
B4: La presente información corresponde a la que, en cumplimiento a las Disposiciones aplicables a cada sector, entregan las entidades supervisadas a la CNBV a través de los reportes regulatorios debiéndose asegurar que la misma sea completa, correcta, precisa, integra, confiable y oportuna. Es importante mencionar, como lo indican las propias Disposiciones, que dicha información debe cumplir con las validaciones establecidas en el Sistema Interinstitucional de Transferencia de Información, así como los estándares de calidad que indique la Comisión a través de dicho sistema, además debe existir consistencia entre la información que las entidades incluyan en uno o más reportes regulatorios, aunque se encuentre con un nivel distinto de integración, por lo que puede ser modificada derivado de las revisiones internas que se hagan a la misma. Por lo anterior se informa que la presente publicación se genera con la información con la que se cuenta al momento de su elaboración, se recomienda su uso tomando en cuenta los aspectos anteriormente descritos.
B6: Consideraciones sobre los criterios para integrar los estados financieros del sector de Banca Múltiple a partir de enero de 2022. El 13 de marzo de 2020 se publicó en el Diario Oficial de la Federación la resolución que modificó las Disposiciones de carácter general aplicables a las instituciones de crédito (Disposiciones), la cual incorporó las nuevas normas de información emitidas por el Consejo Mexicano de Normas de Información Financiera A.C., mismas que serían exigibles a partir del 1 de enero de 2021; sin embargo, su entrada en vigor se aplazó hasta el 1 de enero de 2022, mediante la resolución modificatoria publicada en el Diario Oficial de la Federación el 4 de diciembre de 2020. En la resolución modificatoria del 4 de diciembre, se indica que los estados financieros básicos consolidados trimestrales y anuales requeridos a las instituciones de conformidad con las disposiciones señaladas correspondientes al periodo concluido el 31 de diciembre de 2022, no deberán presentarse comparativos con cada trimestre del ejercicio 2021 y por el periodo terminado el 31 de diciembre de 2021. La información del comunicado de prensa de Banca Múltiple se puede consultar en https://www.cnbv.gob.mx/PRENSA/Paginas/Boletines-de-Prensa.aspx Para la información financiera histórica se recomienda utilizar los reportes publicados en el Portafolio de Información. Para consultar las cifras bajo la norma internacional de información financiera 9 “Instrumentos Financieros” (IFRS 9), dirigirse a la sección de IFRS 9 del Portafolio Consultas.
B11: El presente Boletín Estadístico se elaboró por personal de la Comisión Nacional Bancaria y de Valores (CNBV) con la información correspondiente a julio de 2025 contenida en los reportes regulatorios que las entidades supervisadas envían a esta Comisión, la cual estuvo disponible a partir del 20 de agosto de 2025.
B13: Las cifras aquí contenidas no se actualizan en el tiempo, por lo que para consultar series históricas se recomienda utilizar los reportes publicados en el Portafolio de Información.
B15: Al cierre de julio de 2025, el sector de Banca Múltiple estuvo integrado por 52 instituciones en operación, dos más que el año anterior, considerando el inicio de operaciones de; Openbank México, S.A., Institución de Banca Múltiple, Grupo Financiero Santander México el 19 de noviembre de 2024 y de Hey Banco, S.A. Institución de Banca Múltiple, Banregio Grupo Financiero el 12 de febrero de 2025.
B17: Mediante oficio con fecha del 24 de septiembre de 2024 se aprobó el cambio de denominación de CBM Banco, S.A., Institución de Banca Múltiple, Integrante del Grupo Financiero Citibanamex a Banco Citi México, S.A., Institución de Banca Múltiple, Grupo Financiero Citi México, en el presente Boletin estadístico (Citi México). Mediante oficio con fecha del 24 de septiembre de 2024 se aprobó el cambio de denominación de ABC Capital, S.A., Institución de Banca Múltiple (ABC Capital) a Ualá, S.A., Institución de Banca Múltiple, en el presente Boletín estadístico (Banco Ualá).
B19: El 1 de diciembre de 2024 Citigroup (Citigroup Inc.) concretó la separación del negocio de banca corporativa y privada de los negocios de consumo y banca empresarial. A partir de esa fecha, Citi opera en México a través de dos grupos financieros separados e independientes: Grupo Financiero Banamex y Grupo Financiero Citi México; por lo anterior, Citi gestionará el negocio de banca corporativa y privada (cartera comercial) y Banamex llevará el negocio de consumo y la banca empresarial (cartera comercial, de consumo y a la vivienda).
B21: El 18 de diciembre de 2024 se le notifica a Banco Sabadell, S.A., Institución de Banca Múltiple, que podrá llevar a cabo la fusión con Sabcapital, S.A. de C.V., Sociedad Financiera de Objeto Múltiple, Entidad Regulada, como sociedad fusionada, a partir de enero de 2025.

Sheet Índice
B4: Índice
B5: Presentación
B7: I. Índice de Capitalización y Evaluación de la Calidad de la Información
B8: Artículo 121 Ley de Instituciones de Crédito
B9: Metodología de Evaluación Sistema Financiero
B10: Metodología Evaluación Cartera Comercial
B11: Metodología Evaluación Cartera a la Vivienda
B12: Evaluación de Calidad a la Información
B14: II. Estadísticas de la Banca Múltiple
B15: Principales Rubros del Estado de Situación Financiera y Estado de Resultado Integral
B16: Indicadores Financieros
B17: Cartera de Crédito Total
... B36: III. Estados Financieros

Sheet Presentación
A2: Presentación
A3: La Comisión Nacional Bancaria y de Valores (CNBV) emite el presente documento para cumplir con lo dispuesto por la fracción XXIII del Artículo 4º de la Ley de la Comisión Nacional Bancaria y de Valores. Mediante la difusión de este boletín estadístico se persigue promover la transparencia y autorregulación del sector de Banca Múltiple, así como proveer a los mercados y al público en general información suficiente y confiable, que permita el análisis y seguimiento de estas instituciones.
A4: El boletín estadístico se encuentra dividido en 3 secciones: En primer lugar se informa sobre el nivel del Índice de Capitalización de las instituciones y su correspondiente categoría de Alertas Tempranas. Además, se presenta la tabla de Evaluación de la Calidad y Oportunidad de la Información con el que se califica el envío de los reportes regulatorios que las entidades supervisadas entregan a este organismo.
A5: En segundo lugar se muestra la información estadística relevante y principales indicadores de rentabilidad de cada institución de banca múltiple que proviene o se calcula con sus estados financieros consolidados.
A6: Enseguida se presenta la información reportada por las 52 instituciones de banca múltiple en operación correspondiente a julio de 2025, consolidada con la de sus SOFOMER (Sociedades Financieras de Objeto Múltiple, Entidades Reguladas) en el caso de los siguientes bancos: Banamex con Tarjetas Banamex; Santander con Santander Inclusión Financiera; CI Banco con Finanmadrid México; Banco del Bajío con Financiera Bajío; Banregio con Start Banregio; Inbursa con STM Financial, SOFOM Inbursa y CETELEM Inbursa; Afirme con Arrendadora Afirme; Banco Base con Arrendadora Base, Invex con Invex Consumo; Bancrea con Arrendadora Bancrea, así como Ve por Más con Arrendadora Ve por Más.
A7: Se incluyen los indicadores financieros destacados, los saldos de cada tipo de crédito y de la captación de recursos.
A8: Por último, se hace un compendio de los estados financieros que las instituciones de banca múltiple reportaron a esta Comisión, al igual que en las secciones anteriores, se incluye información consolidada de las instituciones de banca múltiple con las SOFOMER de cada banco.

Sheet Art_121
B4: REGLAS DE CARÁCTER GENERAL A QUE SE REFIERE EL ARTÍCULO 121 DE LA LEY DE INSTITUCIONES DE CRÉDITO.
B5: Con el fin de mantener informado al público sobre el desempeño de las instituciones que conforman al sector de banca múltiple, la CNBV con fundamento en lo dispuesto en el artículo 121 de la Ley de Instituciones de Crédito, en relación con los artículos 220 y 221 de las Disposiciones de carácter general aplicables a las instituciones de crédito (las Disposiciones), da a conocer la clasificación de las instituciones de banca múltiple en categorías, con base en el índice de capitalización requerido conforme a las disposiciones aplicables a los requerimientos de capitalización, emitidas por esta Comisión en términos del artículo 50 de la Ley de Instituciones de Crédito
B6: CLASIFICACIÓN DE LAS INSTITUCIONES DE BANCA MÚLTIPLE DE ACUERDO CON EL ARTÍCULO 220 DE LAS DISPOSICIONES
B7: INDICADORES DE CAPITALIZACIÓN CIFRAS AL 30 DE JUNIO DE 20251/
B8: Institución | C8: CCB 2/ % | D8: CCF 3/ % | E8: ICAP 4/ % | F8: Categoría 5/
B9: Actinver | C9: 18.227443 | D9: 18.227443 | E9: 18.227443 | F9: I
B10: Afirme | C10: 11.278408 | D10: 10.256816 | E10: 15.174032 | F10: I
B11: Autofin | C11: 13.227801 | D11: 13.227801 | E11: 13.227801 | F11: I
B12: Banamex | C12: 21.043783 | D12: 17.878001 | E12: 21.043783 | F12: I
B13: Banca Mifel | C13: 16.491486 | D13: 16.491486 | E13: 16.608245 | F13: I
B14: Banco Azteca | C14: 14.179915 | D14: 14.179915 | E14: 14.708639 | F14: I
B15: Banco Base | C15: 21.307347 | D15: 21.307347 | E15: 21.307347 | F15: I
B16: Banco Bineo | C16: 277.54151 | D16: 277.54151 | E16: 277.54151 | F16: I
B17: Banco Covalto | C17: 13.11962 | D17: 13.11962 | E17: 13.11962 | F17: I
B18: Banco del Bajío | C18: 14.288591 | D18: 14.288591 | E18: 14.525604 | F18: I
B19: Banco S3 | C19: 186.31448 | D19: 186.31448 | E19: 186.31448 | F19: I
B20: Banco Ualá | C20: 44.784858 | D20: 44.784858 | E20: 44.784858 | F20: I
... B60: Volkswagen Bank | C60: 27.47016 | D60: 27.47016 | E60: 27.47016 | F60: I
B61: Total Banca Múltiple | C61: 17.9131 | D61: 16.5832 | E61: 20.0006
B62: 1/ Dado a conocer a esta Comisión por el Banco de México el 12 de agosto de 2025, con base en la información entregada por las Instituciones, conforme a lo dispuesto por el artículo 2 Bis y 2 Bis 4 de las Disposiciones.
B63: 2/ CCB (Coeficiente de Capital Básico) = (Capital Fundamental + Capital no Fundamental) / Activos Ponderados Sujetos a Riesgo Total.
B64: 3/ CCF (Coeficiente de Capital Fundamental) = Capital Fundamental / Activos Ponderados Sujetos a Riesgo Total.
B65: 4/ ICAP (Índice de Capitalización) = Capital Neto / Activos Ponderados Sujetos a Riesgo Total.
B66: 5/ Categorías de Alertas Tempranas determinadas con base en el artículo 220 de las Disposiciones.

Sheet Ficha Técnica
B11: Evaluación de la Calidad de la Información
B12: Banca Múltiple
B14: Derivado de la mejora continua en los procesos de verificación de la calidad en la información, esta comisión ha modificado los criterios de evaluación de la calidad y los hábitos de envío de los reportes regulatorios que son transmitidos por las Instituciones de Banca Múltiple, por lo cual, se ha optado por generar un indicador único de calidad que refleje el estado actual obtenido para los reportes regulatorios, clasificados en 5 tipos de información distintos:
B20: Clave | C20: Clasificación | E20: Reportes | F20: Descripción
B21: 1 | C21: Situación financiera | E21: 22 | F21: Reportes de las series R01, R04 A, R06, R07, R08, R10, R12 , R13, R14, R32, R34 y R36.
B22: 2 | C22: Cartera Comercial | E22: 11 | F22: Reportes de la serie R04 C.
B23: 3 | C23: Cartera a la Vivienda | E23: 4 | F23: Reportes de la serie R04 H.
B24: 4 | C24: Captación | E24: 1 | F24: Reporte R24 B-2421.
B25: 5 | C25: Operativos | E25: 23 | F25: Reportes de las series R15, R24 B-2422, R24 B-2423, R24 C, R24 D, R24 E, R26, R27, R28, R29 y R35.
B27: Tomando en consideración la anterior clasificación, se generan 2 métricas para el cálculo del indicador único, como a continuación se muestra:
B30: 1. Calidad
B32: Para la medición del porcentaje de calidad obtenido, se identifican las incidencias presentadas en la ventana de evaluación del periodo, estas incidencias tienen ponderadores específicos para cada IBM, los cuáles se calculan a través de la distribución de sus errores presentados de manera histórica y se omiten aquellos reportes que por la naturaleza de su negocio no le son aplicables a cada IBM.
B37: 2. Oportunidad 1/
B39: Para la evaluación de hábitos de envío se consideran 3 conductas que no son adecuadas, siendo estas, los reenvíos, entregas extemporáneas y reportes omisos a la fecha de corte y que se encuentren en la ventana de evaluación. De igual forma se ponderan en la ventana de evaluación en función del comportamiento histórico y se ponderan de diferente forma en función del porcentaje de calidad obtenido.
B43: 2. Calificación final
B45: Tomando en consideración las 2 calificaciones previas, se determina una calificación final, la cual servirá como indicador general de evaluación para las IBM, el cual se calcula multiplicando el porcentaje de calidad obtenido por el porcentaje de oportunidad.
B50: Determinación de semáforos
B52: La determinación de semáforos se realiza con base en los siguientes criterios:
B54: Rojo | D54: Se asigna para instituciones que tienen una calificación final inferior a 90 puntos.
B56: Amarillo | D56: Se asigna para las instituciones que tienen una calificación de 90 o más y menor de 95 puntos.
B58: Verde | D58: Se asigna para las instituciones con 95 puntos o más.
B60: 1/ Debido a las intermitencias en el aplicativo SITI WEB, que han ocasionado retrasos involuntarios en la recepción de los Reportes Regulatorios transmitidos a la CNBV, la calificación no penaliza los hábitos de envío desde diciembre de 2023 hasta la fecha.

Sheet Evaluación Calidad
B7: Evaluación de la Calidad de la Información
B8: Banca Múltiple
B9: julio 2025
J10: Fecha de corte: 20 de agosto de 2025
B11: RANKING | C11: INSTITUCIÓN | G11: CALIFICACIÓN | J11: CALIDAD | K11: OPORTUNIDAD
B12: 1 | C12: 040002 | D12: Banamex | G12: 100 | H12: 100 | J12: 100 | K12: 100
B13: 1 | C13: 040126 | D13: Credit Suisse | G13: 100 | H13: 100 | J13: 100 | K13: 100
B14: 1 | C14: 040139 | D14: BIAfirme | G14: 100 | H14: 100 | J14: 100 | K14: 100
B15: 1 | C15: 040162 | D15: KEB Hana México | G15: 100 | H15: 100 | J15: 100 | K15: 100
B16: 1 | C16: 040165 | D16: Banco Bineo | G16: 100 | H16: 100 | J16: 100 | K16: 100
B17: 6 | C17: 040030 | D17: Banco del Bajío | G17: 99.86 | H17: 99.86 | J17: 99.86 | K17: 100
B18: 7 | C18: 040169 | D18: Openbank | G18: 99.84 | H18: 99.84 | J18: 99.84 | K18: 100
B19: 8 | C19: 040108 | D19: MUFG Bank | G19: 99.71 | H19: 99.71 | J19: 99.71 | K19: 100
B20: 8 | C20: 040151 | D20: Dondé Banco | G20: 99.71 | H20: 99.71 | J20: 99.71 | K20: 100
B21: 10 | C21: 040129 | D21: Barclays | G21: 99.56 | H21: 99.56 | J21: 99.56 | K21: 100
B22: 11 | C22: 040147 | D22: Bankaool | G22: 99.43 | H22: 99.43 | J22: 99.43 | K22: 100
B23: 12 | C23: 040159 | D23: Bank of China | G23: 99.42 | H23: 99.42 | J23: 99.42 | K23: 100
... B63: 52 | C63: 040136 | D63: Intercam Banco | G63: 77.4 | H63: 77.4 | J63: 77.4 | K63: 100
B101: =_xlfn.XLOOKUP(C101,[1]Calificación!D:D,[1]Calificación!A:A,"",0,1) | C101: =IF([1]Calificación!D88=0,"",[1]Calificación!D88) | D101: =IFERROR(VLOOKUP(C101,[1]Calificación!$D$1:$X$53,2,0),"") | G101: =IFERROR(VLOOKUP(C101,[1]Calificación!$D$1:$X$53,5,0),"") | H101: =IFERROR(VLOOKUP(C101,[1]Calificación!$D$1:$X$53,6,0),"") | J101: =IFERROR(VLOOKUP(C101,[1]Calificación!$D$1:$X$53,3,0),"") | K101: =IFERROR(VLOOKUP(C101,[1]Calificación!$D$1:$X$53,4,0),"")
B102: =_xlfn.XLOOKUP(C102,[1]Calificación!D:D,[1]Calificación!A:A,"",0,1) | C102: =IF([1]Calificación!D89=0,"",[1]Calificación!D89) | D102: =IFERROR(VLOOKUP(C102,[1]Calificación!$D$1:$X$53,2,0),"") | G102: =IFERROR(VLOOKUP(C102,[1]Calificación!$D$1:$X$53,5,0),"") | H102: =IFERROR(VLOOKUP(C102,[1]Calificación!$D$1:$X$53,6,0),"") | J102: =IFERROR(VLOOKUP(C102,[1]Calificación!$D$1:$X$53,3,0),"") | K102: =IFERROR(VLOOKUP(C102,[1]Calificación!$D$1:$X$53,4,0),"")
B103: =_xlfn.XLOOKUP(C103,[1]Calificación!D:D,[1]Calificación!A:A,"",0,1) | C103: =IF([1]Calificación!D90=0,"",[1]Calificación!D90) | D103: =IFERROR(VLOOKUP(C103,[1]Calificación!$D$1:$X$53,2,0),"") | G103: =IFERROR(VLOOKUP(C103,[1]Calificación!$D$1:$X$53,5,0),"") | H103: =IFERROR(VLOOKUP(C103,[1]Calificación!$D$1:$X$53,6,0),"") | J103: =IFERROR(VLOOKUP(C103,[1]Calificación!$D$1:$X$53,3,0),"") | K103: =IFERROR(VLOOKUP(C103,[1]Calificación!$D$1:$X$53,4,0),"")
B104: =_xlfn.XLOOKUP(C104,[1]Calificación!D:D,[1]Calificación!A:A,"",0,1) | C104: =IF([1]Calificación!D91=0,"",[1]Calificación!D91) | D104: =IFERROR(VLOOKUP(C104,[1]Calificación!$D$1:$X$53,2,0),"") | G104: =IFERROR(VLOOKUP(C104,[1]Calificación!$D$1:$X$53,5,0),"") | H104: =IFERROR(VLOOKUP(C104,[1]Calificación!$D$1:$X$53,6,0),"") | J104: =IFERROR(VLOOKUP(C104,[1]Calificación!$D$1:$X$53,3,0),"") | K104: =IFERROR(VLOOKUP(C104,[1]Calificación!$D$1:$X$53,4,0),"")
B105: =_xlfn.XLOOKUP(C105,[1]Calificación!D:D,[1]Calificación!A:A,"",0,1) | C105: =IF([1]Calificación!D92=0,"",[1]Calificación!D92) | D105: =IFERROR(VLOOKUP(C105,[1]Calificación!$D$1:$X$53,2,0),"") | G105: =IFERROR(VLOOKUP(C105,[1]Calificación!$D$1:$X$53,5,0),"") | H105: =IFERROR(VLOOKUP(C105,[1]Calificación!$D$1:$X$53,6,0),"") | J105: =IFERROR(VLOOKUP(C105,[1]Calificación!$D$1:$X$53,3,0),"") | K105: =IFERROR(VLOOKUP(C105,[1]Calificación!$D$1:$X$53,4,0),"")
B106: =_xlfn.XLOOKUP(C106,[1]Calificación!D:D,[1]Calificación!A:A,"",0,1) | C106: =IF([1]Calificación!D93=0,"",[1]Calificación!D93) | D106: =IFERROR(VLOOKUP(C106,[1]Calificación!$D$1:$X$53,2,0),"") | G106: =IFERROR(VLOOKUP(C106,[1]Calificación!$D$1:$X$53,5,0),"") | H106: =IFERROR(VLOOKUP(C106,[1]Calificación!$D$1:$X$53,6,0),"") | J106: =IFERROR(VLOOKUP(C106,[1]Calificación!$D$1:$X$53,3,0),"") | K106: =IFERROR(VLOOKUP(C106,[1]Calificación!$D$1:$X$53,4,0),"")
B107: =_xlfn.XLOOKUP(C107,[1]Calificación!D:D,[1]Calificación!A:A,"",0,1) | C107: =IF([1]Calificación!D94=0,"",[1]Calificación!D94) | D107: =IFERROR(VLOOKUP(C107,[1]Calificación!$D$1:$X$53,2,0),"") | G107: =IFERROR(VLOOKUP(C107,[1]Calificación!$D$1:$X$53,5,0),"") | H107: =IFERROR(VLOOKUP(C107,[1]Calificación!$D$1:$X$53,6,0),"") | J107: =IFERROR(VLOOKUP(C107,[1]Calificación!$D$1:$X$53,3,0),"") | K107: =IFERROR(VLOOKUP(C107,[1]Calificación!$D$1:$X$53,4,0),"")
B108: =_xlfn.XLOOKUP(C108,[1]Calificación!D:D,[1]Calificación!A:A,"",0,1) | C108: =IF([1]Calificación!D95=0,"",[1]Calificación!D95) | D108: =IFERROR(VLOOKUP(C108,[1]Calificación!$D$1:$X$53,2,0),"") | G108: =IFERROR(VLOOKUP(C108,[1]Calificación!$D$1:$X$53,5,0),"") | H108: =IFERROR(VLOOKUP(C108,[1]Calificación!$D$1:$X$53,6,0),"") | J108: =IFERROR(VLOOKUP(C108,[1]Calificación!$D$1:$X$53,3,0),"") | K108: =IFERROR(VLOOKUP(C108,[1]Calificación!$D$1:$X$53,4,0),"")
B109: =_xlfn.XLOOKUP(C109,[1]Calificación!D:D,[1]Calificación!A:A,"",0,1) | C109: =IF([1]Calificación!D96=0,"",[1]Calificación!D96) | D109: =IFERROR(VLOOKUP(C109,[1]Calificación!$D$1:$X$53,2,0),"") | G109: =IFERROR(VLOOKUP(C109,[1]Calificación!$D$1:$X$53,5,0),"") | H109: =IFERROR(VLOOKUP(C109,[1]Calificación!$D$1:$X$53,6,0),"") | J109: =IFERROR(VLOOKUP(C109,[1]Calificación!$D$1:$X$53,3,0),"") | K109: =IFERROR(VLOOKUP(C109,[1]Calificación!$D$1:$X$53,4,0),"")
B110: =_xlfn.XLOOKUP(C110,[1]Calificación!D:D,[1]Calificación!A:A,"",0,1) | C110: =IF([1]Calificación!D97=0,"",[1]Calificación!D97) | D110: =IFERROR(VLOOKUP(C110,[1]Calificación!$D$1:$X$53,2,0),"") | G110: =IFERROR(VLOOKUP(C110,[1]Calificación!$D$1:$X$53,5,0),"") | H110: =IFERROR(VLOOKUP(C110,[1]Calificación!$D$1:$X$53,6,0),"") | J110: =IFERROR(VLOOKUP(C110,[1]Calificación!$D$1:$X$53,3,0),"") | K110: =IFERROR(VLOOKUP(C110,[1]Calificación!$D$1:$X$53,4,0),"")
B111: =_xlfn.XLOOKUP(C111,[1]Calificación!D:D,[1]Calificación!A:A,"",0,1) | C111: =IF([1]Calificación!D98=0,"",[1]Calificación!D98) | D111: =IFERROR(VLOOKUP(C111,[1]Calificación!$D$1:$X$53,2,0),"") | G111: =IFERROR(VLOOKUP(C111,[1]Calificación!$D$1:$X$53,5,0),"") | H111: =IFERROR(VLOOKUP(C111,[1]Calificación!$D$1:$X$53,6,0),"") | J111: =IFERROR(VLOOKUP(C111,[1]Calificación!$D$1:$X$53,3,0),"") | K111: =IFERROR(VLOOKUP(C111,[1]Calificación!$D$1:$X$53,4,0),"")
B112: =_xlfn.XLOOKUP(C112,[1]Calificación!D:D,[1]Calificación!A:A,"",0,1) | C112: =IF([1]Calificación!D99=0,"",[1]Calificación!D99) | D112: =IFERROR(VLOOKUP(C112,[1]Calificación!$D$1:$X$53,2,0),"") | G112: =IFERROR(VLOOKUP(C112,[1]Calificación!$D$1:$X$53,5,0),"") | H112: =IFERROR(VLOOKUP(C112,[1]Calificación!$D$1:$X$53,6,0),"") | J112: =IFERROR(VLOOKUP(C112,[1]Calificación!$D$1:$X$53,3,0),"") | K112: =IFERROR(VLOOKUP(C112,[1]Calificación!$D$1:$X$53,4,0),"")
... B133: =_xlfn.XLOOKUP(C133,[1]Calificación!D:D,[1]Calificación!A:A,"",0,1) | C133: =IF([1]Calificación!D120=0,"",[1]Calificación!D120) | D133: =IFERROR(VLOOKUP(C133,[1]Calificación!$D$1:$X$53,2,0),"") | G133: =IFERROR(VLOOKUP(C133,[1]Calificación!$D$1:$X$53,5,0),"") | H133: =IFERROR(VLOOKUP(C133,[1]Calificación!$D$1:$X$53,6,0),"") | J133: =IFERROR(VLOOKUP(C133,[1]Calificación!$D$1:$X$53,3,0),"") | K133: =IFERROR(VLOOKUP(C133,[1]Calificación!$D$1:$X$53,4,0),"")

Sheet Evaluación Calidad Grupos
B7: Evaluación de la Calidad de la Información
B8: Banca Múltiple
B9: julio 2025
K10: Fecha de corte: 20 de agosto de 2025
B11: RANKING | C11: INSTITUCIÓN | G11: CALIFICACIÓN | K11: CALIDAD | L11: OPORTUNIDAD
B12: G7
B13: 1 | C13: 040002 | D13: Banamex | G13: 100 | H13: 100 | K13: 100 | L13: 100 | O13: G-7
B14: 2 | C14: 040072 | D14: Banorte | G14: 98.46 | H14: 98.46 | K14: 98.46 | L14: 100 | O14: G-7
B15: 3 | C15: 040044 | D15: Scotiabank | G15: 97.27 | H15: 97.27 | K15: 97.27 | L15: 100 | O15: G-7
B16: 4 | C16: 040036 | D16: Inbursa | G16: 96.8 | H16: 96.8 | K16: 96.8 | L16: 100 | O16: G-7
B17: 5 | C17: 040021 | D17: HSBC | G17: 95.6 | H17: 95.6 | K17: 95.6 | L17: 100 | O17: G-7
B18: 6 | C18: 040012 | D18: BBVA México | G18: 95.08 | H18: 95.08 | K18: 95.08 | L18: 100 | O18: G-7
B19: 7 | C19: 040014 | D19: Santander | G19: 90.06 | H19: 90.06 | K19: 90.06 | L19: 100 | O19: G-7
B21: BANCOS CAMBIARIOS
B22: 1 | C22: 040112 | D22: Monex | G22: 96.53 | H22: 96.53 | K22: 96.53 | L22: 100 | O22: Bancos Cambiarios
B23: 2 | C23: 040143 | D23: CIBanco | G23: 93.9 | H23: 93.9 | K23: 93.9 | L23: 100 | O23: Bancos Cambiarios
B24: 3 | C24: 040145 | D24: Banco Base | G24: 90.46 | H24: 90.46 | K24: 90.46 | L24: 100 | O24: Bancos Cambiarios
B25: 4 | C25: 040136 | D25: Intercam Banco | G25: 77.4 | H25: 77.4 | K25: 77.4 | L25: 100 | O25: Bancos Cambiarios
B27: BANCA DE INVERSIÓN Y OTROS SERVICIOS
B28: 1 | C28: 040126 | D28: Credit Suisse | G28: 100 | H28: 100 | K28: 100 | L28: 100 | O28: Banca de Inversión y Otros Servicios
B29: 1 | C29: 040139 | D29: BIAfirme | G29: 100 | H29: 100 | K29: 100 | L29: 100 | O29: Banca de Inversión y Otros Servicios
B30: 3 | C30: 040108 | D30: MUFG Bank | G30: 99.71 | H30: 99.71 | K30: 99.71 | L30: 100 | O30: Banca de Inversión y Otros Servicios
B31: 4 | C31: 040129 | D31: Barclays | G31: 99.56 | H31: 99.56 | K31: 99.56 | L31: 100 | O31: Banca de Inversión y Otros Servicios
B32: 5 | C32: 040124 | D32: Citi México (Antes CBM Banco) | G32: 99.19 | H32: 99.19 | K32: 99.19 | L32: 100 | O32: Banca de Inversión y Otros Servicios
B33: 6 | C33: 040148 | D33: Pagatodo | G33: 98.41 | H33: 98.41 | K33: 98.41 | L33: 100 | O33: Banca de Inversión y Otros Servicios
B34: 7 | C34: 040164 | D34: BNP Paribas México | G34: 97.99 | H34: 97.99 | K34: 97.99 | L34: 100 | O34: Banca de Inversión y Otros Servicios
B35: 8 | C35: 040106 | D35: Bank of America | G35: 97.84 | H35: 97.84 | K35: 97.84 | L35: 100 | O35: Banca de Inversión y Otros Servicios
B36: 9 | C36: 040160 | D36: Banco S3 | G36: 96.48 | H36: 96.48 | K36: 96.48 | L36: 100 | O36: Banca de Inversión y Otros Servicios
B37: 10 | C37: 040110 | D37: J.P. Morgan | G37: 94.64 | H37: 94.64 | K37: 94.64 | L37: 100 | O37: Banca de Inversión y Otros Servicios
B38: 11 | C38: 040062 | D38: Afirme | G38: 92.93 | H38: 92.93 | K38: 92.93 | L38: 100 | O38: Banca de Inversión y Otros Servicios
B39: 12 | C39: 040059 | D39: Invex | G39: 89 | H39: 89 | K39: 89 | L39: 100 | O39: Banca de Inversión y Otros Servicios
B41: COMERCIAL MEDIANO
B42: 1 | C42: 040030 | D42: Banco del Bajío | G42: 99.86 | H42: 99.86 | K42: 99.86 | L42: 100 | O42: Comercial Mediano
B43: 2 | C43: 040113 | D43: Ve por Más | G43: 99.36 | H43: 99.36 | K43: 99.36 | L43: 100 | O43: Comercial Mediano
B44: 3 | C44: 040156 | D44: Sabadell | G44: 98.66 | H44: 98.66 | K44: 98.66 | L44: 100 | O44: Comercial Mediano
B45: 4 | C45: 040058 | D45: Banregio | G45: 96.87 | H45: 96.87 | K45: 96.87 | L45: 100 | O45: Comercial Mediano
B46: 5 | C46: 040132 | D46: Multiva | G46: 95.22 | H46: 95.22 | K46: 95.22 | L46: 100 | O46: Comercial Mediano
B47: 6 | C47: 040042 | D47: Banca Mifel | G47: 93.55 | H47: 93.55 | K47: 93.55 | L47: 100 | O47: Comercial Mediano
B49: COMERCIAL PEQUEÑO
B50: 1 | C50: 040162 | D50: KEB Hana México | G50: 100 | H50: 100 | K50: 100 | L50: 100 | O50: Comercial pequeño
B51: 2 | C51: 040151 | D51: Dondé Banco | G51: 99.71 | H51: 99.71 | K51: 99.71 | L51: 100 | O51: Comercial pequeño
B52: 3 | C52: 040147 | D52: Bankaool | G52: 99.43 | H52: 99.43 | K52: 99.43 | L52: 100 | O52: Comercial pequeño
B53: 4 | C53: 040159 | D53: Bank of China | G53: 99.42 | H53: 99.42 | K53: 99.42 | L53: 100 | O53: Comercial pequeño
B54: 5 | C54: 040155 | D54: ICBC | G54: 98.86 | H54: 98.86 | K54: 98.86 | L54: 100 | O54: Comercial pequeño
B55: 6 | C55: 040060 | D55: Bansí | G55: 98.18 | H55: 98.18 | K55: 98.18 | L55: 100 | O55: Comercial pequeño
B56: 7 | C56: 040158 | D56: Mizuho Bank | G56: 97.39 | H56: 97.39 | K56: 97.39 | L56: 100 | O56: Comercial pequeño
B57: 8 | C57: 040157 | D57: Shinhan | G57: 97.23 | H57: 97.23 | K57: 97.23 | L57: 100 | O57: Comercial pequeño
B58: 9 | C58: 040133 | D58: Actinver | G58: 96.47 | H58: 96.47 | K58: 96.47 | L58: 100 | O58: Comercial pequeño
B59: 10 | C59: 040150 | D59: Inmobiliario Mexicano | G59: 96.21 | H59: 96.21 | K59: 96.21 | L59: 100 | O59: Comercial pequeño
B60: 11 | C60: 040154 | D60: Covalto | G60: 96.01 | H60: 96.01 | K60: 96.01 | L60: 100 | O60: Comercial pequeño
B61: 12 | C61: 040138 | D61: Ualá | G61: 95.24 | H61: 95.24 | K61: 95.24 | L61: 100 | O61: Comercial pequeño
... B63: 14 | C63: 040152 | D63: Bancrea | G63: 87.26 | H63: 87.26 | K63: 87.26 | L63: 100 | O63: Comercial pequeño
B65: CRÉDITOS A LOS HOGARES
B66: 1 | C66: 040165 | D66: Banco Bineo | G66: 100 | H66: 100 | K66: 100 | L66: 100 | O66: Créditos a los Hogares
B67: 2 | C67: 040169 | D67: Openbank | G67: 99.84 | H67: 99.84 | K67: 99.84 | L67: 100 | O67: Créditos a los Hogares
B68: 3 | C68: 040149 | D68: Forjadores | G68: 99.22 | H68: 99.22 | K68: 99.22 | L68: 100 | O68: Créditos a los Hogares
B69: 4 | C69: 040130 | D69: Compartamos | G69: 99.07 | H69: 99.07 | K69: 99.07 | L69: 100 | O69: Créditos a los Hogares
B70: 5 | C70: 040141 | D70: Volkswagen Bank | G70: 98.84 | H70: 98.84 | K70: 98.84 | L70: 100 | O70: Créditos a los Hogares
B71: 6 | C71: 040137 | D71: Bancoppel | G71: 97.16 | H71: 97.16 | K71: 97.16 | L71: 100 | O71: Créditos a los Hogares
B72: 7 | C72: 040127 | D72: Banco Azteca | G72: 96.14 | H72: 96.14 | K72: 96.14 | L72: 100 | O72: Créditos a los Hogares
B73: 8 | C73: 040167 | D73: Hey Banco | G73: 95 | H73: 95 | K73: 95 | L73: 100 | O73: Créditos a los Hogares
B74: 9 | C74: 040140 | D74: Consubanco | G74: 91.72 | H74: 91.72 | K74: 91.72 | L74: 100 | O74: Créditos a los Hogares

Sheet Evaluación Calidad Detallada
B3: Evaluación de la Calidad de la Información
B4: Banca Múltiple
B5: julio 2025
M6: Fecha de corte: 20 de agosto de 2025
B8: RANKING | C8: INSTITUCIÓN | G8: SITUACIÓN FINANCIERA | J8: CARTERA COMERCIAL | M8: CARTERA A LA VIVIENDA | P8: PRODUCTOS DE CAPTACIÓN | S8: OPERATIVOS
G9: CALIDAD | H9: OPORTUNIDAD | J9: CALIDAD | K9: OPORTUNIDAD | M9: CALIDAD | N9: OPORTUNIDAD | P9: CALIDAD | Q9: OPORTUNIDAD | S9: CALIDAD | T9: OPORTUNIDAD
B10: 1 | C10: 040002 | D10: Banamex | G10: 100 | H10: 100 | J10: 100 | K10: 100 | M10: 100 | N10: 100 | P10: 100 | Q10: 100 | S10: 100 | T10: 100
B11: 1 | C11: 040126 | D11: Credit Suisse | G11: 100 | H11: 100 | J11: n.a | K11: 100 | M11: n.a | N11: 100 | P11: 100 | Q11: 100 | S11: 100 | T11: 100
B12: 1 | C12: 040139 | D12: BIAfirme | G12: 100 | H12: 100 | J12: 100 | K12: 100 | M12: n.a | N12: 100 | P12: 100 | Q12: 100 | S12: 100 | T12: 100
B13: 1 | C13: 040162 | D13: KEB Hana México | G13: 100 | H13: 100 | J13: 100 | K13: 100 | M13: n.a | N13: 100 | P13: 100 | Q13: 100 | S13: 100 | T13: 100
B14: 1 | C14: 040165 | D14: Banco Bineo | G14: 100 | H14: 100 | J14: n.a | K14: 100 | M14: n.a | N14: 100 | P14: 100 | Q14: 100 | S14: 100 | T14: 100
B15: 6 | C15: 040030 | D15: Banco del Bajío | G15: 100 | H15: 100 | J15: 99.52 | K15: 100 | M15: 100 | N15: 100 | P15: 100 | Q15: 100 | S15: 100 | T15: 100
B16: 7 | C16: 040169 | D16: Openbank | G16: 99.73 | H16: 100 | J16: n.a | K16: 100 | M16: n.a | N16: 100 | P16: 100 | Q16: 100 | S16: 100 | T16: 100
B17: 8 | C17: 040108 | D17: MUFG Bank | G17: 99.73 | H17: 100 | J17: 99.54 | K17: 100 | M17: n.a | N17: 100 | P17: 100 | Q17: 100 | S17: 100 | T17: 100
B18: 8 | C18: 040151 | D18: Dondé Banco | G18: 100 | H18: 100 | J18: 99.54 | K18: 100 | M18: n.a | N18: 100 | P18: 97.44 | Q18: 100 | S18: 100 | T18: 100
B19: 10 | C19: 040129 | D19: Barclays | G19: 99.1 | H19: 100 | J19: n.a | K19: 100 | M19: n.a | N19: 100 | P19: 100 | Q19: 100 | S19: 100 | T19: 100
B20: 11 | C20: 040147 | D20: Bankaool | G20: 99.47 | H20: 100 | J20: 99.54 | K20: 100 | M20: n.a | N20: 100 | P20: 100 | Q20: 100 | S20: 98.97 | T20: 100
B21: 12 | C21: 040159 | D21: Bank of China | G21: 99.43 | H21: 100 | J21: 100 | K21: 100 | M21: n.a | N21: 100 | P21: 89.74 | Q21: 100 | S21: 100 | T21: 100
B22: 13 | C22: 040113 | D22: Ve por Más | G22: 100 | H22: 100 | J22: 98.04 | K22: 100 | M22: 100 | N22: 100 | P22: 100 | Q22: 100 | S22: 99.49 | T22: 100
B23: 14 | C23: 040149 | D23: Forjadores | G23: 100 | H23: 100 | J23: 98.15 | K23: 100 | M23: n.a | N23: 100 | P23: 100 | Q23: 100 | S23: 100 | T23: 100
B24: 15 | C24: 040124 | D24: Citi México (Antes CBM Banco) | G24: 100 | H24: 100 | J24: 99 | K24: 100 | M24: n.a | N24: 100 | P24: n.a | Q24: 100 | S24: 97.95 | T24: 100
B25: 16 | C25: 040130 | D25: Compartamos | G25: 99.01 | H25: 100 | J25: 99.76 | K25: 100 | M25: n.a | N25: 100 | P25: 87.18 | Q25: 100 | S25: 100 | T25: 100
B26: 17 | C26: 040155 | D26: ICBC | G26: 97.25 | H26: 100 | J26: 100 | K26: 100 | M26: n.a | N26: 100 | P26: 94.87 | Q26: 100 | S26: 100 | T26: 100
B27: 18 | C27: 040141 | D27: Volkswagen Bank | G27: 99.49 | H27: 100 | J27: n.a | K27: 100 | M27: n.a | N27: 100 | P27: 100 | Q27: 100 | S27: 100 | T27: 100
B28: 19 | C28: 040156 | D28: Sabadell | G28: 100 | H28: 100 | J28: 95.9 | K28: 100 | M28: 99.73 | N28: 100 | P28: 100 | Q28: 100 | S28: 100 | T28: 100
B29: 20 | C29: 040072 | D29: Banorte | G29: 100 | H29: 100 | J29: 99.76 | K29: 100 | M29: 94.99 | N29: 100 | P29: 100 | Q29: 100 | S29: 100 | T29: 100
B30: 21 | C30: 040148 | D30: Pagatodo | G30: 100 | H30: 100 | J30: n.a | K30: 100 | M30: n.a | N30: 100 | P30: 82.05 | Q30: 100 | S30: 100 | T30: 100
B31: 22 | C31: 040060 | D31: Bansí | G31: 100 | H31: 100 | J31: 96.6 | K31: 100 | M31: 100 | N31: 100 | P31: 100 | Q31: 100 | S31: 94.36 | T31: 100
B32: 23 | C32: 040164 | D32: BNP Paribas México | G32: 96.1 | H32: 100 | J32: n.a | K32: 100 | M32: n.a | N32: 100 | P32: n.a | Q32: 100 | S32: 100 | T32: 100
B33: 24 | C33: 040106 | D33: Bank of America | G33: 98.87 | H33: 100 | J33: 98.14 | K33: 100 | M33: n.a | N33: 100 | P33: 97.44 | Q33: 100 | S33: 95.38 | T33: 100
B34: 25 | C34: 040158 | D34: Mizuho Bank | G34: 99.18 | H34: 100 | J34: 94.55 | K34: 100 | M34: n.a | N34: 100 | P34: 100 | Q34: 100 | S34: 100 | T34: 100
B35: 26 | C35: 040044 | D35: Scotiabank | G35: 100 | H35: 100 | J35: 100 | K35: 100 | M35: 90.81 | N35: 100 | P35: 100 | Q35: 100 | S35: 100 | T35: 100
B36: 27 | C36: 040157 | D36: Shinhan | G36: 100 | H36: 100 | J36: 93.51 | K36: 100 | M36: n.a | N36: 100 | P36: 100 | Q36: 100 | S36: 100 | T36: 100
B37: 28 | C37: 040137 | D37: Bancoppel | G37: 96.4 | H37: 100 | J37: 96.94 | K37: 100 | M37: 99.31 | N37: 100 | P37: 100 | Q37: 100 | S37: 93.85 | T37: 100
B38: 29 | C38: 040058 | D38: Banregio | G38: 100 | H38: 100 | J38: 96.43 | K38: 100 | M38: 92.77 | N38: 100 | P38: 100 | Q38: 100 | S38: 100 | T38: 100
B39: 30 | C39: 040036 | D39: Inbursa | G39: 99.47 | H39: 100 | J39: 95.99 | K39: 100 | M39: 98.68 | N39: 100 | P39: 66.67 | Q39: 100 | S39: 95.38 | T39: 100
B40: 31 | C40: 040112 | D40: Monex | G40: 100 | H40: 100 | J40: 91.32 | K40: 100 | M40: 100 | N40: 100 | P40: 100 | Q40: 100 | S40: 93.33 | T40: 100
B41: 32 | C41: 040160 | D41: Banco S3 | G41: 97.55 | H41: 100 | J41: 95.79 | K41: 100 | M41: n.a | N41: 100 | P41: 100 | Q41: 100 | S41: 95.38 | T41: 100
B42: 33 | C42: 040133 | D42: Actinver | G42: 99.73 | H42: 100 | J42: 92.19 | K42: 100 | M42: n.a | N42: 100 | P42: 97.44 | Q42: 100 | S42: 100 | T42: 100
B43: 34 | C43: 040150 | D43: Inmobiliario Mexicano | G43: 100 | H43: 100 | J43: 87.5 | K43: 100 | M43: 100 | N43: 100 | P43: 100 | Q43: 100 | S43: 100 | T43: 100
B44: 35 | C44: 040127 | D44: Banco Azteca | G44: 98.94 | H44: 100 | J44: 93.96 | K44: 100 | M44: 94.01 | N44: 100 | P44: 100 | Q44: 100 | S44: 99.49 | T44: 100
B45: 36 | C45: 040154 | D45: Covalto | G45: 97.25 | H45: 100 | J45: 93.33 | K45: 100 | M45: n.a | N45: 100 | P45: 94.87 | Q45: 100 | S45: 100 | T45: 100
B46: 37 | C46: 040021 | D46: HSBC | G46: 100 | H46: 100 | J46: 96.45 | K46: 100 | M46: 88.29 | N46: 100 | P46: 100 | Q46: 100 | S46: 100 | T46: 100
B47: 38 | C47: 040138 | D47: Ualá | G47: 98.42 | H47: 100 | J47: 89.76 | K47: 100 | M47: 99.52 | N47: 100 | P47: 100 | Q47: 100 | S47: 92.31 | T47: 100
B48: 39 | C48: 040132 | D48: Multiva | G48: 100 | H48: 100 | J48: 87.24 | K48: 100 | M48: 97.16 | N48: 100 | P48: 100 | Q48: 100 | S48: 98.46 | T48: 100
B49: 40 | C49: 040012 | D49: BBVA México | G49: 100 | H49: 100 | J49: 83.85 | K49: 100 | M49: 100 | N49: 100 | P49: 100 | Q49: 100 | S49: 100 | T49: 100
B50: 41 | C50: 040167 | D50: Hey Banco | G50: 100 | H50: 100 | J50: n.a | K50: 100 | M50: n.a | N50: 100 | P50: 100 | Q50: 100 | S50: 100 | T50: 100
B51: 42 | C51: 040110 | D51: J.P. Morgan | G51: 100 | H51: 100 | J51: 90.84 | K51: 100 | M51: n.a | N51: 100 | P51: 94.87 | Q51: 100 | S51: 93.33 | T51: 100
B52: 43 | C52: 040143 | D52: CIBanco | G52: 96.32 | H52: 100 | J52: 94.64 | K52: 100 | M52: 92.22 | N52: 100 | P52: 82.05 | Q52: 100 | S52: 93.85 | T52: 100
B53: 44 | C53: 040042 | D53: Banca Mifel | G53: 100 | H53: 100 | J53: 89.76 | K53: 100 | M53: 90.77 | N53: 100 | P53: 94.87 | Q53: 100 | S53: 95.9 | T53: 100
B54: 45 | C54: 040062 | D54: Afirme | G54: 100 | H54: 100 | J54: 85.84 | K54: 100 | M54: 93.85 | N54: 100 | P54: 100 | Q54: 100 | S54: 91.79 | T54: 100
B55: 46 | C55: 040140 | D55: Consubanco | G55: 93.41 | H55: 100 | J55: 86.87 | K55: 100 | M55: n.a | N55: 100 | P55: 97.44 | Q55: 100 | S55: 98.46 | T55: 100
B56: 47 | C56: 040145 | D56: Banco Base | G56: 98.88 | H56: 100 | J56: 81.01 | K56: 100 | M56: n.a | N56: 100 | P56: 84.62 | Q56: 100 | S56: 97.44 | T56: 100
B57: 48 | C57: 040014 | D57: Santander | G57: 100 | H57: 100 | J57: 82.16 | K57: 100 | M57: 84.46 | N57: 100 | P57: 97.44 | Q57: 100 | S57: 99.49 | T57: 100
B58: 49 | C58: 040128 | D58: Autofin | G58: 97.66 | H58: 100 | J58: 77.72 | K58: 100 | M58: 95.77 | N58: 100 | P58: 64.1 | Q58: 100 | S58: 94.36 | T58: 100
B59: 50 | C59: 040059 | D59: Invex | G59: 100 | H59: 100 | J59: 72.23 | K59: 100 | M59: 92.21 | N59: 100 | P59: 89.74 | Q59: 100 | S59: 99.49 | T59: 100
B60: 51 | C60: 040152 | D60: Bancrea | G60: 96.43 | H60: 100 | J60: 63.92 | K60: 100 | M60: 100 | N60: 100 | P60: 74.36 | Q60: 100 | S60: 96.92 | T60: 100
B61: 52 | C61: 040136 | D61: Intercam Banco | G61: 95.5 | H61: 100 | J61: 66.32 | K61: 100 | M61: n.a | N61: 100 | P61: 89.74 | Q61: 100 | S61: 92.82 | T61: 100
B101: =_xlfn.XLOOKUP(C101,[1]Calificación!D:D,[1]Calificación!A:A,"",0,1) | C101: =IF([1]Calificación!D90=0,"",[1]Calificación!D90) | D101: =IFERROR(VLOOKUP(C101,[1]Calificación!$D$1:$X$53,2,0),"") | G101: =IFERROR(VLOOKUP(C101,[1]Calificación!$D$1:$X$53,12,0),"") | H101: =IFERROR(IF(VLOOKUP(C101,[1]Calificación!$D$1:$X$53,13,0)=0,"n.a",VLOOKUP(C101,[1]Calificación!$D$1:$X$53,13,0)),"") | J101: =IFERROR(IF(VLOOKUP(C101,[1]Calificación!$D$1:$X$53,14,0)=0,"n.a",VLOOKUP(C101,[1]Calificación!$D$1:$X$53,14,0)),"") | K101: =IFERROR(IF(VLOOKUP(C101,[1]Calificación!$D$1:$X$53,15,0)=0,"n.a",VLOOKUP(C101,[1]Calificación!$D$1:$X$53,15,0)),"") | M101: =IFERROR(IF(VLOOKUP(C101,[1]Calificación!$D$1:$X$53,16,0)=0,"n.a",VLOOKUP(C101,[1]Calificación!$D$1:$X$53,16,0)),"") | N101: =IFERROR(IF(VLOOKUP(C101,[1]Calificación!$D$1:$X$53,17,0)=0,"n.a",VLOOKUP(C101,[1]Calificación!$D$1:$X$53,17,0)),"") | P101: =IFERROR(IF(VLOOKUP(C101,[1]Calificación!$D$1:$X$53,18,0)=0,"n.a",VLOOKUP(C101,[1]Calificación!$D$1:$X$53,18,0)),"") | Q101: =IFERROR(IF(VLOOKUP(C101,[1]Calificación!$D$1:$X$53,19,0)=0,"n.a",VLOOKUP(C101,[1]Calificación!$D$1:$X$53,19,0)),"") | S101: =IFERROR(IF(VLOOKUP(C101,[1]Calificación!$D$1:$X$53,20,0)=0,"n.a",VLOOKUP(C101,[1]Calificación!$D$1:$X$53,20,0)),"") | T101: =IFERROR(IF(VLOOKUP(C101,[1]Calificación!$D$1:$X$53,21,0)=0,"n.a",VLOOKUP(C101,[1]Calificación!$D$1:$X$53,21,0)),"")
B102: =_xlfn.XLOOKUP(C102,[1]Calificación!D:D,[1]Calificación!A:A,"",0,1) | C102: =IF([1]Calificación!D91=0,"",[1]Calificación!D91) | D102: =IFERROR(VLOOKUP(C102,[1]Calificación!$D$1:$X$53,2,0),"") | G102: =IFERROR(VLOOKUP(C102,[1]Calificación!$D$1:$X$53,12,0),"") | H102: =IFERROR(IF(VLOOKUP(C102,[1]Calificación!$D$1:$X$53,13,0)=0,"n.a",VLOOKUP(C102,[1]Calificación!$D$1:$X$53,13,0)),"") | J102: =IFERROR(IF(VLOOKUP(C102,[1]Calificación!$D$1:$X$53,14,0)=0,"n.a",VLOOKUP(C102,[1]Calificación!$D$1:$X$53,14,0)),"") | K102: =IFERROR(IF(VLOOKUP(C102,[1]Calificación!$D$1:$X$53,15,0)=0,"n.a",VLOOKUP(C102,[1]Calificación!$D$1:$X$53,15,0)),"") | M102: =IFERROR(IF(VLOOKUP(C102,[1]Calificación!$D$1:$X$53,16,0)=0,"n.a",VLOOKUP(C102,[1]Calificación!$D$1:$X$53,16,0)),"") | N102: =IFERROR(IF(VLOOKUP(C102,[1]Calificación!$D$1:$X$53,17,0)=0,"n.a",VLOOKUP(C102,[1]Calificación!$D$1:$X$53,17,0)),"") | P102: =IFERROR(IF(VLOOKUP(C102,[1]Calificación!$D$1:$X$53,18,0)=0,"n.a",VLOOKUP(C102,[1]Calificación!$D$1:$X$53,18,0)),"") | Q102: =IFERROR(IF(VLOOKUP(C102,[1]Calificación!$D$1:$X$53,19,0)=0,"n.a",VLOOKUP(C102,[1]Calificación!$D$1:$X$53,19,0)),"") | S102: =IFERROR(IF(VLOOKUP(C102,[1]Calificación!$D$1:$X$53,20,0)=0,"n.a",VLOOKUP(C102,[1]Calificación!$D$1:$X$53,20,0)),"") | T102: =IFERROR(IF(VLOOKUP(C102,[1]Calificación!$D$1:$X$53,21,0)=0,"n.a",VLOOKUP(C102,[1]Calificación!$D$1:$X$53,21,0)),"")
B103: =_xlfn.XLOOKUP(C103,[1]Calificación!D:D,[1]Calificación!A:A,"",0,1) | C103: =IF([1]Calificación!D92=0,"",[1]Calificación!D92) | D103: =IFERROR(VLOOKUP(C103,[1]Calificación!$D$1:$X$53,2,0),"") | G103: =IFERROR(VLOOKUP(C103,[1]Calificación!$D$1:$X$53,12,0),"") | H103: =IFERROR(IF(VLOOKUP(C103,[1]Calificación!$D$1:$X$53,13,0)=0,"n.a",VLOOKUP(C103,[1]Calificación!$D$1:$X$53,13,0)),"") | J103: =IFERROR(IF(VLOOKUP(C103,[1]Calificación!$D$1:$X$53,14,0)=0,"n.a",VLOOKUP(C103,[1]Calificación!$D$1:$X$53,14,0)),"") | K103: =IFERROR(IF(VLOOKUP(C103,[1]Calificación!$D$1:$X$53,15,0)=0,"n.a",VLOOKUP(C103,[1]Calificación!$D$1:$X$53,15,0)),"") | M103: =IFERROR(IF(VLOOKUP(C103,[1]Calificación!$D$1:$X$53,16,0)=0,"n.a",VLOOKUP(C103,[1]Calificación!$D$1:$X$53,16,0)),"") | N103: =IFERROR(IF(VLOOKUP(C103,[1]Calificación!$D$1:$X$53,17,0)=0,"n.a",VLOOKUP(C103,[1]Calificación!$D$1:$X$53,17,0)),"") | P103: =IFERROR(IF(VLOOKUP(C103,[1]Calificación!$D$1:$X$53,18,0)=0,"n.a",VLOOKUP(C103,[1]Calificación!$D$1:$X$53,18,0)),"") | Q103: =IFERROR(IF(VLOOKUP(C103,[1]Calificación!$D$1:$X$53,19,0)=0,"n.a",VLOOKUP(C103,[1]Calificación!$D$1:$X$53,19,0)),"") | S103: =IFERROR(IF(VLOOKUP(C103,[1]Calificación!$D$1:$X$53,20,0)=0,"n.a",VLOOKUP(C103,[1]Calificación!$D$1:$X$53,20,0)),"") | T103: =IFERROR(IF(VLOOKUP(C103,[1]Calificación!$D$1:$X$53,21,0)=0,"n.a",VLOOKUP(C103,[1]Calificación!$D$1:$X$53,21,0)),"")
B104: =_xlfn.XLOOKUP(C104,[1]Calificación!D:D,[1]Calificación!A:A,"",0,1) | C104: =IF([1]Calificación!D93=0,"",[1]Calificación!D93) | D104: =IFERROR(VLOOKUP(C104,[1]Calificación!$D$1:$X$53,2,0),"") | G104: =IFERROR(VLOOKUP(C104,[1]Calificación!$D$1:$X$53,12,0),"") | H104: =IFERROR(IF(VLOOKUP(C104,[1]Calificación!$D$1:$X$53,13,0)=0,"n.a",VLOOKUP(C104,[1]Calificación!$D$1:$X$53,13,0)),"") | J104: =IFERROR(IF(VLOOKUP(C104,[1]Calificación!$D$1:$X$53,14,0)=0,"n.a",VLOOKUP(C104,[1]Calificación!$D$1:$X$53,14,0)),"") | K104: =IFERROR(IF(VLOOKUP(C104,[1]Calificación!$D$1:$X$53,15,0)=0,"n.a",VLOOKUP(C104,[1]Calificación!$D$1:$X$53,15,0)),"") | M104: =IFERROR(IF(VLOOKUP(C104,[1]Calificación!$D$1:$X$53,16,0)=0,"n.a",VLOOKUP(C104,[1]Calificación!$D$1:$X$53,16,0)),"") | N104: =IFERROR(IF(VLOOKUP(C104,[1]Calificación!$D$1:$X$53,17,0)=0,"n.a",VLOOKUP(C104,[1]Calificación!$D$1:$X$53,17,0)),"") | P104: =IFERROR(IF(VLOOKUP(C104,[1]Calificación!$D$1:$X$53,18,0)=0,"n.a",VLOOKUP(C104,[1]Calificación!$D$1:$X$53,18,0)),"") | Q104: =IFERROR(IF(VLOOKUP(C104,[1]Calificación!$D$1:$X$53,19,0)=0,"n.a",VLOOKUP(C104,[1]Calificación!$D$1:$X$53,19,0)),"") | S104: =IFERROR(IF(VLOOKUP(C104,[1]Calificación!$D$1:$X$53,20,0)=0,"n.a",VLOOKUP(C104,[1]Calificación!$D$1:$X$53,20,0)),"") | T104: =IFERROR(IF(VLOOKUP(C104,[1]Calificación!$D$1:$X$53,21,0)=0,"n.a",VLOOKUP(C104,[1]Calificación!$D$1:$X$53,21,0)),"")
B105: =_xlfn.XLOOKUP(C105,[1]Calificación!D:D,[1]Calificación!A:A,"",0,1) | C105: =IF([1]Calificación!D94=0,"",[1]Calificación!D94) | D105: =IFERROR(VLOOKUP(C105,[1]Calificación!$D$1:$X$53,2,0),"") | G105: =IFERROR(VLOOKUP(C105,[1]Calificación!$D$1:$X$53,12,0),"") | H105: =IFERROR(IF(VLOOKUP(C105,[1]Calificación!$D$1:$X$53,13,0)=0,"n.a",VLOOKUP(C105,[1]Calificación!$D$1:$X$53,13,0)),"") | J105: =IFERROR(IF(VLOOKUP(C105,[1]Calificación!$D$1:$X$53,14,0)=0,"n.a",VLOOKUP(C105,[1]Calificación!$D$1:$X$53,14,0)),"") | K105: =IFERROR(IF(VLOOKUP(C105,[1]Calificación!$D$1:$X$53,15,0)=0,"n.a",VLOOKUP(C105,[1]Calificación!$D$1:$X$53,15,0)),"") | M105: =IFERROR(IF(VLOOKUP(C105,[1]Calificación!$D$1:$X$53,16,0)=0,"n.a",VLOOKUP(C105,[1]Calificación!$D$1:$X$53,16,0)),"") | N105: =IFERROR(IF(VLOOKUP(C105,[1]Calificación!$D$1:$X$53,17,0)=0,"n.a",VLOOKUP(C105,[1]Calificación!$D$1:$X$53,17,0)),"") | P105: =IFERROR(IF(VLOOKUP(C105,[1]Calificación!$D$1:$X$53,18,0)=0,"n.a",VLOOKUP(C105,[1]Calificación!$D$1:$X$53,18,0)),"") | Q105: =IFERROR(IF(VLOOKUP(C105,[1]Calificación!$D$1:$X$53,19,0)=0,"n.a",VLOOKUP(C105,[1]Calificación!$D$1:$X$53,19,0)),"") | S105: =IFERROR(IF(VLOOKUP(C105,[1]Calificación!$D$1:$X$53,20,0)=0,"n.a",VLOOKUP(C105,[1]Calificación!$D$1:$X$53,20,0)),"") | T105: =IFERROR(IF(VLOOKUP(C105,[1]Calificación!$D$1:$X$53,21,0)=0,"n.a",VLOOKUP(C105,[1]Calificación!$D$1:$X$53,21,0)),"")
B106: =_xlfn.XLOOKUP(C106,[1]Calificación!D:D,[1]Calificación!A:A,"",0,1) | C106: =IF([1]Calificación!D95=0,"",[1]Calificación!D95) | D106: =IFERROR(VLOOKUP(C106,[1]Calificación!$D$1:$X$53,2,0),"") | G106: =IFERROR(VLOOKUP(C106,[1]Calificación!$D$1:$X$53,12,0),"") | H106: =IFERROR(IF(VLOOKUP(C106,[1]Calificación!$D$1:$X$53,13,0)=0,"n.a",VLOOKUP(C106,[1]Calificación!$D$1:$X$53,13,0)),"") | J106: =IFERROR(IF(VLOOKUP(C106,[1]Calificación!$D$1:$X$53,14,0)=0,"n.a",VLOOKUP(C106,[1]Calificación!$D$1:$X$53,14,0)),"") | K106: =IFERROR(IF(VLOOKUP(C106,[1]Calificación!$D$1:$X$53,15,0)=0,"n.a",VLOOKUP(C106,[1]Calificación!$D$1:$X$53,15,0)),"") | M106: =IFERROR(IF(VLOOKUP(C106,[1]Calificación!$D$1:$X$53,16,0)=0,"n.a",VLOOKUP(C106,[1]Calificación!$D$1:$X$53,16,0)),"") | N106: =IFERROR(IF(VLOOKUP(C106,[1]Calificación!$D$1:$X$53,17,0)=0,"n.a",VLOOKUP(C106,[1]Calificación!$D$1:$X$53,17,0)),"") | P106: =IFERROR(IF(VLOOKUP(C106,[1]Calificación!$D$1:$X$53,18,0)=0,"n.a",VLOOKUP(C106,[1]Calificación!$D$1:$X$53,18,0)),"") | Q106: =IFERROR(IF(VLOOKUP(C106,[1]Calificación!$D$1:$X$53,19,0)=0,"n.a",VLOOKUP(C106,[1]Calificación!$D$1:$X$53,19,0)),"") | S106: =IFERROR(IF(VLOOKUP(C106,[1]Calificación!$D$1:$X$53,20,0)=0,"n.a",VLOOKUP(C106,[1]Calificación!$D$1:$X$53,20,0)),"") | T106: =IFERROR(IF(VLOOKUP(C106,[1]Calificación!$D$1:$X$53,21,0)=0,"n.a",VLOOKUP(C106,[1]Calificación!$D$1:$X$53,21,0)),"")
B107: =_xlfn.XLOOKUP(C107,[1]Calificación!D:D,[1]Calificación!A:A,"",0,1) | C107: =IF([1]Calificación!D96=0,"",[1]Calificación!D96) | D107: =IFERROR(VLOOKUP(C107,[1]Calificación!$D$1:$X$53,2,0),"") | G107: =IFERROR(VLOOKUP(C107,[1]Calificación!$D$1:$X$53,12,0),"") | H107: =IFERROR(IF(VLOOKUP(C107,[1]Calificación!$D$1:$X$53,13,0)=0,"n.a",VLOOKUP(C107,[1]Calificación!$D$1:$X$53,13,0)),"") | J107: =IFERROR(IF(VLOOKUP(C107,[1]Calificación!$D$1:$X$53,14,0)=0,"n.a",VLOOKUP(C107,[1]Calificación!$D$1:$X$53,14,0)),"") | K107: =IFERROR(IF(VLOOKUP(C107,[1]Calificación!$D$1:$X$53,15,0)=0,"n.a",VLOOKUP(C107,[1]Calificación!$D$1:$X$53,15,0)),"") | M107: =IFERROR(IF(VLOOKUP(C107,[1]Calificación!$D$1:$X$53,16,0)=0,"n.a",VLOOKUP(C107,[1]Calificación!$D$1:$X$53,16,0)),"") | N107: =IFERROR(IF(VLOOKUP(C107,[1]Calificación!$D$1:$X$53,17,0)=0,"n.a",VLOOKUP(C107,[1]Calificación!$D$1:$X$53,17,0)),"") | P107: =IFERROR(IF(VLOOKUP(C107,[1]Calificación!$D$1:$X$53,18,0)=0,"n.a",VLOOKUP(C107,[1]Calificación!$D$1:$X$53,18,0)),"") | Q107: =IFERROR(IF(VLOOKUP(C107,[1]Calificación!$D$1:$X$53,19,0)=0,"n.a",VLOOKUP(C107,[1]Calificación!$D$1:$X$53,19,0)),"") | S107: =IFERROR(IF(VLOOKUP(C107,[1]Calificación!$D$1:$X$53,20,0)=0,"n.a",VLOOKUP(C107,[1]Calificación!$D$1:$X$53,20,0)),"") | T107: =IFERROR(IF(VLOOKUP(C107,[1]Calificación!$D$1:$X$53,21,0)=0,"n.a",VLOOKUP(C107,[1]Calificación!$D$1:$X$53,21,0)),"")
B108: =_xlfn.XLOOKUP(C108,[1]Calificación!D:D,[1]Calificación!A:A,"",0,1) | C108: =IF([1]Calificación!D97=0,"",[1]Calificación!D97) | D108: =IFERROR(VLOOKUP(C108,[1]Calificación!$D$1:$X$53,2,0),"") | G108: =IFERROR(VLOOKUP(C108,[1]Calificación!$D$1:$X$53,12,0),"") | H108: =IFERROR(IF(VLOOKUP(C108,[1]Calificación!$D$1:$X$53,13,0)=0,"n.a",VLOOKUP(C108,[1]Calificación!$D$1:$X$53,13,0)),"") | J108: =IFERROR(IF(VLOOKUP(C108,[1]Calificación!$D$1:$X$53,14,0)=0,"n.a",VLOOKUP(C108,[1]Calificación!$D$1:$X$53,14,0)),"") | K108: =IFERROR(IF(VLOOKUP(C108,[1]Calificación!$D$1:$X$53,15,0)=0,"n.a",VLOOKUP(C108,[1]Calificación!$D$1:$X$53,15,0)),"") | M108: =IFERROR(IF(VLOOKUP(C108,[1]Calificación!$D$1:$X$53,16,0)=0,"n.a",VLOOKUP(C108,[1]Calificación!$D$1:$X$53,16,0)),"") | N108: =IFERROR(IF(VLOOKUP(C108,[1]Calificación!$D$1:$X$53,17,0)=0,"n.a",VLOOKUP(C108,[1]Calificación!$D$1:$X$53,17,0)),"") | P108: =IFERROR(IF(VLOOKUP(C108,[1]Calificación!$D$1:$X$53,18,0)=0,"n.a",VLOOKUP(C108,[1]Calificación!$D$1:$X$53,18,0)),"") | Q108: =IFERROR(IF(VLOOKUP(C108,[1]Calificación!$D$1:$X$53,19,0)=0,"n.a",VLOOKUP(C108,[1]Calificación!$D$1:$X$53,19,0)),"") | S108: =IFERROR(IF(VLOOKUP(C108,[1]Calificación!$D$1:$X$53,20,0)=0,"n.a",VLOOKUP(C108,[1]Calificación!$D$1:$X$53,20,0)),"") | T108: =IFERROR(IF(VLOOKUP(C108,[1]Calificación!$D$1:$X$53,21,0)=0,"n.a",VLOOKUP(C108,[1]Calificación!$D$1:$X$53,21,0)),"")
B109: =_xlfn.XLOOKUP(C109,[1]Calificación!D:D,[1]Calificación!A:A,"",0,1) | C109: =IF([1]Calificación!D98=0,"",[1]Calificación!D98) | D109: =IFERROR(VLOOKUP(C109,[1]Calificación!$D$1:$X$53,2,0),"") | G109: =IFERROR(VLOOKUP(C109,[1]Calificación!$D$1:$X$53,12,0),"") | H109: =IFERROR(IF(VLOOKUP(C109,[1]Calificación!$D$1:$X$53,13,0)=0,"n.a",VLOOKUP(C109,[1]Calificación!$D$1:$X$53,13,0)),"") | J109: =IFERROR(IF(VLOOKUP(C109,[1]Calificación!$D$1:$X$53,14,0)=0,"n.a",VLOOKUP(C109,[1]Calificación!$D$1:$X$53,14,0)),"") | K109: =IFERROR(IF(VLOOKUP(C109,[1]Calificación!$D$1:$X$53,15,0)=0,"n.a",VLOOKUP(C109,[1]Calificación!$D$1:$X$53,15,0)),"") | M109: =IFERROR(IF(VLOOKUP(C109,[1]Calificación!$D$1:$X$53,16,0)=0,"n.a",VLOOKUP(C109,[1]Calificación!$D$1:$X$53,16,0)),"") | N109: =IFERROR(IF(VLOOKUP(C109,[1]Calificación!$D$1:$X$53,17,0)=0,"n.a",VLOOKUP(C109,[1]Calificación!$D$1:$X$53,17,0)),"") | P109: =IFERROR(IF(VLOOKUP(C109,[1]Calificación!$D$1:$X$53,18,0)=0,"n.a",VLOOKUP(C109,[1]Calificación!$D$1:$X$53,18,0)),"") | Q109: =IFERROR(IF(VLOOKUP(C109,[1]Calificación!$D$1:$X$53,19,0)=0,"n.a",VLOOKUP(C109,[1]Calificación!$D$1:$X$53,19,0)),"") | S109: =IFERROR(IF(VLOOKUP(C109,[1]Calificación!$D$1:$X$53,20,0)=0,"n.a",VLOOKUP(C109,[1]Calificación!$D$1:$X$53,20,0)),"") | T109: =IFERROR(IF(VLOOKUP(C109,[1]Calificación!$D$1:$X$53,21,0)=0,"n.a",VLOOKUP(C109,[1]Calificación!$D$1:$X$53,21,0)),"")
B110: =_xlfn.XLOOKUP(C110,[1]Calificación!D:D,[1]Calificación!A:A,"",0,1) | C110: =IF([1]Calificación!D99=0,"",[1]Calificación!D99) | D110: =IFERROR(VLOOKUP(C110,[1]Calificación!$D$1:$X$53,2,0),"") | G110: =IFERROR(VLOOKUP(C110,[1]Calificación!$D$1:$X$53,12,0),"") | H110: =IFERROR(IF(VLOOKUP(C110,[1]Calificación!$D$1:$X$53,13,0)=0,"n.a",VLOOKUP(C110,[1]Calificación!$D$1:$X$53,13,0)),"") | J110: =IFERROR(IF(VLOOKUP(C110,[1]Calificación!$D$1:$X$53,14,0)=0,"n.a",VLOOKUP(C110,[1]Calificación!$D$1:$X$53,14,0)),"") | K110: =IFERROR(IF(VLOOKUP(C110,[1]Calificación!$D$1:$X$53,15,0)=0,"n.a",VLOOKUP(C110,[1]Calificación!$D$1:$X$53,15,0)),"") | M110: =IFERROR(IF(VLOOKUP(C110,[1]Calificación!$D$1:$X$53,16,0)=0,"n.a",VLOOKUP(C110,[1]Calificación!$D$1:$X$53,16,0)),"") | N110: =IFERROR(IF(VLOOKUP(C110,[1]Calificación!$D$1:$X$53,17,0)=0,"n.a",VLOOKUP(C110,[1]Calificación!$D$1:$X$53,17,0)),"") | P110: =IFERROR(IF(VLOOKUP(C110,[1]Calificación!$D$1:$X$53,18,0)=0,"n.a",VLOOKUP(C110,[1]Calificación!$D$1:$X$53,18,0)),"") | Q110: =IFERROR(IF(VLOOKUP(C110,[1]Calificación!$D$1:$X$53,19,0)=0,"n.a",VLOOKUP(C110,[1]Calificación!$D$1:$X$53,19,0)),"") | S110: =IFERROR(IF(VLOOKUP(C110,[1]Calificación!$D$1:$X$53,20,0)=0,"n.a",VLOOKUP(C110,[1]Calificación!$D$1:$X$53,20,0)),"") | T110: =IFERROR(IF(VLOOKUP(C110,[1]Calificación!$D$1:$X$53,21,0)=0,"n.a",VLOOKUP(C110,[1]Calificación!$D$1:$X$53,21,0)),"")
B111: =_xlfn.XLOOKUP(C111,[1]Calificación!D:D,[1]Calificación!A:A,"",0,1) | C111: =IF([1]Calificación!D100=0,"",[1]Calificación!D100) | D111: =IFERROR(VLOOKUP(C111,[1]Calificación!$D$1:$X$53,2,0),"") | G111: =IFERROR(VLOOKUP(C111,[1]Calificación!$D$1:$X$53,12,0),"") | H111: =IFERROR(IF(VLOOKUP(C111,[1]Calificación!$D$1:$X$53,13,0)=0,"n.a",VLOOKUP(C111,[1]Calificación!$D$1:$X$53,13,0)),"") | J111: =IFERROR(IF(VLOOKUP(C111,[1]Calificación!$D$1:$X$53,14,0)=0,"n.a",VLOOKUP(C111,[1]Calificación!$D$1:$X$53,14,0)),"") | K111: =IFERROR(IF(VLOOKUP(C111,[1]Calificación!$D$1:$X$53,15,0)=0,"n.a",VLOOKUP(C111,[1]Calificación!$D$1:$X$53,15,0)),"") | M111: =IFERROR(IF(VLOOKUP(C111,[1]Calificación!$D$1:$X$53,16,0)=0,"n.a",VLOOKUP(C111,[1]Calificación!$D$1:$X$53,16,0)),"") | N111: =IFERROR(IF(VLOOKUP(C111,[1]Calificación!$D$1:$X$53,17,0)=0,"n.a",VLOOKUP(C111,[1]Calificación!$D$1:$X$53,17,0)),"") | P111: =IFERROR(IF(VLOOKUP(C111,[1]Calificación!$D$1:$X$53,18,0)=0,"n.a",VLOOKUP(C111,[1]Calificación!$D$1:$X$53,18,0)),"") | Q111: =IFERROR(IF(VLOOKUP(C111,[1]Calificación!$D$1:$X$53,19,0)=0,"n.a",VLOOKUP(C111,[1]Calificación!$D$1:$X$53,19,0)),"") | S111: =IFERROR(IF(VLOOKUP(C111,[1]Calificación!$D$1:$X$53,20,0)=0,"n.a",VLOOKUP(C111,[1]Calificación!$D$1:$X$53,20,0)),"") | T111: =IFERROR(IF(VLOOKUP(C111,[1]Calificación!$D$1:$X$53,21,0)=0,"n.a",VLOOKUP(C111,[1]Calificación!$D$1:$X$53,21,0)),"")
B112: =_xlfn.XLOOKUP(C112,[1]Calificación!D:D,[1]Calificación!A:A,"",0,1) | C112: =IF([1]Calificación!D101=0,"",[1]Calificación!D101) | D112: =IFERROR(VLOOKUP(C112,[1]Calificación!$D$1:$X$53,2,0),"") | G112: =IFERROR(VLOOKUP(C112,[1]Calificación!$D$1:$X$53,12,0),"") | H112: =IFERROR(IF(VLOOKUP(C112,[1]Calificación!$D$1:$X$53,13,0)=0,"n.a",VLOOKUP(C112,[1]Calificación!$D$1:$X$53,13,0)),"") | J112: =IFERROR(IF(VLOOKUP(C112,[1]Calificación!$D$1:$X$53,14,0)=0,"n.a",VLOOKUP(C112,[1]Calificación!$D$1:$X$53,14,0)),"") | K112: =IFERROR(IF(VLOOKUP(C112,[1]Calificación!$D$1:$X$53,15,0)=0,"n.a",VLOOKUP(C112,[1]Calificación!$D$1:$X$53,15,0)),"") | M112: =IFERROR(IF(VLOOKUP(C112,[1]Calificación!$D$1:$X$53,16,0)=0,"n.a",VLOOKUP(C112,[1]Calificación!$D$1:$X$53,16,0)),"") | N112: =IFERROR(IF(VLOOKUP(C112,[1]Calificación!$D$1:$X$53,17,0)=0,"n.a",VLOOKUP(C112,[1]Calificación!$D$1:$X$53,17,0)),"") | P112: =IFERROR(IF(VLOOKUP(C112,[1]Calificación!$D$1:$X$53,18,0)=0,"n.a",VLOOKUP(C112,[1]Calificación!$D$1:$X$53,18,0)),"") | Q112: =IFERROR(IF(VLOOKUP(C112,[1]Calificación!$D$1:$X$53,19,0)=0,"n.a",VLOOKUP(C112,[1]Calificación!$D$1:$X$53,19,0)),"") | S112: =IFERROR(IF(VLOOKUP(C112,[1]Calificación!$D$1:$X$53,20,0)=0,"n.a",VLOOKUP(C112,[1]Calificación!$D$1:$X$53,20,0)),"") | T112: =IFERROR(IF(VLOOKUP(C112,[1]Calificación!$D$1:$X$53,21,0)=0,"n.a",VLOOKUP(C112,[1]Calificación!$D$1:$X$53,21,0)),"")
B113: =_xlfn.XLOOKUP(C113,[1]Calificación!D:D,[1]Calificación!A:A,"",0,1) | C113: =IF([1]Calificación!D102=0,"",[1]Calificación!D102) | D113: =IFERROR(VLOOKUP(C113,[1]Calificación!$D$1:$X$53,2,0),"") | G113: =IFERROR(VLOOKUP(C113,[1]Calificación!$D$1:$X$53,12,0),"") | H113: =IFERROR(IF(VLOOKUP(C113,[1]Calificación!$D$1:$X$53,13,0)=0,"n.a",VLOOKUP(C113,[1]Calificación!$D$1:$X$53,13,0)),"") | J113: =IFERROR(IF(VLOOKUP(C113,[1]Calificación!$D$1:$X$53,14,0)=0,"n.a",VLOOKUP(C113,[1]Calificación!$D$1:$X$53,14,0)),"") | K113: =IFERROR(IF(VLOOKUP(C113,[1]Calificación!$D$1:$X$53,15,0)=0,"n.a",VLOOKUP(C113,[1]Calificación!$D$1:$X$53,15,0)),"") | M113: =IFERROR(IF(VLOOKUP(C113,[1]Calificación!$D$1:$X$53,16,0)=0,"n.a",VLOOKUP(C113,[1]Calificación!$D$1:$X$53,16,0)),"") | N113: =IFERROR(IF(VLOOKUP(C113,[1]Calificación!$D$1:$X$53,17,0)=0,"n.a",VLOOKUP(C113,[1]Calificación!$D$1:$X$53,17,0)),"") | P113: =IFERROR(IF(VLOOKUP(C113,[1]Calificación!$D$1:$X$53,18,0)=0,"n.a",VLOOKUP(C113,[1]Calificación!$D$1:$X$53,18,0)),"") | Q113: =IFERROR(IF(VLOOKUP(C113,[1]Calificación!$D$1:$X$53,19,0)=0,"n.a",VLOOKUP(C113,[1]Calificación!$D$1:$X$53,19,0)),"") | S113: =IFERROR(IF(VLOOKUP(C113,[1]Calificación!$D$1:$X$53,20,0)=0,"n.a",VLOOKUP(C113,[1]Calificación!$D$1:$X$53,20,0)),"") | T113: =IFERROR(IF(VLOOKUP(C113,[1]Calificación!$D$1:$X$53,21,0)=0,"n.a",VLOOKUP(C113,[1]Calificación!$D$1:$X$53,21,0)),"")

Sheet Portadilla I
A7: I. Índice de Capitalización y Evaluación de la Calidad de la Información.
A8: El objetivo de este apartado es proporcionar al público los indicadores de capitalización de los bancos, con las cifras disponibles en la fecha de elaboración del presente boletín, así como la clasificación de las instituciones de banca múltiple en distintas categorías, de acuerdo con las disposiciones de Alertas Tempranas.
A9: Por otra parte, se presenta la evaluación de la calidad y oportunidad de la información que entregan las instituciones a este Organismo, la cual considera la oportunidad con la que reportan y el número de reenvíos.

Sheet Portadilla II
B2: II. Estadísticas de la Banca Múltiple
B3: El objetivo de este apartado es proporcionar al público indicadores estadísticos que reflejen adecuadamente la evolución de la condición financiera de la Banca Múltiple, por lo que en esta sección, se presenta la información reportada por las 52 instituciones de banca múltiple en operación correspondiente a julio de 2025, consolidada con la de sus SOFOMER en el caso de las siguientes instituciones: Banamex con Tarjetas Banamex; Santander con Santander Inclusión Financiera; CI Banco con Finanmadrid México; Banco del Bajío con Financiera Bajío; Banregio con Start Banregio; Inbursa con STM Financial, SOFOM Inbursa y CETELEM Inbursa; Afirme con Arrendadora Afirme; Banco Base con Arrendadora Base, Invex con Invex Consumo; Bancrea con Arrendadora Bancrea, así como Ve por Más con Arrendadora Ve por Más.
B5: Notas:
B7: 1/ Para la cartera total se considera la información de cartera de los bancos junto con la cartera de sus respectivas Sociedades Financieras de Objeto Múltiple Reguladas a las que consolidan. Hasta diciembre 2021: Cartera total = Cartera vigente + cartera vencida. A partir de enero 2022: Cartera total = Cartera de crédito con riesgo de crédito en etapa 1 + 2 + 3 + cartera de crédito valuada a valor razonable.
B9: 2/ Respecto al resultado neto se muestran saldos acumulados al cierre de mes.
B10: 3/ ROA = Resultado neto (flujo 12 meses) / Activos totales, promedio 12 meses.
B11: 4/ ROE = Resultado neto (flujo 12 meses) / Capital contable, promedio 12 meses.
B12: 5/ Hasta diciembre 2021: IMOR = Índice de Morosidad = cartera vencida / (Cartera vigente + cartera vencida). A partir de enero 2022: IMOR = Índice de Morosidad = cartera de crédito con riesgo de crédito en etapa 3 / (Cartera de crédito con riesgo de crédito en etapa 1 + 2 + 3).
B13: 6/ Hasta diciembre 2021: ICOR = Índice de cobertura= Estimaciones preventivas para riesgos crediticios del balance general / cartera de crédito vencida. A partir de enero 2022: ICOR = Índice de cobertura= Estimaciones preventivas para riesgos crediticios del estado de situación financiera / cartera de crédito con riesgo de crédito en etapa 3.
B14: 7/ Hasta diciembre 2021: Estimaciones preventivas para riesgo crediticio del balance general / (Cartera vigente + cartera vencida). A partir de enero 2022: Estimaciones preventivas para riesgo crediticio del estado de situación financiera / (Cartera de crédito con riesgo de crédito en etapa 1 + 2 + 3).
B16: */ En todos los casos se presentan las instituciones en orden descendente por tamaño de activo total en el mes de análisis más reciente.
B18: El símbolo ( - ) indica que la cifra es cero. Las cifras en cero indican una cantidad cercana a cero.
... B21: n.d.: No disponible

Sheet Pm2
B3: Principales rubros del estado de situación financiera y estado de resultado integral
B4: Millones de pesos y porcentajes
C5: Activo total | I5: Inversiones en instrumentos financieros | O5: Cartera total1/ | U5: Captación total | AA5: Capital contable | AG5: Resultado neto 2/
C6: 45474 | E6: 45809 | G6: 45839 | I6: =+$C$6 -> 45474 | K6: =+$E$6 -> 45809 | M6: =+$G$6 -> 45839 | O6: =+$C$6 -> 45474 | Q6: =+$E$6 -> 45809 | S6: =+$G$6 -> 45839 | U6: =+$C$6 -> 45474 | W6: =+$E$6 -> 45809 | Y6: =+$G$6 -> 45839 | AA6: =+$C$6 -> 45474 | AC6: =+$E$6 -> 45809 | AE6: =+$G$6 -> 45839 | AG6: =+$C$6 -> 45474 | AI6: =+$E$6 -> 45809 | AK6: =+$G$6 -> 45839
B7: Sistema */ | C7: 14250900 | D7: 100 | E7: 15291765 | F7: 100 | G7: 15388038 | H7: 100 | I7: 3765691.1 | J7: 100 | K7: 4019339.3 | L7: 100 | M7: 4052410.9 | N7: 100 | O7: 7229546 | P7: 100 | Q7: 7797749.9 | R7: 100 | S7: 7839661.6 | T7: 100 | U7: 8419009.1 | V7: 100 | W7: 9112459.1 | X7: 100 | Y7: 9174885.7 | Z7: 100 | AA7: 1588509.5 | AB7: 100 | AC7: 1751973.7 | AD7: 100 | AE7: 1775851.1 | AF7: 100 | AG7: 171838.95 | AH7: 100 | AI7: 152476.18 | AJ7: 100 | AK7: 178430.47 | AL7: 100
B8: BBVA México | C8: 3114454.9 | D8: 21.854444 | E8: 3322036.1 | F8: 21.724346 | G8: 3340530.4 | H8: 21.708617 | I8: 665247.96 | J8: 17.666026 | K8: 610149.88 | L8: 15.180353 | M8: 598949.41 | N8: 14.780076 | O8: 1814429.7 | P8: 25.097422 | Q8: 1992989.5 | R8: 25.558521 | S8: 2015513.2 | T8: 25.709186 | U8: 1807909.4 | V8: 21.474135 | W8: 2083231.9 | X8: 22.861359 | Y8: 2036733.9 | Z8: 22.199012 | AA8: 351794.66 | AB8: 22.14621 | AC8: 382849.72 | AD8: 21.852481 | AE8: 390680.59 | AF8: 21.999625 | AG8: 54549.034 | AH8: 31.744277 | AI8: 49443.265 | AJ8: 32.426879 | AK8: 57711.877 | AL8: 32.344182
B9: Santander | C9: 1881689.9 | D9: 13.204008 | E9: 1950806.7 | F9: 12.757237 | G9: 1974060 | H9: 12.828536 | I9: 601078.02 | J9: 15.961958 | K9: 588439.42 | L9: 14.640203 | M9: 593626.65 | N9: 14.648728 | O9: 880156.9 | P9: 12.174442 | Q9: 932042.92 | R9: 11.952716 | S9: 934236.43 | T9: 11.916795 | U9: 1018558.3 | V9: 12.098316 | W9: 1077295.9 | X9: 11.822231 | Y9: 1098918.5 | Z9: 11.977463 | AA9: 162165.49 | AB9: 10.208657 | AC9: 158890.49 | AD9: 9.0692279 | AE9: 161669.97 | AF9: 9.103802 | AG9: 17402.803 | AH9: 10.127391 | AI9: 15658.709 | AJ9: 10.26961 | AK9: 18535.116 | AL9: 10.387865
B10: Banorte | C10: 1788025.2 | D10: 12.546754 | E10: 1886627.8 | F10: 12.337541 | G10: 1887469.4 | H10: 12.265822 | I10: 397587.24 | J10: 10.558148 | K10: 430204.83 | L10: 10.703372 | M10: 451283.27 | N10: 11.136168 | O10: 1061820.3 | P10: 14.687234 | Q10: 1141382.7 | R10: 14.637334 | S10: 1148959.6 | T10: 14.655729 | U10: 1128928.2 | V10: 13.409276 | W10: 1210098.5 | X10: 13.279605 | Y10: 1186183.1 | Z10: 12.928587 | AA10: 147009.54 | AB10: 9.2545584 | AC10: 163319.58 | AD10: 9.322034 | AE10: 166405.23 | AF10: 9.3704493 | AG10: 26487.739 | AH10: 15.414281 | AI10: 23154.875 | AJ10: 15.185897 | AK10: 27354.42 | AL10: 15.330577
B11: Banamex | C11: 1505565.7 | D11: 10.564707 | E11: 1091590.1 | F11: 7.1384178 | G11: 1106121.1 | H11: 7.1881877 | I11: 571164.98 | J11: 15.1676 | K11: 397583.61 | L11: 9.8917653 | M11: 416428.74 | N11: 10.276074 | O11: 612393.6 | P11: 8.4707061 | Q11: 484729.32 | R11: 6.2162717 | S11: 486300.07 | T11: 6.2030748 | U11: 957318.31 | V11: 11.370914 | W11: 746120.08 | X11: 8.1879114 | Y11: 763127.06 | Z11: 8.3175647 | AA11: 225708.06 | AB11: 14.208795 | AC11: 176197.18 | AD11: 10.057068 | AE11: 177913.35 | AF11: 10.018483 | AG11: 14107.768 | AH11: 8.2098775 | AI11: 6696.5835 | AJ11: 4.3918884 | AK11: 8553.0559 | AL11: 4.7934951
B12: HSBC | C12: 877324.73 | D12: 6.1562761 | E12: 930938.04 | F12: 6.0878389 | G12: 907745.99 | H12: 5.8990364 | I12: 170070.79 | J12: 4.5163236 | K12: 213179.62 | L12: 5.3038473 | M12: 210476.27 | N12: 5.193853 | O12: 498407.66 | P12: 6.8940381 | Q12: 497726.33 | R12: 6.3829481 | S12: 493741.75 | T12: 6.2979982 | U12: 594973.04 | V12: 7.0670198 | W12: 567634.81 | X12: 6.2292165 | Y12: 574253.19 | Z12: 6.2589683 | AA12: 81604.711 | AB12: 5.1371875 | AC12: 85841.897 | AD12: 4.8997253 | AE12: 86701.786 | AF12: 4.8822665 | AG12: 5484.0527 | AH12: 3.1913909 | AI12: 4210.4206 | AJ12: 2.7613629 | AK12: 5108.3384 | AL12: 2.8629294
B13: Scotiabank | C13: 887994.22 | D13: 6.231145 | E13: 873397.97 | F13: 5.7115574 | G13: 861735.43 | H13: 5.6000343 | I13: 185061.29 | J13: 4.9144043 | K13: 163538.32 | L13: 4.0687862 | M13: 166595.17 | N13: 4.1110138 | O13: 523954.07 | P13: 7.2473993 | Q13: 521395.83 | R13: 6.6864908 | S13: 527986.99 | T13: 6.7348186 | U13: 603698.01 | V13: 7.1706539 | W13: 574302.99 | X13: 6.3023931 | Y13: 589058.65 | Z13: 6.4203378 | AA13: 84899.566 | AB13: 5.3446055 | AC13: 90784.527 | AD13: 5.181843 | AE13: 91615.061 | AF13: 5.1589381 | AG13: 6166.4227 | AH13: 3.5884894 | AI13: 4949.2409 | AJ13: 3.245911 | AK13: 5781.6631 | AL13: 3.2402891
B14: Inbursa | C14: 617591.42 | D14: 4.3337013 | E14: 701151.91 | F14: 4.58516 | G14: 698989.33 | H14: 4.54242 | I14: 65740.009 | J14: 1.7457621 | K14: 77138.307 | L14: 1.9191788 | M14: 70030.352 | N14: 1.7281158 | O14: 430414.24 | P14: 5.9535445 | Q14: 462573.5 | R14: 5.9321407 | S14: 461921.58 | T14: 5.8921112 | U14: 419524.95 | V14: 4.983068 | W14: 460048.99 | X14: 5.0485713 | Y14: 465217.13 | Z14: 5.0705496 | AA14: 167612.82 | AB14: 10.551578 | AC14: 198560.63 | AD14: 11.333539 | AE14: 200527.29 | AF14: 11.291897 | AG14: 14117.417 | AH14: 8.2154927 | AI14: 11562.677 | AJ14: 7.5832682 | AK14: 13661.102 | AL14: 7.6562607
B15: Citi México | C15: 2069.4533 | D15: 0.014521563 | E15: 567213.88 | F15: 3.7092766 | G15: 577231.71 | H15: 3.7511715 | I15: 0.00098524 | J15: 2.616359e-08 | K15: 202299.19 | L15: 5.0331455 | M15: 235392.56 | N15: 5.8087043 | O15: 0 | P15: 0 | Q15: 182823.18 | R15: 2.3445633 | S15: 167718.59 | T15: 2.1393601 | U15: 0 | V15: 0 | W15: 337251.71 | X15: 3.7009956 | Y15: 339318.51 | Z15: 3.6983405 | AA15: 1533.653 | AB15: 0.096546669 | AC15: 74437.059 | AD15: 4.2487544 | AE15: 75077.878 | AF15: 4.2277123 | AG15: -2.4246254 | AH15: -0.0014109871 | AI15: 5761.7684 | AJ15: 3.7787991 | AK15: 6447.7772 | AL15: 3.6136077
B16: Banco del Bajío | C16: 339861.56 | D16: 2.3848428 | E16: 372552.28 | F16: 2.4362934 | G16: 374884.01 | H16: 2.436204 | I16: 23815.534 | J16: 0.63243461 | K16: 28005.059 | L16: 0.69675778 | M16: 28262.579 | N16: 0.6974263 | O16: 246819.31 | P16: 3.4140361 | Q16: 265190.05 | R16: 3.4008534 | S16: 264080.65 | T16: 3.368521 | U16: 277484.84 | V16: 3.2959323 | W16: 308786.25 | X16: 3.3886161 | Y16: 310533.69 | Z16: 3.3846056 | AA16: 41415.827 | AB16: 2.6072131 | AC16: 44836.97 | AD16: 2.5592262 | AE16: 45523.253 | AF16: 2.5634611 | AG16: 6499.4597 | AH16: 3.7822971 | AI16: 4656.6649 | AJ16: 3.0540279 | AK16: 5367.0088 | AL16: 3.0078992
B17: Banco Azteca | C17: 308305.92 | D17: 2.1634137 | E17: 348431.86 | F17: 2.2785588 | G17: 358130.15 | H17: 2.3273282 | I17: 84134.092 | J17: 2.2342271 | K17: 102744.81 | L17: 2.5562611 | M17: 107881.59 | N17: 2.6621582 | O17: 177632.42 | P17: 2.4570342 | Q17: 193792 | R17: 2.4852297 | S17: 201079.6 | T17: 2.5649015 | U17: 217320.54 | V17: 2.5813078 | W17: 241453.28 | X17: 2.649705 | Y17: 242117.71 | Z17: 2.638918 | AA17: 36500.64 | AB17: 2.2977917 | AC17: 44174.221 | AD17: 2.5213975 | AE17: 44506.63 | AF17: 2.506214 | AG17: 3027.4149 | AH17: 1.7617745 | AI17: 3047.396 | AJ17: 1.9986047 | AK17: 3379.8051 | AL17: 1.8941861
B18: Afirme | C18: 298548.61 | D18: 2.0949457 | E18: 307728.44 | F18: 2.0123801 | G18: 311426.66 | H18: 2.023823 | I18: 173782.67 | J18: 4.6148944 | K18: 173690.31 | L18: 4.3213647 | M18: 177438.47 | N18: 4.3785902 | O18: 64129.659 | P18: 0.8870496 | Q18: 68546.657 | R18: 0.87905687 | S18: 68150.646 | T18: 0.86930597 | U18: 93503.637 | V18: 1.1106252 | W18: 88530.454 | X18: 0.97153197 | Y18: 84558.258 | Z18: 0.92162738 | AA18: 8472.2736 | AB18: 0.53334737 | AC18: 9063.979 | AD18: 0.51735817 | AE18: 9157.2074 | AF18: 0.51565174 | AG18: 304.55061 | AH18: 0.17723025 | AI18: 458.35173 | AJ18: 0.30060547 | AK18: 540.2653 | AL18: 0.30278758
... B59: Pagatodo | C59: 395.43887 | D59: 0.0027748344 | E59: 342.51926 | F59: 0.0022398935 | G59: 353.01674 | H59: 0.0022940984 | I59: 0 | J59: 0 | K59: 0 | L59: 0 | M59: 0 | N59: 0 | O59: 0 | P59: 0 | Q59: 0 | R59: 0 | S59: 0 | T59: 0 | U59: 26.174597 | V59: 0.00031089878 | W59: 21.57985 | X59: 0.00023681698 | Y59: 27.968025 | Z59: 0.00030483241 | AA59: 353.59994 | AB59: 0.022259857 | AC59: 302.34515 | AD59: 0.017257402 | AE59: 311.01369 | AF59: 0.0175135 | AG59: -41.751171 | AH59: -0.024296686 | AI59: -41.171634 | AJ59: -0.027002011 | AK59: -47.503086 | AL59: -0.026622743

Sheet Indicadores
B2: Indicadores financieros
B3: Porcentajes | O3: 1.5853443
C5: ROA (Flujo 12 meses) 3/ | F5: ROE (Flujo 12 meses) 4/
C6: 45474 | D6: 45809 | E6: 45839 | F6: =+C6 -> 45474 | G6: =+D6 -> 45809 | H6: =+E6 -> 45839
B7: Sistema */ | C7: 2.1000991 | D7: 1.9872541 | E7: 1.9686734 | F7: 18.689216 | G7: 17.729083 | H7: 17.511634
B8: BBVA México | C8: 3.0337262 | D8: 2.9519933 | E8: 2.9236001 | F8: 26.634879 | G8: 26.077726 | H8: 25.7504
B9: Santander | C9: 1.518794 | D9: 1.501388 | E9: 1.5078758 | F9: 17.241766 | G9: 18.462192 | H9: 18.619496
B10: Banorte | C10: 2.5334255 | D10: 2.4864977 | E10: 2.4773689 | F10: 29.1176 | G10: 29.283778 | H10: 29.008945
B11: Banamex | C11: 1.6678524 | D11: 1.3417185 | E11: 1.3808035 | F11: 11.584077 | G11: 8.636677 | H11: 8.8335011
B12: HSBC | C12: 1.025533 | D12: 0.71001546 | E12: 0.70730798 | F12: 10.718761 | G12: 7.8180739 | H12: 7.7701024
B13: Scotiabank | C13: 1.3129002 | D13: 1.2275887 | E13: 1.1895722 | F13: 13.605504 | G13: 12.234088 | H13: 11.752307
B14: Inbursa | C14: 4.1965767 | D14: 3.6814906 | E14: 3.6215481 | F14: 15.653389 | G14: 13.236336 | H14: 12.961588
B15: Citi México | C15: 3.079141 | D15: 1.2497226 | E15: 1.2665408 | F15: 3.3864123 | G15: 10.250186 | H15: 10.327018
B16: Banco del Bajío | C16: 3.2971942 | D16: 2.7030851 | E16: 2.6363784 | F16: 27.176524 | G16: 21.810486 | H16: 21.281448
B17: Banco Azteca | C17: 1.3062664 | D17: 1.7919507 | E17: 1.7763661 | F17: 10.93443 | G17: 14.640319 | H17: 14.45623
B18: Afirme | C18: 0.14473994 | D18: 0.23656955 | E18: 0.24656215 | F18: 4.9271382 | G18: 8.1256616 | H18: 8.4441541
... B48: Volkswagen Bank | C48: 7.5986233 | D48: 5.8534165 | E48: 5.9361469 | F48: 10.508124 | G48: 11.821859 | H48: 12.266385
B49: Openbank | C49: n.a. | D49: -28.036862 | E49: -26.245312 | F49: n.a. | G49: -35.430955 | H49: -35.059007
B50: Shinhan | C50: 2.4855955 | D50: 1.9308331 | E50: 1.7688039 | F50: 7.5678009 | G50: 6.6582391 | H50: 6.1589319
B51: Banco Ualá | C51: -25.426725 | D51: -18.264549 | E51: -18.776095 | F51: -128.50115 | G51: -151.57141 | H51: -154.2955
B52: Banco S3 | C52: 5.8080374 | D52: 5.6348784 | E52: 5.5992688 | F52: 13.964316 | G52: 13.186146 | H52: 13.23618
B53: KEB Hana México | C53: 0.87764407 | D53: 0.86597337 | E53: 0.80838528 | F53: 2.546091 | G53: 2.8422865 | H53: 2.6714134
B54: Banco Bineo | C54: -27.397434 | D54: -30.520194 | E54: -30.346281 | F54: -29.910085 | G54: -32.953984 | H54: -32.608705
B55: Dondé Banco | C55: -10.909768 | D55: -5.3406472 | E55: -5.0866478 | F55: -19.174581 | G55: -22.466151 | H55: -22.529182
B56: Credit Suisse | C56: -12.590114 | D56: -5.1695375 | E56: -4.8495628 | F56: -19.991813 | G56: -5.7376741 | H56: -5.2370058
B57: Hey Banco | C57: n.a. | D57: 6.3969044 | E57: 5.6622236 | F57: n.a. | G57: 6.4296263 | H57: 5.6890569
B58: Forjadores | C58: 0.229957 | D58: -1.2013703 | E58: -1.8791918 | F58: 0.32953565 | G58: -1.7240703 | H58: -2.7057418
B59: Pagatodo | C59: -11.665991 | D59: -21.086738 | E59: -21.537666 | F59: -17.967557 | G59: -24.151553 | H59: -24.703061

Sheet CCT
B2: Cartera de crédito total
B3: Millones de pesos y porcentajes
C5: Cartera total (MDP) 1/ | F5: IMOR (%) 5/ | I5: ICOR (%) 6/ | L5: Pérdida esperada (%) 7/
C6: 45474 | D6: 45809 | E6: 45839 | F6: =C6 -> 45474 | G6: =D6 -> 45809 | H6: =E6 -> 45839 | I6: =C6 -> 45474 | J6: =D6 -> 45809 | K6: =E6 -> 45839 | L6: =C6 -> 45474 | M6: =D6 -> 45809 | N6: =E6 -> 45839
B7: Sistema */ | C7: 7229546 | D7: 7797749.9 | E7: 7839661.6 | F7: 2.0071312 | G7: 2.1016541 | H7: 2.1254588 | I7: 157.05016 | J7: 152.26446 | K7: 151.25758 | L7: 3.1522027 | M7: 3.2000723 | N7: 3.2149175
B8: BBVA México | C8: 1814429.7 | D8: 1992989.5 | E8: 2015513.2 | F8: 1.648246 | G8: 1.6626646 | H8: 1.6346425 | I8: 189.79508 | J8: 185.95197 | K8: 189.1028 | L8: 3.1282897 | M8: 3.0917575 | N8: 3.0911547
B9: Santander | C9: 880156.9 | D9: 932042.92 | E9: 934236.43 | F9: 2.1755974 | G9: 2.3068186 | H9: 2.3224121 | I9: 140.4523 | J9: 136.50075 | K9: 134.65926 | L9: 3.0556766 | M9: 3.1488246 | N9: 3.1273428
B10: Banorte | C10: 1061820.3 | D10: 1141382.7 | E10: 1148959.6 | F10: 0.95815611 | G10: 1.0977863 | H10: 1.1035814 | I10: 175.86451 | J10: 152.28908 | K10: 152.29449 | L10: 1.6850566 | M10: 1.6718086 | N10: 1.6806937
B11: Banamex | C11: 612393.6 | D11: 484729.32 | E11: 486300.07 | F11: 2.137527 | G11: 2.7870775 | H11: 2.8293089 | I11: 201.70285 | J11: 192.2565 | K11: 189.17816 | L11: 4.3114528 | M11: 5.3583378 | N11: 5.3524345
B12: HSBC | C12: 498407.66 | D12: 497726.33 | E12: 493741.75 | F12: 2.209556 | G12: 2.5020973 | H12: 2.7387882 | I12: 154.16456 | J12: 150.94051 | K12: 139.95075 | L12: 3.4063523 | M12: 3.7766783 | N12: 3.8329547
B13: Scotiabank | C13: 523954.07 | D13: 521395.83 | E13: 527986.99 | F13: 3.6628194 | G13: 4.0162303 | H13: 4.0517553 | I13: 75.725386 | J13: 69.283656 | K13: 68.652291 | L13: 2.7736841 | M13: 2.7825912 | N13: 2.7816228
B14: Inbursa | C14: 430414.24 | D14: 462573.5 | E14: 461921.58 | F14: 1.5474035 | G14: 1.4633674 | H14: 1.4786003 | I14: 141.91651 | J14: 150.92454 | K14: 149.75024 | L14: 2.1960211 | M14: 2.2085804 | N14: 2.2142075
B15: Citi México | C15: 0 | D15: 182823.18 | E15: 167718.59 | F15: - | G15: 1.2394049 | H15: 1.350366 | I15: - | J15: 185.60963 | K15: 189.67717 | L15: - | M15: 2.3004549 | N15: 2.561336
B16: Banco del Bajío | C16: 246819.31 | D16: 265190.05 | E16: 264080.65 | F16: 1.5594084 | G16: 1.8343591 | H16: 1.8704086 | I16: 145.43874 | J16: 119.09661 | K16: 121.57592 | L16: 2.2679838 | M16: 2.1846596 | N16: 2.2739665
B17: Banco Azteca | C17: 177632.42 | D17: 193792 | E17: 201079.6 | F17: 3.2442473 | G17: 4.065389 | H17: 4.2294726 | I17: 342.15309 | J17: 288.43673 | K17: 274.04411 | L17: 11.100293 | M17: 11.726075 | N17: 11.590621
B18: Afirme | C18: 64129.659 | D18: 68546.657 | E18: 68150.646 | F18: 5.5273862 | G18: 3.9902362 | H18: 3.9543661 | I18: 68.158152 | J18: 85.247519 | K18: 86.624197 | L18: 3.7673643 | M18: 3.4015774 | N18: 3.4254379
B19: Monex | C19: 42410.257 | D19: 55217.342 | E19: 55679.67 | F19: 1.4063107 | G19: 1.4519538 | H19: 1.4838624 | I19: 153.88106 | J19: 130.06922 | K19: 128.40821 | L19: 2.1640458 | M19: 1.8885449 | N19: 1.9054012
B20: Banregio | C20: 167647.78 | D20: 184117.85 | E20: 184818.19 | F20: 1.301245 | G20: 1.5028619 | H20: 1.4945681 | I20: 164.6593 | J20: 140.32033 | K20: 143.5183 | L20: 2.1426209 | M20: 2.1088207 | N20: 2.1449786
B21: J.P. Morgan | C21: 19096.845 | D21: 24623.542 | E21: 25545.122 | F21: 0 | G21: 0 | H21: 0 | I21: - | J21: - | K21: - | L21: 0.71633014 | M21: 0.65361509 | N21: 0.61994842
B22: Invex | C22: 40370.847 | D22: 47571.074 | E22: 49386.651 | F22: 2.1941927 | G22: 2.3495376 | H22: 2.1702776 | I22: 228.72152 | J22: 244.16324 | K22: 257.61508 | L22: 5.0185909 | M22: 5.7367071 | N22: 5.5909625
B23: Bank of America | C23: 32183.869 | D23: 40215.168 | E23: 41861.69 | F23: 0 | G23: 0 | H23: 0 | I23: - | J23: - | K23: - | L23: 0.81279813 | M23: 0.81053787 | N23: 1.0426333
B24: BanCoppel | C24: 60875.435 | D24: 70278.652 | E24: 69846.329 | F24: 8.0218693 | G24: 5.958428 | H24: 5.881127 | I24: 137.87664 | J24: 145.97489 | K24: 149.55988 | L24: 11.060284 | M24: 8.6978086 | N24: 8.7958066
B25: Banca Mifel | C25: 75813.117 | D25: 82455.168 | E25: 83334.566 | F25: 2.4526773 | G25: 2.561652 | H25: 2.6526099 | I25: 86.497934 | J25: 88.758729 | K25: 86.550689 | L25: 2.1215152 | M25: 2.2736897 | N25: 2.2958521
B26: Multiva | C26: 67072.414 | D26: 76473.215 | E26: 80241.469 | F26: 3.3096588 | G26: 2.8116236 | H26: 2.6201476 | I26: 99.368613 | J26: 108.13525 | K26: 112.41907 | L26: 3.2887621 | M26: 3.0403562 | N26: 2.9455456
B27: Banco Base | C27: 11389.211 | D27: 11001.653 | E27: 10522.093 | F27: 1.90157 | G27: 2.875475 | H27: 3.1417019 | I27: 140.72343 | J27: 104.71268 | K27: 104.19206 | L27: 2.6759546 | M27: 3.0109871 | N27: 3.2734038
B28: Barclays | C28: 0 | D28: 0 | E28: 0 | F28: - | G28: - | H28: - | I28: - | J28: - | K28: - | L28: - | M28: - | N28: -
B29: Sabadell | C29: 93792.06 | D29: 97906.152 | E29: 100065.78 | F29: 1.8691659 | G29: 2.3014467 | H29: 2.2519243 | I29: 75.26519 | J29: 65.037883 | K29: 66.052912 | L29: 1.4068313 | M29: 1.4968122 | N29: 1.4874616
B30: Ve por Más | C30: 57184.649 | D30: 59053.05 | E30: 60019.8 | F30: 3.0448065 | G30: 2.9198691 | H30: 2.8738416 | I30: 102.42263 | J30: 105.19546 | K30: 107.71404 | L30: 3.1185709 | M30: 3.0715698 | N30: 3.095531
B31: CIBanco | C31: 13301.435 | D31: 17706.215 | E31: 16743.919 | F31: 3.5038435 | G31: 2.9305622 | H31: 3.3272579 | I31: 102.51799 | J31: 103.63729 | K31: 102.02887 | L31: 3.5920698 | M31: 3.0371553 | N31: 3.3947636
B32: Bansí | C32: 22336.473 | D32: 27225.967 | E32: 29730.699 | F32: 4.473928 | G32: 4.0523093 | H32: 3.6975682 | I32: 153.94531 | J32: 163.16403 | K32: 166.68465 | L32: 6.8874021 | M32: 6.611911 | N32: 6.1632786
B33: Actinver | C33: 26631.983 | D33: 27833.813 | E33: 28375.644 | F33: 3.3676056 | G33: 3.3312494 | H33: 3.3318947 | I33: 111.48461 | J33: 118.54876 | K33: 107.55651 | L33: 3.754362 | M33: 3.9491548 | N33: 3.5836697
B34: Compartamos | C34: 45844.851 | D34: 54933.984 | E34: 58883.972 | F34: 2.9944215 | G34: 3.315018 | H34: 3.1850154 | I34: 250.62136 | J34: 237.5763 | K34: 234.46744 | L34: 7.5046599 | M34: 7.8756971 | N34: 7.467824
B35: BIAfirme | C35: 273.32896 | D35: 245.00795 | E35: 244.16608 | F35: 0 | G35: 0 | H35: 0 | I35: - | J35: - | K35: - | L35: 0.52316263 | M35: 0.44387457 | N35: 0.44172885
B36: Intercam Banco | C36: 20157.505 | D36: 25340.782 | E36: 18997.184 | F36: 2.5172953 | G36: 3.2699457 | H36: 4.8650035 | I36: 217.23129 | J36: 164.63899 | K36: 144.79065 | L36: 5.4683529 | M36: 5.3836055 | N36: 7.0440702
B37: Bancrea | C37: 35240.32 | D37: 42730.05 | E37: 43235.349 | F37: 0.82656864 | G37: 1.0398351 | H37: 1.035172 | I37: 124.16798 | J37: 151.16894 | K37: 149.35787 | L37: 1.0263336 | M37: 1.5719076 | N37: 1.5461108
B38: MUFG Bank | C38: 11647.884 | D38: 7306.8789 | E38: 6866.0949 | F38: 0 | G38: 0 | H38: 0 | I38: - | J38: - | K38: - | L38: 0.5364314 | M38: 0.81356373 | N38: 0.78265206
B39: Consubanco | C39: 22999.082 | D39: 30230.936 | E39: 30750.111 | F39: 1.7633557 | G39: 1.6858286 | H39: 1.6180695 | I39: 210.41225 | J39: 216.28173 | K39: 224.02722 | L39: 3.7103164 | M39: 3.6461391 | N39: 3.6249161
B40: BNP Paribas México | C40: 0 | D40: 0 | E40: 0 | F40: - | G40: - | H40: - | I40: - | J40: - | K40: - | L40: - | M40: - | N40: -
B41: Autofin | C41: 3639.7169 | D41: 9289.4392 | E41: 9513.4427 | F41: 3.1805317 | G41: 3.7459694 | H41: 3.2162558 | I41: 157.9498 | J41: 117.03858 | K41: 131.88122 | L41: 5.0236436 | M41: 4.3842293 | N41: 4.2416374
B42: Bankaool | C42: 7214.4852 | D42: 11775.756 | E42: 12586.946 | F42: 1.4363382 | G42: 0.94051365 | H42: 0.88075599 | I42: 197.18341 | J42: 215.234 | K42: 209.12365 | L42: 2.8322205 | M42: 2.0243052 | N42: 1.8418691
B43: Inmobiliario Mexicano | C43: 11125.018 | D43: 12503.222 | E43: 12477.747 | F43: 3.9699466 | G43: 2.8683248 | H43: 2.8705839 | I43: 60.240819 | J43: 63.388932 | K43: 65.885064 | L43: 2.3915283 | M43: 1.8182004 | N43: 1.891286
B44: Mizuho Bank | C44: 5742.0744 | D44: 5806.0211 | E44: 6063.7803 | F44: 0 | G44: 0 | H44: 0 | I44: - | J44: - | K44: - | L44: 0.43826501 | M44: 0.43035416 | N44: 0.46593333
B45: ICBC | C45: 3333.0608 | D45: 4250.5851 | E45: 4847.7865 | F45: 0 | G45: 0 | H45: 0 | I45: - | J45: - | K45: - | L45: 3.2745828 | M45: 2.1659089 | N45: 1.9621832
B46: Banco Covalto | C46: 4515.162 | D46: 6910.2811 | E46: 6995.6593 | F46: 6.7387301 | G46: 5.054202 | H46: 5.1230232 | I46: 62.684988 | J46: 67.940321 | K46: 69.276736 | L46: 4.2241722 | M46: 3.4338411 | N46: 3.5490632
B47: Bank of China | C47: 4404.5731 | D47: 3588.8459 | E47: 3537.1302 | F47: 3.952112 | G47: 3.6674515 | H47: 3.3687604 | I47: 97.412492 | J47: 110.38834 | K47: 111.31278 | L47: 3.8498508 | M47: 4.0484388 | N47: 3.7498608
B48: Volkswagen Bank | C48: 4774.4336 | D48: 7208.5168 | E48: 7276.972 | F48: 0.9582271 | G48: 1.2097473 | H48: 1.0732016 | I48: 246.68678 | J48: 217.48819 | K48: 210.49931 | L48: 2.3638196 | M48: 2.6310575 | N48: 2.2590819
B49: Openbank | C49: 0 | D49: 86.174941 | E49: 137.80434 | F49: - | G49: 0.071860798 | H49: 0.90948808 | I49: - | J49: 24627.673 | K49: 2173.6899 | L49: - | M49: 17.697643 | N49: 19.769451
B50: Shinhan | C50: 3276.7847 | D50: 3931.2596 | E50: 4552.7844 | F50: 1.6993355 | G50: 1.4164307 | H50: 1.2230662 | I50: 58.945473 | J50: 66.062442 | K50: 82.618728 | L50: 1.0016814 | M50: 0.9357287 | N50: 1.0104817
B51: Banco Ualá | C51: 481.59008 | D51: 727.32726 | E51: 753.47903 | F51: 28.291762 | G51: 16.879522 | H51: 16.617521 | I51: 80.032006 | J51: 112.65052 | K51: 119.81877 | L51: 22.642464 | M51: 19.014869 | N51: 19.910909
B52: Banco S3 | C52: 8.56684 | D52: 187.93514 | E52: 159.36079 | F52: 0 | G52: 0 | H52: 0 | I52: - | J52: - | K52: - | L52: 0.31325436 | M52: 0.85881489 | N52: 1.0595655
B53: KEB Hana México | C53: 3335.1595 | D53: 3824.654 | E53: 3885.1295 | F53: 1.6654726 | G53: 1.5047377 | H53: 1.485582 | I53: 105.85198 | J53: 126.51901 | K53: 128.45375 | L53: 1.7629357 | M53: 1.9037793 | N53: 1.9082858
B54: Banco Bineo | C54: 31.28364 | D54: 18.537722 | E54: 13.728232 | F54: 1.9831528 | G54: 39.966389 | H54: 41.156656 | I54: 489.84201 | J54: 100.3292 | K54: 98.108709 | L54: 9.7143154 | M54: 40.097958 | N54: 40.378264
B55: Dondé Banco | C55: 736.13702 | D55: 1618.3612 | E55: 1640.4681 | F55: 0.44077052 | G55: 0.2004914 | H55: 0.19778958 | I55: 172.83851 | J55: 390.27517 | K55: 388.35683 | L55: 0.76182121 | M55: 0.78246815 | N55: 0.76812936
B56: Credit Suisse | C56: 0 | D56: 0 | E56: 0 | F56: - | G56: - | H56: - | I56: - | J56: - | K56: - | L56: - | M56: - | N56: -
B57: Hey Banco | C57: 0 | D57: 0 | E57: 0 | F57: - | G57: - | H57: - | I57: - | J57: - | K57: - | L57: - | M57: - | N57: -
B58: Forjadores | C58: 500.79683 | D58: 364.49306 | E58: 381.86234 | F58: 6.3837568 | G58: 11.51854 | H58: 9.7035952 | I58: 146.98541 | J58: 120.36459 | K58: 125.55923 | L58: 9.3831913 | M58: 13.864242 | N58: 12.18376
B59: Pagatodo | C59: 0 | D59: 0 | E59: 0 | F59: - | G59: - | H59: - | I59: - | J59: - | K59: - | L59: - | M59: - | N59: -

Sheet CCE
B2: Cartera de crédito a empresas
B3: Millones de pesos y porcentajes
C5: Cartera total (MDP) 1/ | F5: IMOR (%) 5/ | I5: ICOR (%) 6/ | L5: Pérdida esperada (%) 7/
C6: 45474 | D6: 45809 | E6: 45839 | F6: =C6 -> 45474 | G6: =D6 -> 45809 | H6: =E6 -> 45839 | I6: =C6 -> 45474 | J6: =D6 -> 45809 | K6: =E6 -> 45839 | L6: =C6 -> 45474 | M6: =D6 -> 45809 | N6: =E6 -> 45839
B7: Sistema */ | C7: 3415147.8 | D7: 3704272.8 | E7: 3727749.3 | F7: 1.6869629 | G7: 1.7032783 | H7: 1.7291745 | I7: 98.588435 | J7: 97.355877 | K7: 97.092335 | L7: 1.6631504 | M7: 1.6582415 | N7: 1.6788959
B8: BBVA México | C8: 758333.85 | D8: 829730.83 | E8: 845064.71 | F8: 1.298138 | G8: 1.1445644 | H8: 1.0930512 | I8: 94.680976 | J8: 101.99607 | K8: 107.45246 | L8: 1.2290897 | M8: 1.1674107 | N8: 1.1745104
B9: Santander | C9: 367828.5 | D9: 386570.24 | E9: 387976.99 | F9: 1.3535625 | G9: 1.5088915 | H9: 1.5405653 | I9: 98.845607 | J9: 98.467597 | K9: 97.156531 | L9: 1.337937 | M9: 1.4857692 | N9: 1.4967598
B10: Banorte | C10: 416460.27 | D10: 452770.24 | E10: 454619.9 | F10: 0.94395419 | G10: 1.1629068 | H10: 1.1437797 | I10: 96.632432 | J10: 66.291952 | K10: 68.126721 | L10: 0.9121659 | M10: 0.7709136 | N10: 0.77921957
B11: Banamex | C11: 243153.39 | D11: 132126.95 | E11: 130847.47 | F11: 1.1369857 | G11: 2.8298142 | H11: 2.9437062 | I11: 163.57328 | J11: 100.59623 | K11: 96.591479 | L11: 1.8598048 | M11: 2.8466865 | N11: 2.8433693
B12: HSBC | C12: 215072.55 | D12: 223079.65 | E12: 222562.97 | F12: 2.0672704 | G12: 2.2910929 | H12: 2.8024905 | I12: 90.444959 | J12: 106.09173 | K12: 86.598885 | L12: 1.8697419 | M12: 2.4306601 | N12: 2.4269255
B13: Scotiabank | C13: 199544.45 | D13: 187923.94 | E13: 192263.08 | F13: 3.5503582 | G13: 2.8123065 | H13: 2.8542654 | I13: 86.78343 | J13: 78.052043 | K13: 78.308601 | L13: 3.0811226 | M13: 2.1950627 | N13: 2.2351353
B14: Inbursa | C14: 298404.99 | D14: 320032.28 | E14: 321335.89 | F14: 1.5994125 | G14: 1.5159802 | H14: 1.494835 | I14: 115.05628 | J14: 118.90261 | K14: 120.13973 | L14: 1.8402244 | M14: 1.80254 | N14: 1.7958907
B15: Citi México | C15: 0 | D15: 142814.03 | E15: 137893.37 | F15: - | G15: 0.0071214279 | H15: 0.0065067991 | I15: - | J15: 15729.19 | K15: 17977.824 | L15: - | M15: 1.1201429 | N15: 1.1697809
B16: Banco del Bajío | C16: 207166.71 | D16: 229015.87 | E16: 228199.91 | F16: 1.6684895 | G16: 1.924131 | H16: 1.969894 | I16: 100.61682 | J16: 92.820771 | K16: 95.214421 | L16: 1.678781 | M16: 1.7859933 | N16: 1.8756232
B17: Banco Azteca | C17: 45138.057 | D17: 40345.131 | E17: 44433.97 | F17: 0.95833728 | G17: 3.0459159 | H17: 2.7649932 | I17: 81.159453 | J17: 49.958858 | K17: 56.704017 | L17: 0.7777813 | M17: 1.5217048 | N17: 1.5678622
B18: Afirme | C18: 36536.424 | D18: 39927.423 | E18: 39323.978 | F18: 6.6277771 | G18: 4.490468 | H18: 4.5647443 | I18: 44.469088 | J18: 53.277349 | K18: 54.302093 | L18: 2.947312 | M18: 2.3924023 | N18: 2.4787517
B19: Monex | C19: 32667.158 | D19: 41710.675 | E19: 41614.196 | F19: 1.6761537 | G19: 1.8160797 | H19: 1.8939995 | I19: 134.78391 | J19: 112.70552 | K19: 110.35244 | L19: 2.2591855 | M19: 2.046822 | N19: 2.0900747
B20: Banregio | C20: 134939.08 | D20: 147943.19 | E20: 148361.92 | F20: 1.2124152 | G20: 1.51766 | H20: 1.5097903 | I20: 133.99829 | J20: 110.42067 | K20: 114.66077 | L20: 1.6246156 | M20: 1.6758103 | N20: 1.7311372
B21: J.P. Morgan | C21: 19085.34 | D21: 23770.677 | E21: 24248.486 | F21: 0 | G21: 0 | H21: 0 | I21: - | J21: - | K21: - | L21: 0.70097689 | M21: 0.63402605 | N21: 0.60987204
B22: Invex | C22: 14172.766 | D22: 13834.513 | E22: 14881.706 | F22: 2.4631532 | G22: 1.996656 | H22: 1.8285654 | I22: 80.052622 | J22: 111.74424 | K22: 119.84949 | L22: 1.9718187 | M22: 2.2311481 | N22: 2.1915263
B23: Bank of America | C23: 27684.477 | D23: 27325.407 | E23: 28411.346 | F23: 0 | G23: 0 | H23: 0 | I23: - | J23: - | K23: - | L23: 0.88510385 | M23: 0.84781328 | N23: 1.1874196
B24: BanCoppel | C24: 32202.065 | D24: 41959.665 | E24: 41303.117 | F24: 3.9970273 | G24: 3.791287 | H24: 3.7822899 | I24: 78.692541 | J24: 81.059188 | K24: 86.626422 | L24: 3.1453623 | M24: 3.0731865 | N24: 3.2764624
B25: Banca Mifel | C25: 50746.735 | D25: 58930.895 | E25: 59764.998 | F25: 1.3874607 | G25: 1.2249575 | H25: 1.1732697 | I25: 123.28409 | J25: 145.07861 | K25: 146.55307 | L25: 1.7105182 | M25: 1.7771514 | N25: 1.7194627
B26: Multiva | C26: 32952.945 | D26: 40751.421 | E26: 42771.104 | F26: 5.2346614 | G26: 4.1869802 | H26: 3.8824297 | I26: 86.524648 | J26: 94.25058 | K26: 97.585618 | L26: 4.5292724 | M26: 3.9462532 | N26: 3.788693
B27: Banco Base | C27: 10994.78 | D27: 10694.104 | E27: 10225.457 | F27: 1.9697876 | G27: 2.9581703 | H27: 3.2328412 | I27: 107.53339 | J27: 84.896894 | K27: 85.596186 | L27: 2.1181794 | M27: 2.5113947 | N27: 2.7671888
B28: Barclays | C28: 0 | D28: 0 | E28: 0 | F28: - | G28: - | H28: - | I28: - | J28: - | K28: - | L28: - | M28: - | N28: -
B29: Sabadell | C29: 91103.874 | D29: 95521.632 | E29: 97372.271 | F29: 1.8163116 | G29: 2.3574069 | H29: 2.312779 | I29: 74.144055 | J29: 64.522403 | K29: 65.431454 | L29: 1.3466871 | M29: 1.5210556 | N29: 1.5132849
B30: Ve por Más | C30: 40081.371 | D30: 43602.428 | E30: 43982.27 | F30: 3.930021 | G30: 3.6638171 | H30: 3.670094 | I30: 77.022859 | J30: 81.341647 | K30: 83.36192 | L30: 3.0270145 | M30: 2.9802091 | N30: 3.0594608
B31: CIBanco | C31: 4720.7779 | D31: 6938.5338 | E31: 6578.9624 | F31: 4.4231855 | G31: 4.4765561 | H31: 5.0529099 | I31: 73.496086 | J31: 70.999904 | K31: 71.063815 | L31: 3.2508682 | M31: 3.1783506 | N31: 3.5907905
B32: Bansí | C32: 17505.078 | D32: 18974.086 | E32: 19102.034 | F32: 5.3930418 | G32: 5.4049918 | H32: 5.3504309 | I32: 130.63498 | J32: 150.20064 | K32: 151.00092 | L32: 7.0451991 | M32: 8.1183322 | N32: 8.0791998
B33: Actinver | C33: 22051.469 | D33: 22313.882 | E33: 22346.736 | F33: 3.0658475 | G33: 3.0878394 | H33: 3.2085731 | I33: 99.170821 | J33: 96.256212 | K33: 85.317737 | L33: 3.0404262 | M33: 2.9722372 | N33: 2.737482
B34: Compartamos | C34: 0 | D34: 0 | E34: 0 | F34: - | G34: - | H34: - | I34: - | J34: - | K34: - | L34: - | M34: - | N34: -
B35: BIAfirme | C35: 273.32896 | D35: 245.00795 | E35: 244.16608 | F35: 0 | G35: 0 | H35: 0 | I35: - | J35: - | K35: - | L35: 0.52316263 | M35: 0.44387457 | N35: 0.44172885
B36: Intercam Banco | C36: 16842.357 | D36: 22289.924 | E36: 17071.35 | F36: 3.0065603 | G36: 3.7070251 | H36: 5.4001408 | I36: 107.49437 | J36: 92.253876 | K36: 84.497253 | L36: 3.2318832 | M36: 3.4198743 | N36: 4.5629706
B37: Bancrea | C37: 30144.916 | D37: 36379.643 | E37: 36516.345 | F37: 0.87687862 | G37: 1.1162774 | H37: 1.1203138 | I37: 117.52444 | J37: 145.15619 | K37: 142.8028 | L37: 1.0305467 | M37: 1.6203457 | N37: 1.5998394
B38: MUFG Bank | C38: 8272.5407 | D38: 7306.8789 | E38: 6866.0949 | F38: 0 | G38: 0 | H38: 0 | I38: - | J38: - | K38: - | L38: 0.51399902 | M38: 0.80921763 | N38: 0.77800167
B39: Consubanco | C39: 3477.0636 | D39: 7093.1819 | E39: 7043.5293 | F39: 0 | G39: 0 | H39: 0 | I39: - | J39: - | K39: - | L39: 1.1384982 | M39: 1.3486013 | N39: 1.5676168
B40: BNP Paribas México | C40: 0 | D40: 0 | E40: 0 | F40: - | G40: - | H40: - | I40: - | J40: - | K40: - | L40: - | M40: - | N40: -
B41: Autofin | C41: 2120.0042 | D41: 7169.7078 | E41: 7390.6898 | F41: 2.4326547 | G41: 4.2001956 | H41: 3.5535934 | I41: 219.85528 | J41: 111.68179 | K41: 126.70123 | L41: 5.3483198 | M41: 4.6908538 | N41: 4.5024467
B42: Bankaool | C42: 7165.7305 | D42: 11194.805 | E42: 12001.764 | F42: 1.4242153 | G42: 0.98137731 | H42: 0.91539267 | I42: 197.03182 | J42: 172.42837 | K42: 185.93478 | L42: 2.8061573 | M42: 1.6921729 | N42: 1.7020334
B43: Inmobiliario Mexicano | C43: 10819.181 | D43: 12251.1 | E43: 12233.377 | F43: 3.965371 | G43: 2.8691418 | H43: 2.8732986 | I43: 60.646053 | J43: 63.923473 | K43: 66.385032 | L43: 2.404841 | M43: 1.8340551 | N43: 1.9074402
B44: Mizuho Bank | C44: 738.03227 | D44: 1137.4933 | E44: 1416.4615 | F44: 0 | G44: 0 | H44: 0 | I44: - | J44: - | K44: - | L44: 0.36802455 | M44: 0.42059807 | N44: 0.56292149
B45: ICBC | C45: 2395.6666 | D45: 3279.8709 | E45: 3429.4465 | F45: 0 | G45: 0 | H45: 0 | I45: - | J45: - | K45: - | L45: 2.1439261 | M45: 1.7825791 | N45: 1.7337215
B46: Banco Covalto | C46: 4424.896 | D46: 6314.9972 | E46: 6339.671 | F46: 6.8761974 | G46: 5.5306369 | H46: 5.6531206 | I46: 62.371122 | J46: 67.11662 | K46: 68.7847 | L46: 4.2887615 | M46: 3.7119766 | N46: 3.8884821
B47: Bank of China | C47: 2586.5764 | D47: 2095.5806 | E47: 2097.0594 | F47: 4.6784012 | G47: 3.7305187 | H47: 3.1197058 | I47: 88.508997 | J47: 107.88292 | K47: 110.05393 | L47: 4.140806 | M47: 4.0245925 | N47: 3.4333587
B48: Volkswagen Bank | C48: 0 | D48: 0 | E48: 0 | F48: - | G48: - | H48: - | I48: - | J48: - | K48: - | L48: - | M48: - | N48: -
B49: Openbank | C49: 0 | D49: 0 | E49: 0 | F49: - | G49: - | H49: - | I49: - | J49: - | K49: - | L49: - | M49: - | N49: -
B50: Shinhan | C50: 3276.7847 | D50: 3931.2596 | E50: 4552.7844 | F50: 1.6993355 | G50: 1.4164307 | H50: 1.2230662 | I50: 58.945473 | J50: 66.062442 | K50: 82.618728 | L50: 1.0016814 | M50: 0.9357287 | N50: 1.0104817
B51: Banco Ualá | C51: 240.4358 | D51: 203.17237 | E51: 196.85592 | F51: 41.70553 | G51: 36.164263 | H51: 36.809819 | I51: 40.786116 | J51: 35.240716 | K51: 36.441596 | L51: 17.010066 | M51: 12.744545 | N51: 13.414086
B52: Banco S3 | C52: 0 | D52: 0 | E52: 0 | F52: - | G52: - | H52: - | I52: - | J52: - | K52: - | L52: - | M52: - | N52: -
B53: KEB Hana México | C53: 3279.6134 | D53: 3767.103 | E53: 3827.4127 | F53: 0 | G53: 0 | H53: 0 | I53: - | J53: - | K53: - | L53: 0.47172347 | M53: 0.49680134 | N53: 0.51955719
B54: Banco Bineo | C54: 0 | D54: 0 | E54: 0 | F54: - | G54: - | H54: - | I54: - | J54: - | K54: - | L54: - | M54: - | N54: -
B55: Dondé Banco | C55: 543.44889 | D55: 1005.3742 | E55: 1035.4823 | F55: 0.59705247 | G55: 0.32273306 | H55: 0.31334914 | I55: 146.06881 | J55: 207.88436 | K55: 213.79889 | L55: 0.87210741 | M55: 0.67091157 | N55: 0.66993696
B56: Credit Suisse | C56: 0 | D56: 0 | E56: 0 | F56: - | G56: - | H56: - | I56: - | J56: - | K56: - | L56: - | M56: - | N56: -
B57: Hey Banco | C57: 0 | D57: 0 | E57: 0 | F57: - | G57: - | H57: - | I57: - | J57: - | K57: - | L57: - | M57: - | N57: -
B58: Forjadores | C58: 0.137155 | D58: 0 | E58: 0 | F58: 0 | G58: - | H58: - | I58: - | J58: - | K58: - | L58: 10.717801 | M58: - | N58: -
B59: Pagatodo | C59: 0 | D59: 0 | E59: 0 | F59: - | G59: - | H59: - | I59: - | J59: - | K59: - | L59: - | M59: - | N59: -

Sheet CCEF
B2: Cartera de crédito a entidades financieras
B3: Millones de pesos y porcentajes
C5: Cartera total (MDP) 1/ | F5: IMOR (%) 5/ | I5: ICOR (%) 6/ | L5: Pérdida esperada (%) 7/
C6: 45474 | D6: 45809 | E6: 45839 | F6: =C6 -> 45474 | G6: =D6 -> 45809 | H6: =E6 -> 45839 | I6: =C6 -> 45474 | J6: =D6 -> 45809 | K6: =E6 -> 45839 | L6: =C6 -> 45474 | M6: =D6 -> 45809 | N6: =E6 -> 45839
B7: Sistema */ | C7: 244044.03 | D7: 298289.22 | E7: 293277.47 | F7: 1.2381053 | G7: 1.0269372 | H7: 1.038416 | I7: 155.73814 | J7: 171.62392 | K7: 174.3029 | L7: 1.9282021 | M7: 1.7624698 | N7: 1.8099893
B8: BBVA México | C8: 34798.211 | D8: 56173.712 | E8: 54562.6 | F8: 0.046705199 | G8: 0.038411855 | H8: 0.039576953 | I8: 1084.6117 | J8: 1830.8723 | K8: 1745.4577 | L8: 0.50657007 | M8: 0.70327201 | N8: 0.69079899
B9: Santander | C9: 9226.3624 | D9: 16387.6 | E9: 14410.398 | F9: 0 | G9: 0.060596657 | H9: 0.069556246 | I9: - | J9: 4677.3811 | K9: 3305.1547 | L9: 3.7287188 | M9: 2.8343366 | N9: 2.2989416
B10: Banorte | C10: 52922.949 | D10: 60148.7 | E10: 60102.622 | F10: 0.2450512 | G10: 0.38532829 | H10: 0.3856237 | I10: 116.07994 | J10: 89.94283 | K10: 87.970249 | L10: 0.28445528 | M10: 0.34657517 | N10: 0.33923413
B11: Banamex | C11: 45323.782 | D11: 2166.8079 | E11: 2433.1488 | F11: 4.9740242 | G11: 0 | H11: 0 | I11: 119.63275 | J11: - | K11: - | L11: 5.9505617 | M11: 1.5740576 | N11: 1.159257
B12: HSBC | C12: 9568.6861 | D12: 9540.0045 | E12: 8973.9394 | F12: 0.00030429465 | G12: 2.1771478e-05 | H12: 2.3144796e-05 | I12: 573800.66 | J12: 18207013 | K12: 21711718 | L12: 1.7460447 | M12: 3.9639359 | N12: 5.0251329
B13: Scotiabank | C13: 19576.889 | D13: 23445.462 | E13: 24925.328 | F13: 0.28792348 | G13: 0.40714306 | H13: 0.38297017 | I13: 333.31632 | J13: 214.69549 | K13: 204.50157 | L13: 0.95969597 | M13: 0.87411778 | N13: 0.78318001
B14: Inbursa | C14: 14860.87 | D14: 16371.781 | E14: 17041.669 | F14: 0 | G14: 0 | H14: 0 | I14: - | J14: - | K14: - | L14: 0.69206293 | M14: 0.83101467 | N14: 0.81219593
B15: Citi México | C15: 0 | D15: 31691.966 | E15: 24860.938 | F15: n.a. | G15: 7.1177315 | H15: 9.0738427 | I15: - | J15: 100.50884 | K15: 105.99102 | L15: - | M15: 7.1539492 | N15: 9.6174582
B16: Banco del Bajío | C16: 12534.715 | D16: 11930.668 | E16: 11742.266 | F16: 0.57967545 | G16: 1.0514658 | H16: 0.96219996 | I16: 126.91124 | J16: 206.23373 | K16: 222.1715 | L16: 0.73567333 | M16: 2.1684772 | N16: 2.1377341
B17: Banco Azteca | C17: 8674.8481 | D17: 13393.437 | E17: 13613.495 | F17: 0 | G17: 0 | H17: 0 | I17: - | J17: - | K17: - | L17: 0.89707725 | M17: 0.88831611 | N17: 0.95390729
B18: Afirme | C18: 45.845496 | D18: 108.46004 | E18: 110.98007 | F18: 0 | G18: 0 | H18: 0 | I18: - | J18: - | K18: - | L18: 0.53554879 | M18: 4.0284165 | N18: 3.9378728
B19: Monex | C19: 4968.2745 | D19: 8376.8598 | E19: 9032.9909 | F19: 0.88476771 | G19: 0.52801623 | H19: 0.42109034 | I19: 116.48592 | J19: 143.19754 | K19: 173.30627 | L19: 1.0306298 | M19: 0.75610624 | N19: 0.72977595
B20: Banregio | C20: 4534.8668 | D20: 5902.8327 | E20: 5858.8205 | F20: 0 | G20: 0 | H20: 0 | I20: - | J20: - | K20: - | L20: 2.9815902 | M20: 2.2632691 | N20: 2.2388704
B21: J.P. Morgan | C21: 11.504949 | D21: 852.86473 | E21: 1296.6367 | F21: 0 | G21: 0 | H21: 0 | I21: - | J21: - | K21: - | L21: 0.15718453 | M21: 0.87274063 | N21: 0.62797475
B22: Invex | C22: 1439.2667 | D22: 1775.8897 | E22: 1798.9664 | F22: 0 | G22: 0 | H22: 0 | I22: - | J22: - | K22: - | L22: 0.42039783 | M22: 1.1786222 | N22: 0.56445328
B23: Bank of America | C23: 4499.3922 | D23: 12889.761 | E23: 13450.343 | F23: 0 | G23: 0 | H23: 0 | I23: - | J23: - | K23: - | L23: 0.36790556 | M23: 0.73151655 | N23: 0.73679928
B24: BanCoppel | C24: 1604.8346 | D24: 1535.3471 | E24: 1504.7594 | F24: 2.3279535 | G24: 2.4333132 | H24: 2.4827758 | I24: 89.096983 | J24: 110.06684 | K24: 110.09841 | L24: 2.0741363 | M24: 2.6782709 | N24: 2.7334967
B25: Banca Mifel | C25: 2440.8352 | D25: 2337.2687 | E25: 2405.2553 | F25: 0 | G25: 0 | H25: 0 | I25: - | J25: - | K25: - | L25: 0.68719358 | M25: 0.60195981 | N25: 0.9646494
B26: Multiva | C26: 1058.0199 | D26: 4465.974 | E26: 6304.3348 | F26: 5.3691771 | G26: 1.7893863 | H26: 1.2675965 | I26: 52.649596 | J26: 91.278543 | K26: 129.10088 | L26: 2.82685 | M26: 1.6333258 | N26: 1.6364783
B27: Banco Base | C27: 394.43072 | D27: 307.54984 | E27: 296.63581 | F27: 0 | G27: 0 | H27: 0 | I27: - | J27: - | K27: - | L27: 0.55897065 | M27: 0.59777303 | N27: 0.61810946
B28: Barclays | C28: 0 | D28: 0 | E28: 0 | F28: n.a. | G28: n.a. | H28: n.a. | I28: - | J28: - | K28: - | L28: - | M28: - | N28: -
B29: Sabadell | C29: 1196.0533 | D29: 1782.8308 | E29: 2091.7696 | F29: 7.9869385 | G29: 0 | H29: 0 | I29: 83.909367 | J29: - | K29: - | L29: 6.7017896 | M29: 0.37245543 | N29: 0.43583333
B30: Ve por Más | C30: 3358.3562 | D30: 3228.7167 | E30: 3098.6526 | F30: 1.1556653 | G30: 0.98090979 | H30: 1.0220829 | I30: 113.62997 | J30: 72.709118 | K30: 65.590005 | L30: 1.3131821 | M30: 0.71321086 | N30: 0.67038422
B31: CIBanco | C31: 288.08172 | D31: 1013.0738 | E31: 492.1 | F31: 26.957161 | G31: 0 | H31: 0 | I31: 88.511402 | J31: - | K31: - | L31: 23.860161 | M31: 0.89030806 | N31: 1.4994597
B32: Bansí | C32: 760.39683 | D32: 819.27553 | E32: 823.32027 | F32: 0.93644288 | G32: 0.86914375 | H32: 0.86487389 | I32: 461.84948 | J32: 328.92327 | K32: 321.5449 | L32: 4.3249566 | M32: 2.858816 | N32: 2.7809579
B33: Actinver | C33: 1432.4859 | D33: 1975.1403 | E33: 2412.1418 | F33: 0 | G33: 0 | H33: 0 | I33: - | J33: - | K33: - | L33: 0.85677701 | M33: 1.0818981 | N33: 1.1394403
B34: Compartamos | C34: 0 | D34: 0 | E34: 0 | F34: n.a. | G34: n.a. | H34: n.a. | I34: - | J34: - | K34: - | L34: - | M34: - | N34: -
B35: BIAfirme | C35: 0 | D35: 0 | E35: 0 | F35: n.a. | G35: n.a. | H35: n.a. | I35: - | J35: - | K35: - | L35: - | M35: - | N35: -
B36: Intercam Banco | C36: 1110.2677 | D36: 780.75469 | E36: 567.4266 | F36: 0 | G36: 0 | H36: 0 | I36: - | J36: - | K36: - | L36: 0.57645955 | M36: 1.2392921 | N36: 1.595421
B37: Bancrea | C37: 1938.8279 | D37: 1926.4718 | E37: 2054.5098 | F37: 0 | G37: 0 | H37: 0 | I37: - | J37: - | K37: - | L37: 0.23337747 | M37: 0.80672801 | N37: 0.75526158
B38: MUFG Bank | C38: 0 | D38: 0 | E38: 0 | F38: n.a. | G38: n.a. | H38: n.a. | I38: - | J38: - | K38: - | L38: - | M38: - | N38: -
B39: Consubanco | C39: 2437.7121 | D39: 2072.4968 | E39: 2086.2108 | F39: 0 | G39: 0 | H39: 0 | I39: - | J39: - | K39: - | L39: 2.0283714 | M39: 1.6985834 | N39: 1.6850506
B40: BNP Paribas México | C40: 0 | D40: 0 | E40: 0 | F40: n.a. | G40: n.a. | H40: n.a. | I40: - | J40: - | K40: - | L40: - | M40: - | N40: -
B41: Autofin | C41: 722.40104 | D41: 1414.753 | E41: 1436.5551 | F41: 3.6346002 | G41: 0 | H41: 0 | I41: 99.970909 | J41: - | K41: - | L41: 3.6335429 | M41: 1.2935829 | N41: 1.5681268
B42: Bankaool | C42: 38.828687 | D42: 555.73381 | E42: 558.4779 | F42: 0 | G42: 0 | H42: 0 | I42: - | J42: - | K42: - | L42: 2.1737897 | M42: 7.8305835 | N42: 3.9345073
B43: Inmobiliario Mexicano | C43: 30.698253 | D43: 27.586688 | E43: 22.964855 | F43: 0 | G43: 0 | H43: 0 | I43: - | J43: - | K43: - | L43: 0.47517733 | M43: 0.36729959 | N43: 0.3672996
B44: Mizuho Bank | C44: 1845.2055 | D44: 1090.6252 | E44: 1083.8879 | F44: 0 | G44: 0 | H44: 0 | I44: - | J44: - | K44: - | L44: 0.25227376 | M44: 0.17669103 | N44: 0.18807348
B45: ICBC | C45: 0 | D45: 0 | E45: 0 | F45: n.a. | G45: n.a. | H45: n.a. | I45: - | J45: - | K45: - | L45: - | M45: - | N45: -
B46: Banco Covalto | C46: 90.266024 | D46: 595.28397 | E46: 655.98836 | F46: 0 | G46: 0 | H46: 0 | I46: - | J46: - | K46: - | L46: 1.0579661 | M46: 0.48327463 | N46: 0.26881653
B47: Bank of China | C47: 53.063241 | D47: 303.97881 | E47: 305.38733 | F47: 100 | G47: 17.581212 | H47: 17.595805 | I47: 81 | J47: 97.179116 | K47: 97.177929 | L47: 81 | M47: 17.085266 | N47: 17.099239
B48: Volkswagen Bank | C48: 0 | D48: 0 | E48: 0 | F48: n.a. | G48: n.a. | H48: n.a. | I48: - | J48: - | K48: - | L48: - | M48: - | N48: -
B49: Openbank | C49: 0 | D49: 0 | E49: 0 | F49: n.a. | G49: n.a. | H49: n.a. | I49: - | J49: - | K49: - | L49: - | M49: - | N49: -
B50: Shinhan | C50: 0 | D50: 0 | E50: 0 | F50: n.a. | G50: n.a. | H50: n.a. | I50: - | J50: - | K50: - | L50: - | M50: - | N50: -
B51: Banco Ualá | C51: 0 | D51: 41.081263 | E51: 39.889862 | F51: n.a. | G51: 0 | H51: 0 | I51: - | J51: - | K51: - | L51: - | M51: 0.30115676 | N51: 0.29991079
B52: Banco S3 | C52: 8.56684 | D52: 187.93514 | E52: 159.36079 | F52: 0 | G52: 0 | H52: 0 | I52: - | J52: - | K52: - | L52: 0.31325436 | M52: 0.85881489 | N52: 1.0595655
B53: KEB Hana México | C53: 55.546168 | D53: 57.551012 | E53: 57.716784 | F53: 100 | G53: 100 | H53: 100 | I53: 78 | J53: 94 | K53: 93.999998 | L53: 78 | M53: 94 | N53: 93.999998
B54: Banco Bineo | C54: 0 | D54: 0 | E54: 0 | F54: n.a. | G54: n.a. | H54: n.a. | I54: - | J54: - | K54: - | L54: - | M54: - | N54: -
B55: Dondé Banco | C55: 192.68814 | D55: 612.98698 | E55: 604.98574 | F55: 0 | G55: 0 | H55: 0 | I55: - | J55: - | K55: - | L55: 0.41484806 | M55: 0.95800485 | N55: 0.92956885
B56: Credit Suisse | C56: 0 | D56: 0 | E56: 0 | F56: n.a. | G56: n.a. | H56: n.a. | I56: - | J56: - | K56: - | L56: - | M56: - | N56: -
B57: Hey Banco | C57: 0 | D57: 0 | E57: 0 | F57: n.a. | G57: n.a. | H57: n.a. | I57: - | J57: - | K57: - | L57: - | M57: - | N57: -
B58: Forjadores | C58: 0 | D58: 0 | E58: 0 | F58: n.a. | G58: n.a. | H58: n.a. | I58: - | J58: - | K58: - | L58: - | M58: - | N58: -
B59: Pagatodo | C59: 0 | D59: 0 | E59: 0 | F59: n.a. | G59: n.a. | H59: n.a. | I59: - | J59: - | K59: - | L59: - | M59: - | N59: -

Sheet CCGT
B2: Cartera de crédito a entidades gubernamentales
B3: Millones de pesos y porcentajes
C5: Cartera total (MDP) 1/ | F5: IMOR (%) 5/ | I5: ICOR (%) 6/ | L5: Pérdida esperada (%) 7/
C6: 45474 | D6: 45809 | E6: 45839 | F6: =C6 -> 45474 | G6: =D6 -> 45809 | H6: =E6 -> 45839 | I6: =C6 -> 45474 | J6: =D6 -> 45809 | K6: =E6 -> 45839 | L6: =C6 -> 45474 | M6: =D6 -> 45809 | N6: =E6 -> 45839
B7: Sistema */ | C7: 605448.19 | D7: 549163.31 | E7: 542948.96 | F7: 0.0079027393 | G7: 0.0045918712 | H7: 0.0045685877 | I7: 6033.0186 | J7: 11187.503 | K7: 11378.872 | L7: 0.47677373 | M7: 0.51371572 | N7: 0.51985374
B8: BBVA México | C8: 192050.99 | D8: 195598.06 | E8: 196749.62 | F8: 4.5027427e-05 | G8: 0 | H8: 0 | I8: 780283.11 | J8: - | K8: - | L8: 0.35134141 | M8: 0.47753214 | N8: 0.48551861
B9: Santander | C9: 84215.017 | D9: 70932.22 | E9: 71061.77 | F9: 0 | G9: 0 | H9: 0 | I9: - | J9: - | K9: - | L9: 0.31913857 | M9: 0.37313038 | N9: 0.38905853
B10: Banorte | C10: 137353.92 | D10: 124321.61 | E10: 124724.95 | F10: 0.0022826428 | G10: 0 | H10: 0 | I10: 23773.386 | J10: - | K10: - | L10: 0.5426615 | M10: 0.50427545 | N10: 0.50527903
B11: Banamex | C11: 41411.496 | D11: 30237.031 | E11: 30030.26 | F11: 0 | G11: 0 | H11: 0 | I11: - | J11: - | K11: - | L11: 0.50177915 | M11: 0.51683831 | N11: 0.52146905
B12: HSBC | C12: 17567.351 | D12: 11923.666 | E12: 11140.016 | F12: 5.783456e-06 | G12: 8.5208692e-06 | H12: 9.120274e-06 | I12: 11298363 | J12: 7359322.4 | K12: 6571802.7 | L12: 0.65343588 | M12: 0.62707824 | N12: 0.59936641
B13: Scotiabank | C13: 23404.28 | D13: 8267.0377 | E13: 7225.8747 | F13: 0 | G13: 0 | H13: 0 | I13: - | J13: - | K13: - | L13: 0.58107264 | M13: 0.57865755 | N13: 0.59551915
B14: Inbursa | C14: 30355.233 | D14: 28379.338 | E14: 24548.263 | F14: 0 | G14: 0 | H14: 0 | I14: - | J14: - | K14: - | L14: 0.5 | M14: 0.5 | N14: 0.5
B15: Citi México | C15: 0 | D15: 8317.1868 | E15: 4964.2834 | F15: n.a. | G15: 0 | H15: 0 | I15: - | J15: - | K15: - | L15: - | M15: 0.52711575 | N15: 0.54644286
B16: Banco del Bajío | C16: 16273.252 | D16: 13181.44 | E16: 13008.697 | F16: 0 | G16: 0 | H16: 0 | I16: - | J16: - | K16: - | L16: 0.51399029 | M16: 0.46723951 | N16: 0.46929883
B17: Banco Azteca | C17: 4969.7749 | D17: 4855.4893 | E17: 4320.6831 | F17: 0 | G17: 0 | H17: 0 | I17: - | J17: - | K17: - | L17: 0.99061813 | M17: 0.51372733 | N17: 0.52253581
B18: Afirme | C18: 2061.5103 | D18: 1414.1201 | E18: 1274.0176 | F18: 0 | G18: 0 | H18: 0 | I18: - | J18: - | K18: - | L18: 0.29092626 | M18: 0.58902474 | N18: 0.56171397
B19: Monex | C19: 4767.344 | D19: 5129.8077 | E19: 5032.4839 | F19: 0 | G19: 0 | H19: 0 | I19: - | J19: - | K19: - | L19: 0.50020285 | M19: 0.50144341 | N19: 0.50139744
B20: Banregio | C20: 220.1172 | D20: 153.01766 | E20: 147.68195 | F20: 0 | G20: 0 | H20: 0 | I20: - | J20: - | K20: - | L20: 7.7049093 | M20: 4.2119442 | N20: 4.2475147
B21: J.P. Morgan | C21: 0 | D21: 0 | E21: 0 | F21: n.a. | G21: n.a. | H21: n.a. | I21: - | J21: - | K21: - | L21: - | M21: - | N21: -
B22: Invex | C22: 0 | D22: 0 | E22: 0 | F22: n.a. | G22: n.a. | H22: n.a. | I22: - | J22: - | K22: - | L22: - | M22: - | N22: -
B23: Bank of America | C23: 0 | D23: 0 | E23: 0 | F23: n.a. | G23: n.a. | H23: n.a. | I23: - | J23: - | K23: - | L23: - | M23: - | N23: -
B24: BanCoppel | C24: 0 | D24: 0 | E24: 0 | F24: n.a. | G24: n.a. | H24: n.a. | I24: - | J24: - | K24: - | L24: - | M24: - | N24: -
B25: Banca Mifel | C25: 3440.3894 | D25: 3325.6479 | E25: 3314.6056 | F25: 0 | G25: 0 | H25: 0 | I25: - | J25: - | K25: - | L25: 0.61113108 | M25: 0.61111106 | N25: 0.61111105
B26: Multiva | C26: 27619.428 | D26: 24747.344 | E26: 24486.46 | F26: 0 | G26: 0 | H26: 0 | I26: - | J26: - | K26: - | L26: 0.5236781 | M26: 0.61135886 | N26: 0.58349758
B27: Banco Base | C27: 0 | D27: 0 | E27: 0 | F27: n.a. | G27: n.a. | H27: n.a. | I27: - | J27: - | K27: - | L27: - | M27: - | N27: -
B28: Barclays | C28: 0 | D28: 0 | E28: 0 | F28: n.a. | G28: n.a. | H28: n.a. | I28: - | J28: - | K28: - | L28: - | M28: - | N28: -
B29: Sabadell | C29: 1423.5008 | D29: 542.3555 | E29: 544.19448 | F29: 0 | G29: 0 | H29: 0 | I29: - | J29: - | K29: - | L29: 0.5 | M29: 0.5000001 | N29: 0.50000011
B30: Ve por Más | C30: 2418.871 | D30: 1454.1957 | E30: 2130.3047 | F30: 0 | G30: 0 | H30: 0 | I30: - | J30: - | K30: - | L30: 0.50000001 | M30: 0.49142201 | N30: 0.49260887
B31: CIBanco | C31: 0 | D31: 182.0985 | E31: 0 | F31: n.a. | G31: 0 | H31: n.a. | I31: - | J31: - | K31: - | L31: - | M31: 0.50000027 | N31: -
B32: Bansí | C32: 3465.9981 | D32: 6573.4354 | E32: 8934.1054 | F32: 1.2874849 | G32: 0.3836024 | H32: 0.27763365 | I32: 354.37552 | J32: 685.37555 | K32: 803.55321 | L32: 4.5625312 | M32: 2.6291171 | N32: 2.2309341
B33: Actinver | C33: 0 | D33: 0 | E33: 0 | F33: n.a. | G33: n.a. | H33: n.a. | I33: - | J33: - | K33: - | L33: - | M33: - | N33: -
B34: Compartamos | C34: 0 | D34: 0 | E34: 0 | F34: n.a. | G34: n.a. | H34: n.a. | I34: - | J34: - | K34: - | L34: - | M34: - | N34: -
B35: BIAfirme | C35: 0 | D35: 0 | E35: 0 | F35: n.a. | G35: n.a. | H35: n.a. | I35: - | J35: - | K35: - | L35: - | M35: - | N35: -
B36: Intercam Banco | C36: 1843.3415 | D36: 1797.9522 | E36: 883.45699 | F36: 0 | G36: 0 | H36: 0 | I36: - | J36: - | K36: - | L36: 0.499995 | M36: 0.49999498 | N36: 0.49999503
B37: Bancrea | C37: 1349.8704 | D37: 2092.3518 | E37: 2310.7763 | F37: 0 | G37: 0 | H37: 0 | I37: - | J37: - | K37: - | L37: 0.43716359 | M37: 0.4757599 | N37: 0.49267855
B38: MUFG Bank | C38: 3375.3433 | D38: 0 | E38: 0 | F38: 0 | G38: n.a. | H38: n.a. | I38: - | J38: - | K38: - | L38: 0.58577283 | M38: - | N38: -
B39: Consubanco | C39: 0 | D39: 0 | E39: 0 | F39: n.a. | G39: n.a. | H39: n.a. | I39: - | J39: - | K39: - | L39: - | M39: - | N39: -
B40: BNP Paribas México | C40: 0 | D40: 0 | E40: 0 | F40: n.a. | G40: n.a. | H40: n.a. | I40: - | J40: - | K40: - | L40: - | M40: - | N40: -
B41: Autofin | C41: 0 | D41: 0 | E41: 0 | F41: n.a. | G41: n.a. | H41: n.a. | I41: - | J41: - | K41: - | L41: - | M41: - | N41: -
B42: Bankaool | C42: 0 | D42: 0 | E42: 0 | F42: n.a. | G42: n.a. | H42: n.a. | I42: - | J42: - | K42: - | L42: - | M42: - | N42: -
B43: Inmobiliario Mexicano | C43: 0 | D43: 0 | E43: 0 | F43: n.a. | G43: n.a. | H43: n.a. | I43: - | J43: - | K43: - | L43: - | M43: - | N43: -
B44: Mizuho Bank | C44: 3158.8366 | D44: 3577.9027 | E44: 3563.4308 | F44: 0 | G44: 0 | H44: 0 | I44: - | J44: - | K44: - | L44: 0.5 | M44: 0.5 | N44: 0.5
B45: ICBC | C45: 937.39412 | D45: 970.71421 | E45: 1418.34 | F45: 0 | G45: 0 | H45: 0 | I45: - | J45: - | K45: - | L45: 0.50000004 | M45: 0.53447945 | N45: 0.5
B46: Banco Covalto | C46: 0 | D46: 0 | E46: 0 | F46: n.a. | G46: n.a. | H46: n.a. | I46: - | J46: - | K46: - | L46: - | M46: - | N46: -
B47: Bank of China | C47: 1764.9334 | D47: 1189.2866 | E47: 1134.6835 | F47: 0 | G47: 0 | H47: 0 | I47: - | J47: - | K47: - | L47: 0.52783893 | M47: 0.55628525 | N47: 0.5
B48: Volkswagen Bank | C48: 0 | D48: 0 | E48: 0 | F48: n.a. | G48: n.a. | H48: n.a. | I48: - | J48: - | K48: - | L48: - | M48: - | N48: -
B49: Openbank | C49: 0 | D49: 0 | E49: 0 | F49: n.a. | G49: n.a. | H49: n.a. | I49: - | J49: - | K49: - | L49: - | M49: - | N49: -
B50: Shinhan | C50: 0 | D50: 0 | E50: 0 | F50: n.a. | G50: n.a. | H50: n.a. | I50: - | J50: - | K50: - | L50: - | M50: - | N50: -
B51: Banco Ualá | C51: 0 | D51: 0 | E51: 0 | F51: n.a. | G51: n.a. | H51: n.a. | I51: - | J51: - | K51: - | L51: - | M51: - | N51: -
B52: Banco S3 | C52: 0 | D52: 0 | E52: 0 | F52: n.a. | G52: n.a. | H52: n.a. | I52: - | J52: - | K52: - | L52: - | M52: - | N52: -
B53: KEB Hana México | C53: 0 | D53: 0 | E53: 0 | F53: n.a. | G53: n.a. | H53: n.a. | I53: - | J53: - | K53: - | L53: - | M53: - | N53: -
B54: Banco Bineo | C54: 0 | D54: 0 | E54: 0 | F54: n.a. | G54: n.a. | H54: n.a. | I54: - | J54: - | K54: - | L54: - | M54: - | N54: -
B55: Dondé Banco | C55: 0 | D55: 0 | E55: 0 | F55: n.a. | G55: n.a. | H55: n.a. | I55: - | J55: - | K55: - | L55: - | M55: - | N55: -
B56: Credit Suisse | C56: 0 | D56: 0 | E56: 0 | F56: n.a. | G56: n.a. | H56: n.a. | I56: - | J56: - | K56: - | L56: - | M56: - | N56: -
B57: Hey Banco | C57: 0 | D57: 0 | E57: 0 | F57: n.a. | G57: n.a. | H57: n.a. | I57: - | J57: - | K57: - | L57: - | M57: - | N57: -
B58: Forjadores | C58: 0 | D58: 0 | E58: 0 | F58: n.a. | G58: n.a. | H58: n.a. | I58: - | J58: - | K58: - | L58: - | M58: - | N58: -
B59: Pagatodo | C59: 0 | D59: 0 | E59: 0 | F59: n.a. | G59: n.a. | H59: n.a. | I59: - | J59: - | K59: - | L59: - | M59: - | N59: -

Sheet CCG EyM
B2: Cartera de crédito a estados y municipios
B3: Millones de pesos y porcentajes
C5: Cartera total (MDP) 1/ | G5: IMOR (%) 5/
C6: 45474 | D6: 45809 | E6: 45839 | F6: =C6 -> 45474 | G6: =D6 -> 45809 | H6: =E6 -> 45839
B7: Sistema */ | C7: 276841.42 | D7: 280777.82 | E7: 279285.02 | F7: 0.017251574 | G7: 0.008980715 | H7: 0.0088812796
B8: BBVA México | C8: 87800.852 | D8: 95682.9 | E8: 96306.544 | F8: 0 | G8: 0 | H8: 0
B9: Santander | C9: 48597.835 | D9: 47755.107 | E9: 47964.883 | F9: 0 | G9: 0 | H9: 0
B10: Banorte | C10: 81122.265 | D10: 77003.008 | E10: 75962.761 | F10: 0.0038649061 | G10: 0 | H10: 0
B11: Banamex | C11: 27458.664 | D11: 26381.794 | E11: 26189.195 | F11: 0 | G11: 0 | H11: 0
B12: HSBC | C12: 5793.9415 | D12: 5518.3308 | E12: 4769.719 | F12: 0 | G12: 0 | H12: 0
B13: Scotiabank | C13: 2099.3461 | D13: 404.65389 | E13: 451.8688 | F13: 0 | G13: 0 | H13: 0
B14: Inbursa | C14: 0 | D14: 0 | E14: 0 | F14: n.a. | G14: n.a. | H14: n.a.
B15: Citi México | C15: 0 | D15: 0 | E15: 0 | F15: n.a. | G15: n.a. | H15: n.a.
B16: Banco del Bajío | C16: 7696.4412 | D16: 6582.9826 | E16: 6543.1968 | F16: 0 | G16: 0 | H16: 0
B17: Banco Azteca | C17: 3597.4189 | D17: 3527.5505 | E17: 2997.1543 | F17: 0 | G17: 0 | H17: 0
B18: Afirme | C18: 702.1181 | D18: 1056.3066 | E18: 898.93462 | F18: 0 | G18: 0 | H18: 0
B19: Monex | C19: 0 | D19: 0 | E19: 0 | F19: n.a. | G19: n.a. | H19: n.a.
B20: Banregio | C20: 220.1172 | D20: 153.01766 | E20: 147.68195 | F20: 0 | G20: 0 | H20: 0
B21: J.P. Morgan | C21: 0 | D21: 0 | E21: 0 | F21: n.a. | G21: n.a. | H21: n.a.
B22: Invex | C22: 0 | D22: 0 | E22: 0 | F22: n.a. | G22: n.a. | H22: n.a.
B23: Bank of America | C23: 0 | D23: 0 | E23: 0 | F23: n.a. | G23: n.a. | H23: n.a.
B24: BanCoppel | C24: 0 | D24: 0 | E24: 0 | F24: n.a. | G24: n.a. | H24: n.a.
B25: Banca Mifel | C25: 2.384955 | D25: 0 | E25: 0 | F25: 0 | G25: n.a. | H25: n.a.
B26: Multiva | C26: 7751.4082 | D26: 10942.12 | E26: 10210.792 | F26: 0 | G26: 0 | H26: 0
B27: Banco Base | C27: 0 | D27: 0 | E27: 0 | F27: n.a. | G27: n.a. | H27: n.a.
B28: Barclays | C28: 0 | D28: 0 | E28: 0 | F28: n.a. | G28: n.a. | H28: n.a.
B29: Sabadell | C29: 0 | D29: 0 | E29: 0 | F29: n.a. | G29: n.a. | H29: n.a.
B30: Ve por Más | C30: 0 | D30: 0 | E30: 0 | F30: n.a. | G30: n.a. | H30: n.a.
B31: CIBanco | C31: 0 | D31: 0 | E31: 0 | F31: n.a. | G31: n.a. | H31: n.a.
B32: Bansí | C32: 3241.7009 | D32: 4642.7155 | E32: 5430.5719 | F32: 1.3765675 | G32: 0.54312732 | H32: 0.456749
B33: Actinver | C33: 0 | D33: 0 | E33: 0 | F33: n.a. | G33: n.a. | H33: n.a.
B34: Compartamos | C34: 0 | D34: 0 | E34: 0 | F34: n.a. | G34: n.a. | H34: n.a.
B35: BIAfirme | C35: 0 | D35: 0 | E35: 0 | F35: n.a. | G35: n.a. | H35: n.a.
B36: Intercam Banco | C36: 0 | D36: 0 | E36: 0 | F36: n.a. | G36: n.a. | H36: n.a.
B37: Bancrea | C37: 756.9232 | D37: 1127.3353 | E37: 1411.7116 | F37: 0 | G37: 0 | H37: 0
B38: MUFG Bank | C38: 0 | D38: 0 | E38: 0 | F38: n.a. | G38: n.a. | H38: n.a.
B39: Consubanco | C39: 0 | D39: 0 | E39: 0 | F39: n.a. | G39: n.a. | H39: n.a.
B40: BNP Paribas México | C40: 0 | D40: 0 | E40: 0 | F40: n.a. | G40: n.a. | H40: n.a.
B41: Autofin | C41: 0 | D41: 0 | E41: 0 | F41: n.a. | G41: n.a. | H41: n.a.
B42: Bankaool | C42: 0 | D42: 0 | E42: 0 | F42: n.a. | G42: n.a. | H42: n.a.
B43: Inmobiliario Mexicano | C43: 0 | D43: 0 | E43: 0 | F43: n.a. | G43: n.a. | H43: n.a.
B44: Mizuho Bank | C44: 0 | D44: 0 | E44: 0 | F44: n.a. | G44: n.a. | H44: n.a.
B45: ICBC | C45: 0 | D45: 0 | E45: 0 | F45: n.a. | G45: n.a. | H45: n.a.
B46: Banco Covalto | C46: 0 | D46: 0 | E46: 0 | F46: n.a. | G46: n.a. | H46: n.a.
B47: Bank of China | C47: 0 | D47: 0 | E47: 0 | F47: n.a. | G47: n.a. | H47: n.a.
B48: Volkswagen Bank | C48: 0 | D48: 0 | E48: 0 | F48: n.a. | G48: n.a. | H48: n.a.
B49: Openbank | C49: 0 | D49: 0 | E49: 0 | F49: n.a. | G49: n.a. | H49: n.a.
... B59: Pagatodo | C59: 0 | D59: 0 | E59: 0 | F59: n.a. | G59: n.a. | H59: n.a.

Sheet CCG OG
B2: Cartera de crédito a otras entidades gubernamentales
B3: Millones de pesos y porcentajes
C5: Cartera total (MDP) 1/ | G5: IMOR (%) 5/
C6: 45474 | D6: 45809 | E6: 45839 | F6: =C6 -> 45474 | G6: =D6 -> 45809 | H6: =E6 -> 45839
B7: Sistema */ | C7: 328606.78 | D7: 268385.49 | E7: 263663.94 | F7: 2.662502e-07 | G7: 3.7855996e-09 | H7: 3.85339e-09
B8: BBVA México | C8: 104250.14 | D8: 99915.161 | E8: 100443.07 | F8: 8.2950125e-07 | G8: 0 | H8: 0
B9: Santander | C9: 35617.182 | D9: 23177.113 | E9: 23096.887 | F9: 0 | G9: 0 | H9: 0
B10: Banorte | C10: 56231.654 | D10: 47318.601 | E10: 48762.189 | F10: 0 | G10: 0 | H10: 0
B11: Banamex | C11: 13952.833 | D11: 3855.2373 | E11: 3841.065 | F11: 0 | G11: 0 | H11: 0
B12: HSBC | C12: 11773.409 | D12: 6405.3354 | E12: 6370.2972 | F12: 8.629616e-08 | G12: 1.5861777e-07 | H12: 1.594902e-07
B13: Scotiabank | C13: 21304.934 | D13: 7862.3838 | E13: 6774.0059 | F13: 0 | G13: 0 | H13: 0
B14: Inbursa | C14: 30355.233 | D14: 28379.338 | E14: 24548.263 | F14: 0 | G14: 0 | H14: 0
B15: Citi México | C15: 0 | D15: 8317.1868 | E15: 4964.2834 | F15: n. a. | G15: 0 | H15: 0
B16: Banco del Bajío | C16: 8576.8111 | D16: 6598.4577 | E16: 6465.5004 | F16: 0 | G16: 0 | H16: 0
B17: Banco Azteca | C17: 1372.356 | D17: 1327.9388 | E17: 1323.5288 | F17: 0 | G17: 0 | H17: 0
B18: Afirme | C18: 1359.3922 | D18: 357.81345 | E18: 375.083 | F18: 0 | G18: 0 | H18: 0
B19: Monex | C19: 4767.344 | D19: 5129.8077 | E19: 5032.4839 | F19: 0 | G19: 0 | H19: 0
B20: Banregio | C20: 0 | D20: 0 | E20: 0 | F20: n. a. | G20: n. a. | H20: n. a.
B21: J.P. Morgan | C21: 0 | D21: 0 | E21: 0 | F21: n. a. | G21: n. a. | H21: n. a.
B22: Invex | C22: 0 | D22: 0 | E22: 0 | F22: n. a. | G22: n. a. | H22: n. a.
B23: Bank of America | C23: 0 | D23: 0 | E23: 0 | F23: n. a. | G23: n. a. | H23: n. a.
B24: BanCoppel | C24: 0 | D24: 0 | E24: 0 | F24: n. a. | G24: n. a. | H24: n. a.
B25: Banca Mifel | C25: 3438.0045 | D25: 3325.6479 | E25: 3314.6056 | F25: 0 | G25: 0 | H25: 0
B26: Multiva | C26: 19868.019 | D26: 13805.224 | E26: 14275.668 | F26: 0 | G26: 0 | H26: 0
B27: Banco Base | C27: 0 | D27: 0 | E27: 0 | F27: n. a. | G27: n. a. | H27: n. a.
B28: Barclays | C28: 0 | D28: 0 | E28: 0 | F28: n. a. | G28: n. a. | H28: n. a.
B29: Sabadell | C29: 1423.5008 | D29: 542.3555 | E29: 544.19448 | F29: 0 | G29: 0 | H29: 0
B30: Ve por Más | C30: 2418.871 | D30: 1454.1957 | E30: 2130.3047 | F30: 0 | G30: 0 | H30: 0
B31: CIBanco | C31: 0 | D31: 182.0985 | E31: 0 | F31: n. a. | G31: 0 | H31: n. a.
B32: Bansí | C32: 224.29715 | D32: 1930.7199 | E32: 3503.5335 | F32: 0 | G32: 0 | H32: 0
B33: Actinver | C33: 0 | D33: 0 | E33: 0 | F33: n. a. | G33: n. a. | H33: n. a.
B34: Compartamos | C34: 0 | D34: 0 | E34: 0 | F34: n. a. | G34: n. a. | H34: n. a.
B35: BIAfirme | C35: 0 | D35: 0 | E35: 0 | F35: n. a. | G35: n. a. | H35: n. a.
B36: Intercam Banco | C36: 1843.3415 | D36: 1797.9522 | E36: 883.45699 | F36: 0 | G36: 0 | H36: 0
B37: Bancrea | C37: 592.94717 | D37: 965.01648 | E37: 899.06466 | F37: 0 | G37: 0 | H37: 0
B38: MUFG Bank | C38: 3375.3433 | D38: 0 | E38: 0 | F38: 0 | G38: n. a. | H38: n. a.
B39: Consubanco | C39: 0 | D39: 0 | E39: 0 | F39: n. a. | G39: n. a. | H39: n. a.
B40: BNP Paribas México | C40: 0 | D40: 0 | E40: 0 | F40: n. a. | G40: n. a. | H40: n. a.
B41: Autofin | C41: 0 | D41: 0 | E41: 0 | F41: n. a. | G41: n. a. | H41: n. a.
B42: Bankaool | C42: 0 | D42: 0 | E42: 0 | F42: n. a. | G42: n. a. | H42: n. a.
B43: Inmobiliario Mexicano | C43: 0 | D43: 0 | E43: 0 | F43: n. a. | G43: n. a. | H43: n. a.
B44: Mizuho Bank | C44: 3158.8366 | D44: 3577.9027 | E44: 3563.4308 | F44: 0 | G44: 0 | H44: 0
B45: ICBC | C45: 937.39412 | D45: 970.71421 | E45: 1418.34 | F45: 0 | G45: 0 | H45: 0
B46: Banco Covalto | C46: 0 | D46: 0 | E46: 0 | F46: n. a. | G46: n. a. | H46: n. a.
B47: Bank of China | C47: 1764.9334 | D47: 1189.2866 | E47: 1134.6835 | F47: 0 | G47: 0 | H47: 0
B48: Volkswagen Bank | C48: 0 | D48: 0 | E48: 0 | F48: n. a. | G48: n. a. | H48: n. a.
B49: Openbank | C49: 0 | D49: 0 | E49: 0 | F49: n. a. | G49: n. a. | H49: n. a.
B50: Shinhan | C50: 0 | D50: 0 | E50: 0 | F50: n. a. | G50: n. a. | H50: n. a.
B51: Banco Ualá | C51: 0 | D51: 0 | E51: 0 | F51: n. a. | G51: n. a. | H51: n. a.
B52: Banco S3 | C52: 0 | D52: 0 | E52: 0 | F52: n. a. | G52: n. a. | H52: n. a.
B53: KEB Hana México | C53: 0 | D53: 0 | E53: 0 | F53: n. a. | G53: n. a. | H53: n. a.
B54: Banco Bineo | C54: 0 | D54: 0 | E54: 0 | F54: n. a. | G54: n. a. | H54: n. a.
B55: Dondé Banco | C55: 0 | D55: 0 | E55: 0 | F55: n. a. | G55: n. a. | H55: n. a.
B56: Credit Suisse | C56: 0 | D56: 0 | E56: 0 | F56: n. a. | G56: n. a. | H56: n. a.
B57: Hey Banco | C57: 0 | D57: 0 | E57: 0 | F57: n. a. | G57: n. a. | H57: n. a.
B58: Forjadores | C58: 0 | D58: 0 | E58: 0 | F58: n. a. | G58: n. a. | H58: n. a.
B59: Pagatodo | C59: 0 | D59: 0 | E59: 0 | F59: n. a. | G59: n. a. | H59: n. a.

Sheet CCCT
B2: Cartera de crédito al consumo
B3: Millones de pesos y porcentajes
C5: Cartera total (MDP) 1/ | F5: IMOR (%) 5/ | I5: ICOR (%) 6/ | L5: Pérdida esperada (%) 7/
C6: 45474 | D6: 45809 | E6: 45839 | F6: =C6 -> 45474 | G6: =D6 -> 45809 | H6: =E6 -> 45839 | I6: =C6 -> 45474 | J6: =D6 -> 45809 | K6: =E6 -> 45839 | L6: =C6 -> 45474 | M6: =D6 -> 45809 | N6: =E6 -> 45839
B7: Sistema */ | C7: 1576509.1 | D7: 1779501.8 | E7: 1800615.7 | F7: 2.9781685 | G7: 3.0166919 | H7: 3.0176025 | I7: 266.70695 | J7: 265.0574 | K7: 264.39788 | L7: 7.9429824 | M7: 7.9959651 | N7: 7.9784769
B8: BBVA México | C8: 469247.06 | D8: 528541.61 | E8: 533772.29 | F8: 2.666958 | G8: 2.7177195 | H8: 2.7038895 | I8: 289.12706 | J8: 294.20969 | K8: 297.53794 | L8: 7.7108973 | M8: 7.9957943 | N8: 8.0450972
B9: Santander | C9: 191820.94 | D9: 210536.23 | E9: 211070.48 | F9: 3.2541478 | G9: 3.1997386 | H9: 3.1676704 | I9: 256.8906 | J9: 252.72965 | K9: 253.27721 | L9: 8.3595998 | M9: 8.0866882 | N9: 8.0229871
B10: Banorte | C10: 189769.21 | D10: 219295.48 | E10: 222368.01 | F10: 2.1642409 | G10: 2.1676156 | H10: 2.157128 | I10: 289.82327 | J10: 282.48502 | K10: 283.65547 | L10: 6.2724739 | M10: 6.1231895 | N10: 6.1188116
B11: Banamex | C11: 211167.89 | D11: 242410.98 | E11: 244484.25 | F11: 2.9772361 | G11: 3.2694851 | H11: 3.2765524 | I11: 269.51494 | J11: 254.83122 | K11: 253.23448 | L11: 8.0240959 | M11: 8.3316689 | N11: 8.2973602
B12: HSBC | C12: 104950.28 | D12: 101611.27 | E12: 99988.103 | F12: 2.8218557 | G12: 3.1003888 | H12: 3.0434319 | I12: 357.1687 | J12: 335.92538 | K12: 350.22197 | L12: 10.078785 | M12: 10.414993 | N12: 10.658767
B13: Scotiabank | C13: 43772.901 | D13: 53656.33 | E13: 54528.826 | F13: 2.4022353 | G13: 2.6983831 | H13: 2.6813656 | I13: 280.5403 | J13: 260.37627 | K13: 259.4155 | L13: 6.7392381 | M13: 7.0259492 | N13: 6.955878
B14: Inbursa | C14: 81702.541 | D14: 93291.977 | E14: 94558.224 | F14: 1.4156133 | G14: 1.4853228 | H14: 1.5888618 | I14: 297.31271 | J14: 288.87159 | K14: 268.14343 | L14: 4.2087982 | M14: 4.2906757 | N14: 4.2604285
B15: Citi México | C15: 0 | D15: 0 | E15: 0 | F15: n.a. | G15: n.a. | H15: n.a. | I15: - | J15: - | K15: - | L15: - | M15: - | N15: -
B16: Banco del Bajío | C16: 6538.0297 | D16: 7344.0741 | E16: 7462.3593 | F16: 2.487233 | G16: 2.543806 | H16: 2.5645603 | I16: 363.87438 | J16: 353.64009 | K16: 349.53921 | L16: 9.0504034 | M16: 8.9959176 | N16: 8.9641438
B17: Banco Azteca | C17: 118271.59 | D17: 134631.09 | E17: 138102.77 | F17: 4.4828695 | G17: 4.9248537 | H17: 5.2547384 | I17: 228.82112 | J17: 217.74136 | K17: 204.32913 | L17: 10.257752 | M17: 10.723443 | N17: 10.736961
B18: Afirme | C18: 12045.28 | D18: 13122.169 | E18: 13234.525 | F18: 2.9869999 | G18: 2.6698322 | H18: 2.3201301 | I18: 260.09751 | J18: 296.91996 | K18: 330.63617 | L18: 7.7691124 | M18: 7.9272647 | N18: 7.6711893
B19: Monex | C19: 0 | D19: 0 | E19: 0 | F19: n.a. | G19: n.a. | H19: n.a. | I19: - | J19: - | K19: - | L19: - | M19: - | N19: -
B20: Banregio | C20: 12215.349 | D20: 13223.274 | E20: 13346.974 | F20: 2.6284222 | G20: 2.2760478 | H20: 2.2179998 | I20: 323.35484 | J20: 358.10197 | K20: 363.28692 | L20: 8.4991304 | M20: 8.1505722 | N20: 8.0577031
B21: J.P. Morgan | C21: 0 | D21: 0 | E21: 0 | F21: n.a. | G21: n.a. | H21: n.a. | I21: - | J21: - | K21: - | L21: - | M21: - | N21: -
B22: Invex | C22: 24700.882 | D22: 31902.87 | E22: 32652.582 | F22: 2.1570689 | G22: 2.6376079 | H22: 2.4491346 | I22: 325.25008 | J22: 283.94927 | K22: 301.96074 | L22: 7.0158683 | M22: 7.4894684 | N22: 7.3954251
B23: Bank of America | C23: 0 | D23: 0 | E23: 0 | F23: n.a. | G23: n.a. | H23: n.a. | I23: - | J23: - | K23: - | L23: - | M23: - | N23: -
B24: BanCoppel | C24: 22555.022 | D24: 22361.139 | E24: 22527.043 | F24: 15.473129 | G24: 10.927348 | H24: 10.43607 | I24: 154.75863 | J24: 186.81451 | K24: 192.21657 | L24: 23.946003 | M24: 20.413871 | N24: 20.059856
B25: Banca Mifel | C25: 281.10661 | D25: 420.53582 | E25: 433.82471 | F25: 7.9991373 | G25: 5.0316836 | H25: 5.2994499 | I25: 243.99057 | J25: 356.70829 | K25: 324.20116 | L25: 19.517141 | M25: 17.948433 | N25: 17.180878
B26: Multiva | C26: 4999.1264 | D26: 6095.3217 | E26: 6243.7788 | F26: 2.07771 | G26: 1.2333623 | H26: 1.1835833 | I26: 188.83289 | J26: 265.8886 | K26: 276.64369 | L26: 3.9233998 | M26: 3.2793697 | N26: 3.2743086
B27: Banco Base | C27: 0 | D27: 0 | E27: 0 | F27: n.a. | G27: n.a. | H27: n.a. | I27: - | J27: - | K27: - | L27: - | M27: - | N27: -
B28: Barclays | C28: 0 | D28: 0 | E28: 0 | F28: n.a. | G28: n.a. | H28: n.a. | I28: - | J28: - | K28: - | L28: - | M28: - | N28: -
B29: Sabadell | C29: 12.835845 | D29: 11.524435 | E29: 11.580522 | F29: 12.046499 | G29: 1.5596513 | H29: 1.3422538 | I29: 160.01326 | J29: 672.84927 | K29: 735.94184 | L29: 19.275996 | M29: 10.494102 | N29: 9.8782076
B30: Ve por Más | C30: 133.74245 | D30: 170.171 | E30: 153.45537 | F30: 0.038194307 | G30: 1.0307626 | H30: 1.0322559 | I30: 6478.5835 | J30: 433.35264 | K30: 333.59947 | L30: 2.47445 | M30: 4.4668369 | N30: 3.4436
B31: CIBanco | C31: 7223.5407 | D31: 8909.7905 | E31: 8962.1391 | F31: 2.4552665 | G31: 2.2979199 | H31: 2.4724452 | I31: 133.7702 | J31: 143.95998 | K31: 138.06547 | L31: 3.2844149 | M31: 3.308085 | N31: 3.4135931
B32: Bansí | C32: 587.18263 | D32: 843.46492 | E32: 855.70546 | F32: 0.0083180253 | G32: 4.9727431 | H32: 4.896132 | I32: 52000.129 | J32: 148.87804 | K32: 157.06003 | L32: 4.3253839 | M32: 7.4033226 | N32: 7.6898663
B33: Actinver | C33: 3148.0283 | D33: 3544.7911 | E33: 3616.766 | F33: 7.0137787 | G33: 6.7196323 | H33: 6.3160071 | I33: 140.19119 | J33: 170.54998 | K33: 161.29538 | L33: 9.8326997 | M33: 11.460331 | N33: 10.187428
B34: Compartamos | C34: 45844.851 | D34: 54933.984 | E34: 58883.972 | F34: 2.9944215 | G34: 3.315018 | H34: 3.1850154 | I34: 250.5112 | J34: 237.49325 | K34: 234.3868 | L34: 7.5013612 | M34: 7.8729441 | N34: 7.4652557
B35: BIAfirme | C35: 0 | D35: 0 | E35: 0 | F35: n.a. | G35: n.a. | H35: n.a. | I35: - | J35: - | K35: - | L35: - | M35: - | N35: -
B36: Intercam Banco | C36: 361.53928 | D36: 472.151 | E36: 474.9505 | F36: 0.28995494 | G36: 0.49491264 | H36: 0.49199548 | I36: 1517.9118 | J36: 2218.032 | K36: 2566.5374 | L36: 4.4012604 | M36: 10.977321 | N36: 12.627248
B37: Bancrea | C37: 1806.7065 | D37: 2331.5832 | E37: 2353.7182 | F37: 1.4917264 | G37: 1.6394143 | H37: 1.6341196 | I37: 150.64261 | J37: 148.34792 | K37: 149.13689 | L37: 2.2471755 | M37: 2.4320369 | N37: 2.437075
B38: MUFG Bank | C38: 0 | D38: 0 | E38: 0 | F38: n.a. | G38: n.a. | H38: n.a. | I38: - | J38: - | K38: - | L38: - | M38: - | N38: -
B39: Consubanco | C39: 17084.306 | D39: 21065.258 | E39: 21620.371 | F39: 2.3738489 | G39: 2.4193474 | H39: 2.3013396 | I39: 188.45912 | J39: 190.60451 | K39: 194.77049 | L39: 4.4737348 | M39: 4.6113852 | N39: 4.4823304
B40: BNP Paribas México | C40: 0 | D40: 0 | E40: 0 | F40: n.a. | G40: n.a. | H40: n.a. | I40: - | J40: - | K40: - | L40: - | M40: - | N40: -
B41: Autofin | C41: 730.31605 | D41: 606.62719 | E41: 573.04424 | F41: 1.2268574 | G41: 2.879842 | H41: 2.2954838 | I41: 394.23263 | J41: 214.01563 | K41: 242.47833 | L41: 4.8366722 | M41: 6.163312 | N41: 5.5660508
B42: Bankaool | C42: 9.926073 | D42: 25.217417 | E42: 26.703181 | F42: 15.806644 | G42: 3.5266023 | H42: 3.7336563 | I42: 93.519544 | J42: 159.08123 | K42: 158.47754 | L42: 14.782301 | M42: 5.6101622 | N42: 5.9170067
B43: Inmobiliario Mexicano | C43: 0 | D43: 0 | E43: 0 | F43: n.a. | G43: n.a. | H43: n.a. | I43: - | J43: - | K43: - | L43: - | M43: - | N43: -
B44: Mizuho Bank | C44: 0 | D44: 0 | E44: 0 | F44: n.a. | G44: n.a. | H44: n.a. | I44: - | J44: - | K44: - | L44: - | M44: - | N44: -
B45: ICBC | C45: 0 | D45: 0 | E45: 0 | F45: n.a. | G45: n.a. | H45: n.a. | I45: - | J45: - | K45: - | L45: - | M45: - | N45: -
B46: Banco Covalto | C46: 0 | D46: 0 | E46: 0 | F46: n.a. | G46: n.a. | H46: n.a. | I46: - | J46: - | K46: - | L46: - | M46: - | N46: -
B47: Bank of China | C47: 0 | D47: 0 | E47: 0 | F47: n.a. | G47: n.a. | H47: n.a. | I47: - | J47: - | K47: - | L47: - | M47: - | N47: -
B48: Volkswagen Bank | C48: 4774.4336 | D48: 7208.5168 | E48: 7276.972 | F48: 0.9582271 | G48: 1.2097473 | H48: 1.0732016 | I48: 246.68678 | J48: 217.48819 | K48: 210.49931 | L48: 2.3638196 | M48: 2.6310575 | N48: 2.2590819
B49: Openbank | C49: 0 | D49: 86.174941 | E49: 137.80434 | F49: n.a. | G49: 0.071860798 | H49: 0.90948808 | I49: - | J49: 13763.502 | K49: 1416.6733 | L49: - | M49: 9.890562 | N49: 12.884475
B50: Shinhan | C50: 0 | D50: 0 | E50: 0 | F50: n.a. | G50: n.a. | H50: n.a. | I50: - | J50: - | K50: - | L50: - | M50: - | N50: -
B51: Banco Ualá | C51: 222.54806 | D51: 465.20481 | E51: 498.93344 | F51: 16.16518 | G51: 10.306225 | H51: 10.301717 | I51: 189.30491 | J51: 224.79996 | K51: 237.09834 | L51: 30.60148 | M51: 23.16839 | N51: 24.425198
B52: Banco S3 | C52: 0 | D52: 0 | E52: 0 | F52: n.a. | G52: n.a. | H52: n.a. | I52: - | J52: - | K52: - | L52: - | M52: - | N52: -
B53: KEB Hana México | C53: 0 | D53: 0 | E53: 0 | F53: n.a. | G53: n.a. | H53: n.a. | I53: - | J53: - | K53: - | L53: - | M53: - | N53: -
B54: Banco Bineo | C54: 31.28364 | D54: 18.537722 | E54: 13.728232 | F54: 1.9831528 | G54: 39.966389 | H54: 41.156656 | I54: 489.84201 | J54: 100.3292 | K54: 98.108709 | L54: 9.7143154 | M54: 40.097958 | N54: 40.378264
B55: Dondé Banco | C55: 0 | D55: 0 | E55: 0 | F55: n.a. | G55: n.a. | H55: n.a. | I55: - | J55: - | K55: - | L55: - | M55: - | N55: -
B56: Credit Suisse | C56: 0 | D56: 0 | E56: 0 | F56: n.a. | G56: n.a. | H56: n.a. | I56: - | J56: - | K56: - | L56: - | M56: - | N56: -
B57: Hey Banco | C57: 0 | D57: 0 | E57: 0 | F57: n.a. | G57: n.a. | H57: n.a. | I57: - | J57: - | K57: - | L57: - | M57: - | N57: -
B58: Forjadores | C58: 500.65968 | D58: 364.49306 | E58: 381.86234 | F58: 6.3855057 | G58: 11.51854 | H58: 9.7035952 | I58: 138.30468 | J58: 111.92801 | K58: 117.05369 | L58: 8.8314534 | M58: 12.892472 | N58: 11.358417
B59: Pagatodo | C59: 0 | D59: 0 | E59: 0 | F59: n.a. | G59: n.a. | H59: n.a. | I59: - | J59: - | K59: - | L59: - | M59: - | N59: -

Sheet CCCTC
B2: Cartera de crédito al consumo
B3: Millones de pesos y porcentajes
C5: Tarjeta de crédito (MDP) 1/ | F5: IMOR (%) 5/ | I5: ICOR (%) 6/ | L5: Pérdida esperada (%) 7/
C6: 45474 | D6: 45809 | E6: 45839 | F6: =C6 -> 45474 | G6: =D6 -> 45809 | H6: =E6 -> 45839 | I6: =C6 -> 45474 | J6: =D6 -> 45809 | K6: =E6 -> 45839 | L6: =C6 -> 45474 | M6: =D6 -> 45809 | N6: =E6 -> 45839
B7: Sistema */ | C7: 586127.27 | D7: 656045.92 | E7: 658350.58 | F7: 3.3827147 | G7: 3.3028471 | H7: 3.2697198 | I7: 308.30214 | J7: 320.15656 | K7: 325.30862 | L7: 10.428982 | M7: 10.574282 | N7: 10.63668
B8: BBVA México | C8: 188359.73 | D8: 212507.97 | E8: 214347.95 | F8: 2.8489523 | G8: 2.6934511 | H8: 2.6645707 | I8: 313.87706 | J8: 362.48127 | K8: 371.59516 | L8: 8.9422077 | M8: 9.7632559 | N8: 9.9014156
B9: Santander | C9: 80635.458 | D9: 83557.492 | E9: 82579.934 | F9: 4.0173846 | G9: 4.1780983 | H9: 4.0030479 | I9: 302.04346 | J9: 283.51592 | K9: 294.81869 | L9: 12.134248 | M9: 11.845574 | N9: 11.801734
B10: Banorte | C10: 58747.013 | D10: 68583.361 | E10: 68957.995 | F10: 2.8295389 | G10: 2.8786593 | H10: 3.0251406 | I10: 325.46783 | J10: 332.64044 | K10: 319.77149 | L10: 9.2092388 | M10: 9.5755849 | N10: 9.6735369
B11: Banamex | C11: 131950.72 | D11: 152603.92 | E11: 153359.24 | F11: 3.0497952 | G11: 3.2110228 | H11: 3.2139626 | I11: 296.65899 | J11: 284.23128 | K11: 285.37423 | L11: 9.0474915 | M11: 9.1267313 | N11: 9.171821
B12: HSBC | C12: 42528.81 | D12: 43623.801 | E12: 42937.521 | F12: 3.2456956 | G12: 3.7435814 | H12: 3.9009822 | I12: 412.52113 | J12: 369.9238 | K12: 368.07781 | L12: 13.38918 | M12: 13.848398 | N12: 14.35865
B13: Scotiabank | C13: 11400.024 | D13: 13237.013 | E13: 13421.879 | F13: 2.6170092 | G13: 2.6768456 | H13: 2.6308271 | I13: 463.90209 | J13: 469.62401 | K13: 481.9732 | L13: 12.14036 | M13: 12.57111 | N13: 12.679882
B14: Inbursa | C14: 14847.642 | D14: 16538.887 | E14: 16529.981 | F14: 1.2564323 | G14: 1.4155709 | H14: 1.4187997 | I14: 835.34041 | J14: 765.10836 | K14: 746.67908 | L14: 10.495487 | M14: 10.830652 | N14: 10.59388
B15: Citi México | C15: 0 | D15: 0 | E15: 0 | F15: n.a. | G15: n.a. | H15: n.a. | I15: - | J15: - | K15: - | L15: - | M15: - | N15: -
B16: Banco del Bajío | C16: 2648.6916 | D16: 2997.7841 | E16: 3029.7871 | F16: 3.0133835 | G16: 2.9416154 | H16: 2.9798901 | I16: 400.5655 | J16: 389.66153 | K16: 390.5011 | L16: 12.070574 | M16: 11.462344 | N16: 11.636503
B17: Banco Azteca | C17: 8122.119 | D17: 6851.9122 | E17: 6666.9365 | F17: 7.6058519 | G17: 7.3407279 | H17: 7.3743289 | I17: 274.88664 | J17: 292.47167 | K17: 288.7011 | L17: 20.907471 | M17: 21.469549 | N17: 21.289769
B18: Afirme | C18: 1520.085 | D18: 1739.2131 | E18: 1737.4808 | F18: 2.8326639 | G18: 3.115384 | H18: 3.0269642 | I18: 544.98726 | J18: 500.98119 | K18: 512.6568 | L18: 15.437658 | M18: 15.607488 | N18: 15.517938
B19: Monex | C19: 0 | D19: 0 | E19: 0 | F19: n.a. | G19: n.a. | H19: n.a. | I19: - | J19: - | K19: - | L19: - | M19: - | N19: -
B20: Banregio | C20: 5925.5374 | D20: 6356.9921 | E20: 6332.5415 | F20: 4.2422285 | G20: 3.5550511 | H20: 3.4681109 | I20: 321.86725 | J20: 373.17796 | K20: 384.03489 | L20: 13.654344 | M20: 13.266667 | N20: 13.318756
B21: J.P. Morgan | C21: 0 | D21: 0 | E21: 0 | F21: n.a. | G21: n.a. | H21: n.a. | I21: - | J21: - | K21: - | L21: - | M21: - | N21: -
B22: Invex | C22: 24509.782 | D22: 31736.68 | E22: 32471.908 | F22: 2.1394776 | G22: 2.6514198 | H22: 2.4627617 | I22: 327.97457 | J22: 283.02871 | K22: 301.17773 | L22: 7.0169424 | M22: 7.504279 | N22: 7.4172897
B23: Bank of America | C23: 0 | D23: 0 | E23: 0 | F23: n.a. | G23: n.a. | H23: n.a. | I23: - | J23: - | K23: - | L23: - | M23: - | N23: -
B24: BanCoppel | C24: 14454.008 | D24: 14782.179 | E24: 14945.64 | F24: 14.504675 | G24: 10.695159 | H24: 10.08453 | I24: 172.3601 | J24: 204.93253 | K24: 212.47552 | L24: 25.000274 | M24: 21.917861 | N24: 21.427158
B25: Banca Mifel | C25: 278.78976 | D25: 418.42109 | E25: 431.77166 | F25: 8.0656132 | G25: 5.0382188 | H25: 5.3051704 | I25: 243.34686 | J25: 357.10362 | K25: 324.49837 | L25: 19.627417 | M25: 17.991662 | N25: 17.215191
B26: Multiva | C26: 0 | D26: 0 | E26: 0 | F26: n.a. | G26: n.a. | H26: n.a. | I26: - | J26: - | K26: - | L26: - | M26: - | N26: -
B27: Banco Base | C27: 0 | D27: 0 | E27: 0 | F27: n.a. | G27: n.a. | H27: n.a. | I27: - | J27: - | K27: - | L27: - | M27: - | N27: -
B28: Barclays | C28: 0 | D28: 0 | E28: 0 | F28: n.a. | G28: n.a. | H28: n.a. | I28: - | J28: - | K28: - | L28: - | M28: - | N28: -
B29: Sabadell | C29: 0 | D29: 0 | E29: 0 | F29: n.a. | G29: n.a. | H29: n.a. | I29: - | J29: - | K29: - | L29: - | M29: - | N29: -
B30: Ve por Más | C30: 0 | D30: 0 | E30: 0 | F30: n.a. | G30: n.a. | H30: n.a. | I30: - | J30: - | K30: - | L30: - | M30: - | N30: -
B31: CIBanco | C31: 0 | D31: 0 | E31: 0 | F31: n.a. | G31: n.a. | H31: n.a. | I31: - | J31: - | K31: - | L31: - | M31: - | N31: -
B32: Bansí | C32: 0 | D32: 0 | E32: 0 | F32: n.a. | G32: n.a. | H32: n.a. | I32: - | J32: - | K32: - | L32: - | M32: - | N32: -
B33: Actinver | C33: 0 | D33: 0 | E33: 0 | F33: n.a. | G33: n.a. | H33: n.a. | I33: - | J33: - | K33: - | L33: - | M33: - | N33: -
B34: Compartamos | C34: 0 | D34: 0 | E34: 0 | F34: n.a. | G34: n.a. | H34: n.a. | I34: - | J34: - | K34: - | L34: - | M34: - | N34: -
B35: BIAfirme | C35: 0 | D35: 0 | E35: 0 | F35: n.a. | G35: n.a. | H35: n.a. | I35: - | J35: - | K35: - | L35: - | M35: - | N35: -
B36: Intercam Banco | C36: 0 | D36: 0 | E36: 0 | F36: n.a. | G36: n.a. | H36: n.a. | I36: - | J36: - | K36: - | L36: - | M36: - | N36: -
B37: Bancrea | C37: 0 | D37: 0 | E37: 0 | F37: n.a. | G37: n.a. | H37: n.a. | I37: - | J37: - | K37: - | L37: - | M37: - | N37: -
... B48: Volkswagen Bank | C48: 0 | D48: 0 | E48: 0 | F48: n.a. | G48: n.a. | H48: n.a. | I48: - | J48: - | K48: - | L48: - | M48: - | N48: -
B49: Openbank | C49: 0 | D49: 86.174941 | E49: 137.80434 | F49: n.a. | G49: 0.071860798 | H49: 0.90948808 | I49: - | J49: 13763.502 | K49: 1416.6733 | L49: - | M49: 9.890562 | N49: 12.884475
B50: Shinhan | C50: 0 | D50: 0 | E50: 0 | F50: n.a. | G50: n.a. | H50: n.a. | I50: - | J50: - | K50: - | L50: - | M50: - | N50: -
B51: Banco Ualá | C51: 198.86147 | D51: 424.1193 | E51: 462.21036 | F51: 17.186012 | G51: 9.990641 | H51: 10.005616 | I51: 188.45132 | J51: 236.51831 | K51: 247.53224 | L51: 32.387266 | M51: 23.629695 | N51: 24.767125
B52: Banco S3 | C52: 0 | D52: 0 | E52: 0 | F52: n.a. | G52: n.a. | H52: n.a. | I52: - | J52: - | K52: - | L52: - | M52: - | N52: -
B53: KEB Hana México | C53: 0 | D53: 0 | E53: 0 | F53: n.a. | G53: n.a. | H53: n.a. | I53: - | J53: - | K53: - | L53: - | M53: - | N53: -
B54: Banco Bineo | C54: 0 | D54: 0 | E54: 0 | F54: n.a. | G54: n.a. | H54: n.a. | I54: - | J54: - | K54: - | L54: - | M54: - | N54: -
B55: Dondé Banco | C55: 0 | D55: 0 | E55: 0 | F55: n.a. | G55: n.a. | H55: n.a. | I55: - | J55: - | K55: - | L55: - | M55: - | N55: -
B56: Credit Suisse | C56: 0 | D56: 0 | E56: 0 | F56: n.a. | G56: n.a. | H56: n.a. | I56: - | J56: - | K56: - | L56: - | M56: - | N56: -
B57: Hey Banco | C57: 0 | D57: 0 | E57: 0 | F57: n.a. | G57: n.a. | H57: n.a. | I57: - | J57: - | K57: - | L57: - | M57: - | N57: -
B58: Forjadores | C58: 0 | D58: 0 | E58: 0 | F58: n.a. | G58: n.a. | H58: n.a. | I58: - | J58: - | K58: - | L58: - | M58: - | N58: -
B59: Pagatodo | C59: 0 | D59: 0 | E59: 0 | F59: n.a. | G59: n.a. | H59: n.a. | I59: - | J59: - | K59: - | L59: - | M59: - | N59: -

Sheet CCCN
B2: Cartera de crédito al consumo
B3: Millones de pesos y porcentajes
C5: Cartera de nómina (MDP) 1/ | F5: IMOR (%) 5/ | I5: ICOR (%) 6/ | L5: Pérdida esperada (%) 7/
C6: 45474 | D6: 45809 | E6: 45839 | F6: =C6 -> 45474 | G6: =D6 -> 45809 | H6: =E6 -> 45839 | I6: =C6 -> 45474 | J6: =D6 -> 45809 | K6: =E6 -> 45839 | L6: =C6 -> 45474 | M6: =D6 -> 45809 | N6: =E6 -> 45839
B7: Sistema */ | C7: 391538.26 | D7: 418607.38 | E7: 422658.79 | F7: 2.6770793 | G7: 2.8547349 | H7: 2.7954448 | I7: 268.15516 | J7: 250.39887 | K7: 253.78037 | L7: 7.1787262 | M7: 7.1482239 | N7: 7.09429
B8: BBVA México | C8: 152927.18 | D8: 166911.42 | E8: 168966.31 | F8: 2.3583119 | G8: 2.6310093 | H8: 2.6142045 | I8: 306.8347 | J8: 258.88631 | K8: 259.10653 | L8: 7.2361192 | M8: 6.8113229 | N8: 6.7735745
B9: Santander | C9: 53813.935 | D9: 55040.536 | E9: 55425.954 | F9: 3.4987696 | G9: 3.5418289 | H9: 3.5071355 | I9: 210.86678 | J9: 201.44236 | K9: 204.03325 | L9: 7.3777427 | M9: 7.1347436 | N9: 7.1557227
B10: Banorte | C10: 81820.8 | D10: 88217.491 | E10: 89295.962 | F10: 2.6079759 | G10: 2.684724 | H10: 2.5852445 | I10: 265.6144 | J10: 246.00133 | K10: 256.91411 | L10: 6.9271595 | M10: 6.6044568 | N10: 6.6418579
B11: Banamex | C11: 59520.033 | D11: 65942.707 | E11: 66865.377 | F11: 2.7358699 | G11: 3.1556112 | H11: 3.1530465 | I11: 227.33733 | J11: 201.16689 | K11: 193.03685 | L11: 6.2196537 | M11: 6.348045 | N11: 6.0865417
B12: HSBC | C12: 33066.587 | D12: 31072.536 | E12: 30570.598 | F12: 2.8820565 | G12: 2.6985318 | H12: 2.3533093 | I12: 311.47416 | J12: 320.81269 | K12: 382.6553 | L12: 8.9768611 | M12: 8.6572325 | N12: 9.0050629
B13: Scotiabank | C13: 1968.9194 | D13: 1646.0801 | E13: 1633.7834 | F13: 2.857311 | G13: 3.7239479 | H13: 3.9720694 | I13: 215.70373 | J13: 181.91151 | K13: 164.94656 | L13: 6.1633264 | M13: 6.7742897 | N13: 6.5517919
B14: Inbursa | C14: 1611.5854 | D14: 2369.7254 | E14: 2434.2377 | F14: 1.874303 | G14: 2.9321204 | H14: 3.0363816 | I14: 374.03628 | J14: 271.57509 | K14: 273.92583 | L14: 7.0105733 | M14: 7.9629085 | N14: 8.3174336
B15: Citi México | C15: 0 | D15: 0 | E15: 0 | F15: n.a. | G15: n.a. | H15: n.a. | I15: - | J15: - | K15: - | L15: - | M15: - | N15: -
B16: Banco del Bajío | C16: 2384.4307 | D16: 2602.972 | E16: 2660.5293 | F16: 2.2451293 | G16: 2.6201386 | H16: 2.3782292 | I16: 316.5726 | J16: 272.53709 | K16: 292.86509 | L16: 7.1074642 | M16: 7.1408496 | N16: 6.9650029
B17: Banco Azteca | C17: 2048.1073 | D17: 2007.1558 | E17: 1991.5408 | F17: 3.3031987 | G17: 2.1979376 | H17: 2.6782164 | I17: 227.39634 | J17: 347.92097 | K17: 273.99471 | L17: 7.5113529 | M17: 7.6470856 | N17: 7.3381713
B18: Afirme | C18: 2303.1533 | D18: 2304.76 | E18: 2281.2487 | F18: 2.8422676 | G18: 2.6106285 | H18: 1.9089713 | I18: 257.3632 | J18: 314.19006 | K18: 421.18897 | L18: 7.3149511 | M18: 8.2023352 | N18: 8.0403765
B19: Monex | C19: 0 | D19: 0 | E19: 0 | F19: n.a. | G19: n.a. | H19: n.a. | I19: - | J19: - | K19: - | L19: - | M19: - | N19: -
B20: Banregio | C20: 15.018387 | D20: 31.227541 | E20: 36.121764 | F20: 3.0659275 | G20: 0.94725076 | H20: 0.77776982 | I20: 290.39329 | J20: 641.76304 | K20: 790.23775 | L20: 8.9032479 | M20: 6.0791053 | N20: 6.1462308
B21: J.P. Morgan | C21: 0 | D21: 0 | E21: 0 | F21: n.a. | G21: n.a. | H21: n.a. | I21: - | J21: - | K21: - | L21: - | M21: - | N21: -
B22: Invex | C22: 0 | D22: 0 | E22: 0 | F22: n.a. | G22: n.a. | H22: n.a. | I22: - | J22: - | K22: - | L22: - | M22: - | N22: -
B23: Bank of America | C23: 0 | D23: 0 | E23: 0 | F23: n.a. | G23: n.a. | H23: n.a. | I23: - | J23: - | K23: - | L23: - | M23: - | N23: -
B24: BanCoppel | C24: 17.518095 | D24: 409.56396 | E24: 443.63179 | F24: 20.393109 | G24: 4.1687968 | H24: 4.0409498 | I24: 96.417654 | J24: 150.31109 | K24: 165.50034 | L24: 19.662557 | M24: 6.2661639 | N24: 6.6877859
B25: Banca Mifel | C25: 0.165899 | D25: 0.094106 | E25: 0.082928 | F25: 0 | G25: 0 | H25: 0 | I25: - | J25: - | K25: - | L25: 8.7354354 | M25: 11.23414 | N25: 11.765628
B26: Multiva | C26: 38.418333 | D26: 48.712668 | E26: 51.129241 | F26: 0.10007982 | G26: 1.0560949 | H26: 0.99077356 | I26: 5256.3344 | J26: 552.22139 | K26: 653.04525 | L26: 5.2605302 | M26: 5.8319819 | N26: 6.4701997
B27: Banco Base | C27: 0 | D27: 0 | E27: 0 | F27: n.a. | G27: n.a. | H27: n.a. | I27: - | J27: - | K27: - | L27: - | M27: - | N27: -
B28: Barclays | C28: 0 | D28: 0 | E28: 0 | F28: n.a. | G28: n.a. | H28: n.a. | I28: - | J28: - | K28: - | L28: - | M28: - | N28: -
B29: Sabadell | C29: 0 | D29: 0 | E29: 0 | F29: n.a. | G29: n.a. | H29: n.a. | I29: - | J29: - | K29: - | L29: - | M29: - | N29: -
B30: Ve por Más | C30: 0 | D30: 0 | E30: 0 | F30: n.a. | G30: n.a. | H30: n.a. | I30: - | J30: - | K30: - | L30: - | M30: - | N30: -
B31: CIBanco | C31: 0 | D31: 0 | E31: 0 | F31: n.a. | G31: n.a. | H31: n.a. | I31: - | J31: - | K31: - | L31: - | M31: - | N31: -
B32: Bansí | C32: 0 | D32: 0 | E32: 0 | F32: n.a. | G32: n.a. | H32: n.a. | I32: - | J32: - | K32: - | L32: - | M32: - | N32: -
B33: Actinver | C33: 0 | D33: 0 | E33: 0 | F33: n.a. | G33: n.a. | H33: n.a. | I33: - | J33: - | K33: - | L33: - | M33: - | N33: -
B34: Compartamos | C34: 0 | D34: 0 | E34: 0 | F34: n.a. | G34: n.a. | H34: n.a. | I34: - | J34: - | K34: - | L34: - | M34: - | N34: -
B35: BIAfirme | C35: 0 | D35: 0 | E35: 0 | F35: n.a. | G35: n.a. | H35: n.a. | I35: - | J35: - | K35: - | L35: - | M35: - | N35: -
B36: Intercam Banco | C36: 0 | D36: 0 | E36: 0 | F36: n.a. | G36: n.a. | H36: n.a. | I36: - | J36: - | K36: - | L36: - | M36: - | N36: -
B37: Bancrea | C37: 0 | D37: 0 | E37: 0 | F37: n.a. | G37: n.a. | H37: n.a. | I37: - | J37: - | K37: - | L37: - | M37: - | N37: -
B38: MUFG Bank | C38: 0 | D38: 0 | E38: 0 | F38: n.a. | G38: n.a. | H38: n.a. | I38: - | J38: - | K38: - | L38: - | M38: - | N38: -
... B40: BNP Paribas México | C40: 0 | D40: 0 | E40: 0 | F40: n.a. | G40: n.a. | H40: n.a. | I40: - | J40: - | K40: - | L40: - | M40: - | N40: -
B41: Autofin | C41: 2.1115635 | D41: 1.5388825 | E41: 1.4574089 | F41: 0 | G41: 10.593044 | H41: 11.126392 | I41: - | J41: 48.251668 | K41: 75.386684 | L41: 4.961908 | M41: 5.1113202 | N41: 8.3878176
B42: Bankaool | C42: 0.294952 | D42: 0.857506 | E42: 0.82494 | F42: 8.5129106 | G42: 14.521531 | H42: 15.106432 | I42: 127.81871 | J42: 56.120556 | K42: 74.307289 | L42: 10.881093 | M42: 8.149564 | N42: 11.22518
B43: Inmobiliario Mexicano | C43: 0 | D43: 0 | E43: 0 | F43: n.a. | G43: n.a. | H43: n.a. | I43: - | J43: - | K43: - | L43: - | M43: - | N43: -
B44: Mizuho Bank | C44: 0 | D44: 0 | E44: 0 | F44: n.a. | G44: n.a. | H44: n.a. | I44: - | J44: - | K44: - | L44: - | M44: - | N44: -
B45: ICBC | C45: 0 | D45: 0 | E45: 0 | F45: n.a. | G45: n.a. | H45: n.a. | I45: - | J45: - | K45: - | L45: - | M45: - | N45: -
B46: Banco Covalto | C46: 0 | D46: 0 | E46: 0 | F46: n.a. | G46: n.a. | H46: n.a. | I46: - | J46: - | K46: - | L46: - | M46: - | N46: -
B47: Bank of China | C47: 0 | D47: 0 | E47: 0 | F47: n.a. | G47: n.a. | H47: n.a. | I47: - | J47: - | K47: - | L47: - | M47: - | N47: -
B48: Volkswagen Bank | C48: 0 | D48: 0 | E48: 0 | F48: n.a. | G48: n.a. | H48: n.a. | I48: - | J48: - | K48: - | L48: - | M48: - | N48: -
B49: Openbank | C49: 0 | D49: 0 | E49: 0 | F49: n.a. | G49: n.a. | H49: n.a. | I49: - | J49: - | K49: - | L49: - | M49: - | N49: -
B50: Shinhan | C50: 0 | D50: 0 | E50: 0 | F50: n.a. | G50: n.a. | H50: n.a. | I50: - | J50: - | K50: - | L50: - | M50: - | N50: -
B51: Banco Ualá | C51: 0 | D51: 0 | E51: 0 | F51: n.a. | G51: n.a. | H51: n.a. | I51: - | J51: - | K51: - | L51: - | M51: - | N51: -
B52: Banco S3 | C52: 0 | D52: 0 | E52: 0 | F52: n.a. | G52: n.a. | H52: n.a. | I52: - | J52: - | K52: - | L52: - | M52: - | N52: -
B53: KEB Hana México | C53: 0 | D53: 0 | E53: 0 | F53: n.a. | G53: n.a. | H53: n.a. | I53: - | J53: - | K53: - | L53: - | M53: - | N53: -
B54: Banco Bineo | C54: 0 | D54: 0 | E54: 0 | F54: n.a. | G54: n.a. | H54: n.a. | I54: - | J54: - | K54: - | L54: - | M54: - | N54: -
... B59: Pagatodo | C59: 0 | D59: 0 | E59: 0 | F59: n.a. | G59: n.a. | H59: n.a. | I59: - | J59: - | K59: - | L59: - | M59: - | N59: -

Sheet CCCnrP
B2: Cartera de crédito al consumo
B3: Millones de pesos y porcentajes
C5: Créditos personales (MDP) 1/ | F5: IMOR (%) 5/ | I5: ICOR (%) 6/ | L5: Pérdida esperada (%) 7/
C6: 45474 | D6: 45809 | E6: 45839 | F6: =C6 -> 45474 | G6: =D6 -> 45809 | H6: =E6 -> 45839 | I6: =C6 -> 45474 | J6: =D6 -> 45809 | K6: =E6 -> 45839 | L6: =C6 -> 45474 | M6: =D6 -> 45809 | N6: =E6 -> 45839
B7: Sistema */ | C7: 245392.28 | D7: 281257.75 | E7: 286390.18 | F7: 4.4452919 | G7: 4.4924877 | H7: 4.6233246 | I7: 205.49088 | J7: 213.67906 | K7: 208.17168 | L7: 9.1346692 | M7: 9.5995058 | N7: 9.6244523
B8: BBVA México | C8: 66854.123 | D8: 75864.62 | E8: 76095.132 | F8: 4.5356486 | G8: 4.694206 | H8: 4.7398545 | I8: 224.28402 | J8: 218.91083 | K8: 217.7479 | L8: 10.172735 | M8: 10.276125 | N8: 10.320934
B9: Santander | C9: 14958.593 | D9: 13808.807 | E9: 13823.56 | F9: 5.0621733 | G9: 5.3086 | H9: 5.2679381 | I9: 183.84917 | J9: 240.42946 | K9: 241.22897 | L9: 9.3067636 | M9: 12.763438 | N9: 12.707793
B10: Banorte | C10: 1079.0782 | D10: 1109.4704 | E10: 1109.9151 | F10: 6.7142703 | G10: 5.1052002 | H10: 4.6160801 | I10: 177.16455 | J10: 211.90848 | K10: 221.90666 | L10: 11.895307 | M10: 10.818352 | N10: 10.243389
B11: Banamex | C11: 19692.947 | D11: 23863.887 | E11: 24259.242 | F11: 3.2147099 | G11: 3.956804 | H11: 4.011446 | I11: 205.8014 | J11: 185.30755 | K11: 185.78824 | L11: 6.6159181 | M11: 7.3322565 | N11: 7.452795
B12: HSBC | C12: 12341.818 | D12: 12389.707 | E12: 12202.198 | F12: 2.6663143 | G12: 3.2223957 | H12: 3.1953135 | I12: 362.99556 | J12: 323.29273 | K12: 334.09163 | L12: 9.6786025 | M12: 10.417771 | N12: 10.675275
B13: Scotiabank | C13: 7547.2058 | D13: 9178.9496 | E13: 9396.2079 | F13: 3.4027492 | G13: 3.4788808 | H13: 3.4919317 | I13: 301.6206 | J13: 285.03127 | K13: 278.98091 | L13: 10.263393 | M13: 9.9158982 | N13: 9.741823
B14: Inbursa | C14: 7028.7672 | D14: 8688.5859 | E14: 8794.4087 | F14: 3.8456306 | G14: 3.4155198 | H14: 3.5211182 | I14: 209.46778 | J14: 209.27781 | K14: 198.98134 | L14: 8.055357 | M14: 7.1479252 | N14: 7.0063681
B15: Citi México | C15: 0 | D15: 0 | E15: 0 | F15: n.a. | G15: n.a. | H15: n.a. | I15: - | J15: - | K15: - | L15: - | M15: - | N15: -
B16: Banco del Bajío | C16: 1157.2639 | D16: 1389.5982 | E16: 1413.4348 | F16: 2.1679777 | G16: 1.8784746 | H16: 2.2971461 | I16: 371.40341 | J16: 428.5256 | K16: 354.74577 | L16: 8.0519433 | M16: 8.0497444 | N16: 8.1490288
B17: Banco Azteca | C17: 68693.221 | D17: 80600.607 | E17: 83852.352 | F17: 4.4335828 | G17: 5.1233298 | H17: 5.5903025 | I17: 199.55419 | J17: 201.63976 | K17: 188.01614 | L17: 8.8474005 | M17: 10.33067 | N17: 10.510671
B18: Afirme | C18: 2565.1368 | D18: 2433.3721 | E18: 2461.0094 | F18: 4.0504701 | G18: 3.6648589 | H18: 3.0164433 | I18: 255.5529 | J18: 275.43297 | K18: 320.70824 | L18: 10.351094 | M18: 10.09423 | N18: 9.673982
B19: Monex | C19: 0 | D19: 0 | E19: 0 | F19: n.a. | G19: n.a. | H19: n.a. | I19: - | J19: - | K19: - | L19: - | M19: - | N19: -
B20: Banregio | C20: 939.42382 | D20: 1036.5189 | E20: 1060.5314 | F20: 3.7865898 | G20: 3.3906108 | H20: 3.0110695 | I20: 297.21456 | J20: 315.41031 | K20: 337.31942 | L20: 11.254296 | M20: 10.694336 | N20: 10.156922
B21: J.P. Morgan | C21: 0 | D21: 0 | E21: 0 | F21: n.a. | G21: n.a. | H21: n.a. | I21: - | J21: - | K21: - | L21: - | M21: - | N21: -
B22: Invex | C22: 187.48317 | D22: 166.18923 | E22: 180.67476 | F22: 4.4983983 | G22: 0 | H22: 0 | I22: 155.8508 | J22: - | K22: - | L22: 7.0107897 | M22: 4.6611275 | N22: 3.4657841
B23: Bank of America | C23: 0 | D23: 0 | E23: 0 | F23: n.a. | G23: n.a. | H23: n.a. | I23: - | J23: - | K23: - | L23: - | M23: - | N23: -
B24: BanCoppel | C24: 8083.4957 | D24: 7169.3964 | E24: 7137.7711 | F24: 17.194147 | G24: 11.792178 | H24: 11.569627 | I24: 128.35854 | J24: 152.46447 | K24: 154.52612 | L24: 22.070156 | M24: 17.978882 | N24: 17.878095
B25: Banca Mifel | C25: 2.150951 | D25: 2.020623 | E25: 1.970123 | F25: 0 | G25: 3.9127536 | H25: 4.2688198 | I25: - | J25: 237.9272 | K25: 231.65242 | L25: 6.055554 | M25: 9.309505 | N25: 9.8888242
B26: Multiva | C26: 4951.6129 | D26: 6039.7859 | E26: 6186.1077 | F26: 2.0968703 | G26: 1.2361853 | H26: 1.1864286 | I26: 186.84159 | J26: 263.11577 | K26: 273.27455 | L26: 3.9178257 | M26: 3.2525986 | N26: 3.2422074
B27: Banco Base | C27: 0 | D27: 0 | E27: 0 | F27: n.a. | G27: n.a. | H27: n.a. | I27: - | J27: - | K27: - | L27: - | M27: - | N27: -
B28: Barclays | C28: 0 | D28: 0 | E28: 0 | F28: n.a. | G28: n.a. | H28: n.a. | I28: - | J28: - | K28: - | L28: - | M28: - | N28: -
B29: Sabadell | C29: 12.835845 | D29: 11.524435 | E29: 11.580522 | F29: 12.046499 | G29: 1.5596513 | H29: 1.3422538 | I29: 160.01326 | J29: 672.84927 | K29: 735.94184 | L29: 19.275996 | M29: 10.494102 | N29: 9.8782076
B30: Ve por Más | C30: 9.464703 | D30: 7.591593 | E30: 7.417216 | F30: 0.53969998 | G30: 22.944289 | H30: 21.191644 | I30: 2075.809 | J30: 112.13081 | K30: 126.8363 | L30: 11.203141 | M30: 25.727617 | N30: 26.878697
B31: CIBanco | C31: 587.01614 | D31: 555.58866 | E31: 523.3974 | F31: 7.6977171 | G31: 6.6004651 | H31: 8.1356795 | I31: 126.17314 | J31: 165.91889 | K31: 150.30078 | L31: 9.7124511 | M31: 10.951418 | N31: 12.22799
B32: Bansí | C32: 585.42607 | D32: 842.1498 | E32: 854.44588 | F32: 0.007210475 | G32: 4.9797214 | H32: 4.9025737 | I32: 60121.679 | J32: 148.87646 | K32: 157.06016 | L32: 4.3350586 | M32: 7.4136329 | N32: 7.69999
B33: Actinver | C33: 2812.6683 | D33: 3137.639 | E33: 3199.7647 | F33: 7.5591586 | G33: 7.2518334 | H33: 6.8902744 | I33: 131.05241 | J33: 166.56553 | K33: 155.43903 | L33: 9.9064596 | M33: 12.079055 | N33: 10.710175
B34: Compartamos | C34: 5973.3617 | D34: 8960.0372 | E34: 9228.5462 | F34: 2.48488 | G34: 2.8695906 | H34: 2.9597687 | I34: 366.95633 | J34: 338.60966 | K34: 319.82091 | L34: 9.1184245 | M34: 9.7167109 | N34: 9.4659594
B35: BIAfirme | C35: 0 | D35: 0 | E35: 0 | F35: n.a. | G35: n.a. | H35: n.a. | I35: - | J35: - | K35: - | L35: - | M35: - | N35: -
B36: Intercam Banco | C36: 361.53928 | D36: 472.151 | E36: 474.9505 | F36: 0.28995494 | G36: 0.49491264 | H36: 0.49199548 | I36: 1517.9118 | J36: 2218.032 | K36: 2566.5374 | L36: 4.4012604 | M36: 10.977321 | N36: 12.627248
B37: Bancrea | C37: 1806.7065 | D37: 2331.5832 | E37: 2353.7182 | F37: 1.4917264 | G37: 1.6394143 | H37: 1.6341196 | I37: 150.64261 | J37: 148.34792 | K37: 149.13689 | L37: 2.2471755 | M37: 2.4320369 | N37: 2.437075
B38: MUFG Bank | C38: 0 | D38: 0 | E38: 0 | F38: n.a. | G38: n.a. | H38: n.a. | I38: - | J38: - | K38: - | L38: - | M38: - | N38: -
B39: Consubanco | C39: 17084.306 | D39: 21065.258 | E39: 21620.371 | F39: 2.3738489 | G39: 2.4193474 | H39: 2.3013396 | I39: 188.45912 | J39: 190.60451 | K39: 194.77049 | L39: 4.4737348 | M39: 4.6113852 | N39: 4.4823304
B40: BNP Paribas México | C40: 0 | D40: 0 | E40: 0 | F40: n.a. | G40: n.a. | H40: n.a. | I40: - | J40: - | K40: - | L40: - | M40: - | N40: -
B41: Autofin | C41: 10.567709 | D41: 29.276426 | E41: 28.958102 | F41: 0 | G41: 0 | H41: 0 | I41: - | J41: - | K41: - | L41: 7.7084619 | M41: 7.8304536 | N41: 7.8850478
B42: Bankaool | C42: 8.652132 | D42: 20.959322 | E42: 22.551151 | F42: 11.736437 | G42: 3.6489491 | H42: 3.8684766 | I42: 89.138039 | J42: 151.62939 | K42: 147.08099 | L42: 10.46163 | M42: 5.5328794 | N42: 5.6897938
B43: Inmobiliario Mexicano | C43: 0 | D43: 0 | E43: 0 | F43: n.a. | G43: n.a. | H43: n.a. | I43: - | J43: - | K43: - | L43: - | M43: - | N43: -
B44: Mizuho Bank | C44: 0 | D44: 0 | E44: 0 | F44: n.a. | G44: n.a. | H44: n.a. | I44: - | J44: - | K44: - | L44: - | M44: - | N44: -
B45: ICBC | C45: 0 | D45: 0 | E45: 0 | F45: n.a. | G45: n.a. | H45: n.a. | I45: - | J45: - | K45: - | L45: - | M45: - | N45: -
B46: Banco Covalto | C46: 0 | D46: 0 | E46: 0 | F46: n.a. | G46: n.a. | H46: n.a. | I46: - | J46: - | K46: - | L46: - | M46: - | N46: -
B47: Bank of China | C47: 0 | D47: 0 | E47: 0 | F47: n.a. | G47: n.a. | H47: n.a. | I47: - | J47: - | K47: - | L47: - | M47: - | N47: -
B48: Volkswagen Bank | C48: 0 | D48: 0 | E48: 0 | F48: n.a. | G48: n.a. | H48: n.a. | I48: - | J48: - | K48: - | L48: - | M48: - | N48: -
B49: Openbank | C49: 0 | D49: 0 | E49: 0 | F49: n.a. | G49: n.a. | H49: n.a. | I49: - | J49: - | K49: - | L49: - | M49: - | N49: -
B50: Shinhan | C50: 0 | D50: 0 | E50: 0 | F50: n.a. | G50: n.a. | H50: n.a. | I50: - | J50: - | K50: - | L50: - | M50: - | N50: -
B51: Banco Ualá | C51: 23.686595 | D51: 41.085505 | E51: 36.723086 | F51: 7.5947598 | G51: 13.563952 | H51: 14.028551 | I51: 205.52153 | J51: 135.70091 | K51: 143.43313 | L51: 15.608867 | M51: 18.406406 | N51: 20.121591
B52: Banco S3 | C52: 0 | D52: 0 | E52: 0 | F52: n.a. | G52: n.a. | H52: n.a. | I52: - | J52: - | K52: - | L52: - | M52: - | N52: -
B53: KEB Hana México | C53: 0 | D53: 0 | E53: 0 | F53: n.a. | G53: n.a. | H53: n.a. | I53: - | J53: - | K53: - | L53: - | M53: - | N53: -
B54: Banco Bineo | C54: 31.28364 | D54: 18.537722 | E54: 13.728232 | F54: 1.9831528 | G54: 39.966389 | H54: 41.156656 | I54: 489.84201 | J54: 100.3292 | K54: 98.108709 | L54: 9.7143154 | M54: 40.097958 | N54: 40.378264
B55: Dondé Banco | C55: 0 | D55: 0 | E55: 0 | F55: n.a. | G55: n.a. | H55: n.a. | I55: - | J55: - | K55: - | L55: - | M55: - | N55: -
B56: Credit Suisse | C56: 0 | D56: 0 | E56: 0 | F56: n.a. | G56: n.a. | H56: n.a. | I56: - | J56: - | K56: - | L56: - | M56: - | N56: -
B57: Hey Banco | C57: 0 | D57: 0 | E57: 0 | F57: n.a. | G57: n.a. | H57: n.a. | I57: - | J57: - | K57: - | L57: - | M57: - | N57: -
B58: Forjadores | C58: 2.443996 | D58: 22.854118 | E58: 39.516348 | F58: 62.526862 | G58: 3.4011726 | H58: 3.0170146 | I58: 86.074048 | J58: 409.44053 | K58: 404.81239 | L58: 53.819401 | M58: 13.925779 | N58: 12.213249
B59: Pagatodo | C59: 0 | D59: 0 | E59: 0 | F59: n.a. | G59: n.a. | H59: n.a. | I59: - | J59: - | K59: - | L59: - | M59: - | N59: -

Sheet CCCAut
B2: Cartera de crédito al consumo
B3: Millones de pesos y porcentajes
C5: Automotriz (MDP) 1/ | F5: IMOR (%) 5/ | I5: ICOR (%) 6/ | L5: Pérdida esperada (%) 7/
C6: 45474 | D6: 45809 | E6: 45839 | F6: =C6 -> 45474 | G6: =D6 -> 45809 | H6: =E6 -> 45839 | I6: =C6 -> 45474 | J6: =D6 -> 45809 | K6: =E6 -> 45839 | L6: =C6 -> 45474 | M6: =D6 -> 45809 | N6: =E6 -> 45839
B7: Sistema */ | C7: 267960.75 | D7: 327662.64 | E7: 333131.89 | F7: 1.0114109 | G7: 1.1382859 | H7: 1.1919643 | I7: 216.35487 | J7: 202.65 | K7: 192.26597 | L7: 2.1882368 | M7: 2.3067363 | N7: 2.2917417
B8: BBVA México | C8: 61094.675 | D8: 73244.398 | E8: 74340.891 | F8: 0.86543221 | G8: 1.0055714 | H8: 1.0054726 | I8: 283.99901 | J8: 247.43961 | K8: 249.63264 | L8: 2.4578189 | M8: 2.4881818 | N8: 2.5099878
B9: Santander | C9: 40597.367 | D9: 55928.008 | E9: 57000.872 | F9: 0.79129854 | G9: 0.88336357 | H9: 1.1150568 | I9: 232.90243 | J9: 239.94365 | K9: 190.89386 | L9: 1.8429535 | M9: 2.1195748 | N9: 2.128575
B10: Banorte | C10: 48063.746 | D10: 61328.874 | E10: 62949.063 | F10: 0.48644535 | G10: 0.56999404 | H10: 0.55035941 | I10: 292.30042 | J10: 215.11603 | K10: 217.35448 | L10: 1.4218818 | M10: 1.2261486 | N10: 1.1962308
B11: Banamex | C11: 4.0083588 | D11: 0.27930114 | E11: 0.19818957 | F11: 27.229075 | G11: 40.18589 | H11: 57.287662 | I11: 99.71514 | J11: 91.523076 | K11: 83.062806 | L11: 27.151511 | M11: 36.779363 | N11: 47.584739
B12: HSBC | C12: 15783.887 | D12: 13360.337 | E12: 13107.893 | F12: 1.2412715 | G12: 1.5422667 | H12: 1.5320433 | I12: 242.41164 | J12: 228.73491 | K12: 228.71155 | L12: 3.0089865 | M12: 3.5277024 | N12: 3.5039599
B13: Scotiabank | C13: 22848.476 | D13: 29587.083 | E13: 30069.257 | F13: 1.9077916 | G13: 2.3951787 | H13: 2.3671141 | I13: 152.72451 | J13: 151.8407 | K13: 148.61844 | L13: 2.9136654 | M13: 3.6368561 | N13: 3.517968
B14: Inbursa | C14: 56247.098 | D14: 65691.603 | E14: 66786.042 | F14: 1.1055412 | G14: 1.1951674 | H14: 1.3223194 | I14: 172.4695 | J14: 174.64199 | K14: 161.13043 | L14: 1.9067215 | M14: 2.0872641 | N14: 2.1306589
B15: Citi México | C15: 0 | D15: 0 | E15: 0 | F15: n.a. | G15: n.a. | H15: n.a. | I15: - | J15: - | K15: - | L15: - | M15: - | N15: -
B16: Banco del Bajío | C16: 347.64352 | D16: 353.71979 | E16: 358.60809 | F16: 1.2018114 | G16: 1.2244128 | H16: 1.4919443 | I16: 223.81373 | J16: 204.5925 | K16: 173.91628 | L16: 2.689819 | M16: 2.5050568 | N16: 2.594734
B17: Banco Azteca | C17: 8.3016735 | D17: 19.652511 | E17: 20.693281 | F17: 0 | G17: 0 | H17: 0 | I17: - | J17: - | K17: - | L17: 1.4442358 | M17: 1.474188 | N17: 1.4909364
B18: Afirme | C18: 5612.1804 | D18: 6337.8935 | E18: 6449.5198 | F18: 2.601801 | G18: 2.1046591 | H18: 1.988746 | I18: 178.10243 | J18: 220.12346 | K18: 233.7552 | L18: 4.6338708 | M18: 4.6328482 | N18: 4.6487972
B19: Monex | C19: 0 | D19: 0 | E19: 0 | F19: n.a. | G19: n.a. | H19: n.a. | I19: - | J19: - | K19: - | L19: - | M19: - | N19: -
B20: Banregio | C20: 5253.393 | D20: 5702.1585 | E20: 5817.7304 | F20: 0.62559503 | G20: 0.67930452 | H20: 0.74570086 | I20: 365.50982 | J20: 309.03225 | K20: 276.77918 | L20: 2.2866113 | M20: 2.09927 | N20: 2.0639448
B21: J.P. Morgan | C21: 0 | D21: 0 | E21: 0 | F21: n.a. | G21: n.a. | H21: n.a. | I21: - | J21: - | K21: - | L21: - | M21: - | N21: -
B22: Invex | C22: 0 | D22: 0 | E22: 0 | F22: n.a. | G22: n.a. | H22: n.a. | I22: - | J22: - | K22: - | L22: - | M22: - | N22: -
B23: Bank of America | C23: 0 | D23: 0 | E23: 0 | F23: n.a. | G23: n.a. | H23: n.a. | I23: - | J23: - | K23: - | L23: - | M23: - | N23: -
B24: BanCoppel | C24: 0 | D24: 0 | E24: 0 | F24: n.a. | G24: n.a. | H24: n.a. | I24: - | J24: - | K24: - | L24: - | M24: - | N24: -
B25: Banca Mifel | C25: 0 | D25: 0 | E25: 0 | F25: n.a. | G25: n.a. | H25: n.a. | I25: - | J25: - | K25: - | L25: - | M25: - | N25: -
B26: Multiva | C26: 9.095148 | D26: 6.823134 | E26: 6.541886 | F26: 0 | G26: 0 | H26: 0 | I26: - | J26: - | K26: - | L26: 1.3099952 | M26: 2.256617 | N26: 1.8345933
B27: Banco Base | C27: 0 | D27: 0 | E27: 0 | F27: n.a. | G27: n.a. | H27: n.a. | I27: - | J27: - | K27: - | L27: - | M27: - | N27: -
B28: Barclays | C28: 0 | D28: 0 | E28: 0 | F28: n.a. | G28: n.a. | H28: n.a. | I28: - | J28: - | K28: - | L28: - | M28: - | N28: -
B29: Sabadell | C29: 0 | D29: 0 | E29: 0 | F29: n.a. | G29: n.a. | H29: n.a. | I29: - | J29: - | K29: - | L29: - | M29: - | N29: -
B30: Ve por Más | C30: 0 | D30: 0 | E30: 0 | F30: n.a. | G30: n.a. | H30: n.a. | I30: - | J30: - | K30: - | L30: - | M30: - | N30: -
B31: CIBanco | C31: 6573.518 | D31: 8301.7218 | E31: 8391.5169 | F31: 1.9859529 | G31: 2.0008163 | H31: 2.1099234 | I31: 134.50979 | J31: 138.39383 | K31: 134.46955 | L31: 2.6713011 | M31: 2.7690063 | N31: 2.8372046
B32: Bansí | C32: 1.756566 | D32: 1.315117 | E32: 1.25958 | F32: 0.37744098 | G32: 0.50413765 | H32: 0.52636593 | I32: 291.70437 | J32: 158.88386 | K32: 156.24434 | L32: 1.1010119 | M32: 0.80099337 | N32: 0.822417
B33: Actinver | C33: 22.556734 | D33: 11.043764 | E33: 8.878185 | F33: 12.413087 | G33: 23.219964 | H33: 3.6020087 | I33: 107.34421 | J33: 104.082 | K33: 111.77574 | L33: 13.32473 | M33: 24.167802 | N33: 4.026172
B34: Compartamos | C34: 0 | D34: 0 | E34: 0 | F34: n.a. | G34: n.a. | H34: n.a. | I34: - | J34: - | K34: - | L34: - | M34: - | N34: -
B35: BIAfirme | C35: 0 | D35: 0 | E35: 0 | F35: n.a. | G35: n.a. | H35: n.a. | I35: - | J35: - | K35: - | L35: - | M35: - | N35: -
B36: Intercam Banco | C36: 0 | D36: 0 | E36: 0 | F36: n.a. | G36: n.a. | H36: n.a. | I36: - | J36: - | K36: - | L36: - | M36: - | N36: -
B37: Bancrea | C37: 0 | D37: 0 | E37: 0 | F37: n.a. | G37: n.a. | H37: n.a. | I37: - | J37: - | K37: - | L37: - | M37: - | N37: -
B38: MUFG Bank | C38: 0 | D38: 0 | E38: 0 | F38: n.a. | G38: n.a. | H38: n.a. | I38: - | J38: - | K38: - | L38: - | M38: - | N38: -
B39: Consubanco | C39: 0 | D39: 0 | E39: 0 | F39: n.a. | G39: n.a. | H39: n.a. | I39: - | J39: - | K39: - | L39: - | M39: - | N39: -
B40: BNP Paribas México | C40: 0 | D40: 0 | E40: 0 | F40: n.a. | G40: n.a. | H40: n.a. | I40: - | J40: - | K40: - | L40: - | M40: - | N40: -
B41: Autofin | C41: 717.63678 | D41: 575.81188 | E41: 542.62873 | F41: 1.2485336 | G41: 3.00565 | H41: 2.3942671 | I41: 383.9716 | J41: 201.43726 | K41: 226.59531 | L41: 4.7940146 | M41: 6.0544991 | N41: 5.4252968
B42: Bankaool | C42: 0.978989 | D42: 3.400589 | E42: 3.32709 | F42: 53.975887 | G42: 0 | H42: 0 | I42: 100.3096 | J42: - | K42: - | L42: 54.142999 | M42: 3.4417273 | N42: 4.0902711
B43: Inmobiliario Mexicano | C43: 0 | D43: 0 | E43: 0 | F43: n.a. | G43: n.a. | H43: n.a. | I43: - | J43: - | K43: - | L43: - | M43: - | N43: -
B44: Mizuho Bank | C44: 0 | D44: 0 | E44: 0 | F44: n.a. | G44: n.a. | H44: n.a. | I44: - | J44: - | K44: - | L44: - | M44: - | N44: -
B45: ICBC | C45: 0 | D45: 0 | E45: 0 | F45: n.a. | G45: n.a. | H45: n.a. | I45: - | J45: - | K45: - | L45: - | M45: - | N45: -
B46: Banco Covalto | C46: 0 | D46: 0 | E46: 0 | F46: n.a. | G46: n.a. | H46: n.a. | I46: - | J46: - | K46: - | L46: - | M46: - | N46: -
B47: Bank of China | C47: 0 | D47: 0 | E47: 0 | F47: n.a. | G47: n.a. | H47: n.a. | I47: - | J47: - | K47: - | L47: - | M47: - | N47: -
B48: Volkswagen Bank | C48: 4774.4336 | D48: 7208.5168 | E48: 7276.972 | F48: 0.9582271 | G48: 1.2097473 | H48: 1.0732016 | I48: 246.68678 | J48: 217.48819 | K48: 210.49931 | L48: 2.3638196 | M48: 2.6310575 | N48: 2.2590819
B49: Openbank | C49: 0 | D49: 0 | E49: 0 | F49: n.a. | G49: n.a. | H49: n.a. | I49: - | J49: - | K49: - | L49: - | M49: - | N49: -
B50: Shinhan | C50: 0 | D50: 0 | E50: 0 | F50: n.a. | G50: n.a. | H50: n.a. | I50: - | J50: - | K50: - | L50: - | M50: - | N50: -
B51: Banco Ualá | C51: 0 | D51: 0 | E51: 0 | F51: n.a. | G51: n.a. | H51: n.a. | I51: - | J51: - | K51: - | L51: - | M51: - | N51: -
B52: Banco S3 | C52: 0 | D52: 0 | E52: 0 | F52: n.a. | G52: n.a. | H52: n.a. | I52: - | J52: - | K52: - | L52: - | M52: - | N52: -
B53: KEB Hana México | C53: 0 | D53: 0 | E53: 0 | F53: n.a. | G53: n.a. | H53: n.a. | I53: - | J53: - | K53: - | L53: - | M53: - | N53: -
B54: Banco Bineo | C54: 0 | D54: 0 | E54: 0 | F54: n.a. | G54: n.a. | H54: n.a. | I54: - | J54: - | K54: - | L54: - | M54: - | N54: -
B55: Dondé Banco | C55: 0 | D55: 0 | E55: 0 | F55: n.a. | G55: n.a. | H55: n.a. | I55: - | J55: - | K55: - | L55: - | M55: - | N55: -
B56: Credit Suisse | C56: 0 | D56: 0 | E56: 0 | F56: n.a. | G56: n.a. | H56: n.a. | I56: - | J56: - | K56: - | L56: - | M56: - | N56: -
B57: Hey Banco | C57: 0 | D57: 0 | E57: 0 | F57: n.a. | G57: n.a. | H57: n.a. | I57: - | J57: - | K57: - | L57: - | M57: - | N57: -
B58: Forjadores | C58: 0 | D58: 0 | E58: 0 | F58: n.a. | G58: n.a. | H58: n.a. | I58: - | J58: - | K58: - | L58: - | M58: - | N58: -
B59: Pagatodo | C59: 0 | D59: 0 | E59: 0 | F59: n.a. | G59: n.a. | H59: n.a. | I59: - | J59: - | K59: - | L59: - | M59: - | N59: -

Sheet CCCAdq BiMu
B2: Cartera de crédito al consumo
B3: Millones de pesos y porcentajes
C5: Adquisición de bienes muebles (MDP) 1/ | F5: IMOR (%) 5/ | I5: ICOR (%) 6/ | L5: Pérdida esperada (%) 7/
C6: 45474 | D6: 45809 | E6: 45839 | F6: =C6 -> 45474 | G6: =D6 -> 45809 | H6: =E6 -> 45839 | I6: =C6 -> 45474 | J6: =D6 -> 45809 | K6: =E6 -> 45839 | L6: =C6 -> 45474 | M6: =D6 -> 45809 | N6: =E6 -> 45839
B7: Sistema */ | C7: 38916.904 | D7: 44065.439 | E7: 44445.115 | F7: 3.9593869 | G7: 4.263692 | H7: 4.3777003 | I7: 271.85114 | J7: 234.63524 | K7: 224.27364 | L7: 10.763638 | M7: 10.004124 | N7: 9.8180278
B8: BBVA México | C8: 0 | D8: 0 | E8: 0 | F8: n.a. | G8: n.a. | H8: n.a. | I8: - | J8: - | K8: - | L8: - | M8: - | N8: -
B9: Santander | C9: 900.0377 | D9: 1108.959 | E9: 1134.883 | F9: 1.3113616 | G9: 0.94447858 | H9: 1.3101137 | I9: 605.08182 | J9: 891.46608 | K9: 642.26574 | L9: 7.9348107 | M9: 8.4197061 | N9: 8.4144116
B10: Banorte | C10: 0 | D10: 0 | E10: 0 | F10: n.a. | G10: n.a. | H10: n.a. | I10: - | J10: - | K10: - | L10: - | M10: - | N10: -
B11: Banamex | C11: 0 | D11: 0 | E11: 0 | F11: n.a. | G11: n.a. | H11: n.a. | I11: - | J11: - | K11: - | L11: - | M11: - | N11: -
B12: HSBC | C12: 0 | D12: 0 | E12: 0 | F12: n.a. | G12: n.a. | H12: n.a. | I12: - | J12: - | K12: - | L12: - | M12: - | N12: -
B13: Scotiabank | C13: 0 | D13: 0 | E13: 0 | F13: n.a. | G13: n.a. | H13: n.a. | I13: - | J13: - | K13: - | L13: - | M13: - | N13: -
B14: Inbursa | C14: 10.496361 | D14: 3.175432 | E14: 2.90531 | F14: 8.0225137 | G14: 6.2728473 | H14: 6.0769763 | I14: 157.94208 | J14: 129.26653 | K14: 146.63136 | L14: 12.670925 | M14: 8.108692 | N14: 8.9107531
B15: Citi México | C15: 0 | D15: 0 | E15: 0 | F15: n.a. | G15: n.a. | H15: n.a. | I15: - | J15: - | K15: - | L15: - | M15: - | N15: -
B16: Banco del Bajío | C16: 0 | D16: 0 | E16: 0 | F16: n.a. | G16: n.a. | H16: n.a. | I16: - | J16: - | K16: - | L16: - | M16: - | N16: -
B17: Banco Azteca | C17: 37898.639 | D17: 42863.628 | E17: 43223.439 | F17: 4.0245474 | G17: 4.3521427 | H17: 4.4616539 | I17: 269.09706 | J17: 230.76691 | K17: 220.86144 | L17: 10.829938 | M17: 10.043305 | N17: 9.8540728
B18: Afirme | C18: 44.724424 | D18: 37.19708 | E18: 36.662047 | F18: 3.027319 | G18: 1.8524787 | H18: 0.54936376 | I18: 523.67981 | J18: 839.40554 | K18: 2366.552 | L18: 15.853459 | M18: 15.549809 | N18: 13.000979
B19: Monex | C19: 0 | D19: 0 | E19: 0 | F19: n.a. | G19: n.a. | H19: n.a. | I19: - | J19: - | K19: - | L19: - | M19: - | N19: -
B20: Banregio | C20: 0 | D20: 0 | E20: 0 | F20: n.a. | G20: n.a. | H20: n.a. | I20: - | J20: - | K20: - | L20: - | M20: - | N20: -
B21: J.P. Morgan | C21: 0 | D21: 0 | E21: 0 | F21: n.a. | G21: n.a. | H21: n.a. | I21: - | J21: - | K21: - | L21: - | M21: - | N21: -
B22: Invex | C22: 0 | D22: 0 | E22: 0 | F22: n.a. | G22: n.a. | H22: n.a. | I22: - | J22: - | K22: - | L22: - | M22: - | N22: -
B23: Bank of America | C23: 0 | D23: 0 | E23: 0 | F23: n.a. | G23: n.a. | H23: n.a. | I23: - | J23: - | K23: - | L23: - | M23: - | N23: -
B24: BanCoppel | C24: 0 | D24: 0 | E24: 0 | F24: n.a. | G24: n.a. | H24: n.a. | I24: - | J24: - | K24: - | L24: - | M24: - | N24: -
B25: Banca Mifel | C25: 0 | D25: 0 | E25: 0 | F25: n.a. | G25: n.a. | H25: n.a. | I25: - | J25: - | K25: - | L25: - | M25: - | N25: -
B26: Multiva | C26: 0 | D26: 0 | E26: 0 | F26: n.a. | G26: n.a. | H26: n.a. | I26: - | J26: - | K26: - | L26: - | M26: - | N26: -
B27: Banco Base | C27: 0 | D27: 0 | E27: 0 | F27: n.a. | G27: n.a. | H27: n.a. | I27: - | J27: - | K27: - | L27: - | M27: - | N27: -
B28: Barclays | C28: 0 | D28: 0 | E28: 0 | F28: n.a. | G28: n.a. | H28: n.a. | I28: - | J28: - | K28: - | L28: - | M28: - | N28: -
B29: Sabadell | C29: 0 | D29: 0 | E29: 0 | F29: n.a. | G29: n.a. | H29: n.a. | I29: - | J29: - | K29: - | L29: - | M29: - | N29: -
B30: Ve por Más | C30: 0 | D30: 0 | E30: 0 | F30: n.a. | G30: n.a. | H30: n.a. | I30: - | J30: - | K30: - | L30: - | M30: - | N30: -
B31: CIBanco | C31: 63.006506 | D31: 52.480073 | E31: 47.224782 | F31: 2.5764958 | G31: 3.7465782 | H31: 4.1238009 | I31: 285.76101 | J31: 204.62779 | K31: 197.46192 | L31: 7.3626206 | M31: 7.6665404 | N31: 8.1429365
B32: Bansí | C32: 0 | D32: 0 | E32: 0 | F32: n.a. | G32: n.a. | H32: n.a. | I32: - | J32: - | K32: - | L32: - | M32: - | N32: -
B33: Actinver | C33: 0 | D33: 0 | E33: 0 | F33: n.a. | G33: n.a. | H33: n.a. | I33: - | J33: - | K33: - | L33: - | M33: - | N33: -
B34: Compartamos | C34: 0 | D34: 0 | E34: 0 | F34: n.a. | G34: n.a. | H34: n.a. | I34: - | J34: - | K34: - | L34: - | M34: - | N34: -
B35: BIAfirme | C35: 0 | D35: 0 | E35: 0 | F35: n.a. | G35: n.a. | H35: n.a. | I35: - | J35: - | K35: - | L35: - | M35: - | N35: -
B36: Intercam Banco | C36: 0 | D36: 0 | E36: 0 | F36: n.a. | G36: n.a. | H36: n.a. | I36: - | J36: - | K36: - | L36: - | M36: - | N36: -
B37: Bancrea | C37: 0 | D37: 0 | E37: 0 | F37: n.a. | G37: n.a. | H37: n.a. | I37: - | J37: - | K37: - | L37: - | M37: - | N37: -
B38: MUFG Bank | C38: 0 | D38: 0 | E38: 0 | F38: n.a. | G38: n.a. | H38: n.a. | I38: - | J38: - | K38: - | L38: - | M38: - | N38: -
B39: Consubanco | C39: 0 | D39: 0 | E39: 0 | F39: n.a. | G39: n.a. | H39: n.a. | I39: - | J39: - | K39: - | L39: - | M39: - | N39: -
B40: BNP Paribas México | C40: 0 | D40: 0 | E40: 0 | F40: n.a. | G40: n.a. | H40: n.a. | I40: - | J40: - | K40: - | L40: - | M40: - | N40: -
B41: Autofin | C41: 0 | D41: 0 | E41: 0 | F41: n.a. | G41: n.a. | H41: n.a. | I41: - | J41: - | K41: - | L41: - | M41: - | N41: -
B42: Bankaool | C42: 0 | D42: 0 | E42: 0 | F42: n.a. | G42: n.a. | H42: n.a. | I42: - | J42: - | K42: - | L42: - | M42: - | N42: -
B43: Inmobiliario Mexicano | C43: 0 | D43: 0 | E43: 0 | F43: n.a. | G43: n.a. | H43: n.a. | I43: - | J43: - | K43: - | L43: - | M43: - | N43: -
... B59: Pagatodo | C59: 0 | D59: 0 | E59: 0 | F59: n.a. | G59: n.a. | H59: n.a. | I59: - | J59: - | K59: - | L59: - | M59: - | N59: -

Sheet CCOAC
B2: Cartera de crédito al consumo
B3: Millones de pesos y porcentajes
C5: Op. de arrendamiento financiero (MDP) 1/ | F5: IMOR (%) 5/ | I5: ICOR (%) 6/ | L5: Pérdida esperada (%) 7/
C6: 45474 | D6: 45809 | E6: 45839 | F6: =C6 -> 45474 | G6: =D6 -> 45809 | H6: =E6 -> 45839 | I6: =C6 -> 45474 | J6: =D6 -> 45809 | K6: =E6 -> 45839 | L6: =C6 -> 45474 | M6: =D6 -> 45809 | N6: =E6 -> 45839
B7: Sistema */ | C7: 93.408144 | D7: 107.9587 | E7: 111.27518 | F7: 0.85492434 | G7: 0.73970751 | H7: 0.73613374 | I7: 260.1931 | J7: 289.43082 | K7: 274.63985 | L7: 2.2244542 | M7: 2.1409416 | N7: 2.0217166
B8: BBVA México | C8: 0 | D8: 0 | E8: 0 | F8: n.a. | G8: n.a. | H8: n.a. | I8: - | J8: - | K8: - | L8: - | M8: - | N8: -
B9: Santander | C9: 0 | D9: 0 | E9: 0 | F9: n.a. | G9: n.a. | H9: n.a. | I9: - | J9: - | K9: - | L9: - | M9: - | N9: -
B10: Banorte | C10: 0 | D10: 0 | E10: 0 | F10: n.a. | G10: n.a. | H10: n.a. | I10: - | J10: - | K10: - | L10: - | M10: - | N10: -
B11: Banamex | C11: 0 | D11: 0 | E11: 0 | F11: n.a. | G11: n.a. | H11: n.a. | I11: - | J11: - | K11: - | L11: - | M11: - | N11: -
B12: HSBC | C12: 0 | D12: 0 | E12: 0 | F12: n.a. | G12: n.a. | H12: n.a. | I12: - | J12: - | K12: - | L12: - | M12: - | N12: -
B13: Scotiabank | C13: 0 | D13: 0 | E13: 0 | F13: n.a. | G13: n.a. | H13: n.a. | I13: - | J13: - | K13: - | L13: - | M13: - | N13: -
B14: Inbursa | C14: 0 | D14: 0 | E14: 0 | F14: n.a. | G14: n.a. | H14: n.a. | I14: - | J14: - | K14: - | L14: - | M14: - | N14: -
B15: Citi México | C15: 0 | D15: 0 | E15: 0 | F15: n.a. | G15: n.a. | H15: n.a. | I15: - | J15: - | K15: - | L15: - | M15: - | N15: -
B16: Banco del Bajío | C16: 0 | D16: 0 | E16: 0 | F16: n.a. | G16: n.a. | H16: n.a. | I16: - | J16: - | K16: - | L16: - | M16: - | N16: -
B17: Banco Azteca | C17: 0 | D17: 0 | E17: 0 | F17: n.a. | G17: n.a. | H17: n.a. | I17: - | J17: - | K17: - | L17: - | M17: - | N17: -
B18: Afirme | C18: 0 | D18: 0 | E18: 0 | F18: n.a. | G18: n.a. | H18: n.a. | I18: - | J18: - | K18: - | L18: - | M18: - | N18: -
B19: Monex | C19: 0 | D19: 0 | E19: 0 | F19: n.a. | G19: n.a. | H19: n.a. | I19: - | J19: - | K19: - | L19: - | M19: - | N19: -
B20: Banregio | C20: 81.928814 | D20: 96.37689 | E20: 100.04839 | F20: 0.97471075 | G20: 0.82859966 | H20: 0.81873796 | I20: 239.98708 | J20: 260.70767 | K20: 262.89672 | L20: 2.3391799 | M20: 2.1602228 | N20: 2.1524353
B21: J.P. Morgan | C21: 0 | D21: 0 | E21: 0 | F21: n.a. | G21: n.a. | H21: n.a. | I21: - | J21: - | K21: - | L21: - | M21: - | N21: -
B22: Invex | C22: 0 | D22: 0 | E22: 0 | F22: n.a. | G22: n.a. | H22: n.a. | I22: - | J22: - | K22: - | L22: - | M22: - | N22: -
B23: Bank of America | C23: 0 | D23: 0 | E23: 0 | F23: n.a. | G23: n.a. | H23: n.a. | I23: - | J23: - | K23: - | L23: - | M23: - | N23: -
B24: BanCoppel | C24: 0 | D24: 0 | E24: 0 | F24: n.a. | G24: n.a. | H24: n.a. | I24: - | J24: - | K24: - | L24: - | M24: - | N24: -
B25: Banca Mifel | C25: 0 | D25: 0 | E25: 0 | F25: n.a. | G25: n.a. | H25: n.a. | I25: - | J25: - | K25: - | L25: - | M25: - | N25: -
B26: Multiva | C26: 0 | D26: 0 | E26: 0 | F26: n.a. | G26: n.a. | H26: n.a. | I26: - | J26: - | K26: - | L26: - | M26: - | N26: -
B27: Banco Base | C27: 0 | D27: 0 | E27: 0 | F27: n.a. | G27: n.a. | H27: n.a. | I27: - | J27: - | K27: - | L27: - | M27: - | N27: -
B28: Barclays | C28: 0 | D28: 0 | E28: 0 | F28: n.a. | G28: n.a. | H28: n.a. | I28: - | J28: - | K28: - | L28: - | M28: - | N28: -
B29: Sabadell | C29: 0 | D29: 0 | E29: 0 | F29: n.a. | G29: n.a. | H29: n.a. | I29: - | J29: - | K29: - | L29: - | M29: - | N29: -
B30: Ve por Más | C30: 11.47933 | D30: 11.581806 | E30: 11.226791 | F30: 0 | G30: 0 | H30: 0 | I30: - | J30: - | K30: - | L30: 1.4056482 | M30: 1.9804942 | N30: 0.85680761
B31: CIBanco | C31: 0 | D31: 0 | E31: 0 | F31: n.a. | G31: n.a. | H31: n.a. | I31: - | J31: - | K31: - | L31: - | M31: - | N31: -
B32: Bansí | C32: 0 | D32: 0 | E32: 0 | F32: n.a. | G32: n.a. | H32: n.a. | I32: - | J32: - | K32: - | L32: - | M32: - | N32: -
B33: Actinver | C33: 0 | D33: 0 | E33: 0 | F33: n.a. | G33: n.a. | H33: n.a. | I33: - | J33: - | K33: - | L33: - | M33: - | N33: -
B34: Compartamos | C34: 0 | D34: 0 | E34: 0 | F34: n.a. | G34: n.a. | H34: n.a. | I34: - | J34: - | K34: - | L34: - | M34: - | N34: -
B35: BIAfirme | C35: 0 | D35: 0 | E35: 0 | F35: n.a. | G35: n.a. | H35: n.a. | I35: - | J35: - | K35: - | L35: - | M35: - | N35: -
B36: Intercam Banco | C36: 0 | D36: 0 | E36: 0 | F36: n.a. | G36: n.a. | H36: n.a. | I36: - | J36: - | K36: - | L36: - | M36: - | N36: -
B37: Bancrea | C37: 0 | D37: 0 | E37: 0 | F37: n.a. | G37: n.a. | H37: n.a. | I37: - | J37: - | K37: - | L37: - | M37: - | N37: -
B38: MUFG Bank | C38: 0 | D38: 0 | E38: 0 | F38: n.a. | G38: n.a. | H38: n.a. | I38: - | J38: - | K38: - | L38: - | M38: - | N38: -
B39: Consubanco | C39: 0 | D39: 0 | E39: 0 | F39: n.a. | G39: n.a. | H39: n.a. | I39: - | J39: - | K39: - | L39: - | M39: - | N39: -
B40: BNP Paribas México | C40: 0 | D40: 0 | E40: 0 | F40: n.a. | G40: n.a. | H40: n.a. | I40: - | J40: - | K40: - | L40: - | M40: - | N40: -
B41: Autofin | C41: 0 | D41: 0 | E41: 0 | F41: n.a. | G41: n.a. | H41: n.a. | I41: - | J41: - | K41: - | L41: - | M41: - | N41: -
B42: Bankaool | C42: 0 | D42: 0 | E42: 0 | F42: n.a. | G42: n.a. | H42: n.a. | I42: - | J42: - | K42: - | L42: - | M42: - | N42: -
... B59: Pagatodo | C59: 0 | D59: 0 | E59: 0 | F59: n.a. | G59: n.a. | H59: n.a. | I59: - | J59: - | K59: - | L59: - | M59: - | N59: -

Sheet CCCMicro
B2: Cartera de crédito al consumo
B3: Millones de pesos y porcentajes
C5: Microcréditos (MDP) 1/ | F5: IMOR (%) 5/ | I5: ICOR (%) 6/ | L5: Pérdida esperada (%) 7/
C6: 45474 | D6: 45809 | E6: 45839 | F6: =C6 -> 45474 | G6: =D6 -> 45809 | H6: =E6 -> 45839 | I6: =C6 -> 45474 | J6: =D6 -> 45809 | K6: =E6 -> 45839 | L6: =C6 -> 45474 | M6: =D6 -> 45809 | N6: =E6 -> 45839
B7: Sistema */ | C7: 41285.25 | D7: 47677.254 | E7: 51371.162 | F7: 3.1110246 | G7: 3.5150476 | H7: 3.3163959 | I7: 234.05167 | J7: 217.38649 | K7: 217.46984 | L7: 7.2814051 | M7: 7.6412386 | N7: 7.2121609
B8: BBVA México | C8: 0 | D8: 0 | E8: 0 | F8: n.a. | G8: n.a. | H8: n.a. | I8: - | J8: - | K8: - | L8: - | M8: - | N8: -
B9: Santander | C9: 915.54518 | D9: 1092.4238 | E9: 1105.2752 | F9: 3.2325646 | G9: 5.3529792 | H9: 5.2260675 | I9: 232.92359 | J9: 183.13153 | K9: 189.18431 | L9: 7.5294054 | M9: 9.8029927 | N9: 9.8868996
B10: Banorte | C10: 0 | D10: 0 | E10: 0 | F10: n.a. | G10: n.a. | H10: n.a. | I10: - | J10: - | K10: - | L10: - | M10: - | N10: -
B11: Banamex | C11: 0 | D11: 0 | E11: 0 | F11: n.a. | G11: n.a. | H11: n.a. | I11: - | J11: - | K11: - | L11: - | M11: - | N11: -
B12: HSBC | C12: 0 | D12: 0 | E12: 0 | F12: n.a. | G12: n.a. | H12: n.a. | I12: - | J12: - | K12: - | L12: - | M12: - | N12: -
B13: Scotiabank | C13: 0 | D13: 0 | E13: 0 | F13: n.a. | G13: n.a. | H13: n.a. | I13: - | J13: - | K13: - | L13: - | M13: - | N13: -
B14: Inbursa | C14: 0 | D14: 0 | E14: 0 | F14: n.a. | G14: n.a. | H14: n.a. | I14: - | J14: - | K14: - | L14: - | M14: - | N14: -
B15: Citi México | C15: 0 | D15: 0 | E15: 0 | F15: n.a. | G15: n.a. | H15: n.a. | I15: - | J15: - | K15: - | L15: - | M15: - | N15: -
B16: Banco del Bajío | C16: 0 | D16: 0 | E16: 0 | F16: n.a. | G16: n.a. | H16: n.a. | I16: - | J16: - | K16: - | L16: - | M16: - | N16: -
B17: Banco Azteca | C17: 0 | D17: 0 | E17: 0 | F17: n.a. | G17: n.a. | H17: n.a. | I17: - | J17: - | K17: - | L17: - | M17: - | N17: -
B18: Afirme | C18: 0 | D18: 269.73347 | E18: 268.60438 | F18: n.a. | G18: 4.7188234 | H18: 3.0587621 | I18: - | J18: 301.12829 | K18: 429.45186 | L18: - | M18: 14.209712 | N18: 13.135911
B19: Monex | C19: 0 | D19: 0 | E19: 0 | F19: n.a. | G19: n.a. | H19: n.a. | I19: - | J19: - | K19: - | L19: - | M19: - | N19: -
B20: Banregio | C20: 0 | D20: 0 | E20: 0 | F20: n.a. | G20: n.a. | H20: n.a. | I20: - | J20: - | K20: - | L20: - | M20: - | N20: -
B21: J.P. Morgan | C21: 0 | D21: 0 | E21: 0 | F21: n.a. | G21: n.a. | H21: n.a. | I21: - | J21: - | K21: - | L21: - | M21: - | N21: -
B22: Invex | C22: 0 | D22: 0 | E22: 0 | F22: n.a. | G22: n.a. | H22: n.a. | I22: - | J22: - | K22: - | L22: - | M22: - | N22: -
B23: Bank of America | C23: 0 | D23: 0 | E23: 0 | F23: n.a. | G23: n.a. | H23: n.a. | I23: - | J23: - | K23: - | L23: - | M23: - | N23: -
B24: BanCoppel | C24: 0 | D24: 0 | E24: 0 | F24: n.a. | G24: n.a. | H24: n.a. | I24: - | J24: - | K24: - | L24: - | M24: - | N24: -
B25: Banca Mifel | C25: 0 | D25: 0 | E25: 0 | F25: n.a. | G25: n.a. | H25: n.a. | I25: - | J25: - | K25: - | L25: - | M25: - | N25: -
B26: Multiva | C26: 0 | D26: 0 | E26: 0 | F26: n.a. | G26: n.a. | H26: n.a. | I26: - | J26: - | K26: - | L26: - | M26: - | N26: -
B27: Banco Base | C27: 0 | D27: 0 | E27: 0 | F27: n.a. | G27: n.a. | H27: n.a. | I27: - | J27: - | K27: - | L27: - | M27: - | N27: -
B28: Barclays | C28: 0 | D28: 0 | E28: 0 | F28: n.a. | G28: n.a. | H28: n.a. | I28: - | J28: - | K28: - | L28: - | M28: - | N28: -
B29: Sabadell | C29: 0 | D29: 0 | E29: 0 | F29: n.a. | G29: n.a. | H29: n.a. | I29: - | J29: - | K29: - | L29: - | M29: - | N29: -
B30: Ve por Más | C30: 0 | D30: 0 | E30: 0 | F30: n.a. | G30: n.a. | H30: n.a. | I30: - | J30: - | K30: - | L30: - | M30: - | N30: -
... B33: Actinver | C33: 0 | D33: 0 | E33: 0 | F33: n.a. | G33: n.a. | H33: n.a. | I33: - | J33: - | K33: - | L33: - | M33: - | N33: -
B34: Compartamos | C34: 39871.489 | D34: 45973.458 | E34: 49654.937 | F34: 3.0707587 | G34: 3.4008009 | H34: 3.2259241 | I34: 236.39433 | J34: 220.91335 | K34: 219.86486 | L34: 7.2590994 | M34: 7.5128232 | N34: 7.0926734
B35: BIAfirme | C35: 0 | D35: 0 | E35: 0 | F35: n.a. | G35: n.a. | H35: n.a. | I35: - | J35: - | K35: - | L35: - | M35: - | N35: -
B36: Intercam Banco | C36: 0 | D36: 0 | E36: 0 | F36: n.a. | G36: n.a. | H36: n.a. | I36: - | J36: - | K36: - | L36: - | M36: - | N36: -
B37: Bancrea | C37: 0 | D37: 0 | E37: 0 | F37: n.a. | G37: n.a. | H37: n.a. | I37: - | J37: - | K37: - | L37: - | M37: - | N37: -
B38: MUFG Bank | C38: 0 | D38: 0 | E38: 0 | F38: n.a. | G38: n.a. | H38: n.a. | I38: - | J38: - | K38: - | L38: - | M38: - | N38: -
B39: Consubanco | C39: 0 | D39: 0 | E39: 0 | F39: n.a. | G39: n.a. | H39: n.a. | I39: - | J39: - | K39: - | L39: - | M39: - | N39: -
B40: BNP Paribas México | C40: 0 | D40: 0 | E40: 0 | F40: n.a. | G40: n.a. | H40: n.a. | I40: - | J40: - | K40: - | L40: - | M40: - | N40: -
B41: Autofin | C41: 0 | D41: 0 | E41: 0 | F41: n.a. | G41: n.a. | H41: n.a. | I41: - | J41: - | K41: - | L41: - | M41: - | N41: -
B42: Bankaool | C42: 0 | D42: 0 | E42: 0 | F42: n.a. | G42: n.a. | H42: n.a. | I42: - | J42: - | K42: - | L42: - | M42: - | N42: -
B43: Inmobiliario Mexicano | C43: 0 | D43: 0 | E43: 0 | F43: n.a. | G43: n.a. | H43: n.a. | I43: - | J43: - | K43: - | L43: - | M43: - | N43: -
B44: Mizuho Bank | C44: 0 | D44: 0 | E44: 0 | F44: n.a. | G44: n.a. | H44: n.a. | I44: - | J44: - | K44: - | L44: - | M44: - | N44: -
B45: ICBC | C45: 0 | D45: 0 | E45: 0 | F45: n.a. | G45: n.a. | H45: n.a. | I45: - | J45: - | K45: - | L45: - | M45: - | N45: -
B46: Banco Covalto | C46: 0 | D46: 0 | E46: 0 | F46: n.a. | G46: n.a. | H46: n.a. | I46: - | J46: - | K46: - | L46: - | M46: - | N46: -
... B57: Hey Banco | C57: 0 | D57: 0 | E57: 0 | F57: n.a. | G57: n.a. | H57: n.a. | I57: - | J57: - | K57: - | L57: - | M57: - | N57: -
B58: Forjadores | C58: 498.21568 | D58: 341.63894 | E58: 342.346 | F58: 6.1101044 | G58: 12.061555 | H58: 10.475414 | I58: 140.92665 | J58: 106.31588 | K58: 107.48735 | L58: 8.6107651 | M58: 12.823349 | N58: 11.259745
B59: Pagatodo | C59: 0 | D59: 0 | E59: 0 | F59: n.a. | G59: n.a. | H59: n.a. | I59: - | J59: - | K59: - | L59: - | M59: - | N59: -

Sheet CCCnrO
B2: Cartera de crédito al consumo
B3: Millones de pesos y porcentajes
C5: Otros créditos al consumo (MDP) 1/ | F5: IMOR (%) 5/ | I5: ICOR (%) 6/ | L5: Pérdida esperada (%) 7/
C6: 45474 | D6: 45809 | E6: 45839 | F6: =C6 -> 45474 | G6: =D6 -> 45809 | H6: =E6 -> 45839 | I6: =C6 -> 45474 | J6: =D6 -> 45809 | K6: =E6 -> 45839 | L6: =C6 -> 45474 | M6: =D6 -> 45809 | N6: =E6 -> 45839
B7: Sistema */ | C7: 5194.9891 | D7: 4077.5027 | E7: 4156.7498 | F7: 4.2655735 | G7: 4.4031948 | H7: 4.1388928 | I7: 239.28357 | J7: 234.69406 | K7: 245.46817 | L7: 10.206817 | M7: 10.334037 | N7: 10.159664
B8: BBVA México | C8: 11.350798 | D8: 13.201303 | E8: 22.006469 | F8: 100 | G8: 0.81948052 | H8: 0.75818447 | I8: 99.999998 | J8: 1928.6243 | K8: 1792.5832 | L8: 99.999998 | M8: 15.8047 | N8: 13.591088
B9: Santander | C9: 0 | D9: 0 | E9: 0 | F9: n.a. | G9: n.a. | H9: n.a. | I9: - | J9: - | K9: - | L9: - | M9: - | N9: -
B10: Banorte | C10: 58.572137 | D10: 56.280632 | E10: 55.075033 | F10: 7.9738771 | G10: 8.1627206 | H10: 8.1466807 | I10: 287.86692 | J10: 246.01459 | K10: 241.33972 | L10: 22.954154 | M10: 20.081483 | N10: 19.661177
B11: Banamex | C11: 0.18682194 | D11: 0.18944533 | E11: 0.18931033 | F11: 100 | G11: 100 | H11: 100 | I11: 100 | J11: 100 | K11: 100 | L11: 100 | M11: 100 | N11: 100
B12: HSBC | C12: 1229.1809 | D12: 1164.8948 | E12: 1169.8935 | F12: 8.3957986 | G12: 6.3054949 | H12: 4.9531789 | I12: 238.04598 | J12: 241.15689 | K12: 302.40975 | L12: 19.985861 | M12: 15.206136 | N12: 14.978896
B13: Scotiabank | C13: 8.276182 | D13: 7.203878 | E13: 7.698748 | F13: 50.946825 | G13: 58.740056 | H13: 54.982122 | I13: 101.45051 | J13: 100.21014 | K13: 101.17148 | L13: 51.685814 | M13: 58.86349 | N13: 55.626226
B14: Inbursa | C14: 1956.9522 | D14: 0 | E14: 10.649414 | F14: 2.3944429 | G14: n.a. | H14: 9.3578388 | I14: 271.84993 | J14: - | K14: 81.112533 | L14: 6.5092913 | M14: - | N14: 7.5903801
B15: Citi México | C15: 0 | D15: 0 | E15: 0 | F15: n.a. | G15: n.a. | H15: n.a. | I15: - | J15: - | K15: - | L15: - | M15: - | N15: -
B16: Banco del Bajío | C16: 0 | D16: 0 | E16: 0 | F16: n.a. | G16: n.a. | H16: n.a. | I16: - | J16: - | K16: - | L16: - | M16: - | N16: -
B17: Banco Azteca | C17: 1501.204 | D17: 2288.1373 | E17: 2347.8135 | F17: 3.0463674 | G17: 3.8619614 | H17: 4.0837844 | I17: 214.18798 | J17: 221.82838 | K17: 207.52783 | L17: 6.5249527 | M17: 8.5669265 | N17: 8.4749891
B18: Afirme | C18: 0 | D18: 0 | E18: 0 | F18: n.a. | G18: n.a. | H18: n.a. | I18: - | J18: - | K18: - | L18: - | M18: - | N18: -
B19: Monex | C19: 0 | D19: 0 | E19: 0 | F19: n.a. | G19: n.a. | H19: n.a. | I19: - | J19: - | K19: - | L19: - | M19: - | N19: -
B20: Banregio | C20: 0.04765562 | D20: 0 | E20: 0 | F20: 0 | G20: n.a. | H20: n.a. | I20: - | J20: - | K20: - | L20: 2.8674687 | M20: - | N20: -
B21: J.P. Morgan | C21: 0 | D21: 0 | E21: 0 | F21: n.a. | G21: n.a. | H21: n.a. | I21: - | J21: - | K21: - | L21: - | M21: - | N21: -
B22: Invex | C22: 3.616712 | D22: 0 | E22: 0 | F22: 0 | G22: n.a. | H22: n.a. | I22: - | J22: - | K22: - | L22: 0 | M22: - | N22: -
B23: Bank of America | C23: 0 | D23: 0 | E23: 0 | F23: n.a. | G23: n.a. | H23: n.a. | I23: - | J23: - | K23: - | L23: - | M23: - | N23: -
B24: BanCoppel | C24: 0 | D24: 0 | E24: 0 | F24: n.a. | G24: n.a. | H24: n.a. | I24: - | J24: - | K24: - | L24: - | M24: - | N24: -
B25: Banca Mifel | C25: 0 | D25: 0 | E25: 0 | F25: n.a. | G25: n.a. | H25: n.a. | I25: - | J25: - | K25: - | L25: - | M25: - | N25: -
B26: Multiva | C26: 0 | D26: 0 | E26: 0 | F26: n.a. | G26: n.a. | H26: n.a. | I26: - | J26: - | K26: - | L26: - | M26: - | N26: -
B27: Banco Base | C27: 0 | D27: 0 | E27: 0 | F27: n.a. | G27: n.a. | H27: n.a. | I27: - | J27: - | K27: - | L27: - | M27: - | N27: -
B28: Barclays | C28: 0 | D28: 0 | E28: 0 | F28: n.a. | G28: n.a. | H28: n.a. | I28: - | J28: - | K28: - | L28: - | M28: - | N28: -
B29: Sabadell | C29: 0 | D29: 0 | E29: 0 | F29: n.a. | G29: n.a. | H29: n.a. | I29: - | J29: - | K29: - | L29: - | M29: - | N29: -
B30: Ve por Más | C30: 112.79841 | D30: 150.9976 | E30: 134.81136 | F30: 8.865373e-07 | G30: 0.0080941684 | H30: 0.0090660016 | I30: 208768700 | J30: 44336.017 | K30: 26137.67 | L30: 1.8508124 | M30: 3.5886319 | N30: 2.3696416
B31: CIBanco | C31: 0 | D31: 0 | E31: 0 | F31: n.a. | G31: n.a. | H31: n.a. | I31: - | J31: - | K31: - | L31: - | M31: - | N31: -
B32: Bansí | C32: 0 | D32: 0 | E32: 0 | F32: n.a. | G32: n.a. | H32: n.a. | I32: - | J32: - | K32: - | L32: - | M32: - | N32: -
B33: Actinver | C33: 312.80319 | D33: 396.10835 | E33: 408.12308 | F33: 1.7204712 | G33: 2.04394 | H33: 1.8726785 | I33: 518.3259 | J33: 303.58187 | K33: 332.30547 | L33: 8.9176481 | M33: 6.2050314 | N33: 6.223013
B34: Compartamos | C34: 0 | D34: 0.489365 | E34: 0.489365 | F34: n.a. | G34: 100 | H34: 100 | I34: - | J34: 81.000072 | K34: 83.00001 | L34: - | M34: 81.000072 | N34: 83.00001
B35: BIAfirme | C35: 0 | D35: 0 | E35: 0 | F35: n.a. | G35: n.a. | H35: n.a. | I35: - | J35: - | K35: - | L35: - | M35: - | N35: -
B36: Intercam Banco | C36: 0 | D36: 0 | E36: 0 | F36: n.a. | G36: n.a. | H36: n.a. | I36: - | J36: - | K36: - | L36: - | M36: - | N36: -
B37: Bancrea | C37: 0 | D37: 0 | E37: 0 | F37: n.a. | G37: n.a. | H37: n.a. | I37: - | J37: - | K37: - | L37: - | M37: - | N37: -
B38: MUFG Bank | C38: 0 | D38: 0 | E38: 0 | F38: n.a. | G38: n.a. | H38: n.a. | I38: - | J38: - | K38: - | L38: - | M38: - | N38: -
B39: Consubanco | C39: 0 | D39: 0 | E39: 0 | F39: n.a. | G39: n.a. | H39: n.a. | I39: - | J39: - | K39: - | L39: - | M39: - | N39: -
B40: BNP Paribas México | C40: 0 | D40: 0 | E40: 0 | F40: n.a. | G40: n.a. | H40: n.a. | I40: - | J40: - | K40: - | L40: - | M40: - | N40: -
B41: Autofin | C41: 0 | D41: 0 | E41: 0 | F41: n.a. | G41: n.a. | H41: n.a. | I41: - | J41: - | K41: - | L41: - | M41: - | N41: -
B42: Bankaool | C42: 0 | D42: 0 | E42: 0 | F42: n.a. | G42: n.a. | H42: n.a. | I42: - | J42: - | K42: - | L42: - | M42: - | N42: -
B43: Inmobiliario Mexicano | C43: 0 | D43: 0 | E43: 0 | F43: n.a. | G43: n.a. | H43: n.a. | I43: - | J43: - | K43: - | L43: - | M43: - | N43: -
B44: Mizuho Bank | C44: 0 | D44: 0 | E44: 0 | F44: n.a. | G44: n.a. | H44: n.a. | I44: - | J44: - | K44: - | L44: - | M44: - | N44: -
B45: ICBC | C45: 0 | D45: 0 | E45: 0 | F45: n.a. | G45: n.a. | H45: n.a. | I45: - | J45: - | K45: - | L45: - | M45: - | N45: -
B46: Banco Covalto | C46: 0 | D46: 0 | E46: 0 | F46: n.a. | G46: n.a. | H46: n.a. | I46: - | J46: - | K46: - | L46: - | M46: - | N46: -
... B59: Pagatodo | C59: 0 | D59: 0 | E59: 0 | F59: n.a. | G59: n.a. | H59: n.a. | I59: - | J59: - | K59: - | L59: - | M59: - | N59: -

Sheet CCV
B2: Cartera de crédito a la vivienda
B3: Millones de pesos y porcentajes
C5: Cartera total (MDP) 1/ | F5: IMOR (%) 5/ | I5: ICOR (%) 6/ | L5: Pérdida esperada (%) 7/
C6: 45474 | D6: 45809 | E6: 45839 | F6: =C6 -> 45474 | G6: =D6 -> 45809 | H6: =E6 -> 45839 | I6: =C6 -> 45474 | J6: =D6 -> 45809 | K6: =E6 -> 45839 | L6: =C6 -> 45474 | M6: =D6 -> 45809 | N6: =E6 -> 45839
B7: Sistema */ | C7: 1388396.9 | D7: 1466522.8 | E7: 1475070.1 | F7: 2.6991842 | G7: 3.0006324 | H7: 3.0338235 | I7: 53.288613 | J7: 54.800996 | K7: 54.528415 | L7: 1.4383578 | M7: 1.6443765 | N7: 1.6542958
B8: BBVA México | C8: 354914.02 | D8: 382945.32 | E8: 385363.94 | F8: 2.1222591 | G8: 2.4108361 | H8: 2.3958391 | I8: 50.247417 | J8: 64.505657 | K8: 65.972488 | L8: 1.0663804 | M8: 1.5551257 | N8: 1.5805947
B9: Santander | C9: 232151.61 | D9: 247616.64 | E9: 249716.79 | F9: 3.4149 | G9: 3.6027768 | H9: 3.6135898 | I9: 64.894763 | J9: 63.492232 | K9: 63.199723 | L9: 2.2160913 | M9: 2.2874834 | N9: 2.2837787
B10: Banorte | C10: 265313.97 | D10: 284846.67 | E10: 287144.1 | F10: 0.75488508 | G10: 0.80021779 | H10: 0.85369057 | I10: 62.822934 | J10: 56.975681 | K10: 53.920689 | L10: 0.47424095 | M10: 0.45592954 | N10: 0.46031583
B11: Banamex | C11: 71337.034 | D11: 77787.552 | E11: 78504.947 | F11: 2.5009124 | G11: 2.3721581 | H11: 2.4157862 | I11: 49.264768 | J11: 44.806077 | K11: 44.298045 | L11: 1.2320687 | M11: 1.062871 | N11: 1.0701461
B12: HSBC | C12: 151248.79 | D12: 151571.73 | E12: 151076.72 | F12: 2.3834171 | G12: 2.7658767 | H12: 2.807952 | I12: 55.189395 | J12: 51.972776 | K12: 51.667314 | L12: 1.3153935 | M12: 1.4375029 | N12: 1.4507934
B13: Scotiabank | C13: 237655.55 | D13: 248103.06 | E13: 249043.88 | F13: 4.6281494 | G13: 5.6880194 | H13: 5.7610203 | I13: 42.286113 | J13: 42.922078 | K13: 42.269868 | L13: 1.9570645 | M13: 2.4414161 | N13: 2.4351757
B14: Inbursa | C14: 5090.6004 | D14: 4498.1231 | E14: 4437.5326 | F14: 14.358355 | G14: 11.823522 | H14: 11.81137 | I14: 33.210531 | J14: 26.996827 | K14: 27.536164 | L14: 4.7684861 | M14: 3.1919757 | N14: 3.2523982
B15: Citi México | C15: 0 | D15: 0 | E15: 0 | F15: n.a. | G15: n.a. | H15: n.a. | I15: - | J15: - | K15: - | L15: - | M15: - | N15: -
B16: Banco del Bajío | C16: 4306.6071 | D16: 3717.9934 | E16: 3667.4166 | F16: 3.6476419 | G16: 3.9189575 | H16: 3.8100395 | I16: 49.253275 | J16: 43.257821 | K16: 45.097257 | L16: 1.7965831 | M16: 1.6952556 | N16: 1.7182233
B17: Banco Azteca | C17: 578.14639 | D17: 566.85036 | E17: 608.67915 | F17: 4.8947872 | G17: 3.3757547 | H17: 3.1331622 | I17: 29.843386 | J17: 30.658311 | K17: 40.917008 | L17: 1.4607702 | M17: 1.0349494 | N17: 1.2819963
B18: Afirme | C18: 13440.599 | D18: 13974.485 | E18: 14207.146 | F18: 5.6794245 | G18: 4.2356158 | H18: 4.1727509 | I18: 38.794389 | J18: 44.318603 | K18: 45.927971 | L18: 2.203298 | M18: 1.8771657 | N18: 1.9164598
B19: Monex | C19: 7.481171 | D19: 0 | E19: 0 | F19: 65.63878 | G19: n.a. | H19: n.a. | I19: 96.014078 | J19: - | K19: - | L19: 63.022469 | M19: - | N19: -
B20: Banregio | C20: 15738.364 | D20: 16895.535 | E20: 17102.787 | F20: 1.4259138 | G20: 1.3068204 | H20: 1.3228479 | I20: 71.428556 | J20: 81.194068 | K20: 77.959231 | L20: 1.0185097 | M20: 1.0610606 | N20: 1.031282
B21: J.P. Morgan | C21: 0 | D21: 0 | E21: 0 | F21: n.a. | G21: n.a. | H21: n.a. | I21: - | J21: - | K21: - | L21: - | M21: - | N21: -
B22: Invex | C22: 57.93314 | D22: 57.801718 | E22: 53.39593 | F22: 6.7357561 | G22: 0 | H22: 0 | I22: 14.01402 | J22: - | K22: - | L22: 0.94395022 | M22: 0.1203632 | N22: 0.11869631
B23: Bank of America | C23: 0 | D23: 0 | E23: 0 | F23: n.a. | G23: n.a. | H23: n.a. | I23: - | J23: - | K23: - | L23: - | M23: - | N23: -
B24: BanCoppel | C24: 4513.5144 | D24: 4422.5014 | E24: 4511.4099 | F24: 1.5264206 | G24: 2.6196105 | H24: 3.4856055 | I24: 159.6154 | J24: 126.58772 | K24: 103.21644 | L24: 2.4364024 | M24: 3.3161052 | N24: 3.5977181
B25: Banca Mifel | C25: 18904.05 | D25: 17440.822 | E25: 17415.882 | F25: 5.9927583 | G25: 7.85041 | H25: 8.5344284 | I25: 50.359174 | J25: 44.749223 | K25: 42.724203 | L25: 3.0179036 | M25: 3.5129975 | N25: 3.6462665
B26: Multiva | C26: 442.89502 | D26: 413.15433 | E26: 435.7915 | F26: 75.462274 | G26: 69.899805 | H26: 66.103404 | I26: 97.164421 | J26: 98.617209 | K26: 98.844699 | L26: 73.322481 | M26: 68.933236 | N26: 65.339711
B27: Banco Base | C27: 0 | D27: 0 | E27: 0 | F27: n.a. | G27: n.a. | H27: n.a. | I27: - | J27: - | K27: - | L27: - | M27: - | N27: -
B28: Barclays | C28: 0 | D28: 0 | E28: 0 | F28: n.a. | G28: n.a. | H28: n.a. | I28: - | J28: - | K28: - | L28: - | M28: - | N28: -
B29: Sabadell | C29: 55.795581 | D29: 47.808671 | E29: 45.960187 | F29: 2.3740894 | G29: 2.6033938 | H29: 2.7081004 | I29: 40.093701 | J29: 32.16556 | K29: 31.10751 | L29: 0.95186033 | M29: 0.83739621 | N29: 0.8424226
B30: Ve por Más | C30: 11192.309 | D30: 10597.538 | E30: 10655.117 | F30: 1.1355405 | G30: 0.88071117 | H30: 0.72667893 | I30: 342.06756 | J30: 433.21949 | K30: 522.78728 | L30: 3.8843157 | M30: 3.8154125 | N30: 3.798985
B31: CIBanco | C31: 1069.0346 | D31: 662.71809 | E31: 710.71782 | F31: 0.20924215 | G31: 0.53483043 | H31: 0.43622953 | I31: 795.0623 | J31: 340.89707 | K31: 593.42428 | L31: 1.6636054 | M31: 1.8232212 | N31: 2.588692
B32: Bansí | C32: 17.817096 | D32: 15.70577 | E32: 15.533492 | F32: 19.463351 | G32: 21.984042 | H32: 22.213234 | I32: 21.903977 | J32: 31.514095 | K32: 31.343423 | L32: 4.2632481 | M32: 6.9280717 | N32: 6.9623881
B33: Actinver | C33: 0 | D33: 0 | E33: 0 | F33: n.a. | G33: n.a. | H33: n.a. | I33: - | J33: - | K33: - | L33: - | M33: - | N33: -
B34: Compartamos | C34: 0 | D34: 0 | E34: 0 | F34: n.a. | G34: n.a. | H34: n.a. | I34: - | J34: - | K34: - | L34: - | M34: - | N34: -
B35: BIAfirme | C35: 0 | D35: 0 | E35: 0 | F35: n.a. | G35: n.a. | H35: n.a. | I35: - | J35: - | K35: - | L35: - | M35: - | N35: -
B36: Intercam Banco | C36: 0 | D36: 0 | E36: 0 | F36: n.a. | G36: n.a. | H36: n.a. | I36: - | J36: - | K36: - | L36: - | M36: - | N36: -
B37: Bancrea | C37: 0 | D37: 0 | E37: 0 | F37: n.a. | G37: n.a. | H37: n.a. | I37: - | J37: - | K37: - | L37: - | M37: - | N37: -
B38: MUFG Bank | C38: 0 | D38: 0 | E38: 0 | F38: n.a. | G38: n.a. | H38: n.a. | I38: - | J38: - | K38: - | L38: - | M38: - | N38: -
B39: Consubanco | C39: 0 | D39: 0 | E39: 0 | F39: n.a. | G39: n.a. | H39: n.a. | I39: - | J39: - | K39: - | L39: - | M39: - | N39: -
B40: BNP Paribas México | C40: 0 | D40: 0 | E40: 0 | F40: n.a. | G40: n.a. | H40: n.a. | I40: - | J40: - | K40: - | L40: - | M40: - | N40: -
B41: Autofin | C41: 66.995646 | D41: 98.351228 | E41: 113.15354 | F41: 43.247053 | G41: 29.860221 | H41: 26.678305 | I41: 27.231854 | J41: 51.963106 | K41: 54.131559 | L41: 11.776974 | M41: 15.516298 | N41: 14.441382
B42: Bankaool | C42: 0 | D42: 0 | E42: 0 | F42: n.a. | G42: n.a. | H42: n.a. | I42: - | J42: - | K42: - | L42: - | M42: - | N42: -
B43: Inmobiliario Mexicano | C43: 275.13897 | D43: 224.5346 | E43: 221.40536 | F43: 4.5928113 | G43: 3.176153 | H43: 3.0183324 | I43: 45.328549 | J43: 35.621616 | K43: 38.325375 | L43: 2.0818547 | M43: 1.1313971 | N43: 1.1567872
B44: Mizuho Bank | C44: 0 | D44: 0 | E44: 0 | F44: n.a. | G44: n.a. | H44: n.a. | I44: - | J44: - | K44: - | L44: - | M44: - | N44: -
B45: ICBC | C45: 0 | D45: 0 | E45: 0 | F45: n.a. | G45: n.a. | H45: n.a. | I45: - | J45: - | K45: - | L45: - | M45: - | N45: -
B46: Banco Covalto | C46: 0 | D46: 0 | E46: 0 | F46: n.a. | G46: n.a. | H46: n.a. | I46: - | J46: - | K46: - | L46: - | M46: - | N46: -
B47: Bank of China | C47: 0 | D47: 0 | E47: 0 | F47: n.a. | G47: n.a. | H47: n.a. | I47: - | J47: - | K47: - | L47: - | M47: - | N47: -
B48: Volkswagen Bank | C48: 0 | D48: 0 | E48: 0 | F48: n.a. | G48: n.a. | H48: n.a. | I48: - | J48: - | K48: - | L48: - | M48: - | N48: -
B49: Openbank | C49: 0 | D49: 0 | E49: 0 | F49: n.a. | G49: n.a. | H49: n.a. | I49: - | J49: - | K49: - | L49: - | M49: - | N49: -
B50: Shinhan | C50: 0 | D50: 0 | E50: 0 | F50: n.a. | G50: n.a. | H50: n.a. | I50: - | J50: - | K50: - | L50: - | M50: - | N50: -
B51: Banco Ualá | C51: 18.606222 | D51: 17.868824 | E51: 17.799801 | F51: 0 | G51: 7.5467697 | H51: 7.5760341 | I51: - | J51: 9.1455886 | K51: 11.205626 | L51: 0.22881593 | M51: 0.69019651 | N51: 0.84894208
B52: Banco S3 | C52: 0 | D52: 0 | E52: 0 | F52: n.a. | G52: n.a. | H52: n.a. | I52: - | J52: - | K52: - | L52: - | M52: - | N52: -
B53: KEB Hana México | C53: 0 | D53: 0 | E53: 0 | F53: n.a. | G53: n.a. | H53: n.a. | I53: - | J53: - | K53: - | L53: - | M53: - | N53: -
B54: Banco Bineo | C54: 0 | D54: 0 | E54: 0 | F54: n.a. | G54: n.a. | H54: n.a. | I54: - | J54: - | K54: - | L54: - | M54: - | N54: -
B55: Dondé Banco | C55: 0 | D55: 0 | E55: 0 | F55: n.a. | G55: n.a. | H55: n.a. | I55: - | J55: - | K55: - | L55: - | M55: - | N55: -
B56: Credit Suisse | C56: 0 | D56: 0 | E56: 0 | F56: n.a. | G56: n.a. | H56: n.a. | I56: - | J56: - | K56: - | L56: - | M56: - | N56: -
B57: Hey Banco | C57: 0 | D57: 0 | E57: 0 | F57: n.a. | G57: n.a. | H57: n.a. | I57: - | J57: - | K57: - | L57: - | M57: - | N57: -
B58: Forjadores | C58: 0 | D58: 0 | E58: 0 | F58: n.a. | G58: n.a. | H58: n.a. | I58: - | J58: - | K58: - | L58: - | M58: - | N58: -
B59: Pagatodo | C59: 0 | D59: 0 | E59: 0 | F59: n.a. | G59: n.a. | H59: n.a. | I59: - | J59: - | K59: - | L59: - | M59: - | N59: -

Sheet CaptRec
B2: Saldos de la captación bancaria
B3: Millones de pesos
C5: Captación total | F5: Depósitos exigibilidad inmediata | I5: Depósitos a plazo público en general | L5: Depósitos a plazo mercado de dinero | O5: Títulos de crédito | R5: Préstamos interbancarios y otros | U5: Cuenta global de captación sin movimientos
C6: 45474 | D6: 45809 | E6: 45839 | F6: =C6 -> 45474 | G6: =D6 -> 45809 | H6: =E6 -> 45839 | I6: =C6 -> 45474 | J6: =D6 -> 45809 | K6: =E6 -> 45839 | L6: =C6 -> 45474 | M6: =D6 -> 45809 | N6: =E6 -> 45839 | O6: =C6 -> 45474 | P6: =D6 -> 45809 | Q6: =E6 -> 45839 | R6: =C6 -> 45474 | S6: =D6 -> 45809 | T6: =E6 -> 45839 | U6: =C6 -> 45474 | V6: =D6 -> 45809 | W6: =E6 -> 45839
B7: Sistema */ | C7: 8419009.1 | D7: 9112459.1 | E7: 9174885.7 | F7: 5316065.2 | G7: 5820819 | H7: 5769964.9 | I7: 1999333.1 | J7: 2063486.9 | K7: 2091608.5 | L7: 378943.1 | M7: 398501.03 | N7: 484377.6 | O7: 352077.99 | P7: 367587.38 | Q7: 366274.29 | R7: 346302.56 | S7: 432777.31 | T7: 433158.66 | U7: 26287.12 | V7: 29287.528 | W7: 29501.709
B8: BBVA México | C8: 1807909.4 | D8: 2083231.9 | E8: 2036733.9 | F8: 1410902.4 | G8: 1600622.5 | H8: 1543480.4 | I8: 241092.67 | J8: 282023.2 | K8: 293383.71 | L8: 17403.436 | M8: 29989.392 | N8: 26947.908 | O8: 108491.4 | P8: 148329.82 | Q8: 149157.34 | R8: 23321.516 | S8: 15049.024 | T8: 16414.325 | U8: 6697.9763 | V8: 7218.0281 | W8: 7350.2648
B9: Santander | C9: 1018558.3 | D9: 1077295.9 | E9: 1098918.5 | F9: 611239.51 | G9: 644281.95 | H9: 663304.68 | I9: 253381.51 | J9: 264123.22 | K9: 268209.36 | L9: 38205.866 | M9: 62557.021 | N9: 62030.315 | O9: 81768.067 | P9: 64961.955 | Q9: 64462.076 | R9: 31496.168 | S9: 38644.793 | T9: 38195.625 | U9: 2467.1771 | V9: 2726.9779 | W9: 2716.4515
B10: Banorte | C10: 1128928.2 | D10: 1210098.5 | E10: 1186183.1 | F10: 700586.06 | G10: 790361.72 | H10: 772141.42 | I10: 361139.07 | J10: 367414.74 | K10: 363755.19 | L10: 5935.7878 | M10: 5202.8293 | N10: 5177.8475 | O10: 43328.03 | P10: 34181.408 | Q10: 32108.67 | R10: 14233.066 | S10: 8605.5784 | T10: 8717.6055 | U10: 3706.1921 | V10: 4332.2746 | W10: 4282.3733
B11: Banamex | C11: 957318.31 | D11: 746120.08 | E11: 763127.06 | F11: 716616.19 | G11: 537694.48 | H11: 537405.93 | I11: 118342.28 | J11: 117820.85 | K11: 121299.03 | L11: 103159.88 | M11: 57492.378 | N11: 71137.909 | O11: 4713.5804 | P11: 0 | Q11: 0 | R11: 6405.2265 | S11: 24465.314 | T11: 24560.443 | U11: 8081.1555 | V11: 8647.0517 | W11: 8723.7519
B12: HSBC | C12: 594973.04 | D12: 567634.81 | E12: 574253.19 | F12: 379011.16 | G12: 363137.54 | H12: 379318.62 | I12: 164385.15 | J12: 156686.09 | K12: 154260.29 | L12: 16273.896 | M12: 15622.715 | N12: 9338.3367 | O12: 19031.421 | P12: 18950.677 | Q12: 19062.749 | R12: 14185.533 | S12: 10645.513 | T12: 9639.646 | U12: 2085.879 | V12: 2592.2692 | W12: 2633.5555
B13: Scotiabank | C13: 603698.01 | D13: 574302.99 | E13: 589058.65 | F13: 295644.06 | G13: 284201.19 | H13: 293224.86 | I13: 225043.23 | J13: 183941.3 | K13: 190988.51 | L13: 24801.619 | M13: 31211.352 | N13: 28393.797 | O13: 20696.128 | P13: 29733.036 | Q13: 30903.49 | R13: 36085.591 | S13: 43594.618 | T13: 43918.854 | U13: 1427.377 | V13: 1621.4988 | W13: 1629.1445
